Workbook

Sheet Assumptions
A1: EFIR — Staff Costs Budget Assumptions
A3: GENERAL PARAMETERS
A4: Budget Year | B4: 2026 | C4: Calendar year for budget
A5: Salary Increase Effective Month | B5: 9 | C5: 9 = September
A6: Seniority Threshold (years) | B6: 1 | C6: >1 year as of Sep 1 to qualify for increase
A7: Budget Start Date | B7: =DATE(B4,1,1) -> 46023 | C7: Auto-calculated
A8: Budget End Date | B8: =DATE(B4,12,31) -> 46387 | C8: Auto-calculated
A9: Increase Effective Date | B9: =DATE(B4,B5,1) -> 46266 | C9: Auto-calculated
A11: GOSI RATES
A12: Employer Rate — Saudi | B12: 0.1175 | C12: 9% pension + 2% OccHaz + 0.75% SANED
A13: Employer Rate — Non-Saudi | B13: 0 | C13: 0% — Ajeer/dependent workers exempt
A14: GOSI Salary Cap (monthly) | B14: 45000 | C14: Max base for GOSI calculation
A15: GOSI Basis | B15: Base + Housing | C15: Components subject to GOSI
A17: END OF SERVICE (EoS)
A18: Rate — First 5 years (months/year) | B18: 0.5 | C18: 0.5 month salary per year of service
A19: Rate — After 5 years (months/year) | B19: 1 | C19: 1 month salary per year of service
A20: YoS Threshold (years) | B20: 5 | C20: Tier breakpoint
A21: EoS Basis | B21: Full Monthly Gross | C21: Base+Housing+Transport+Premium+HSA
A23: AJEER COSTS
A24: Annual Ajeer Fee per Worker (incl. VAT) | B24: 10925 | C24: SAR 10,925/year — dependent education permit
A25: Monthly Ajeer Fee per Worker | B25: =B24/12 -> 910.41667 | C25: Auto-calculated
A27: HEADCOUNT (auto-calculated)
A28: Total Contrat Local | B28: =COUNTIF('Master Data'!D5:D194,"Contrat Local") -> 160 | C28: Auto from Master Data
A29: Saudi Employees | B29: =COUNTIFS('Master Data'!D5:D194,"Contrat Local",'Master Data'!M5:M194,"Saudi") -> 2 | C29: Auto from Master Data
A30: Non-Saudi Employees (Ajeer) | B30: =COUNTIFS('Master Data'!D5:D194,"Contrat Local",'Master Data'!M5:M194,"Non-Saudi") -> 158 | C30: Auto from Master Data
A32: NEW POSITIONS
A33: New Positions Start Month | B33: 9 | C33: 9 = September — change to shift all new position costs
A34: New Positions Start Date | B34: =DATE(B4,B33,1) -> 46266 | C34: Auto-calculated
A36: Position | B36: Monthly Gross | C36: Base Salary | D36: IL (Housing) | E36: IT (Transport) | F36: FY Cost
A37: Infirmière (1/2 temps) | B37: 5200 | C37: 3700 | D37: 1250 | E37: 250 | F37: =B37*MAX(0,13-B33) -> 20800
A38: Administratif RH | B38: 10400 | C38: 7400 | D38: 2500 | E38: 500 | F38: =B38*MAX(0,13-$B$33) -> 41600
A39: Administratif Odoo | B39: 10400 | C39: 7400 | D39: 2500 | E39: 500 | F39: =B39*MAX(0,13-$B$33) -> 41600
A40: Administratif MG | B40: 10400 | C40: 7400 | D40: 2500 | E40: 500 | F40: =B40*MAX(0,13-$B$33) -> 41600
A41: Administratif Technicien IT | B41: 10600 | C41: 7600 | D41: 2500 | E41: 500 | F41: =B41*MAX(0,13-$B$33) -> 42400
A42: Administratif Inscription | B42: 10400 | C42: 7400 | D42: 2500 | E42: 500 | F42: =B42*MAX(0,13-$B$33) -> 41600
A43: TOTAL NEW POSITIONS | B43: =SUM(B37:B42) -> 57400 | C43: =SUM(C37:C42) -> 40900 | D43: =SUM(D37:D42) -> 13750 | E43: =SUM(E37:E42) -> 2750 | F43: =SUM(F37:F42) -> 229600
A45: CALCULATED OUTPUTS
A46: Number of New Positions | B46: =COUNTA(A37:A42) -> 6 | C46: Auto-counted from table above
A47: FY Months Active | B47: =MAX(0,13-B33) -> 4 | C47: Months from start month to Dec
A48: Total Monthly Gross (all new) | B48: =B43 -> 57400 | C48: Sum of all new positions monthly gross
A49: Monthly EoS Accrual (new positions) | B49: =B48*B18/12 -> 2391.6667 | C49: Gross × 0.5 mo/yr ÷ 12 (all <5 yrs)
A50: Monthly Ajeer Cost (new positions) | B50: =B46*B25 -> 5462.5 | C50: Count × monthly Ajeer fee per worker

Sheet Number of class 2025-26
A1: École Française Internationale de Riyad (EFIR) - Classes by Level
A3: Cycle | B3: Level | C3: Number of students | D3: Number of Classes
A4: Maternelle | B4: Petite Section (PS) | C4: 65 | D4: 3
A5: Maternelle | B5: Moyenne Section (MS) | C5: 77 | D5: 4
A6: Maternelle | B6: Grande Section (GS) | C6: 124 | D6: 6
A7: Élémentaire | B7: CP (Cours Préparatoire) | C7: 126 | D7: 5
A8: Élémentaire | B8: CE1 | C8: 118 | D8: 5
A9: Élémentaire | B9: CE2 | C9: 132 | D9: 6
A10: Élémentaire | B10: CM1 | C10: 121 | D10: 5
A11: Élémentaire | B11: CM2 | C11: 121 | D11: 5
A12: Collège | B12: 6ème | C12: 151 | D12: 6
A13: Collège | B13: 5ème | C13: 139 | D13: 6
A14: Collège | B14: 4ème | C14: 120 | D14: 5
A15: Collège | B15: 3ème | C15: 103 | D15: 4
... A18: Lycée | B18: Terminale | C18: 111 | D18: 4
A20: SUMMARY BY CYCLE
A21: Maternelle (Kindergarten) | C21: =SUM(C4:C6) -> 266 | D21: =SUM(D4:D6) -> 13
A22: Élémentaire (Elementary) | C22: =SUM(C7:C11) -> 618 | D22: =SUM(D7:D11) -> 26
A23: Collège (Middle School) | C23: =SUM(C12:C15) -> 513 | D23: =SUM(D12:D15) -> 21
A24: Lycée (High School) | C24: =SUM(C16:C18) -> 356 | D24: =SUM(D16:D18) -> 14
A26: TOTAL CLASSES | C26: =SUM(C21:C24) -> 1753 | D26: =SUM(D21:D24) -> 74
A27: Source: EFIR Structure Pédagogique — https://www.efiriyad.com/structure-pedagogique/

Sheet Teacher Requirements
A1: EFIR — Teacher Staffing Requirements Matrix 2025-26
A2: Purpose: Calculate FTE requirements per teacher profile. Blue cells = editable assumptions.
A4: PARAMETERS
A5: Statutory Hours / Week | C5: Certifié | D5: 18 | E5: h/week | G5: HSA (Supp. Hrs) | H5: 2 | I5: h/week
C6: Prof. des Écoles (PE) | D6: 24 | E6: h/week | G6: Effective Certifié | H6: =$D$5+$H$5 -> 20 | I6: h/week
A7: LV2/LVB Student Split | C7: % Arabic | D7: 0.5 | E7: % German | F7: 0.1 | G7: % Spanish | H7: 0.4 | I7: =IF(D7+F7+H7=1,"✓","≠100%!") -> ✓
G8: MATERNELLE | J8: ÉLÉMENTAIRE | O8: COLLÈGE | S8: LYCÉE | V8: COMPUTATION
A9: Category | B9: Type | C9: Subject / Matière | D9: Teacher Profile | E9: Groups / Class | G9: PS | H9: MS | I9: GS | J9: CP | K9: CE1 | L9: CE2 | M9: CM1 | N9: CM2 | O9: 6ème | P9: 5ème | Q9: 4ème | R9: 3ème | S9: 2nde | T9: 1ère | U9: Tle | V9: Total Hrs/Wk | W9: Statutory | X9: FTE Req. | Y9: Headcount
C10: Number of Classes | G10: 3 | H10: 3 | I10: 5 | J10: 6 | K10: 5 | L10: 6 | M10: 5 | N10: 5 | O10: 6 | P10: 6 | Q10: 5 | R10: 4 | S10: 5 | T10: 5 | U10: 4
A11: BLOCK 1 — MATERNELLE / PRIMAIRE
A12: HOMEROOM
A13: Homeroom | C13: Homeroom Maternelle | D13: Professeur des écoles (PE) | E13: 1 | G13: 24 | H13: 24 | I13: 24 | V13: {=SUMPRODUCT(IF(ISNUMBER(G13:U13),G13:U13,0),$G$10:$U$10)*E13} -> 264 | W13: =IF(ISNUMBER(SEARCH("PE",D13)),$D$6,$D$5) -> 24 | X13: =SUM($G$10:$I$10) -> 11 | Y13: =X13 -> 11
A14: Homeroom | B14: Homeroom | C14: ASEM Maternelle | D14: ASEM | E14: 1 | G14: 24 | H14: 24 | I14: 24 | V14: {=SUMPRODUCT(IF(ISNUMBER(G14:U14),G14:U14,0),$G$10:$U$10)*E14} -> 264 | W14: =$D$6 -> 24 | X14: =SUM($G$10:$I$10) -> 11 | Y14: =X14 -> 11
B15: Homeroom | C15: ⬛ Subtotal Maternelle | V15: =V13+V14 -> 528 | W15: =$D$6 -> 24 | X15: =X13 -> 11 | Y15: =X15 -> 11
A16: Homeroom | C16: Homeroom Élémentaire | D16: Professeur des écoles (PE) | E16: 1 | J16: 24 | K16: 24 | L16: 24 | M16: 24 | N16: 24 | V16: {=SUMPRODUCT(IF(ISNUMBER(G16:U16),G16:U16,0),$G$10:$U$10)*E16} -> 648 | W16: =IF(ISNUMBER(SEARCH("PE",D16)),$D$6,$D$5) -> 24 | X16: =SUM($J$10:$N$10) -> 27 | Y16: =X16 -> 27
B17: Homeroom | C17: ⬛ Subtotal Élémentaire | V17: =V16 -> 648 | W17: =$D$6 -> 24 | X17: =X16 -> 27 | Y17: =X16 -> 27
A18: ARABIC LANGUAGE
A19: ▸ Primaire | C19: Arabe (Arabophone group) | D19: Enseignant Arabe | E19: 1 | G19: 2 | H19: 2 | I19: 2.67 | J19: 2 | K19: 2 | L19: 2 | M19: 2 | N19: 2 | V19: {=SUMPRODUCT(IF(ISNUMBER(G19:U19),G19:U19,0),$G$10:$U$10)*E19} -> 79.35 | W19: =IF(ISNUMBER(SEARCH("PE",D19)),$D$6,$D$5) -> 18 | X19: =IF(V19=0,"",V19/$H$6) -> 3.9675 | Y19: =IF(X19="","",ROUNDUP(X19,0)) -> 4
A20: ▸ Primaire | B20: Core | C20: Arabe (Non-Arabophone group) | D20: Enseignant Arabe | E20: 1 | I20: 2.67 | J20: 2 | K20: 2 | L20: 2 | M20: 2 | N20: 2 | V20: {=SUMPRODUCT(IF(ISNUMBER(G20:U20),G20:U20,0),$G$10:$U$10)*E20} -> 67.35 | W20: =IF(ISNUMBER(SEARCH("PE",D20)),$D$6,$D$5) -> 18 | X20: =IF(V20=0,"",V20/$H$6) -> 3.3675 | Y20: =IF(X20="","",ROUNDUP(X20,0)) -> 4
B21: Core | C21: ⬛ Subtotal Primaire (shared pool) | V21: =V19+V20 -> 146.7 | W21: =$D$5 -> 18 | X21: =IF(V21=0,"",V21/$H$6) -> 7.335 | Y21: =IF(X21="","",ROUNDUP(X21,0)) -> 8
A22: ENGLISH LANGUAGE
A23: ▸ Primaire | C23: Anglais (Primaire) | D23: Enseignant Anglais Primaire | E23: 1 | I23: 0.67 | J23: 1.5 | K23: 1.5 | L23: 1.5 | M23: 1.5 | N23: 1.5 | V23: {=SUMPRODUCT(IF(ISNUMBER(G23:U23),G23:U23,0),$G$10:$U$10)*E23} -> 43.85 | W23: =IF(ISNUMBER(SEARCH("PE",D23)),$D$6,$D$5) -> 18 | X23: =IF(V23=0,"",V23/$H$6) -> 2.1925 | Y23: =IF(X23="","",ROUNDUP(X23,0)) -> 3
B24: Core | C24: ⬛ Subtotal Primaire (shared pool) | V24: =V23 -> 43.85 | W24: =$D$5 -> 18 | X24: =IF(V24=0,"",V24/$H$6) -> 2.1925 | Y24: =IF(X24="","",ROUNDUP(X24,0)) -> 3
A26: BLOCK 2 — COLLÈGE / LYCÉE
A27: CORE SUBJECTS — TRONC COMMUN
A28: FRENCH LANGUAGE
A29: Français | B29: Core | C29: Français | D29: Certifié Lettres | E29: 1 | O29: {=IFERROR(INDEX(Curriculum_Detail!H:H,MATCH(1,(Curriculum_Detail!D:D="6e")*(Curriculum_Detail!F:F="Français")*(Curriculum_Detail!E:E="Core"),0)),"")} -> 4.5 | P29: {=IFERROR(INDEX(Curriculum_Detail!H:H,MATCH(1,(Curriculum_Detail!D:D="5e")*(Curriculum_Detail!F:F="Français")*(Curriculum_Detail!E:E="Core"),0)),"")} -> 4.5 | Q29: {=IFERROR(INDEX(Curriculum_Detail!H:H,MATCH(1,(Curriculum_Detail!D:D="4e")*(Curriculum_Detail!F:F="Français")*(Curriculum_Detail!E:E="Core"),0)),"")} -> 4.5 | R29: {=IFERROR(INDEX(Curriculum_Detail!H:H,MATCH(1,(Curriculum_Detail!D:D="3e")*(Curriculum_Detail!F:F="Français")*(Curriculum_Detail!E:E="Core"),0)),"")} -> 4 | S29: {=IFERROR(INDEX(Curriculum_Detail!H:H,MATCH(1,(Curriculum_Detail!D:D="Seconde")*(Curriculum_Detail!F:F="Français")*(Curriculum_Detail!E:E="Core"),0)),"")} -> 4 | T29: {=IFERROR(INDEX(Curriculum_Detail!H:H,MATCH(1,(Curriculum_Detail!D:D="Première")*(Curriculum_Detail!F:F="Français")*(Curriculum_Detail!E:E="Core"),0)),"")} -> 4 | V29: {=SUMPRODUCT(IF(ISNUMBER(G29:U29),G29:U29,0),$G$10:$U$10)*E29} -> 132.5 | W29: =IF(ISNUMBER(SEARCH("PE",D29)),$D$6,$D$5) -> 18 | X29: =IF(V29=0,"",V29/$H$6) -> 6.625 | Y29: =IF(X29="","",ROUNDUP(X29,0)) -> 7
A30: Français | B30: Core | C30: Philosophie | D30: Certifié Philosophie | E30: 1 | U30: {=IFERROR(INDEX(Curriculum_Detail!H:H,MATCH(1,(Curriculum_Detail!D:D="Terminale")*(Curriculum_Detail!F:F="Philosophie")*(Curriculum_Detail!E:E="Core"),0)),"")} -> 4 | V30: {=SUMPRODUCT(IF(ISNUMBER(G30:U30),G30:U30,0),$G$10:$U$10)*E30} -> 16 | W30: =IF(ISNUMBER(SEARCH("PE",D30)),$D$6,$D$5) -> 18 | X30: =IF(V30=0,"",V30/$H$6) -> 0.8 | Y30: =IF(X30="","",ROUNDUP(X30,0)) -> 1
A31: Français | B31: Specialty | C31: Spé. HLP (1ère) | D31: Certifié Lettres | E31: 1 | T31: {=IFERROR(INDEX(Curriculum_Detail!H:H,MATCH(1,(Curriculum_Detail!D:D="Première")*(Curriculum_Detail!F:F="Humanités, littérature et philosophie")*(Curriculum_Detail!E:E="Specialty"),0)),0)} -> 4 | V31: =T31*E31 -> 4 | W31: =$D$5 -> 18 | X31: =IF(V31=0,"",V31/$H$6) -> 0.2 | Y31: =IF(X31="","",ROUNDUP(X31,0)) -> 1
A32: Français | B32: Specialty | C32: Spé. HLP (Tle) | D32: Certifié Philosophie | F32: 1 | U32: {=IFERROR(INDEX(Curriculum_Detail!H:H,MATCH(1,(Curriculum_Detail!D:D="Terminale")*(Curriculum_Detail!F:F="Humanités, littérature et philosophie")*(Curriculum_Detail!E:E="Specialty"),0)),0)} -> 6 | V32: =U32*F32 -> 6 | W32: =$D$5 -> 18 | X32: =IF(V32=0,"",V32/$H$6) -> 0.3 | Y32: =IF(X32="","",ROUNDUP(X32,0)) -> 1
A33: MATHEMATICS
A34: Maths | B34: Core | C34: Mathématiques | D34: Certifié Maths | E34: 1 | O34: {=IFERROR(INDEX(Curriculum_Detail!H:H,MATCH(1,(Curriculum_Detail!D:D="6e")*(Curriculum_Detail!F:F="Mathématiques")*(Curriculum_Detail!E:E="Core"),0)),"")} -> 4.5 | P34: {=IFERROR(INDEX(Curriculum_Detail!H:H,MATCH(1,(Curriculum_Detail!D:D="5e")*(Curriculum_Detail!F:F="Mathématiques")*(Curriculum_Detail!E:E="Core"),0)),"")} -> 3.5 | Q34: {=IFERROR(INDEX(Curriculum_Detail!H:H,MATCH(1,(Curriculum_Detail!D:D="4e")*(Curriculum_Detail!F:F="Mathématiques")*(Curriculum_Detail!E:E="Core"),0)),"")} -> 3.5 | R34: {=IFERROR(INDEX(Curriculum_Detail!H:H,MATCH(1,(Curriculum_Detail!D:D="3e")*(Curriculum_Detail!F:F="Mathématiques")*(Curriculum_Detail!E:E="Core"),0)),"")} -> 3.5 | S34: {=IFERROR(INDEX(Curriculum_Detail!H:H,MATCH(1,(Curriculum_Detail!D:D="Seconde")*(Curriculum_Detail!F:F="Mathématiques")*(Curriculum_Detail!E:E="Core"),0)),"")} -> 4 | V34: {=SUMPRODUCT(IF(ISNUMBER(G34:U34),G34:U34,0),$G$10:$U$10)*E34} -> 99.5 | W34: =IF(ISNUMBER(SEARCH("PE",D34)),$D$6,$D$5) -> 18 | X34: =IF(V34=0,"",V34/$H$6) -> 4.975 | Y34: =IF(X34="","",ROUNDUP(X34,0)) -> 5
A35: Maths | B35: Core | C35: Soutien / approfondissement | D35: Certifié Maths | E35: 1 | O35: {=IFERROR(INDEX(Curriculum_Detail!H:H,MATCH(1,(Curriculum_Detail!D:D="6e")*(Curriculum_Detail!F:F="Soutien / approfondissement en français ou mathématiques")*(Curriculum_Detail!E:E="Core"),0)),"")} -> 1 | V35: {=SUMPRODUCT(IF(ISNUMBER(G35:U35),G35:U35,0),$G$10:$U$10)*E35} -> 6 | W35: =IF(ISNUMBER(SEARCH("PE",D35)),$D$6,$D$5) -> 18 | X35: =IF(V35=0,"",V35/$H$6) -> 0.3 | Y35: =IF(X35="","",ROUNDUP(X35,0)) -> 1
A36: Maths | B36: Specialty | C36: Spé. Mathématiques | D36: Certifié Maths | E36: 2 | F36: 2 | T36: {=IFERROR(INDEX(Curriculum_Detail!H:H,MATCH(1,(Curriculum_Detail!D:D="Première")*(Curriculum_Detail!F:F="Mathématiques")*(Curriculum_Detail!E:E="Specialty"),0)),0)} -> 4 | U36: {=IFERROR(INDEX(Curriculum_Detail!H:H,MATCH(1,(Curriculum_Detail!D:D="Terminale")*(Curriculum_Detail!F:F="Mathématiques")*(Curriculum_Detail!E:E="Specialty"),0)),0)} -> 6 | V36: =T36*E36+U36*F36 -> 20 | W36: =$D$5 -> 18 | X36: =IF(V36=0,"",V36/$H$6) -> 1 | Y36: =IF(X36="","",ROUNDUP(X36,0)) -> 1
A37: Maths | B37: Option | C37: Maths Complémentaires (opt.) | D37: Certifié Maths | E37: 0 | F37: 4 | T37: 0 | U37: 3 | V37: =T37*E37+U37*F37 -> 12 | W37: =$D$5 -> 18 | X37: =IF(V37=0,"",V37/$H$6) -> 0.6 | Y37: =IF(X37="","",ROUNDUP(X37,0)) -> 1
A38: Maths | B38: Option | C38: Maths Expertes (opt.) | D38: Certifié Maths | E38: 0 | F38: 2 | T38: 0 | U38: 3 | V38: =T38*E38+U38*F38 -> 6 | W38: =$D$5 -> 18 | X38: =IF(V38=0,"",V38/$H$6) -> 0.3 | Y38: =IF(X38="","",ROUNDUP(X38,0)) -> 1
A39: HISTORY, GEOGRAPHY & CIVICS
A40: HG-EMC | B40: Core | C40: Histoire-Géographie | D40: Certifié Hist-Géo | E40: 1 | O40: {=IFERROR(INDEX(Curriculum_Detail!H:H,MATCH(1,(Curriculum_Detail!D:D="6e")*(Curriculum_Detail!F:F="Histoire-géographie")*(Curriculum_Detail!E:E="Core"),0)),"")} -> 2.5 | P40: {=IFERROR(INDEX(Curriculum_Detail!H:H,MATCH(1,(Curriculum_Detail!D:D="5e")*(Curriculum_Detail!F:F="Histoire-géographie")*(Curriculum_Detail!E:E="Core"),0)),"")} -> 2.5 | Q40: {=IFERROR(INDEX(Curriculum_Detail!H:H,MATCH(1,(Curriculum_Detail!D:D="4e")*(Curriculum_Detail!F:F="Histoire-géographie")*(Curriculum_Detail!E:E="Core"),0)),"")} -> 2.5 | R40: {=IFERROR(INDEX(Curriculum_Detail!H:H,MATCH(1,(Curriculum_Detail!D:D="3e")*(Curriculum_Detail!F:F="Histoire-géographie")*(Curriculum_Detail!E:E="Core"),0)),"")} -> 3 | S40: {=IFERROR(INDEX(Curriculum_Detail!H:H,MATCH(1,(Curriculum_Detail!D:D="Seconde")*(Curriculum_Detail!F:F="Histoire-géographie")*(Curriculum_Detail!E:E="Core"),0)),"")} -> 3 | T40: {=IFERROR(INDEX(Curriculum_Detail!H:H,MATCH(1,(Curriculum_Detail!D:D="Première")*(Curriculum_Detail!F:F="Histoire-géographie")*(Curriculum_Detail!E:E="Core"),0)),"")} -> 3 | U40: {=IFERROR(INDEX(Curriculum_Detail!H:H,MATCH(1,(Curriculum_Detail!D:D="Terminale")*(Curriculum_Detail!F:F="Histoire-géographie")*(Curriculum_Detail!E:E="Core"),0)),"")} -> 3 | V40: {=SUMPRODUCT(IF(ISNUMBER(G40:U40),G40:U40,0),$G$10:$U$10)*E40} -> 96.5 | W40: =IF(ISNUMBER(SEARCH("PE",D40)),$D$6,$D$5) -> 18 | X40: =IF(V40=0,"",V40/$H$6) -> 4.825 | Y40: =IF(X40="","",ROUNDUP(X40,0)) -> 5
A41: HG-EMC | B41: Core | C41: Enseignement moral et civique | D41: Certifié EMC | E41: 1 | O41: {=IFERROR(INDEX(Curriculum_Detail!H:H,MATCH(1,(Curriculum_Detail!D:D="6e")*(Curriculum_Detail!F:F="Enseignement moral et civique")*(Curriculum_Detail!E:E="Core"),0)),"")} -> 0.5 | P41: {=IFERROR(INDEX(Curriculum_Detail!H:H,MATCH(1,(Curriculum_Detail!D:D="5e")*(Curriculum_Detail!F:F="Enseignement moral et civique")*(Curriculum_Detail!E:E="Core"),0)),"")} -> 0.5 | Q41: {=IFERROR(INDEX(Curriculum_Detail!H:H,MATCH(1,(Curriculum_Detail!D:D="4e")*(Curriculum_Detail!F:F="Enseignement moral et civique")*(Curriculum_Detail!E:E="Core"),0)),"")} -> 0.5 | R41: {=IFERROR(INDEX(Curriculum_Detail!H:H,MATCH(1,(Curriculum_Detail!D:D="3e")*(Curriculum_Detail!F:F="Enseignement moral et civique")*(Curriculum_Detail!E:E="Core"),0)),"")} -> 0.5 | S41: {=IFERROR(INDEX(Curriculum_Detail!H:H,MATCH(1,(Curriculum_Detail!D:D="Seconde")*(Curriculum_Detail!F:F="Enseignement moral et civique")*(Curriculum_Detail!E:E="Core"),0)),"")} -> 0.5 | T41: {=IFERROR(INDEX(Curriculum_Detail!H:H,MATCH(1,(Curriculum_Detail!D:D="Première")*(Curriculum_Detail!F:F="Enseignement moral et civique")*(Curriculum_Detail!E:E="Core"),0)),"")} -> 0.5 | U41: {=IFERROR(INDEX(Curriculum_Detail!H:H,MATCH(1,(Curriculum_Detail!D:D="Terminale")*(Curriculum_Detail!F:F="Enseignement moral et civique")*(Curriculum_Detail!E:E="Core"),0)),"")} -> 0.5 | V41: {=SUMPRODUCT(IF(ISNUMBER(G41:U41),G41:U41,0),$G$10:$U$10)*E41} -> 17.5 | W41: =IF(ISNUMBER(SEARCH("PE",D41)),$D$6,$D$5) -> 18 | X41: =IF(V41=0,"",V41/$H$6) -> 0.875 | Y41: =IF(X41="","",ROUNDUP(X41,0)) -> 1
A42: HG-EMC | B42: Specialty | C42: Spé. HGGSP | D42: Certifié Hist-Géo | E42: 2 | F42: 1 | T42: {=IFERROR(INDEX(Curriculum_Detail!H:H,MATCH(1,(Curriculum_Detail!D:D="Première")*(Curriculum_Detail!F:F="Histoire-géographie, géopolitique et sciences politiques")*(Curriculum_Detail!E:E="Specialty"),0)),0)} -> 4 | U42: {=IFERROR(INDEX(Curriculum_Detail!H:H,MATCH(1,(Curriculum_Detail!D:D="Terminale")*(Curriculum_Detail!F:F="Histoire-géographie, géopolitique et sciences politiques")*(Curriculum_Detail!E:E="Specialty"),0)),0)} -> 6 | V42: =T42*E42+U42*F42 -> 14 | W42: =$D$5 -> 18 | X42: =IF(V42=0,"",V42/$H$6) -> 0.7 | Y42: =IF(X42="","",ROUNDUP(X42,0)) -> 1
A43: ENGLISH LANGUAGE
A44: ▸ Col | B44: Core | C44: Anglais — LV1 (Collège) | D44: Certifié Anglais | E44: 1 | O44: {=IFERROR(INDEX(Curriculum_Detail!H:H,MATCH(1,(Curriculum_Detail!D:D="6e")*(Curriculum_Detail!F:F="Langue vivante 1")*(Curriculum_Detail!E:E="Core"),0)),"")} -> 4 | P44: {=IFERROR(INDEX(Curriculum_Detail!H:H,MATCH(1,(Curriculum_Detail!D:D="5e")*(Curriculum_Detail!F:F="Langue vivante 1")*(Curriculum_Detail!E:E="Core"),0)),"")} -> 3 | Q44: {=IFERROR(INDEX(Curriculum_Detail!H:H,MATCH(1,(Curriculum_Detail!D:D="4e")*(Curriculum_Detail!F:F="Langue vivante 1")*(Curriculum_Detail!E:E="Core"),0)),"")} -> 3 | R44: {=IFERROR(INDEX(Curriculum_Detail!H:H,MATCH(1,(Curriculum_Detail!D:D="3e")*(Curriculum_Detail!F:F="Langue vivante 1")*(Curriculum_Detail!E:E="Core"),0)),"")} -> 3 | V44: {=SUMPRODUCT(IF(ISNUMBER(G44:U44),G44:U44,0),$G$10:$U$10)*E44} -> 69 | W44: =IF(ISNUMBER(SEARCH("PE",D44)),$D$6,$D$5) -> 18 | X44: =IF(V44=0,"",V44/$H$6) -> 3.45 | Y44: =IF(X44="","",ROUNDUP(X44,0)) -> 4
A45: ▸ Lyc | B45: Core | C45: Anglais — LVA (Lycée) | D45: Certifié Anglais | E45: 1 | S45: {=IFERROR(INDEX(Curriculum_Detail!H:H,MATCH(1,(Curriculum_Detail!D:D="Seconde")*(Curriculum_Detail!F:F="LVA + LVB")*(Curriculum_Detail!E:E="Core"),0)),"") - 2.5} -> 3 | T45: {=IFERROR(INDEX(Curriculum_Detail!H:H,MATCH(1,(Curriculum_Detail!D:D="Première")*(Curriculum_Detail!F:F="LVA + LVB")*(Curriculum_Detail!E:E="Core"),0)),"") - 2.5} -> 2 | U45: {=IFERROR(INDEX(Curriculum_Detail!H:H,MATCH(1,(Curriculum_Detail!D:D="Terminale")*(Curriculum_Detail!F:F="LVA + LVB")*(Curriculum_Detail!E:E="Core"),0)),"") - 2.5} -> 1.5 | V45: {=SUMPRODUCT(IF(ISNUMBER(G45:U45),G45:U45,0),$G$10:$U$10)*E45} -> 31 | W45: =IF(ISNUMBER(SEARCH("PE",D45)),$D$6,$D$5) -> 18 | X45: =IF(V45=0,"",V45/$H$6) -> 1.55 | Y45: =IF(X45="","",ROUNDUP(X45,0)) -> 2
A46: ▸ Lyc | B46: Specialty | C46: Spé. LLCE Anglais | D46: Certifié Anglais | E46: 0 | F46: 0 | T46: {=IFERROR(INDEX(Curriculum_Detail!H:H,MATCH(1,(Curriculum_Detail!D:D="Première")*(Curriculum_Detail!F:F="Langues, littératures et cultures étrangères et régionales")*(Curriculum_Detail!E:E="Specialty"),0)),0)} -> 4 | U46: {=IFERROR(INDEX(Curriculum_Detail!H:H,MATCH(1,(Curriculum_Detail!D:D="Terminale")*(Curriculum_Detail!F:F="Langues, littératures et cultures étrangères et régionales")*(Curriculum_Detail!E:E="Specialty"),0)),0)} -> 6 | V46: =T46*E46+U46*F46 -> 0 | W46: =$D$5 -> 18 | X46: =IF(V46=0,"",V46/$H$6) | Y46: =IF(X46="","",ROUNDUP(X46,0))
C47: Total Certifié Anglais | V47: =V44+V45+V46 -> 100 | W47: =$D$5 -> 18 | X47: =IF(V47=0,"",V47/$H$6) -> 5 | Y47: =IF(X47="","",ROUNDUP(X47,0)) -> 5
A48: ARABIC LANGUAGE
A49: ▸ Col | B49: Core | C49: Arabe — LV2 (Collège 5e–3e) | D49: Certifié Arabe | E49: =$D$7 -> 0.5 | P49: {=IFERROR(INDEX(Curriculum_Detail!H:H,MATCH(1,(Curriculum_Detail!D:D="5e")*(Curriculum_Detail!F:F="Langue vivante 2")*(Curriculum_Detail!E:E="Core"),0)),"")} -> 2.5 | Q49: {=IFERROR(INDEX(Curriculum_Detail!H:H,MATCH(1,(Curriculum_Detail!D:D="4e")*(Curriculum_Detail!F:F="Langue vivante 2")*(Curriculum_Detail!E:E="Core"),0)),"")} -> 2.5 | R49: {=IFERROR(INDEX(Curriculum_Detail!H:H,MATCH(1,(Curriculum_Detail!D:D="3e")*(Curriculum_Detail!F:F="Langue vivante 2")*(Curriculum_Detail!E:E="Core"),0)),"")} -> 2.5 | V49: {=SUMPRODUCT(IF(ISNUMBER(G49:U49),G49:U49,0),$G$10:$U$10)*E49} -> 18.75 | W49: =IF(ISNUMBER(SEARCH("PE",D49)),$D$6,$D$5) -> 18 | X49: =IF(V49=0,"",V49/$H$6) -> 0.9375 | Y49: =IF(X49="","",ROUNDUP(X49,0)) -> 1
A50: ▸ Lyc | B50: Core | C50: Arabe — LVB (Lycée) | D50: Certifié Arabe | E50: =$D$7 -> 0.5 | S50: 2.5 | T50: 2.5 | U50: 2.5 | V50: {=SUMPRODUCT(IF(ISNUMBER(G50:U50),G50:U50,0),$G$10:$U$10)*E50} -> 17.5 | W50: =IF(ISNUMBER(SEARCH("PE",D50)),$D$6,$D$5) -> 18 | X50: =IF(V50=0,"",V50/$H$6) -> 0.875 | Y50: =IF(X50="","",ROUNDUP(X50,0)) -> 1
C51: Total Certifié Arabe | V51: =V49+V50 -> 36.25 | W51: =$D$5 -> 18 | X51: =IF(V51=0,"",V51/$H$6) -> 1.8125 | Y51: =IF(X51="","",ROUNDUP(X51,0)) -> 2
A52: GERMAN LANGUAGE
A53: ▸ Col | B53: Core | C53: Allemand — LV2 (Collège 5e–3e) | D53: Certifié Allemand | E53: =$F$7 -> 0.1 | P53: {=IFERROR(INDEX(Curriculum_Detail!H:H,MATCH(1,(Curriculum_Detail!D:D="5e")*(Curriculum_Detail!F:F="Langue vivante 2")*(Curriculum_Detail!E:E="Core"),0)),"")} -> 2.5 | Q53: {=IFERROR(INDEX(Curriculum_Detail!H:H,MATCH(1,(Curriculum_Detail!D:D="4e")*(Curriculum_Detail!F:F="Langue vivante 2")*(Curriculum_Detail!E:E="Core"),0)),"")} -> 2.5 | R53: {=IFERROR(INDEX(Curriculum_Detail!H:H,MATCH(1,(Curriculum_Detail!D:D="3e")*(Curriculum_Detail!F:F="Langue vivante 2")*(Curriculum_Detail!E:E="Core"),0)),"")} -> 2.5 | V53: {=SUMPRODUCT(IF(ISNUMBER(G53:U53),G53:U53,0),$G$10:$U$10)*E53} -> 3.75 | W53: =IF(ISNUMBER(SEARCH("PE",D53)),$D$6,$D$5) -> 18 | X53: =IF(V53=0,"",V53/$H$6) -> 0.1875 | Y53: =IF(X53="","",ROUNDUP(X53,0)) -> 1
A54: ▸ Lyc | B54: Core | C54: Allemand — LVB (Lycée) | D54: Certifié Allemand | E54: =$F$7 -> 0.1 | S54: 2.5 | T54: 2.5 | U54: 2.5 | V54: {=SUMPRODUCT(IF(ISNUMBER(G54:U54),G54:U54,0),$G$10:$U$10)*E54} -> 3.5 | W54: =IF(ISNUMBER(SEARCH("PE",D54)),$D$6,$D$5) -> 18 | X54: =IF(V54=0,"",V54/$H$6) -> 0.175 | Y54: =IF(X54="","",ROUNDUP(X54,0)) -> 1
C55: Total Certifié Allemand | V55: =V53+V54 -> 7.25 | W55: =$D$5 -> 18 | X55: =IF(V55=0,"",V55/$H$6) -> 0.3625 | Y55: =IF(X55="","",ROUNDUP(X55,0)) -> 1
A56: SPANISH LANGUAGE
A57: ▸ Col | B57: Core | C57: Espagnol — LV2 (Collège 5e–3e) | D57: Certifié Espagnol | E57: =$H$7 -> 0.4 | P57: {=IFERROR(INDEX(Curriculum_Detail!H:H,MATCH(1,(Curriculum_Detail!D:D="5e")*(Curriculum_Detail!F:F="Langue vivante 2")*(Curriculum_Detail!E:E="Core"),0)),"")} -> 2.5 | Q57: {=IFERROR(INDEX(Curriculum_Detail!H:H,MATCH(1,(Curriculum_Detail!D:D="4e")*(Curriculum_Detail!F:F="Langue vivante 2")*(Curriculum_Detail!E:E="Core"),0)),"")} -> 2.5 | R57: {=IFERROR(INDEX(Curriculum_Detail!H:H,MATCH(1,(Curriculum_Detail!D:D="3e")*(Curriculum_Detail!F:F="Langue vivante 2")*(Curriculum_Detail!E:E="Core"),0)),"")} -> 2.5 | V57: {=SUMPRODUCT(IF(ISNUMBER(G57:U57),G57:U57,0),$G$10:$U$10)*E57} -> 15 | W57: =IF(ISNUMBER(SEARCH("PE",D57)),$D$6,$D$5) -> 18 | X57: =IF(V57=0,"",V57/$H$6) -> 0.75 | Y57: =IF(X57="","",ROUNDUP(X57,0)) -> 1
A58: ▸ Lyc | B58: Core | C58: Espagnol — LVB (Lycée) | D58: Certifié Espagnol | E58: =$H$7 -> 0.4 | S58: 2.5 | T58: 2.5 | U58: 2.5 | V58: {=SUMPRODUCT(IF(ISNUMBER(G58:U58),G58:U58,0),$G$10:$U$10)*E58} -> 14 | W58: =IF(ISNUMBER(SEARCH("PE",D58)),$D$6,$D$5) -> 18 | X58: =IF(V58=0,"",V58/$H$6) -> 0.7 | Y58: =IF(X58="","",ROUNDUP(X58,0)) -> 1
C59: Total Certifié Espagnol | V59: =V57+V58 -> 29 | W59: =$D$5 -> 18 | X59: =IF(V59=0,"",V59/$H$6) -> 1.45 | Y59: =IF(X59="","",ROUNDUP(X59,0)) -> 2
A60: SCIENCES
A61: Sciences | B61: Core | C61: SVT | D61: Certifié SVT | E61: 1 | O61: 1.5 | P61: {=IFERROR(INDEX(Curriculum_Detail!H:H,MATCH(1,(Curriculum_Detail!D:D="5e")*(Curriculum_Detail!F:F="Sciences de la vie et de la Terre")*(Curriculum_Detail!E:E="Core"),0)),"")} -> 1.5 | Q61: {=IFERROR(INDEX(Curriculum_Detail!H:H,MATCH(1,(Curriculum_Detail!D:D="4e")*(Curriculum_Detail!F:F="Sciences de la vie et de la Terre")*(Curriculum_Detail!E:E="Core"),0)),"")} -> 1.5 | R61: {=IFERROR(INDEX(Curriculum_Detail!H:H,MATCH(1,(Curriculum_Detail!D:D="3e")*(Curriculum_Detail!F:F="Sciences de la vie et de la Terre")*(Curriculum_Detail!E:E="Core"),0)),"")} -> 1.5 | S61: {=IFERROR(INDEX(Curriculum_Detail!H:H,MATCH(1,(Curriculum_Detail!D:D="Seconde")*(Curriculum_Detail!F:F="Sciences de la vie et de la Terre")*(Curriculum_Detail!E:E="Core"),0)),"")} -> 1.5 | V61: {=SUMPRODUCT(IF(ISNUMBER(G61:U61),G61:U61,0),$G$10:$U$10)*E61} -> 39 | W61: =IF(ISNUMBER(SEARCH("PE",D61)),$D$6,$D$5) -> 18 | X61: =IF(V61=0,"",V61/$H$6) -> 1.95 | Y61: =IF(X61="","",ROUNDUP(X61,0)) -> 2
A62: Sciences | B62: Specialty | C62: Spé. SVT | D62: Certifié SVT | E62: 1 | F62: 1 | T62: {=IFERROR(INDEX(Curriculum_Detail!H:H,MATCH(1,(Curriculum_Detail!D:D="Première")*(Curriculum_Detail!F:F="Sciences de la vie et de la Terre")*(Curriculum_Detail!E:E="Specialty"),0)),0)} -> 4 | U62: {=IFERROR(INDEX(Curriculum_Detail!H:H,MATCH(1,(Curriculum_Detail!D:D="Terminale")*(Curriculum_Detail!F:F="Sciences de la vie et de la Terre")*(Curriculum_Detail!E:E="Specialty"),0)),0)} -> 6 | V62: =T62*E62+U62*F62 -> 10 | W62: =$D$5 -> 18 | X62: =IF(V62=0,"",V62/$H$6) -> 0.5 | Y62: =IF(X62="","",ROUNDUP(X62,0)) -> 1
A63: Sciences | B63: Core | C63: Physique-Chimie | D63: Certifié Physique-Chimie | E63: 1 | O63: 1.5 | P63: {=IFERROR(INDEX(Curriculum_Detail!H:H,MATCH(1,(Curriculum_Detail!D:D="5e")*(Curriculum_Detail!F:F="Physique-chimie")*(Curriculum_Detail!E:E="Core"),0)),"")} -> 1.5 | Q63: {=IFERROR(INDEX(Curriculum_Detail!H:H,MATCH(1,(Curriculum_Detail!D:D="4e")*(Curriculum_Detail!F:F="Physique-chimie")*(Curriculum_Detail!E:E="Core"),0)),"")} -> 1.5 | R63: {=IFERROR(INDEX(Curriculum_Detail!H:H,MATCH(1,(Curriculum_Detail!D:D="3e")*(Curriculum_Detail!F:F="Physique-chimie")*(Curriculum_Detail!E:E="Core"),0)),"")} -> 1.5 | S63: {=IFERROR(INDEX(Curriculum_Detail!H:H,MATCH(1,(Curriculum_Detail!D:D="Seconde")*(Curriculum_Detail!F:F="Physique-chimie")*(Curriculum_Detail!E:E="Core"),0)),"")} -> 3 | V63: {=SUMPRODUCT(IF(ISNUMBER(G63:U63),G63:U63,0),$G$10:$U$10)*E63} -> 46.5 | W63: =IF(ISNUMBER(SEARCH("PE",D63)),$D$6,$D$5) -> 18 | X63: =IF(V63=0,"",V63/$H$6) -> 2.325 | Y63: =IF(X63="","",ROUNDUP(X63,0)) -> 3
A64: Sciences | B64: Specialty | C64: Spé. Physique-Chimie | D64: Certifié Physique-Chimie | E64: 1 | F64: 1 | T64: {=IFERROR(INDEX(Curriculum_Detail!H:H,MATCH(1,(Curriculum_Detail!D:D="Première")*(Curriculum_Detail!F:F="Physique-chimie")*(Curriculum_Detail!E:E="Specialty"),0)),0)} -> 4 | U64: {=IFERROR(INDEX(Curriculum_Detail!H:H,MATCH(1,(Curriculum_Detail!D:D="Terminale")*(Curriculum_Detail!F:F="Physique-chimie")*(Curriculum_Detail!E:E="Specialty"),0)),0)} -> 6 | V64: =T64*E64+U64*F64 -> 10 | W64: =$D$5 -> 18 | X64: =IF(V64=0,"",V64/$H$6) -> 0.5 | Y64: =IF(X64="","",ROUNDUP(X64,0)) -> 1
A65: Sciences | B65: Core | C65: Technologie (Cycle 4) | D65: Certifié Technologie | E65: 1 | P65: {=IFERROR(INDEX(Curriculum_Detail!H:H,MATCH(1,(Curriculum_Detail!D:D="5e")*(Curriculum_Detail!F:F="Technologie")*(Curriculum_Detail!E:E="Core"),0)),"")} -> 1.5 | Q65: {=IFERROR(INDEX(Curriculum_Detail!H:H,MATCH(1,(Curriculum_Detail!D:D="4e")*(Curriculum_Detail!F:F="Technologie")*(Curriculum_Detail!E:E="Core"),0)),"")} -> 1.5 | R65: {=IFERROR(INDEX(Curriculum_Detail!H:H,MATCH(1,(Curriculum_Detail!D:D="3e")*(Curriculum_Detail!F:F="Technologie")*(Curriculum_Detail!E:E="Core"),0)),"")} -> 1.5 | V65: {=SUMPRODUCT(IF(ISNUMBER(G65:U65),G65:U65,0),$G$10:$U$10)*E65} -> 22.5 | W65: =IF(ISNUMBER(SEARCH("PE",D65)),$D$6,$D$5) -> 18 | X65: =IF(V65=0,"",V65/$H$6) -> 1.125 | Y65: =IF(X65="","",ROUNDUP(X65,0)) -> 2
A66: Sciences | B66: Core | C66: SNT (2nde) | D66: Certifié Technologie | E66: 1 | S66: {=IFERROR(INDEX(Curriculum_Detail!H:H,MATCH(1,(Curriculum_Detail!D:D="Seconde")*(Curriculum_Detail!F:F="Sciences numériques et technologie")*(Curriculum_Detail!E:E="Core"),0)),"")} -> 1.5 | V66: {=SUMPRODUCT(IF(ISNUMBER(G66:U66),G66:U66,0),$G$10:$U$10)*E66} -> 7.5 | W66: =IF(ISNUMBER(SEARCH("PE",D66)),$D$6,$D$5) -> 18 | X66: =IF(V66=0,"",V66/$H$6) -> 0.375 | Y66: =IF(X66="","",ROUNDUP(X66,0)) -> 1
A67: Sciences | B67: Core | C67: Enseignement Scientifique | D67: Certifié Sciences (mutualisé) | E67: 1 | T67: {=IFERROR(INDEX(Curriculum_Detail!H:H,MATCH(1,(Curriculum_Detail!D:D="Première")*(Curriculum_Detail!F:F="Enseignement scientifique")*(Curriculum_Detail!E:E="Core"),0)),"")} -> 2 | U67: {=IFERROR(INDEX(Curriculum_Detail!H:H,MATCH(1,(Curriculum_Detail!D:D="Terminale")*(Curriculum_Detail!F:F="Enseignement scientifique")*(Curriculum_Detail!E:E="Core"),0)),"")} -> 2 | V67: {=SUMPRODUCT(IF(ISNUMBER(G67:U67),G67:U67,0),$G$10:$U$10)*E67} -> 18 | W67: =IF(ISNUMBER(SEARCH("PE",D67)),$D$6,$D$5) -> 18 | X67: =IF(V67=0,"",V67/$H$6) -> 0.9 | Y67: =IF(X67="","",ROUNDUP(X67,0)) -> 1
A68: Sciences | B68: Core | C68: SES (2nde) | D68: Certifié SES | E68: 1 | S68: {=IFERROR(INDEX(Curriculum_Detail!H:H,MATCH(1,(Curriculum_Detail!D:D="Seconde")*(Curriculum_Detail!F:F="Sciences économiques et sociales")*(Curriculum_Detail!E:E="Core"),0)),"")} -> 1.5 | V68: {=SUMPRODUCT(IF(ISNUMBER(G68:U68),G68:U68,0),$G$10:$U$10)*E68} -> 7.5 | W68: =IF(ISNUMBER(SEARCH("PE",D68)),$D$6,$D$5) -> 18 | X68: =IF(V68=0,"",V68/$H$6) -> 0.375 | Y68: =IF(X68="","",ROUNDUP(X68,0)) -> 1
A69: Sciences | B69: Specialty | C69: Spé. SES | D69: Certifié SES | E69: 1 | F69: 4 | T69: {=IFERROR(INDEX(Curriculum_Detail!H:H,MATCH(1,(Curriculum_Detail!D:D="Première")*(Curriculum_Detail!F:F="Sciences économiques et sociales")*(Curriculum_Detail!E:E="Specialty"),0)),0)} -> 4 | U69: {=IFERROR(INDEX(Curriculum_Detail!H:H,MATCH(1,(Curriculum_Detail!D:D="Terminale")*(Curriculum_Detail!F:F="Sciences économiques et sociales")*(Curriculum_Detail!E:E="Specialty"),0)),0)} -> 6 | V69: =T69*E69+U69*F69 -> 28 | W69: =$D$5 -> 18 | X69: =IF(V69=0,"",V69/$H$6) -> 1.4 | Y69: =IF(X69="","",ROUNDUP(X69,0)) -> 2
A70: Sciences | B70: Specialty | C70: Spé. NSI | D70: Certifié NSI/Maths | E70: 1 | F70: 1 | T70: {=IFERROR(INDEX(Curriculum_Detail!H:H,MATCH(1,(Curriculum_Detail!D:D="Première")*(Curriculum_Detail!F:F="Numérique et sciences informatiques")*(Curriculum_Detail!E:E="Specialty"),0)),0)} -> 4 | U70: {=IFERROR(INDEX(Curriculum_Detail!H:H,MATCH(1,(Curriculum_Detail!D:D="Terminale")*(Curriculum_Detail!F:F="Numérique et sciences informatiques")*(Curriculum_Detail!E:E="Specialty"),0)),0)} -> 6 | V70: =T70*E70+U70*F70 -> 10 | W70: =$D$5 -> 18 | X70: =IF(V70=0,"",V70/$H$6) -> 0.5 | Y70: =IF(X70="","",ROUNDUP(X70,0)) -> 1
A71: Arts | B71: Core | C71: Arts Plastiques | D71: Certifié Arts Plastiques | E71: 1 | O71: {=IFERROR(INDEX(Curriculum_Detail!H:H,MATCH(1,(Curriculum_Detail!D:D="6e")*(Curriculum_Detail!F:F="Arts plastiques")*(Curriculum_Detail!E:E="Core"),0)),"")} -> 1 | P71: {=IFERROR(INDEX(Curriculum_Detail!H:H,MATCH(1,(Curriculum_Detail!D:D="5e")*(Curriculum_Detail!F:F="Arts plastiques")*(Curriculum_Detail!E:E="Core"),0)),"")} -> 1 | Q71: {=IFERROR(INDEX(Curriculum_Detail!H:H,MATCH(1,(Curriculum_Detail!D:D="4e")*(Curriculum_Detail!F:F="Arts plastiques")*(Curriculum_Detail!E:E="Core"),0)),"")} -> 1 | R71: {=IFERROR(INDEX(Curriculum_Detail!H:H,MATCH(1,(Curriculum_Detail!D:D="3e")*(Curriculum_Detail!F:F="Arts plastiques")*(Curriculum_Detail!E:E="Core"),0)),"")} -> 1 | V71: {=SUMPRODUCT(IF(ISNUMBER(G71:U71),G71:U71,0),$G$10:$U$10)*E71} -> 21 | W71: =IF(ISNUMBER(SEARCH("PE",D71)),$D$6,$D$5) -> 18 | X71: =IF(V71=0,"",V71/$H$6) -> 1.05 | Y71: =IF(X71="","",ROUNDUP(X71,0)) -> 2
A72: Arts | B72: Core | C72: Éducation Musicale | D72: Certifié Éducation Musicale | E72: 1 | O72: {=IFERROR(INDEX(Curriculum_Detail!H:H,MATCH(1,(Curriculum_Detail!D:D="6e")*(Curriculum_Detail!F:F="Éducation musicale")*(Curriculum_Detail!E:E="Core"),0)),"")} -> 1 | P72: {=IFERROR(INDEX(Curriculum_Detail!H:H,MATCH(1,(Curriculum_Detail!D:D="5e")*(Curriculum_Detail!F:F="Éducation musicale")*(Curriculum_Detail!E:E="Core"),0)),"")} -> 1 | Q72: {=IFERROR(INDEX(Curriculum_Detail!H:H,MATCH(1,(Curriculum_Detail!D:D="4e")*(Curriculum_Detail!F:F="Éducation musicale")*(Curriculum_Detail!E:E="Core"),0)),"")} -> 1 | R72: {=IFERROR(INDEX(Curriculum_Detail!H:H,MATCH(1,(Curriculum_Detail!D:D="3e")*(Curriculum_Detail!F:F="Éducation musicale")*(Curriculum_Detail!E:E="Core"),0)),"")} -> 1 | V72: {=SUMPRODUCT(IF(ISNUMBER(G72:U72),G72:U72,0),$G$10:$U$10)*E72} -> 21 | W72: =IF(ISNUMBER(SEARCH("PE",D72)),$D$6,$D$5) -> 18 | X72: =IF(V72=0,"",V72/$H$6) -> 1.05 | Y72: =IF(X72="","",ROUNDUP(X72,0)) -> 2
A73: EPS
A74: EPS | B74: Core | C74: EPS | D74: Certifié EPS | E74: 1 | O74: {=IFERROR(INDEX(Curriculum_Detail!H:H,MATCH(1,(Curriculum_Detail!D:D="6e")*(Curriculum_Detail!F:F="Éducation physique et sportive")*(Curriculum_Detail!E:E="Core"),0)),"")} -> 4 | P74: {=IFERROR(INDEX(Curriculum_Detail!H:H,MATCH(1,(Curriculum_Detail!D:D="5e")*(Curriculum_Detail!F:F="Éducation physique et sportive")*(Curriculum_Detail!E:E="Core"),0)),"")} -> 3 | Q74: {=IFERROR(INDEX(Curriculum_Detail!H:H,MATCH(1,(Curriculum_Detail!D:D="4e")*(Curriculum_Detail!F:F="Éducation physique et sportive")*(Curriculum_Detail!E:E="Core"),0)),"")} -> 3 | R74: {=IFERROR(INDEX(Curriculum_Detail!H:H,MATCH(1,(Curriculum_Detail!D:D="3e")*(Curriculum_Detail!F:F="Éducation physique et sportive")*(Curriculum_Detail!E:E="Core"),0)),"")} -> 3 | S74: {=IFERROR(INDEX(Curriculum_Detail!H:H,MATCH(1,(Curriculum_Detail!D:D="Seconde")*(Curriculum_Detail!F:F="Éducation physique et sportive")*(Curriculum_Detail!E:E="Core"),0)),"")} -> 2 | T74: {=IFERROR(INDEX(Curriculum_Detail!H:H,MATCH(1,(Curriculum_Detail!D:D="Première")*(Curriculum_Detail!F:F="Éducation physique et sportive")*(Curriculum_Detail!E:E="Core"),0)),"")} -> 2 | U74: {=IFERROR(INDEX(Curriculum_Detail!H:H,MATCH(1,(Curriculum_Detail!D:D="Terminale")*(Curriculum_Detail!F:F="Éducation physique et sportive")*(Curriculum_Detail!E:E="Core"),0)),"")} -> 2 | V74: {=SUMPRODUCT(IF(ISNUMBER(G74:U74),G74:U74,0),$G$10:$U$10)*E74} -> 97 | W74: =IF(ISNUMBER(SEARCH("PE",D74)),$D$6,$D$5) -> 18 | X74: =IF(V74=0,"",V74/$H$6) -> 4.85 | Y74: =IF(X74="","",ROUNDUP(X74,0)) -> 5
A75: ⬛ SUBTOTAL BLOCK 2 — COLLÈGE / LYCÉE | V75: =V29+V30+V31+V34+V35+V36+V37+V38+V40+V41+V42+V44+V45+V48+V49+V50+V59+V61+V62+V63+V64+V65+V66+V67+V68+V69+V70+V71+V72+V74 -> 927.25 | W75: =$D$5 -> 18 | X75: =IF(V75=0,"",V75/$H$6) -> 46.3625 | Y75: =IF(X75="","",ROUNDUP(X75,0)) -> 47
A77: # | B77: Teacher Profile | C77: Block | D77: Total Hrs/Wk | E77: Statutory | F77: HSA | G77: FTE Req. | H77: Headcount | I77: Existing | J77: Titulaire EN | K77: Total Supply | L77: Gap / Surplus | M77: Action
A78: 1 | B78: Professeur des écoles (PE) | C78: Primaire | D78: =SUMIF($D$11:$D$74,B78,$V$11:$V$74) -> 912 | E78: =$D$6 -> 24 | G78: =IF(D78=0,"",D78/(E78+F78)) -> 38 | H78: =IF(G78="","",ROUNDUP(G78,0)) -> 38 | I78: =COUNTIFS('Master Data'!$J:$J,B78,'Master Data'!$L:$L,"Existing") -> 33 | J78: =COUNTIFS('Master Data'!$J:$J,B78,'Master Data'!$L:$L,"Titulaire EN") -> 7 | K78: =I78+J78 -> 40 | L78: =K78-H78 -> 2 | M78: =IF(L78<0,"Recruit "&ABS(L78),IF(L78>0,"Surplus "&L78,"OK")) -> Surplus 2
A79: 2 | B79: ASEM | C79: Primaire | D79: =SUMIF($D$11:$D$74,B79,$V$11:$V$74) -> 264 | E79: =$D$6 -> 24 | G79: =IF(D79=0,"",D79/(E79+F79)) -> 11 | H79: =IF(G79="","",ROUNDUP(G79,0)) -> 11 | I79: =COUNTIFS('Master Data'!$H:$H,B79,'Master Data'!$L:$L,"Existing") -> 13 | J79: =COUNTIFS('Master Data'!$H:$H,B79,'Master Data'!$L:$L,"Titulaire EN") -> 0 | K79: =I79+J79 -> 13 | L79: =K79-H79 -> 2 | M79: =IF(L79<0,"Recruit "&ABS(L79),IF(L79>0,"Surplus "&L79,"OK")) -> Surplus 2
A80: 3 | B80: Enseignant Arabe | C80: Primaire | D80: =SUMIF($D$11:$D$74,B80,$V$11:$V$74) -> 146.7 | E80: =$D$5 -> 18 | F80: 1 | G80: =IF(D80=0,"",D80/(E80+F80)) -> 7.7210526 | H80: =IF(G80="","",ROUNDUP(G80,0)) -> 8 | I80: =COUNTIFS('Master Data'!$J:$J,B80,'Master Data'!$L:$L,"Existing") -> 7 | J80: =COUNTIFS('Master Data'!$J:$J,B80,'Master Data'!$L:$L,"Titulaire EN") -> 0 | K80: =I80+J80 -> 7 | L80: =K80-H80 -> -1 | M80: =IF(L80<0,"Recruit "&ABS(L80),IF(L80>0,"Surplus "&L80,"OK")) -> Recruit 1
A81: 4 | B81: Enseignant Anglais Primaire | C81: Primaire | D81: =SUMIF($D$11:$D$74,B81,$V$11:$V$74) -> 43.85 | E81: =$D$5 -> 18 | G81: =IF(D81=0,"",D81/(E81+F81)) -> 2.4361111 | H81: =IF(G81="","",ROUNDUP(G81,0)) -> 3 | I81: =COUNTIFS('Master Data'!$J:$J,B81,'Master Data'!$L:$L,"Existing") -> 4 | J81: =COUNTIFS('Master Data'!$J:$J,B81,'Master Data'!$L:$L,"Titulaire EN") -> 0 | K81: =I81+J81 -> 4 | L81: =K81-H81 -> 1 | M81: =IF(L81<0,"Recruit "&ABS(L81),IF(L81>0,"Surplus "&L81,"OK")) -> Surplus 1
A82: 5 | B82: Certifié Lettres | C82: Collège/Lycée | D82: =SUMIF($D$11:$D$74,B82,$V$11:$V$74) -> 136.5 | E82: =$D$5 -> 18 | F82: 2 | G82: =IF(D82=0,"",D82/(E82+F82)) -> 6.825 | H82: =IF(G82="","",ROUNDUP(G82,0)) -> 7 | I82: =COUNTIFS('Master Data'!$J:$J,B82,'Master Data'!$L:$L,"Existing") -> 7 | J82: =COUNTIFS('Master Data'!$J:$J,B82,'Master Data'!$L:$L,"Titulaire EN") -> 3 | K82: =I82+J82 -> 10 | L82: =K82-H82 -> 3 | M82: =IF(L82<0,"Recruit "&ABS(L82),IF(L82>0,"Surplus "&L82,"OK")) -> Surplus 3
A83: 6 | B83: Certifié Philosophie | C83: Collège/Lycée | D83: =SUMIF($D$11:$D$74,B83,$V$11:$V$74) -> 22 | E83: =$D$5 -> 18 | F83: 2 | G83: =IF(D83=0,"",D83/(E83+F83)) -> 1.1 | H83: =IF(G83="","",ROUNDUP(G83,0)) -> 2 | I83: =COUNTIFS('Master Data'!$J:$J,B83,'Master Data'!$L:$L,"Existing") -> 1 | J83: =COUNTIFS('Master Data'!$J:$J,B83,'Master Data'!$L:$L,"Titulaire EN") -> 0 | K83: =I83+J83 -> 1 | L83: =K83-H83 -> -1 | M83: =IF(L83<0,"Recruit "&ABS(L83),IF(L83>0,"Surplus "&L83,"OK")) -> Recruit 1
A84: 7 | B84: Certifié Maths | C84: Collège/Lycée | D84: =SUMIF($D$11:$D$74,B84,$V$11:$V$74) -> 143.5 | E84: =$D$5 -> 18 | G84: =IF(D84=0,"",D84/(E84+F84)) -> 7.9722222 | H84: =IF(G84="","",ROUNDUP(G84,0)) -> 8 | I84: =COUNTIFS('Master Data'!$J:$J,B84,'Master Data'!$L:$L,"Existing") -> 6 | J84: =COUNTIFS('Master Data'!$J:$J,B84,'Master Data'!$L:$L,"Titulaire EN") -> 2 | K84: =I84+J84 -> 8 | L84: =K84-H84 -> 0 | M84: =IF(L84<0,"Recruit "&ABS(L84),IF(L84>0,"Surplus "&L84,"OK")) -> OK
A85: 8 | B85: Certifié Hist-Géo | C85: Collège/Lycée | D85: =SUMIF($D$11:$D$74,B85,$V$11:$V$74) -> 110.5 | E85: =$D$5 -> 18 | F85: 1 | G85: =IF(D85=0,"",D85/(E85+F85)) -> 5.8157895 | H85: =IF(G85="","",ROUNDUP(G85,0)) -> 6 | I85: =COUNTIFS('Master Data'!$J:$J,B85,'Master Data'!$L:$L,"Existing") -> 3 | J85: =COUNTIFS('Master Data'!$J:$J,B85,'Master Data'!$L:$L,"Titulaire EN") -> 2 | K85: =I85+J85 -> 5 | L85: =K85-H85 -> -1 | M85: =IF(L85<0,"Recruit "&ABS(L85),IF(L85>0,"Surplus "&L85,"OK")) -> Recruit 1
A86: 9 | B86: Certifié EMC | C86: Collège/Lycée | D86: =SUMIF($D$11:$D$74,B86,$V$11:$V$74) -> 17.5 | E86: =$D$5 -> 18 | G86: =IF(D86=0,"",D86/(E86+F86)) -> 0.97222222 | H86: =IF(G86="","",ROUNDUP(G86,0)) -> 1 | I86: =COUNTIFS('Master Data'!$J:$J,B86,'Master Data'!$L:$L,"Existing") -> 1 | J86: =COUNTIFS('Master Data'!$J:$J,B86,'Master Data'!$L:$L,"Titulaire EN") -> 0 | K86: =I86+J86 -> 1 | L86: =K86-H86 -> 0 | M86: =IF(L86<0,"Recruit "&ABS(L86),IF(L86>0,"Surplus "&L86,"OK")) -> OK
A87: 10 | B87: Certifié Anglais | C87: Collège/Lycée | D87: =SUMIF($D$11:$D$74,B87,$V$11:$V$74) -> 100 | E87: =$D$5 -> 18 | F87: 2 | G87: =IF(D87=0,"",D87/(E87+F87)) -> 5 | H87: =IF(G87="","",ROUNDUP(G87,0)) -> 5 | I87: =COUNTIFS('Master Data'!$J:$J,B87,'Master Data'!$L:$L,"Existing") -> 4 | J87: =COUNTIFS('Master Data'!$J:$J,B87,'Master Data'!$L:$L,"Titulaire EN") -> 2 | K87: =I87+J87 -> 6 | L87: =K87-H87 -> 1 | M87: =IF(L87<0,"Recruit "&ABS(L87),IF(L87>0,"Surplus "&L87,"OK")) -> Surplus 1
A88: 11 | B88: Certifié Arabe | C88: Collège/Lycée | D88: =SUMIF($D$11:$D$74,B88,$V$11:$V$74) -> 36.25 | E88: =$D$5 -> 18 | G88: =IF(D88=0,"",D88/(E88+F88)) -> 2.0138889 | H88: =IF(G88="","",ROUNDUP(G88,0)) -> 3 | I88: =COUNTIFS('Master Data'!$J:$J,B88,'Master Data'!$L:$L,"Existing") -> 5 | J88: =COUNTIFS('Master Data'!$J:$J,B88,'Master Data'!$L:$L,"Titulaire EN") -> 0 | K88: =I88+J88 -> 5 | L88: =K88-H88 -> 2 | M88: =IF(L88<0,"Recruit "&ABS(L88),IF(L88>0,"Surplus "&L88,"OK")) -> Surplus 2
A89: 12 | B89: Certifié Allemand | C89: Collège/Lycée | D89: =SUMIF($D$11:$D$74,B89,$V$11:$V$74) -> 7.25 | E89: =$D$5 -> 18 | G89: =IF(D89=0,"",D89/(E89+F89)) -> 0.40277778 | H89: =IF(G89="","",ROUNDUP(G89,0)) -> 1 | I89: =COUNTIFS('Master Data'!$J:$J,B89,'Master Data'!$L:$L,"Existing") -> 1 | J89: =COUNTIFS('Master Data'!$J:$J,B89,'Master Data'!$L:$L,"Titulaire EN") -> 0 | K89: =I89+J89 -> 1 | L89: =K89-H89 -> 0 | M89: =IF(L89<0,"Recruit "&ABS(L89),IF(L89>0,"Surplus "&L89,"OK")) -> OK
A90: 13 | B90: Certifié Espagnol | C90: Collège/Lycée | D90: =SUMIF($D$11:$D$74,B90,$V$11:$V$74) -> 29 | E90: =$D$5 -> 18 | G90: =IF(D90=0,"",D90/(E90+F90)) -> 1.6111111 | H90: =IF(G90="","",ROUNDUP(G90,0)) -> 2 | I90: =COUNTIFS('Master Data'!$J:$J,B90,'Master Data'!$L:$L,"Existing") -> 2 | J90: =COUNTIFS('Master Data'!$J:$J,B90,'Master Data'!$L:$L,"Titulaire EN") -> 1 | K90: =I90+J90 -> 3 | L90: =K90-H90 -> 1 | M90: =IF(L90<0,"Recruit "&ABS(L90),IF(L90>0,"Surplus "&L90,"OK")) -> Surplus 1
A91: 14 | B91: Certifié SVT | C91: Collège/Lycée | D91: =SUMIF($D$11:$D$74,B91,$V$11:$V$74) -> 49 | E91: =$D$5 -> 18 | G91: =IF(D91=0,"",D91/(E91+F91)) -> 2.7222222 | H91: =IF(G91="","",ROUNDUP(G91,0)) -> 3 | I91: =COUNTIFS('Master Data'!$J:$J,B91,'Master Data'!$L:$L,"Existing") -> 5 | J91: =COUNTIFS('Master Data'!$J:$J,B91,'Master Data'!$L:$L,"Titulaire EN") -> 1 | K91: =I91+J91 -> 6 | L91: =K91-H91 -> 3 | M91: =IF(L91<0,"Recruit "&ABS(L91),IF(L91>0,"Surplus "&L91,"OK")) -> Surplus 3
A92: 15 | B92: Certifié Physique-Chimie | C92: Collège/Lycée | D92: =SUMIF($D$11:$D$74,B92,$V$11:$V$74) -> 56.5 | E92: =$D$5 -> 18 | F92: 1 | G92: =IF(D92=0,"",D92/(E92+F92)) -> 2.9736842 | H92: =IF(G92="","",ROUNDUP(G92,0)) -> 3 | I92: =COUNTIFS('Master Data'!$J:$J,B92,'Master Data'!$L:$L,"Existing") -> 6 | J92: =COUNTIFS('Master Data'!$J:$J,B92,'Master Data'!$L:$L,"Titulaire EN") -> 1 | K92: =I92+J92 -> 7 | L92: =K92-H92 -> 4 | M92: =IF(L92<0,"Recruit "&ABS(L92),IF(L92>0,"Surplus "&L92,"OK")) -> Surplus 4
A93: 16 | B93: Certifié Technologie | C93: Collège/Lycée | D93: =SUMIF($D$11:$D$74,B93,$V$11:$V$74) -> 30 | E93: =$D$5 -> 18 | G93: =IF(D93=0,"",D93/(E93+F93)) -> 1.6666667 | H93: =IF(G93="","",ROUNDUP(G93,0)) -> 2 | I93: =COUNTIFS('Master Data'!$J:$J,B93,'Master Data'!$L:$L,"Existing") -> 2 | J93: =COUNTIFS('Master Data'!$J:$J,B93,'Master Data'!$L:$L,"Titulaire EN") -> 1 | K93: =I93+J93 -> 3 | L93: =K93-H93 -> 1 | M93: =IF(L93<0,"Recruit "&ABS(L93),IF(L93>0,"Surplus "&L93,"OK")) -> Surplus 1
A94: 17 | B94: Certifié Sciences (mutualisé) | C94: Collège/Lycée | D94: =SUMIF($D$11:$D$74,B94,$V$11:$V$74) -> 18 | E94: =$D$5 -> 18 | G94: =IF(D94=0,"",D94/(E94+F94)) -> 1 | H94: =IF(G94="","",ROUNDUP(G94,0)) -> 1 | I94: =COUNTIFS('Master Data'!$J:$J,B94,'Master Data'!$L:$L,"Existing") -> 0 | J94: =COUNTIFS('Master Data'!$J:$J,B94,'Master Data'!$L:$L,"Titulaire EN") -> 0 | K94: =I94+J94 -> 0 | L94: =K94-H94 -> -1 | M94: =IF(L94<0,"Recruit "&ABS(L94),IF(L94>0,"Surplus "&L94,"OK")) -> Recruit 1
A95: 18 | B95: Certifié SES | C95: Collège/Lycée | D95: =SUMIF($D$11:$D$74,B95,$V$11:$V$74) -> 35.5 | E95: =$D$5 -> 18 | G95: =IF(D95=0,"",D95/(E95+F95)) -> 1.9722222 | H95: =IF(G95="","",ROUNDUP(G95,0)) -> 2 | I95: =COUNTIFS('Master Data'!$J:$J,B95,'Master Data'!$L:$L,"Existing") -> 2 | J95: =COUNTIFS('Master Data'!$J:$J,B95,'Master Data'!$L:$L,"Titulaire EN") -> 1 | K95: =I95+J95 -> 3 | L95: =K95-H95 -> 1 | M95: =IF(L95<0,"Recruit "&ABS(L95),IF(L95>0,"Surplus "&L95,"OK")) -> Surplus 1
A96: 19 | B96: Certifié NSI/Maths | C96: Collège/Lycée | D96: =SUMIF($D$11:$D$74,B96,$V$11:$V$74) -> 10 | E96: =$D$5 -> 18 | G96: =IF(D96=0,"",D96/(E96+F96)) -> 0.55555556 | H96: =IF(G96="","",ROUNDUP(G96,0)) -> 1 | I96: =COUNTIFS('Master Data'!$J:$J,B96,'Master Data'!$L:$L,"Existing") -> 0 | J96: =COUNTIFS('Master Data'!$J:$J,B96,'Master Data'!$L:$L,"Titulaire EN") -> 0 | K96: =I96+J96 -> 0 | L96: =K96-H96 -> -1 | M96: =IF(L96<0,"Recruit "&ABS(L96),IF(L96>0,"Surplus "&L96,"OK")) -> Recruit 1
A97: 20 | B97: Certifié Arts Plastiques | C97: Collège/Lycée | D97: =SUMIF($D$11:$D$74,B97,$V$11:$V$74) -> 21 | E97: =$D$5 -> 18 | F97: 2 | G97: =IF(D97=0,"",D97/(E97+F97)) -> 1.05 | H97: =IF(G97="","",ROUNDUP(G97,0)) -> 2 | I97: =COUNTIFS('Master Data'!$J:$J,B97,'Master Data'!$L:$L,"Existing") -> 1 | J97: =COUNTIFS('Master Data'!$J:$J,B97,'Master Data'!$L:$L,"Titulaire EN") -> 0 | K97: =I97+J97 -> 1 | L97: =K97-H97 -> -1 | M97: =IF(L97<0,"Recruit "&ABS(L97),IF(L97>0,"Surplus "&L97,"OK")) -> Recruit 1
A98: 21 | B98: Certifié Éducation Musicale | C98: Collège/Lycée | D98: =SUMIF($D$11:$D$74,B98,$V$11:$V$74) -> 21 | E98: =$D$5 -> 18 | F98: 2 | G98: =IF(D98=0,"",D98/(E98+F98)) -> 1.05 | H98: =IF(G98="","",ROUNDUP(G98,0)) -> 2 | I98: =COUNTIFS('Master Data'!$J:$J,B98,'Master Data'!$L:$L,"Existing") -> 1 | J98: =COUNTIFS('Master Data'!$J:$J,B98,'Master Data'!$L:$L,"Titulaire EN") -> 0 | K98: =I98+J98 -> 1 | L98: =K98-H98 -> -1 | M98: =IF(L98<0,"Recruit "&ABS(L98),IF(L98>0,"Surplus "&L98,"OK")) -> Recruit 1
A99: 22 | B99: Certifié EPS | C99: Collège/Lycée | D99: =SUMIF($D$11:$D$74,B99,$V$11:$V$74) -> 97 | E99: =$D$5 -> 18 | F99: 2 | G99: =IF(D99=0,"",D99/(E99+F99)) -> 4.85 | H99: =IF(G99="","",ROUNDUP(G99,0)) -> 5 | I99: =COUNTIFS('Master Data'!$J:$J,B99,'Master Data'!$L:$L,"Existing") -> 6 | J99: =COUNTIFS('Master Data'!$J:$J,B99,'Master Data'!$L:$L,"Titulaire EN") -> 0 | K99: =I99+J99 -> 6 | L99: =K99-H99 -> 1 | M99: =IF(L99<0,"Recruit "&ABS(L99),IF(L99>0,"Surplus "&L99,"OK")) -> Surplus 1
B100: TOTAL | D100: =SUM(D78:D99) -> 2307.05 | G100: =SUM(G78:G99) -> 108.71053 | H100: =SUM(H78:H99) -> 116 | I100: =SUM(I78:I99) -> 110 | J100: =SUM(J78:J99) -> 21 | K100: =SUM(K78:K99) -> 131 | L100: =SUM(L78:L99) -> 15 | M100: =COUNTIF(L78:L99,"<0")&" to recruit" -> 7 to recruit

Sheet Curriculum_Detail
A1: Sort Order | B1: Cycle | C1: Stage | D1: Level | E1: Track | F1: Subject | G1: Hour Status | H1: Weekly Hours | I1: Annual Hours | J1: Planning Groups | K1: Delivered Hours/Wk | L1: Teacher Load Hrs/Wk | M1: Required FTE | N1: Avg Cost per FTE | O1: Est Annual Cost | P1: Source URL | Q1: Notes
A2: 300 | B2: Cycle 3 | C2: Collège | D2: 6e | E2: Core | F2: Français | G2: Official | H2: 4.5 | I2: 162 | J2: 6 | K2: 27 | L2: 18 | M2: 1.5 | N2: 0 | O2: 0 | P2: https://www.education.gouv.fr/les-horaires-par-cycle-au-college-9884
A3: 301 | B3: Cycle 3 | C3: Collège | D3: 6e | E3: Core | F3: Mathématiques | G3: Official | H3: 4.5 | I3: 162 | J3: 6 | K3: 27 | L3: 18 | M3: 1.5 | N3: 0 | O3: 0 | P3: https://www.education.gouv.fr/les-horaires-par-cycle-au-college-9884
A4: 302 | B4: Cycle 3 | C4: Collège | D4: 6e | E4: Core | F4: Histoire-géographie | G4: Derived from official grouped block | H4: 2.5 | I4: 90 | J4: 6 | K4: 15 | L4: 18 | M4: 0.83333333 | N4: 0 | O4: 0 | P4: https://www.education.gouv.fr/les-horaires-par-cycle-au-college-9884 | Q4: Derived from official 3 h grouped block 'Histoire-géographie + EMC', of which EMC is 30 minutes.
A5: 303 | B5: Cycle 3 | C5: Collège | D5: 6e | E5: Core | F5: Enseignement moral et civique | G5: Derived from official grouped block | H5: 0.5 | I5: 18 | J5: 6 | K5: 3 | L5: 18 | M5: 0.16666667 | N5: 0 | O5: 0 | P5: https://www.education.gouv.fr/les-horaires-par-cycle-au-college-9884 | Q5: Derived from official 3 h grouped block 'Histoire-géographie + EMC', of which EMC is 30 minutes.
A6: 304 | B6: Cycle 3 | C6: Collège | D6: 6e | E6: Core | F6: Langue vivante 1 | G6: Official | H6: 4 | I6: 144 | J6: 6 | K6: 24 | L6: 18 | M6: 1.3333333 | N6: 0 | O6: 0 | P6: https://www.education.gouv.fr/les-horaires-par-cycle-au-college-9884
A7: 305 | B7: Cycle 3 | C7: Collège | D7: 6e | E7: Core | F7: Sciences de la vie et de la Terre + Physique-chimie | G7: Official grouped sciences block | H7: 3 | I7: 108 | J7: 6 | K7: 18 | L7: 18 | M7: 1 | N7: 0 | O7: 0 | P7: https://www.education.gouv.fr/les-horaires-par-cycle-au-college-9884 | Q7: Current official 6e timetable groups the sciences block at 3 h/week.
A8: 306 | B8: Cycle 3 | C8: Collège | D8: 6e | E8: Core | F8: Éducation physique et sportive | G8: Official | H8: 4 | I8: 144 | J8: 6 | K8: 24 | L8: 18 | M8: 1.3333333 | N8: 0 | O8: 0 | P8: https://www.education.gouv.fr/les-horaires-par-cycle-au-college-9884
A9: 307 | B9: Cycle 3 | C9: Collège | D9: 6e | E9: Core | F9: Arts plastiques | G9: Official | H9: 1 | I9: 36 | J9: 6 | K9: 6 | L9: 18 | M9: 0.33333333 | N9: 0 | O9: 0 | P9: https://www.education.gouv.fr/les-horaires-par-cycle-au-college-9884
A10: 308 | B10: Cycle 3 | C10: Collège | D10: 6e | E10: Core | F10: Éducation musicale | G10: Official | H10: 1 | I10: 36 | J10: 6 | K10: 6 | L10: 18 | M10: 0.33333333 | N10: 0 | O10: 0 | P10: https://www.education.gouv.fr/les-horaires-par-cycle-au-college-9884
A11: 309 | B11: Cycle 3 | C11: Collège | D11: 6e | E11: Core | F11: Soutien / approfondissement en français ou mathématiques | G11: Official | H11: 1 | I11: 36 | J11: 6 | K11: 6 | L11: 18 | M11: 0.33333333 | N11: 0 | O11: 0 | P11: https://www.education.gouv.fr/les-horaires-par-cycle-au-college-9884
A12: 400 | B12: Cycle 4 | C12: Collège | D12: 5e | E12: Core | F12: Français | G12: Official | H12: 4.5 | I12: 162 | J12: 6 | K12: 27 | L12: 18 | M12: 1.5 | N12: 0 | O12: 0 | P12: https://www.education.gouv.fr/les-horaires-par-cycle-au-college-9884
A13: 401 | B13: Cycle 4 | C13: Collège | D13: 5e | E13: Core | F13: Mathématiques | G13: Official | H13: 3.5 | I13: 126 | J13: 6 | K13: 21 | L13: 18 | M13: 1.1666667 | N13: 0 | O13: 0 | P13: https://www.education.gouv.fr/les-horaires-par-cycle-au-college-9884
A14: 402 | B14: Cycle 4 | C14: Collège | D14: 5e | E14: Core | F14: Histoire-géographie | G14: Derived from official grouped block | H14: 2.5 | I14: 90 | J14: 6 | K14: 15 | L14: 18 | M14: 0.83333333 | N14: 0 | O14: 0 | P14: https://www.education.gouv.fr/les-horaires-par-cycle-au-college-9884 | Q14: Derived from official grouped block 'Histoire-géographie + EMC' with EMC = 30 minutes.
A15: 403 | B15: Cycle 4 | C15: Collège | D15: 5e | E15: Core | F15: Enseignement moral et civique | G15: Derived from official grouped block | H15: 0.5 | I15: 18 | J15: 6 | K15: 3 | L15: 18 | M15: 0.16666667 | N15: 0 | O15: 0 | P15: https://www.education.gouv.fr/les-horaires-par-cycle-au-college-9884 | Q15: Derived from official grouped block 'Histoire-géographie + EMC' with EMC = 30 minutes.
A16: 404 | B16: Cycle 4 | C16: Collège | D16: 5e | E16: Core | F16: Langue vivante 1 | G16: Official | H16: 3 | I16: 108 | J16: 6 | K16: 18 | L16: 18 | M16: 1 | N16: 0 | O16: 0 | P16: https://www.education.gouv.fr/les-horaires-par-cycle-au-college-9884
A17: 405 | B17: Cycle 4 | C17: Collège | D17: 5e | E17: Core | F17: Langue vivante 2 | G17: Official | H17: 2.5 | I17: 90 | J17: 6 | K17: 15 | L17: 18 | M17: 0.83333333 | N17: 0 | O17: 0 | P17: https://www.education.gouv.fr/les-horaires-par-cycle-au-college-9884
A18: 406 | B18: Cycle 4 | C18: Collège | D18: 5e | E18: Core | F18: Sciences de la vie et de la Terre | G18: Official | H18: 1.5 | I18: 54 | J18: 6 | K18: 9 | L18: 18 | M18: 0.5 | N18: 0 | O18: 0 | P18: https://www.education.gouv.fr/les-horaires-par-cycle-au-college-9884
A19: 407 | B19: Cycle 4 | C19: Collège | D19: 5e | E19: Core | F19: Physique-chimie | G19: Official | H19: 1.5 | I19: 54 | J19: 6 | K19: 9 | L19: 18 | M19: 0.5 | N19: 0 | O19: 0 | P19: https://www.education.gouv.fr/les-horaires-par-cycle-au-college-9884
A20: 408 | B20: Cycle 4 | C20: Collège | D20: 5e | E20: Core | F20: Technologie | G20: Official | H20: 1.5 | I20: 54 | J20: 6 | K20: 9 | L20: 18 | M20: 0.5 | N20: 0 | O20: 0 | P20: https://www.education.gouv.fr/les-horaires-par-cycle-au-college-9884
A21: 409 | B21: Cycle 4 | C21: Collège | D21: 5e | E21: Core | F21: Éducation physique et sportive | G21: Official | H21: 3 | I21: 108 | J21: 6 | K21: 18 | L21: 18 | M21: 1 | N21: 0 | O21: 0 | P21: https://www.education.gouv.fr/les-horaires-par-cycle-au-college-9884
A22: 410 | B22: Cycle 4 | C22: Collège | D22: 5e | E22: Core | F22: Arts plastiques | G22: Official | H22: 1 | I22: 36 | J22: 6 | K22: 6 | L22: 18 | M22: 0.33333333 | N22: 0 | O22: 0 | P22: https://www.education.gouv.fr/les-horaires-par-cycle-au-college-9884
A23: 411 | B23: Cycle 4 | C23: Collège | D23: 5e | E23: Core | F23: Éducation musicale | G23: Official | H23: 1 | I23: 36 | J23: 6 | K23: 6 | L23: 18 | M23: 0.33333333 | N23: 0 | O23: 0 | P23: https://www.education.gouv.fr/les-horaires-par-cycle-au-college-9884
A24: 412 | B24: Cycle 4 | C24: Collège | D24: 4e | E24: Core | F24: Français | G24: Official | H24: 4.5 | I24: 162 | J24: 5 | K24: 22.5 | L24: 18 | M24: 1.25 | N24: 0 | O24: 0 | P24: https://www.education.gouv.fr/les-horaires-par-cycle-au-college-9884
A25: 413 | B25: Cycle 4 | C25: Collège | D25: 4e | E25: Core | F25: Mathématiques | G25: Official | H25: 3.5 | I25: 126 | J25: 5 | K25: 17.5 | L25: 18 | M25: 0.97222222 | N25: 0 | O25: 0 | P25: https://www.education.gouv.fr/les-horaires-par-cycle-au-college-9884
A26: 414 | B26: Cycle 4 | C26: Collège | D26: 4e | E26: Core | F26: Histoire-géographie | G26: Derived from official grouped block | H26: 2.5 | I26: 90 | J26: 5 | K26: 12.5 | L26: 18 | M26: 0.69444444 | N26: 0 | O26: 0 | P26: https://www.education.gouv.fr/les-horaires-par-cycle-au-college-9884 | Q26: Derived from official grouped block 'Histoire-géographie + EMC' with EMC = 30 minutes.
A27: 415 | B27: Cycle 4 | C27: Collège | D27: 4e | E27: Core | F27: Enseignement moral et civique | G27: Derived from official grouped block | H27: 0.5 | I27: 18 | J27: 5 | K27: 2.5 | L27: 18 | M27: 0.13888889 | N27: 0 | O27: 0 | P27: https://www.education.gouv.fr/les-horaires-par-cycle-au-college-9884 | Q27: Derived from official grouped block 'Histoire-géographie + EMC' with EMC = 30 minutes.
A28: 416 | B28: Cycle 4 | C28: Collège | D28: 4e | E28: Core | F28: Langue vivante 1 | G28: Official | H28: 3 | I28: 108 | J28: 5 | K28: 15 | L28: 18 | M28: 0.83333333 | N28: 0 | O28: 0 | P28: https://www.education.gouv.fr/les-horaires-par-cycle-au-college-9884
A29: 417 | B29: Cycle 4 | C29: Collège | D29: 4e | E29: Core | F29: Langue vivante 2 | G29: Official | H29: 2.5 | I29: 90 | J29: 5 | K29: 12.5 | L29: 18 | M29: 0.69444444 | N29: 0 | O29: 0 | P29: https://www.education.gouv.fr/les-horaires-par-cycle-au-college-9884
A30: 418 | B30: Cycle 4 | C30: Collège | D30: 4e | E30: Core | F30: Sciences de la vie et de la Terre | G30: Official | H30: 1.5 | I30: 54 | J30: 5 | K30: 7.5 | L30: 18 | M30: 0.41666667 | N30: 0 | O30: 0 | P30: https://www.education.gouv.fr/les-horaires-par-cycle-au-college-9884
A31: 419 | B31: Cycle 4 | C31: Collège | D31: 4e | E31: Core | F31: Physique-chimie | G31: Official | H31: 1.5 | I31: 54 | J31: 5 | K31: 7.5 | L31: 18 | M31: 0.41666667 | N31: 0 | O31: 0 | P31: https://www.education.gouv.fr/les-horaires-par-cycle-au-college-9884
A32: 420 | B32: Cycle 4 | C32: Collège | D32: 4e | E32: Core | F32: Technologie | G32: Official | H32: 1.5 | I32: 54 | J32: 5 | K32: 7.5 | L32: 18 | M32: 0.41666667 | N32: 0 | O32: 0 | P32: https://www.education.gouv.fr/les-horaires-par-cycle-au-college-9884
A33: 421 | B33: Cycle 4 | C33: Collège | D33: 4e | E33: Core | F33: Éducation physique et sportive | G33: Official | H33: 3 | I33: 108 | J33: 5 | K33: 15 | L33: 18 | M33: 0.83333333 | N33: 0 | O33: 0 | P33: https://www.education.gouv.fr/les-horaires-par-cycle-au-college-9884
A34: 422 | B34: Cycle 4 | C34: Collège | D34: 4e | E34: Core | F34: Arts plastiques | G34: Official | H34: 1 | I34: 36 | J34: 5 | K34: 5 | L34: 18 | M34: 0.27777778 | N34: 0 | O34: 0 | P34: https://www.education.gouv.fr/les-horaires-par-cycle-au-college-9884
A35: 423 | B35: Cycle 4 | C35: Collège | D35: 4e | E35: Core | F35: Éducation musicale | G35: Official | H35: 1 | I35: 36 | J35: 5 | K35: 5 | L35: 18 | M35: 0.27777778 | N35: 0 | O35: 0 | P35: https://www.education.gouv.fr/les-horaires-par-cycle-au-college-9884
A36: 424 | B36: Cycle 4 | C36: Collège | D36: 3e | E36: Core | F36: Français | G36: Official | H36: 4 | I36: 144 | J36: 4 | K36: 16 | L36: 18 | M36: 0.88888889 | N36: 0 | O36: 0 | P36: https://www.education.gouv.fr/les-horaires-par-cycle-au-college-9884
A37: 425 | B37: Cycle 4 | C37: Collège | D37: 3e | E37: Core | F37: Mathématiques | G37: Official | H37: 3.5 | I37: 126 | J37: 4 | K37: 14 | L37: 18 | M37: 0.77777778 | N37: 0 | O37: 0 | P37: https://www.education.gouv.fr/les-horaires-par-cycle-au-college-9884
A38: 426 | B38: Cycle 4 | C38: Collège | D38: 3e | E38: Core | F38: Histoire-géographie | G38: Derived from official grouped block | H38: 3 | I38: 108 | J38: 4 | K38: 12 | L38: 18 | M38: 0.66666667 | N38: 0 | O38: 0 | P38: https://www.education.gouv.fr/les-horaires-par-cycle-au-college-9884 | Q38: Derived from official grouped block 'Histoire-géographie + EMC' with EMC = 30 minutes.
A39: 427 | B39: Cycle 4 | C39: Collège | D39: 3e | E39: Core | F39: Enseignement moral et civique | G39: Derived from official grouped block | H39: 0.5 | I39: 18 | J39: 4 | K39: 2 | L39: 18 | M39: 0.11111111 | N39: 0 | O39: 0 | P39: https://www.education.gouv.fr/les-horaires-par-cycle-au-college-9884 | Q39: Derived from official grouped block 'Histoire-géographie + EMC' with EMC = 30 minutes.
A40: 428 | B40: Cycle 4 | C40: Collège | D40: 3e | E40: Core | F40: Langue vivante 1 | G40: Official | H40: 3 | I40: 108 | J40: 4 | K40: 12 | L40: 18 | M40: 0.66666667 | N40: 0 | O40: 0 | P40: https://www.education.gouv.fr/les-horaires-par-cycle-au-college-9884
A41: 429 | B41: Cycle 4 | C41: Collège | D41: 3e | E41: Core | F41: Langue vivante 2 | G41: Official | H41: 2.5 | I41: 90 | J41: 4 | K41: 10 | L41: 18 | M41: 0.55555556 | N41: 0 | O41: 0 | P41: https://www.education.gouv.fr/les-horaires-par-cycle-au-college-9884
A42: 430 | B42: Cycle 4 | C42: Collège | D42: 3e | E42: Core | F42: Sciences de la vie et de la Terre | G42: Official | H42: 1.5 | I42: 54 | J42: 4 | K42: 6 | L42: 18 | M42: 0.33333333 | N42: 0 | O42: 0 | P42: https://www.education.gouv.fr/les-horaires-par-cycle-au-college-9884
A43: 431 | B43: Cycle 4 | C43: Collège | D43: 3e | E43: Core | F43: Physique-chimie | G43: Official | H43: 1.5 | I43: 54 | J43: 4 | K43: 6 | L43: 18 | M43: 0.33333333 | N43: 0 | O43: 0 | P43: https://www.education.gouv.fr/les-horaires-par-cycle-au-college-9884
A44: 432 | B44: Cycle 4 | C44: Collège | D44: 3e | E44: Core | F44: Technologie | G44: Official | H44: 1.5 | I44: 54 | J44: 4 | K44: 6 | L44: 18 | M44: 0.33333333 | N44: 0 | O44: 0 | P44: https://www.education.gouv.fr/les-horaires-par-cycle-au-college-9884
A45: 433 | B45: Cycle 4 | C45: Collège | D45: 3e | E45: Core | F45: Éducation physique et sportive | G45: Official | H45: 3 | I45: 108 | J45: 4 | K45: 12 | L45: 18 | M45: 0.66666667 | N45: 0 | O45: 0 | P45: https://www.education.gouv.fr/les-horaires-par-cycle-au-college-9884
A46: 434 | B46: Cycle 4 | C46: Collège | D46: 3e | E46: Core | F46: Arts plastiques | G46: Official | H46: 1 | I46: 36 | J46: 4 | K46: 4 | L46: 18 | M46: 0.22222222 | N46: 0 | O46: 0 | P46: https://www.education.gouv.fr/les-horaires-par-cycle-au-college-9884
A47: 435 | B47: Cycle 4 | C47: Collège | D47: 3e | E47: Core | F47: Éducation musicale | G47: Official | H47: 1 | I47: 36 | J47: 4 | K47: 4 | L47: 18 | M47: 0.22222222 | N47: 0 | O47: 0 | P47: https://www.education.gouv.fr/les-horaires-par-cycle-au-college-9884
A48: 500 | B48: Lycée | C48: Lycée | D48: Seconde | E48: Core | F48: Français | G48: Official | H48: 4 | I48: 144 | J48: 5 | K48: 20 | L48: 18 | M48: 1.1111111 | N48: 0 | O48: 0 | P48: https://eduscol.education.gouv.fr/5466/seconde-generale-et-technologique
A49: 501 | B49: Lycée | C49: Lycée | D49: Seconde | E49: Core | F49: Histoire-géographie | G49: Official | H49: 3 | I49: 108 | J49: 5 | K49: 15 | L49: 18 | M49: 0.83333333 | N49: 0 | O49: 0 | P49: https://eduscol.education.gouv.fr/5466/seconde-generale-et-technologique
A50: 502 | B50: Lycée | C50: Lycée | D50: Seconde | E50: Core | F50: LVA + LVB | G50: Official | H50: 5.5 | I50: 198 | J50: 5 | K50: 27.5 | L50: 18 | M50: 1.5277778 | N50: 0 | O50: 0 | P50: https://eduscol.education.gouv.fr/5466/seconde-generale-et-technologique
A51: 503 | B51: Lycée | C51: Lycée | D51: Seconde | E51: Core | F51: Sciences économiques et sociales | G51: Official | H51: 1.5 | I51: 54 | J51: 5 | K51: 7.5 | L51: 18 | M51: 0.41666667 | N51: 0 | O51: 0 | P51: https://eduscol.education.gouv.fr/5466/seconde-generale-et-technologique
... A60: 602 | B60: Lycée | C60: Lycée | D60: Première | E60: Core | F60: LVA + LVB | G60: Official | H60: 4.5 | I60: 162 | J60: 5 | K60: 22.5 | L60: 18 | M60: 1.25 | N60: 0 | O60: 0 | P60: https://eduscol.education.gouv.fr/5418/cycle-terminal-de-la-voie-generale
A61: 603 | B61: Lycée | C61: Lycée | D61: Première | E61: Core | F61: Enseignement scientifique | G61: Official | H61: 2 | I61: 72 | J61: 5 | K61: 10 | L61: 18 | M61: 0.55555556 | N61: 0 | O61: 0 | P61: https://eduscol.education.gouv.fr/5418/cycle-terminal-de-la-voie-generale | Q61: Base common hours for all Première générale students.
A62: 604 | B62: Lycée | C62: Lycée | D62: Première | E62: Conditional | F62: Mathématiques spécifiques intégrées à l'enseignement scientifique | G62: Conditional | H62: 1.5 | I62: 54 | J62: 0 | K62: 0 | L62: 18 | M62: 0 | N62: 0 | O62: 0 | P62: https://eduscol.education.gouv.fr/5790/programmes-et-ressources-en-enseignement-scientifique-voie-g | Q62: Only for students not choosing the math specialty.
A63: 605 | B63: Lycée | C63: Lycée | D63: Première | E63: Core | F63: Éducation physique et sportive | G63: Official | H63: 2 | I63: 72 | J63: 5 | K63: 10 | L63: 18 | M63: 0.55555556 | N63: 0 | O63: 0 | P63: https://eduscol.education.gouv.fr/5418/cycle-terminal-de-la-voie-generale
A64: 606 | B64: Lycée | C64: Lycée | D64: Première | E64: Core | F64: Enseignement moral et civique | G64: Official annual 18h converted to weekly equivalent | H64: 0.5 | I64: 18 | J64: 5 | K64: 2.5 | L64: 18 | M64: 0.13888889 | N64: 0 | O64: 0 | P64: https://eduscol.education.gouv.fr/5418/cycle-terminal-de-la-voie-generale | Q64: 18 annual hours expressed here as a 0.5 h weekly equivalent.
A65: 650 | B65: Lycée | C65: Lycée | D65: Terminale | E65: Core | F65: Philosophie | G65: Official | H65: 4 | I65: 144 | J65: 4 | K65: 16 | L65: 18 | M65: 0.88888889 | N65: 0 | O65: 0 | P65: https://eduscol.education.gouv.fr/5418/cycle-terminal-de-la-voie-generale
A66: 651 | B66: Lycée | C66: Lycée | D66: Terminale | E66: Core | F66: Histoire-géographie | G66: Official | H66: 3 | I66: 108 | J66: 4 | K66: 12 | L66: 18 | M66: 0.66666667 | N66: 0 | O66: 0 | P66: https://eduscol.education.gouv.fr/5418/cycle-terminal-de-la-voie-generale
A67: 652 | B67: Lycée | C67: Lycée | D67: Terminale | E67: Core | F67: LVA + LVB | G67: Official | H67: 4 | I67: 144 | J67: 4 | K67: 16 | L67: 18 | M67: 0.88888889 | N67: 0 | O67: 0 | P67: https://eduscol.education.gouv.fr/5418/cycle-terminal-de-la-voie-generale
A68: 653 | B68: Lycée | C68: Lycée | D68: Terminale | E68: Core | F68: Enseignement scientifique | G68: Official | H68: 2 | I68: 72 | J68: 4 | K68: 8 | L68: 18 | M68: 0.44444444 | N68: 0 | O68: 0 | P68: https://eduscol.education.gouv.fr/5418/cycle-terminal-de-la-voie-generale
A69: 654 | B69: Lycée | C69: Lycée | D69: Terminale | E69: Core | F69: Éducation physique et sportive | G69: Official | H69: 2 | I69: 72 | J69: 4 | K69: 8 | L69: 18 | M69: 0.44444444 | N69: 0 | O69: 0 | P69: https://eduscol.education.gouv.fr/5418/cycle-terminal-de-la-voie-generale
A70: 655 | B70: Lycée | C70: Lycée | D70: Terminale | E70: Core | F70: Enseignement moral et civique | G70: Official annual 18h converted to weekly equivalent | H70: 0.5 | I70: 18 | J70: 4 | K70: 2 | L70: 18 | M70: 0.11111111 | N70: 0 | O70: 0 | P70: https://eduscol.education.gouv.fr/5418/cycle-terminal-de-la-voie-generale | Q70: 18 annual hours expressed here as a 0.5 h weekly equivalent.
A71: 700 | B71: Lycée | C71: Lycée | D71: Première | E71: Specialty | F71: Arts | G71: Official specialty | H71: 4 | I71: 144 | J71: 0 | K71: 0 | L71: 18 | M71: 0 | N71: 0 | O71: 0 | P71: https://eduscol.education.gouv.fr/5418/cycle-terminal-de-la-voie-generale | Q71: National list; local school availability may differ. Students choose 3 specialties in Première.
A72: 701 | B72: Lycée | C72: Lycée | D72: Première | E72: Specialty | F72: Biologie-écologie | G72: Official specialty | H72: 4 | I72: 144 | J72: 0 | K72: 0 | L72: 18 | M72: 0 | N72: 0 | O72: 0 | P72: https://eduscol.education.gouv.fr/5418/cycle-terminal-de-la-voie-generale | Q72: Agricultural lycée specialty; usually not applicable in mainstream AEFE schools. Students choose 3 specialties in Première.
A73: 702 | B73: Lycée | C73: Lycée | D73: Première | E73: Specialty | F73: Éducation physique, pratiques et culture sportives | G73: Official specialty | H73: 4 | I73: 144 | J73: 0 | K73: 0 | L73: 18 | M73: 0 | N73: 0 | O73: 0 | P73: https://eduscol.education.gouv.fr/5418/cycle-terminal-de-la-voie-generale | Q73: School availability dependent. Students choose 3 specialties in Première.
A74: 703 | B74: Lycée | C74: Lycée | D74: Première | E74: Specialty | F74: Histoire-géographie, géopolitique et sciences politiques | G74: Official specialty | H74: 4 | I74: 144 | J74: 0 | K74: 0 | L74: 18 | M74: 0 | N74: 0 | O74: 0 | P74: https://eduscol.education.gouv.fr/5418/cycle-terminal-de-la-voie-generale | Q74: Students choose 3 specialties in Première.
A75: 704 | B75: Lycée | C75: Lycée | D75: Première | E75: Specialty | F75: Humanités, littérature et philosophie | G75: Official specialty | H75: 4 | I75: 144 | J75: 0 | K75: 0 | L75: 18 | M75: 0 | N75: 0 | O75: 0 | P75: https://eduscol.education.gouv.fr/5418/cycle-terminal-de-la-voie-generale | Q75: Students choose 3 specialties in Première.
A76: 705 | B76: Lycée | C76: Lycée | D76: Première | E76: Specialty | F76: Langues, littératures et cultures étrangères et régionales | G76: Official specialty | H76: 4 | I76: 144 | J76: 0 | K76: 0 | L76: 18 | M76: 0 | N76: 0 | O76: 0 | P76: https://eduscol.education.gouv.fr/5418/cycle-terminal-de-la-voie-generale | Q76: Students choose 3 specialties in Première.
A77: 706 | B77: Lycée | C77: Lycée | D77: Première | E77: Specialty | F77: Littératures et langues et cultures de l'Antiquité | G77: Official specialty | H77: 4 | I77: 144 | J77: 0 | K77: 0 | L77: 18 | M77: 0 | N77: 0 | O77: 0 | P77: https://eduscol.education.gouv.fr/5418/cycle-terminal-de-la-voie-generale | Q77: Students choose 3 specialties in Première.
A78: 707 | B78: Lycée | C78: Lycée | D78: Première | E78: Specialty | F78: Mathématiques | G78: Official specialty | H78: 4 | I78: 144 | J78: 0 | K78: 0 | L78: 18 | M78: 0 | N78: 0 | O78: 0 | P78: https://eduscol.education.gouv.fr/5418/cycle-terminal-de-la-voie-generale | Q78: Students choose 3 specialties in Première.
A79: 708 | B79: Lycée | C79: Lycée | D79: Première | E79: Specialty | F79: Numérique et sciences informatiques | G79: Official specialty | H79: 4 | I79: 144 | J79: 0 | K79: 0 | L79: 18 | M79: 0 | N79: 0 | O79: 0 | P79: https://eduscol.education.gouv.fr/5418/cycle-terminal-de-la-voie-generale | Q79: Students choose 3 specialties in Première.
A80: 709 | B80: Lycée | C80: Lycée | D80: Première | E80: Specialty | F80: Physique-chimie | G80: Official specialty | H80: 4 | I80: 144 | J80: 0 | K80: 0 | L80: 18 | M80: 0 | N80: 0 | O80: 0 | P80: https://eduscol.education.gouv.fr/5418/cycle-terminal-de-la-voie-generale | Q80: Students choose 3 specialties in Première.
A81: 710 | B81: Lycée | C81: Lycée | D81: Première | E81: Specialty | F81: Sciences de la vie et de la Terre | G81: Official specialty | H81: 4 | I81: 144 | J81: 0 | K81: 0 | L81: 18 | M81: 0 | N81: 0 | O81: 0 | P81: https://eduscol.education.gouv.fr/5418/cycle-terminal-de-la-voie-generale | Q81: Students choose 3 specialties in Première.
... A96: 725 | B96: Lycée | C96: Lycée | D96: Terminale | E96: Specialty | F96: Sciences économiques et sociales | G96: Official specialty | H96: 6 | I96: 216 | J96: 0 | K96: 0 | L96: 18 | M96: 0 | N96: 0 | O96: 0 | P96: https://eduscol.education.gouv.fr/5418/cycle-terminal-de-la-voie-generale | Q96: Students continue 2 specialties in Terminale.

Sheet Master Data
A1: EFIR — Staff Master Data FY2025-2026 | Y1: Calc Engine — Per-Employee Monthly Calculations (auto-generated)
A2: Active: 186 (160 Local + 26 AEFE) | Departed: 7 | Total rows: 193 | Currency: SAR | Updated: Feb 2026 payroll reconciliation | Y2: Do not edit — all formulas driven from Master Data columns & Assumptions
Y3: =DATE(Assumptions!$B$4,1,28) -> 46050 | AD3: =DATE(Assumptions!$B$4,2,28) -> 46081 | AI3: =DATE(Assumptions!$B$4,3,28) -> 46109 | AN3: =DATE(Assumptions!$B$4,4,28) -> 46140 | AS3: =DATE(Assumptions!$B$4,5,28) -> 46170 | AX3: =DATE(Assumptions!$B$4,6,28) -> 46201 | BC3: =DATE(Assumptions!$B$4,7,28) -> 46231 | BH3: =DATE(Assumptions!$B$4,8,28) -> 46262 | BM3: =DATE(Assumptions!$B$4,9,28) -> 46293 | BR3: =DATE(Assumptions!$B$4,10,28) -> 46323 | BW3: =DATE(Assumptions!$B$4,11,28) -> 46354 | CB3: =DATE(Assumptions!$B$4,12,28) -> 46384 | CG3: FY2026 Total
A4: # | B4: Last Name | C4: First Name | D4: Contract Type | E4: Contract Status | F4: Function / Role | G4: Department | H4: Subject / Discipline | I4: Teacher / Non-Teacher | J4: Teacher Profile | K4: Level | L4: Status | M4: Nationality | N4: Joining Date | O4: YoS | P4: Base Salary (SAR) | Q4: Housing (IL) | R4: Transport (IT) | S4: Resp. Premium | T4: HSA (10m) | U4: Monthly Gross (SAR) | V4: Hourly % | W4: Payment Method | X4: Increase | Y4: Eff. Base | Z4: Mth Gross | AA4: Cumul EoS | AB4: GOSI | AC4: Ajeer | AD4: Eff. Base | AE4: Mth Gross | AF4: Cumul EoS | AG4: GOSI | AH4: Ajeer | AI4: Eff. Base | AJ4: Mth Gross | AK4: Cumul EoS | AL4: GOSI | AM4: Ajeer | AN4: Eff. Base | AO4: Mth Gross | AP4: Cumul EoS | AQ4: GOSI | AR4: Ajeer | AS4: Eff. Base | AT4: Mth Gross | AU4: Cumul EoS | AV4: GOSI | AW4: Ajeer | AX4: Eff. Base | AY4: Mth Gross | AZ4: Cumul EoS | BA4: GOSI | BB4: Ajeer | BC4: Eff. Base | BD4: Mth Gross | BE4: Cumul EoS | BF4: GOSI | BG4: Ajeer | BH4: Eff. Base | BI4: Mth Gross | BJ4: Cumul EoS | BK4: GOSI | BL4: Ajeer | BM4: Eff. Base | BN4: Mth Gross | BO4: Cumul EoS | BP4: GOSI | BQ4: Ajeer | BR4: Eff. Base | BS4: Mth Gross | BT4: Cumul EoS | BU4: GOSI | BV4: Ajeer | BW4: Eff. Base | BX4: Mth Gross | BY4: Cumul EoS | BZ4: GOSI | CA4: Ajeer | CB4: Eff. Base | CC4: Mth Gross | CD4: Cumul EoS | CE4: GOSI | CF4: Ajeer | CG4: FY Base | CH4: FY Gross | CI4: FY EoS Prov | CJ4: FY GOSI | CK4: FY Ajeer
A5: 1 | B5: ABED | C5: Ghina | D5: Contrat Local | E5: Permanent | F5: Assistant(e) d'éducation | G5: Vie Scolaire & Support | H5: Vie scolaire | I5: Non-Teacher | K5: Vie Scolaire & Support | L5: Existing | M5: =IF(D5="Titulaire EN","",IF(OR(B5="AL OSSAIMI AL OTAIBI",B5="ALAMRI"),"Saudi","Non-Saudi")) -> Non-Saudi | N5: 45170 | O5: 3.3 | P5: 7400 | Q5: 2500 | R5: 500 | U5: 10400 | V5: 1 | W5: Liquide | X5: 200 | Y5: =IF(AND($D5="Contrat Local",$N5<>""),$P5*$V5,0) -> 7400 | Z5: =IF(Y5>0,Y5+($Q5+$R5+IF(ISNUMBER($S5),$S5,0)+IF(ISNUMBER($T5),$T5,0))*$V5,0) -> 10400 | AA5: =IF(AND(Z5>0,$N5<>""),IF((DATE(Assumptions!$B$4,1,28)-$N5)/365.25<=Assumptions!$B$20,(DATE(Assumptions!$B$4,1,28)-$N5)/365.25*Assumptions!$B$18*Z5,(Assumptions!$B$20*Assumptions!$B$18+((DATE(Assumptions!$B$4,1,28)-$N5)/365.25-Assumptions!$B$20)*Assumptions!$B$19)*Z5),0) -> 12528.405 | AB5: =IF(Y5>0,IF($M5="Saudi",MIN(Y5+$Q5*$V5,Assumptions!$B$14)*Assumptions!$B$12,MIN(Y5+$Q5*$V5,Assumptions!$B$14)*Assumptions!$B$13),0) -> 0 | AC5: =IF(AND(Y5>0,$M5="Non-Saudi"),Assumptions!$B$25,0) -> 910.41667 | AD5: =IF(AND($D5="Contrat Local",$N5<>""),$P5*$V5,0) -> 7400 | AE5: =IF(AD5>0,AD5+($Q5+$R5+IF(ISNUMBER($S5),$S5,0)+IF(ISNUMBER($T5),$T5,0))*$V5,0) -> 10400 | AF5: =IF(AND(AE5>0,$N5<>""),IF((DATE(Assumptions!$B$4,2,28)-$N5)/365.25<=Assumptions!$B$20,(DATE(Assumptions!$B$4,2,28)-$N5)/365.25*Assumptions!$B$18*AE5,(Assumptions!$B$20*Assumptions!$B$18+((DATE(Assumptions!$B$4,2,28)-$N5)/365.25-Assumptions!$B$20)*Assumptions!$B$19)*AE5),0) -> 12969.747 | AG5: =IF(AD5>0,IF($M5="Saudi",MIN(AD5+$Q5*$V5,Assumptions!$B$14)*Assumptions!$B$12,MIN(AD5+$Q5*$V5,Assumptions!$B$14)*Assumptions!$B$13),0) -> 0 | AH5: =IF(AND(AD5>0,$M5="Non-Saudi"),Assumptions!$B$25,0) -> 910.41667 | AI5: =IF(AND($D5="Contrat Local",$N5<>""),$P5*$V5,0) -> 7400 | AJ5: =IF(AI5>0,AI5+($Q5+$R5+IF(ISNUMBER($S5),$S5,0)+IF(ISNUMBER($T5),$T5,0))*$V5,0) -> 10400 | AK5: =IF(AND(AJ5>0,$N5<>""),IF((DATE(Assumptions!$B$4,3,28)-$N5)/365.25<=Assumptions!$B$20,(DATE(Assumptions!$B$4,3,28)-$N5)/365.25*Assumptions!$B$18*AJ5,(Assumptions!$B$20*Assumptions!$B$18+((DATE(Assumptions!$B$4,3,28)-$N5)/365.25-Assumptions!$B$20)*Assumptions!$B$19)*AJ5),0) -> 13368.378 | AL5: =IF(AI5>0,IF($M5="Saudi",MIN(AI5+$Q5*$V5,Assumptions!$B$14)*Assumptions!$B$12,MIN(AI5+$Q5*$V5,Assumptions!$B$14)*Assumptions!$B$13),0) -> 0 | AM5: =IF(AND(AI5>0,$M5="Non-Saudi"),Assumptions!$B$25,0) -> 910.41667 | AN5: =IF(AND($D5="Contrat Local",$N5<>""),$P5*$V5,0) -> 7400 | AO5: =IF(AN5>0,AN5+($Q5+$R5+IF(ISNUMBER($S5),$S5,0)+IF(ISNUMBER($T5),$T5,0))*$V5,0) -> 10400 | AP5: =IF(AND(AO5>0,$N5<>""),IF((DATE(Assumptions!$B$4,4,28)-$N5)/365.25<=Assumptions!$B$20,(DATE(Assumptions!$B$4,4,28)-$N5)/365.25*Assumptions!$B$18*AO5,(Assumptions!$B$20*Assumptions!$B$18+((DATE(Assumptions!$B$4,4,28)-$N5)/365.25-Assumptions!$B$20)*Assumptions!$B$19)*AO5),0) -> 13809.719 | AQ5: =IF(AN5>0,IF($M5="Saudi",MIN(AN5+$Q5*$V5,Assumptions!$B$14)*Assumptions!$B$12,MIN(AN5+$Q5*$V5,Assumptions!$B$14)*Assumptions!$B$13),0) -> 0 | AR5: =IF(AND(AN5>0,$M5="Non-Saudi"),Assumptions!$B$25,0) -> 910.41667 | AS5: =IF(AND($D5="Contrat Local",$N5<>""),$P5*$V5,0) -> 7400 | AT5: =IF(AS5>0,AS5+($Q5+$R5+IF(ISNUMBER($S5),$S5,0)+IF(ISNUMBER($T5),$T5,0))*$V5,0) -> 10400 | AU5: =IF(AND(AT5>0,$N5<>""),IF((DATE(Assumptions!$B$4,5,28)-$N5)/365.25<=Assumptions!$B$20,(DATE(Assumptions!$B$4,5,28)-$N5)/365.25*Assumptions!$B$18*AT5,(Assumptions!$B$20*Assumptions!$B$18+((DATE(Assumptions!$B$4,5,28)-$N5)/365.25-Assumptions!$B$20)*Assumptions!$B$19)*AT5),0) -> 14236.824 | AV5: =IF(AS5>0,IF($M5="Saudi",MIN(AS5+$Q5*$V5,Assumptions!$B$14)*Assumptions!$B$12,MIN(AS5+$Q5*$V5,Assumptions!$B$14)*Assumptions!$B$13),0) -> 0 | AW5: =IF(AND(AS5>0,$M5="Non-Saudi"),Assumptions!$B$25,0) -> 910.41667 | AX5: =IF(AND($D5="Contrat Local",$N5<>""),$P5*$V5,0) -> 7400 | AY5: =IF(AX5>0,AX5+($Q5+$R5+IF(ISNUMBER($S5),$S5,0)+IF(ISNUMBER($T5),$T5,0))*$V5,0) -> 10400 | AZ5: =IF(AND(AY5>0,$N5<>""),IF((DATE(Assumptions!$B$4,6,28)-$N5)/365.25<=Assumptions!$B$20,(DATE(Assumptions!$B$4,6,28)-$N5)/365.25*Assumptions!$B$18*AY5,(Assumptions!$B$20*Assumptions!$B$18+((DATE(Assumptions!$B$4,6,28)-$N5)/365.25-Assumptions!$B$20)*Assumptions!$B$19)*AY5),0) -> 14678.166 | BA5: =IF(AX5>0,IF($M5="Saudi",MIN(AX5+$Q5*$V5,Assumptions!$B$14)*Assumptions!$B$12,MIN(AX5+$Q5*$V5,Assumptions!$B$14)*Assumptions!$B$13),0) -> 0 | BB5: =IF(AND(AX5>0,$M5="Non-Saudi"),Assumptions!$B$25,0) -> 910.41667 | BC5: =IF(AND($D5="Contrat Local",$N5<>""),$P5*$V5,0) -> 7400 | BD5: =IF(BC5>0,BC5+($Q5+$R5+IF(ISNUMBER($S5),$S5,0)+IF(ISNUMBER($T5),$T5,0))*$V5,0) -> 10400 | BE5: =IF(AND(BD5>0,$N5<>""),IF((DATE(Assumptions!$B$4,7,28)-$N5)/365.25<=Assumptions!$B$20,(DATE(Assumptions!$B$4,7,28)-$N5)/365.25*Assumptions!$B$18*BD5,(Assumptions!$B$20*Assumptions!$B$18+((DATE(Assumptions!$B$4,7,28)-$N5)/365.25-Assumptions!$B$20)*Assumptions!$B$19)*BD5),0) -> 15105.27 | BF5: =IF(BC5>0,IF($M5="Saudi",MIN(BC5+$Q5*$V5,Assumptions!$B$14)*Assumptions!$B$12,MIN(BC5+$Q5*$V5,Assumptions!$B$14)*Assumptions!$B$13),0) -> 0 | BG5: =IF(AND(BC5>0,$M5="Non-Saudi"),Assumptions!$B$25,0) -> 910.41667 | BH5: =IF(AND($D5="Contrat Local",$N5<>""),$P5*$V5,0) -> 7400 | BI5: =IF(BH5>0,BH5+($Q5+$R5+IF(ISNUMBER($S5),$S5,0)+IF(ISNUMBER($T5),$T5,0))*$V5,0) -> 10400 | BJ5: =IF(AND(BI5>0,$N5<>""),IF((DATE(Assumptions!$B$4,8,28)-$N5)/365.25<=Assumptions!$B$20,(DATE(Assumptions!$B$4,8,28)-$N5)/365.25*Assumptions!$B$18*BI5,(Assumptions!$B$20*Assumptions!$B$18+((DATE(Assumptions!$B$4,8,28)-$N5)/365.25-Assumptions!$B$20)*Assumptions!$B$19)*BI5),0) -> 15546.612 | BK5: =IF(BH5>0,IF($M5="Saudi",MIN(BH5+$Q5*$V5,Assumptions!$B$14)*Assumptions!$B$12,MIN(BH5+$Q5*$V5,Assumptions!$B$14)*Assumptions!$B$13),0) -> 0 | BL5: =IF(AND(BH5>0,$M5="Non-Saudi"),Assumptions!$B$25,0) -> 910.41667 | BM5: =IF(AND($D5="Contrat Local",$N5<>""),IF(AND(9>=Assumptions!$B$5,ISNUMBER($X5),$N5<EDATE(Assumptions!$B$9,-Assumptions!$B$6*12)),($P5+$X5)*$V5,$P5*$V5),0) -> 7600 | BN5: =IF(BM5>0,BM5+($Q5+$R5+IF(ISNUMBER($S5),$S5,0)+IF(ISNUMBER($T5),$T5,0))*$V5,0) -> 10600 | BO5: =IF(AND(BN5>0,$N5<>""),IF((DATE(Assumptions!$B$4,9,28)-$N5)/365.25<=Assumptions!$B$20,(DATE(Assumptions!$B$4,9,28)-$N5)/365.25*Assumptions!$B$18*BN5,(Assumptions!$B$20*Assumptions!$B$18+((DATE(Assumptions!$B$4,9,28)-$N5)/365.25-Assumptions!$B$20)*Assumptions!$B$19)*BN5),0) -> 16295.414 | BP5: =IF(BM5>0,IF($M5="Saudi",MIN(BM5+$Q5*$V5,Assumptions!$B$14)*Assumptions!$B$12,MIN(BM5+$Q5*$V5,Assumptions!$B$14)*Assumptions!$B$13),0) -> 0 | BQ5: =IF(AND(BM5>0,$M5="Non-Saudi"),Assumptions!$B$25,0) -> 910.41667 | BR5: =IF(AND($D5="Contrat Local",$N5<>""),IF(AND(10>=Assumptions!$B$5,ISNUMBER($X5),$N5<EDATE(Assumptions!$B$9,-Assumptions!$B$6*12)),($P5+$X5)*$V5,$P5*$V5),0) -> 7600 | BS5: =IF(BR5>0,BR5+($Q5+$R5+IF(ISNUMBER($S5),$S5,0)+IF(ISNUMBER($T5),$T5,0))*$V5,0) -> 10600 | BT5: =IF(AND(BS5>0,$N5<>""),IF((DATE(Assumptions!$B$4,10,28)-$N5)/365.25<=Assumptions!$B$20,(DATE(Assumptions!$B$4,10,28)-$N5)/365.25*Assumptions!$B$18*BS5,(Assumptions!$B$20*Assumptions!$B$18+((DATE(Assumptions!$B$4,10,28)-$N5)/365.25-Assumptions!$B$20)*Assumptions!$B$19)*BS5),0) -> 16730.732 | BU5: =IF(BR5>0,IF($M5="Saudi",MIN(BR5+$Q5*$V5,Assumptions!$B$14)*Assumptions!$B$12,MIN(BR5+$Q5*$V5,Assumptions!$B$14)*Assumptions!$B$13),0) -> 0 | BV5: =IF(AND(BR5>0,$M5="Non-Saudi"),Assumptions!$B$25,0) -> 910.41667 | BW5: =IF(AND($D5="Contrat Local",$N5<>""),IF(AND(11>=Assumptions!$B$5,ISNUMBER($X5),$N5<EDATE(Assumptions!$B$9,-Assumptions!$B$6*12)),($P5+$X5)*$V5,$P5*$V5),0) -> 7600 | BX5: =IF(BW5>0,BW5+($Q5+$R5+IF(ISNUMBER($S5),$S5,0)+IF(ISNUMBER($T5),$T5,0))*$V5,0) -> 10600 | BY5: =IF(AND(BX5>0,$N5<>""),IF((DATE(Assumptions!$B$4,11,28)-$N5)/365.25<=Assumptions!$B$20,(DATE(Assumptions!$B$4,11,28)-$N5)/365.25*Assumptions!$B$18*BX5,(Assumptions!$B$20*Assumptions!$B$18+((DATE(Assumptions!$B$4,11,28)-$N5)/365.25-Assumptions!$B$20)*Assumptions!$B$19)*BX5),0) -> 17180.561 | BZ5: =IF(BW5>0,IF($M5="Saudi",MIN(BW5+$Q5*$V5,Assumptions!$B$14)*Assumptions!$B$12,MIN(BW5+$Q5*$V5,Assumptions!$B$14)*Assumptions!$B$13),0) -> 0 | CA5: =IF(AND(BW5>0,$M5="Non-Saudi"),Assumptions!$B$25,0) -> 910.41667 | CB5: =IF(AND($D5="Contrat Local",$N5<>""),IF(AND(12>=Assumptions!$B$5,ISNUMBER($X5),$N5<EDATE(Assumptions!$B$9,-Assumptions!$B$6*12)),($P5+$X5)*$V5,$P5*$V5),0) -> 7600 | CC5: =IF(CB5>0,CB5+($Q5+$R5+IF(ISNUMBER($S5),$S5,0)+IF(ISNUMBER($T5),$T5,0))*$V5,0) -> 10600 | CD5: =IF(AND(CC5>0,$N5<>""),IF((DATE(Assumptions!$B$4,12,28)-$N5)/365.25<=Assumptions!$B$20,(DATE(Assumptions!$B$4,12,28)-$N5)/365.25*Assumptions!$B$18*CC5,(Assumptions!$B$20*Assumptions!$B$18+((DATE(Assumptions!$B$4,12,28)-$N5)/365.25-Assumptions!$B$20)*Assumptions!$B$19)*CC5),0) -> 17615.88 | CE5: =IF(CB5>0,IF($M5="Saudi",MIN(CB5+$Q5*$V5,Assumptions!$B$14)*Assumptions!$B$12,MIN(CB5+$Q5*$V5,Assumptions!$B$14)*Assumptions!$B$13),0) -> 0 | CF5: =IF(AND(CB5>0,$M5="Non-Saudi"),Assumptions!$B$25,0) -> 910.41667 | CG5: =Y5+AD5+AI5+AN5+AS5+AX5+BC5+BH5+BM5+BR5+BW5+CB5 -> 89600 | CH5: =Z5+AE5+AJ5+AO5+AT5+AY5+BD5+BI5+BN5+BS5+BX5+CC5 -> 125600 | CI5: =CD5-IF(AND(Z5>0,$N5<>""),IF((DATE(Assumptions!$B$4-1,12,28)-$N5)/365.25<=Assumptions!$B$20,(DATE(Assumptions!$B$4-1,12,28)-$N5)/365.25*Assumptions!$B$18*Z5,(Assumptions!$B$20*Assumptions!$B$18+((DATE(Assumptions!$B$4-1,12,28)-$N5)/365.25-Assumptions!$B$20)*Assumptions!$B$19)*Z5),0) -> 5528.8159 | CJ5: =AB5+AG5+AL5+AQ5+AV5+BA5+BF5+BK5+BP5+BU5+BZ5+CE5 -> 0 | CK5: =AC5+AH5+AM5+AR5+AW5+BB5+BG5+BL5+BQ5+BV5+CA5+CF5 -> 10925
A6: 2 | B6: ABID | C6: Hamdi | D6: Contrat Local | E6: Permanent | F6: Assistant(e) d'éducation | G6: Vie Scolaire & Support | H6: Vie scolaire | I6: Non-Teacher | K6: Vie Scolaire & Support | L6: Existing | M6: =IF(D6="Titulaire EN","",IF(OR(B6="AL OSSAIMI AL OTAIBI",B6="ALAMRI"),"Saudi","Non-Saudi")) -> Non-Saudi | N6: 42614 | O6: 10.3 | P6: 9000 | Q6: 2500 | R6: 500 | U6: 12000 | V6: 1 | W6: Virement | X6: 400 | Y6: =IF(AND($D6="Contrat Local",$N6<>""),$P6*$V6,0) -> 9000 | Z6: =IF(Y6>0,Y6+($Q6+$R6+IF(ISNUMBER($S6),$S6,0)+IF(ISNUMBER($T6),$T6,0))*$V6,0) -> 12000 | AA6: =IF(AND(Z6>0,$N6<>""),IF((DATE(Assumptions!$B$4,1,28)-$N6)/365.25<=Assumptions!$B$20,(DATE(Assumptions!$B$4,1,28)-$N6)/365.25*Assumptions!$B$18*Z6,(Assumptions!$B$20*Assumptions!$B$18+((DATE(Assumptions!$B$4,1,28)-$N6)/365.25-Assumptions!$B$20)*Assumptions!$B$19)*Z6),0) -> 82887.064 | AB6: =IF(Y6>0,IF($M6="Saudi",MIN(Y6+$Q6*$V6,Assumptions!$B$14)*Assumptions!$B$12,MIN(Y6+$Q6*$V6,Assumptions!$B$14)*Assumptions!$B$13),0) -> 0 | AC6: =IF(AND(Y6>0,$M6="Non-Saudi"),Assumptions!$B$25,0) -> 910.41667 | AD6: =IF(AND($D6="Contrat Local",$N6<>""),$P6*$V6,0) -> 9000 | AE6: =IF(AD6>0,AD6+($Q6+$R6+IF(ISNUMBER($S6),$S6,0)+IF(ISNUMBER($T6),$T6,0))*$V6,0) -> 12000 | AF6: =IF(AND(AE6>0,$N6<>""),IF((DATE(Assumptions!$B$4,2,28)-$N6)/365.25<=Assumptions!$B$20,(DATE(Assumptions!$B$4,2,28)-$N6)/365.25*Assumptions!$B$18*AE6,(Assumptions!$B$20*Assumptions!$B$18+((DATE(Assumptions!$B$4,2,28)-$N6)/365.25-Assumptions!$B$20)*Assumptions!$B$19)*AE6),0) -> 83905.544 | AG6: =IF(AD6>0,IF($M6="Saudi",MIN(AD6+$Q6*$V6,Assumptions!$B$14)*Assumptions!$B$12,MIN(AD6+$Q6*$V6,Assumptions!$B$14)*Assumptions!$B$13),0) -> 0 | AH6: =IF(AND(AD6>0,$M6="Non-Saudi"),Assumptions!$B$25,0) -> 910.41667 | AI6: =IF(AND($D6="Contrat Local",$N6<>""),$P6*$V6,0) -> 9000 | AJ6: =IF(AI6>0,AI6+($Q6+$R6+IF(ISNUMBER($S6),$S6,0)+IF(ISNUMBER($T6),$T6,0))*$V6,0) -> 12000 | AK6: =IF(AND(AJ6>0,$N6<>""),IF((DATE(Assumptions!$B$4,3,28)-$N6)/365.25<=Assumptions!$B$20,(DATE(Assumptions!$B$4,3,28)-$N6)/365.25*Assumptions!$B$18*AJ6,(Assumptions!$B$20*Assumptions!$B$18+((DATE(Assumptions!$B$4,3,28)-$N6)/365.25-Assumptions!$B$20)*Assumptions!$B$19)*AJ6),0) -> 84825.462 | AL6: =IF(AI6>0,IF($M6="Saudi",MIN(AI6+$Q6*$V6,Assumptions!$B$14)*Assumptions!$B$12,MIN(AI6+$Q6*$V6,Assumptions!$B$14)*Assumptions!$B$13),0) -> 0 | AM6: =IF(AND(AI6>0,$M6="Non-Saudi"),Assumptions!$B$25,0) -> 910.41667 | AN6: =IF(AND($D6="Contrat Local",$N6<>""),$P6*$V6,0) -> 9000 | AO6: =IF(AN6>0,AN6+($Q6+$R6+IF(ISNUMBER($S6),$S6,0)+IF(ISNUMBER($T6),$T6,0))*$V6,0) -> 12000 | AP6: =IF(AND(AO6>0,$N6<>""),IF((DATE(Assumptions!$B$4,4,28)-$N6)/365.25<=Assumptions!$B$20,(DATE(Assumptions!$B$4,4,28)-$N6)/365.25*Assumptions!$B$18*AO6,(Assumptions!$B$20*Assumptions!$B$18+((DATE(Assumptions!$B$4,4,28)-$N6)/365.25-Assumptions!$B$20)*Assumptions!$B$19)*AO6),0) -> 85843.943 | AQ6: =IF(AN6>0,IF($M6="Saudi",MIN(AN6+$Q6*$V6,Assumptions!$B$14)*Assumptions!$B$12,MIN(AN6+$Q6*$V6,Assumptions!$B$14)*Assumptions!$B$13),0) -> 0 | AR6: =IF(AND(AN6>0,$M6="Non-Saudi"),Assumptions!$B$25,0) -> 910.41667 | AS6: =IF(AND($D6="Contrat Local",$N6<>""),$P6*$V6,0) -> 9000 | AT6: =IF(AS6>0,AS6+($Q6+$R6+IF(ISNUMBER($S6),$S6,0)+IF(ISNUMBER($T6),$T6,0))*$V6,0) -> 12000 | AU6: =IF(AND(AT6>0,$N6<>""),IF((DATE(Assumptions!$B$4,5,28)-$N6)/365.25<=Assumptions!$B$20,(DATE(Assumptions!$B$4,5,28)-$N6)/365.25*Assumptions!$B$18*AT6,(Assumptions!$B$20*Assumptions!$B$18+((DATE(Assumptions!$B$4,5,28)-$N6)/365.25-Assumptions!$B$20)*Assumptions!$B$19)*AT6),0) -> 86829.569 | AV6: =IF(AS6>0,IF($M6="Saudi",MIN(AS6+$Q6*$V6,Assumptions!$B$14)*Assumptions!$B$12,MIN(AS6+$Q6*$V6,Assumptions!$B$14)*Assumptions!$B$13),0) -> 0 | AW6: =IF(AND(AS6>0,$M6="Non-Saudi"),Assumptions!$B$25,0) -> 910.41667 | AX6: =IF(AND($D6="Contrat Local",$N6<>""),$P6*$V6,0) -> 9000 | AY6: =IF(AX6>0,AX6+($Q6+$R6+IF(ISNUMBER($S6),$S6,0)+IF(ISNUMBER($T6),$T6,0))*$V6,0) -> 12000 | AZ6: =IF(AND(AY6>0,$N6<>""),IF((DATE(Assumptions!$B$4,6,28)-$N6)/365.25<=Assumptions!$B$20,(DATE(Assumptions!$B$4,6,28)-$N6)/365.25*Assumptions!$B$18*AY6,(Assumptions!$B$20*Assumptions!$B$18+((DATE(Assumptions!$B$4,6,28)-$N6)/365.25-Assumptions!$B$20)*Assumptions!$B$19)*AY6),0) -> 87848.049 | BA6: =IF(AX6>0,IF($M6="Saudi",MIN(AX6+$Q6*$V6,Assumptions!$B$14)*Assumptions!$B$12,MIN(AX6+$Q6*$V6,Assumptions!$B$14)*Assumptions!$B$13),0) -> 0 | BB6: =IF(AND(AX6>0,$M6="Non-Saudi"),Assumptions!$B$25,0) -> 910.41667 | BC6: =IF(AND($D6="Contrat Local",$N6<>""),$P6*$V6,0) -> 9000 | BD6: =IF(BC6>0,BC6+($Q6+$R6+IF(ISNUMBER($S6),$S6,0)+IF(ISNUMBER($T6),$T6,0))*$V6,0) -> 12000 | BE6: =IF(AND(BD6>0,$N6<>""),IF((DATE(Assumptions!$B$4,7,28)-$N6)/365.25<=Assumptions!$B$20,(DATE(Assumptions!$B$4,7,28)-$N6)/365.25*Assumptions!$B$18*BD6,(Assumptions!$B$20*Assumptions!$B$18+((DATE(Assumptions!$B$4,7,28)-$N6)/365.25-Assumptions!$B$20)*Assumptions!$B$19)*BD6),0) -> 88833.676 | BF6: =IF(BC6>0,IF($M6="Saudi",MIN(BC6+$Q6*$V6,Assumptions!$B$14)*Assumptions!$B$12,MIN(BC6+$Q6*$V6,Assumptions!$B$14)*Assumptions!$B$13),0) -> 0 | BG6: =IF(AND(BC6>0,$M6="Non-Saudi"),Assumptions!$B$25,0) -> 910.41667 | BH6: =IF(AND($D6="Contrat Local",$N6<>""),$P6*$V6,0) -> 9000 | BI6: =IF(BH6>0,BH6+($Q6+$R6+IF(ISNUMBER($S6),$S6,0)+IF(ISNUMBER($T6),$T6,0))*$V6,0) -> 12000 | BJ6: =IF(AND(BI6>0,$N6<>""),IF((DATE(Assumptions!$B$4,8,28)-$N6)/365.25<=Assumptions!$B$20,(DATE(Assumptions!$B$4,8,28)-$N6)/365.25*Assumptions!$B$18*BI6,(Assumptions!$B$20*Assumptions!$B$18+((DATE(Assumptions!$B$4,8,28)-$N6)/365.25-Assumptions!$B$20)*Assumptions!$B$19)*BI6),0) -> 89852.156 | BK6: =IF(BH6>0,IF($M6="Saudi",MIN(BH6+$Q6*$V6,Assumptions!$B$14)*Assumptions!$B$12,MIN(BH6+$Q6*$V6,Assumptions!$B$14)*Assumptions!$B$13),0) -> 0 | BL6: =IF(AND(BH6>0,$M6="Non-Saudi"),Assumptions!$B$25,0) -> 910.41667 | BM6: =IF(AND($D6="Contrat Local",$N6<>""),IF(AND(9>=Assumptions!$B$5,ISNUMBER($X6),$N6<EDATE(Assumptions!$B$9,-Assumptions!$B$6*12)),($P6+$X6)*$V6,$P6*$V6),0) -> 9400 | BN6: =IF(BM6>0,BM6+($Q6+$R6+IF(ISNUMBER($S6),$S6,0)+IF(ISNUMBER($T6),$T6,0))*$V6,0) -> 12400 | BO6: =IF(AND(BN6>0,$N6<>""),IF((DATE(Assumptions!$B$4,9,28)-$N6)/365.25<=Assumptions!$B$20,(DATE(Assumptions!$B$4,9,28)-$N6)/365.25*Assumptions!$B$18*BN6,(Assumptions!$B$20*Assumptions!$B$18+((DATE(Assumptions!$B$4,9,28)-$N6)/365.25-Assumptions!$B$20)*Assumptions!$B$19)*BN6),0) -> 93899.658 | BP6: =IF(BM6>0,IF($M6="Saudi",MIN(BM6+$Q6*$V6,Assumptions!$B$14)*Assumptions!$B$12,MIN(BM6+$Q6*$V6,Assumptions!$B$14)*Assumptions!$B$13),0) -> 0 | BQ6: =IF(AND(BM6>0,$M6="Non-Saudi"),Assumptions!$B$25,0) -> 910.41667 | BR6: =IF(AND($D6="Contrat Local",$N6<>""),IF(AND(10>=Assumptions!$B$5,ISNUMBER($X6),$N6<EDATE(Assumptions!$B$9,-Assumptions!$B$6*12)),($P6+$X6)*$V6,$P6*$V6),0) -> 9400 | BS6: =IF(BR6>0,BR6+($Q6+$R6+IF(ISNUMBER($S6),$S6,0)+IF(ISNUMBER($T6),$T6,0))*$V6,0) -> 12400 | BT6: =IF(AND(BS6>0,$N6<>""),IF((DATE(Assumptions!$B$4,10,28)-$N6)/365.25<=Assumptions!$B$20,(DATE(Assumptions!$B$4,10,28)-$N6)/365.25*Assumptions!$B$18*BS6,(Assumptions!$B$20*Assumptions!$B$18+((DATE(Assumptions!$B$4,10,28)-$N6)/365.25-Assumptions!$B$20)*Assumptions!$B$19)*BS6),0) -> 94918.138 | BU6: =IF(BR6>0,IF($M6="Saudi",MIN(BR6+$Q6*$V6,Assumptions!$B$14)*Assumptions!$B$12,MIN(BR6+$Q6*$V6,Assumptions!$B$14)*Assumptions!$B$13),0) -> 0 | BV6: =IF(AND(BR6>0,$M6="Non-Saudi"),Assumptions!$B$25,0) -> 910.41667 | BW6: =IF(AND($D6="Contrat Local",$N6<>""),IF(AND(11>=Assumptions!$B$5,ISNUMBER($X6),$N6<EDATE(Assumptions!$B$9,-Assumptions!$B$6*12)),($P6+$X6)*$V6,$P6*$V6),0) -> 9400 | BX6: =IF(BW6>0,BW6+($Q6+$R6+IF(ISNUMBER($S6),$S6,0)+IF(ISNUMBER($T6),$T6,0))*$V6,0) -> 12400 | BY6: =IF(AND(BX6>0,$N6<>""),IF((DATE(Assumptions!$B$4,11,28)-$N6)/365.25<=Assumptions!$B$20,(DATE(Assumptions!$B$4,11,28)-$N6)/365.25*Assumptions!$B$18*BX6,(Assumptions!$B$20*Assumptions!$B$18+((DATE(Assumptions!$B$4,11,28)-$N6)/365.25-Assumptions!$B$20)*Assumptions!$B$19)*BX6),0) -> 95970.568 | BZ6: =IF(BW6>0,IF($M6="Saudi",MIN(BW6+$Q6*$V6,Assumptions!$B$14)*Assumptions!$B$12,MIN(BW6+$Q6*$V6,Assumptions!$B$14)*Assumptions!$B$13),0) -> 0 | CA6: =IF(AND(BW6>0,$M6="Non-Saudi"),Assumptions!$B$25,0) -> 910.41667 | CB6: =IF(AND($D6="Contrat Local",$N6<>""),IF(AND(12>=Assumptions!$B$5,ISNUMBER($X6),$N6<EDATE(Assumptions!$B$9,-Assumptions!$B$6*12)),($P6+$X6)*$V6,$P6*$V6),0) -> 9400 | CC6: =IF(CB6>0,CB6+($Q6+$R6+IF(ISNUMBER($S6),$S6,0)+IF(ISNUMBER($T6),$T6,0))*$V6,0) -> 12400 | CD6: =IF(AND(CC6>0,$N6<>""),IF((DATE(Assumptions!$B$4,12,28)-$N6)/365.25<=Assumptions!$B$20,(DATE(Assumptions!$B$4,12,28)-$N6)/365.25*Assumptions!$B$18*CC6,(Assumptions!$B$20*Assumptions!$B$18+((DATE(Assumptions!$B$4,12,28)-$N6)/365.25-Assumptions!$B$20)*Assumptions!$B$19)*CC6),0) -> 96989.049 | CE6: =IF(CB6>0,IF($M6="Saudi",MIN(CB6+$Q6*$V6,Assumptions!$B$14)*Assumptions!$B$12,MIN(CB6+$Q6*$V6,Assumptions!$B$14)*Assumptions!$B$13),0) -> 0 | CF6: =IF(AND(CB6>0,$M6="Non-Saudi"),Assumptions!$B$25,0) -> 910.41667 | CG6: =Y6+AD6+AI6+AN6+AS6+AX6+BC6+BH6+BM6+BR6+BW6+CB6 -> 109600 | CH6: =Z6+AE6+AJ6+AO6+AT6+AY6+BD6+BI6+BN6+BS6+BX6+CC6 -> 145600 | CI6: =CD6-IF(AND(Z6>0,$N6<>""),IF((DATE(Assumptions!$B$4-1,12,28)-$N6)/365.25<=Assumptions!$B$20,(DATE(Assumptions!$B$4-1,12,28)-$N6)/365.25*Assumptions!$B$18*Z6,(Assumptions!$B$20*Assumptions!$B$18+((DATE(Assumptions!$B$4-1,12,28)-$N6)/365.25-Assumptions!$B$20)*Assumptions!$B$19)*Z6),0) -> 15120.465 | CJ6: =AB6+AG6+AL6+AQ6+AV6+BA6+BF6+BK6+BP6+BU6+BZ6+CE6 -> 0 | CK6: =AC6+AH6+AM6+AR6+AW6+BB6+BG6+BL6+BQ6+BV6+CA6+CF6 -> 10925
A7: 3 | B7: ABOU RJEILI | C7: Christina | D7: Contrat Local | E7: Permanent | F7: Assistant(e) d'éducation | G7: Vie Scolaire & Support | H7: Vie scolaire | I7: Non-Teacher | K7: Vie Scolaire & Support | L7: Existing | M7: =IF(D7="Titulaire EN","",IF(OR(B7="AL OSSAIMI AL OTAIBI",B7="ALAMRI"),"Saudi","Non-Saudi")) -> Non-Saudi | N7: 45536 | O7: 2.3 | P7: 7200 | Q7: 2500 | R7: 500 | U7: 10200 | V7: 1 | W7: Virement | X7: 200 | Y7: =IF(AND($D7="Contrat Local",$N7<>""),$P7*$V7,0) -> 7200 | Z7: =IF(Y7>0,Y7+($Q7+$R7+IF(ISNUMBER($S7),$S7,0)+IF(ISNUMBER($T7),$T7,0))*$V7,0) -> 10200 | AA7: =IF(AND(Z7>0,$N7<>""),IF((DATE(Assumptions!$B$4,1,28)-$N7)/365.25<=Assumptions!$B$20,(DATE(Assumptions!$B$4,1,28)-$N7)/365.25*Assumptions!$B$18*Z7,(Assumptions!$B$20*Assumptions!$B$18+((DATE(Assumptions!$B$4,1,28)-$N7)/365.25-Assumptions!$B$20)*Assumptions!$B$19)*Z7),0) -> 7177.0021 | AB7: =IF(Y7>0,IF($M7="Saudi",MIN(Y7+$Q7*$V7,Assumptions!$B$14)*Assumptions!$B$12,MIN(Y7+$Q7*$V7,Assumptions!$B$14)*Assumptions!$B$13),0) -> 0 | AC7: =IF(AND(Y7>0,$M7="Non-Saudi"),Assumptions!$B$25,0) -> 910.41667 | AD7: =IF(AND($D7="Contrat Local",$N7<>""),$P7*$V7,0) -> 7200 | AE7: =IF(AD7>0,AD7+($Q7+$R7+IF(ISNUMBER($S7),$S7,0)+IF(ISNUMBER($T7),$T7,0))*$V7,0) -> 10200 | AF7: =IF(AND(AE7>0,$N7<>""),IF((DATE(Assumptions!$B$4,2,28)-$N7)/365.25<=Assumptions!$B$20,(DATE(Assumptions!$B$4,2,28)-$N7)/365.25*Assumptions!$B$18*AE7,(Assumptions!$B$20*Assumptions!$B$18+((DATE(Assumptions!$B$4,2,28)-$N7)/365.25-Assumptions!$B$20)*Assumptions!$B$19)*AE7),0) -> 7609.8563 | AG7: =IF(AD7>0,IF($M7="Saudi",MIN(AD7+$Q7*$V7,Assumptions!$B$14)*Assumptions!$B$12,MIN(AD7+$Q7*$V7,Assumptions!$B$14)*Assumptions!$B$13),0) -> 0 | AH7: =IF(AND(AD7>0,$M7="Non-Saudi"),Assumptions!$B$25,0) -> 910.41667 | AI7: =IF(AND($D7="Contrat Local",$N7<>""),$P7*$V7,0) -> 7200 | AJ7: =IF(AI7>0,AI7+($Q7+$R7+IF(ISNUMBER($S7),$S7,0)+IF(ISNUMBER($T7),$T7,0))*$V7,0) -> 10200 | AK7: =IF(AND(AJ7>0,$N7<>""),IF((DATE(Assumptions!$B$4,3,28)-$N7)/365.25<=Assumptions!$B$20,(DATE(Assumptions!$B$4,3,28)-$N7)/365.25*Assumptions!$B$18*AJ7,(Assumptions!$B$20*Assumptions!$B$18+((DATE(Assumptions!$B$4,3,28)-$N7)/365.25-Assumptions!$B$20)*Assumptions!$B$19)*AJ7),0) -> 8000.8214 | AL7: =IF(AI7>0,IF($M7="Saudi",MIN(AI7+$Q7*$V7,Assumptions!$B$14)*Assumptions!$B$12,MIN(AI7+$Q7*$V7,Assumptions!$B$14)*Assumptions!$B$13),0) -> 0 | AM7: =IF(AND(AI7>0,$M7="Non-Saudi"),Assumptions!$B$25,0) -> 910.41667 | AN7: =IF(AND($D7="Contrat Local",$N7<>""),$P7*$V7,0) -> 7200 | AO7: =IF(AN7>0,AN7+($Q7+$R7+IF(ISNUMBER($S7),$S7,0)+IF(ISNUMBER($T7),$T7,0))*$V7,0) -> 10200 | AP7: =IF(AND(AO7>0,$N7<>""),IF((DATE(Assumptions!$B$4,4,28)-$N7)/365.25<=Assumptions!$B$20,(DATE(Assumptions!$B$4,4,28)-$N7)/365.25*Assumptions!$B$18*AO7,(Assumptions!$B$20*Assumptions!$B$18+((DATE(Assumptions!$B$4,4,28)-$N7)/365.25-Assumptions!$B$20)*Assumptions!$B$19)*AO7),0) -> 8433.6756 | AQ7: =IF(AN7>0,IF($M7="Saudi",MIN(AN7+$Q7*$V7,Assumptions!$B$14)*Assumptions!$B$12,MIN(AN7+$Q7*$V7,Assumptions!$B$14)*Assumptions!$B$13),0) -> 0 | AR7: =IF(AND(AN7>0,$M7="Non-Saudi"),Assumptions!$B$25,0) -> 910.41667 | AS7: =IF(AND($D7="Contrat Local",$N7<>""),$P7*$V7,0) -> 7200 | AT7: =IF(AS7>0,AS7+($Q7+$R7+IF(ISNUMBER($S7),$S7,0)+IF(ISNUMBER($T7),$T7,0))*$V7,0) -> 10200 | AU7: =IF(AND(AT7>0,$N7<>""),IF((DATE(Assumptions!$B$4,5,28)-$N7)/365.25<=Assumptions!$B$20,(DATE(Assumptions!$B$4,5,28)-$N7)/365.25*Assumptions!$B$18*AT7,(Assumptions!$B$20*Assumptions!$B$18+((DATE(Assumptions!$B$4,5,28)-$N7)/365.25-Assumptions!$B$20)*Assumptions!$B$19)*AT7),0) -> 8852.5667 | AV7: =IF(AS7>0,IF($M7="Saudi",MIN(AS7+$Q7*$V7,Assumptions!$B$14)*Assumptions!$B$12,MIN(AS7+$Q7*$V7,Assumptions!$B$14)*Assumptions!$B$13),0) -> 0 | AW7: =IF(AND(AS7>0,$M7="Non-Saudi"),Assumptions!$B$25,0) -> 910.41667 | AX7: =IF(AND($D7="Contrat Local",$N7<>""),$P7*$V7,0) -> 7200 | AY7: =IF(AX7>0,AX7+($Q7+$R7+IF(ISNUMBER($S7),$S7,0)+IF(ISNUMBER($T7),$T7,0))*$V7,0) -> 10200 | AZ7: =IF(AND(AY7>0,$N7<>""),IF((DATE(Assumptions!$B$4,6,28)-$N7)/365.25<=Assumptions!$B$20,(DATE(Assumptions!$B$4,6,28)-$N7)/365.25*Assumptions!$B$18*AY7,(Assumptions!$B$20*Assumptions!$B$18+((DATE(Assumptions!$B$4,6,28)-$N7)/365.25-Assumptions!$B$20)*Assumptions!$B$19)*AY7),0) -> 9285.4209 | BA7: =IF(AX7>0,IF($M7="Saudi",MIN(AX7+$Q7*$V7,Assumptions!$B$14)*Assumptions!$B$12,MIN(AX7+$Q7*$V7,Assumptions!$B$14)*Assumptions!$B$13),0) -> 0 | BB7: =IF(AND(AX7>0,$M7="Non-Saudi"),Assumptions!$B$25,0) -> 910.41667 | BC7: =IF(AND($D7="Contrat Local",$N7<>""),$P7*$V7,0) -> 7200 | BD7: =IF(BC7>0,BC7+($Q7+$R7+IF(ISNUMBER($S7),$S7,0)+IF(ISNUMBER($T7),$T7,0))*$V7,0) -> 10200 | BE7: =IF(AND(BD7>0,$N7<>""),IF((DATE(Assumptions!$B$4,7,28)-$N7)/365.25<=Assumptions!$B$20,(DATE(Assumptions!$B$4,7,28)-$N7)/365.25*Assumptions!$B$18*BD7,(Assumptions!$B$20*Assumptions!$B$18+((DATE(Assumptions!$B$4,7,28)-$N7)/365.25-Assumptions!$B$20)*Assumptions!$B$19)*BD7),0) -> 9704.3121 | BF7: =IF(BC7>0,IF($M7="Saudi",MIN(BC7+$Q7*$V7,Assumptions!$B$14)*Assumptions!$B$12,MIN(BC7+$Q7*$V7,Assumptions!$B$14)*Assumptions!$B$13),0) -> 0 | BG7: =IF(AND(BC7>0,$M7="Non-Saudi"),Assumptions!$B$25,0) -> 910.41667 | BH7: =IF(AND($D7="Contrat Local",$N7<>""),$P7*$V7,0) -> 7200 | BI7: =IF(BH7>0,BH7+($Q7+$R7+IF(ISNUMBER($S7),$S7,0)+IF(ISNUMBER($T7),$T7,0))*$V7,0) -> 10200 | BJ7: =IF(AND(BI7>0,$N7<>""),IF((DATE(Assumptions!$B$4,8,28)-$N7)/365.25<=Assumptions!$B$20,(DATE(Assumptions!$B$4,8,28)-$N7)/365.25*Assumptions!$B$18*BI7,(Assumptions!$B$20*Assumptions!$B$18+((DATE(Assumptions!$B$4,8,28)-$N7)/365.25-Assumptions!$B$20)*Assumptions!$B$19)*BI7),0) -> 10137.166 | BK7: =IF(BH7>0,IF($M7="Saudi",MIN(BH7+$Q7*$V7,Assumptions!$B$14)*Assumptions!$B$12,MIN(BH7+$Q7*$V7,Assumptions!$B$14)*Assumptions!$B$13),0) -> 0 | BL7: =IF(AND(BH7>0,$M7="Non-Saudi"),Assumptions!$B$25,0) -> 910.41667 | BM7: =IF(AND($D7="Contrat Local",$N7<>""),IF(AND(9>=Assumptions!$B$5,ISNUMBER($X7),$N7<EDATE(Assumptions!$B$9,-Assumptions!$B$6*12)),($P7+$X7)*$V7,$P7*$V7),0) -> 7400 | BN7: =IF(BM7>0,BM7+($Q7+$R7+IF(ISNUMBER($S7),$S7,0)+IF(ISNUMBER($T7),$T7,0))*$V7,0) -> 10400 | BO7: =IF(AND(BN7>0,$N7<>""),IF((DATE(Assumptions!$B$4,9,28)-$N7)/365.25<=Assumptions!$B$20,(DATE(Assumptions!$B$4,9,28)-$N7)/365.25*Assumptions!$B$18*BN7,(Assumptions!$B$20*Assumptions!$B$18+((DATE(Assumptions!$B$4,9,28)-$N7)/365.25-Assumptions!$B$20)*Assumptions!$B$19)*BN7),0) -> 10777.276 | BP7: =IF(BM7>0,IF($M7="Saudi",MIN(BM7+$Q7*$V7,Assumptions!$B$14)*Assumptions!$B$12,MIN(BM7+$Q7*$V7,Assumptions!$B$14)*Assumptions!$B$13),0) -> 0 | BQ7: =IF(AND(BM7>0,$M7="Non-Saudi"),Assumptions!$B$25,0) -> 910.41667 | BR7: =IF(AND($D7="Contrat Local",$N7<>""),IF(AND(10>=Assumptions!$B$5,ISNUMBER($X7),$N7<EDATE(Assumptions!$B$9,-Assumptions!$B$6*12)),($P7+$X7)*$V7,$P7*$V7),0) -> 7400 | BS7: =IF(BR7>0,BR7+($Q7+$R7+IF(ISNUMBER($S7),$S7,0)+IF(ISNUMBER($T7),$T7,0))*$V7,0) -> 10400 | BT7: =IF(AND(BS7>0,$N7<>""),IF((DATE(Assumptions!$B$4,10,28)-$N7)/365.25<=Assumptions!$B$20,(DATE(Assumptions!$B$4,10,28)-$N7)/365.25*Assumptions!$B$18*BS7,(Assumptions!$B$20*Assumptions!$B$18+((DATE(Assumptions!$B$4,10,28)-$N7)/365.25-Assumptions!$B$20)*Assumptions!$B$19)*BS7),0) -> 11204.381 | BU7: =IF(BR7>0,IF($M7="Saudi",MIN(BR7+$Q7*$V7,Assumptions!$B$14)*Assumptions!$B$12,MIN(BR7+$Q7*$V7,Assumptions!$B$14)*Assumptions!$B$13),0) -> 0 | BV7: =IF(AND(BR7>0,$M7="Non-Saudi"),Assumptions!$B$25,0) -> 910.41667 | BW7: =IF(AND($D7="Contrat Local",$N7<>""),IF(AND(11>=Assumptions!$B$5,ISNUMBER($X7),$N7<EDATE(Assumptions!$B$9,-Assumptions!$B$6*12)),($P7+$X7)*$V7,$P7*$V7),0) -> 7400 | BX7: =IF(BW7>0,BW7+($Q7+$R7+IF(ISNUMBER($S7),$S7,0)+IF(ISNUMBER($T7),$T7,0))*$V7,0) -> 10400 | BY7: =IF(AND(BX7>0,$N7<>""),IF((DATE(Assumptions!$B$4,11,28)-$N7)/365.25<=Assumptions!$B$20,(DATE(Assumptions!$B$4,11,28)-$N7)/365.25*Assumptions!$B$18*BX7,(Assumptions!$B$20*Assumptions!$B$18+((DATE(Assumptions!$B$4,11,28)-$N7)/365.25-Assumptions!$B$20)*Assumptions!$B$19)*BX7),0) -> 11645.722 | BZ7: =IF(BW7>0,IF($M7="Saudi",MIN(BW7+$Q7*$V7,Assumptions!$B$14)*Assumptions!$B$12,MIN(BW7+$Q7*$V7,Assumptions!$B$14)*Assumptions!$B$13),0) -> 0 | CA7: =IF(AND(BW7>0,$M7="Non-Saudi"),Assumptions!$B$25,0) -> 910.41667 | CB7: =IF(AND($D7="Contrat Local",$N7<>""),IF(AND(12>=Assumptions!$B$5,ISNUMBER($X7),$N7<EDATE(Assumptions!$B$9,-Assumptions!$B$6*12)),($P7+$X7)*$V7,$P7*$V7),0) -> 7400 | CC7: =IF(CB7>0,CB7+($Q7+$R7+IF(ISNUMBER($S7),$S7,0)+IF(ISNUMBER($T7),$T7,0))*$V7,0) -> 10400 | CD7: =IF(AND(CC7>0,$N7<>""),IF((DATE(Assumptions!$B$4,12,28)-$N7)/365.25<=Assumptions!$B$20,(DATE(Assumptions!$B$4,12,28)-$N7)/365.25*Assumptions!$B$18*CC7,(Assumptions!$B$20*Assumptions!$B$18+((DATE(Assumptions!$B$4,12,28)-$N7)/365.25-Assumptions!$B$20)*Assumptions!$B$19)*CC7),0) -> 12072.827 | CE7: =IF(CB7>0,IF($M7="Saudi",MIN(CB7+$Q7*$V7,Assumptions!$B$14)*Assumptions!$B$12,MIN(CB7+$Q7*$V7,Assumptions!$B$14)*Assumptions!$B$13),0) -> 0 | CF7: =IF(AND(CB7>0,$M7="Non-Saudi"),Assumptions!$B$25,0) -> 910.41667 | CG7: =Y7+AD7+AI7+AN7+AS7+AX7+BC7+BH7+BM7+BR7+BW7+CB7 -> 87200 | CH7: =Z7+AE7+AJ7+AO7+AT7+AY7+BD7+BI7+BN7+BS7+BX7+CC7 -> 123200 | CI7: =CD7-IF(AND(Z7>0,$N7<>""),IF((DATE(Assumptions!$B$4-1,12,28)-$N7)/365.25<=Assumptions!$B$20,(DATE(Assumptions!$B$4-1,12,28)-$N7)/365.25*Assumptions!$B$18*Z7,(Assumptions!$B$20*Assumptions!$B$18+((DATE(Assumptions!$B$4-1,12,28)-$N7)/365.25-Assumptions!$B$20)*Assumptions!$B$19)*Z7),0) -> 5328.679 | CJ7: =AB7+AG7+AL7+AQ7+AV7+BA7+BF7+BK7+BP7+BU7+BZ7+CE7 -> 0 | CK7: =AC7+AH7+AM7+AR7+AW7+BB7+BG7+BL7+BQ7+BV7+CA7+CF7 -> 10925
A8: 4 | B8: ABOUTALEB | C8: Hasnae | D8: Contrat Local | E8: Permanent | F8: Professeur(e) des écoles | G8: Élémentaire | H8: Generaliste | I8: Teacher | J8: Professeur des écoles (PE) | K8: Maternelle | L8: Existing | M8: =IF(D8="Titulaire EN","",IF(OR(B8="AL OSSAIMI AL OTAIBI",B8="ALAMRI"),"Saudi","Non-Saudi")) -> Non-Saudi | N8: 44440 | O8: 5.3 | P8: 9000 | Q8: 2500 | R8: 500 | U8: 12000 | V8: 1 | W8: Virement | X8: 250 | Y8: =IF(AND($D8="Contrat Local",$N8<>""),$P8*$V8,0) -> 9000 | Z8: =IF(Y8>0,Y8+($Q8+$R8+IF(ISNUMBER($S8),$S8,0)+IF(ISNUMBER($T8),$T8,0))*$V8,0) -> 12000 | AA8: =IF(AND(Z8>0,$N8<>""),IF((DATE(Assumptions!$B$4,1,28)-$N8)/365.25<=Assumptions!$B$20,(DATE(Assumptions!$B$4,1,28)-$N8)/365.25*Assumptions!$B$18*Z8,(Assumptions!$B$20*Assumptions!$B$18+((DATE(Assumptions!$B$4,1,28)-$N8)/365.25-Assumptions!$B$20)*Assumptions!$B$19)*Z8),0) -> 26447.639 | AB8: =IF(Y8>0,IF($M8="Saudi",MIN(Y8+$Q8*$V8,Assumptions!$B$14)*Assumptions!$B$12,MIN(Y8+$Q8*$V8,Assumptions!$B$14)*Assumptions!$B$13),0) -> 0 | AC8: =IF(AND(Y8>0,$M8="Non-Saudi"),Assumptions!$B$25,0) -> 910.41667 | AD8: =IF(AND($D8="Contrat Local",$N8<>""),$P8*$V8,0) -> 9000 | AE8: =IF(AD8>0,AD8+($Q8+$R8+IF(ISNUMBER($S8),$S8,0)+IF(ISNUMBER($T8),$T8,0))*$V8,0) -> 12000 | AF8: =IF(AND(AE8>0,$N8<>""),IF((DATE(Assumptions!$B$4,2,28)-$N8)/365.25<=Assumptions!$B$20,(DATE(Assumptions!$B$4,2,28)-$N8)/365.25*Assumptions!$B$18*AE8,(Assumptions!$B$20*Assumptions!$B$18+((DATE(Assumptions!$B$4,2,28)-$N8)/365.25-Assumptions!$B$20)*Assumptions!$B$19)*AE8),0) -> 26956.879 | AG8: =IF(AD8>0,IF($M8="Saudi",MIN(AD8+$Q8*$V8,Assumptions!$B$14)*Assumptions!$B$12,MIN(AD8+$Q8*$V8,Assumptions!$B$14)*Assumptions!$B$13),0) -> 0 | AH8: =IF(AND(AD8>0,$M8="Non-Saudi"),Assumptions!$B$25,0) -> 910.41667 | AI8: =IF(AND($D8="Contrat Local",$N8<>""),$P8*$V8,0) -> 9000 | AJ8: =IF(AI8>0,AI8+($Q8+$R8+IF(ISNUMBER($S8),$S8,0)+IF(ISNUMBER($T8),$T8,0))*$V8,0) -> 12000 | AK8: =IF(AND(AJ8>0,$N8<>""),IF((DATE(Assumptions!$B$4,3,28)-$N8)/365.25<=Assumptions!$B$20,(DATE(Assumptions!$B$4,3,28)-$N8)/365.25*Assumptions!$B$18*AJ8,(Assumptions!$B$20*Assumptions!$B$18+((DATE(Assumptions!$B$4,3,28)-$N8)/365.25-Assumptions!$B$20)*Assumptions!$B$19)*AJ8),0) -> 27416.838 | AL8: =IF(AI8>0,IF($M8="Saudi",MIN(AI8+$Q8*$V8,Assumptions!$B$14)*Assumptions!$B$12,MIN(AI8+$Q8*$V8,Assumptions!$B$14)*Assumptions!$B$13),0) -> 0 | AM8: =IF(AND(AI8>0,$M8="Non-Saudi"),Assumptions!$B$25,0) -> 910.41667 | AN8: =IF(AND($D8="Contrat Local",$N8<>""),$P8*$V8,0) -> 9000 | AO8: =IF(AN8>0,AN8+($Q8+$R8+IF(ISNUMBER($S8),$S8,0)+IF(ISNUMBER($T8),$T8,0))*$V8,0) -> 12000 | AP8: =IF(AND(AO8>0,$N8<>""),IF((DATE(Assumptions!$B$4,4,28)-$N8)/365.25<=Assumptions!$B$20,(DATE(Assumptions!$B$4,4,28)-$N8)/365.25*Assumptions!$B$18*AO8,(Assumptions!$B$20*Assumptions!$B$18+((DATE(Assumptions!$B$4,4,28)-$N8)/365.25-Assumptions!$B$20)*Assumptions!$B$19)*AO8),0) -> 27926.078 | AQ8: =IF(AN8>0,IF($M8="Saudi",MIN(AN8+$Q8*$V8,Assumptions!$B$14)*Assumptions!$B$12,MIN(AN8+$Q8*$V8,Assumptions!$B$14)*Assumptions!$B$13),0) -> 0 | AR8: =IF(AND(AN8>0,$M8="Non-Saudi"),Assumptions!$B$25,0) -> 910.41667 | AS8: =IF(AND($D8="Contrat Local",$N8<>""),$P8*$V8,0) -> 9000 | AT8: =IF(AS8>0,AS8+($Q8+$R8+IF(ISNUMBER($S8),$S8,0)+IF(ISNUMBER($T8),$T8,0))*$V8,0) -> 12000 | AU8: =IF(AND(AT8>0,$N8<>""),IF((DATE(Assumptions!$B$4,5,28)-$N8)/365.25<=Assumptions!$B$20,(DATE(Assumptions!$B$4,5,28)-$N8)/365.25*Assumptions!$B$18*AT8,(Assumptions!$B$20*Assumptions!$B$18+((DATE(Assumptions!$B$4,5,28)-$N8)/365.25-Assumptions!$B$20)*Assumptions!$B$19)*AT8),0) -> 28418.891 | AV8: =IF(AS8>0,IF($M8="Saudi",MIN(AS8+$Q8*$V8,Assumptions!$B$14)*Assumptions!$B$12,MIN(AS8+$Q8*$V8,Assumptions!$B$14)*Assumptions!$B$13),0) -> 0 | AW8: =IF(AND(AS8>0,$M8="Non-Saudi"),Assumptions!$B$25,0) -> 910.41667 | AX8: =IF(AND($D8="Contrat Local",$N8<>""),$P8*$V8,0) -> 9000 | AY8: =IF(AX8>0,AX8+($Q8+$R8+IF(ISNUMBER($S8),$S8,0)+IF(ISNUMBER($T8),$T8,0))*$V8,0) -> 12000 | AZ8: =IF(AND(AY8>0,$N8<>""),IF((DATE(Assumptions!$B$4,6,28)-$N8)/365.25<=Assumptions!$B$20,(DATE(Assumptions!$B$4,6,28)-$N8)/365.25*Assumptions!$B$18*AY8,(Assumptions!$B$20*Assumptions!$B$18+((DATE(Assumptions!$B$4,6,28)-$N8)/365.25-Assumptions!$B$20)*Assumptions!$B$19)*AY8),0) -> 28928.131 | BA8: =IF(AX8>0,IF($M8="Saudi",MIN(AX8+$Q8*$V8,Assumptions!$B$14)*Assumptions!$B$12,MIN(AX8+$Q8*$V8,Assumptions!$B$14)*Assumptions!$B$13),0) -> 0 | BB8: =IF(AND(AX8>0,$M8="Non-Saudi"),Assumptions!$B$25,0) -> 910.41667 | BC8: =IF(AND($D8="Contrat Local",$N8<>""),$P8*$V8,0) -> 9000 | BD8: =IF(BC8>0,BC8+($Q8+$R8+IF(ISNUMBER($S8),$S8,0)+IF(ISNUMBER($T8),$T8,0))*$V8,0) -> 12000 | BE8: =IF(AND(BD8>0,$N8<>""),IF((DATE(Assumptions!$B$4,7,28)-$N8)/365.25<=Assumptions!$B$20,(DATE(Assumptions!$B$4,7,28)-$N8)/365.25*Assumptions!$B$18*BD8,(Assumptions!$B$20*Assumptions!$B$18+((DATE(Assumptions!$B$4,7,28)-$N8)/365.25-Assumptions!$B$20)*Assumptions!$B$19)*BD8),0) -> 29420.945 | BF8: =IF(BC8>0,IF($M8="Saudi",MIN(BC8+$Q8*$V8,Assumptions!$B$14)*Assumptions!$B$12,MIN(BC8+$Q8*$V8,Assumptions!$B$14)*Assumptions!$B$13),0) -> 0 | BG8: =IF(AND(BC8>0,$M8="Non-Saudi"),Assumptions!$B$25,0) -> 910.41667 | BH8: =IF(AND($D8="Contrat Local",$N8<>""),$P8*$V8,0) -> 9000 | BI8: =IF(BH8>0,BH8+($Q8+$R8+IF(ISNUMBER($S8),$S8,0)+IF(ISNUMBER($T8),$T8,0))*$V8,0) -> 12000 | BJ8: =IF(AND(BI8>0,$N8<>""),IF((DATE(Assumptions!$B$4,8,28)-$N8)/365.25<=Assumptions!$B$20,(DATE(Assumptions!$B$4,8,28)-$N8)/365.25*Assumptions!$B$18*BI8,(Assumptions!$B$20*Assumptions!$B$18+((DATE(Assumptions!$B$4,8,28)-$N8)/365.25-Assumptions!$B$20)*Assumptions!$B$19)*BI8),0) -> 29930.185 | BK8: =IF(BH8>0,IF($M8="Saudi",MIN(BH8+$Q8*$V8,Assumptions!$B$14)*Assumptions!$B$12,MIN(BH8+$Q8*$V8,Assumptions!$B$14)*Assumptions!$B$13),0) -> 0 | BL8: =IF(AND(BH8>0,$M8="Non-Saudi"),Assumptions!$B$25,0) -> 910.41667 | BM8: =IF(AND($D8="Contrat Local",$N8<>""),IF(AND(9>=Assumptions!$B$5,ISNUMBER($X8),$N8<EDATE(Assumptions!$B$9,-Assumptions!$B$6*12)),($P8+$X8)*$V8,$P8*$V8),0) -> 9250 | BN8: =IF(BM8>0,BM8+($Q8+$R8+IF(ISNUMBER($S8),$S8,0)+IF(ISNUMBER($T8),$T8,0))*$V8,0) -> 12250 | BO8: =IF(AND(BN8>0,$N8<>""),IF((DATE(Assumptions!$B$4,9,28)-$N8)/365.25<=Assumptions!$B$20,(DATE(Assumptions!$B$4,9,28)-$N8)/365.25*Assumptions!$B$18*BN8,(Assumptions!$B$20*Assumptions!$B$18+((DATE(Assumptions!$B$4,9,28)-$N8)/365.25-Assumptions!$B$20)*Assumptions!$B$19)*BN8),0) -> 31522.159 | BP8: =IF(BM8>0,IF($M8="Saudi",MIN(BM8+$Q8*$V8,Assumptions!$B$14)*Assumptions!$B$12,MIN(BM8+$Q8*$V8,Assumptions!$B$14)*Assumptions!$B$13),0) -> 0 | BQ8: =IF(AND(BM8>0,$M8="Non-Saudi"),Assumptions!$B$25,0) -> 910.41667 | BR8: =IF(AND($D8="Contrat Local",$N8<>""),IF(AND(10>=Assumptions!$B$5,ISNUMBER($X8),$N8<EDATE(Assumptions!$B$9,-Assumptions!$B$6*12)),($P8+$X8)*$V8,$P8*$V8),0) -> 9250 | BS8: =IF(BR8>0,BR8+($Q8+$R8+IF(ISNUMBER($S8),$S8,0)+IF(ISNUMBER($T8),$T8,0))*$V8,0) -> 12250 | BT8: =IF(AND(BS8>0,$N8<>""),IF((DATE(Assumptions!$B$4,10,28)-$N8)/365.25<=Assumptions!$B$20,(DATE(Assumptions!$B$4,10,28)-$N8)/365.25*Assumptions!$B$18*BS8,(Assumptions!$B$20*Assumptions!$B$18+((DATE(Assumptions!$B$4,10,28)-$N8)/365.25-Assumptions!$B$20)*Assumptions!$B$19)*BS8),0) -> 32528.32 | BU8: =IF(BR8>0,IF($M8="Saudi",MIN(BR8+$Q8*$V8,Assumptions!$B$14)*Assumptions!$B$12,MIN(BR8+$Q8*$V8,Assumptions!$B$14)*Assumptions!$B$13),0) -> 0 | BV8: =IF(AND(BR8>0,$M8="Non-Saudi"),Assumptions!$B$25,0) -> 910.41667 | BW8: =IF(AND($D8="Contrat Local",$N8<>""),IF(AND(11>=Assumptions!$B$5,ISNUMBER($X8),$N8<EDATE(Assumptions!$B$9,-Assumptions!$B$6*12)),($P8+$X8)*$V8,$P8*$V8),0) -> 9250 | BX8: =IF(BW8>0,BW8+($Q8+$R8+IF(ISNUMBER($S8),$S8,0)+IF(ISNUMBER($T8),$T8,0))*$V8,0) -> 12250 | BY8: =IF(AND(BX8>0,$N8<>""),IF((DATE(Assumptions!$B$4,11,28)-$N8)/365.25<=Assumptions!$B$20,(DATE(Assumptions!$B$4,11,28)-$N8)/365.25*Assumptions!$B$18*BX8,(Assumptions!$B$20*Assumptions!$B$18+((DATE(Assumptions!$B$4,11,28)-$N8)/365.25-Assumptions!$B$20)*Assumptions!$B$19)*BX8),0) -> 33568.018 | BZ8: =IF(BW8>0,IF($M8="Saudi",MIN(BW8+$Q8*$V8,Assumptions!$B$14)*Assumptions!$B$12,MIN(BW8+$Q8*$V8,Assumptions!$B$14)*Assumptions!$B$13),0) -> 0 | CA8: =IF(AND(BW8>0,$M8="Non-Saudi"),Assumptions!$B$25,0) -> 910.41667 | CB8: =IF(AND($D8="Contrat Local",$N8<>""),IF(AND(12>=Assumptions!$B$5,ISNUMBER($X8),$N8<EDATE(Assumptions!$B$9,-Assumptions!$B$6*12)),($P8+$X8)*$V8,$P8*$V8),0) -> 9250 | CC8: =IF(CB8>0,CB8+($Q8+$R8+IF(ISNUMBER($S8),$S8,0)+IF(ISNUMBER($T8),$T8,0))*$V8,0) -> 12250 | CD8: =IF(AND(CC8>0,$N8<>""),IF((DATE(Assumptions!$B$4,12,28)-$N8)/365.25<=Assumptions!$B$20,(DATE(Assumptions!$B$4,12,28)-$N8)/365.25*Assumptions!$B$18*CC8,(Assumptions!$B$20*Assumptions!$B$18+((DATE(Assumptions!$B$4,12,28)-$N8)/365.25-Assumptions!$B$20)*Assumptions!$B$19)*CC8),0) -> 34574.179 | CE8: =IF(CB8>0,IF($M8="Saudi",MIN(CB8+$Q8*$V8,Assumptions!$B$14)*Assumptions!$B$12,MIN(CB8+$Q8*$V8,Assumptions!$B$14)*Assumptions!$B$13),0) -> 0 | CF8: =IF(AND(CB8>0,$M8="Non-Saudi"),Assumptions!$B$25,0) -> 910.41667 | CG8: =Y8+AD8+AI8+AN8+AS8+AX8+BC8+BH8+BM8+BR8+BW8+CB8 -> 109000 | CH8: =Z8+AE8+AJ8+AO8+AT8+AY8+BD8+BI8+BN8+BS8+BX8+CC8 -> 145000 | CI8: =CD8-IF(AND(Z8>0,$N8<>""),IF((DATE(Assumptions!$B$4-1,12,28)-$N8)/365.25<=Assumptions!$B$20,(DATE(Assumptions!$B$4-1,12,28)-$N8)/365.25*Assumptions!$B$18*Z8,(Assumptions!$B$20*Assumptions!$B$18+((DATE(Assumptions!$B$4-1,12,28)-$N8)/365.25-Assumptions!$B$20)*Assumptions!$B$19)*Z8),0) -> 8635.7803 | CJ8: =AB8+AG8+AL8+AQ8+AV8+BA8+BF8+BK8+BP8+BU8+BZ8+CE8 -> 0 | CK8: =AC8+AH8+AM8+AR8+AW8+BB8+BG8+BL8+BQ8+BV8+CA8+CF8 -> 10925
A9: 5 | B9: ABSIL | C9: Marie-Savine | D9: Contrat Local | E9: Permanent | F9: Professeur(e) des écoles | G9: Élémentaire | H9: Generaliste | I9: Teacher | J9: Professeur des écoles (PE) | K9: Élémentaire | L9: Existing | M9: =IF(D9="Titulaire EN","",IF(OR(B9="AL OSSAIMI AL OTAIBI",B9="ALAMRI"),"Saudi","Non-Saudi")) -> Non-Saudi | N9: 45901 | O9: 1.3 | P9: 10500 | Q9: 2500 | R9: 500 | U9: 13500 | V9: 1 | W9: Liquide | X9: Nouveau Contrat | Y9: =IF(AND($D9="Contrat Local",$N9<>""),$P9*$V9,0) -> 10500 | Z9: =IF(Y9>0,Y9+($Q9+$R9+IF(ISNUMBER($S9),$S9,0)+IF(ISNUMBER($T9),$T9,0))*$V9,0) -> 13500 | AA9: =IF(AND(Z9>0,$N9<>""),IF((DATE(Assumptions!$B$4,1,28)-$N9)/365.25<=Assumptions!$B$20,(DATE(Assumptions!$B$4,1,28)-$N9)/365.25*Assumptions!$B$18*Z9,(Assumptions!$B$20*Assumptions!$B$18+((DATE(Assumptions!$B$4,1,28)-$N9)/365.25-Assumptions!$B$20)*Assumptions!$B$19)*Z9),0) -> 2753.5934 | AB9: =IF(Y9>0,IF($M9="Saudi",MIN(Y9+$Q9*$V9,Assumptions!$B$14)*Assumptions!$B$12,MIN(Y9+$Q9*$V9,Assumptions!$B$14)*Assumptions!$B$13),0) -> 0 | AC9: =IF(AND(Y9>0,$M9="Non-Saudi"),Assumptions!$B$25,0) -> 910.41667 | AD9: =IF(AND($D9="Contrat Local",$N9<>""),$P9*$V9,0) -> 10500 | AE9: =IF(AD9>0,AD9+($Q9+$R9+IF(ISNUMBER($S9),$S9,0)+IF(ISNUMBER($T9),$T9,0))*$V9,0) -> 13500 | AF9: =IF(AND(AE9>0,$N9<>""),IF((DATE(Assumptions!$B$4,2,28)-$N9)/365.25<=Assumptions!$B$20,(DATE(Assumptions!$B$4,2,28)-$N9)/365.25*Assumptions!$B$18*AE9,(Assumptions!$B$20*Assumptions!$B$18+((DATE(Assumptions!$B$4,2,28)-$N9)/365.25-Assumptions!$B$20)*Assumptions!$B$19)*AE9),0) -> 3326.4887 | AG9: =IF(AD9>0,IF($M9="Saudi",MIN(AD9+$Q9*$V9,Assumptions!$B$14)*Assumptions!$B$12,MIN(AD9+$Q9*$V9,Assumptions!$B$14)*Assumptions!$B$13),0) -> 0 | AH9: =IF(AND(AD9>0,$M9="Non-Saudi"),Assumptions!$B$25,0) -> 910.41667 | AI9: =IF(AND($D9="Contrat Local",$N9<>""),$P9*$V9,0) -> 10500 | AJ9: =IF(AI9>0,AI9+($Q9+$R9+IF(ISNUMBER($S9),$S9,0)+IF(ISNUMBER($T9),$T9,0))*$V9,0) -> 13500 | AK9: =IF(AND(AJ9>0,$N9<>""),IF((DATE(Assumptions!$B$4,3,28)-$N9)/365.25<=Assumptions!$B$20,(DATE(Assumptions!$B$4,3,28)-$N9)/365.25*Assumptions!$B$18*AJ9,(Assumptions!$B$20*Assumptions!$B$18+((DATE(Assumptions!$B$4,3,28)-$N9)/365.25-Assumptions!$B$20)*Assumptions!$B$19)*AJ9),0) -> 3843.9425 | AL9: =IF(AI9>0,IF($M9="Saudi",MIN(AI9+$Q9*$V9,Assumptions!$B$14)*Assumptions!$B$12,MIN(AI9+$Q9*$V9,Assumptions!$B$14)*Assumptions!$B$13),0) -> 0 | AM9: =IF(AND(AI9>0,$M9="Non-Saudi"),Assumptions!$B$25,0) -> 910.41667 | AN9: =IF(AND($D9="Contrat Local",$N9<>""),$P9*$V9,0) -> 10500 | AO9: =IF(AN9>0,AN9+($Q9+$R9+IF(ISNUMBER($S9),$S9,0)+IF(ISNUMBER($T9),$T9,0))*$V9,0) -> 13500 | AP9: =IF(AND(AO9>0,$N9<>""),IF((DATE(Assumptions!$B$4,4,28)-$N9)/365.25<=Assumptions!$B$20,(DATE(Assumptions!$B$4,4,28)-$N9)/365.25*Assumptions!$B$18*AO9,(Assumptions!$B$20*Assumptions!$B$18+((DATE(Assumptions!$B$4,4,28)-$N9)/365.25-Assumptions!$B$20)*Assumptions!$B$19)*AO9),0) -> 4416.8378 | AQ9: =IF(AN9>0,IF($M9="Saudi",MIN(AN9+$Q9*$V9,Assumptions!$B$14)*Assumptions!$B$12,MIN(AN9+$Q9*$V9,Assumptions!$B$14)*Assumptions!$B$13),0) -> 0 | AR9: =IF(AND(AN9>0,$M9="Non-Saudi"),Assumptions!$B$25,0) -> 910.41667 | AS9: =IF(AND($D9="Contrat Local",$N9<>""),$P9*$V9,0) -> 10500 | AT9: =IF(AS9>0,AS9+($Q9+$R9+IF(ISNUMBER($S9),$S9,0)+IF(ISNUMBER($T9),$T9,0))*$V9,0) -> 13500 | AU9: =IF(AND(AT9>0,$N9<>""),IF((DATE(Assumptions!$B$4,5,28)-$N9)/365.25<=Assumptions!$B$20,(DATE(Assumptions!$B$4,5,28)-$N9)/365.25*Assumptions!$B$18*AT9,(Assumptions!$B$20*Assumptions!$B$18+((DATE(Assumptions!$B$4,5,28)-$N9)/365.25-Assumptions!$B$20)*Assumptions!$B$19)*AT9),0) -> 4971.2526 | AV9: =IF(AS9>0,IF($M9="Saudi",MIN(AS9+$Q9*$V9,Assumptions!$B$14)*Assumptions!$B$12,MIN(AS9+$Q9*$V9,Assumptions!$B$14)*Assumptions!$B$13),0) -> 0 | AW9: =IF(AND(AS9>0,$M9="Non-Saudi"),Assumptions!$B$25,0) -> 910.41667 | AX9: =IF(AND($D9="Contrat Local",$N9<>""),$P9*$V9,0) -> 10500 | AY9: =IF(AX9>0,AX9+($Q9+$R9+IF(ISNUMBER($S9),$S9,0)+IF(ISNUMBER($T9),$T9,0))*$V9,0) -> 13500 | AZ9: =IF(AND(AY9>0,$N9<>""),IF((DATE(Assumptions!$B$4,6,28)-$N9)/365.25<=Assumptions!$B$20,(DATE(Assumptions!$B$4,6,28)-$N9)/365.25*Assumptions!$B$18*AY9,(Assumptions!$B$20*Assumptions!$B$18+((DATE(Assumptions!$B$4,6,28)-$N9)/365.25-Assumptions!$B$20)*Assumptions!$B$19)*AY9),0) -> 5544.1478 | BA9: =IF(AX9>0,IF($M9="Saudi",MIN(AX9+$Q9*$V9,Assumptions!$B$14)*Assumptions!$B$12,MIN(AX9+$Q9*$V9,Assumptions!$B$14)*Assumptions!$B$13),0) -> 0 | BB9: =IF(AND(AX9>0,$M9="Non-Saudi"),Assumptions!$B$25,0) -> 910.41667 | BC9: =IF(AND($D9="Contrat Local",$N9<>""),$P9*$V9,0) -> 10500 | BD9: =IF(BC9>0,BC9+($Q9+$R9+IF(ISNUMBER($S9),$S9,0)+IF(ISNUMBER($T9),$T9,0))*$V9,0) -> 13500 | BE9: =IF(AND(BD9>0,$N9<>""),IF((DATE(Assumptions!$B$4,7,28)-$N9)/365.25<=Assumptions!$B$20,(DATE(Assumptions!$B$4,7,28)-$N9)/365.25*Assumptions!$B$18*BD9,(Assumptions!$B$20*Assumptions!$B$18+((DATE(Assumptions!$B$4,7,28)-$N9)/365.25-Assumptions!$B$20)*Assumptions!$B$19)*BD9),0) -> 6098.5626 | BF9: =IF(BC9>0,IF($M9="Saudi",MIN(BC9+$Q9*$V9,Assumptions!$B$14)*Assumptions!$B$12,MIN(BC9+$Q9*$V9,Assumptions!$B$14)*Assumptions!$B$13),0) -> 0 | BG9: =IF(AND(BC9>0,$M9="Non-Saudi"),Assumptions!$B$25,0) -> 910.41667 | BH9: =IF(AND($D9="Contrat Local",$N9<>""),$P9*$V9,0) -> 10500 | BI9: =IF(BH9>0,BH9+($Q9+$R9+IF(ISNUMBER($S9),$S9,0)+IF(ISNUMBER($T9),$T9,0))*$V9,0) -> 13500 | BJ9: =IF(AND(BI9>0,$N9<>""),IF((DATE(Assumptions!$B$4,8,28)-$N9)/365.25<=Assumptions!$B$20,(DATE(Assumptions!$B$4,8,28)-$N9)/365.25*Assumptions!$B$18*BI9,(Assumptions!$B$20*Assumptions!$B$18+((DATE(Assumptions!$B$4,8,28)-$N9)/365.25-Assumptions!$B$20)*Assumptions!$B$19)*BI9),0) -> 6671.4579 | BK9: =IF(BH9>0,IF($M9="Saudi",MIN(BH9+$Q9*$V9,Assumptions!$B$14)*Assumptions!$B$12,MIN(BH9+$Q9*$V9,Assumptions!$B$14)*Assumptions!$B$13),0) -> 0 | BL9: =IF(AND(BH9>0,$M9="Non-Saudi"),Assumptions!$B$25,0) -> 910.41667 | BM9: =IF(AND($D9="Contrat Local",$N9<>""),IF(AND(9>=Assumptions!$B$5,ISNUMBER($X9),$N9<EDATE(Assumptions!$B$9,-Assumptions!$B$6*12)),($P9+$X9)*$V9,$P9*$V9),0) -> 10500 | BN9: =IF(BM9>0,BM9+($Q9+$R9+IF(ISNUMBER($S9),$S9,0)+IF(ISNUMBER($T9),$T9,0))*$V9,0) -> 13500 | BO9: =IF(AND(BN9>0,$N9<>""),IF((DATE(Assumptions!$B$4,9,28)-$N9)/365.25<=Assumptions!$B$20,(DATE(Assumptions!$B$4,9,28)-$N9)/365.25*Assumptions!$B$18*BN9,(Assumptions!$B$20*Assumptions!$B$18+((DATE(Assumptions!$B$4,9,28)-$N9)/365.25-Assumptions!$B$20)*Assumptions!$B$19)*BN9),0) -> 7244.3532 | BP9: =IF(BM9>0,IF($M9="Saudi",MIN(BM9+$Q9*$V9,Assumptions!$B$14)*Assumptions!$B$12,MIN(BM9+$Q9*$V9,Assumptions!$B$14)*Assumptions!$B$13),0) -> 0 | BQ9: =IF(AND(BM9>0,$M9="Non-Saudi"),Assumptions!$B$25,0) -> 910.41667 | BR9: =IF(AND($D9="Contrat Local",$N9<>""),IF(AND(10>=Assumptions!$B$5,ISNUMBER($X9),$N9<EDATE(Assumptions!$B$9,-Assumptions!$B$6*12)),($P9+$X9)*$V9,$P9*$V9),0) -> 10500 | BS9: =IF(BR9>0,BR9+($Q9+$R9+IF(ISNUMBER($S9),$S9,0)+IF(ISNUMBER($T9),$T9,0))*$V9,0) -> 13500 | BT9: =IF(AND(BS9>0,$N9<>""),IF((DATE(Assumptions!$B$4,10,28)-$N9)/365.25<=Assumptions!$B$20,(DATE(Assumptions!$B$4,10,28)-$N9)/365.25*Assumptions!$B$18*BS9,(Assumptions!$B$20*Assumptions!$B$18+((DATE(Assumptions!$B$4,10,28)-$N9)/365.25-Assumptions!$B$20)*Assumptions!$B$19)*BS9),0) -> 7798.768 | BU9: =IF(BR9>0,IF($M9="Saudi",MIN(BR9+$Q9*$V9,Assumptions!$B$14)*Assumptions!$B$12,MIN(BR9+$Q9*$V9,Assumptions!$B$14)*Assumptions!$B$13),0) -> 0 | BV9: =IF(AND(BR9>0,$M9="Non-Saudi"),Assumptions!$B$25,0) -> 910.41667 | BW9: =IF(AND($D9="Contrat Local",$N9<>""),IF(AND(11>=Assumptions!$B$5,ISNUMBER($X9),$N9<EDATE(Assumptions!$B$9,-Assumptions!$B$6*12)),($P9+$X9)*$V9,$P9*$V9),0) -> 10500 | BX9: =IF(BW9>0,BW9+($Q9+$R9+IF(ISNUMBER($S9),$S9,0)+IF(ISNUMBER($T9),$T9,0))*$V9,0) -> 13500 | BY9: =IF(AND(BX9>0,$N9<>""),IF((DATE(Assumptions!$B$4,11,28)-$N9)/365.25<=Assumptions!$B$20,(DATE(Assumptions!$B$4,11,28)-$N9)/365.25*Assumptions!$B$18*BX9,(Assumptions!$B$20*Assumptions!$B$18+((DATE(Assumptions!$B$4,11,28)-$N9)/365.25-Assumptions!$B$20)*Assumptions!$B$19)*BX9),0) -> 8371.6632 | BZ9: =IF(BW9>0,IF($M9="Saudi",MIN(BW9+$Q9*$V9,Assumptions!$B$14)*Assumptions!$B$12,MIN(BW9+$Q9*$V9,Assumptions!$B$14)*Assumptions!$B$13),0) -> 0 | CA9: =IF(AND(BW9>0,$M9="Non-Saudi"),Assumptions!$B$25,0) -> 910.41667 | CB9: =IF(AND($D9="Contrat Local",$N9<>""),IF(AND(12>=Assumptions!$B$5,ISNUMBER($X9),$N9<EDATE(Assumptions!$B$9,-Assumptions!$B$6*12)),($P9+$X9)*$V9,$P9*$V9),0) -> 10500 | CC9: =IF(CB9>0,CB9+($Q9+$R9+IF(ISNUMBER($S9),$S9,0)+IF(ISNUMBER($T9),$T9,0))*$V9,0) -> 13500 | CD9: =IF(AND(CC9>0,$N9<>""),IF((DATE(Assumptions!$B$4,12,28)-$N9)/365.25<=Assumptions!$B$20,(DATE(Assumptions!$B$4,12,28)-$N9)/365.25*Assumptions!$B$18*CC9,(Assumptions!$B$20*Assumptions!$B$18+((DATE(Assumptions!$B$4,12,28)-$N9)/365.25-Assumptions!$B$20)*Assumptions!$B$19)*CC9),0) -> 8926.078 | CE9: =IF(CB9>0,IF($M9="Saudi",MIN(CB9+$Q9*$V9,Assumptions!$B$14)*Assumptions!$B$12,MIN(CB9+$Q9*$V9,Assumptions!$B$14)*Assumptions!$B$13),0) -> 0 | CF9: =IF(AND(CB9>0,$M9="Non-Saudi"),Assumptions!$B$25,0) -> 910.41667 | CG9: =Y9+AD9+AI9+AN9+AS9+AX9+BC9+BH9+BM9+BR9+BW9+CB9 -> 126000 | CH9: =Z9+AE9+AJ9+AO9+AT9+AY9+BD9+BI9+BN9+BS9+BX9+CC9 -> 162000 | CI9: =CD9-IF(AND(Z9>0,$N9<>""),IF((DATE(Assumptions!$B$4-1,12,28)-$N9)/365.25<=Assumptions!$B$20,(DATE(Assumptions!$B$4-1,12,28)-$N9)/365.25*Assumptions!$B$18*Z9,(Assumptions!$B$20*Assumptions!$B$18+((DATE(Assumptions!$B$4-1,12,28)-$N9)/365.25-Assumptions!$B$20)*Assumptions!$B$19)*Z9),0) -> 6745.3799 | CJ9: =AB9+AG9+AL9+AQ9+AV9+BA9+BF9+BK9+BP9+BU9+BZ9+CE9 -> 0 | CK9: =AC9+AH9+AM9+AR9+AW9+BB9+BG9+BL9+BQ9+BV9+CA9+CF9 -> 10925
A10: 6 | B10: ACHATOU | C10: Nadia | D10: Contrat Local | E10: Permanent | F10: Responsable RH | G10: Administration | H10: Ressources humaines | I10: Non-Teacher | K10: Administration | L10: Existing | M10: =IF(D10="Titulaire EN","",IF(OR(B10="AL OSSAIMI AL OTAIBI",B10="ALAMRI"),"Saudi","Non-Saudi")) -> Non-Saudi | N10: 42614 | O10: 10.3 | P10: 12250 | Q10: 2500 | R10: 500 | S10: 1000 | U10: 16250 | V10: 1 | W10: Mudad | X10: 250 | Y10: =IF(AND($D10="Contrat Local",$N10<>""),$P10*$V10,0) -> 12250 | Z10: =IF(Y10>0,Y10+($Q10+$R10+IF(ISNUMBER($S10),$S10,0)+IF(ISNUMBER($T10),$T10,0))*$V10,0) -> 16250 | AA10: =IF(AND(Z10>0,$N10<>""),IF((DATE(Assumptions!$B$4,1,28)-$N10)/365.25<=Assumptions!$B$20,(DATE(Assumptions!$B$4,1,28)-$N10)/365.25*Assumptions!$B$18*Z10,(Assumptions!$B$20*Assumptions!$B$18+((DATE(Assumptions!$B$4,1,28)-$N10)/365.25-Assumptions!$B$20)*Assumptions!$B$19)*Z10),0) -> 112242.9 | AB10: =IF(Y10>0,IF($M10="Saudi",MIN(Y10+$Q10*$V10,Assumptions!$B$14)*Assumptions!$B$12,MIN(Y10+$Q10*$V10,Assumptions!$B$14)*Assumptions!$B$13),0) -> 0 | AC10: =IF(AND(Y10>0,$M10="Non-Saudi"),Assumptions!$B$25,0) -> 910.41667 | AD10: =IF(AND($D10="Contrat Local",$N10<>""),$P10*$V10,0) -> 12250 | AE10: =IF(AD10>0,AD10+($Q10+$R10+IF(ISNUMBER($S10),$S10,0)+IF(ISNUMBER($T10),$T10,0))*$V10,0) -> 16250 | AF10: =IF(AND(AE10>0,$N10<>""),IF((DATE(Assumptions!$B$4,2,28)-$N10)/365.25<=Assumptions!$B$20,(DATE(Assumptions!$B$4,2,28)-$N10)/365.25*Assumptions!$B$18*AE10,(Assumptions!$B$20*Assumptions!$B$18+((DATE(Assumptions!$B$4,2,28)-$N10)/365.25-Assumptions!$B$20)*Assumptions!$B$19)*AE10),0) -> 113622.09 | AG10: =IF(AD10>0,IF($M10="Saudi",MIN(AD10+$Q10*$V10,Assumptions!$B$14)*Assumptions!$B$12,MIN(AD10+$Q10*$V10,Assumptions!$B$14)*Assumptions!$B$13),0) -> 0 | AH10: =IF(AND(AD10>0,$M10="Non-Saudi"),Assumptions!$B$25,0) -> 910.41667 | AI10: =IF(AND($D10="Contrat Local",$N10<>""),$P10*$V10,0) -> 12250 | AJ10: =IF(AI10>0,AI10+($Q10+$R10+IF(ISNUMBER($S10),$S10,0)+IF(ISNUMBER($T10),$T10,0))*$V10,0) -> 16250 | AK10: =IF(AND(AJ10>0,$N10<>""),IF((DATE(Assumptions!$B$4,3,28)-$N10)/365.25<=Assumptions!$B$20,(DATE(Assumptions!$B$4,3,28)-$N10)/365.25*Assumptions!$B$18*AJ10,(Assumptions!$B$20*Assumptions!$B$18+((DATE(Assumptions!$B$4,3,28)-$N10)/365.25-Assumptions!$B$20)*Assumptions!$B$19)*AJ10),0) -> 114867.81 | AL10: =IF(AI10>0,IF($M10="Saudi",MIN(AI10+$Q10*$V10,Assumptions!$B$14)*Assumptions!$B$12,MIN(AI10+$Q10*$V10,Assumptions!$B$14)*Assumptions!$B$13),0) -> 0 | AM10: =IF(AND(AI10>0,$M10="Non-Saudi"),Assumptions!$B$25,0) -> 910.41667 | AN10: =IF(AND($D10="Contrat Local",$N10<>""),$P10*$V10,0) -> 12250 | AO10: =IF(AN10>0,AN10+($Q10+$R10+IF(ISNUMBER($S10),$S10,0)+IF(ISNUMBER($T10),$T10,0))*$V10,0) -> 16250 | AP10: =IF(AND(AO10>0,$N10<>""),IF((DATE(Assumptions!$B$4,4,28)-$N10)/365.25<=Assumptions!$B$20,(DATE(Assumptions!$B$4,4,28)-$N10)/365.25*Assumptions!$B$18*AO10,(Assumptions!$B$20*Assumptions!$B$18+((DATE(Assumptions!$B$4,4,28)-$N10)/365.25-Assumptions!$B$20)*Assumptions!$B$19)*AO10),0) -> 116247.01 | AQ10: =IF(AN10>0,IF($M10="Saudi",MIN(AN10+$Q10*$V10,Assumptions!$B$14)*Assumptions!$B$12,MIN(AN10+$Q10*$V10,Assumptions!$B$14)*Assumptions!$B$13),0) -> 0 | AR10: =IF(AND(AN10>0,$M10="Non-Saudi"),Assumptions!$B$25,0) -> 910.41667 | AS10: =IF(AND($D10="Contrat Local",$N10<>""),$P10*$V10,0) -> 12250 | AT10: =IF(AS10>0,AS10+($Q10+$R10+IF(ISNUMBER($S10),$S10,0)+IF(ISNUMBER($T10),$T10,0))*$V10,0) -> 16250 | AU10: =IF(AND(AT10>0,$N10<>""),IF((DATE(Assumptions!$B$4,5,28)-$N10)/365.25<=Assumptions!$B$20,(DATE(Assumptions!$B$4,5,28)-$N10)/365.25*Assumptions!$B$18*AT10,(Assumptions!$B$20*Assumptions!$B$18+((DATE(Assumptions!$B$4,5,28)-$N10)/365.25-Assumptions!$B$20)*Assumptions!$B$19)*AT10),0) -> 117581.71 | AV10: =IF(AS10>0,IF($M10="Saudi",MIN(AS10+$Q10*$V10,Assumptions!$B$14)*Assumptions!$B$12,MIN(AS10+$Q10*$V10,Assumptions!$B$14)*Assumptions!$B$13),0) -> 0 | AW10: =IF(AND(AS10>0,$M10="Non-Saudi"),Assumptions!$B$25,0) -> 910.41667 | AX10: =IF(AND($D10="Contrat Local",$N10<>""),$P10*$V10,0) -> 12250 | AY10: =IF(AX10>0,AX10+($Q10+$R10+IF(ISNUMBER($S10),$S10,0)+IF(ISNUMBER($T10),$T10,0))*$V10,0) -> 16250 | AZ10: =IF(AND(AY10>0,$N10<>""),IF((DATE(Assumptions!$B$4,6,28)-$N10)/365.25<=Assumptions!$B$20,(DATE(Assumptions!$B$4,6,28)-$N10)/365.25*Assumptions!$B$18*AY10,(Assumptions!$B$20*Assumptions!$B$18+((DATE(Assumptions!$B$4,6,28)-$N10)/365.25-Assumptions!$B$20)*Assumptions!$B$19)*AY10),0) -> 118960.9 | BA10: =IF(AX10>0,IF($M10="Saudi",MIN(AX10+$Q10*$V10,Assumptions!$B$14)*Assumptions!$B$12,MIN(AX10+$Q10*$V10,Assumptions!$B$14)*Assumptions!$B$13),0) -> 0 | BB10: =IF(AND(AX10>0,$M10="Non-Saudi"),Assumptions!$B$25,0) -> 910.41667 | BC10: =IF(AND($D10="Contrat Local",$N10<>""),$P10*$V10,0) -> 12250 | BD10: =IF(BC10>0,BC10+($Q10+$R10+IF(ISNUMBER($S10),$S10,0)+IF(ISNUMBER($T10),$T10,0))*$V10,0) -> 16250 | BE10: =IF(AND(BD10>0,$N10<>""),IF((DATE(Assumptions!$B$4,7,28)-$N10)/365.25<=Assumptions!$B$20,(DATE(Assumptions!$B$4,7,28)-$N10)/365.25*Assumptions!$B$18*BD10,(Assumptions!$B$20*Assumptions!$B$18+((DATE(Assumptions!$B$4,7,28)-$N10)/365.25-Assumptions!$B$20)*Assumptions!$B$19)*BD10),0) -> 120295.6 | BF10: =IF(BC10>0,IF($M10="Saudi",MIN(BC10+$Q10*$V10,Assumptions!$B$14)*Assumptions!$B$12,MIN(BC10+$Q10*$V10,Assumptions!$B$14)*Assumptions!$B$13),0) -> 0 | BG10: =IF(AND(BC10>0,$M10="Non-Saudi"),Assumptions!$B$25,0) -> 910.41667 | BH10: =IF(AND($D10="Contrat Local",$N10<>""),$P10*$V10,0) -> 12250 | BI10: =IF(BH10>0,BH10+($Q10+$R10+IF(ISNUMBER($S10),$S10,0)+IF(ISNUMBER($T10),$T10,0))*$V10,0) -> 16250 | BJ10: =IF(AND(BI10>0,$N10<>""),IF((DATE(Assumptions!$B$4,8,28)-$N10)/365.25<=Assumptions!$B$20,(DATE(Assumptions!$B$4,8,28)-$N10)/365.25*Assumptions!$B$18*BI10,(Assumptions!$B$20*Assumptions!$B$18+((DATE(Assumptions!$B$4,8,28)-$N10)/365.25-Assumptions!$B$20)*Assumptions!$B$19)*BI10),0) -> 121674.79 | BK10: =IF(BH10>0,IF($M10="Saudi",MIN(BH10+$Q10*$V10,Assumptions!$B$14)*Assumptions!$B$12,MIN(BH10+$Q10*$V10,Assumptions!$B$14)*Assumptions!$B$13),0) -> 0 | BL10: =IF(AND(BH10>0,$M10="Non-Saudi"),Assumptions!$B$25,0) -> 910.41667 | BM10: =IF(AND($D10="Contrat Local",$N10<>""),IF(AND(9>=Assumptions!$B$5,ISNUMBER($X10),$N10<EDATE(Assumptions!$B$9,-Assumptions!$B$6*12)),($P10+$X10)*$V10,$P10*$V10),0) -> 12500 | BN10: =IF(BM10>0,BM10+($Q10+$R10+IF(ISNUMBER($S10),$S10,0)+IF(ISNUMBER($T10),$T10,0))*$V10,0) -> 16500 | BO10: =IF(AND(BN10>0,$N10<>""),IF((DATE(Assumptions!$B$4,9,28)-$N10)/365.25<=Assumptions!$B$20,(DATE(Assumptions!$B$4,9,28)-$N10)/365.25*Assumptions!$B$18*BN10,(Assumptions!$B$20*Assumptions!$B$18+((DATE(Assumptions!$B$4,9,28)-$N10)/365.25-Assumptions!$B$20)*Assumptions!$B$19)*BN10),0) -> 124947.13 | BP10: =IF(BM10>0,IF($M10="Saudi",MIN(BM10+$Q10*$V10,Assumptions!$B$14)*Assumptions!$B$12,MIN(BM10+$Q10*$V10,Assumptions!$B$14)*Assumptions!$B$13),0) -> 0 | BQ10: =IF(AND(BM10>0,$M10="Non-Saudi"),Assumptions!$B$25,0) -> 910.41667 | BR10: =IF(AND($D10="Contrat Local",$N10<>""),IF(AND(10>=Assumptions!$B$5,ISNUMBER($X10),$N10<EDATE(Assumptions!$B$9,-Assumptions!$B$6*12)),($P10+$X10)*$V10,$P10*$V10),0) -> 12500 | BS10: =IF(BR10>0,BR10+($Q10+$R10+IF(ISNUMBER($S10),$S10,0)+IF(ISNUMBER($T10),$T10,0))*$V10,0) -> 16500 | BT10: =IF(AND(BS10>0,$N10<>""),IF((DATE(Assumptions!$B$4,10,28)-$N10)/365.25<=Assumptions!$B$20,(DATE(Assumptions!$B$4,10,28)-$N10)/365.25*Assumptions!$B$18*BS10,(Assumptions!$B$20*Assumptions!$B$18+((DATE(Assumptions!$B$4,10,28)-$N10)/365.25-Assumptions!$B$20)*Assumptions!$B$19)*BS10),0) -> 126302.36 | BU10: =IF(BR10>0,IF($M10="Saudi",MIN(BR10+$Q10*$V10,Assumptions!$B$14)*Assumptions!$B$12,MIN(BR10+$Q10*$V10,Assumptions!$B$14)*Assumptions!$B$13),0) -> 0 | BV10: =IF(AND(BR10>0,$M10="Non-Saudi"),Assumptions!$B$25,0) -> 910.41667 | BW10: =IF(AND($D10="Contrat Local",$N10<>""),IF(AND(11>=Assumptions!$B$5,ISNUMBER($X10),$N10<EDATE(Assumptions!$B$9,-Assumptions!$B$6*12)),($P10+$X10)*$V10,$P10*$V10),0) -> 12500 | BX10: =IF(BW10>0,BW10+($Q10+$R10+IF(ISNUMBER($S10),$S10,0)+IF(ISNUMBER($T10),$T10,0))*$V10,0) -> 16500 | BY10: =IF(AND(BX10>0,$N10<>""),IF((DATE(Assumptions!$B$4,11,28)-$N10)/365.25<=Assumptions!$B$20,(DATE(Assumptions!$B$4,11,28)-$N10)/365.25*Assumptions!$B$18*BX10,(Assumptions!$B$20*Assumptions!$B$18+((DATE(Assumptions!$B$4,11,28)-$N10)/365.25-Assumptions!$B$20)*Assumptions!$B$19)*BX10),0) -> 127702.77 | BZ10: =IF(BW10>0,IF($M10="Saudi",MIN(BW10+$Q10*$V10,Assumptions!$B$14)*Assumptions!$B$12,MIN(BW10+$Q10*$V10,Assumptions!$B$14)*Assumptions!$B$13),0) -> 0 | CA10: =IF(AND(BW10>0,$M10="Non-Saudi"),Assumptions!$B$25,0) -> 910.41667 | CB10: =IF(AND($D10="Contrat Local",$N10<>""),IF(AND(12>=Assumptions!$B$5,ISNUMBER($X10),$N10<EDATE(Assumptions!$B$9,-Assumptions!$B$6*12)),($P10+$X10)*$V10,$P10*$V10),0) -> 12500 | CC10: =IF(CB10>0,CB10+($Q10+$R10+IF(ISNUMBER($S10),$S10,0)+IF(ISNUMBER($T10),$T10,0))*$V10,0) -> 16500 | CD10: =IF(AND(CC10>0,$N10<>""),IF((DATE(Assumptions!$B$4,12,28)-$N10)/365.25<=Assumptions!$B$20,(DATE(Assumptions!$B$4,12,28)-$N10)/365.25*Assumptions!$B$18*CC10,(Assumptions!$B$20*Assumptions!$B$18+((DATE(Assumptions!$B$4,12,28)-$N10)/365.25-Assumptions!$B$20)*Assumptions!$B$19)*CC10),0) -> 129058.01 | CE10: =IF(CB10>0,IF($M10="Saudi",MIN(CB10+$Q10*$V10,Assumptions!$B$14)*Assumptions!$B$12,MIN(CB10+$Q10*$V10,Assumptions!$B$14)*Assumptions!$B$13),0) -> 0 | CF10: =IF(AND(CB10>0,$M10="Non-Saudi"),Assumptions!$B$25,0) -> 910.41667 | CG10: =Y10+AD10+AI10+AN10+AS10+AX10+BC10+BH10+BM10+BR10+BW10+CB10 -> 148000 | CH10: =Z10+AE10+AJ10+AO10+AT10+AY10+BD10+BI10+BN10+BS10+BX10+CC10 -> 196000 | CI10: =CD10-IF(AND(Z10>0,$N10<>""),IF((DATE(Assumptions!$B$4-1,12,28)-$N10)/365.25<=Assumptions!$B$20,(DATE(Assumptions!$B$4-1,12,28)-$N10)/365.25*Assumptions!$B$18*Z10,(Assumptions!$B$20*Assumptions!$B$18+((DATE(Assumptions!$B$4-1,12,28)-$N10)/365.25-Assumptions!$B$20)*Assumptions!$B$19)*Z10),0) -> 18194.302 | CJ10: =AB10+AG10+AL10+AQ10+AV10+BA10+BF10+BK10+BP10+BU10+BZ10+CE10 -> 0 | CK10: =AC10+AH10+AM10+AR10+AW10+BB10+BG10+BL10+BQ10+BV10+CA10+CF10 -> 10925
A11: 7 | B11: ADJTOUTAH | C11: Anissa | D11: Contrat Local | E11: Permanent | F11: Professeur(e) des écoles | G11: Élémentaire | H11: Generaliste | I11: Teacher | J11: Professeur des écoles (PE) | K11: Élémentaire | L11: Existing | M11: =IF(D11="Titulaire EN","",IF(OR(B11="AL OSSAIMI AL OTAIBI",B11="ALAMRI"),"Saudi","Non-Saudi")) -> Non-Saudi | N11: 45901 | O11: 1.3 | P11: 8250 | Q11: 2500 | R11: 500 | U11: 11250 | V11: 1 | W11: Liquide | X11: Nouveau Contrat | Y11: =IF(AND($D11="Contrat Local",$N11<>""),$P11*$V11,0) -> 8250 | Z11: =IF(Y11>0,Y11+($Q11+$R11+IF(ISNUMBER($S11),$S11,0)+IF(ISNUMBER($T11),$T11,0))*$V11,0) -> 11250 | AA11: =IF(AND(Z11>0,$N11<>""),IF((DATE(Assumptions!$B$4,1,28)-$N11)/365.25<=Assumptions!$B$20,(DATE(Assumptions!$B$4,1,28)-$N11)/365.25*Assumptions!$B$18*Z11,(Assumptions!$B$20*Assumptions!$B$18+((DATE(Assumptions!$B$4,1,28)-$N11)/365.25-Assumptions!$B$20)*Assumptions!$B$19)*Z11),0) -> 2294.6612 | AB11: =IF(Y11>0,IF($M11="Saudi",MIN(Y11+$Q11*$V11,Assumptions!$B$14)*Assumptions!$B$12,MIN(Y11+$Q11*$V11,Assumptions!$B$14)*Assumptions!$B$13),0) -> 0 | AC11: =IF(AND(Y11>0,$M11="Non-Saudi"),Assumptions!$B$25,0) -> 910.41667 | AD11: =IF(AND($D11="Contrat Local",$N11<>""),$P11*$V11,0) -> 8250 | AE11: =IF(AD11>0,AD11+($Q11+$R11+IF(ISNUMBER($S11),$S11,0)+IF(ISNUMBER($T11),$T11,0))*$V11,0) -> 11250 | AF11: =IF(AND(AE11>0,$N11<>""),IF((DATE(Assumptions!$B$4,2,28)-$N11)/365.25<=Assumptions!$B$20,(DATE(Assumptions!$B$4,2,28)-$N11)/365.25*Assumptions!$B$18*AE11,(Assumptions!$B$20*Assumptions!$B$18+((DATE(Assumptions!$B$4,2,28)-$N11)/365.25-Assumptions!$B$20)*Assumptions!$B$19)*AE11),0) -> 2772.0739 | AG11: =IF(AD11>0,IF($M11="Saudi",MIN(AD11+$Q11*$V11,Assumptions!$B$14)*Assumptions!$B$12,MIN(AD11+$Q11*$V11,Assumptions!$B$14)*Assumptions!$B$13),0) -> 0 | AH11: =IF(AND(AD11>0,$M11="Non-Saudi"),Assumptions!$B$25,0) -> 910.41667 | AI11: =IF(AND($D11="Contrat Local",$N11<>""),$P11*$V11,0) -> 8250 | AJ11: =IF(AI11>0,AI11+($Q11+$R11+IF(ISNUMBER($S11),$S11,0)+IF(ISNUMBER($T11),$T11,0))*$V11,0) -> 11250 | AK11: =IF(AND(AJ11>0,$N11<>""),IF((DATE(Assumptions!$B$4,3,28)-$N11)/365.25<=Assumptions!$B$20,(DATE(Assumptions!$B$4,3,28)-$N11)/365.25*Assumptions!$B$18*AJ11,(Assumptions!$B$20*Assumptions!$B$18+((DATE(Assumptions!$B$4,3,28)-$N11)/365.25-Assumptions!$B$20)*Assumptions!$B$19)*AJ11),0) -> 3203.2854 | AL11: =IF(AI11>0,IF($M11="Saudi",MIN(AI11+$Q11*$V11,Assumptions!$B$14)*Assumptions!$B$12,MIN(AI11+$Q11*$V11,Assumptions!$B$14)*Assumptions!$B$13),0) -> 0 | AM11: =IF(AND(AI11>0,$M11="Non-Saudi"),Assumptions!$B$25,0) -> 910.41667 | AN11: =IF(AND($D11="Contrat Local",$N11<>""),$P11*$V11,0) -> 8250 | AO11: =IF(AN11>0,AN11+($Q11+$R11+IF(ISNUMBER($S11),$S11,0)+IF(ISNUMBER($T11),$T11,0))*$V11,0) -> 11250 | AP11: =IF(AND(AO11>0,$N11<>""),IF((DATE(Assumptions!$B$4,4,28)-$N11)/365.25<=Assumptions!$B$20,(DATE(Assumptions!$B$4,4,28)-$N11)/365.25*Assumptions!$B$18*AO11,(Assumptions!$B$20*Assumptions!$B$18+((DATE(Assumptions!$B$4,4,28)-$N11)/365.25-Assumptions!$B$20)*Assumptions!$B$19)*AO11),0) -> 3680.6982 | AQ11: =IF(AN11>0,IF($M11="Saudi",MIN(AN11+$Q11*$V11,Assumptions!$B$14)*Assumptions!$B$12,MIN(AN11+$Q11*$V11,Assumptions!$B$14)*Assumptions!$B$13),0) -> 0 | AR11: =IF(AND(AN11>0,$M11="Non-Saudi"),Assumptions!$B$25,0) -> 910.41667 | AS11: =IF(AND($D11="Contrat Local",$N11<>""),$P11*$V11,0) -> 8250 | AT11: =IF(AS11>0,AS11+($Q11+$R11+IF(ISNUMBER($S11),$S11,0)+IF(ISNUMBER($T11),$T11,0))*$V11,0) -> 11250 | AU11: =IF(AND(AT11>0,$N11<>""),IF((DATE(Assumptions!$B$4,5,28)-$N11)/365.25<=Assumptions!$B$20,(DATE(Assumptions!$B$4,5,28)-$N11)/365.25*Assumptions!$B$18*AT11,(Assumptions!$B$20*Assumptions!$B$18+((DATE(Assumptions!$B$4,5,28)-$N11)/365.25-Assumptions!$B$20)*Assumptions!$B$19)*AT11),0) -> 4142.7105 | AV11: =IF(AS11>0,IF($M11="Saudi",MIN(AS11+$Q11*$V11,Assumptions!$B$14)*Assumptions!$B$12,MIN(AS11+$Q11*$V11,Assumptions!$B$14)*Assumptions!$B$13),0) -> 0 | AW11: =IF(AND(AS11>0,$M11="Non-Saudi"),Assumptions!$B$25,0) -> 910.41667 | AX11: =IF(AND($D11="Contrat Local",$N11<>""),$P11*$V11,0) -> 8250 | AY11: =IF(AX11>0,AX11+($Q11+$R11+IF(ISNUMBER($S11),$S11,0)+IF(ISNUMBER($T11),$T11,0))*$V11,0) -> 11250 | AZ11: =IF(AND(AY11>0,$N11<>""),IF((DATE(Assumptions!$B$4,6,28)-$N11)/365.25<=Assumptions!$B$20,(DATE(Assumptions!$B$4,6,28)-$N11)/365.25*Assumptions!$B$18*AY11,(Assumptions!$B$20*Assumptions!$B$18+((DATE(Assumptions!$B$4,6,28)-$N11)/365.25-Assumptions!$B$20)*Assumptions!$B$19)*AY11),0) -> 4620.1232 | BA11: =IF(AX11>0,IF($M11="Saudi",MIN(AX11+$Q11*$V11,Assumptions!$B$14)*Assumptions!$B$12,MIN(AX11+$Q11*$V11,Assumptions!$B$14)*Assumptions!$B$13),0) -> 0 | BB11: =IF(AND(AX11>0,$M11="Non-Saudi"),Assumptions!$B$25,0) -> 910.41667 | BC11: =IF(AND($D11="Contrat Local",$N11<>""),$P11*$V11,0) -> 8250 | BD11: =IF(BC11>0,BC11+($Q11+$R11+IF(ISNUMBER($S11),$S11,0)+IF(ISNUMBER($T11),$T11,0))*$V11,0) -> 11250 | BE11: =IF(AND(BD11>0,$N11<>""),IF((DATE(Assumptions!$B$4,7,28)-$N11)/365.25<=Assumptions!$B$20,(DATE(Assumptions!$B$4,7,28)-$N11)/365.25*Assumptions!$B$18*BD11,(Assumptions!$B$20*Assumptions!$B$18+((DATE(Assumptions!$B$4,7,28)-$N11)/365.25-Assumptions!$B$20)*Assumptions!$B$19)*BD11),0) -> 5082.1355 | BF11: =IF(BC11>0,IF($M11="Saudi",MIN(BC11+$Q11*$V11,Assumptions!$B$14)*Assumptions!$B$12,MIN(BC11+$Q11*$V11,Assumptions!$B$14)*Assumptions!$B$13),0) -> 0 | BG11: =IF(AND(BC11>0,$M11="Non-Saudi"),Assumptions!$B$25,0) -> 910.41667 | BH11: =IF(AND($D11="Contrat Local",$N11<>""),$P11*$V11,0) -> 8250 | BI11: =IF(BH11>0,BH11+($Q11+$R11+IF(ISNUMBER($S11),$S11,0)+IF(ISNUMBER($T11),$T11,0))*$V11,0) -> 11250 | BJ11: =IF(AND(BI11>0,$N11<>""),IF((DATE(Assumptions!$B$4,8,28)-$N11)/365.25<=Assumptions!$B$20,(DATE(Assumptions!$B$4,8,28)-$N11)/365.25*Assumptions!$B$18*BI11,(Assumptions!$B$20*Assumptions!$B$18+((DATE(Assumptions!$B$4,8,28)-$N11)/365.25-Assumptions!$B$20)*Assumptions!$B$19)*BI11),0) -> 5559.5483 | BK11: =IF(BH11>0,IF($M11="Saudi",MIN(BH11+$Q11*$V11,Assumptions!$B$14)*Assumptions!$B$12,MIN(BH11+$Q11*$V11,Assumptions!$B$14)*Assumptions!$B$13),0) -> 0 | BL11: =IF(AND(BH11>0,$M11="Non-Saudi"),Assumptions!$B$25,0) -> 910.41667 | BM11: =IF(AND($D11="Contrat Local",$N11<>""),IF(AND(9>=Assumptions!$B$5,ISNUMBER($X11),$N11<EDATE(Assumptions!$B$9,-Assumptions!$B$6*12)),($P11+$X11)*$V11,$P11*$V11),0) -> 8250 | BN11: =IF(BM11>0,BM11+($Q11+$R11+IF(ISNUMBER($S11),$S11,0)+IF(ISNUMBER($T11),$T11,0))*$V11,0) -> 11250 | BO11: =IF(AND(BN11>0,$N11<>""),IF((DATE(Assumptions!$B$4,9,28)-$N11)/365.25<=Assumptions!$B$20,(DATE(Assumptions!$B$4,9,28)-$N11)/365.25*Assumptions!$B$18*BN11,(Assumptions!$B$20*Assumptions!$B$18+((DATE(Assumptions!$B$4,9,28)-$N11)/365.25-Assumptions!$B$20)*Assumptions!$B$19)*BN11),0) -> 6036.961 | BP11: =IF(BM11>0,IF($M11="Saudi",MIN(BM11+$Q11*$V11,Assumptions!$B$14)*Assumptions!$B$12,MIN(BM11+$Q11*$V11,Assumptions!$B$14)*Assumptions!$B$13),0) -> 0 | BQ11: =IF(AND(BM11>0,$M11="Non-Saudi"),Assumptions!$B$25,0) -> 910.41667 | BR11: =IF(AND($D11="Contrat Local",$N11<>""),IF(AND(10>=Assumptions!$B$5,ISNUMBER($X11),$N11<EDATE(Assumptions!$B$9,-Assumptions!$B$6*12)),($P11+$X11)*$V11,$P11*$V11),0) -> 8250 | BS11: =IF(BR11>0,BR11+($Q11+$R11+IF(ISNUMBER($S11),$S11,0)+IF(ISNUMBER($T11),$T11,0))*$V11,0) -> 11250 | BT11: =IF(AND(BS11>0,$N11<>""),IF((DATE(Assumptions!$B$4,10,28)-$N11)/365.25<=Assumptions!$B$20,(DATE(Assumptions!$B$4,10,28)-$N11)/365.25*Assumptions!$B$18*BS11,(Assumptions!$B$20*Assumptions!$B$18+((DATE(Assumptions!$B$4,10,28)-$N11)/365.25-Assumptions!$B$20)*Assumptions!$B$19)*BS11),0) -> 6498.9733 | BU11: =IF(BR11>0,IF($M11="Saudi",MIN(BR11+$Q11*$V11,Assumptions!$B$14)*Assumptions!$B$12,MIN(BR11+$Q11*$V11,Assumptions!$B$14)*Assumptions!$B$13),0) -> 0 | BV11: =IF(AND(BR11>0,$M11="Non-Saudi"),Assumptions!$B$25,0) -> 910.41667 | BW11: =IF(AND($D11="Contrat Local",$N11<>""),IF(AND(11>=Assumptions!$B$5,ISNUMBER($X11),$N11<EDATE(Assumptions!$B$9,-Assumptions!$B$6*12)),($P11+$X11)*$V11,$P11*$V11),0) -> 8250 | BX11: =IF(BW11>0,BW11+($Q11+$R11+IF(ISNUMBER($S11),$S11,0)+IF(ISNUMBER($T11),$T11,0))*$V11,0) -> 11250 | BY11: =IF(AND(BX11>0,$N11<>""),IF((DATE(Assumptions!$B$4,11,28)-$N11)/365.25<=Assumptions!$B$20,(DATE(Assumptions!$B$4,11,28)-$N11)/365.25*Assumptions!$B$18*BX11,(Assumptions!$B$20*Assumptions!$B$18+((DATE(Assumptions!$B$4,11,28)-$N11)/365.25-Assumptions!$B$20)*Assumptions!$B$19)*BX11),0) -> 6976.386 | BZ11: =IF(BW11>0,IF($M11="Saudi",MIN(BW11+$Q11*$V11,Assumptions!$B$14)*Assumptions!$B$12,MIN(BW11+$Q11*$V11,Assumptions!$B$14)*Assumptions!$B$13),0) -> 0 | CA11: =IF(AND(BW11>0,$M11="Non-Saudi"),Assumptions!$B$25,0) -> 910.41667 | CB11: =IF(AND($D11="Contrat Local",$N11<>""),IF(AND(12>=Assumptions!$B$5,ISNUMBER($X11),$N11<EDATE(Assumptions!$B$9,-Assumptions!$B$6*12)),($P11+$X11)*$V11,$P11*$V11),0) -> 8250 | CC11: =IF(CB11>0,CB11+($Q11+$R11+IF(ISNUMBER($S11),$S11,0)+IF(ISNUMBER($T11),$T11,0))*$V11,0) -> 11250 | CD11: =IF(AND(CC11>0,$N11<>""),IF((DATE(Assumptions!$B$4,12,28)-$N11)/365.25<=Assumptions!$B$20,(DATE(Assumptions!$B$4,12,28)-$N11)/365.25*Assumptions!$B$18*CC11,(Assumptions!$B$20*Assumptions!$B$18+((DATE(Assumptions!$B$4,12,28)-$N11)/365.25-Assumptions!$B$20)*Assumptions!$B$19)*CC11),0) -> 7438.3984 | CE11: =IF(CB11>0,IF($M11="Saudi",MIN(CB11+$Q11*$V11,Assumptions!$B$14)*Assumptions!$B$12,MIN(CB11+$Q11*$V11,Assumptions!$B$14)*Assumptions!$B$13),0) -> 0 | CF11: =IF(AND(CB11>0,$M11="Non-Saudi"),Assumptions!$B$25,0) -> 910.41667 | CG11: =Y11+AD11+AI11+AN11+AS11+AX11+BC11+BH11+BM11+BR11+BW11+CB11 -> 99000 | CH11: =Z11+AE11+AJ11+AO11+AT11+AY11+BD11+BI11+BN11+BS11+BX11+CC11 -> 135000 | CI11: =CD11-IF(AND(Z11>0,$N11<>""),IF((DATE(Assumptions!$B$4-1,12,28)-$N11)/365.25<=Assumptions!$B$20,(DATE(Assumptions!$B$4-1,12,28)-$N11)/365.25*Assumptions!$B$18*Z11,(Assumptions!$B$20*Assumptions!$B$18+((DATE(Assumptions!$B$4-1,12,28)-$N11)/365.25-Assumptions!$B$20)*Assumptions!$B$19)*Z11),0) -> 5621.1499 | CJ11: =AB11+AG11+AL11+AQ11+AV11+BA11+BF11+BK11+BP11+BU11+BZ11+CE11 -> 0 | CK11: =AC11+AH11+AM11+AR11+AW11+BB11+BG11+BL11+BQ11+BV11+CA11+CF11 -> 10925
A12: 8 | B12: AHYOUD | C12: Hanan | D12: Contrat Local | E12: Permanent | F12: Professeur(e) des écoles | G12: Élémentaire | H12: Generaliste | I12: Teacher | J12: Professeur des écoles (PE) | K12: Maternelle | L12: Existing | M12: =IF(D12="Titulaire EN","",IF(OR(B12="AL OSSAIMI AL OTAIBI",B12="ALAMRI"),"Saudi","Non-Saudi")) -> Non-Saudi | N12: 42614 | O12: 10.3 | P12: 10250 | Q12: 2500 | R12: 500 | U12: 13250 | V12: 1 | W12: Virement | X12: 250 | Y12: =IF(AND($D12="Contrat Local",$N12<>""),$P12*$V12,0) -> 10250 | Z12: =IF(Y12>0,Y12+($Q12+$R12+IF(ISNUMBER($S12),$S12,0)+IF(ISNUMBER($T12),$T12,0))*$V12,0) -> 13250 | AA12: =IF(AND(Z12>0,$N12<>""),IF((DATE(Assumptions!$B$4,1,28)-$N12)/365.25<=Assumptions!$B$20,(DATE(Assumptions!$B$4,1,28)-$N12)/365.25*Assumptions!$B$18*Z12,(Assumptions!$B$20*Assumptions!$B$18+((DATE(Assumptions!$B$4,1,28)-$N12)/365.25-Assumptions!$B$20)*Assumptions!$B$19)*Z12),0) -> 91521.133 | AB12: =IF(Y12>0,IF($M12="Saudi",MIN(Y12+$Q12*$V12,Assumptions!$B$14)*Assumptions!$B$12,MIN(Y12+$Q12*$V12,Assumptions!$B$14)*Assumptions!$B$13),0) -> 0 | AC12: =IF(AND(Y12>0,$M12="Non-Saudi"),Assumptions!$B$25,0) -> 910.41667 | AD12: =IF(AND($D12="Contrat Local",$N12<>""),$P12*$V12,0) -> 10250 | AE12: =IF(AD12>0,AD12+($Q12+$R12+IF(ISNUMBER($S12),$S12,0)+IF(ISNUMBER($T12),$T12,0))*$V12,0) -> 13250 | AF12: =IF(AND(AE12>0,$N12<>""),IF((DATE(Assumptions!$B$4,2,28)-$N12)/365.25<=Assumptions!$B$20,(DATE(Assumptions!$B$4,2,28)-$N12)/365.25*Assumptions!$B$18*AE12,(Assumptions!$B$20*Assumptions!$B$18+((DATE(Assumptions!$B$4,2,28)-$N12)/365.25-Assumptions!$B$20)*Assumptions!$B$19)*AE12),0) -> 92645.705 | AG12: =IF(AD12>0,IF($M12="Saudi",MIN(AD12+$Q12*$V12,Assumptions!$B$14)*Assumptions!$B$12,MIN(AD12+$Q12*$V12,Assumptions!$B$14)*Assumptions!$B$13),0) -> 0 | AH12: =IF(AND(AD12>0,$M12="Non-Saudi"),Assumptions!$B$25,0) -> 910.41667 | AI12: =IF(AND($D12="Contrat Local",$N12<>""),$P12*$V12,0) -> 10250 | AJ12: =IF(AI12>0,AI12+($Q12+$R12+IF(ISNUMBER($S12),$S12,0)+IF(ISNUMBER($T12),$T12,0))*$V12,0) -> 13250 | AK12: =IF(AND(AJ12>0,$N12<>""),IF((DATE(Assumptions!$B$4,3,28)-$N12)/365.25<=Assumptions!$B$20,(DATE(Assumptions!$B$4,3,28)-$N12)/365.25*Assumptions!$B$18*AJ12,(Assumptions!$B$20*Assumptions!$B$18+((DATE(Assumptions!$B$4,3,28)-$N12)/365.25-Assumptions!$B$20)*Assumptions!$B$19)*AJ12),0) -> 93661.448 | AL12: =IF(AI12>0,IF($M12="Saudi",MIN(AI12+$Q12*$V12,Assumptions!$B$14)*Assumptions!$B$12,MIN(AI12+$Q12*$V12,Assumptions!$B$14)*Assumptions!$B$13),0) -> 0 | AM12: =IF(AND(AI12>0,$M12="Non-Saudi"),Assumptions!$B$25,0) -> 910.41667 | AN12: =IF(AND($D12="Contrat Local",$N12<>""),$P12*$V12,0) -> 10250 | AO12: =IF(AN12>0,AN12+($Q12+$R12+IF(ISNUMBER($S12),$S12,0)+IF(ISNUMBER($T12),$T12,0))*$V12,0) -> 13250 | AP12: =IF(AND(AO12>0,$N12<>""),IF((DATE(Assumptions!$B$4,4,28)-$N12)/365.25<=Assumptions!$B$20,(DATE(Assumptions!$B$4,4,28)-$N12)/365.25*Assumptions!$B$18*AO12,(Assumptions!$B$20*Assumptions!$B$18+((DATE(Assumptions!$B$4,4,28)-$N12)/365.25-Assumptions!$B$20)*Assumptions!$B$19)*AO12),0) -> 94786.02 | AQ12: =IF(AN12>0,IF($M12="Saudi",MIN(AN12+$Q12*$V12,Assumptions!$B$14)*Assumptions!$B$12,MIN(AN12+$Q12*$V12,Assumptions!$B$14)*Assumptions!$B$13),0) -> 0 | AR12: =IF(AND(AN12>0,$M12="Non-Saudi"),Assumptions!$B$25,0) -> 910.41667 | AS12: =IF(AND($D12="Contrat Local",$N12<>""),$P12*$V12,0) -> 10250 | AT12: =IF(AS12>0,AS12+($Q12+$R12+IF(ISNUMBER($S12),$S12,0)+IF(ISNUMBER($T12),$T12,0))*$V12,0) -> 13250 | AU12: =IF(AND(AT12>0,$N12<>""),IF((DATE(Assumptions!$B$4,5,28)-$N12)/365.25<=Assumptions!$B$20,(DATE(Assumptions!$B$4,5,28)-$N12)/365.25*Assumptions!$B$18*AT12,(Assumptions!$B$20*Assumptions!$B$18+((DATE(Assumptions!$B$4,5,28)-$N12)/365.25-Assumptions!$B$20)*Assumptions!$B$19)*AT12),0) -> 95874.316 | AV12: =IF(AS12>0,IF($M12="Saudi",MIN(AS12+$Q12*$V12,Assumptions!$B$14)*Assumptions!$B$12,MIN(AS12+$Q12*$V12,Assumptions!$B$14)*Assumptions!$B$13),0) -> 0 | AW12: =IF(AND(AS12>0,$M12="Non-Saudi"),Assumptions!$B$25,0) -> 910.41667 | AX12: =IF(AND($D12="Contrat Local",$N12<>""),$P12*$V12,0) -> 10250 | AY12: =IF(AX12>0,AX12+($Q12+$R12+IF(ISNUMBER($S12),$S12,0)+IF(ISNUMBER($T12),$T12,0))*$V12,0) -> 13250 | AZ12: =IF(AND(AY12>0,$N12<>""),IF((DATE(Assumptions!$B$4,6,28)-$N12)/365.25<=Assumptions!$B$20,(DATE(Assumptions!$B$4,6,28)-$N12)/365.25*Assumptions!$B$18*AY12,(Assumptions!$B$20*Assumptions!$B$18+((DATE(Assumptions!$B$4,6,28)-$N12)/365.25-Assumptions!$B$20)*Assumptions!$B$19)*AY12),0) -> 96998.888 | BA12: =IF(AX12>0,IF($M12="Saudi",MIN(AX12+$Q12*$V12,Assumptions!$B$14)*Assumptions!$B$12,MIN(AX12+$Q12*$V12,Assumptions!$B$14)*Assumptions!$B$13),0) -> 0 | BB12: =IF(AND(AX12>0,$M12="Non-Saudi"),Assumptions!$B$25,0) -> 910.41667 | BC12: =IF(AND($D12="Contrat Local",$N12<>""),$P12*$V12,0) -> 10250 | BD12: =IF(BC12>0,BC12+($Q12+$R12+IF(ISNUMBER($S12),$S12,0)+IF(ISNUMBER($T12),$T12,0))*$V12,0) -> 13250 | BE12: =IF(AND(BD12>0,$N12<>""),IF((DATE(Assumptions!$B$4,7,28)-$N12)/365.25<=Assumptions!$B$20,(DATE(Assumptions!$B$4,7,28)-$N12)/365.25*Assumptions!$B$18*BD12,(Assumptions!$B$20*Assumptions!$B$18+((DATE(Assumptions!$B$4,7,28)-$N12)/365.25-Assumptions!$B$20)*Assumptions!$B$19)*BD12),0) -> 98087.183 | BF12: =IF(BC12>0,IF($M12="Saudi",MIN(BC12+$Q12*$V12,Assumptions!$B$14)*Assumptions!$B$12,MIN(BC12+$Q12*$V12,Assumptions!$B$14)*Assumptions!$B$13),0) -> 0 | BG12: =IF(AND(BC12>0,$M12="Non-Saudi"),Assumptions!$B$25,0) -> 910.41667 | BH12: =IF(AND($D12="Contrat Local",$N12<>""),$P12*$V12,0) -> 10250 | BI12: =IF(BH12>0,BH12+($Q12+$R12+IF(ISNUMBER($S12),$S12,0)+IF(ISNUMBER($T12),$T12,0))*$V12,0) -> 13250 | BJ12: =IF(AND(BI12>0,$N12<>""),IF((DATE(Assumptions!$B$4,8,28)-$N12)/365.25<=Assumptions!$B$20,(DATE(Assumptions!$B$4,8,28)-$N12)/365.25*Assumptions!$B$18*BI12,(Assumptions!$B$20*Assumptions!$B$18+((DATE(Assumptions!$B$4,8,28)-$N12)/365.25-Assumptions!$B$20)*Assumptions!$B$19)*BI12),0) -> 99211.756 | BK12: =IF(BH12>0,IF($M12="Saudi",MIN(BH12+$Q12*$V12,Assumptions!$B$14)*Assumptions!$B$12,MIN(BH12+$Q12*$V12,Assumptions!$B$14)*Assumptions!$B$13),0) -> 0 | BL12: =IF(AND(BH12>0,$M12="Non-Saudi"),Assumptions!$B$25,0) -> 910.41667 | BM12: =IF(AND($D12="Contrat Local",$N12<>""),IF(AND(9>=Assumptions!$B$5,ISNUMBER($X12),$N12<EDATE(Assumptions!$B$9,-Assumptions!$B$6*12)),($P12+$X12)*$V12,$P12*$V12),0) -> 10500 | BN12: =IF(BM12>0,BM12+($Q12+$R12+IF(ISNUMBER($S12),$S12,0)+IF(ISNUMBER($T12),$T12,0))*$V12,0) -> 13500 | BO12: =IF(AND(BN12>0,$N12<>""),IF((DATE(Assumptions!$B$4,9,28)-$N12)/365.25<=Assumptions!$B$20,(DATE(Assumptions!$B$4,9,28)-$N12)/365.25*Assumptions!$B$18*BN12,(Assumptions!$B$20*Assumptions!$B$18+((DATE(Assumptions!$B$4,9,28)-$N12)/365.25-Assumptions!$B$20)*Assumptions!$B$19)*BN12),0) -> 102229.47 | BP12: =IF(BM12>0,IF($M12="Saudi",MIN(BM12+$Q12*$V12,Assumptions!$B$14)*Assumptions!$B$12,MIN(BM12+$Q12*$V12,Assumptions!$B$14)*Assumptions!$B$13),0) -> 0 | BQ12: =IF(AND(BM12>0,$M12="Non-Saudi"),Assumptions!$B$25,0) -> 910.41667 | BR12: =IF(AND($D12="Contrat Local",$N12<>""),IF(AND(10>=Assumptions!$B$5,ISNUMBER($X12),$N12<EDATE(Assumptions!$B$9,-Assumptions!$B$6*12)),($P12+$X12)*$V12,$P12*$V12),0) -> 10500 | BS12: =IF(BR12>0,BR12+($Q12+$R12+IF(ISNUMBER($S12),$S12,0)+IF(ISNUMBER($T12),$T12,0))*$V12,0) -> 13500 | BT12: =IF(AND(BS12>0,$N12<>""),IF((DATE(Assumptions!$B$4,10,28)-$N12)/365.25<=Assumptions!$B$20,(DATE(Assumptions!$B$4,10,28)-$N12)/365.25*Assumptions!$B$18*BS12,(Assumptions!$B$20*Assumptions!$B$18+((DATE(Assumptions!$B$4,10,28)-$N12)/365.25-Assumptions!$B$20)*Assumptions!$B$19)*BS12),0) -> 103338.3 | BU12: =IF(BR12>0,IF($M12="Saudi",MIN(BR12+$Q12*$V12,Assumptions!$B$14)*Assumptions!$B$12,MIN(BR12+$Q12*$V12,Assumptions!$B$14)*Assumptions!$B$13),0) -> 0 | BV12: =IF(AND(BR12>0,$M12="Non-Saudi"),Assumptions!$B$25,0) -> 910.41667 | BW12: =IF(AND($D12="Contrat Local",$N12<>""),IF(AND(11>=Assumptions!$B$5,ISNUMBER($X12),$N12<EDATE(Assumptions!$B$9,-Assumptions!$B$6*12)),($P12+$X12)*$V12,$P12*$V12),0) -> 10500 | BX12: =IF(BW12>0,BW12+($Q12+$R12+IF(ISNUMBER($S12),$S12,0)+IF(ISNUMBER($T12),$T12,0))*$V12,0) -> 13500 | BY12: =IF(AND(BX12>0,$N12<>""),IF((DATE(Assumptions!$B$4,11,28)-$N12)/365.25<=Assumptions!$B$20,(DATE(Assumptions!$B$4,11,28)-$N12)/365.25*Assumptions!$B$18*BX12,(Assumptions!$B$20*Assumptions!$B$18+((DATE(Assumptions!$B$4,11,28)-$N12)/365.25-Assumptions!$B$20)*Assumptions!$B$19)*BX12),0) -> 104484.09 | BZ12: =IF(BW12>0,IF($M12="Saudi",MIN(BW12+$Q12*$V12,Assumptions!$B$14)*Assumptions!$B$12,MIN(BW12+$Q12*$V12,Assumptions!$B$14)*Assumptions!$B$13),0) -> 0 | CA12: =IF(AND(BW12>0,$M12="Non-Saudi"),Assumptions!$B$25,0) -> 910.41667 | CB12: =IF(AND($D12="Contrat Local",$N12<>""),IF(AND(12>=Assumptions!$B$5,ISNUMBER($X12),$N12<EDATE(Assumptions!$B$9,-Assumptions!$B$6*12)),($P12+$X12)*$V12,$P12*$V12),0) -> 10500 | CC12: =IF(CB12>0,CB12+($Q12+$R12+IF(ISNUMBER($S12),$S12,0)+IF(ISNUMBER($T12),$T12,0))*$V12,0) -> 13500 | CD12: =IF(AND(CC12>0,$N12<>""),IF((DATE(Assumptions!$B$4,12,28)-$N12)/365.25<=Assumptions!$B$20,(DATE(Assumptions!$B$4,12,28)-$N12)/365.25*Assumptions!$B$18*CC12,(Assumptions!$B$20*Assumptions!$B$18+((DATE(Assumptions!$B$4,12,28)-$N12)/365.25-Assumptions!$B$20)*Assumptions!$B$19)*CC12),0) -> 105592.92 | CE12: =IF(CB12>0,IF($M12="Saudi",MIN(CB12+$Q12*$V12,Assumptions!$B$14)*Assumptions!$B$12,MIN(CB12+$Q12*$V12,Assumptions!$B$14)*Assumptions!$B$13),0) -> 0 | CF12: =IF(AND(CB12>0,$M12="Non-Saudi"),Assumptions!$B$25,0) -> 910.41667 | CG12: =Y12+AD12+AI12+AN12+AS12+AX12+BC12+BH12+BM12+BR12+BW12+CB12 -> 124000 | CH12: =Z12+AE12+AJ12+AO12+AT12+AY12+BD12+BI12+BN12+BS12+BX12+CC12 -> 160000 | CI12: =CD12-IF(AND(Z12>0,$N12<>""),IF((DATE(Assumptions!$B$4-1,12,28)-$N12)/365.25<=Assumptions!$B$20,(DATE(Assumptions!$B$4-1,12,28)-$N12)/365.25*Assumptions!$B$18*Z12,(Assumptions!$B$20*Assumptions!$B$18+((DATE(Assumptions!$B$4-1,12,28)-$N12)/365.25-Assumptions!$B$20)*Assumptions!$B$19)*Z12),0) -> 15196.355 | CJ12: =AB12+AG12+AL12+AQ12+AV12+BA12+BF12+BK12+BP12+BU12+BZ12+CE12 -> 0 | CK12: =AC12+AH12+AM12+AR12+AW12+BB12+BG12+BL12+BQ12+BV12+CA12+CF12 -> 10925
A13: 9 | B13: AL JUNDI | C13: Tamara | D13: Contrat Local | E13: Permanent | F13: Enseignant de langue étrangère | G13: Élémentaire | H13: Arabe | I13: Teacher | J13: Enseignant Arabe | K13: Primaire | L13: Existing | M13: =IF(D13="Titulaire EN","",IF(OR(B13="AL OSSAIMI AL OTAIBI",B13="ALAMRI"),"Saudi","Non-Saudi")) -> Non-Saudi | N13: 35309 | O13: 30.3 | P13: 9750 | Q13: 2500 | R13: 500 | T13: 1140 | U13: 13890 | V13: 1 | W13: Virement | X13: 250 | Y13: =IF(AND($D13="Contrat Local",$N13<>""),$P13*$V13,0) -> 9750 | Z13: =IF(Y13>0,Y13+($Q13+$R13+IF(ISNUMBER($S13),$S13,0)+IF(ISNUMBER($T13),$T13,0))*$V13,0) -> 13890 | AA13: =IF(AND(Z13>0,$N13<>""),IF((DATE(Assumptions!$B$4,1,28)-$N13)/365.25<=Assumptions!$B$20,(DATE(Assumptions!$B$4,1,28)-$N13)/365.25*Assumptions!$B$18*Z13,(Assumptions!$B$20*Assumptions!$B$18+((DATE(Assumptions!$B$4,1,28)-$N13)/365.25-Assumptions!$B$20)*Assumptions!$B$19)*Z13),0) -> 373741.78 | AB13: =IF(Y13>0,IF($M13="Saudi",MIN(Y13+$Q13*$V13,Assumptions!$B$14)*Assumptions!$B$12,MIN(Y13+$Q13*$V13,Assumptions!$B$14)*Assumptions!$B$13),0) -> 0 | AC13: =IF(AND(Y13>0,$M13="Non-Saudi"),Assumptions!$B$25,0) -> 910.41667 | AD13: =IF(AND($D13="Contrat Local",$N13<>""),$P13*$V13,0) -> 9750 | AE13: =IF(AD13>0,AD13+($Q13+$R13+IF(ISNUMBER($S13),$S13,0)+IF(ISNUMBER($T13),$T13,0))*$V13,0) -> 13890 | AF13: =IF(AND(AE13>0,$N13<>""),IF((DATE(Assumptions!$B$4,2,28)-$N13)/365.25<=Assumptions!$B$20,(DATE(Assumptions!$B$4,2,28)-$N13)/365.25*Assumptions!$B$18*AE13,(Assumptions!$B$20*Assumptions!$B$18+((DATE(Assumptions!$B$4,2,28)-$N13)/365.25-Assumptions!$B$20)*Assumptions!$B$19)*AE13),0) -> 374920.67 | AG13: =IF(AD13>0,IF($M13="Saudi",MIN(AD13+$Q13*$V13,Assumptions!$B$14)*Assumptions!$B$12,MIN(AD13+$Q13*$V13,Assumptions!$B$14)*Assumptions!$B$13),0) -> 0 | AH13: =IF(AND(AD13>0,$M13="Non-Saudi"),Assumptions!$B$25,0) -> 910.41667 | AI13: =IF(AND($D13="Contrat Local",$N13<>""),$P13*$V13,0) -> 9750 | AJ13: =IF(AI13>0,AI13+($Q13+$R13+IF(ISNUMBER($S13),$S13,0)+IF(ISNUMBER($T13),$T13,0))*$V13,0) -> 13890 | AK13: =IF(AND(AJ13>0,$N13<>""),IF((DATE(Assumptions!$B$4,3,28)-$N13)/365.25<=Assumptions!$B$20,(DATE(Assumptions!$B$4,3,28)-$N13)/365.25*Assumptions!$B$18*AJ13,(Assumptions!$B$20*Assumptions!$B$18+((DATE(Assumptions!$B$4,3,28)-$N13)/365.25-Assumptions!$B$20)*Assumptions!$B$19)*AJ13),0) -> 375985.47 | AL13: =IF(AI13>0,IF($M13="Saudi",MIN(AI13+$Q13*$V13,Assumptions!$B$14)*Assumptions!$B$12,MIN(AI13+$Q13*$V13,Assumptions!$B$14)*Assumptions!$B$13),0) -> 0 | AM13: =IF(AND(AI13>0,$M13="Non-Saudi"),Assumptions!$B$25,0) -> 910.41667 | AN13: =IF(AND($D13="Contrat Local",$N13<>""),$P13*$V13,0) -> 9750 | AO13: =IF(AN13>0,AN13+($Q13+$R13+IF(ISNUMBER($S13),$S13,0)+IF(ISNUMBER($T13),$T13,0))*$V13,0) -> 13890 | AP13: =IF(AND(AO13>0,$N13<>""),IF((DATE(Assumptions!$B$4,4,28)-$N13)/365.25<=Assumptions!$B$20,(DATE(Assumptions!$B$4,4,28)-$N13)/365.25*Assumptions!$B$18*AO13,(Assumptions!$B$20*Assumptions!$B$18+((DATE(Assumptions!$B$4,4,28)-$N13)/365.25-Assumptions!$B$20)*Assumptions!$B$19)*AO13),0) -> 377164.36 | AQ13: =IF(AN13>0,IF($M13="Saudi",MIN(AN13+$Q13*$V13,Assumptions!$B$14)*Assumptions!$B$12,MIN(AN13+$Q13*$V13,Assumptions!$B$14)*Assumptions!$B$13),0) -> 0 | AR13: =IF(AND(AN13>0,$M13="Non-Saudi"),Assumptions!$B$25,0) -> 910.41667 | AS13: =IF(AND($D13="Contrat Local",$N13<>""),$P13*$V13,0) -> 9750 | AT13: =IF(AS13>0,AS13+($Q13+$R13+IF(ISNUMBER($S13),$S13,0)+IF(ISNUMBER($T13),$T13,0))*$V13,0) -> 13890 | AU13: =IF(AND(AT13>0,$N13<>""),IF((DATE(Assumptions!$B$4,5,28)-$N13)/365.25<=Assumptions!$B$20,(DATE(Assumptions!$B$4,5,28)-$N13)/365.25*Assumptions!$B$18*AT13,(Assumptions!$B$20*Assumptions!$B$18+((DATE(Assumptions!$B$4,5,28)-$N13)/365.25-Assumptions!$B$20)*Assumptions!$B$19)*AT13),0) -> 378305.23 | AV13: =IF(AS13>0,IF($M13="Saudi",MIN(AS13+$Q13*$V13,Assumptions!$B$14)*Assumptions!$B$12,MIN(AS13+$Q13*$V13,Assumptions!$B$14)*Assumptions!$B$13),0) -> 0 | AW13: =IF(AND(AS13>0,$M13="Non-Saudi"),Assumptions!$B$25,0) -> 910.41667 | AX13: =IF(AND($D13="Contrat Local",$N13<>""),$P13*$V13,0) -> 9750 | AY13: =IF(AX13>0,AX13+($Q13+$R13+IF(ISNUMBER($S13),$S13,0)+IF(ISNUMBER($T13),$T13,0))*$V13,0) -> 13890 | AZ13: =IF(AND(AY13>0,$N13<>""),IF((DATE(Assumptions!$B$4,6,28)-$N13)/365.25<=Assumptions!$B$20,(DATE(Assumptions!$B$4,6,28)-$N13)/365.25*Assumptions!$B$18*AY13,(Assumptions!$B$20*Assumptions!$B$18+((DATE(Assumptions!$B$4,6,28)-$N13)/365.25-Assumptions!$B$20)*Assumptions!$B$19)*AY13),0) -> 379484.12 | BA13: =IF(AX13>0,IF($M13="Saudi",MIN(AX13+$Q13*$V13,Assumptions!$B$14)*Assumptions!$B$12,MIN(AX13+$Q13*$V13,Assumptions!$B$14)*Assumptions!$B$13),0) -> 0 | BB13: =IF(AND(AX13>0,$M13="Non-Saudi"),Assumptions!$B$25,0) -> 910.41667 | BC13: =IF(AND($D13="Contrat Local",$N13<>""),$P13*$V13,0) -> 9750 | BD13: =IF(BC13>0,BC13+($Q13+$R13+IF(ISNUMBER($S13),$S13,0)+IF(ISNUMBER($T13),$T13,0))*$V13,0) -> 13890 | BE13: =IF(AND(BD13>0,$N13<>""),IF((DATE(Assumptions!$B$4,7,28)-$N13)/365.25<=Assumptions!$B$20,(DATE(Assumptions!$B$4,7,28)-$N13)/365.25*Assumptions!$B$18*BD13,(Assumptions!$B$20*Assumptions!$B$18+((DATE(Assumptions!$B$4,7,28)-$N13)/365.25-Assumptions!$B$20)*Assumptions!$B$19)*BD13),0) -> 380624.98 | BF13: =IF(BC13>0,IF($M13="Saudi",MIN(BC13+$Q13*$V13,Assumptions!$B$14)*Assumptions!$B$12,MIN(BC13+$Q13*$V13,Assumptions!$B$14)*Assumptions!$B$13),0) -> 0 | BG13: =IF(AND(BC13>0,$M13="Non-Saudi"),Assumptions!$B$25,0) -> 910.41667 | BH13: =IF(AND($D13="Contrat Local",$N13<>""),$P13*$V13,0) -> 9750 | BI13: =IF(BH13>0,BH13+($Q13+$R13+IF(ISNUMBER($S13),$S13,0)+IF(ISNUMBER($T13),$T13,0))*$V13,0) -> 13890 | BJ13: =IF(AND(BI13>0,$N13<>""),IF((DATE(Assumptions!$B$4,8,28)-$N13)/365.25<=Assumptions!$B$20,(DATE(Assumptions!$B$4,8,28)-$N13)/365.25*Assumptions!$B$18*BI13,(Assumptions!$B$20*Assumptions!$B$18+((DATE(Assumptions!$B$4,8,28)-$N13)/365.25-Assumptions!$B$20)*Assumptions!$B$19)*BI13),0) -> 381803.87 | BK13: =IF(BH13>0,IF($M13="Saudi",MIN(BH13+$Q13*$V13,Assumptions!$B$14)*Assumptions!$B$12,MIN(BH13+$Q13*$V13,Assumptions!$B$14)*Assumptions!$B$13),0) -> 0 | BL13: =IF(AND(BH13>0,$M13="Non-Saudi"),Assumptions!$B$25,0) -> 910.41667 | BM13: =IF(AND($D13="Contrat Local",$N13<>""),IF(AND(9>=Assumptions!$B$5,ISNUMBER($X13),$N13<EDATE(Assumptions!$B$9,-Assumptions!$B$6*12)),($P13+$X13)*$V13,$P13*$V13),0) -> 10000 | BN13: =IF(BM13>0,BM13+($Q13+$R13+IF(ISNUMBER($S13),$S13,0)+IF(ISNUMBER($T13),$T13,0))*$V13,0) -> 14140 | BO13: =IF(AND(BN13>0,$N13<>""),IF((DATE(Assumptions!$B$4,9,28)-$N13)/365.25<=Assumptions!$B$20,(DATE(Assumptions!$B$4,9,28)-$N13)/365.25*Assumptions!$B$18*BN13,(Assumptions!$B$20*Assumptions!$B$18+((DATE(Assumptions!$B$4,9,28)-$N13)/365.25-Assumptions!$B$20)*Assumptions!$B$19)*BN13),0) -> 389875.9 | BP13: =IF(BM13>0,IF($M13="Saudi",MIN(BM13+$Q13*$V13,Assumptions!$B$14)*Assumptions!$B$12,MIN(BM13+$Q13*$V13,Assumptions!$B$14)*Assumptions!$B$13),0) -> 0 | BQ13: =IF(AND(BM13>0,$M13="Non-Saudi"),Assumptions!$B$25,0) -> 910.41667 | BR13: =IF(AND($D13="Contrat Local",$N13<>""),IF(AND(10>=Assumptions!$B$5,ISNUMBER($X13),$N13<EDATE(Assumptions!$B$9,-Assumptions!$B$6*12)),($P13+$X13)*$V13,$P13*$V13),0) -> 10000 | BS13: =IF(BR13>0,BR13+($Q13+$R13+IF(ISNUMBER($S13),$S13,0)+IF(ISNUMBER($T13),$T13,0))*$V13,0) -> 14140 | BT13: =IF(AND(BS13>0,$N13<>""),IF((DATE(Assumptions!$B$4,10,28)-$N13)/365.25<=Assumptions!$B$20,(DATE(Assumptions!$B$4,10,28)-$N13)/365.25*Assumptions!$B$18*BS13,(Assumptions!$B$20*Assumptions!$B$18+((DATE(Assumptions!$B$4,10,28)-$N13)/365.25-Assumptions!$B$20)*Assumptions!$B$19)*BS13),0) -> 391037.3 | BU13: =IF(BR13>0,IF($M13="Saudi",MIN(BR13+$Q13*$V13,Assumptions!$B$14)*Assumptions!$B$12,MIN(BR13+$Q13*$V13,Assumptions!$B$14)*Assumptions!$B$13),0) -> 0 | BV13: =IF(AND(BR13>0,$M13="Non-Saudi"),Assumptions!$B$25,0) -> 910.41667 | BW13: =IF(AND($D13="Contrat Local",$N13<>""),IF(AND(11>=Assumptions!$B$5,ISNUMBER($X13),$N13<EDATE(Assumptions!$B$9,-Assumptions!$B$6*12)),($P13+$X13)*$V13,$P13*$V13),0) -> 10000 | BX13: =IF(BW13>0,BW13+($Q13+$R13+IF(ISNUMBER($S13),$S13,0)+IF(ISNUMBER($T13),$T13,0))*$V13,0) -> 14140 | BY13: =IF(AND(BX13>0,$N13<>""),IF((DATE(Assumptions!$B$4,11,28)-$N13)/365.25<=Assumptions!$B$20,(DATE(Assumptions!$B$4,11,28)-$N13)/365.25*Assumptions!$B$18*BX13,(Assumptions!$B$20*Assumptions!$B$18+((DATE(Assumptions!$B$4,11,28)-$N13)/365.25-Assumptions!$B$20)*Assumptions!$B$19)*BX13),0) -> 392237.41 | BZ13: =IF(BW13>0,IF($M13="Saudi",MIN(BW13+$Q13*$V13,Assumptions!$B$14)*Assumptions!$B$12,MIN(BW13+$Q13*$V13,Assumptions!$B$14)*Assumptions!$B$13),0) -> 0 | CA13: =IF(AND(BW13>0,$M13="Non-Saudi"),Assumptions!$B$25,0) -> 910.41667 | CB13: =IF(AND($D13="Contrat Local",$N13<>""),IF(AND(12>=Assumptions!$B$5,ISNUMBER($X13),$N13<EDATE(Assumptions!$B$9,-Assumptions!$B$6*12)),($P13+$X13)*$V13,$P13*$V13),0) -> 10000 | CC13: =IF(CB13>0,CB13+($Q13+$R13+IF(ISNUMBER($S13),$S13,0)+IF(ISNUMBER($T13),$T13,0))*$V13,0) -> 14140 | CD13: =IF(AND(CC13>0,$N13<>""),IF((DATE(Assumptions!$B$4,12,28)-$N13)/365.25<=Assumptions!$B$20,(DATE(Assumptions!$B$4,12,28)-$N13)/365.25*Assumptions!$B$18*CC13,(Assumptions!$B$20*Assumptions!$B$18+((DATE(Assumptions!$B$4,12,28)-$N13)/365.25-Assumptions!$B$20)*Assumptions!$B$19)*CC13),0) -> 393398.8 | CE13: =IF(CB13>0,IF($M13="Saudi",MIN(CB13+$Q13*$V13,Assumptions!$B$14)*Assumptions!$B$12,MIN(CB13+$Q13*$V13,Assumptions!$B$14)*Assumptions!$B$13),0) -> 0 | CF13: =IF(AND(CB13>0,$M13="Non-Saudi"),Assumptions!$B$25,0) -> 910.41667 | CG13: =Y13+AD13+AI13+AN13+AS13+AX13+BC13+BH13+BM13+BR13+BW13+CB13 -> 118000 | CH13: =Z13+AE13+AJ13+AO13+AT13+AY13+BD13+BI13+BN13+BS13+BX13+CC13 -> 167680 | CI13: =CD13-IF(AND(Z13>0,$N13<>""),IF((DATE(Assumptions!$B$4-1,12,28)-$N13)/365.25<=Assumptions!$B$20,(DATE(Assumptions!$B$4-1,12,28)-$N13)/365.25*Assumptions!$B$18*Z13,(Assumptions!$B$20*Assumptions!$B$18+((DATE(Assumptions!$B$4-1,12,28)-$N13)/365.25-Assumptions!$B$20)*Assumptions!$B$19)*Z13),0) -> 20835.917 | CJ13: =AB13+AG13+AL13+AQ13+AV13+BA13+BF13+BK13+BP13+BU13+BZ13+CE13 -> 0 | CK13: =AC13+AH13+AM13+AR13+AW13+BB13+BG13+BL13+BQ13+BV13+CA13+CF13 -> 10925
A14: 10 | B14: AL NAHED | C14: Saliha | D14: Contrat Local | E14: Permanent | F14: Professeur(e) des écoles | G14: Élémentaire | H14: Generaliste | I14: Teacher | J14: Professeur des écoles (PE) | K14: Élémentaire | L14: Existing | M14: =IF(D14="Titulaire EN","",IF(OR(B14="AL OSSAIMI AL OTAIBI",B14="ALAMRI"),"Saudi","Non-Saudi")) -> Non-Saudi | N14: 45536 | O14: 2.3 | P14: 8750 | Q14: 2500 | R14: 500 | U14: 11750 | V14: 1 | W14: Virement | X14: 250 | Y14: =IF(AND($D14="Contrat Local",$N14<>""),$P14*$V14,0) -> 8750 | Z14: =IF(Y14>0,Y14+($Q14+$R14+IF(ISNUMBER($S14),$S14,0)+IF(ISNUMBER($T14),$T14,0))*$V14,0) -> 11750 | AA14: =IF(AND(Z14>0,$N14<>""),IF((DATE(Assumptions!$B$4,1,28)-$N14)/365.25<=Assumptions!$B$20,(DATE(Assumptions!$B$4,1,28)-$N14)/365.25*Assumptions!$B$18*Z14,(Assumptions!$B$20*Assumptions!$B$18+((DATE(Assumptions!$B$4,1,28)-$N14)/365.25-Assumptions!$B$20)*Assumptions!$B$19)*Z14),0) -> 8267.6249 | AB14: =IF(Y14>0,IF($M14="Saudi",MIN(Y14+$Q14*$V14,Assumptions!$B$14)*Assumptions!$B$12,MIN(Y14+$Q14*$V14,Assumptions!$B$14)*Assumptions!$B$13),0) -> 0 | AC14: =IF(AND(Y14>0,$M14="Non-Saudi"),Assumptions!$B$25,0) -> 910.41667 | AD14: =IF(AND($D14="Contrat Local",$N14<>""),$P14*$V14,0) -> 8750 | AE14: =IF(AD14>0,AD14+($Q14+$R14+IF(ISNUMBER($S14),$S14,0)+IF(ISNUMBER($T14),$T14,0))*$V14,0) -> 11750 | AF14: =IF(AND(AE14>0,$N14<>""),IF((DATE(Assumptions!$B$4,2,28)-$N14)/365.25<=Assumptions!$B$20,(DATE(Assumptions!$B$4,2,28)-$N14)/365.25*Assumptions!$B$18*AE14,(Assumptions!$B$20*Assumptions!$B$18+((DATE(Assumptions!$B$4,2,28)-$N14)/365.25-Assumptions!$B$20)*Assumptions!$B$19)*AE14),0) -> 8766.256 | AG14: =IF(AD14>0,IF($M14="Saudi",MIN(AD14+$Q14*$V14,Assumptions!$B$14)*Assumptions!$B$12,MIN(AD14+$Q14*$V14,Assumptions!$B$14)*Assumptions!$B$13),0) -> 0 | AH14: =IF(AND(AD14>0,$M14="Non-Saudi"),Assumptions!$B$25,0) -> 910.41667 | AI14: =IF(AND($D14="Contrat Local",$N14<>""),$P14*$V14,0) -> 8750 | AJ14: =IF(AI14>0,AI14+($Q14+$R14+IF(ISNUMBER($S14),$S14,0)+IF(ISNUMBER($T14),$T14,0))*$V14,0) -> 11750 | AK14: =IF(AND(AJ14>0,$N14<>""),IF((DATE(Assumptions!$B$4,3,28)-$N14)/365.25<=Assumptions!$B$20,(DATE(Assumptions!$B$4,3,28)-$N14)/365.25*Assumptions!$B$18*AJ14,(Assumptions!$B$20*Assumptions!$B$18+((DATE(Assumptions!$B$4,3,28)-$N14)/365.25-Assumptions!$B$20)*Assumptions!$B$19)*AJ14),0) -> 9216.6324 | AL14: =IF(AI14>0,IF($M14="Saudi",MIN(AI14+$Q14*$V14,Assumptions!$B$14)*Assumptions!$B$12,MIN(AI14+$Q14*$V14,Assumptions!$B$14)*Assumptions!$B$13),0) -> 0 | AM14: =IF(AND(AI14>0,$M14="Non-Saudi"),Assumptions!$B$25,0) -> 910.41667 | AN14: =IF(AND($D14="Contrat Local",$N14<>""),$P14*$V14,0) -> 8750 | AO14: =IF(AN14>0,AN14+($Q14+$R14+IF(ISNUMBER($S14),$S14,0)+IF(ISNUMBER($T14),$T14,0))*$V14,0) -> 11750 | AP14: =IF(AND(AO14>0,$N14<>""),IF((DATE(Assumptions!$B$4,4,28)-$N14)/365.25<=Assumptions!$B$20,(DATE(Assumptions!$B$4,4,28)-$N14)/365.25*Assumptions!$B$18*AO14,(Assumptions!$B$20*Assumptions!$B$18+((DATE(Assumptions!$B$4,4,28)-$N14)/365.25-Assumptions!$B$20)*Assumptions!$B$19)*AO14),0) -> 9715.2635 | AQ14: =IF(AN14>0,IF($M14="Saudi",MIN(AN14+$Q14*$V14,Assumptions!$B$14)*Assumptions!$B$12,MIN(AN14+$Q14*$V14,Assumptions!$B$14)*Assumptions!$B$13),0) -> 0 | AR14: =IF(AND(AN14>0,$M14="Non-Saudi"),Assumptions!$B$25,0) -> 910.41667 | AS14: =IF(AND($D14="Contrat Local",$N14<>""),$P14*$V14,0) -> 8750 | AT14: =IF(AS14>0,AS14+($Q14+$R14+IF(ISNUMBER($S14),$S14,0)+IF(ISNUMBER($T14),$T14,0))*$V14,0) -> 11750 | AU14: =IF(AND(AT14>0,$N14<>""),IF((DATE(Assumptions!$B$4,5,28)-$N14)/365.25<=Assumptions!$B$20,(DATE(Assumptions!$B$4,5,28)-$N14)/365.25*Assumptions!$B$18*AT14,(Assumptions!$B$20*Assumptions!$B$18+((DATE(Assumptions!$B$4,5,28)-$N14)/365.25-Assumptions!$B$20)*Assumptions!$B$19)*AT14),0) -> 10197.81 | AV14: =IF(AS14>0,IF($M14="Saudi",MIN(AS14+$Q14*$V14,Assumptions!$B$14)*Assumptions!$B$12,MIN(AS14+$Q14*$V14,Assumptions!$B$14)*Assumptions!$B$13),0) -> 0 | AW14: =IF(AND(AS14>0,$M14="Non-Saudi"),Assumptions!$B$25,0) -> 910.41667 | AX14: =IF(AND($D14="Contrat Local",$N14<>""),$P14*$V14,0) -> 8750 | AY14: =IF(AX14>0,AX14+($Q14+$R14+IF(ISNUMBER($S14),$S14,0)+IF(ISNUMBER($T14),$T14,0))*$V14,0) -> 11750 | AZ14: =IF(AND(AY14>0,$N14<>""),IF((DATE(Assumptions!$B$4,6,28)-$N14)/365.25<=Assumptions!$B$20,(DATE(Assumptions!$B$4,6,28)-$N14)/365.25*Assumptions!$B$18*AY14,(Assumptions!$B$20*Assumptions!$B$18+((DATE(Assumptions!$B$4,6,28)-$N14)/365.25-Assumptions!$B$20)*Assumptions!$B$19)*AY14),0) -> 10696.441 | BA14: =IF(AX14>0,IF($M14="Saudi",MIN(AX14+$Q14*$V14,Assumptions!$B$14)*Assumptions!$B$12,MIN(AX14+$Q14*$V14,Assumptions!$B$14)*Assumptions!$B$13),0) -> 0 | BB14: =IF(AND(AX14>0,$M14="Non-Saudi"),Assumptions!$B$25,0) -> 910.41667 | BC14: =IF(AND($D14="Contrat Local",$N14<>""),$P14*$V14,0) -> 8750 | BD14: =IF(BC14>0,BC14+($Q14+$R14+IF(ISNUMBER($S14),$S14,0)+IF(ISNUMBER($T14),$T14,0))*$V14,0) -> 11750 | BE14: =IF(AND(BD14>0,$N14<>""),IF((DATE(Assumptions!$B$4,7,28)-$N14)/365.25<=Assumptions!$B$20,(DATE(Assumptions!$B$4,7,28)-$N14)/365.25*Assumptions!$B$18*BD14,(Assumptions!$B$20*Assumptions!$B$18+((DATE(Assumptions!$B$4,7,28)-$N14)/365.25-Assumptions!$B$20)*Assumptions!$B$19)*BD14),0) -> 11178.987 | BF14: =IF(BC14>0,IF($M14="Saudi",MIN(BC14+$Q14*$V14,Assumptions!$B$14)*Assumptions!$B$12,MIN(BC14+$Q14*$V14,Assumptions!$B$14)*Assumptions!$B$13),0) -> 0 | BG14: =IF(AND(BC14>0,$M14="Non-Saudi"),Assumptions!$B$25,0) -> 910.41667 | BH14: =IF(AND($D14="Contrat Local",$N14<>""),$P14*$V14,0) -> 8750 | BI14: =IF(BH14>0,BH14+($Q14+$R14+IF(ISNUMBER($S14),$S14,0)+IF(ISNUMBER($T14),$T14,0))*$V14,0) -> 11750 | BJ14: =IF(AND(BI14>0,$N14<>""),IF((DATE(Assumptions!$B$4,8,28)-$N14)/365.25<=Assumptions!$B$20,(DATE(Assumptions!$B$4,8,28)-$N14)/365.25*Assumptions!$B$18*BI14,(Assumptions!$B$20*Assumptions!$B$18+((DATE(Assumptions!$B$4,8,28)-$N14)/365.25-Assumptions!$B$20)*Assumptions!$B$19)*BI14),0) -> 11677.618 | BK14: =IF(BH14>0,IF($M14="Saudi",MIN(BH14+$Q14*$V14,Assumptions!$B$14)*Assumptions!$B$12,MIN(BH14+$Q14*$V14,Assumptions!$B$14)*Assumptions!$B$13),0) -> 0 | BL14: =IF(AND(BH14>0,$M14="Non-Saudi"),Assumptions!$B$25,0) -> 910.41667 | BM14: =IF(AND($D14="Contrat Local",$N14<>""),IF(AND(9>=Assumptions!$B$5,ISNUMBER($X14),$N14<EDATE(Assumptions!$B$9,-Assumptions!$B$6*12)),($P14+$X14)*$V14,$P14*$V14),0) -> 9000 | BN14: =IF(BM14>0,BM14+($Q14+$R14+IF(ISNUMBER($S14),$S14,0)+IF(ISNUMBER($T14),$T14,0))*$V14,0) -> 12000 | BO14: =IF(AND(BN14>0,$N14<>""),IF((DATE(Assumptions!$B$4,9,28)-$N14)/365.25<=Assumptions!$B$20,(DATE(Assumptions!$B$4,9,28)-$N14)/365.25*Assumptions!$B$18*BN14,(Assumptions!$B$20*Assumptions!$B$18+((DATE(Assumptions!$B$4,9,28)-$N14)/365.25-Assumptions!$B$20)*Assumptions!$B$19)*BN14),0) -> 12435.318 | BP14: =IF(BM14>0,IF($M14="Saudi",MIN(BM14+$Q14*$V14,Assumptions!$B$14)*Assumptions!$B$12,MIN(BM14+$Q14*$V14,Assumptions!$B$14)*Assumptions!$B$13),0) -> 0 | BQ14: =IF(AND(BM14>0,$M14="Non-Saudi"),Assumptions!$B$25,0) -> 910.41667 | BR14: =IF(AND($D14="Contrat Local",$N14<>""),IF(AND(10>=Assumptions!$B$5,ISNUMBER($X14),$N14<EDATE(Assumptions!$B$9,-Assumptions!$B$6*12)),($P14+$X14)*$V14,$P14*$V14),0) -> 9000 | BS14: =IF(BR14>0,BR14+($Q14+$R14+IF(ISNUMBER($S14),$S14,0)+IF(ISNUMBER($T14),$T14,0))*$V14,0) -> 12000 | BT14: =IF(AND(BS14>0,$N14<>""),IF((DATE(Assumptions!$B$4,10,28)-$N14)/365.25<=Assumptions!$B$20,(DATE(Assumptions!$B$4,10,28)-$N14)/365.25*Assumptions!$B$18*BS14,(Assumptions!$B$20*Assumptions!$B$18+((DATE(Assumptions!$B$4,10,28)-$N14)/365.25-Assumptions!$B$20)*Assumptions!$B$19)*BS14),0) -> 12928.131 | BU14: =IF(BR14>0,IF($M14="Saudi",MIN(BR14+$Q14*$V14,Assumptions!$B$14)*Assumptions!$B$12,MIN(BR14+$Q14*$V14,Assumptions!$B$14)*Assumptions!$B$13),0) -> 0 | BV14: =IF(AND(BR14>0,$M14="Non-Saudi"),Assumptions!$B$25,0) -> 910.41667 | BW14: =IF(AND($D14="Contrat Local",$N14<>""),IF(AND(11>=Assumptions!$B$5,ISNUMBER($X14),$N14<EDATE(Assumptions!$B$9,-Assumptions!$B$6*12)),($P14+$X14)*$V14,$P14*$V14),0) -> 9000 | BX14: =IF(BW14>0,BW14+($Q14+$R14+IF(ISNUMBER($S14),$S14,0)+IF(ISNUMBER($T14),$T14,0))*$V14,0) -> 12000 | BY14: =IF(AND(BX14>0,$N14<>""),IF((DATE(Assumptions!$B$4,11,28)-$N14)/365.25<=Assumptions!$B$20,(DATE(Assumptions!$B$4,11,28)-$N14)/365.25*Assumptions!$B$18*BX14,(Assumptions!$B$20*Assumptions!$B$18+((DATE(Assumptions!$B$4,11,28)-$N14)/365.25-Assumptions!$B$20)*Assumptions!$B$19)*BX14),0) -> 13437.372 | BZ14: =IF(BW14>0,IF($M14="Saudi",MIN(BW14+$Q14*$V14,Assumptions!$B$14)*Assumptions!$B$12,MIN(BW14+$Q14*$V14,Assumptions!$B$14)*Assumptions!$B$13),0) -> 0 | CA14: =IF(AND(BW14>0,$M14="Non-Saudi"),Assumptions!$B$25,0) -> 910.41667 | CB14: =IF(AND($D14="Contrat Local",$N14<>""),IF(AND(12>=Assumptions!$B$5,ISNUMBER($X14),$N14<EDATE(Assumptions!$B$9,-Assumptions!$B$6*12)),($P14+$X14)*$V14,$P14*$V14),0) -> 9000 | CC14: =IF(CB14>0,CB14+($Q14+$R14+IF(ISNUMBER($S14),$S14,0)+IF(ISNUMBER($T14),$T14,0))*$V14,0) -> 12000 | CD14: =IF(AND(CC14>0,$N14<>""),IF((DATE(Assumptions!$B$4,12,28)-$N14)/365.25<=Assumptions!$B$20,(DATE(Assumptions!$B$4,12,28)-$N14)/365.25*Assumptions!$B$18*CC14,(Assumptions!$B$20*Assumptions!$B$18+((DATE(Assumptions!$B$4,12,28)-$N14)/365.25-Assumptions!$B$20)*Assumptions!$B$19)*CC14),0) -> 13930.185 | CE14: =IF(CB14>0,IF($M14="Saudi",MIN(CB14+$Q14*$V14,Assumptions!$B$14)*Assumptions!$B$12,MIN(CB14+$Q14*$V14,Assumptions!$B$14)*Assumptions!$B$13),0) -> 0 | CF14: =IF(AND(CB14>0,$M14="Non-Saudi"),Assumptions!$B$25,0) -> 910.41667 | CG14: =Y14+AD14+AI14+AN14+AS14+AX14+BC14+BH14+BM14+BR14+BW14+CB14 -> 106000 | CH14: =Z14+AE14+AJ14+AO14+AT14+AY14+BD14+BI14+BN14+BS14+BX14+CC14 -> 142000 | CI14: =CD14-IF(AND(Z14>0,$N14<>""),IF((DATE(Assumptions!$B$4-1,12,28)-$N14)/365.25<=Assumptions!$B$20,(DATE(Assumptions!$B$4-1,12,28)-$N14)/365.25*Assumptions!$B$18*Z14,(Assumptions!$B$20*Assumptions!$B$18+((DATE(Assumptions!$B$4-1,12,28)-$N14)/365.25-Assumptions!$B$20)*Assumptions!$B$19)*Z14),0) -> 6161.191 | CJ14: =AB14+AG14+AL14+AQ14+AV14+BA14+BF14+BK14+BP14+BU14+BZ14+CE14 -> 0 | CK14: =AC14+AH14+AM14+AR14+AW14+BB14+BG14+BL14+BQ14+BV14+CA14+CF14 -> 10925
A15: 11 | B15: AL OSSAIMI AL OTAIBI | C15: BADR | D15: Contrat Local | E15: Permanent | F15: Démarcheur | G15: Administration | H15: Relations publiques | I15: Non-Teacher | K15: Administration | L15: Existing | M15: =IF(D15="Titulaire EN","",IF(OR(B15="AL OSSAIMI AL OTAIBI",B15="ALAMRI"),"Saudi","Non-Saudi")) -> Saudi | P15: 2000 | Q15: 2500 | R15: 500 | U15: 5000 | V15: 1 | W15: Virement | X15: Nouveau Contrat | Y15: =IF(AND($D15="Contrat Local",$N15<>""),$P15*$V15,0) -> 0 | Z15: =IF(Y15>0,Y15+($Q15+$R15+IF(ISNUMBER($S15),$S15,0)+IF(ISNUMBER($T15),$T15,0))*$V15,0) -> 0 | AA15: =IF(AND(Z15>0,$N15<>""),IF((DATE(Assumptions!$B$4,1,28)-$N15)/365.25<=Assumptions!$B$20,(DATE(Assumptions!$B$4,1,28)-$N15)/365.25*Assumptions!$B$18*Z15,(Assumptions!$B$20*Assumptions!$B$18+((DATE(Assumptions!$B$4,1,28)-$N15)/365.25-Assumptions!$B$20)*Assumptions!$B$19)*Z15),0) -> 0 | AB15: =IF(Y15>0,IF($M15="Saudi",MIN(Y15+$Q15*$V15,Assumptions!$B$14)*Assumptions!$B$12,MIN(Y15+$Q15*$V15,Assumptions!$B$14)*Assumptions!$B$13),0) -> 0 | AC15: =IF(AND(Y15>0,$M15="Non-Saudi"),Assumptions!$B$25,0) -> 0 | AD15: =IF(AND($D15="Contrat Local",$N15<>""),$P15*$V15,0) -> 0 | AE15: =IF(AD15>0,AD15+($Q15+$R15+IF(ISNUMBER($S15),$S15,0)+IF(ISNUMBER($T15),$T15,0))*$V15,0) -> 0 | AF15: =IF(AND(AE15>0,$N15<>""),IF((DATE(Assumptions!$B$4,2,28)-$N15)/365.25<=Assumptions!$B$20,(DATE(Assumptions!$B$4,2,28)-$N15)/365.25*Assumptions!$B$18*AE15,(Assumptions!$B$20*Assumptions!$B$18+((DATE(Assumptions!$B$4,2,28)-$N15)/365.25-Assumptions!$B$20)*Assumptions!$B$19)*AE15),0) -> 0 | AG15: =IF(AD15>0,IF($M15="Saudi",MIN(AD15+$Q15*$V15,Assumptions!$B$14)*Assumptions!$B$12,MIN(AD15+$Q15*$V15,Assumptions!$B$14)*Assumptions!$B$13),0) -> 0 | AH15: =IF(AND(AD15>0,$M15="Non-Saudi"),Assumptions!$B$25,0) -> 0 | AI15: =IF(AND($D15="Contrat Local",$N15<>""),$P15*$V15,0) -> 0 | AJ15: =IF(AI15>0,AI15+($Q15+$R15+IF(ISNUMBER($S15),$S15,0)+IF(ISNUMBER($T15),$T15,0))*$V15,0) -> 0 | AK15: =IF(AND(AJ15>0,$N15<>""),IF((DATE(Assumptions!$B$4,3,28)-$N15)/365.25<=Assumptions!$B$20,(DATE(Assumptions!$B$4,3,28)-$N15)/365.25*Assumptions!$B$18*AJ15,(Assumptions!$B$20*Assumptions!$B$18+((DATE(Assumptions!$B$4,3,28)-$N15)/365.25-Assumptions!$B$20)*Assumptions!$B$19)*AJ15),0) -> 0 | AL15: =IF(AI15>0,IF($M15="Saudi",MIN(AI15+$Q15*$V15,Assumptions!$B$14)*Assumptions!$B$12,MIN(AI15+$Q15*$V15,Assumptions!$B$14)*Assumptions!$B$13),0) -> 0 | AM15: =IF(AND(AI15>0,$M15="Non-Saudi"),Assumptions!$B$25,0) -> 0 | AN15: =IF(AND($D15="Contrat Local",$N15<>""),$P15*$V15,0) -> 0 | AO15: =IF(AN15>0,AN15+($Q15+$R15+IF(ISNUMBER($S15),$S15,0)+IF(ISNUMBER($T15),$T15,0))*$V15,0) -> 0 | AP15: =IF(AND(AO15>0,$N15<>""),IF((DATE(Assumptions!$B$4,4,28)-$N15)/365.25<=Assumptions!$B$20,(DATE(Assumptions!$B$4,4,28)-$N15)/365.25*Assumptions!$B$18*AO15,(Assumptions!$B$20*Assumptions!$B$18+((DATE(Assumptions!$B$4,4,28)-$N15)/365.25-Assumptions!$B$20)*Assumptions!$B$19)*AO15),0) -> 0 | AQ15: =IF(AN15>0,IF($M15="Saudi",MIN(AN15+$Q15*$V15,Assumptions!$B$14)*Assumptions!$B$12,MIN(AN15+$Q15*$V15,Assumptions!$B$14)*Assumptions!$B$13),0) -> 0 | AR15: =IF(AND(AN15>0,$M15="Non-Saudi"),Assumptions!$B$25,0) -> 0 | AS15: =IF(AND($D15="Contrat Local",$N15<>""),$P15*$V15,0) -> 0 | AT15: =IF(AS15>0,AS15+($Q15+$R15+IF(ISNUMBER($S15),$S15,0)+IF(ISNUMBER($T15),$T15,0))*$V15,0) -> 0 | AU15: =IF(AND(AT15>0,$N15<>""),IF((DATE(Assumptions!$B$4,5,28)-$N15)/365.25<=Assumptions!$B$20,(DATE(Assumptions!$B$4,5,28)-$N15)/365.25*Assumptions!$B$18*AT15,(Assumptions!$B$20*Assumptions!$B$18+((DATE(Assumptions!$B$4,5,28)-$N15)/365.25-Assumptions!$B$20)*Assumptions!$B$19)*AT15),0) -> 0 | AV15: =IF(AS15>0,IF($M15="Saudi",MIN(AS15+$Q15*$V15,Assumptions!$B$14)*Assumptions!$B$12,MIN(AS15+$Q15*$V15,Assumptions!$B$14)*Assumptions!$B$13),0) -> 0 | AW15: =IF(AND(AS15>0,$M15="Non-Saudi"),Assumptions!$B$25,0) -> 0 | AX15: =IF(AND($D15="Contrat Local",$N15<>""),$P15*$V15,0) -> 0 | AY15: =IF(AX15>0,AX15+($Q15+$R15+IF(ISNUMBER($S15),$S15,0)+IF(ISNUMBER($T15),$T15,0))*$V15,0) -> 0 | AZ15: =IF(AND(AY15>0,$N15<>""),IF((DATE(Assumptions!$B$4,6,28)-$N15)/365.25<=Assumptions!$B$20,(DATE(Assumptions!$B$4,6,28)-$N15)/365.25*Assumptions!$B$18*AY15,(Assumptions!$B$20*Assumptions!$B$18+((DATE(Assumptions!$B$4,6,28)-$N15)/365.25-Assumptions!$B$20)*Assumptions!$B$19)*AY15),0) -> 0 | BA15: =IF(AX15>0,IF($M15="Saudi",MIN(AX15+$Q15*$V15,Assumptions!$B$14)*Assumptions!$B$12,MIN(AX15+$Q15*$V15,Assumptions!$B$14)*Assumptions!$B$13),0) -> 0 | BB15: =IF(AND(AX15>0,$M15="Non-Saudi"),Assumptions!$B$25,0) -> 0 | BC15: =IF(AND($D15="Contrat Local",$N15<>""),$P15*$V15,0) -> 0 | BD15: =IF(BC15>0,BC15+($Q15+$R15+IF(ISNUMBER($S15),$S15,0)+IF(ISNUMBER($T15),$T15,0))*$V15,0) -> 0 | BE15: =IF(AND(BD15>0,$N15<>""),IF((DATE(Assumptions!$B$4,7,28)-$N15)/365.25<=Assumptions!$B$20,(DATE(Assumptions!$B$4,7,28)-$N15)/365.25*Assumptions!$B$18*BD15,(Assumptions!$B$20*Assumptions!$B$18+((DATE(Assumptions!$B$4,7,28)-$N15)/365.25-Assumptions!$B$20)*Assumptions!$B$19)*BD15),0) -> 0 | BF15: =IF(BC15>0,IF($M15="Saudi",MIN(BC15+$Q15*$V15,Assumptions!$B$14)*Assumptions!$B$12,MIN(BC15+$Q15*$V15,Assumptions!$B$14)*Assumptions!$B$13),0) -> 0 | BG15: =IF(AND(BC15>0,$M15="Non-Saudi"),Assumptions!$B$25,0) -> 0 | BH15: =IF(AND($D15="Contrat Local",$N15<>""),$P15*$V15,0) -> 0 | BI15: =IF(BH15>0,BH15+($Q15+$R15+IF(ISNUMBER($S15),$S15,0)+IF(ISNUMBER($T15),$T15,0))*$V15,0) -> 0 | BJ15: =IF(AND(BI15>0,$N15<>""),IF((DATE(Assumptions!$B$4,8,28)-$N15)/365.25<=Assumptions!$B$20,(DATE(Assumptions!$B$4,8,28)-$N15)/365.25*Assumptions!$B$18*BI15,(Assumptions!$B$20*Assumptions!$B$18+((DATE(Assumptions!$B$4,8,28)-$N15)/365.25-Assumptions!$B$20)*Assumptions!$B$19)*BI15),0) -> 0 | BK15: =IF(BH15>0,IF($M15="Saudi",MIN(BH15+$Q15*$V15,Assumptions!$B$14)*Assumptions!$B$12,MIN(BH15+$Q15*$V15,Assumptions!$B$14)*Assumptions!$B$13),0) -> 0 | BL15: =IF(AND(BH15>0,$M15="Non-Saudi"),Assumptions!$B$25,0) -> 0 | BM15: =IF(AND($D15="Contrat Local",$N15<>""),IF(AND(9>=Assumptions!$B$5,ISNUMBER($X15),$N15<EDATE(Assumptions!$B$9,-Assumptions!$B$6*12)),($P15+$X15)*$V15,$P15*$V15),0) -> 0 | BN15: =IF(BM15>0,BM15+($Q15+$R15+IF(ISNUMBER($S15),$S15,0)+IF(ISNUMBER($T15),$T15,0))*$V15,0) -> 0 | BO15: =IF(AND(BN15>0,$N15<>""),IF((DATE(Assumptions!$B$4,9,28)-$N15)/365.25<=Assumptions!$B$20,(DATE(Assumptions!$B$4,9,28)-$N15)/365.25*Assumptions!$B$18*BN15,(Assumptions!$B$20*Assumptions!$B$18+((DATE(Assumptions!$B$4,9,28)-$N15)/365.25-Assumptions!$B$20)*Assumptions!$B$19)*BN15),0) -> 0 | BP15: =IF(BM15>0,IF($M15="Saudi",MIN(BM15+$Q15*$V15,Assumptions!$B$14)*Assumptions!$B$12,MIN(BM15+$Q15*$V15,Assumptions!$B$14)*Assumptions!$B$13),0) -> 0 | BQ15: =IF(AND(BM15>0,$M15="Non-Saudi"),Assumptions!$B$25,0) -> 0 | BR15: =IF(AND($D15="Contrat Local",$N15<>""),IF(AND(10>=Assumptions!$B$5,ISNUMBER($X15),$N15<EDATE(Assumptions!$B$9,-Assumptions!$B$6*12)),($P15+$X15)*$V15,$P15*$V15),0) -> 0 | BS15: =IF(BR15>0,BR15+($Q15+$R15+IF(ISNUMBER($S15),$S15,0)+IF(ISNUMBER($T15),$T15,0))*$V15,0) -> 0 | BT15: =IF(AND(BS15>0,$N15<>""),IF((DATE(Assumptions!$B$4,10,28)-$N15)/365.25<=Assumptions!$B$20,(DATE(Assumptions!$B$4,10,28)-$N15)/365.25*Assumptions!$B$18*BS15,(Assumptions!$B$20*Assumptions!$B$18+((DATE(Assumptions!$B$4,10,28)-$N15)/365.25-Assumptions!$B$20)*Assumptions!$B$19)*BS15),0) -> 0 | BU15: =IF(BR15>0,IF($M15="Saudi",MIN(BR15+$Q15*$V15,Assumptions!$B$14)*Assumptions!$B$12,MIN(BR15+$Q15*$V15,Assumptions!$B$14)*Assumptions!$B$13),0) -> 0 | BV15: =IF(AND(BR15>0,$M15="Non-Saudi"),Assumptions!$B$25,0) -> 0 | BW15: =IF(AND($D15="Contrat Local",$N15<>""),IF(AND(11>=Assumptions!$B$5,ISNUMBER($X15),$N15<EDATE(Assumptions!$B$9,-Assumptions!$B$6*12)),($P15+$X15)*$V15,$P15*$V15),0) -> 0 | BX15: =IF(BW15>0,BW15+($Q15+$R15+IF(ISNUMBER($S15),$S15,0)+IF(ISNUMBER($T15),$T15,0))*$V15,0) -> 0 | BY15: =IF(AND(BX15>0,$N15<>""),IF((DATE(Assumptions!$B$4,11,28)-$N15)/365.25<=Assumptions!$B$20,(DATE(Assumptions!$B$4,11,28)-$N15)/365.25*Assumptions!$B$18*BX15,(Assumptions!$B$20*Assumptions!$B$18+((DATE(Assumptions!$B$4,11,28)-$N15)/365.25-Assumptions!$B$20)*Assumptions!$B$19)*BX15),0) -> 0 | BZ15: =IF(BW15>0,IF($M15="Saudi",MIN(BW15+$Q15*$V15,Assumptions!$B$14)*Assumptions!$B$12,MIN(BW15+$Q15*$V15,Assumptions!$B$14)*Assumptions!$B$13),0) -> 0 | CA15: =IF(AND(BW15>0,$M15="Non-Saudi"),Assumptions!$B$25,0) -> 0 | CB15: =IF(AND($D15="Contrat Local",$N15<>""),IF(AND(12>=Assumptions!$B$5,ISNUMBER($X15),$N15<EDATE(Assumptions!$B$9,-Assumptions!$B$6*12)),($P15+$X15)*$V15,$P15*$V15),0) -> 0 | CC15: =IF(CB15>0,CB15+($Q15+$R15+IF(ISNUMBER($S15),$S15,0)+IF(ISNUMBER($T15),$T15,0))*$V15,0) -> 0 | CD15: =IF(AND(CC15>0,$N15<>""),IF((DATE(Assumptions!$B$4,12,28)-$N15)/365.25<=Assumptions!$B$20,(DATE(Assumptions!$B$4,12,28)-$N15)/365.25*Assumptions!$B$18*CC15,(Assumptions!$B$20*Assumptions!$B$18+((DATE(Assumptions!$B$4,12,28)-$N15)/365.25-Assumptions!$B$20)*Assumptions!$B$19)*CC15),0) -> 0 | CE15: =IF(CB15>0,IF($M15="Saudi",MIN(CB15+$Q15*$V15,Assumptions!$B$14)*Assumptions!$B$12,MIN(CB15+$Q15*$V15,Assumptions!$B$14)*Assumptions!$B$13),0) -> 0 | CF15: =IF(AND(CB15>0,$M15="Non-Saudi"),Assumptions!$B$25,0) -> 0 | CG15: =Y15+AD15+AI15+AN15+AS15+AX15+BC15+BH15+BM15+BR15+BW15+CB15 -> 0 | CH15: =Z15+AE15+AJ15+AO15+AT15+AY15+BD15+BI15+BN15+BS15+BX15+CC15 -> 0 | CI15: =CD15-IF(AND(Z15>0,$N15<>""),IF((DATE(Assumptions!$B$4-1,12,28)-$N15)/365.25<=Assumptions!$B$20,(DATE(Assumptions!$B$4-1,12,28)-$N15)/365.25*Assumptions!$B$18*Z15,(Assumptions!$B$20*Assumptions!$B$18+((DATE(Assumptions!$B$4-1,12,28)-$N15)/365.25-Assumptions!$B$20)*Assumptions!$B$19)*Z15),0) -> 0 | CJ15: =AB15+AG15+AL15+AQ15+AV15+BA15+BF15+BK15+BP15+BU15+BZ15+CE15 -> 0 | CK15: =AC15+AH15+AM15+AR15+AW15+BB15+BG15+BL15+BQ15+BV15+CA15+CF15 -> 0
A16: 12 | B16: AL SHAKHAA | C16: Nada | D16: Contrat Local | E16: Permanent | F16: Chargé(e) du programme noor | G16: Administration | H16: Programme Noor | I16: Non-Teacher | K16: Administration | L16: Existing | M16: =IF(D16="Titulaire EN","",IF(OR(B16="AL OSSAIMI AL OTAIBI",B16="ALAMRI"),"Saudi","Non-Saudi")) -> Non-Saudi | N16: 42283 | O16: 11.2 | P16: 9500 | Q16: 2500 | R16: 500 | U16: 12500 | V16: 1 | W16: Mudad | X16: 250 | Y16: =IF(AND($D16="Contrat Local",$N16<>""),$P16*$V16,0) -> 9500 | Z16: =IF(Y16>0,Y16+($Q16+$R16+IF(ISNUMBER($S16),$S16,0)+IF(ISNUMBER($T16),$T16,0))*$V16,0) -> 12500 | AA16: =IF(AND(Z16>0,$N16<>""),IF((DATE(Assumptions!$B$4,1,28)-$N16)/365.25<=Assumptions!$B$20,(DATE(Assumptions!$B$4,1,28)-$N16)/365.25*Assumptions!$B$18*Z16,(Assumptions!$B$20*Assumptions!$B$18+((DATE(Assumptions!$B$4,1,28)-$N16)/365.25-Assumptions!$B$20)*Assumptions!$B$19)*Z16),0) -> 97668.549 | AB16: =IF(Y16>0,IF($M16="Saudi",MIN(Y16+$Q16*$V16,Assumptions!$B$14)*Assumptions!$B$12,MIN(Y16+$Q16*$V16,Assumptions!$B$14)*Assumptions!$B$13),0) -> 0 | AC16: =IF(AND(Y16>0,$M16="Non-Saudi"),Assumptions!$B$25,0) -> 910.41667 | AD16: =IF(AND($D16="Contrat Local",$N16<>""),$P16*$V16,0) -> 9500 | AE16: =IF(AD16>0,AD16+($Q16+$R16+IF(ISNUMBER($S16),$S16,0)+IF(ISNUMBER($T16),$T16,0))*$V16,0) -> 12500 | AF16: =IF(AND(AE16>0,$N16<>""),IF((DATE(Assumptions!$B$4,2,28)-$N16)/365.25<=Assumptions!$B$20,(DATE(Assumptions!$B$4,2,28)-$N16)/365.25*Assumptions!$B$18*AE16,(Assumptions!$B$20*Assumptions!$B$18+((DATE(Assumptions!$B$4,2,28)-$N16)/365.25-Assumptions!$B$20)*Assumptions!$B$19)*AE16),0) -> 98729.466 | AG16: =IF(AD16>0,IF($M16="Saudi",MIN(AD16+$Q16*$V16,Assumptions!$B$14)*Assumptions!$B$12,MIN(AD16+$Q16*$V16,Assumptions!$B$14)*Assumptions!$B$13),0) -> 0 | AH16: =IF(AND(AD16>0,$M16="Non-Saudi"),Assumptions!$B$25,0) -> 910.41667 | AI16: =IF(AND($D16="Contrat Local",$N16<>""),$P16*$V16,0) -> 9500 | AJ16: =IF(AI16>0,AI16+($Q16+$R16+IF(ISNUMBER($S16),$S16,0)+IF(ISNUMBER($T16),$T16,0))*$V16,0) -> 12500 | AK16: =IF(AND(AJ16>0,$N16<>""),IF((DATE(Assumptions!$B$4,3,28)-$N16)/365.25<=Assumptions!$B$20,(DATE(Assumptions!$B$4,3,28)-$N16)/365.25*Assumptions!$B$18*AJ16,(Assumptions!$B$20*Assumptions!$B$18+((DATE(Assumptions!$B$4,3,28)-$N16)/365.25-Assumptions!$B$20)*Assumptions!$B$19)*AJ16),0) -> 99687.714 | AL16: =IF(AI16>0,IF($M16="Saudi",MIN(AI16+$Q16*$V16,Assumptions!$B$14)*Assumptions!$B$12,MIN(AI16+$Q16*$V16,Assumptions!$B$14)*Assumptions!$B$13),0) -> 0 | AM16: =IF(AND(AI16>0,$M16="Non-Saudi"),Assumptions!$B$25,0) -> 910.41667 | AN16: =IF(AND($D16="Contrat Local",$N16<>""),$P16*$V16,0) -> 9500 | AO16: =IF(AN16>0,AN16+($Q16+$R16+IF(ISNUMBER($S16),$S16,0)+IF(ISNUMBER($T16),$T16,0))*$V16,0) -> 12500 | AP16: =IF(AND(AO16>0,$N16<>""),IF((DATE(Assumptions!$B$4,4,28)-$N16)/365.25<=Assumptions!$B$20,(DATE(Assumptions!$B$4,4,28)-$N16)/365.25*Assumptions!$B$18*AO16,(Assumptions!$B$20*Assumptions!$B$18+((DATE(Assumptions!$B$4,4,28)-$N16)/365.25-Assumptions!$B$20)*Assumptions!$B$19)*AO16),0) -> 100748.63 | AQ16: =IF(AN16>0,IF($M16="Saudi",MIN(AN16+$Q16*$V16,Assumptions!$B$14)*Assumptions!$B$12,MIN(AN16+$Q16*$V16,Assumptions!$B$14)*Assumptions!$B$13),0) -> 0 | AR16: =IF(AND(AN16>0,$M16="Non-Saudi"),Assumptions!$B$25,0) -> 910.41667 | AS16: =IF(AND($D16="Contrat Local",$N16<>""),$P16*$V16,0) -> 9500 | AT16: =IF(AS16>0,AS16+($Q16+$R16+IF(ISNUMBER($S16),$S16,0)+IF(ISNUMBER($T16),$T16,0))*$V16,0) -> 12500 | AU16: =IF(AND(AT16>0,$N16<>""),IF((DATE(Assumptions!$B$4,5,28)-$N16)/365.25<=Assumptions!$B$20,(DATE(Assumptions!$B$4,5,28)-$N16)/365.25*Assumptions!$B$18*AT16,(Assumptions!$B$20*Assumptions!$B$18+((DATE(Assumptions!$B$4,5,28)-$N16)/365.25-Assumptions!$B$20)*Assumptions!$B$19)*AT16),0) -> 101775.33 | AV16: =IF(AS16>0,IF($M16="Saudi",MIN(AS16+$Q16*$V16,Assumptions!$B$14)*Assumptions!$B$12,MIN(AS16+$Q16*$V16,Assumptions!$B$14)*Assumptions!$B$13),0) -> 0 | AW16: =IF(AND(AS16>0,$M16="Non-Saudi"),Assumptions!$B$25,0) -> 910.41667 | AX16: =IF(AND($D16="Contrat Local",$N16<>""),$P16*$V16,0) -> 9500 | AY16: =IF(AX16>0,AX16+($Q16+$R16+IF(ISNUMBER($S16),$S16,0)+IF(ISNUMBER($T16),$T16,0))*$V16,0) -> 12500 | AZ16: =IF(AND(AY16>0,$N16<>""),IF((DATE(Assumptions!$B$4,6,28)-$N16)/365.25<=Assumptions!$B$20,(DATE(Assumptions!$B$4,6,28)-$N16)/365.25*Assumptions!$B$18*AY16,(Assumptions!$B$20*Assumptions!$B$18+((DATE(Assumptions!$B$4,6,28)-$N16)/365.25-Assumptions!$B$20)*Assumptions!$B$19)*AY16),0) -> 102836.24 | BA16: =IF(AX16>0,IF($M16="Saudi",MIN(AX16+$Q16*$V16,Assumptions!$B$14)*Assumptions!$B$12,MIN(AX16+$Q16*$V16,Assumptions!$B$14)*Assumptions!$B$13),0) -> 0 | BB16: =IF(AND(AX16>0,$M16="Non-Saudi"),Assumptions!$B$25,0) -> 910.41667 | BC16: =IF(AND($D16="Contrat Local",$N16<>""),$P16*$V16,0) -> 9500 | BD16: =IF(BC16>0,BC16+($Q16+$R16+IF(ISNUMBER($S16),$S16,0)+IF(ISNUMBER($T16),$T16,0))*$V16,0) -> 12500 | BE16: =IF(AND(BD16>0,$N16<>""),IF((DATE(Assumptions!$B$4,7,28)-$N16)/365.25<=Assumptions!$B$20,(DATE(Assumptions!$B$4,7,28)-$N16)/365.25*Assumptions!$B$18*BD16,(Assumptions!$B$20*Assumptions!$B$18+((DATE(Assumptions!$B$4,7,28)-$N16)/365.25-Assumptions!$B$20)*Assumptions!$B$19)*BD16),0) -> 103862.94 | BF16: =IF(BC16>0,IF($M16="Saudi",MIN(BC16+$Q16*$V16,Assumptions!$B$14)*Assumptions!$B$12,MIN(BC16+$Q16*$V16,Assumptions!$B$14)*Assumptions!$B$13),0) -> 0 | BG16: =IF(AND(BC16>0,$M16="Non-Saudi"),Assumptions!$B$25,0) -> 910.41667 | BH16: =IF(AND($D16="Contrat Local",$N16<>""),$P16*$V16,0) -> 9500 | BI16: =IF(BH16>0,BH16+($Q16+$R16+IF(ISNUMBER($S16),$S16,0)+IF(ISNUMBER($T16),$T16,0))*$V16,0) -> 12500 | BJ16: =IF(AND(BI16>0,$N16<>""),IF((DATE(Assumptions!$B$4,8,28)-$N16)/365.25<=Assumptions!$B$20,(DATE(Assumptions!$B$4,8,28)-$N16)/365.25*Assumptions!$B$18*BI16,(Assumptions!$B$20*Assumptions!$B$18+((DATE(Assumptions!$B$4,8,28)-$N16)/365.25-Assumptions!$B$20)*Assumptions!$B$19)*BI16),0) -> 104923.85 | BK16: =IF(BH16>0,IF($M16="Saudi",MIN(BH16+$Q16*$V16,Assumptions!$B$14)*Assumptions!$B$12,MIN(BH16+$Q16*$V16,Assumptions!$B$14)*Assumptions!$B$13),0) -> 0 | BL16: =IF(AND(BH16>0,$M16="Non-Saudi"),Assumptions!$B$25,0) -> 910.41667 | BM16: =IF(AND($D16="Contrat Local",$N16<>""),IF(AND(9>=Assumptions!$B$5,ISNUMBER($X16),$N16<EDATE(Assumptions!$B$9,-Assumptions!$B$6*12)),($P16+$X16)*$V16,$P16*$V16),0) -> 9750 | BN16: =IF(BM16>0,BM16+($Q16+$R16+IF(ISNUMBER($S16),$S16,0)+IF(ISNUMBER($T16),$T16,0))*$V16,0) -> 12750 | BO16: =IF(AND(BN16>0,$N16<>""),IF((DATE(Assumptions!$B$4,9,28)-$N16)/365.25<=Assumptions!$B$20,(DATE(Assumptions!$B$4,9,28)-$N16)/365.25*Assumptions!$B$18*BN16,(Assumptions!$B$20*Assumptions!$B$18+((DATE(Assumptions!$B$4,9,28)-$N16)/365.25-Assumptions!$B$20)*Assumptions!$B$19)*BN16),0) -> 108104.47 | BP16: =IF(BM16>0,IF($M16="Saudi",MIN(BM16+$Q16*$V16,Assumptions!$B$14)*Assumptions!$B$12,MIN(BM16+$Q16*$V16,Assumptions!$B$14)*Assumptions!$B$13),0) -> 0 | BQ16: =IF(AND(BM16>0,$M16="Non-Saudi"),Assumptions!$B$25,0) -> 910.41667 | BR16: =IF(AND($D16="Contrat Local",$N16<>""),IF(AND(10>=Assumptions!$B$5,ISNUMBER($X16),$N16<EDATE(Assumptions!$B$9,-Assumptions!$B$6*12)),($P16+$X16)*$V16,$P16*$V16),0) -> 9750 | BS16: =IF(BR16>0,BR16+($Q16+$R16+IF(ISNUMBER($S16),$S16,0)+IF(ISNUMBER($T16),$T16,0))*$V16,0) -> 12750 | BT16: =IF(AND(BS16>0,$N16<>""),IF((DATE(Assumptions!$B$4,10,28)-$N16)/365.25<=Assumptions!$B$20,(DATE(Assumptions!$B$4,10,28)-$N16)/365.25*Assumptions!$B$18*BS16,(Assumptions!$B$20*Assumptions!$B$18+((DATE(Assumptions!$B$4,10,28)-$N16)/365.25-Assumptions!$B$20)*Assumptions!$B$19)*BS16),0) -> 109151.69 | BU16: =IF(BR16>0,IF($M16="Saudi",MIN(BR16+$Q16*$V16,Assumptions!$B$14)*Assumptions!$B$12,MIN(BR16+$Q16*$V16,Assumptions!$B$14)*Assumptions!$B$13),0) -> 0 | BV16: =IF(AND(BR16>0,$M16="Non-Saudi"),Assumptions!$B$25,0) -> 910.41667 | BW16: =IF(AND($D16="Contrat Local",$N16<>""),IF(AND(11>=Assumptions!$B$5,ISNUMBER($X16),$N16<EDATE(Assumptions!$B$9,-Assumptions!$B$6*12)),($P16+$X16)*$V16,$P16*$V16),0) -> 9750 | BX16: =IF(BW16>0,BW16+($Q16+$R16+IF(ISNUMBER($S16),$S16,0)+IF(ISNUMBER($T16),$T16,0))*$V16,0) -> 12750 | BY16: =IF(AND(BX16>0,$N16<>""),IF((DATE(Assumptions!$B$4,11,28)-$N16)/365.25<=Assumptions!$B$20,(DATE(Assumptions!$B$4,11,28)-$N16)/365.25*Assumptions!$B$18*BX16,(Assumptions!$B$20*Assumptions!$B$18+((DATE(Assumptions!$B$4,11,28)-$N16)/365.25-Assumptions!$B$20)*Assumptions!$B$19)*BX16),0) -> 110233.83 | BZ16: =IF(BW16>0,IF($M16="Saudi",MIN(BW16+$Q16*$V16,Assumptions!$B$14)*Assumptions!$B$12,MIN(BW16+$Q16*$V16,Assumptions!$B$14)*Assumptions!$B$13),0) -> 0 | CA16: =IF(AND(BW16>0,$M16="Non-Saudi"),Assumptions!$B$25,0) -> 910.41667 | CB16: =IF(AND($D16="Contrat Local",$N16<>""),IF(AND(12>=Assumptions!$B$5,ISNUMBER($X16),$N16<EDATE(Assumptions!$B$9,-Assumptions!$B$6*12)),($P16+$X16)*$V16,$P16*$V16),0) -> 9750 | CC16: =IF(CB16>0,CB16+($Q16+$R16+IF(ISNUMBER($S16),$S16,0)+IF(ISNUMBER($T16),$T16,0))*$V16,0) -> 12750 | CD16: =IF(AND(CC16>0,$N16<>""),IF((DATE(Assumptions!$B$4,12,28)-$N16)/365.25<=Assumptions!$B$20,(DATE(Assumptions!$B$4,12,28)-$N16)/365.25*Assumptions!$B$18*CC16,(Assumptions!$B$20*Assumptions!$B$18+((DATE(Assumptions!$B$4,12,28)-$N16)/365.25-Assumptions!$B$20)*Assumptions!$B$19)*CC16),0) -> 111281.06 | CE16: =IF(CB16>0,IF($M16="Saudi",MIN(CB16+$Q16*$V16,Assumptions!$B$14)*Assumptions!$B$12,MIN(CB16+$Q16*$V16,Assumptions!$B$14)*Assumptions!$B$13),0) -> 0 | CF16: =IF(AND(CB16>0,$M16="Non-Saudi"),Assumptions!$B$25,0) -> 910.41667 | CG16: =Y16+AD16+AI16+AN16+AS16+AX16+BC16+BH16+BM16+BR16+BW16+CB16 -> 115000 | CH16: =Z16+AE16+AJ16+AO16+AT16+AY16+BD16+BI16+BN16+BS16+BX16+CC16 -> 151000 | CI16: =CD16-IF(AND(Z16>0,$N16<>""),IF((DATE(Assumptions!$B$4-1,12,28)-$N16)/365.25<=Assumptions!$B$20,(DATE(Assumptions!$B$4-1,12,28)-$N16)/365.25*Assumptions!$B$18*Z16,(Assumptions!$B$20*Assumptions!$B$18+((DATE(Assumptions!$B$4-1,12,28)-$N16)/365.25-Assumptions!$B$20)*Assumptions!$B$19)*Z16),0) -> 14673.426 | CJ16: =AB16+AG16+AL16+AQ16+AV16+BA16+BF16+BK16+BP16+BU16+BZ16+CE16 -> 0 | CK16: =AC16+AH16+AM16+AR16+AW16+BB16+BG16+BL16+BQ16+BV16+CA16+CF16 -> 10925
A17: 13 | B17: ALAMRI | C17: Shalan | D17: Contrat Local | E17: Permanent | F17: Chargé(e) des relations publiques | G17: Administration | H17: Relations publiques | I17: Non-Teacher | K17: Administration | L17: Existing | M17: =IF(D17="Titulaire EN","",IF(OR(B17="AL OSSAIMI AL OTAIBI",B17="ALAMRI"),"Saudi","Non-Saudi")) -> Saudi | N17: 44867 | O17: 4.2 | P17: 12250 | Q17: 2500 | R17: 500 | S17: 1000 | U17: 16250 | V17: 1 | W17: Mudad | X17: 250 | Y17: =IF(AND($D17="Contrat Local",$N17<>""),$P17*$V17,0) -> 12250 | Z17: =IF(Y17>0,Y17+($Q17+$R17+IF(ISNUMBER($S17),$S17,0)+IF(ISNUMBER($T17),$T17,0))*$V17,0) -> 16250 | AA17: =IF(AND(Z17>0,$N17<>""),IF((DATE(Assumptions!$B$4,1,28)-$N17)/365.25<=Assumptions!$B$20,(DATE(Assumptions!$B$4,1,28)-$N17)/365.25*Assumptions!$B$18*Z17,(Assumptions!$B$20*Assumptions!$B$18+((DATE(Assumptions!$B$4,1,28)-$N17)/365.25-Assumptions!$B$20)*Assumptions!$B$19)*Z17),0) -> 26315.88 | AB17: =IF(Y17>0,IF($M17="Saudi",MIN(Y17+$Q17*$V17,Assumptions!$B$14)*Assumptions!$B$12,MIN(Y17+$Q17*$V17,Assumptions!$B$14)*Assumptions!$B$13),0) -> 1733.125 | AC17: =IF(AND(Y17>0,$M17="Non-Saudi"),Assumptions!$B$25,0) -> 0 | AD17: =IF(AND($D17="Contrat Local",$N17<>""),$P17*$V17,0) -> 12250 | AE17: =IF(AD17>0,AD17+($Q17+$R17+IF(ISNUMBER($S17),$S17,0)+IF(ISNUMBER($T17),$T17,0))*$V17,0) -> 16250 | AF17: =IF(AND(AE17>0,$N17<>""),IF((DATE(Assumptions!$B$4,2,28)-$N17)/365.25<=Assumptions!$B$20,(DATE(Assumptions!$B$4,2,28)-$N17)/365.25*Assumptions!$B$18*AE17,(Assumptions!$B$20*Assumptions!$B$18+((DATE(Assumptions!$B$4,2,28)-$N17)/365.25-Assumptions!$B$20)*Assumptions!$B$19)*AE17),0) -> 27005.476 | AG17: =IF(AD17>0,IF($M17="Saudi",MIN(AD17+$Q17*$V17,Assumptions!$B$14)*Assumptions!$B$12,MIN(AD17+$Q17*$V17,Assumptions!$B$14)*Assumptions!$B$13),0) -> 1733.125 | AH17: =IF(AND(AD17>0,$M17="Non-Saudi"),Assumptions!$B$25,0) -> 0 | AI17: =IF(AND($D17="Contrat Local",$N17<>""),$P17*$V17,0) -> 12250 | AJ17: =IF(AI17>0,AI17+($Q17+$R17+IF(ISNUMBER($S17),$S17,0)+IF(ISNUMBER($T17),$T17,0))*$V17,0) -> 16250 | AK17: =IF(AND(AJ17>0,$N17<>""),IF((DATE(Assumptions!$B$4,3,28)-$N17)/365.25<=Assumptions!$B$20,(DATE(Assumptions!$B$4,3,28)-$N17)/365.25*Assumptions!$B$18*AJ17,(Assumptions!$B$20*Assumptions!$B$18+((DATE(Assumptions!$B$4,3,28)-$N17)/365.25-Assumptions!$B$20)*Assumptions!$B$19)*AJ17),0) -> 27628.337 | AL17: =IF(AI17>0,IF($M17="Saudi",MIN(AI17+$Q17*$V17,Assumptions!$B$14)*Assumptions!$B$12,MIN(AI17+$Q17*$V17,Assumptions!$B$14)*Assumptions!$B$13),0) -> 1733.125 | AM17: =IF(AND(AI17>0,$M17="Non-Saudi"),Assumptions!$B$25,0) -> 0 | AN17: =IF(AND($D17="Contrat Local",$N17<>""),$P17*$V17,0) -> 12250 | AO17: =IF(AN17>0,AN17+($Q17+$R17+IF(ISNUMBER($S17),$S17,0)+IF(ISNUMBER($T17),$T17,0))*$V17,0) -> 16250 | AP17: =IF(AND(AO17>0,$N17<>""),IF((DATE(Assumptions!$B$4,4,28)-$N17)/365.25<=Assumptions!$B$20,(DATE(Assumptions!$B$4,4,28)-$N17)/365.25*Assumptions!$B$18*AO17,(Assumptions!$B$20*Assumptions!$B$18+((DATE(Assumptions!$B$4,4,28)-$N17)/365.25-Assumptions!$B$20)*Assumptions!$B$19)*AO17),0) -> 28317.933 | AQ17: =IF(AN17>0,IF($M17="Saudi",MIN(AN17+$Q17*$V17,Assumptions!$B$14)*Assumptions!$B$12,MIN(AN17+$Q17*$V17,Assumptions!$B$14)*Assumptions!$B$13),0) -> 1733.125 | AR17: =IF(AND(AN17>0,$M17="Non-Saudi"),Assumptions!$B$25,0) -> 0 | AS17: =IF(AND($D17="Contrat Local",$N17<>""),$P17*$V17,0) -> 12250 | AT17: =IF(AS17>0,AS17+($Q17+$R17+IF(ISNUMBER($S17),$S17,0)+IF(ISNUMBER($T17),$T17,0))*$V17,0) -> 16250 | AU17: =IF(AND(AT17>0,$N17<>""),IF((DATE(Assumptions!$B$4,5,28)-$N17)/365.25<=Assumptions!$B$20,(DATE(Assumptions!$B$4,5,28)-$N17)/365.25*Assumptions!$B$18*AT17,(Assumptions!$B$20*Assumptions!$B$18+((DATE(Assumptions!$B$4,5,28)-$N17)/365.25-Assumptions!$B$20)*Assumptions!$B$19)*AT17),0) -> 28985.284 | AV17: =IF(AS17>0,IF($M17="Saudi",MIN(AS17+$Q17*$V17,Assumptions!$B$14)*Assumptions!$B$12,MIN(AS17+$Q17*$V17,Assumptions!$B$14)*Assumptions!$B$13),0) -> 1733.125 | AW17: =IF(AND(AS17>0,$M17="Non-Saudi"),Assumptions!$B$25,0) -> 0 | AX17: =IF(AND($D17="Contrat Local",$N17<>""),$P17*$V17,0) -> 12250 | AY17: =IF(AX17>0,AX17+($Q17+$R17+IF(ISNUMBER($S17),$S17,0)+IF(ISNUMBER($T17),$T17,0))*$V17,0) -> 16250 | AZ17: =IF(AND(AY17>0,$N17<>""),IF((DATE(Assumptions!$B$4,6,28)-$N17)/365.25<=Assumptions!$B$20,(DATE(Assumptions!$B$4,6,28)-$N17)/365.25*Assumptions!$B$18*AY17,(Assumptions!$B$20*Assumptions!$B$18+((DATE(Assumptions!$B$4,6,28)-$N17)/365.25-Assumptions!$B$20)*Assumptions!$B$19)*AY17),0) -> 29674.88 | BA17: =IF(AX17>0,IF($M17="Saudi",MIN(AX17+$Q17*$V17,Assumptions!$B$14)*Assumptions!$B$12,MIN(AX17+$Q17*$V17,Assumptions!$B$14)*Assumptions!$B$13),0) -> 1733.125 | BB17: =IF(AND(AX17>0,$M17="Non-Saudi"),Assumptions!$B$25,0) -> 0 | BC17: =IF(AND($D17="Contrat Local",$N17<>""),$P17*$V17,0) -> 12250 | BD17: =IF(BC17>0,BC17+($Q17+$R17+IF(ISNUMBER($S17),$S17,0)+IF(ISNUMBER($T17),$T17,0))*$V17,0) -> 16250 | BE17: =IF(AND(BD17>0,$N17<>""),IF((DATE(Assumptions!$B$4,7,28)-$N17)/365.25<=Assumptions!$B$20,(DATE(Assumptions!$B$4,7,28)-$N17)/365.25*Assumptions!$B$18*BD17,(Assumptions!$B$20*Assumptions!$B$18+((DATE(Assumptions!$B$4,7,28)-$N17)/365.25-Assumptions!$B$20)*Assumptions!$B$19)*BD17),0) -> 30342.231 | BF17: =IF(BC17>0,IF($M17="Saudi",MIN(BC17+$Q17*$V17,Assumptions!$B$14)*Assumptions!$B$12,MIN(BC17+$Q17*$V17,Assumptions!$B$14)*Assumptions!$B$13),0) -> 1733.125 | BG17: =IF(AND(BC17>0,$M17="Non-Saudi"),Assumptions!$B$25,0) -> 0 | BH17: =IF(AND($D17="Contrat Local",$N17<>""),$P17*$V17,0) -> 12250 | BI17: =IF(BH17>0,BH17+($Q17+$R17+IF(ISNUMBER($S17),$S17,0)+IF(ISNUMBER($T17),$T17,0))*$V17,0) -> 16250 | BJ17: =IF(AND(BI17>0,$N17<>""),IF((DATE(Assumptions!$B$4,8,28)-$N17)/365.25<=Assumptions!$B$20,(DATE(Assumptions!$B$4,8,28)-$N17)/365.25*Assumptions!$B$18*BI17,(Assumptions!$B$20*Assumptions!$B$18+((DATE(Assumptions!$B$4,8,28)-$N17)/365.25-Assumptions!$B$20)*Assumptions!$B$19)*BI17),0) -> 31031.828 | BK17: =IF(BH17>0,IF($M17="Saudi",MIN(BH17+$Q17*$V17,Assumptions!$B$14)*Assumptions!$B$12,MIN(BH17+$Q17*$V17,Assumptions!$B$14)*Assumptions!$B$13),0) -> 1733.125 | BL17: =IF(AND(BH17>0,$M17="Non-Saudi"),Assumptions!$B$25,0) -> 0 | BM17: =IF(AND($D17="Contrat Local",$N17<>""),IF(AND(9>=Assumptions!$B$5,ISNUMBER($X17),$N17<EDATE(Assumptions!$B$9,-Assumptions!$B$6*12)),($P17+$X17)*$V17,$P17*$V17),0) -> 12500 | BN17: =IF(BM17>0,BM17+($Q17+$R17+IF(ISNUMBER($S17),$S17,0)+IF(ISNUMBER($T17),$T17,0))*$V17,0) -> 16500 | BO17: =IF(AND(BN17>0,$N17<>""),IF((DATE(Assumptions!$B$4,9,28)-$N17)/365.25<=Assumptions!$B$20,(DATE(Assumptions!$B$4,9,28)-$N17)/365.25*Assumptions!$B$18*BN17,(Assumptions!$B$20*Assumptions!$B$18+((DATE(Assumptions!$B$4,9,28)-$N17)/365.25-Assumptions!$B$20)*Assumptions!$B$19)*BN17),0) -> 32209.446 | BP17: =IF(BM17>0,IF($M17="Saudi",MIN(BM17+$Q17*$V17,Assumptions!$B$14)*Assumptions!$B$12,MIN(BM17+$Q17*$V17,Assumptions!$B$14)*Assumptions!$B$13),0) -> 1762.5 | BQ17: =IF(AND(BM17>0,$M17="Non-Saudi"),Assumptions!$B$25,0) -> 0 | BR17: =IF(AND($D17="Contrat Local",$N17<>""),IF(AND(10>=Assumptions!$B$5,ISNUMBER($X17),$N17<EDATE(Assumptions!$B$9,-Assumptions!$B$6*12)),($P17+$X17)*$V17,$P17*$V17),0) -> 12500 | BS17: =IF(BR17>0,BR17+($Q17+$R17+IF(ISNUMBER($S17),$S17,0)+IF(ISNUMBER($T17),$T17,0))*$V17,0) -> 16500 | BT17: =IF(AND(BS17>0,$N17<>""),IF((DATE(Assumptions!$B$4,10,28)-$N17)/365.25<=Assumptions!$B$20,(DATE(Assumptions!$B$4,10,28)-$N17)/365.25*Assumptions!$B$18*BS17,(Assumptions!$B$20*Assumptions!$B$18+((DATE(Assumptions!$B$4,10,28)-$N17)/365.25-Assumptions!$B$20)*Assumptions!$B$19)*BS17),0) -> 32887.064 | BU17: =IF(BR17>0,IF($M17="Saudi",MIN(BR17+$Q17*$V17,Assumptions!$B$14)*Assumptions!$B$12,MIN(BR17+$Q17*$V17,Assumptions!$B$14)*Assumptions!$B$13),0) -> 1762.5 | BV17: =IF(AND(BR17>0,$M17="Non-Saudi"),Assumptions!$B$25,0) -> 0 | BW17: =IF(AND($D17="Contrat Local",$N17<>""),IF(AND(11>=Assumptions!$B$5,ISNUMBER($X17),$N17<EDATE(Assumptions!$B$9,-Assumptions!$B$6*12)),($P17+$X17)*$V17,$P17*$V17),0) -> 12500 | BX17: =IF(BW17>0,BW17+($Q17+$R17+IF(ISNUMBER($S17),$S17,0)+IF(ISNUMBER($T17),$T17,0))*$V17,0) -> 16500 | BY17: =IF(AND(BX17>0,$N17<>""),IF((DATE(Assumptions!$B$4,11,28)-$N17)/365.25<=Assumptions!$B$20,(DATE(Assumptions!$B$4,11,28)-$N17)/365.25*Assumptions!$B$18*BX17,(Assumptions!$B$20*Assumptions!$B$18+((DATE(Assumptions!$B$4,11,28)-$N17)/365.25-Assumptions!$B$20)*Assumptions!$B$19)*BX17),0) -> 33587.269 | BZ17: =IF(BW17>0,IF($M17="Saudi",MIN(BW17+$Q17*$V17,Assumptions!$B$14)*Assumptions!$B$12,MIN(BW17+$Q17*$V17,Assumptions!$B$14)*Assumptions!$B$13),0) -> 1762.5 | CA17: =IF(AND(BW17>0,$M17="Non-Saudi"),Assumptions!$B$25,0) -> 0 | CB17: =IF(AND($D17="Contrat Local",$N17<>""),IF(AND(12>=Assumptions!$B$5,ISNUMBER($X17),$N17<EDATE(Assumptions!$B$9,-Assumptions!$B$6*12)),($P17+$X17)*$V17,$P17*$V17),0) -> 12500 | CC17: =IF(CB17>0,CB17+($Q17+$R17+IF(ISNUMBER($S17),$S17,0)+IF(ISNUMBER($T17),$T17,0))*$V17,0) -> 16500 | CD17: =IF(AND(CC17>0,$N17<>""),IF((DATE(Assumptions!$B$4,12,28)-$N17)/365.25<=Assumptions!$B$20,(DATE(Assumptions!$B$4,12,28)-$N17)/365.25*Assumptions!$B$18*CC17,(Assumptions!$B$20*Assumptions!$B$18+((DATE(Assumptions!$B$4,12,28)-$N17)/365.25-Assumptions!$B$20)*Assumptions!$B$19)*CC17),0) -> 34264.887 | CE17: =IF(CB17>0,IF($M17="Saudi",MIN(CB17+$Q17*$V17,Assumptions!$B$14)*Assumptions!$B$12,MIN(CB17+$Q17*$V17,Assumptions!$B$14)*Assumptions!$B$13),0) -> 1762.5 | CF17: =IF(AND(CB17>0,$M17="Non-Saudi"),Assumptions!$B$25,0) -> 0 | CG17: =Y17+AD17+AI17+AN17+AS17+AX17+BC17+BH17+BM17+BR17+BW17+CB17 -> 148000 | CH17: =Z17+AE17+AJ17+AO17+AT17+AY17+BD17+BI17+BN17+BS17+BX17+CC17 -> 196000 | CI17: =CD17-IF(AND(Z17>0,$N17<>""),IF((DATE(Assumptions!$B$4-1,12,28)-$N17)/365.25<=Assumptions!$B$20,(DATE(Assumptions!$B$4-1,12,28)-$N17)/365.25*Assumptions!$B$18*Z17,(Assumptions!$B$20*Assumptions!$B$18+((DATE(Assumptions!$B$4-1,12,28)-$N17)/365.25-Assumptions!$B$20)*Assumptions!$B$19)*Z17),0) -> 8638.6037 | CJ17: =AB17+AG17+AL17+AQ17+AV17+BA17+BF17+BK17+BP17+BU17+BZ17+CE17 -> 20915 | CK17: =AC17+AH17+AM17+AR17+AW17+BB17+BG17+BL17+BQ17+BV17+CA17+CF17 -> 0
