Workbook

Sheet Reference_Data
A1: EFIR — Operating Expenses Budget FY2026
A2: Reference Data — Revenue & Headcount from Source Files (auto-linked)
A4: REVENUE REFERENCE
A5: Source: 01_EFIR_Revenue_FY2026.xlsx → EXECUTIVE_SUMMARY
A7: Revenue Line | B7: Jan | C7: Feb | D7: Mar | E7: Apr | F7: May | G7: Jun | H7: Jul | I7: Aug | J7: Sep | K7: Oct | L7: Nov | M7: Dec | N7: FY2026 Total
A8: Tuition Fees | B8: 5820906.5 | C8: 5820906.5 | D8: 5820906.5 | E8: 5820906.5 | F8: 5820906.5 | G8: 5820906.5 | H8: 0 | I8: 0 | J8: 5820906.5 | K8: 5820906.5 | L8: 5820906.5 | M8: 5820906.5
A9: Registration & Re-registration | B9: 0 | C9: 0 | D9: 0 | E9: 0 | F9: 0 | G9: 7620291 | H9: 0 | I9: 0 | J9: 942250 | K9: 6250 | L9: 0 | M9: 0
A10: Activities & Services | B10: 126000 | C10: 126000 | D10: 126000 | E10: 126000 | F10: 126000 | G10: 126000 | H10: 0 | I10: 0 | J10: 126000 | K10: 126000 | L10: 152400 | M10: 152400
A11: Examination Fees | B11: 0 | C11: 0 | D11: 0 | E11: 182239.5 | F11: 182239.5 | G11: 0 | H11: 0 | I11: 0 | J11: 0 | K11: 0 | L11: 0 | M11: 0
A12: Rental Income | B12: 4269.17 | C12: 4269.17 | D12: 4269.17 | E12: 4269.17 | F12: 4269.17 | G12: 4269.17 | H12: 4269.17 | I12: 4269.17 | J12: 4269.17 | K12: 4269.17 | L12: 4269.17 | M12: 4269.17
A13: TOTAL REVENUE | B13: =SUM(B8:B12) -> 5951175.7 | C13: =SUM(C8:C12) -> 5951175.7 | D13: =SUM(D8:D12) -> 5951175.7 | E13: =SUM(E8:E12) -> 6133415.2 | F13: =SUM(F8:F12) -> 6133415.2 | G13: =SUM(G8:G12) -> 13571467 | H13: =SUM(H8:H12) -> 4269.17 | I13: =SUM(I8:I12) -> 4269.17 | ... M13: =SUM(M8:M12) -> 5977575.7 | N13: =SUM(B13:M13) -> 68506365
A16: HEADCOUNT REFERENCE
A17: Source: 02_EFIR_Staff_Costs_FY2026.xlsx → Budget Summary
A19: Category | B19: Jan | C19: Feb | D19: Mar | E19: Apr | F19: May | G19: Jun | H19: Jul | I19: Aug | J19: Sep | K19: Oct | L19: Nov | M19: Dec | N19: FY Avg
A20: Teachers | B20: 136 | C20: 136 | D20: 136 | E20: 136 | F20: 136 | G20: 136 | H20: 136 | I20: 136 | J20: 136 | K20: 136 | L20: 136 | M20: 136 | N20: 136
A21: Non-Teachers | B21: 50 | C21: 50 | D21: 50 | E21: 50 | F21: 50 | G21: 50 | H21: 50 | I21: 50 | J21: 50 | K21: 50 | L21: 50 | M21: 50 | N21: 50
A22: New Positions | B22: 0 | C22: 0 | D22: 0 | E22: 0 | F22: 0 | G22: 0 | H22: 0 | I22: 0 | J22: 6 | K22: 6 | L22: 6 | M22: 6 | N22: 2
A23: TOTAL HEADCOUNT | B23: =SUM(B20:B22) -> 186 | C23: =SUM(C20:C22) -> 186 | D23: =SUM(D20:D22) -> 186 | E23: =SUM(E20:E22) -> 186 | F23: =SUM(F20:F22) -> 186 | G23: =SUM(G20:G22) -> 186 | H23: =SUM(H20:H22) -> 186 | I23: =SUM(I20:I22) -> 186 | ... M23: =SUM(M20:M22) -> 192 | N23: =AVERAGE(B23:M23) -> 188
A26: STUDENT ENROLLMENT
A27: Source: 01_EFIR_Revenue_FY2026.xlsx → ENROLLMENT_HEADCOUNT
A29: Total Students (FY2026) | B29: 1753

Sheet Operating_Expenses
A1: EFIR — Other Operating Expenses FY2026
A2: Monthly Budget Input — All amounts in SAR — Blue cells = editable inputs
A4: IFRS Category | B4: Line Item | C4: Jan | D4: Feb | E4: Mar | F4: Apr | G4: May | H4: Jun | I4: Jul | J4: Aug | K4: Sep | L4: Oct | M4: Nov | N4: Dec | O4: FY2026 Total | P4: Budget V6 Total | Q4: FY2025 Actual | R4: FY2024 Actual | S4: Comments
A5: Rent & Utilities
A6: Rent & Utilities | B6: Rent | C6: 699626.5 | D6: 699626.5 | E6: 699626.5 | F6: 699626.5 | G6: 699626.5 | H6: 699626.5 | I6: 699626.5 | J6: 699626.5 | K6: 699626.5 | L6: 699626.5 | M6: 699626.5 | N6: 699626.5 | O6: =SUM(C6:N6) -> 8395518 | P6: 8395518 | Q6: 8395516 | R6: 7631145.3 | S6: Review: was 7.2m, check contract
A7: Rent & Utilities | B7: Electricity | C7: 35000 | D7: 35000 | E7: 35000 | F7: 35000 | G7: 35000 | H7: 35000 | I7: 35000 | J7: 35000 | K7: 35000 | L7: 35000 | M7: 35000 | N7: 35000 | O7: =SUM(C7:N7) -> 420000 | P7: 420000
A8: Rent & Utilities | B8: Water | C8: 13833.33 | D8: 13833.33 | E8: 13833.33 | F8: 13833.33 | G8: 13833.33 | H8: 13833.33 | I8: 13833.33 | J8: 13833.33 | K8: 13833.33 | L8: 13833.33 | M8: 13833.33 | N8: 13833.33 | O8: =SUM(C8:N8) -> 165999.96 | P8: 166000 | Q8: 0 | R8: 15004.25
B9: Subtotal Rent & Utilities | C9: =SUM(C6:C8) -> 748459.83 | D9: =SUM(D6:D8) -> 748459.83 | E9: =SUM(E6:E8) -> 748459.83 | F9: =SUM(F6:F8) -> 748459.83 | G9: =SUM(G6:G8) -> 748459.83 | H9: =SUM(H6:H8) -> 748459.83 | I9: =SUM(I6:I8) -> 748459.83 | J9: =SUM(J6:J8) -> 748459.83 | ... R9: =SUM(R6:R8) -> 7646149.6
A11: Building Services
A12: Building Services | B12: Maintenance Contracts | C12: 230521 | D12: 230521 | E12: 230521 | F12: 230521 | G12: 230521 | H12: 230521 | I12: 230521 | J12: 230521 | K12: 230521 | L12: 230521 | M12: 230521 | N12: 230521 | O12: =SUM(C12:N12) -> 2766252 | P12: 2766252 | Q12: 2783447 | R12: 3591010 | S12: Review Metabuild contract
A13: Building Services | B13: Security | C13: 144200 | D13: 144200 | E13: 144200 | F13: 144200 | G13: 144200 | H13: 144200 | I13: 144200 | J13: 144200 | K13: 144200 | L13: 144200 | M13: 144200 | N13: 144200 | O13: =SUM(C13:N13) -> 1730400 | P13: 1730400 | S13: Review security contract
A14: Building Services | B14: Equipment Maintenance | C14: =350000/10 -> 35000 | D14: =C14 -> 35000 | E14: =D14 -> 35000 | F14: =E14 -> 35000 | G14: =F14 -> 35000 | H14: =G14 -> 35000 | K14: =H14 -> 35000 | L14: =K14 -> 35000 | M14: =L14 -> 35000 | N14: =M14 -> 35000 | O14: =SUM(C14:N14) -> 350000 | P14: 355886
B15: Subtotal Building Services | C15: =SUM(C12:C14) -> 409721 | D15: =SUM(D12:D14) -> 409721 | E15: =SUM(E12:E14) -> 409721 | F15: =SUM(F12:F14) -> 409721 | G15: =SUM(G12:G14) -> 409721 | H15: =SUM(H12:H14) -> 409721 | I15: =SUM(I12:I14) -> 374721 | J15: =SUM(J12:J14) -> 374721 | ... R15: =SUM(R12:R14) -> 3591010
A17: Office & Supplies
A18: Office & Supplies | B18: Administration Supplies | C18: =470000/10 -> 47000 | D18: =C18 -> 47000 | E18: =D18 -> 47000 | F18: =E18 -> 47000 | G18: =F18 -> 47000 | H18: =G18 -> 47000 | K18: =H18 -> 47000 | L18: =K18 -> 47000 | M18: =L18 -> 47000 | N18: =M18 -> 47000 | O18: =SUM(C18:N18) -> 470000 | P18: 465139 | S18: Clarify scope
A19: Office & Supplies | B19: Photocopier Contract | C19: 6192.67 | D19: 6192.67 | E19: 6192.67 | F19: 6192.67 | G19: 6192.67 | H19: 6192.67 | I19: 6192.67 | J19: 6192.67 | K19: 6192.67 | L19: 6192.67 | M19: 6192.67 | N19: 6192.67 | O19: =SUM(C19:N19) -> 74312.04 | P19: 150000 | Q19: 10944 | R19: 48085.29
B20: Subtotal Office & Supplies | C20: =SUM(C18:C19) -> 53192.67 | D20: =SUM(D18:D19) -> 53192.67 | E20: =SUM(E18:E19) -> 53192.67 | F20: =SUM(F18:F19) -> 53192.67 | G20: =SUM(G18:G19) -> 53192.67 | H20: =SUM(H18:H19) -> 53192.67 | I20: =SUM(I18:I19) -> 6192.67 | J20: =SUM(J18:J19) -> 6192.67 | ... R20: =SUM(R18:R19) -> 48085.29
A22: Insurance
A23: Insurance | B23: Medical Insurance – Saudi Staff | C23: 5794.42 | D23: 5794.42 | E23: 5794.42 | F23: 5794.42 | G23: 5794.42 | H23: 5794.42 | I23: 5794.42 | J23: 5794.42 | K23: 5794.42 | L23: 5794.42 | M23: 5794.42 | N23: 5794.42 | O23: =SUM(C23:N23) -> 69533.04 | P23: 69533
A24: Insurance | B24: School Insurance | C24: =180000/10 -> 18000 | D24: =180000/10 -> 18000 | E24: =180000/10 -> 18000 | F24: =180000/10 -> 18000 | G24: =180000/10 -> 18000 | H24: =180000/10 -> 18000 | I24: =180000/10 -> 18000 | J24: =180000/10 -> 18000 | ... N24: =180000/10 -> 18000 | O24: =SUM(C24:N24) -> 216000 | P24: 101789
B25: Subtotal Insurance | C25: =SUM(C23:C24) -> 23794.42 | D25: =SUM(D23:D24) -> 23794.42 | E25: =SUM(E23:E24) -> 23794.42 | F25: =SUM(F23:F24) -> 23794.42 | G25: =SUM(G23:G24) -> 23794.42 | H25: =SUM(H23:H24) -> 23794.42 | I25: =SUM(I23:I24) -> 23794.42 | J25: =SUM(J23:J24) -> 23794.42 | ... P25: =SUM(P23:P24) -> 171322 | Q25: 165852 | R25: 195526.6
A27: Professional Services
A28: Professional Services | B28: External Audit | C28: 3000 | D28: 3000 | E28: 3000 | F28: 3000 | G28: 3000 | H28: 3000 | I28: 3000 | J28: 3000 | K28: 3000 | L28: 3000 | M28: 3000 | N28: 3000 | O28: =SUM(C28:N28) -> 36000 | P28: 32000
A29: Professional Services | B29: Communication | C29: 2500 | D29: 2500 | E29: 2500 | F29: 2500 | G29: 2500 | H29: 2500 | I29: 2500 | J29: 2500 | K29: 2500 | L29: 2500 | M29: 2500 | N29: 2500 | O29: =SUM(C29:N29) -> 30000 | P29: 30000
B30: Subtotal Professional Services | C30: =SUM(C28:C29) -> 5500 | D30: =SUM(D28:D29) -> 5500 | E30: =SUM(E28:E29) -> 5500 | F30: =SUM(F28:F29) -> 5500 | G30: =SUM(G28:G29) -> 5500 | H30: =SUM(H28:H29) -> 5500 | I30: =SUM(I28:I29) -> 5500 | J30: =SUM(J28:J29) -> 5500 | ... R30: =SUM(R28:R29) -> 0
A32: IT & Telecom
A33: IT & Telecom | B33: IT Equipment | C33: =400000/10 -> 40000 | D33: =C33 -> 40000 | E33: =D33 -> 40000 | F33: =E33 -> 40000 | G33: =F33 -> 40000 | H33: =G33 -> 40000 | K33: =H33 -> 40000 | L33: =K33 -> 40000 | M33: =L33 -> 40000 | N33: =M33 -> 40000 | O33: =SUM(C33:N33) -> 400000 | P33: 330077 | Q33: 0 | R33: 29825.17 | S33: Clarify: OpEx or CapEx?
A34: IT & Telecom | B34: Telephone & Internet | C34: =300000/12 -> 25000 | D34: =300000/12 -> 25000 | E34: =300000/12 -> 25000 | F34: =300000/12 -> 25000 | G34: =300000/12 -> 25000 | H34: =300000/12 -> 25000 | I34: =300000/12 -> 25000 | J34: =300000/12 -> 25000 | ... N34: =300000/12 -> 25000 | O34: =SUM(C34:N34) -> 300000 | P34: 263791 | Q34: 0 | R34: 230
B35: Subtotal IT & Telecom | C35: =SUM(C33:C34) -> 65000 | D35: =SUM(D33:D34) -> 65000 | E35: =SUM(E33:E34) -> 65000 | F35: =SUM(F33:F34) -> 65000 | G35: =SUM(G33:G34) -> 65000 | H35: =SUM(H33:H34) -> 65000 | I35: =SUM(I33:I34) -> 25000 | J35: =SUM(J33:J34) -> 25000 | ... R35: =SUM(R33:R34) -> 30055.17
A37: Other General
A38: Other General | B38: Vehicle Fuel & Maintenance | C38: =20000/10 -> 2000 | D38: =C38 -> 2000 | E38: =D38 -> 2000 | F38: =E38 -> 2000 | G38: =F38 -> 2000 | H38: =G38 -> 2000 | K38: =H38 -> 2000 | L38: =K38 -> 2000 | M38: =L38 -> 2000 | N38: =M38 -> 2000 | O38: =SUM(C38:N38) -> 20000 | P38: 20000 | Q38: 9746.15 | R38: 5167.57
A39: Other General | B39: Infirmary | C39: =25000/10 -> 2500 | D39: =C39 -> 2500 | E39: =D39 -> 2500 | F39: =E39 -> 2500 | G39: =F39 -> 2500 | H39: =G39 -> 2500 | K39: =H39 -> 2500 | L39: =K39 -> 2500 | M39: =L39 -> 2500 | N39: =M39 -> 2500 | O39: =SUM(C39:N39) -> 25000 | P39: 23269
A40: Other General | B40: Reception & Events | C40: =25000/10 -> 2500 | D40: =C40 -> 2500 | E40: =D40 -> 2500 | F40: =E40 -> 2500 | G40: =F40 -> 2500 | H40: =G40 -> 2500 | K40: =H40 -> 2500 | L40: =K40 -> 2500 | M40: =L40 -> 2500 | N40: =M40 -> 2500 | O40: =SUM(C40:N40) -> 25000 | P40: 25000
A41: Other General | B41: Class Photos / Printing | C41: =20000/10 -> 2000 | D41: =C41 -> 2000 | E41: =D41 -> 2000 | F41: =E41 -> 2000 | G41: =F41 -> 2000 | H41: =G41 -> 2000 | K41: =H41 -> 2000 | L41: =K41 -> 2000 | M41: =L41 -> 2000 | N41: =M41 -> 2000 | O41: =SUM(C41:N41) -> 20000 | P41: 18180
A42: Other General | B42: Social Aid Fund | C42: =80000/10 -> 8000 | D42: =C42 -> 8000 | E42: =D42 -> 8000 | F42: =E42 -> 8000 | G42: =F42 -> 8000 | H42: =G42 -> 8000 | K42: =H42 -> 8000 | L42: =K42 -> 8000 | M42: =L42 -> 8000 | N42: =M42 -> 8000 | O42: =SUM(C42:N42) -> 80000 | P42: 80000
A43: Other General | B43: Payment Processing (Moyasar) | C43: 73500 | D43: 73500 | E43: 73500 | F43: 73500 | G43: 73500 | H43: 73500 | I43: 0 | J43: 0 | K43: 73500 | L43: 73500 | M43: 73500 | N43: 73500 | O43: =SUM(C43:N43) -> 735000 | P43: 735000 | S43: Moved from Finance Costs — online payment commissions
A44: Other General | B44: PFC Contribution (6%) | C44: =(Reference_Data!B8+Reference_Data!B9)*94%*6% -> 328299.13 | D44: =(Reference_Data!C8+Reference_Data!C9)*94%*6% -> 328299.13 | E44: =(Reference_Data!D8+Reference_Data!D9)*94%*6% -> 328299.13 | F44: =(Reference_Data!E8+Reference_Data!E9)*94%*6% -> 328299.13 | G44: =(Reference_Data!F8+Reference_Data!F9)*94%*6% -> 328299.13 | H44: =(Reference_Data!G8+Reference_Data!G9)*94%*6% -> 758083.54 | I44: =(Reference_Data!H8+Reference_Data!H9)*94%*6% -> 0 | J44: =(Reference_Data!I8+Reference_Data!I9)*94%*6% -> 0 | ... N44: =(Reference_Data!M8+Reference_Data!M9)*94%*6% -> 328299.13 | O44: =SUM(C44:N44) -> 3766271.1 | P44: 4120473 | S44: AEFE to recalculate based on revenue
B45: Subtotal Other General | C45: =SUM(C38:C44) -> 418799.13 | D45: =SUM(D38:D44) -> 418799.13 | E45: =SUM(E38:E44) -> 418799.13 | F45: =SUM(F38:F44) -> 418799.13 | G45: =SUM(G38:G44) -> 418799.13 | H45: =SUM(H38:H44) -> 848583.54 | I45: =SUM(I38:I44) -> 0 | J45: =SUM(J38:J44) -> 0 | ... R45: =SUM(R38:R44) -> 5167.57
A47: School Materials
A48: School Materials | B48: Workbooks (Fichiers) | C48: 45119.95 | D48: 45119.95 | E48: 45119.95 | F48: 45119.95 | G48: 45119.95 | H48: 45119.95 | I48: 45119.95 | J48: 45119.95 | K48: 45119.95 | L48: 45119.95 | M48: 45119.95 | N48: 45119.95 | O48: =SUM(C48:N48) -> 541439.4 | P48: 541439.36 | Q48: 0 | R48: 24713.69
A49: School Materials | B49: Supplies (Fournitures) | C49: 35451.39 | D49: 35451.39 | E49: 35451.39 | F49: 35451.39 | G49: 35451.39 | H49: 35451.39 | I49: 35451.39 | J49: 35451.39 | K49: 35451.39 | L49: 35451.39 | M49: 35451.39 | N49: 35451.39 | O49: =SUM(C49:N49) -> 425416.68 | P49: 425416.64
A50: School Materials | B50: Other Materials | C50: 8333.33 | D50: 8333.33 | E50: 8333.33 | F50: 8333.33 | G50: 8333.33 | H50: 8333.33 | I50: 8333.33 | J50: 8333.33 | K50: 8333.33 | L50: 8333.33 | M50: 8333.33 | N50: 8333.33 | O50: =SUM(C50:N50) -> 99999.96 | P50: 100000
B51: Subtotal School Materials | C51: =SUM(C48:C50) -> 88904.67 | D51: =SUM(D48:D50) -> 88904.67 | E51: =SUM(E48:E50) -> 88904.67 | F51: =SUM(F48:F50) -> 88904.67 | G51: =SUM(G48:G50) -> 88904.67 | H51: =SUM(H48:H50) -> 88904.67 | I51: =SUM(I48:I50) -> 88904.67 | J51: =SUM(J48:J50) -> 88904.67 | ... R51: =SUM(R48:R50) -> 24713.69
A53: Pedagogical
A54: Pedagogical | B54: Pedagogical Credits | C54: 36878.25 | D54: 36878.25 | E54: 36878.25 | F54: 36878.25 | G54: 36878.25 | H54: 36878.25 | I54: 36878.25 | J54: 36878.25 | K54: 36878.25 | L54: 36878.25 | M54: 36878.25 | N54: 36878.25 | O54: =SUM(C54:N54) -> 442539 | P54: 442539 | S54: Clarify purpose
A55: Pedagogical | B55: Teaching Credits | C55: 23078.5 | D55: 23078.5 | E55: 23078.5 | F55: 23078.5 | G55: 23078.5 | H55: 23078.5 | I55: 23078.5 | J55: 23078.5 | K55: 23078.5 | L55: 23078.5 | M55: 23078.5 | N55: 23078.5 | O55: =SUM(C55:N55) -> 276942 | P55: 276942
B56: Subtotal Pedagogical | C56: =SUM(C54:C55) -> 59956.75 | D56: =SUM(D54:D55) -> 59956.75 | E56: =SUM(E54:E55) -> 59956.75 | F56: =SUM(F54:F55) -> 59956.75 | G56: =SUM(G54:G55) -> 59956.75 | H56: =SUM(H54:H55) -> 59956.75 | I56: =SUM(I54:I55) -> 59956.75 | J56: =SUM(J54:J55) -> 59956.75 | ... R56: =SUM(R54:R55) -> 0
A58: Library & Subscriptions
A59: Library & Subscriptions | B59: BCD Subscriptions | C59: 1842.67 | D59: 1842.67 | E59: 1842.67 | F59: 1842.67 | G59: 1842.67 | H59: 1842.67 | I59: 1842.67 | J59: 1842.67 | K59: 1842.67 | L59: 1842.67 | M59: 1842.67 | N59: 1842.67 | O59: =SUM(C59:N59) -> 22112.04 | P59: 22112.08 | Q59: 0 | R59: 7276.24
A60: Library & Subscriptions | B60: CDI Subscriptions | C60: 995.54 | D60: 995.54 | E60: 995.54 | F60: 995.54 | G60: 995.54 | H60: 995.54 | I60: 995.54 | J60: 995.54 | K60: 995.54 | L60: 995.54 | M60: 995.54 | N60: 995.54 | O60: =SUM(C60:N60) -> 11946.48 | P60: 11946.48 | Q60: 0 | R60: 11731.56
B61: Subtotal Library & Subscriptions | C61: =SUM(C59:C60) -> 2838.21 | D61: =SUM(D59:D60) -> 2838.21 | E61: =SUM(E59:E60) -> 2838.21 | F61: =SUM(F59:F60) -> 2838.21 | G61: =SUM(G59:G60) -> 2838.21 | H61: =SUM(H59:H60) -> 2838.21 | I61: =SUM(I59:I60) -> 2838.21 | J61: =SUM(J59:J60) -> 2838.21 | ... R61: =SUM(R59:R60) -> 19007.8
A63: Evaluation & Testing
A64: Evaluation & Testing | B64: Tests & Evaluations | C64: 1041.67 | D64: 1041.67 | E64: 1041.67 | F64: 1041.67 | G64: 1041.67 | H64: 1041.67 | I64: 1041.67 | J64: 1041.67 | K64: 1041.67 | L64: 1041.67 | M64: 1041.67 | N64: 1041.67 | O64: =SUM(C64:N64) -> 12500.04 | P64: 12500
B65: Subtotal Evaluation & Testing | C65: =SUM(C64) -> 1041.67 | D65: =SUM(D64) -> 1041.67 | E65: =SUM(E64) -> 1041.67 | F65: =SUM(F64) -> 1041.67 | G65: =SUM(G64) -> 1041.67 | H65: =SUM(H64) -> 1041.67 | I65: =SUM(I64) -> 1041.67 | J65: =SUM(J64) -> 1041.67 | ... R65: =SUM(R64) -> 0
A67: Activities & Projects
A68: Activities & Projects | B68: School Projects | C68: 25000 | D68: 25000 | E68: 25000 | F68: 25000 | G68: 25000 | H68: 25000 | I68: 25000 | J68: 25000 | K68: 25000 | L68: 25000 | M68: 25000 | N68: 25000 | O68: =SUM(C68:N68) -> 300000 | P68: 300000
A69: Activities & Projects | B69: Trip Accompaniment | C69: 16666.67 | D69: 16666.67 | E69: 16666.67 | F69: 16666.67 | G69: 16666.67 | H69: 16666.67 | I69: 16666.67 | J69: 16666.67 | K69: 16666.67 | L69: 16666.67 | M69: 16666.67 | N69: 16666.67 | O69: =SUM(C69:N69) -> 200000.04 | P69: 200000
A70: Activities & Projects | B70: School Outings – Bus | C70: 3750 | D70: 3750 | E70: 3750 | F70: 3750 | G70: 3750 | H70: 3750 | I70: 3750 | J70: 3750 | K70: 3750 | L70: 3750 | M70: 3750 | N70: 3750 | O70: =SUM(C70:N70) -> 45000 | P70: 45000
B71: Subtotal Activities & Projects | C71: =SUM(C68:C70) -> 45416.67 | D71: =SUM(D68:D70) -> 45416.67 | E71: =SUM(E68:E70) -> 45416.67 | F71: =SUM(F68:F70) -> 45416.67 | G71: =SUM(G68:G70) -> 45416.67 | H71: =SUM(H68:H70) -> 45416.67 | I71: =SUM(I68:I70) -> 45416.67 | J71: =SUM(J68:J70) -> 45416.67 | ... R71: =SUM(R68:R70) -> 0
A73: TOTAL OTHER OPERATING EXPENSES | C73: =C9+C15+C20+C25+C30+C35+C45+C51+C56+C61+C65+C71 -> 1922625 | D73: =D9+D15+D20+D25+D30+D35+D45+D51+D56+D61+D65+D71 -> 1922625 | E73: =E9+E15+E20+E25+E30+E35+E45+E51+E56+E61+E65+E71 -> 1922625 | F73: =F9+F15+F20+F25+F30+F35+F45+F51+F56+F61+F65+F71 -> 1922625 | G73: =G9+G15+G20+G25+G30+G35+G45+G51+G56+G61+G65+G71 -> 1922625 | H73: =H9+H15+H20+H25+H30+H35+H45+H51+H56+H61+H65+H71 -> 2352409.4 | I73: =I9+I15+I20+I25+I30+I35+I45+I51+I56+I61+I65+I71 -> 1381825.9 | J73: =J9+J15+J20+J25+J30+J35+J45+J51+J56+J61+J65+J71 -> 1381825.9 | ... R73: =R9+R15+R20+R25+R30+R35+R45+R51+R56+R61+R65+R71 -> 11559716
B74: % of Revenue | C74: =IF(Reference_Data!C13=0,0,C73/Reference_Data!C13) -> 0.32306642 | D74: =IF(Reference_Data!D13=0,0,D73/Reference_Data!D13) -> 0.32306642 | E74: =IF(Reference_Data!E13=0,0,E73/Reference_Data!E13) -> 0.31346729 | F74: =IF(Reference_Data!F13=0,0,F73/Reference_Data!F13) -> 0.31346729 | G74: =IF(Reference_Data!G13=0,0,G73/Reference_Data!G13) -> 0.14166671 | H74: =IF(Reference_Data!H13=0,0,H73/Reference_Data!H13) -> 551.02266 | I74: =IF(Reference_Data!I13=0,0,I73/Reference_Data!I13) -> 323.67554 | J74: =IF(Reference_Data!J13=0,0,J73/Reference_Data!J13) -> 0.20045562 | ... O74: =IF(Reference_Data!O13=0,0,O73/Reference_Data!O13) -> 0

Sheet Non_Operating_Items
A1: EFIR — Non-Operating Items FY2026
A2: Depreciation, Impairment, Finance Income & Costs — Monthly Input
A4: Category | B4: Line Item | C4: Jan | D4: Feb | E4: Mar | F4: Apr | G4: May | H4: Jun | I4: Jul | J4: Aug | K4: Sep | L4: Oct | M4: Nov | N4: Dec | O4: FY2026 Total | P4: Comments
A5: DEPRECIATION & AMORTIZATION
A6: Depreciation | B6: Depreciation of Assets (DOA) | C6: 439818 | D6: 439818 | E6: 439818 | F6: 439818 | G6: 439818 | H6: 439818 | I6: 439818 | J6: 439818 | K6: 439818 | L6: 439818 | M6: 439818 | N6: 439818 | O6: =SUM(C6:N6) -> 5277816 | P6: Link to CapEx file once available
B7: Total Depreciation & Amortization | C7: =C6 -> 439818 | D7: =D6 -> 439818 | E7: =E6 -> 439818 | F7: =F6 -> 439818 | G7: =G6 -> 439818 | H7: =H6 -> 439818 | I7: =I6 -> 439818 | J7: =J6 -> 439818 | ... O7: =O6 -> 5277816
A9: IMPAIRMENT LOSSES (IFRS 9)
A10: Impairment | B10: Expected Credit Loss – Bad Debt | O10: =SUM(C10:N10) -> 0 | P10: Review: existing provision may cover
B11: Total Impairment Losses | C11: =C10 -> 0 | D11: =D10 -> 0 | E11: =E10 -> 0 | F11: =F10 -> 0 | G11: =G10 -> 0 | H11: =H10 -> 0 | I11: =I10 -> 0 | J11: =J10 -> 0 | ... O11: =O10 -> 0
A13: FINANCE INCOME
A14: Finance Income | B14: Investment Income (Placements) | C14: 41666.67 | D14: 41666.67 | E14: 41666.67 | F14: 41666.67 | G14: 41666.67 | H14: 41666.67 | I14: 41666.67 | J14: 41666.67 | K14: 41666.67 | L14: 41666.67 | M14: 41666.67 | N14: 41666.67 | O14: =SUM(C14:N14) -> 500000.04 | P14: Analyze cashflow needs
A15: Finance Income | B15: Foreign Exchange Gains | C15: 0 | D15: =C15 -> 0 | E15: =D15 -> 0 | F15: =E15 -> 0 | G15: =F15 -> 0 | H15: =G15 -> 0 | I15: =H15 -> 0 | J15: =I15 -> 0 | K15: =J15 -> 0 | ... N15: =M15 -> 0 | O15: =SUM(C15:N15) -> 0
B16: Total Finance Income | C16: =SUM(C14:C15) -> 41666.67 | D16: =SUM(D14:D15) -> 41666.67 | E16: =SUM(E14:E15) -> 41666.67 | F16: =SUM(F14:F15) -> 41666.67 | G16: =SUM(G14:G15) -> 41666.67 | H16: =SUM(H14:H15) -> 41666.67 | I16: =SUM(I14:I15) -> 41666.67 | J16: =SUM(J14:J15) -> 41666.67 | ... O16: =SUM(O14:O15) -> 500000.04
A18: FINANCE COSTS
A19: Finance Costs | B19: Bank Charges | C19: 23820.85 | D19: 23820.85 | E19: 23820.85 | F19: 23820.85 | G19: 23820.85 | H19: 23820.85 | I19: 23820.85 | J19: 23820.85 | K19: 23820.85 | L19: 23820.85 | M19: 23820.85 | N19: 23820.85 | O19: =SUM(C19:N19) -> 285850.2
A20: Finance Costs | B20: Foreign Exchange Losses | C20: 0 | D20: =C20 -> 0 | E20: =D20 -> 0 | F20: =E20 -> 0 | G20: =F20 -> 0 | H20: =G20 -> 0 | I20: =H20 -> 0 | J20: =I20 -> 0 | K20: =J20 -> 0 | ... N20: =M20 -> 0 | O20: =SUM(C20:N20) -> 0
B21: Total Finance Costs | C21: =SUM(C19:C20) -> 23820.85 | D21: =SUM(D19:D20) -> 23820.85 | E21: =SUM(E19:E20) -> 23820.85 | F21: =SUM(F19:F20) -> 23820.85 | G21: =SUM(G19:G20) -> 23820.85 | H21: =SUM(H19:H20) -> 23820.85 | I21: =SUM(I19:I20) -> 23820.85 | J21: =SUM(J19:J20) -> 23820.85 | ... O21: =SUM(O19:O20) -> 285850.2

Sheet Summary
A1: EFIR — OpEx & Non-Operating Summary FY2026
A2: Auto-calculated from input sheets — Do not edit
A4: Item | B4: Jan | C4: Feb | D4: Mar | E4: Apr | F4: May | G4: Jun | H4: Jul | I4: Aug | J4: Sep | K4: Oct | L4: Nov | M4: Dec | N4: FY2026 Total
A5: Total Other Operating Expenses | B5: =Operating_Expenses!C73 -> 1922625 | C5: =Operating_Expenses!D73 -> 1922625 | D5: =Operating_Expenses!E73 -> 1922625 | E5: =Operating_Expenses!F73 -> 1922625 | F5: =Operating_Expenses!G73 -> 1922625 | G5: =Operating_Expenses!H73 -> 2352409.4 | H5: =Operating_Expenses!I73 -> 1381825.9 | I5: =Operating_Expenses!J73 -> 1381825.9 | ... M5: =Operating_Expenses!N73 -> 1922625 | N5: =SUM(B5:M5) -> 22473182
A6: Total Depreciation & Amortization | B6: =Non_Operating_Items!C7 -> 439818 | C6: =Non_Operating_Items!D7 -> 439818 | D6: =Non_Operating_Items!E7 -> 439818 | E6: =Non_Operating_Items!F7 -> 439818 | F6: =Non_Operating_Items!G7 -> 439818 | G6: =Non_Operating_Items!H7 -> 439818 | H6: =Non_Operating_Items!I7 -> 439818 | I6: =Non_Operating_Items!J7 -> 439818 | ... M6: =Non_Operating_Items!N7 -> 439818 | N6: =SUM(B6:M6) -> 5277816
A7: Total Impairment Losses | B7: =Non_Operating_Items!C11 -> 0 | C7: =Non_Operating_Items!D11 -> 0 | D7: =Non_Operating_Items!E11 -> 0 | E7: =Non_Operating_Items!F11 -> 0 | F7: =Non_Operating_Items!G11 -> 0 | G7: =Non_Operating_Items!H11 -> 0 | H7: =Non_Operating_Items!I11 -> 0 | I7: =Non_Operating_Items!J11 -> 0 | ... M7: =Non_Operating_Items!N11 -> 0 | N7: =SUM(B7:M7) -> 0
A8: Total Finance Income | B8: =Non_Operating_Items!C16 -> 41666.67 | C8: =Non_Operating_Items!D16 -> 41666.67 | D8: =Non_Operating_Items!E16 -> 41666.67 | E8: =Non_Operating_Items!F16 -> 41666.67 | F8: =Non_Operating_Items!G16 -> 41666.67 | G8: =Non_Operating_Items!H16 -> 41666.67 | H8: =Non_Operating_Items!I16 -> 41666.67 | I8: =Non_Operating_Items!J16 -> 41666.67 | ... M8: =Non_Operating_Items!N16 -> 41666.67 | N8: =SUM(B8:M8) -> 500000.04
A9: Total Finance Costs | B9: =Non_Operating_Items!C21 -> 23820.85 | C9: =Non_Operating_Items!D21 -> 23820.85 | D9: =Non_Operating_Items!E21 -> 23820.85 | E9: =Non_Operating_Items!F21 -> 23820.85 | F9: =Non_Operating_Items!G21 -> 23820.85 | G9: =Non_Operating_Items!H21 -> 23820.85 | H9: =Non_Operating_Items!I21 -> 23820.85 | I9: =Non_Operating_Items!J21 -> 23820.85 | ... M9: =Non_Operating_Items!N21 -> 23820.85 | N9: =SUM(B9:M9) -> 285850.2
