Workbook

Sheet IFRS Mapping
A1: EFIR – IFRS RECLASSIFIED MONTHLY BUDGET FY2026
A2: Reclassified per IAS 1 Presentation — Currency: SAR
A4: IFRS Category | B4: Line Item | C4: Jan | D4: Feb | E4: Mar | F4: Apr | G4: May | H4: Jun | I4: Jul | J4: Aug | K4: Sep | L4: Oct | M4: Nov | N4: Dec | O4: FY2026 Total | Q4: Comments
A5: REVENUE FROM CONTRACTS WITH CUSTOMERS (IFRS 15)
A6: Tuition Fees | B6: Maternelle – Tarif Réduit | C6: 138227.96 | D6: 138227.96 | E6: 138227.96 | F6: 138227.96 | G6: 138227.96 | H6: 138227.96 | I6: 0 | J6: 0 | K6: 138227.96 | L6: 138227.96 | M6: 138227.96 | N6: 138227.96 | O6: =SUM(C6:N6) -> 1382279.6
A7: Tuition Fees | B7: Maternelle – Tarif Plein | C7: 574782.21 | D7: 574782.21 | E7: 574782.21 | F7: 574782.21 | G7: 574782.21 | H7: 574782.21 | I7: 0 | J7: 0 | K7: 574782.21 | L7: 574782.21 | M7: 574782.21 | N7: 574782.21 | O7: =SUM(C7:N7) -> 5747822.1
A8: Tuition Fees | B8: Élémentaire – Tarif Réduit | C8: 322596.69 | D8: 322596.69 | E8: 322596.69 | F8: 322596.69 | G8: 322596.69 | H8: 322596.69 | I8: 0 | J8: 0 | K8: 322596.69 | L8: 322596.69 | M8: 322596.69 | N8: 322596.69 | O8: =SUM(C8:N8) -> 3225966.9
A9: Tuition Fees | B9: Élémentaire – Tarif Plein | C9: 1712432.6 | D9: 1712432.6 | E9: 1712432.6 | F9: 1712432.6 | G9: 1712432.6 | H9: 1712432.6 | I9: 0 | J9: 0 | K9: 1712432.6 | L9: 1712432.6 | M9: 1712432.6 | N9: 1712432.6 | O9: =SUM(C9:N9) -> 17124326
A10: Tuition Fees | B10: Collège – Tarif Réduit | C10: 142238.8 | D10: 142238.8 | E10: 142238.8 | F10: 142238.8 | G10: 142238.8 | H10: 142238.8 | I10: 0 | J10: 0 | K10: 142238.8 | L10: 142238.8 | M10: 142238.8 | N10: 142238.8 | O10: =SUM(C10:N10) -> 1422388
A11: Tuition Fees | B11: Collège – Tarif Plein | C11: 1631389.1 | D11: 1631389.1 | E11: 1631389.1 | F11: 1631389.1 | G11: 1631389.1 | H11: 1631389.1 | I11: 0 | J11: 0 | K11: 1631389.1 | L11: 1631389.1 | M11: 1631389.1 | N11: 1631389.1 | O11: =SUM(C11:N11) -> 16313891
A12: Tuition Fees | B12: Lycée – Tarif Réduit | C12: 63065.22 | D12: 63065.22 | E12: 63065.22 | F12: 63065.22 | G12: 63065.22 | H12: 63065.22 | I12: 0 | J12: 0 | K12: 63065.22 | L12: 63065.22 | M12: 63065.22 | N12: 63065.22 | O12: =SUM(C12:N12) -> 630652.2
A13: Tuition Fees | B13: Lycée – Tarif Plein | C13: 1236173.9 | D13: 1236173.9 | E13: 1236173.9 | F13: 1236173.9 | G13: 1236173.9 | H13: 1236173.9 | I13: 0 | J13: 0 | K13: 1236173.9 | L13: 1236173.9 | M13: 1236173.9 | N13: 1236173.9 | O13: =SUM(C13:N13) -> 12361739
A14: Registration Fees | B14: New Student Registration (DPI/FD) | C14: 0 | D14: 0 | E14: 0 | F14: 0 | G14: 0 | H14: 0 | I14: 0 | J14: 0 | K14: 936000 | L14: 0 | M14: 0 | N14: 0 | O14: =SUM(C14:N14) -> 936000
A15: Registration Fees | B15: Re-registration (DAI) | C15: 0 | D15: 0 | E15: 0 | F15: 0 | G15: 0 | H15: 7620291 | I15: 0 | J15: 0 | K15: 0 | L15: 0 | M15: 0 | N15: 0 | O15: =SUM(C15:N15) -> 7620291
A16: Registration Fees | B16: Evaluation Tests | C16: 0 | D16: 0 | E16: 0 | F16: 0 | G16: 0 | H16: 0 | I16: 0 | J16: 0 | K16: 6250 | L16: 6250 | M16: 0 | N16: 0 | O16: =SUM(C16:N16) -> 12500
A17: Activities & Services | B17: After-School Activities (APS) | C17: 123000 | D17: 123000 | E17: 123000 | F17: 123000 | G17: 123000 | H17: 123000 | I17: 0 | J17: 0 | K17: 123000 | L17: 123000 | M17: 123000 | N17: 123000 | O17: =SUM(C17:N17) -> 1230000
... A21: Examination Fees | B21: DNB Examination Fees | C21: 0 | D21: 0 | E21: 0 | F21: 30375 | G21: 30375 | H21: 0 | I21: 0 | J21: 0 | K21: 0 | L21: 0 | M21: 0 | N21: 0 | O21: =SUM(C21:N21) -> 60750
A22: Examination Fees | B22: EAF Examination Fees | C22: 0 | D22: 0 | E22: 0 | F22: 45375 | G22: 45375 | H22: 0 | I22: 0 | J22: 0 | K22: 0 | L22: 0 | M22: 0 | N22: 0 | O22: =SUM(C22:N22) -> 90750 | R22: students | S22: fees/student
B23: Total Revenue from Contracts with Customers | C23: =SUM(C6:C22) -> 5946906.5 | D23: =SUM(D6:D22) -> 5946906.5 | E23: =SUM(E6:E22) -> 5946906.5 | F23: =SUM(F6:F22) -> 6129146 | G23: =SUM(G6:G22) -> 6129146 | H23: =SUM(H6:H22) -> 13567198 | I23: =SUM(I6:I22) -> 0 | J23: =SUM(J6:J22) -> 0 | ... O23: =SUM(O6:O22) -> 68455135 | R23: 1753 | S23: =O23/R23 -> 39050.277 | V23: Confirmed
A25: RENTAL INCOME (IFRS 16)
A26: Rental Income | B26: PSG Academy KSA (Rental) | C26: 4269.17 | D26: 4269.17 | E26: 4269.17 | F26: 4269.17 | G26: 4269.17 | H26: 4269.17 | I26: 4269.17 | J26: 4269.17 | K26: 4269.17 | L26: 4269.17 | M26: 4269.17 | N26: 4269.17 | O26: =SUM(C26:N26) -> 51230.04
B27: Total Rental Income | C27: =C26 -> 4269.17 | D27: =D26 -> 4269.17 | E27: =E26 -> 4269.17 | F27: =F26 -> 4269.17 | G27: =G26 -> 4269.17 | H27: =H26 -> 4269.17 | I27: =I26 -> 4269.17 | J27: =J26 -> 4269.17 | ... O27: =O26 -> 51230.04
A29: STAFF COSTS
A30: Local Staff Salaries | B30: Base Salaries (Existing Staff) | C30: 1447910 | D30: 1447910 | E30: 1447910 | F30: 1447910 | G30: 1447910 | H30: 1447910 | I30: 1447910 | J30: 1447910 | K30: 1478810 | L30: 1478810 | M30: 1478810 | N30: 1478810 | O30: =SUM(C30:N30) -> 17498520 | Q30: Extra teacher to be removed??
A31: Local Staff Salaries | B31: Housing Allowance (Existing) | C31: 391300 | D31: 391300 | E31: 391300 | F31: 391300 | G31: 391300 | H31: 391300 | I31: 391300 | J31: 391300 | K31: 391300 | L31: 391300 | M31: 391300 | N31: 391300 | O31: =SUM(C31:N31) -> 4695600
A32: Local Staff Salaries | B32: Transport Allowance (Existing) | C32: 78259 | D32: 78259 | E32: 78259 | F32: 78259 | G32: 78259 | H32: 78259 | I32: 78259 | J32: 78259 | K32: 78259 | L32: 78259 | M32: 78259 | N32: 78259 | O32: =SUM(C32:N32) -> 939108
A33: Local Staff Salaries | B33: Responsibility Premium (Existing) | C33: 12500 | D33: 12500 | E33: 12500 | F33: 12500 | G33: 12500 | H33: 12500 | I33: 12500 | J33: 12500 | K33: 12500 | L33: 12500 | M33: 12500 | N33: 12500 | O33: =SUM(C33:N33) -> 150000
A34: Local Staff Salaries | B34: HSA Overtime (Existing) | C34: 57424 | D34: 57424 | E34: 57424 | F34: 57424 | G34: 57424 | H34: 57424 | I34: 0 | J34: 0 | K34: 57424 | L34: 57424 | M34: 57424 | N34: 57424 | O34: =SUM(C34:N34) -> 574240 | Q34: Why that much? Any optimization
A35: Local Staff Salaries | B35: Subtotal Existing Staff | C35: =SUM(C30:C34) -> 1987393 | D35: =SUM(D30:D34) -> 1987393 | E35: =SUM(E30:E34) -> 1987393 | F35: =SUM(F30:F34) -> 1987393 | G35: =SUM(G30:G34) -> 1987393 | H35: =SUM(H30:H34) -> 1987393 | I35: =SUM(I30:I34) -> 1929969 | J35: =SUM(J30:J34) -> 1929969 | ... O35: =SUM(O30:O34) -> 23857468
A36: Local Staff Salaries | B36: New Positions (6 FTE – Sep 2026) | C36: 0 | D36: 0 | E36: 0 | F36: 0 | G36: 0 | H36: 0 | I36: 0 | J36: 0 | K36: 57400 | L36: 57400 | M36: 57400 | N36: 57400 | O36: =SUM(C36:N36) -> 229600
A37: Additional Staff Costs | B37: Replacement Contracts | C37: 22681 | D37: 22681 | E37: 22681 | F37: 22681 | G37: 22681 | H37: 22681 | I37: 22681 | J37: 22681 | K37: 22681 | L37: 22681 | M37: 22681 | N37: 22681 | O37: =SUM(C37:N37) -> 272172
A38: Additional Staff Costs | B38: Continuing Education (1% Payroll) | C38: 25504 | D38: 25504 | E38: 25504 | F38: 25504 | G38: 25504 | H38: 25504 | I38: 25504 | J38: 25504 | K38: 25504 | L38: 25504 | M38: 25504 | N38: 25504 | O38: =SUM(C38:N38) -> 306048 | Q38: To recalculate with accurate salary base
A39: Additional Staff Costs | B39: Resident Salaries | C39: 613008 | D39: 613008 | E39: 613008 | F39: 613008 | G39: 613008 | H39: 613008 | I39: 613008 | J39: 613008 | K39: 613008 | L39: 613008 | M39: 613008 | N39: 613008 | O39: =SUM(C39:N39) -> 7356096 | Q39: To provide the latest assumptions
A40: Additional Staff Costs | B40: Pension Contribution (35%) | C40: 69750 | D40: 69750 | E40: 69750 | F40: 69750 | G40: 69750 | H40: 69750 | I40: 69750 | J40: 69750 | K40: 69750 | L40: 69750 | M40: 69750 | N40: 69750 | O40: =SUM(C40:N40) -> 837000 | Q40: To validate once AEFE provide invoices
A41: Additional Staff Costs | B41: Resident Housing & Flights | C41: 53950 | D41: 53950 | E41: 53950 | F41: 53950 | G41: 53950 | H41: 53950 | I41: 53950 | J41: 53950 | K41: 53950 | L41: 53950 | M41: 53950 | N41: 53950 | O41: =SUM(C41:N41) -> 647400 | Q41: Negotiations? Is it approved?
A42: Employer Charges | B42: GOSI – Saudi Employees | C42: 2497 | D42: 2497 | E42: 2497 | F42: 2497 | G42: 2497 | H42: 2497 | I42: 2497 | J42: 2497 | K42: 2526 | L42: 2526 | M42: 2526 | N42: 2526 | O42: =SUM(C42:N42) -> 30080
A43: Employer Charges | B43: End of Service Provision | C43: 125579 | D43: 125579 | E43: 125579 | F43: 125579 | G43: 125579 | H43: 125579 | I43: 125579 | J43: 125579 | K43: 125579 | L43: 125579 | M43: 125579 | N43: 125579 | O43: =SUM(C43:N43) -> 1506948
A44: Employer Charges | B44: Ajeer Costs – Existing (160) | C44: 152266.67 | D44: 152266.67 | E44: 152266.67 | F44: 152266.67 | G44: 152266.67 | H44: 152266.67 | I44: 152266.67 | J44: 152266.67 | K44: 152266.67 | L44: 152266.67 | M44: 152266.67 | N44: 152266.67 | O44: =SUM(C44:N44) -> 1827200 | Q44: Actual projection, to clean provisions
A45: Employer Charges | B45: Ajeer Costs – New (6, Sep–Dec) | C45: 0 | D45: 0 | E45: 0 | F45: 0 | G45: 0 | H45: 0 | I45: 0 | J45: 0 | K45: 5710 | L45: 5710 | M45: 5710 | N45: 5710 | O45: =SUM(C45:N45) -> 22840
B46: Total Staff Costs | C46: =C35+SUM(C36:C45) -> 3052628.7 | D46: =D35+SUM(D36:D45) -> 3052628.7 | E46: =E35+SUM(E36:E45) -> 3052628.7 | F46: =F35+SUM(F36:F45) -> 3052628.7 | G46: =G35+SUM(G36:G45) -> 3052628.7 | H46: =H35+SUM(H36:H45) -> 3052628.7 | I46: =I35+SUM(I36:I45) -> 2995204.7 | J46: =J35+SUM(J36:J45) -> 2995204.7 | ... O46: =O35+SUM(O36:O45) -> 36892852 | S46: =O46/S23 -> 944.75264 | V46: Confirmed
A48: OTHER OPERATING EXPENSES
A49: Rent & Utilities | B49: Rent | C49: 699626.5 | D49: 699626.5 | E49: 699626.5 | F49: 699626.5 | G49: 699626.5 | H49: 699626.5 | I49: 699626.5 | J49: 699626.5 | K49: 699626.5 | L49: 699626.5 | M49: 699626.5 | N49: 699626.5 | O49: =SUM(C49:N49) -> 8395518 | Q49: Why this amount? Use to be 7.2m to check contract
A50: Rent & Utilities | B50: Electricity | C50: 35000 | D50: 35000 | E50: 35000 | F50: 35000 | G50: 35000 | H50: 35000 | I50: 35000 | J50: 35000 | K50: 35000 | L50: 35000 | M50: 35000 | N50: 35000 | O50: =SUM(C50:N50) -> 420000
A51: Rent & Utilities | B51: Water | C51: 13833.33 | D51: 13833.33 | E51: 13833.33 | F51: 13833.33 | G51: 13833.33 | H51: 13833.33 | I51: 13833.33 | J51: 13833.33 | K51: 13833.33 | L51: 13833.33 | M51: 13833.33 | N51: 13833.33 | O51: =SUM(C51:N51) -> 165999.96
A52: Building Services | B52: Maintenance Contracts | C52: 230521 | D52: 230521 | E52: 230521 | F52: 230521 | G52: 230521 | H52: 230521 | I52: 230521 | J52: 230521 | K52: 230521 | L52: 230521 | M52: 230521 | N52: 230521 | O52: =SUM(C52:N52) -> 2766252 | Q52: To review Metabuild contract
A53: Building Services | B53: Security | C53: 144200 | D53: 144200 | E53: 144200 | F53: 144200 | G53: 144200 | H53: 144200 | I53: 144200 | J53: 144200 | K53: 144200 | L53: 144200 | M53: 144200 | N53: 144200 | O53: =SUM(C53:N53) -> 1730400 | Q53: To review security contract
A54: Building Services | B54: Equipment Maintenance | C54: 29657.17 | D54: 29657.17 | E54: 29657.17 | F54: 29657.17 | G54: 29657.17 | H54: 29657.17 | I54: 29657.17 | J54: 29657.17 | K54: 29657.17 | L54: 29657.17 | M54: 29657.17 | N54: 29657.17 | O54: =SUM(C54:N54) -> 355886.04
A55: Office & Supplies | B55: Administration Supplies | C55: 38761.58 | D55: 38761.58 | E55: 38761.58 | F55: 38761.58 | G55: 38761.58 | H55: 38761.58 | I55: 38761.58 | J55: 38761.58 | K55: 38761.58 | L55: 38761.58 | M55: 38761.58 | N55: 38761.58 | O55: =SUM(C55:N55) -> 465138.96 | Q55: What is this ?
A56: Office & Supplies | B56: Photocopier Contract | C56: 6192.67 | D56: 6192.67 | E56: 6192.67 | F56: 6192.67 | G56: 6192.67 | H56: 6192.67 | I56: 6192.67 | J56: 6192.67 | K56: 6192.67 | L56: 6192.67 | M56: 6192.67 | N56: 6192.67 | O56: =SUM(C56:N56) -> 74312.04
A57: Insurance | B57: Medical Insurance – Saudi Staff | C57: 5794.42 | D57: 5794.42 | E57: 5794.42 | F57: 5794.42 | G57: 5794.42 | H57: 5794.42 | I57: 5794.42 | J57: 5794.42 | K57: 5794.42 | L57: 5794.42 | M57: 5794.42 | N57: 5794.42 | O57: =SUM(C57:N57) -> 69533.04
A58: Insurance | B58: School Insurance | C58: 8482.42 | D58: 8482.42 | E58: 8482.42 | F58: 8482.42 | G58: 8482.42 | H58: 8482.42 | I58: 8482.42 | J58: 8482.42 | K58: 8482.42 | L58: 8482.42 | M58: 8482.42 | N58: 8482.42 | O58: =SUM(C58:N58) -> 101789.04
A59: Professional Services | B59: External Audit | C59: 2666.67 | D59: 2666.67 | E59: 2666.67 | F59: 2666.67 | G59: 2666.67 | H59: 2666.67 | I59: 2666.67 | J59: 2666.67 | K59: 2666.67 | L59: 2666.67 | M59: 2666.67 | N59: 2666.67 | O59: =SUM(C59:N59) -> 32000.04
A60: Professional Services | B60: Communication | C60: 2500 | D60: 2500 | E60: 2500 | F60: 2500 | G60: 2500 | H60: 2500 | I60: 2500 | J60: 2500 | K60: 2500 | L60: 2500 | M60: 2500 | N60: 2500 | O60: =SUM(C60:N60) -> 30000
A61: IT & Telecom | B61: IT Equipment | C61: 27506.42 | D61: 27506.42 | E61: 27506.42 | F61: 27506.42 | G61: 27506.42 | H61: 27506.42 | I61: 27506.42 | J61: 27506.42 | K61: 27506.42 | L61: 27506.42 | M61: 27506.42 | N61: 27506.42 | O61: =SUM(C61:N61) -> 330077.04 | Q61: What is this for?
A62: IT & Telecom | B62: Telephone & Internet | C62: 21982.58 | D62: 21982.58 | E62: 21982.58 | F62: 21982.58 | G62: 21982.58 | H62: 21982.58 | I62: 21982.58 | J62: 21982.58 | K62: 21982.58 | L62: 21982.58 | M62: 21982.58 | N62: 21982.58 | O62: =SUM(C62:N62) -> 263790.96
A63: Other General | B63: New School Provision | C63: 125000 | D63: 125000 | E63: 125000 | F63: 125000 | G63: 125000 | H63: 125000 | I63: 125000 | J63: 125000 | K63: 125000 | L63: 125000 | M63: 125000 | N63: 125000 | O63: =SUM(C63:N63) -> 1500000 | Q63: Not required, to be removed
A64: Other General | B64: Vehicle Fuel & Maintenance | C64: 1666.67 | D64: 1666.67 | E64: 1666.67 | F64: 1666.67 | G64: 1666.67 | H64: 1666.67 | I64: 1666.67 | J64: 1666.67 | K64: 1666.67 | L64: 1666.67 | M64: 1666.67 | N64: 1666.67 | O64: =SUM(C64:N64) -> 20000.04
A65: Other General | B65: Infirmary | C65: 1939.08 | D65: 1939.08 | E65: 1939.08 | F65: 1939.08 | G65: 1939.08 | H65: 1939.08 | I65: 1939.08 | J65: 1939.08 | K65: 1939.08 | L65: 1939.08 | M65: 1939.08 | N65: 1939.08 | O65: =SUM(C65:N65) -> 23268.96
A66: Other General | B66: Reception & Events | C66: 20833.33 | D66: 20833.33 | E66: 20833.33 | F66: 20833.33 | G66: 20833.33 | H66: 20833.33 | I66: 20833.33 | J66: 20833.33 | K66: 20833.33 | L66: 20833.33 | M66: 20833.33 | N66: 20833.33 | O66: =SUM(C66:N66) -> 249999.96
A67: Other General | B67: Class Photos / Printing | C67: 1515 | D67: 1515 | E67: 1515 | F67: 1515 | G67: 1515 | H67: 1515 | I67: 1515 | J67: 1515 | K67: 1515 | L67: 1515 | M67: 1515 | N67: 1515 | O67: =SUM(C67:N67) -> 18180
A68: Other General | B68: Social Aid Fund | C68: 6666.67 | D68: 6666.67 | E68: 6666.67 | F68: 6666.67 | G68: 6666.67 | H68: 6666.67 | I68: 6666.67 | J68: 6666.67 | K68: 6666.67 | L68: 6666.67 | M68: 6666.67 | N68: 6666.67 | O68: =SUM(C68:N68) -> 80000.04
A69: Other General | B69: PFC Contribution (6%) | C69: 343372.75 | D69: 343372.75 | E69: 343372.75 | F69: 343372.75 | G69: 343372.75 | H69: 343372.75 | I69: 343372.75 | J69: 343372.75 | K69: 343372.75 | L69: 343372.75 | M69: 343372.75 | N69: 343372.75 | O69: =SUM(C69:N69) -> 4120473 | Q69: AEFE to recalculate based on the estimated revenues
A70: School Materials | B70: Workbooks (Fichiers) | C70: 45119.95 | D70: 45119.95 | E70: 45119.95 | F70: 45119.95 | G70: 45119.95 | H70: 45119.95 | I70: 45119.95 | J70: 45119.95 | K70: 45119.95 | L70: 45119.95 | M70: 45119.95 | N70: 45119.95 | O70: =SUM(C70:N70) -> 541439.4
A71: School Materials | B71: Supplies (Fournitures) | C71: 35451.39 | D71: 35451.39 | E71: 35451.39 | F71: 35451.39 | G71: 35451.39 | H71: 35451.39 | I71: 35451.39 | J71: 35451.39 | K71: 35451.39 | L71: 35451.39 | M71: 35451.39 | N71: 35451.39 | O71: =SUM(C71:N71) -> 425416.68
A72: School Materials | B72: Other Materials | C72: 8333.33 | D72: 8333.33 | E72: 8333.33 | F72: 8333.33 | G72: 8333.33 | H72: 8333.33 | I72: 8333.33 | J72: 8333.33 | K72: 8333.33 | L72: 8333.33 | M72: 8333.33 | N72: 8333.33 | O72: =SUM(C72:N72) -> 99999.96
A73: Pedagogical | B73: Pedagogical Credits | C73: 36878.25 | D73: 36878.25 | E73: 36878.25 | F73: 36878.25 | G73: 36878.25 | H73: 36878.25 | I73: 36878.25 | J73: 36878.25 | K73: 36878.25 | L73: 36878.25 | M73: 36878.25 | N73: 36878.25 | O73: =SUM(C73:N73) -> 442539 | Q73: What is this line?
A74: Pedagogical | B74: Teaching Credits | C74: 23078.5 | D74: 23078.5 | E74: 23078.5 | F74: 23078.5 | G74: 23078.5 | H74: 23078.5 | I74: 23078.5 | J74: 23078.5 | K74: 23078.5 | L74: 23078.5 | M74: 23078.5 | N74: 23078.5 | O74: =SUM(C74:N74) -> 276942
A75: Library & Subscriptions | B75: BCD Subscriptions | C75: 1842.67 | D75: 1842.67 | E75: 1842.67 | F75: 1842.67 | G75: 1842.67 | H75: 1842.67 | I75: 1842.67 | J75: 1842.67 | K75: 1842.67 | L75: 1842.67 | M75: 1842.67 | N75: 1842.67 | O75: =SUM(C75:N75) -> 22112.04
A76: Library & Subscriptions | B76: CDI Subscriptions | C76: 995.54 | D76: 995.54 | E76: 995.54 | F76: 995.54 | G76: 995.54 | H76: 995.54 | I76: 995.54 | J76: 995.54 | K76: 995.54 | L76: 995.54 | M76: 995.54 | N76: 995.54 | O76: =SUM(C76:N76) -> 11946.48
A77: Evaluation & Testing | B77: Tests & Evaluations | C77: 1041.67 | D77: 1041.67 | E77: 1041.67 | F77: 1041.67 | G77: 1041.67 | H77: 1041.67 | I77: 1041.67 | J77: 1041.67 | K77: 1041.67 | L77: 1041.67 | M77: 1041.67 | N77: 1041.67 | O77: =SUM(C77:N77) -> 12500.04
A78: Activities & Projects | B78: School Projects | C78: 25000 | D78: 25000 | E78: 25000 | F78: 25000 | G78: 25000 | H78: 25000 | I78: 25000 | J78: 25000 | K78: 25000 | L78: 25000 | M78: 25000 | N78: 25000 | O78: =SUM(C78:N78) -> 300000
A79: Activities & Projects | B79: Trip Accompaniment | C79: 16666.67 | D79: 16666.67 | E79: 16666.67 | F79: 16666.67 | G79: 16666.67 | H79: 16666.67 | I79: 16666.67 | J79: 16666.67 | K79: 16666.67 | L79: 16666.67 | M79: 16666.67 | N79: 16666.67 | O79: =SUM(C79:N79) -> 200000.04
A80: Activities & Projects | B80: School Outings – Bus | C80: 3750 | D80: 3750 | E80: 3750 | F80: 3750 | G80: 3750 | H80: 3750 | I80: 3750 | J80: 3750 | K80: 3750 | L80: 3750 | M80: 3750 | N80: 3750 | O80: =SUM(C80:N80) -> 45000
B81: Total Other Operating Expenses | C81: =SUM(C49:C80) -> 1965876.2 | D81: =SUM(D49:D80) -> 1965876.2 | E81: =SUM(E49:E80) -> 1965876.2 | F81: =SUM(F49:F80) -> 1965876.2 | G81: =SUM(G49:G80) -> 1965876.2 | H81: =SUM(H49:H80) -> 1965876.2 | I81: =SUM(I49:I80) -> 1965876.2 | J81: =SUM(J49:J80) -> 1965876.2 | ... O81: =SUM(O49:O80) -> 23590515 | V81: Confirmed
A83: DEPRECIATION & AMORTIZATION
A84: Depreciation | B84: Depreciation of Assets (DOA) | C84: 439818 | D84: 439818 | E84: 439818 | F84: 439818 | G84: 439818 | H84: 439818 | I84: 439818 | J84: 439818 | K84: 439818 | L84: 439818 | M84: 439818 | N84: 439818 | O84: =SUM(C84:N84) -> 5277816 | Q84: Why Depreciation is jumping?
B85: Total Depreciation & Amortization | C85: =C84 -> 439818 | D85: =D84 -> 439818 | E85: =E84 -> 439818 | F85: =F84 -> 439818 | G85: =G84 -> 439818 | H85: =H84 -> 439818 | I85: =I84 -> 439818 | J85: =J84 -> 439818 | ... O85: =O84 -> 5277816 | V85: Confirmed
A87: IMPAIRMENT LOSSES (IFRS 9)
A88: Impairment | B88: Expected Credit Loss – Bad Debt Provision | C88: 95432.83 | D88: 95432.83 | E88: 95432.83 | F88: 95432.83 | G88: 95432.83 | H88: 95432.83 | I88: 95432.83 | J88: 95432.83 | K88: 95432.83 | L88: 95432.83 | M88: 95432.83 | N88: 95432.83 | O88: =SUM(C88:N88) -> 1145194 | Q88: There is already a provisions
B89: Total Impairment Losses | C89: =C88 -> 95432.83 | D89: =D88 -> 95432.83 | E89: =E88 -> 95432.83 | F89: =F88 -> 95432.83 | G89: =G88 -> 95432.83 | H89: =H88 -> 95432.83 | I89: =I88 -> 95432.83 | J89: =J88 -> 95432.83 | ... O89: =O88 -> 1145194 | V89: Confirmed
A91: FINANCE INCOME
A92: Finance Income | B92: Investment Income (Placements) | C92: 41666.67 | D92: 41666.67 | E92: 41666.67 | F92: 41666.67 | G92: 41666.67 | H92: 41666.67 | I92: 41666.67 | J92: 41666.67 | K92: 41666.67 | L92: 41666.67 | M92: 41666.67 | N92: 41666.67 | O92: =SUM(C92:N92) -> 500000.04 | Q92: To analyze the cashflow needs and adjust the amount
A93: Finance Income | B93: Foreign Exchange Gains | C93: 8261.25 | D93: 8261.25 | E93: 8261.25 | F93: 8261.25 | G93: 8261.25 | H93: 8261.25 | I93: 8261.25 | J93: 8261.25 | K93: 8261.25 | L93: 8261.25 | M93: 8261.25 | N93: 8261.25 | O93: =SUM(C93:N93) -> 99135
B94: Total Finance Income | C94: =SUM(C92:C93) -> 49927.92 | D94: =SUM(D92:D93) -> 49927.92 | E94: =SUM(E92:E93) -> 49927.92 | F94: =SUM(F92:F93) -> 49927.92 | G94: =SUM(G92:G93) -> 49927.92 | H94: =SUM(H92:H93) -> 49927.92 | I94: =SUM(I92:I93) -> 49927.92 | J94: =SUM(J92:J93) -> 49927.92 | ... O94: =SUM(O92:O93) -> 599135.04 | V94: Confirmed
A96: FINANCE COSTS
A97: Finance Costs | B97: Payment Processing Fees (Moyasar) | C97: 73500 | D97: 73500 | E97: 73500 | F97: 73500 | G97: 73500 | H97: 73500 | I97: 0 | J97: 0 | K97: 73500 | L97: 73500 | M97: 73500 | N97: 73500 | O97: =SUM(C97:N97) -> 735000 | Q97: Need to stop
A98: Finance Costs | B98: Bank Charges | C98: 23820.85 | D98: 23820.85 | E98: 23820.85 | F98: 23820.85 | G98: 23820.85 | H98: 23820.85 | I98: 23820.85 | J98: 23820.85 | K98: 23820.85 | L98: 23820.85 | M98: 23820.85 | N98: 23820.85 | O98: =SUM(C98:N98) -> 285850.2
A99: Finance Costs | B99: Foreign Exchange Losses | C99: 60250 | D99: 60250 | E99: 60250 | F99: 60250 | G99: 60250 | H99: 60250 | I99: 60250 | J99: 60250 | K99: 60250 | L99: 60250 | M99: 60250 | N99: 60250 | O99: =SUM(C99:N99) -> 723000
B100: Total Finance Costs | C100: =SUM(C97:C99) -> 157570.85 | D100: =SUM(D97:D99) -> 157570.85 | E100: =SUM(E97:E99) -> 157570.85 | F100: =SUM(F97:F99) -> 157570.85 | G100: =SUM(G97:G99) -> 157570.85 | H100: =SUM(H97:H99) -> 157570.85 | I100: =SUM(I97:I99) -> 84070.85 | J100: =SUM(J97:J99) -> 84070.85 | ... O100: =SUM(O97:O99) -> 1743850.2 | V100: Confirmed
C102: =C23+C27-C46-C81-C85-C89+C94-C100 -> 289777.04 | D102: =D23+D27-D46-D81-D85-D89+D94-D100 -> 289777.04 | E102: =E23+E27-E46-E81-E85-E89+E94-E100 -> 289777.04 | F102: =F23+F27-F46-F81-F85-F89+F94-F100 -> 472016.54 | G102: =G23+G27-G46-G81-G85-G89+G94-G100 -> 472016.54 | H102: =H23+H27-H46-H81-H85-H89+H94-H100 -> 7910068 | I102: =I23+I27-I46-I81-I85-I89+I94-I100 -> -5526205.5 | J102: =J23+J27-J46-J81-J85-J89+J94-J100 -> -5526205.5 | ... O102: =O23+O27-O46-O81-O85-O89+O94-O100 -> 455273.42
N103: -1

Sheet IFRS Income Statement
A1: EFIR – BUDGET INCOME STATEMENT FY2026
A2: Presented per IAS 1 — Function of Expense Method — Currency: SAR
B4: Jan | C4: Feb | D4: Mar | E4: Apr | F4: May | G4: Jun | H4: Jul | I4: Aug | J4: Sep | K4: Oct | L4: Nov | M4: Dec | N4: FY2026 Total
A5: Revenue
A6: Tuition fees | B6: =SUM('IFRS Mapping'!C6:C13) -> 5820906.5 | C6: =SUM('IFRS Mapping'!D6:D13) -> 5820906.5 | D6: =SUM('IFRS Mapping'!E6:E13) -> 5820906.5 | E6: =SUM('IFRS Mapping'!F6:F13) -> 5820906.5 | F6: =SUM('IFRS Mapping'!G6:G13) -> 5820906.5 | G6: =SUM('IFRS Mapping'!H6:H13) -> 5820906.5 | H6: =SUM('IFRS Mapping'!I6:I13) -> 0 | I6: =SUM('IFRS Mapping'!J6:J13) -> 0 | ... M6: =SUM('IFRS Mapping'!N6:N13) -> 5820906.5 | N6: =SUM(B6:M6) -> 58209065
A7: Registration & re-registration fees | B7: =SUM('IFRS Mapping'!C14:C16) -> 0 | C7: =SUM('IFRS Mapping'!D14:D16) -> 0 | D7: =SUM('IFRS Mapping'!E14:E16) -> 0 | E7: =SUM('IFRS Mapping'!F14:F16) -> 0 | F7: =SUM('IFRS Mapping'!G14:G16) -> 0 | G7: =SUM('IFRS Mapping'!H14:H16) -> 7620291 | H7: =SUM('IFRS Mapping'!I14:I16) -> 0 | I7: =SUM('IFRS Mapping'!J14:J16) -> 0 | ... M7: =SUM('IFRS Mapping'!N14:N16) -> 0 | N7: =SUM(B7:M7) -> 8568791
A8: Activities & services | B8: =SUM('IFRS Mapping'!C17:C19) -> 126000 | C8: =SUM('IFRS Mapping'!D17:D19) -> 126000 | D8: =SUM('IFRS Mapping'!E17:E19) -> 126000 | E8: =SUM('IFRS Mapping'!F17:F19) -> 126000 | F8: =SUM('IFRS Mapping'!G17:G19) -> 126000 | G8: =SUM('IFRS Mapping'!H17:H19) -> 126000 | H8: =SUM('IFRS Mapping'!I17:I19) -> 0 | I8: =SUM('IFRS Mapping'!J17:J19) -> 0 | ... M8: =SUM('IFRS Mapping'!N17:N19) -> 152400 | N8: =SUM(B8:M8) -> 1312800
A9: Examination fees | B9: =SUM('IFRS Mapping'!C20:C22) -> 0 | C9: =SUM('IFRS Mapping'!D20:D22) -> 0 | D9: =SUM('IFRS Mapping'!E20:E22) -> 0 | E9: =SUM('IFRS Mapping'!F20:F22) -> 182239.5 | F9: =SUM('IFRS Mapping'!G20:G22) -> 182239.5 | G9: =SUM('IFRS Mapping'!H20:H22) -> 0 | H9: =SUM('IFRS Mapping'!I20:I22) -> 0 | I9: =SUM('IFRS Mapping'!J20:J22) -> 0 | ... M9: =SUM('IFRS Mapping'!N20:N22) -> 0 | N9: =SUM(B9:M9) -> 364479
A10: Revenue from contracts with customers | B10: =SUM(B6:B9) -> 5946906.5 | C10: =SUM(C6:C9) -> 5946906.5 | D10: =SUM(D6:D9) -> 5946906.5 | E10: =SUM(E6:E9) -> 6129146 | F10: =SUM(F6:F9) -> 6129146 | G10: =SUM(G6:G9) -> 13567198 | H10: =SUM(H6:H9) -> 0 | I10: =SUM(I6:I9) -> 0 | ... M10: =SUM(M6:M9) -> 5973306.5 | N10: =SUM(B10:M10) -> 68455135
A11: Rental income | B11: ='IFRS Mapping'!C27 -> 4269.17 | C11: ='IFRS Mapping'!D27 -> 4269.17 | D11: ='IFRS Mapping'!E27 -> 4269.17 | E11: ='IFRS Mapping'!F27 -> 4269.17 | F11: ='IFRS Mapping'!G27 -> 4269.17 | G11: ='IFRS Mapping'!H27 -> 4269.17 | H11: ='IFRS Mapping'!I27 -> 4269.17 | I11: ='IFRS Mapping'!J27 -> 4269.17 | ... M11: ='IFRS Mapping'!N27 -> 4269.17 | N11: =SUM(B11:M11) -> 51230.04
A12: Total Revenue | B12: =B10+B11 -> 5951175.7 | C12: =C10+C11 -> 5951175.7 | D12: =D10+D11 -> 5951175.7 | E12: =E10+E11 -> 6133415.2 | F12: =F10+F11 -> 6133415.2 | G12: =G10+G11 -> 13571467 | H12: =H10+H11 -> 4269.17 | I12: =I10+I11 -> 4269.17 | ... M12: =M10+M11 -> 5977575.7 | N12: =SUM(B12:M12) -> 68506365
A14: Operating Expenses
A15: Staff costs | B15: =-'IFRS Mapping'!C46 -> -3052628.7 | C15: =-'IFRS Mapping'!D46 -> -3052628.7 | D15: =-'IFRS Mapping'!E46 -> -3052628.7 | E15: =-'IFRS Mapping'!F46 -> -3052628.7 | F15: =-'IFRS Mapping'!G46 -> -3052628.7 | G15: =-'IFRS Mapping'!H46 -> -3052628.7 | H15: =-'IFRS Mapping'!I46 -> -2995204.7 | I15: =-'IFRS Mapping'!J46 -> -2995204.7 | ... M15: =-'IFRS Mapping'!N46 -> -3146667.7 | N15: =SUM(B15:M15) -> -36892852 | O15: =N15/$N$12 -> -0.53853174
A16: Other operating expenses | B16: =-'IFRS Mapping'!C81 -> -1965876.2 | C16: =-'IFRS Mapping'!D81 -> -1965876.2 | D16: =-'IFRS Mapping'!E81 -> -1965876.2 | E16: =-'IFRS Mapping'!F81 -> -1965876.2 | F16: =-'IFRS Mapping'!G81 -> -1965876.2 | G16: =-'IFRS Mapping'!H81 -> -1965876.2 | H16: =-'IFRS Mapping'!I81 -> -1965876.2 | I16: =-'IFRS Mapping'!J81 -> -1965876.2 | ... M16: =-'IFRS Mapping'!N81 -> -1965876.2 | N16: =SUM(B16:M16) -> -23590515 | O16: =N16/$N$12 -> -0.34435508
A17: Depreciation & amortization | B17: =-'IFRS Mapping'!C85 -> -439818 | C17: =-'IFRS Mapping'!D85 -> -439818 | D17: =-'IFRS Mapping'!E85 -> -439818 | E17: =-'IFRS Mapping'!F85 -> -439818 | F17: =-'IFRS Mapping'!G85 -> -439818 | G17: =-'IFRS Mapping'!H85 -> -439818 | H17: =-'IFRS Mapping'!I85 -> -439818 | I17: =-'IFRS Mapping'!J85 -> -439818 | ... M17: =-'IFRS Mapping'!N85 -> -439818 | N17: =SUM(B17:M17) -> -5277816 | O17: =N17/$N$12 -> -0.07704125
A18: Impairment losses on receivables | B18: =-'IFRS Mapping'!C89 -> -95432.83 | C18: =-'IFRS Mapping'!D89 -> -95432.83 | D18: =-'IFRS Mapping'!E89 -> -95432.83 | E18: =-'IFRS Mapping'!F89 -> -95432.83 | F18: =-'IFRS Mapping'!G89 -> -95432.83 | G18: =-'IFRS Mapping'!H89 -> -95432.83 | H18: =-'IFRS Mapping'!I89 -> -95432.83 | I18: =-'IFRS Mapping'!J89 -> -95432.83 | ... M18: =-'IFRS Mapping'!N89 -> -95432.83 | N18: =SUM(B18:M18) -> -1145194
A19: Total Operating Expenses | B19: =SUM(B15:B18) -> -5553755.7 | C19: =SUM(C15:C18) -> -5553755.7 | D19: =SUM(D15:D18) -> -5553755.7 | E19: =SUM(E15:E18) -> -5553755.7 | F19: =SUM(F15:F18) -> -5553755.7 | G19: =SUM(G15:G18) -> -5553755.7 | H19: =SUM(H15:H18) -> -5496331.7 | I19: =SUM(I15:I18) -> -5496331.7 | ... M19: =SUM(M15:M18) -> -5647794.7 | N19: =SUM(B19:M19) -> -66906377 | O19: =N19/$N$12 -> -0.97664467
A21: OPERATING PROFIT / (LOSS) | B21: =B12+B19 -> 397419.97 | C21: =C12+C19 -> 397419.97 | D21: =D12+D19 -> 397419.97 | E21: =E12+E19 -> 579659.47 | F21: =F12+F19 -> 579659.47 | G21: =G12+G19 -> 8017711 | H21: =H12+H19 -> -5492062.6 | I21: =I12+I19 -> -5492062.6 | ... M21: =M12+M19 -> 329780.97 | N21: =SUM(B21:M21) -> 1599988.6 | O21: =N21/$N$12 -> 0.023355327
A23: Finance
A24: Finance income | B24: ='IFRS Mapping'!C94 -> 49927.92 | C24: ='IFRS Mapping'!D94 -> 49927.92 | D24: ='IFRS Mapping'!E94 -> 49927.92 | E24: ='IFRS Mapping'!F94 -> 49927.92 | F24: ='IFRS Mapping'!G94 -> 49927.92 | G24: ='IFRS Mapping'!H94 -> 49927.92 | H24: ='IFRS Mapping'!I94 -> 49927.92 | I24: ='IFRS Mapping'!J94 -> 49927.92 | ... M24: ='IFRS Mapping'!N94 -> 49927.92 | N24: =SUM(B24:M24) -> 599135.04
A25: Finance costs | B25: =-'IFRS Mapping'!C100 -> -157570.85 | C25: =-'IFRS Mapping'!D100 -> -157570.85 | D25: =-'IFRS Mapping'!E100 -> -157570.85 | E25: =-'IFRS Mapping'!F100 -> -157570.85 | F25: =-'IFRS Mapping'!G100 -> -157570.85 | G25: =-'IFRS Mapping'!H100 -> -157570.85 | H25: =-'IFRS Mapping'!I100 -> -84070.85 | I25: =-'IFRS Mapping'!J100 -> -84070.85 | ... M25: =-'IFRS Mapping'!N100 -> -157570.85 | N25: =SUM(B25:M25) -> -1743850.2
A26: Net Finance Income / (Cost) | B26: =B24+B25 -> -107642.93 | C26: =C24+C25 -> -107642.93 | D26: =D24+D25 -> -107642.93 | E26: =E24+E25 -> -107642.93 | F26: =F24+F25 -> -107642.93 | G26: =G24+G25 -> -107642.93 | H26: =H24+H25 -> -34142.93 | I26: =I24+I25 -> -34142.93 | ... M26: =M24+M25 -> -107642.93 | N26: =SUM(B26:M26) -> -1144715.2 | O26: =N26/$N$12 -> -0.016709617
A28: PROFIT / (LOSS) BEFORE ZAKAT | B28: =B21+B26 -> 289777.04 | C28: =C21+C26 -> 289777.04 | D28: =D21+D26 -> 289777.04 | E28: =E21+E26 -> 472016.54 | F28: =F21+F26 -> 472016.54 | G28: =G21+G26 -> 7910068 | H28: =H21+H26 -> -5526205.5 | I28: =I21+I26 -> -5526205.5 | ... M28: =M21+M26 -> 222138.04 | N28: =SUM(B28:M28) -> 455273.42
A29: Estimated Zakat (2.5%) | B29: =IF(B28>0,-B28*2.5%,0) -> -7244.426 | C29: =IF(C28>0,-C28*2.5%,0) -> -7244.426 | D29: =IF(D28>0,-D28*2.5%,0) -> -7244.426 | E29: =IF(E28>0,-E28*2.5%,0) -> -11800.413 | F29: =IF(F28>0,-F28*2.5%,0) -> -11800.413 | G29: =IF(G28>0,-G28*2.5%,0) -> -197751.7 | H29: =IF(H28>0,-H28*2.5%,0) -> 0 | I29: =IF(I28>0,-I28*2.5%,0) -> 0 | ... M29: =IF(M28>0,-M28*2.5%,0) -> -5553.451 | N29: =SUM(B29:M29) -> -287692.11 | O29: =N29/$N$12 -> -0.0041994946
A31: NET PROFIT / (LOSS) FOR THE PERIOD | B31: =B28+B29 -> 282532.61 | C31: =C28+C29 -> 282532.61 | D31: =D28+D29 -> 282532.61 | E31: =E28+E29 -> 460216.13 | F31: =F28+F29 -> 460216.13 | G31: =G28+G29 -> 7712316.3 | H31: =H28+H29 -> -5526205.5 | I31: =I28+I29 -> -5526205.5 | ... M31: =M28+M29 -> 216584.59 | N31: =SUM(B31:M31) -> 167581.31
A33: Notes:
A34: 1. Revenue presented net per IFRS 15 — Moyasar processing fees reclassified to Finance Costs.
A35: 2. Bad debt provision reclassified to Impairment Losses per IFRS 9 (Expected Credit Loss model).
A36: 3. Bank charges and FX losses reclassified from Administrative & General to Finance Costs per IAS 1.
A37: 4. Financial income (investment returns & FX gains) separated from operating revenue per IAS 1.
A38: 5. Zakat estimated at 2.5% on positive monthly profit — actual computation per ZATCA regulations may differ.
