Workbook

Sheet Méthodo
B3: METHODOLOGIE du modèle de projections financières
C5: Ce modèle est un outil d'aide à la décision, outil de projection dynamique des données fiancières d'un établissement déjà existant de l'EFE.
C6: Il permet de faire des simulations en faisant varier de nombreuses hypothèses telles que l'augmentation des frais de scolarité, de salaire, le nombre d'élèves par division … et en mesurant l'impact sur le résultat et sur l'augmentation induite des frais de scolarité.
C7: Le modèle donne une analyse par niveau, maternelle/élémentaire/collège/lycée.
C8: L'outil n'est pas directement à destination des établissements, il doit être préparé par un expert ou un personnel AEFE pour saisir des données historiques et de base. Ensuite, soit il peut être transmis à l'établissement qui complète et s'empare des prévisions, soit il est piloté en totalité par l'AEFE
C9: Le modèle ne concerne que la partie "fonctionnement pédagogique" cœur de métier de l'établissement. Les services annexes tels que la restauration, le transport, les activités extra scolaires ou les examens ne sont pas, et ne doivent pas être comptabilisés.
C11: Code Couleur :
C12: A saisir par l'AEFE
C13: A saisir par l'établissement - Seules les cellules en jaune sont à saisir ou modifier
C14: Informations concernant la maternelle
C15: Informations concernant l'élémentaire
C16: Informations concernant le collège
C17: Informations concernant le lycée
... C50: - lignes nb intervenants et base H/E et masquées

Sheet Projection Effectifs
A1: PROJECTION D'EFFECTIFS HOMOLOGUES
A3: HYPOTHESES | B3: Taux de croissance des cohortes
B4: Le taux de croissance pondéré par niveau de 2020 à 2023 permet de projeter les effectifs jusqu'à 2030
B5: Par exemple , s'il y a 50 élèves en CP et un taux de "montée" moyen de 110%, on prévoie un effectif de 55 élèves en CE1 l'année suivante
B6: Les cases en Jaune pour la Petite Section et le Préscolaire éventuel sont à saisir
B7: Les autres cases à partir de 2024 peuvent être forcées en cas de situation particulière ou atteinte du potentiel maximum
B8: Le taux de croissance moyen est calculé à partir des 3 années précédentes
A12: Année Scolaire Rentrée 20xx | B12: Taux Croissance moyen | C12: =VLOOKUP('Hypothèses '!$C$10,'table années scolaires'!$C$9:$O$13,'Hypothèses '!D$11,FALSE) -> 2021/2022 | D12: =VLOOKUP('Hypothèses '!$C$10,'table années scolaires'!$C$9:$O$13,'Hypothèses '!E$11,FALSE) -> 2022/2023 | E12: =VLOOKUP('Hypothèses '!$C$10,'table années scolaires'!$C$9:$O$13,'Hypothèses '!F$11,FALSE) -> 2023/2024 | F12: =VLOOKUP('Hypothèses '!$C$10,'table années scolaires'!$C$9:$O$13,'Hypothèses '!G$11,FALSE) -> 2024/2025 | G12: =VLOOKUP('Hypothèses '!$C$10,'table années scolaires'!$C$9:$O$13,'Hypothèses '!H$11,FALSE) -> 2025/2026 | H12: =VLOOKUP('Hypothèses '!$C$10,'table années scolaires'!$C$9:$O$13,'Hypothèses '!I$11,FALSE) -> 2026/2027 | I12: =VLOOKUP('Hypothèses '!$C$10,'table années scolaires'!$C$9:$O$13,'Hypothèses '!J$11,FALSE) -> 2027/2028 | J12: =VLOOKUP('Hypothèses '!$C$10,'table années scolaires'!$C$9:$O$13,'Hypothèses '!K$11,FALSE) -> 2028/2029 | ... M12: =VLOOKUP('Hypothèses '!$C$10,'table années scolaires'!$C$9:$O$13,'Hypothèses '!N$11,FALSE) -> 2031/2032 | O12: POTENTIEL | P12: Nb divisions | Q12: Nb max d'élèves
C13: =SUM(C15:C29) -> 0 | D13: =SUM(D15:D29) -> 0 | E13: =SUM(E15:E29) -> 0 | F13: =SUM(F15:F29) -> 1796 | G13: =SUM(G15:G29) -> 1825 | H13: =SUM(H15:H29) -> 1775 | I13: =SUM(I15:I29) -> 1709 | J13: =SUM(J15:J29) -> 1699 | ... M13: =SUM(M15:M29) -> 1677 | O13: =SUM(O15:O29) -> 1875
A14: 00- Préscolaire
A15: 01- Petite Section | F15: 61 | G15: 70 | H15: 60 | I15: 60 | J15: 120 | K15: 120 | L15: 120 | M15: 120 | O15: =P15*Q15 -> 125 | P15: 5 | Q15: 25
A16: 02- Moyenne Section | B16: =IFERROR((M16/E16)^(1/(8))-1,0) -> 0 | F16: 109 | G16: 72 | H16: =G15 -> 70 | I16: =H15 -> 60 | J16: =I15 -> 60 | K16: =J15 -> 120 | L16: =K15 -> 120 | M16: =L15 -> 120 | O16: =P16*Q16 -> 125 | P16: 5 | Q16: 25
A17: 03- Grande Section | B17: =IFERROR((M17/E17)^(1/(8))-1,0) -> 0 | F17: 123 | G17: 130 | H17: =G16 -> 72 | I17: =H16 -> 70 | J17: =I16 -> 60 | K17: =J16 -> 60 | L17: =K16 -> 120 | M17: =L16 -> 120 | O17: =P17*Q17 -> 125 | P17: 5 | Q17: 25
A18: 04- CP | B18: =IFERROR((M18/E18)^(1/(8))-1,0) -> 0 | F18: 116 | G18: 134 | H18: =G17 -> 130 | I18: =H17 -> 72 | J18: =I17 -> 70 | K18: =J17 -> 60 | L18: =K17 -> 60 | M18: =L17 -> 120 | O18: =P18*Q18 -> 125 | P18: 5 | Q18: 25
A19: 05- CE1 | B19: =IFERROR((M19/E19)^(1/(8))-1,0) -> 0 | F19: 140 | G19: 124 | H19: =G18 -> 134 | I19: =H18 -> 130 | J19: =I18 -> 72 | K19: =J18 -> 70 | L19: =K18 -> 60 | M19: =L18 -> 60 | O19: =P19*Q19 -> 125 | P19: 5 | Q19: 25
A20: 06- CE2 | B20: =IFERROR((M20/E20)^(1/(8))-1,0) -> 0 | F20: 126 | G20: 137 | H20: =G19 -> 124 | I20: =H19 -> 134 | J20: =I19 -> 130 | K20: =J19 -> 72 | L20: =K19 -> 70 | M20: =L19 -> 60 | O20: =P20*Q20 -> 125 | P20: 5 | Q20: 25
A21: 07- CM1 | B21: =IFERROR((M21/E21)^(1/(8))-1,0) -> 0 | F21: 124 | G21: 128 | H21: =G20 -> 137 | I21: =H20 -> 124 | J21: =I20 -> 134 | K21: =J20 -> 130 | L21: =K20 -> 72 | M21: =L20 -> 70 | O21: =P21*Q21 -> 125 | P21: 5 | Q21: 25
A22: 08- CM2 | B22: =IFERROR((M22/E22)^(1/(8))-1,0) -> 0 | F22: 145 | G22: 129 | H22: =G21 -> 128 | I22: =H21 -> 137 | J22: =I21 -> 124 | K22: =J21 -> 134 | L22: =K21 -> 130 | M22: =L21 -> 72 | O22: =P22*Q22 -> 125 | P22: 5 | Q22: 25
A23: 09- 6ème | B23: =IFERROR((M23/E23)^(1/(8))-1,0) -> 0 | F23: 146 | G23: 153 | H23: =G22 -> 129 | I23: =H22 -> 128 | J23: =I22 -> 137 | K23: =J22 -> 124 | L23: =K22 -> 134 | M23: =L22 -> 130 | O23: =P23*Q23 -> 125 | P23: 5 | Q23: 25
A24: 10- 5ème | B24: =IFERROR((M24/E24)^(1/(8))-1,0) -> 0 | F24: 121 | G24: 143 | H24: =G23 -> 153 | I24: =H23 -> 129 | J24: =I23 -> 128 | K24: =J23 -> 137 | L24: =K23 -> 124 | M24: =L23 -> 134 | O24: =P24*Q24 -> 125 | P24: 5 | Q24: 25
A25: 11- 4ème | B25: =IFERROR((M25/E25)^(1/(8))-1,0) -> 0 | F25: 104 | G25: 126 | H25: =G24 -> 143 | I25: =H24 -> 153 | J25: =I24 -> 129 | K25: =J24 -> 128 | L25: =K24 -> 137 | M25: =L24 -> 124 | O25: =P25*Q25 -> 125 | P25: 5 | Q25: 25
A26: 12- 3ème | B26: =IFERROR((M26/E26)^(1/(8))-1,0) -> 0 | F26: 128 | G26: 113 | H26: =G25 -> 126 | I26: =H25 -> 143 | J26: =I25 -> 153 | K26: =J25 -> 129 | L26: =K25 -> 128 | M26: =L25 -> 137 | O26: =P26*Q26 -> 125 | P26: 5 | Q26: 25
A27: 13- Seconde | B27: =IFERROR((M27/E27)^(1/(8))-1,0) -> 0 | F27: 130 | G27: 130 | H27: =G26 -> 113 | I27: =H26 -> 126 | J27: =I26 -> 143 | K27: =J26 -> 153 | L27: =K26 -> 129 | M27: =L26 -> 128 | O27: =P27*Q27 -> 125 | P27: 5 | Q27: 25
... A29: 15- Terminale | B29: =IFERROR((M29/E29)^(1/(8))-1,0) -> 0 | F29: 109 | G29: 110 | H29: =G28 -> 126 | I29: =H28 -> 130 | J29: =I28 -> 113 | K29: =J28 -> 126 | L29: =K28 -> 143 | M29: =L28 -> 153 | O29: =P29*Q29 -> 125 | P29: 5 | Q29: 25
R30: Clés de répartition
C31: =C12 -> 2021/2022 | D31: =D12 -> 2022/2023 | E31: =E12 -> 2023/2024 | F31: =F12 -> 2024/2025 | G31: =G12 -> 2025/2026 | H31: =H12 -> 2026/2027 | I31: =I12 -> 2027/2028 | J31: =J12 -> 2028/2029 | ... M31: =M12 -> 2031/2032 | R31: Pro rata Global | S31: =C12 -> 2021/2022 | T31: =D12 -> 2022/2023 | U31: =E12 -> 2023/2024 | V31: =F12 -> 2024/2025 | W31: =G12 -> 2025/2026 | X31: =H12 -> 2026/2027 | Y31: =I12 -> 2027/2028 | Z31: =J12 -> 2028/2029 | ... AC31: =M12 -> 2031/2032
A32: Maternelle | C32: =SUM(C14:C17) -> 0 | D32: =SUM(D14:D17) -> 0 | E32: =SUM(E14:E17) -> 0 | F32: =SUM(F14:F17) -> 293 | G32: =SUM(G14:G17) -> 272 | H32: =SUM(H14:H17) -> 202 | I32: =SUM(I14:I17) -> 190 | J32: =SUM(J14:J17) -> 240 | ... M32: =SUM(M14:M17) -> 360 | R32: Maternelle | S32: =IFERROR(C32/C$38,0) -> 0 | T32: =IFERROR(D32/D$38,0) -> 0 | U32: =IFERROR(E32/E$38,0) -> 0 | V32: =IFERROR(F32/F$38,0) -> 0.16314031 | W32: =IFERROR(G32/G$38,0) -> 0.1490411 | X32: =IFERROR(H32/H$38,0) -> 0.11380282 | Y32: =IFERROR(I32/I$38,0) -> 0.11117613 | Z32: =IFERROR(J32/J$38,0) -> 0.14125956 | ... AC32: =IFERROR(M32/M$38,0) -> 0.21466905
A33: Elémentaire | C33: =SUM(C18:C22) -> 0 | D33: =SUM(D18:D22) -> 0 | E33: =SUM(E18:E22) -> 0 | F33: =SUM(F18:F22) -> 651 | G33: =SUM(G18:G22) -> 652 | H33: =SUM(H18:H22) -> 653 | I33: =SUM(I18:I22) -> 597 | J33: =SUM(J18:J22) -> 530 | ... M33: =SUM(M18:M22) -> 382 | R33: Elémentaire | S33: =IFERROR(C33/C$38,0) -> 0 | T33: =IFERROR(D33/D$38,0) -> 0 | U33: =IFERROR(E33/E$38,0) -> 0 | V33: =IFERROR(F33/F$38,0) -> 0.36247216 | W33: =IFERROR(G33/G$38,0) -> 0.35726027 | X33: =IFERROR(H33/H$38,0) -> 0.36788732 | Y33: =IFERROR(I33/I$38,0) -> 0.34932709 | Z33: =IFERROR(J33/J$38,0) -> 0.3119482 | ... AC33: =IFERROR(M33/M$38,0) -> 0.22778772
A34: PRIMAIRE | C34: =C33+C32 -> 0 | D34: =D33+D32 -> 0 | E34: =E33+E32 -> 0 | F34: =F33+F32 -> 944 | G34: =G33+G32 -> 924 | H34: =H33+H32 -> 855 | I34: =I33+I32 -> 787 | J34: =J33+J32 -> 770 | ... M34: =M33+M32 -> 742 | R34: Collège | S34: =IFERROR(C35/C$38,0) -> 0 | T34: =IFERROR(D35/D$38,0) -> 0 | U34: =IFERROR(E35/E$38,0) -> 0 | V34: =IFERROR(F35/F$38,0) -> 0.27783964 | W34: =IFERROR(G35/G$38,0) -> 0.29315068 | X34: =IFERROR(H35/H$38,0) -> 0.31042254 | Y34: =IFERROR(I35/I$38,0) -> 0.32358104 | Z34: =IFERROR(J35/J$38,0) -> 0.32195409 | ... AC34: =IFERROR(M35/M$38,0) -> 0.31305903
A35: Collège | C35: =SUM(C23:C26) -> 0 | D35: =SUM(D23:D26) -> 0 | E35: =SUM(E23:E26) -> 0 | F35: =SUM(F23:F26) -> 499 | G35: =SUM(G23:G26) -> 535 | H35: =SUM(H23:H26) -> 551 | I35: =SUM(I23:I26) -> 553 | J35: =SUM(J23:J26) -> 547 | ... M35: =SUM(M23:M26) -> 525 | R35: Lycée | S35: =IFERROR(C36/C$38,0) -> 0 | T35: =IFERROR(D36/D$38,0) -> 0 | U35: =IFERROR(E36/E$38,0) -> 0 | V35: =IFERROR(F36/F$38,0) -> 0.19654788 | W35: =IFERROR(G36/G$38,0) -> 0.20054795 | X35: =IFERROR(H36/H$38,0) -> 0.20788732 | Y35: =IFERROR(I36/I$38,0) -> 0.21591574 | Z35: =IFERROR(J36/J$38,0) -> 0.22483814 | ... AC35: =IFERROR(M36/M$38,0) -> 0.2444842
A36: Lycée | C36: =SUM(C27:C29) -> 0 | D36: =SUM(D27:D29) -> 0 | E36: =SUM(E27:E29) -> 0 | F36: =SUM(F27:F29) -> 353 | G36: =SUM(G27:G29) -> 366 | H36: =SUM(H27:H29) -> 369 | I36: =SUM(I27:I29) -> 369 | J36: =SUM(J27:J29) -> 382 | ... M36: =SUM(M27:M29) -> 410 | S36: =IFERROR(C38/C$38,0) -> 0 | T36: =IFERROR(D38/D$38,0) -> 0 | U36: =IFERROR(E38/E$38,0) -> 0 | V36: =IFERROR(F38/F$38,0) -> 1 | W36: =G38/G$38 -> 1 | X36: =H38/H$38 -> 1 | Y36: =I38/I$38 -> 1 | Z36: =J38/J$38 -> 1 | AA36: =K38/K$38 -> 1 | AB36: =L38/L$38 -> 1 | AC36: =M38/M$38 -> 1
A37: SECONDAIRE | C37: =C36+C35 -> 0 | D37: =D36+D35 -> 0 | E37: =E36+E35 -> 0 | F37: =F36+F35 -> 852 | G37: =G36+G35 -> 901 | H37: =H36+H35 -> 920 | I37: =I36+I35 -> 922 | J37: =J36+J35 -> 929 | ... M37: =M36+M35 -> 935 | R37: Pro rata Niveau | S37: =C12 -> 2021/2022 | T37: =D12 -> 2022/2023 | U37: =E12 -> 2023/2024 | V37: =F12 -> 2024/2025 | W37: =G12 -> 2025/2026 | X37: =H12 -> 2026/2027 | Y37: =I12 -> 2027/2028 | Z37: =J12 -> 2028/2029 | ... AC37: =M12 -> 2031/2032
A38: Total ETABLISSEMENT | C38: =C37+C34 -> 0 | D38: =D37+D34 -> 0 | E38: =E37+E34 -> 0 | F38: =F37+F34 -> 1796 | G38: =G37+G34 -> 1825 | H38: =H37+H34 -> 1775 | I38: =I37+I34 -> 1709 | J38: =J37+J34 -> 1699 | ... M38: =M37+M34 -> 1677 | R38: Maternelle | S38: =IFERROR(C32/C$34,0) -> 0 | T38: =IFERROR(D32/D$34,0) -> 0 | U38: =IFERROR(E32/E$34,0) -> 0 | V38: =IFERROR(F32/F$34,0) -> 0.31038136 | W38: =IFERROR(G32/G$34,0) -> 0.29437229 | X38: =IFERROR(H32/H$34,0) -> 0.23625731 | Y38: =IFERROR(I32/I$34,0) -> 0.24142313 | Z38: =IFERROR(J32/J$34,0) -> 0.31168831 | ... AC38: =IFERROR(M32/M$34,0) -> 0.4851752
R39: Elémentaire | S39: =IFERROR(C33/C$34,0) -> 0 | T39: =IFERROR(D33/D$34,0) -> 0 | U39: =IFERROR(E33/E$34,0) -> 0 | V39: =IFERROR(F33/F$34,0) -> 0.68961864 | W39: =IFERROR(G33/G$34,0) -> 0.70562771 | X39: =IFERROR(H33/H$34,0) -> 0.76374269 | Y39: =IFERROR(I33/I$34,0) -> 0.75857687 | Z39: =IFERROR(J33/J$34,0) -> 0.68831169 | ... AC39: =IFERROR(M33/M$34,0) -> 0.5148248
R40: Primaire | S40: =S39+S38 -> 0 | T40: =T39+T38 -> 0 | U40: =U39+U38 -> 0 | V40: =V39+V38 -> 1 | W40: =W39+W38 -> 1 | X40: =X39+X38 -> 1 | Y40: =Y39+Y38 -> 1 | Z40: =Z39+Z38 -> 1 | ... AC40: =AC39+AC38 -> 1
R41: Collège | S41: =IFERROR(C35/C$37,0) -> 0 | T41: =IFERROR(D35/D$37,0) -> 0 | U41: =IFERROR(E35/E$37,0) -> 0 | V41: =IFERROR(F35/F$37,0) -> 0.58568075 | W41: =IFERROR(G35/G$37,0) -> 0.59378468 | X41: =IFERROR(H35/H$37,0) -> 0.59891304 | Y41: =IFERROR(I35/I$37,0) -> 0.59978308 | Z41: =IFERROR(J35/J$37,0) -> 0.58880517 | ... AC41: =IFERROR(M35/M$37,0) -> 0.56149733
R42: Lycée | S42: =IFERROR(C36/C$37,0) -> 0 | T42: =IFERROR(D36/D$37,0) -> 0 | U42: =IFERROR(E36/E$37,0) -> 0 | V42: =IFERROR(F36/F$37,0) -> 0.41431925 | W42: =IFERROR(G36/G$37,0) -> 0.40621532 | X42: =IFERROR(H36/H$37,0) -> 0.40108696 | Y42: =IFERROR(I36/I$37,0) -> 0.40021692 | Z42: =IFERROR(J36/J$37,0) -> 0.41119483 | ... AC42: =IFERROR(M36/M$37,0) -> 0.43850267
R43: Secondaire | S43: =S41+S42 -> 0 | T43: =T41+T42 -> 0 | U43: =U41+U42 -> 0 | V43: =V41+V42 -> 1 | W43: =W41+W42 -> 1 | X43: =X41+X42 -> 1 | Y43: =Y41+Y42 -> 1 | Z43: =Z41+Z42 -> 1 | ... AC43: =AC41+AC42 -> 1
R44: Taux croissance | S44: =C12 -> 2021/2022 | T44: =D12 -> 2022/2023 | U44: =E12 -> 2023/2024 | V44: =F12 -> 2024/2025 | W44: =G12 -> 2025/2026 | X44: =H12 -> 2026/2027 | Y44: =I12 -> 2027/2028 | Z44: =J12 -> 2028/2029 | ... AC44: =M12 -> 2031/2032
R45: Maternelle | T45: =IFERROR((D32-C32)/C32,0) -> 0 | U45: =IFERROR((E32-D32)/D32,0) -> 0 | V45: =IFERROR((F32-E32)/E32,0) -> 0 | W45: =IFERROR((G32-F32)/F32,0) -> -0.071672355 | X45: =IFERROR((H32-G32)/G32,0) -> -0.25735294 | Y45: =IFERROR((I32-H32)/H32,0) -> -0.059405941 | Z45: =IFERROR((J32-I32)/I32,0) -> 0.26315789 | AA45: =IFERROR((K32-J32)/J32,0) -> 0.25 | ... AC45: =IFERROR((M32-L32)/L32,0) -> 0
R46: Elémentaire | T46: =IFERROR((D33-C33)/C33,0) -> 0 | U46: =IFERROR((E33-D33)/D33,0) -> 0 | V46: =IFERROR((F33-E33)/E33,0) -> 0 | W46: =IFERROR((G33-F33)/F33,0) -> 0.0015360983 | X46: =IFERROR((H33-G33)/G33,0) -> 0.0015337423 | Y46: =IFERROR((I33-H33)/H33,0) -> -0.08575804 | Z46: =IFERROR((J33-I33)/I33,0) -> -0.11222781 | AA46: =IFERROR((K33-J33)/J33,0) -> -0.12075472 | ... AC46: =IFERROR((M33-L33)/L33,0) -> -0.025510204
R47: Collège | T47: =IFERROR((D35-C35)/C35,0) -> 0 | U47: =IFERROR((E35-D35)/D35,0) -> 0 | V47: =IFERROR((F35-E35)/E35,0) -> 0 | W47: =IFERROR((G35-F35)/F35,0) -> 0.072144289 | X47: =IFERROR((H35-G35)/G35,0) -> 0.029906542 | Y47: =IFERROR((I35-H35)/H35,0) -> 0.0036297641 | Z47: =IFERROR((J35-I35)/I35,0) -> -0.01084991 | AA47: =IFERROR((K35-J35)/J35,0) -> -0.053016453 | ... AC47: =IFERROR((M35-L35)/L35,0) -> 0.0038240918
R48: Lycée | T48: =IFERROR((D36-C36)/C36,0) -> 0 | U48: =IFERROR((E36-D36)/D36,0) -> 0 | V48: =IFERROR((F36-E36)/E36,0) -> 0 | W48: =IFERROR((G36-F36)/F36,0) -> 0.036827195 | X48: =IFERROR((H36-G36)/G36,0) -> 0.0081967213 | Y48: =IFERROR((I36-H36)/H36,0) -> 0 | Z48: =IFERROR((J36-I36)/I36,0) -> 0.035230352 | AA48: =IFERROR((K36-J36)/J36,0) -> 0.10471204 | ... AC48: =IFERROR((M36-L36)/L36,0) -> -0.035294118

Sheet Nbre de divisions
B1: R.2024 | E1: R.2025 | H1: R.2026 | K1: R.2027
A2: Année Scolaire Rentrée 20xx | B2: Effectifs | C2: Division | D2: Elève/classe | E2: Effectifs | F2: Division | G2: Elève/classe | H2: Effectifs | I2: Division | J2: Elèves/Classe | K2: Effectifs | L2: Division | M2: Elève/classe
B3: =SUM(B4:B18) -> 1794 | E3: =SUM(E4:E18) -> 1825 | H3: =SUM(H4:H18) -> 1765 | K3: =SUM(K4:K18) -> 1699
A4: 01- Petite Section | B4: 59 | C4: 3 | D4: =B4/C4 -> 19.666667 | E4: 70 | F4: 3 | G4: =E4/F4 -> 23.333333 | H4: 60 | K4: 60 | M4: =K4/L4 -> #DIV/0!
A5: 02- Moyenne Section | B5: 109 | C5: 5 | D5: =B5/C5 -> 21.8 | E5: 72 | F5: 3 | G5: =E5/F5 -> 24 | H5: 60 | K5: =H4 -> 60 | M5: =K5/L5 -> #DIV/0!
A6: 03- Grande Section | B6: 123 | C6: 5 | D6: =B6/C6 -> 24.6 | E6: 130 | F6: 5 | G6: =E6/F6 -> 26 | H6: =E5 -> 72 | K6: =H5 -> 60 | M6: =K6/L6 -> #DIV/0!
A7: 04- CP | B7: 116 | C7: 5 | D7: =B7/C7 -> 23.2 | E7: 134 | F7: 6 | G7: =E7/F7 -> 22.333333 | H7: =E6 -> 130 | K7: =H6 -> 72 | M7: =K7/L7 -> #DIV/0!
A8: 05- CE1 | B8: 140 | C8: 6 | D8: =B8/C8 -> 23.333333 | E8: 124 | F8: 5 | G8: =E8/F8 -> 24.8 | H8: =E7 -> 134 | K8: =H7 -> 130 | M8: =K8/L8 -> #DIV/0!
A9: 06- CE2 | B9: 126 | C9: 5 | D9: =B9/C9 -> 25.2 | E9: 137 | F9: 6 | G9: =E9/F9 -> 22.833333 | H9: =E8 -> 124 | K9: =H8 -> 134 | M9: =K9/L9 -> #DIV/0!
A10: 07- CM1 | B10: 124 | C10: 5 | D10: =B10/C10 -> 24.8 | E10: 128 | F10: 5 | G10: =E10/F10 -> 25.6 | H10: =E9 -> 137 | K10: =H9 -> 124 | M10: =K10/L10 -> #DIV/0!
A11: 08- CM2 | B11: 145 | C11: 6 | D11: =B11/C11 -> 24.166667 | E11: 129 | F11: 5 | G11: =E11/F11 -> 25.8 | H11: =E10 -> 128 | K11: =H10 -> 137 | M11: =K11/L11 -> #DIV/0!
A12: 09- 6ème | B12: 146 | C12: 6 | D12: =B12/C12 -> 24.333333 | E12: 153 | F12: 6 | G12: =E12/F12 -> 25.5 | H12: =E11 -> 129 | K12: =H11 -> 128 | M12: =K12/L12 -> #DIV/0!
A13: 10- 5ème | B13: 121 | C13: 5 | D13: =B13/C13 -> 24.2 | E13: 143 | F13: 6 | G13: =E13/F13 -> 23.833333 | H13: =E12 -> 153 | K13: =H12 -> 129 | M13: =K13/L13 -> #DIV/0!
A14: 11- 4ème | B14: 104 | C14: 4 | D14: =B14/C14 -> 26 | E14: 126 | F14: 5 | G14: =E14/F14 -> 25.2 | H14: =E13 -> 143 | K14: =H13 -> 153 | M14: =K14/L14 -> #DIV/0!
A15: 12- 3ème | B15: 128 | C15: 5 | D15: =B15/C15 -> 25.6 | E15: 113 | F15: 4 | G15: =E15/F15 -> 28.25 | H15: =E14 -> 126 | K15: =H14 -> 143 | M15: =K15/L15 -> #DIV/0!
A16: 13- Seconde | B16: 130 | C16: 5 | D16: =B16/C16 -> 26 | E16: 130 | F16: 5 | G16: =E16/F16 -> 26 | H16: =E15 -> 113 | K16: =H15 -> 126 | M16: =K16/L16 -> #DIV/0!
A17: 14- Première | B17: 114 | C17: 4 | D17: =B17/C17 -> 28.5 | E17: 126 | F17: 5 | G17: =E17/F17 -> 25.2 | H17: =E16 -> 130 | K17: =H16 -> 113 | M17: =K17/L17 -> #DIV/0!
A18: 15- Terminale | B18: 109 | C18: 4 | D18: =B18/C18 -> 27.25 | E18: 110 | F18: 4 | G18: =E18/F18 -> 27.5 | H18: =E17 -> 126 | K18: =H17 -> 130 | M18: =K18/L18 -> #DIV/0!
B20: Effectifs | C20: Division | D20: Elève/classe | E20: Effectifs | F20: Division | G20: Elève/classe | H20: Effectifs | I20: Division | J20: Elèves/Classe | K20: Effectifs | L20: Division | M20: Elève/classe
A21: Maternelle | B21: =B4+B5+B6 -> 291 | C21: =C4+C5+C6 -> 13 | D21: =B21/C21 -> 22.384615 | E21: =E4+E5+E6 -> 272 | F21: =F4+F5+F6 -> 11 | G21: =E21/F21 -> 24.727273 | H21: =H4+H5+H6 -> 192 | I21: =I4+I5+I6 -> 0 | J21: =H21/I21 -> #DIV/0! | K21: =K4+K5+K6 -> 180 | L21: =L4+L5+L6 -> 0 | M21: =K21/L21 -> #DIV/0!
A22: Elémentaire | B22: =B7+B8+B9+B10+B11 -> 651 | C22: =C7+C8+C9+C10+C11 -> 27 | D22: =B22/C22 -> 24.111111 | E22: =E7+E8+E9+E10+E11 -> 652 | F22: =F7+F8+F9+F10+F11 -> 27 | G22: =E22/F22 -> 24.148148 | H22: =H7+H8+H9+H10+H11 -> 653 | I22: =I7+I8+I9+I10+I11 -> 0 | J22: =H22/I22 -> #DIV/0! | K22: =K7+K8+K9+K10+K11 -> 597 | L22: =L7+L8+L9+L10+L11 -> 0 | M22: =K22/L22 -> #DIV/0!
A23: PRIMAIRE | B23: =B21+B22 -> 942 | C23: =C21+C22 -> 40 | D23: =B23/C23 -> 23.55 | E23: =E21+E22 -> 924 | F23: =F21+F22 -> 38 | G23: =E23/F23 -> 24.315789 | H23: =H21+H22 -> 845 | I23: =I21+I22 -> 0 | J23: =H23/I23 -> #DIV/0! | K23: =K21+K22 -> 777 | L23: =L21+L22 -> 0 | M23: =K23/L23 -> #DIV/0!
A24: Collège | B24: =B12+B13+B14+B15 -> 499 | C24: =C12+C13+C14+C15 -> 20 | D24: =B24/C24 -> 24.95 | E24: =E12+E13+E14+E15 -> 535 | F24: =F12+F13+F14+F15 -> 21 | G24: =E24/F24 -> 25.47619 | H24: =H12+H13+H14+H15 -> 551 | I24: =I12+I13+I14+I15 -> 0 | J24: =H24/I24 -> #DIV/0! | K24: =K12+K13+K14+K15 -> 553 | L24: =L12+L13+L14+L15 -> 0 | M24: =K24/L24 -> #DIV/0!
A25: Lycée | B25: =B16+B17+B18 -> 353 | C25: =C16+C17+C18 -> 13 | D25: =B25/C25 -> 27.153846 | E25: =E16+E17+E18 -> 366 | F25: =F16+F17+F18 -> 14 | G25: =E25/F25 -> 26.142857 | H25: =H16+H17+H18 -> 369 | I25: =I16+I17+I18 -> 0 | J25: =H25/I25 -> #DIV/0! | K25: =K16+K17+K18 -> 369 | L25: =L16+L17+L18 -> 0 | M25: =K25/L25 -> #DIV/0!
A26: SECONDAIRE | B26: =B24+B25 -> 852 | C26: =C24+C25 -> 33 | D26: =B26/C26 -> 25.818182 | E26: =E24+E25 -> 901 | F26: =F24+F25 -> 35 | G26: =E26/F26 -> 25.742857 | H26: =H24+H25 -> 920 | I26: =I24+I25 -> 0 | J26: =H26/I26 -> #DIV/0! | K26: =K24+K25 -> 922 | L26: =L24+L25 -> 0 | M26: =K26/L26 -> #DIV/0!
A27: Total ETABLISSEMENT | B27: =B23+B26 -> 1794 | C27: =C23+C26 -> 73 | D27: =B27/C27 -> 24.575342 | E27: =E23+E26 -> 1825 | F27: =F23+F26 -> 73 | G27: =E27/F27 -> 25 | H27: =H23+H26 -> 1765 | I27: =I23+I26 -> 0 | J27: =H27/I27 -> #DIV/0! | K27: =K23+K26 -> 1699 | L27: =L23+L26 -> 0 | M27: =K27/L27 -> #DIV/0!
A30: Structure prévisionnelle Maternelle
A31: PS
A32: MS
A33: GS
A34: CP
A35: CE1
A36: CE2
A37: CM1
A38: CM2
B39: =SUM(B31:B38) -> 0

Sheet Hypothèses 
A2: HYPOTHESES et DONNEES du modèle | M2: RESULTAT des SIMULATIONS du modèle | X2: TABLES du modele
D4: Données à remplir par l'AEFE
D5: Données ou hypothèses à compléter par l'établissement
A6: HYPOTHESES ET DONNEES GENERALES
B7: Statut de l'établissement | C7: conventionné | D7: après homologation
B8: Année 1 de la projection financière | C8: 2025
B9: Année référence compte financier | C9: =C8-1 -> 2024
B10: Année scolaire initiale | C10: =IF(C8=2024,"2022/2023",IF(C8=2025,"2023/2024",IF(C8=2026,"2024/2025",IF(C8=2027,"2025/2026","2026/2027")))) -> 2023/2024
C11: Indice | D11: 3 | E11: 4 | F11: 5 | G11: 6 | H11: 7 | I11: 8 | J11: 9 | K11: 10 | L11: 11 | M11: 12 | N11: 13
B12: Niveaux homologués | C12: =C10 -> 2023/2024 | D12: =VLOOKUP($C$10,'table années scolaires'!$C$2:$L$6,'Hypothèses '!D$11,FALSE) -> 2024/2025 | E12: =VLOOKUP($C$10,'table années scolaires'!$C$2:$L$6,'Hypothèses '!E$11,FALSE) -> 2025/2026 | F12: =VLOOKUP($C$10,'table années scolaires'!$C$2:$L$6,'Hypothèses '!F$11,FALSE) -> 2026/2027 | G12: =VLOOKUP($C$10,'table années scolaires'!$C$2:$L$6,'Hypothèses '!G$11,FALSE) -> 2027/2028 | H12: =VLOOKUP($C$10,'table années scolaires'!$C$2:$L$6,'Hypothèses '!H$11,FALSE) -> 2028/2029 | I12: =VLOOKUP($C$10,'table années scolaires'!$C$2:$L$6,'Hypothèses '!I$11,FALSE) -> 2029/2030 | J12: =VLOOKUP($C$10,'table années scolaires'!$C$2:$L$6,'Hypothèses '!J$11,FALSE) -> 2030/2031 | K12: =VLOOKUP($C$10,'table années scolaires'!$C$2:$L$6,'Hypothèses '!K$11,FALSE) -> 2031/2032
B13: Maternelle | C13: non | D13: non | E13: non | F13: oui | G13: =F13 -> oui | H13: =G13 -> oui | I13: =H13 -> oui | J13: =I13 -> oui | K13: =J13 -> oui
B14: Elémentaire | C14: non | D14: non | E14: non | F14: =E14 -> non | G14: oui | H14: =G14 -> oui | I14: =H14 -> oui | J14: =I14 -> oui | K14: =J14 -> oui
B15: Collège | C15: non | D15: non | E15: non | F15: =E15 -> non | G15: =F15 -> non | H15: =G15 -> non | I15: =H15 -> non | J15: =I15 -> non | K15: =J15 -> non
B16: Lycée | C16: non | D16: non | E16: non | F16: =E16 -> non | G16: =F16 -> non | H16: =G16 -> non | I16: oui | J16: =I16 -> oui | K16: =J16 -> oui
B18: Tarifs - moyens pondérés en fonction des nationalités | M18: RESULTAT OPERATIONNEL SCOLAIRE
C19: =C12 -> 2023/2024 | D19: =D12 -> 2024/2025 | E19: =E12 -> 2025/2026 | F19: =F12 -> 2026/2027 | G19: =G12 -> 2027/2028 | H19: =H12 -> 2028/2029 | I19: =I12 -> 2029/2030 | J19: =J12 -> 2030/2031 | K19: =K12 -> 2031/2032 | M19: =B38 -> Monnaie : Riyal
B20: Frais Reinscription | E20: 65000 | F20: 65000 | G20: 65000 | H20: 65000 | I20: 65000 | J20: 65000 | K20: 65000 | N20: ='Hypothèses '!$C$8 -> 2025 | O20: =N20+1 -> 2026 | P20: =O20+1 -> 2027 | Q20: =P20+1 -> 2028 | R20: =Q20+1 -> 2029 | S20: =R20+1 -> 2030 | T20: =S20+1 -> 2031
B21: Droits Première Inscription | E21: 500000 | F21: 500000 | G21: 500000 | H21: 500000 | I21: 500000 | J21: 500000 | K21: 500000 | M21: GLOBAL | N21: =HLOOKUP(N$20,'Compte Résultat ML'!$C$4:$J$10,3,FALSE) -> #N/A | O21: =HLOOKUP(O$20,'Compte Résultat ML'!$C$4:$J$10,3,FALSE) -> #N/A | P21: =HLOOKUP(P$20,'Compte Résultat ML'!$C$4:$J$10,3,FALSE) -> #N/A | Q21: =HLOOKUP(Q$20,'Compte Résultat ML'!$C$4:$J$10,3,FALSE) -> #N/A | R21: =HLOOKUP(R$20,'Compte Résultat ML'!$C$4:$J$10,3,FALSE) -> #N/A | S21: =HLOOKUP(S$20,'Compte Résultat ML'!$C$4:$J$10,3,FALSE) -> #N/A | T21: =HLOOKUP(T$20,'Compte Résultat ML'!$C$4:$J$10,3,FALSE) -> #N/A
B22: Frais scolarité GLOBAL | E22: =D22*(1+E$32) -> 0 | F22: =E22*(1+F$32) -> 0 | G22: =F22*(1+G$32) -> 0 | H22: =G22*(1+H$32) -> 0 | I22: =H22*(1+I$32) -> 0 | J22: =I22*(1+J$32) -> 0 | K22: =J22*(1+K$32) -> 0 | M22: MATERNELLE | N22: =HLOOKUP(N$20,'Compte Résultat ML'!$C$4:$J$10,4,FALSE) -> #N/A | O22: =HLOOKUP(O$20,'Compte Résultat ML'!$C$4:$J$10,4,FALSE) -> #N/A | P22: =HLOOKUP(P$20,'Compte Résultat ML'!$C$4:$J$10,4,FALSE) -> #N/A | Q22: =HLOOKUP(Q$20,'Compte Résultat ML'!$C$4:$J$10,4,FALSE) -> #N/A | R22: =HLOOKUP(R$20,'Compte Résultat ML'!$C$4:$J$10,4,FALSE) -> #N/A | S22: =HLOOKUP(S$20,'Compte Résultat ML'!$C$4:$J$10,4,FALSE) -> #N/A | T22: =HLOOKUP(T$20,'Compte Résultat ML'!$C$4:$J$10,4,FALSE) -> #N/A
B23: Frais scolarité MATERNELLE | E23: =D23*(1+E$32) -> 0 | F23: =E23*(1+F$32) -> 0 | G23: =F23*(1+G$32) -> 0 | H23: =G23*(1+H$32) -> 0 | I23: =H23*(1+I$32) -> 0 | J23: =I23*(1+J$32) -> 0 | K23: =J23*(1+K$32) -> 0 | M23: MS enseignants PDL | N23: =HLOOKUP(N$20,'Compte Résultat ML'!$C$58:$J$87,29,FALSE) -> 0 | O23: =HLOOKUP(O$20,'Compte Résultat ML'!$C$58:$J$87,29,FALSE) -> 0 | P23: =HLOOKUP(P$20,'Compte Résultat ML'!$C$58:$J$87,29,FALSE) -> 0 | Q23: =HLOOKUP(Q$20,'Compte Résultat ML'!$C$58:$J$87,29,FALSE) -> 0 | R23: =HLOOKUP(R$20,'Compte Résultat ML'!$C$58:$J$87,29,FALSE) -> 0 | S23: =HLOOKUP(S$20,'Compte Résultat ML'!$C$58:$J$87,29,FALSE) -> 0 | T23: =HLOOKUP(T$20,'Compte Résultat ML'!$C$58:$J$87,29,FALSE) -> 0
B24: Frais scolarité ELEMENTAIRE | E24: =D24*(1+E$32) -> 0 | F24: =E24*(1+F$32) -> 0 | G24: =F24*(1+G$32) -> 0 | H24: =G24*(1+H$32) -> 0 | I24: =H24*(1+I$32) -> 0 | J24: =I24*(1+J$32) -> 0 | K24: =J24*(1+K$32) -> 0 | M24: Frais réseau AEFE (FC+Partenariat) | N24: =HLOOKUP(N$20,'Compte Résultat ML'!$C$58:$J$104,47,FALSE) -> 0 | O24: =HLOOKUP(O$20,'Compte Résultat ML'!$C$58:$J$104,47,FALSE) -> 0 | P24: =HLOOKUP(P$20,'Compte Résultat ML'!$C$58:$J$104,47,FALSE) -> #N/A | Q24: =HLOOKUP(Q$20,'Compte Résultat ML'!$C$58:$J$104,47,FALSE) -> #N/A | R24: =HLOOKUP(R$20,'Compte Résultat ML'!$C$58:$J$104,47,FALSE) -> #N/A | S24: =HLOOKUP(S$20,'Compte Résultat ML'!$C$58:$J$104,47,FALSE) -> #N/A | T24: =HLOOKUP(T$20,'Compte Résultat ML'!$C$58:$J$104,47,FALSE) -> #N/A
B25: Frais scolarité COLLEGE | E25: =D25*(1+E$32) -> 0 | F25: =E25*(1+F$32) -> 0 | G25: =F25*(1+G$32) -> 0 | H25: =G25*(1+H$32) -> 0 | I25: =H25*(1+I$32) -> 0 | J25: =I25*(1+J$32) -> 0 | K25: =J25*(1+K$32) -> 0 | M25: ELEMENTAIRE | N25: =HLOOKUP(N$20,'Compte Résultat ML'!$C$4:$J$10,5,FALSE) -> #N/A | O25: =HLOOKUP(O$20,'Compte Résultat ML'!$C$4:$J$10,5,FALSE) -> #N/A | P25: =HLOOKUP(P$20,'Compte Résultat ML'!$C$4:$J$10,5,FALSE) -> #N/A | Q25: =HLOOKUP(Q$20,'Compte Résultat ML'!$C$4:$J$10,5,FALSE) -> #N/A | R25: =HLOOKUP(R$20,'Compte Résultat ML'!$C$4:$J$10,5,FALSE) -> #N/A | S25: =HLOOKUP(S$20,'Compte Résultat ML'!$C$4:$J$10,5,FALSE) -> #N/A | T25: =HLOOKUP(T$20,'Compte Résultat ML'!$C$4:$J$10,5,FALSE) -> #N/A
B26: Frais scolarité LYCEE | E26: =D26*(1+E$32) -> 0 | F26: =E26*(1+F$32) -> 0 | G26: =F26*(1+G$32) -> 0 | H26: =G26*(1+H$32) -> 0 | I26: =H26*(1+I$32) -> 0 | J26: =I26*(1+J$32) -> 0 | K26: =J26*(1+K$32) -> 0 | M26: MS enseignants PDL | N26: =HLOOKUP(N$20,'Compte Résultat ML'!$C$58:$J$112,55,FALSE) -> 0 | O26: =HLOOKUP(O$20,'Compte Résultat ML'!$C$58:$J$112,55,FALSE) -> 0 | P26: =HLOOKUP(P$20,'Compte Résultat ML'!$C$58:$J$112,55,FALSE) -> 0 | Q26: =HLOOKUP(Q$20,'Compte Résultat ML'!$C$58:$J$112,55,FALSE) -> 0 | R26: =HLOOKUP(R$20,'Compte Résultat ML'!$C$58:$J$112,55,FALSE) -> 0 | S26: =HLOOKUP(S$20,'Compte Résultat ML'!$C$58:$J$112,55,FALSE) -> 0 | T26: =HLOOKUP(T$20,'Compte Résultat ML'!$C$58:$J$112,55,FALSE) -> 0
M27: Frais réseau AEFE (FC+Partenariat) | N27: =HLOOKUP(N$20,'Compte Résultat ML'!$C$58:$J$300,73,FALSE) -> 0 | O27: =HLOOKUP(O$20,'Compte Résultat ML'!$C$58:$J$300,73,FALSE) -> 0 | P27: =HLOOKUP(P$20,'Compte Résultat ML'!$C$58:$J$300,73,FALSE) -> 0 | Q27: =HLOOKUP(Q$20,'Compte Résultat ML'!$C$58:$J$300,73,FALSE) -> #N/A | R27: =HLOOKUP(R$20,'Compte Résultat ML'!$C$58:$J$300,73,FALSE) -> #N/A | S27: =HLOOKUP(S$20,'Compte Résultat ML'!$C$58:$J$300,73,FALSE) -> #N/A | T27: =HLOOKUP(T$20,'Compte Résultat ML'!$C$58:$J$300,73,FALSE) -> #N/A
B28: Taux nouveaux inscrits | D28: 0.1 | E28: =D28 -> 0.1 | F28: =E28 -> 0.1 | G28: =F28 -> 0.1 | H28: =G28 -> 0.1 | I28: =H28 -> 0.1 | J28: =I28 -> 0.1 | K28: =J28 -> 0.1 | M28: COLLEGE | N28: =HLOOKUP(N$20,'Compte Résultat ML'!$C$4:$J$10,6,FALSE) -> #N/A | O28: =HLOOKUP(O$20,'Compte Résultat ML'!$C$4:$J$10,6,FALSE) -> #N/A | P28: =HLOOKUP(P$20,'Compte Résultat ML'!$C$4:$J$10,6,FALSE) -> #N/A | Q28: =HLOOKUP(Q$20,'Compte Résultat ML'!$C$4:$J$10,6,FALSE) -> #N/A | R28: =HLOOKUP(R$20,'Compte Résultat ML'!$C$4:$J$10,6,FALSE) -> #N/A | S28: =HLOOKUP(S$20,'Compte Résultat ML'!$C$4:$J$10,6,FALSE) -> #N/A | T28: =HLOOKUP(T$20,'Compte Résultat ML'!$C$4:$J$10,6,FALSE) -> #N/A
B29: Taux abattement (familles nombreuses … ou exonérations personnels) | D29: 0.06 | E29: 0.06 | F29: 0.06 | G29: 0.06 | H29: 0.06 | I29: 0.06 | J29: 0.06 | K29: 0.06 | M29: MS enseignants PDL | N29: =HLOOKUP(N$20,'Compte Résultat ML'!$C$58:$J$138,81,FALSE) -> 0 | O29: =HLOOKUP(O$20,'Compte Résultat ML'!$C$58:$J$138,81,FALSE) -> 0 | P29: =HLOOKUP(P$20,'Compte Résultat ML'!$C$58:$J$138,81,FALSE) -> 0 | Q29: =HLOOKUP(Q$20,'Compte Résultat ML'!$C$58:$J$138,81,FALSE) -> 0 | R29: =HLOOKUP(R$20,'Compte Résultat ML'!$C$58:$J$138,81,FALSE) -> 0 | S29: =HLOOKUP(S$20,'Compte Résultat ML'!$C$58:$J$138,81,FALSE) -> 0 | T29: =HLOOKUP(T$20,'Compte Résultat ML'!$C$58:$J$138,81,FALSE) -> 0
M30: Frais réseau AEFE (FC+Partenariat) | N30: =HLOOKUP(N$20,'Compte Résultat ML'!$C$58:$J$300,99,FALSE) -> 0 | O30: =HLOOKUP(O$20,'Compte Résultat ML'!$C$58:$J$300,99,FALSE) -> 0 | P30: =HLOOKUP(P$20,'Compte Résultat ML'!$C$58:$J$300,99,FALSE) -> 0 | Q30: =HLOOKUP(Q$20,'Compte Résultat ML'!$C$58:$J$300,99,FALSE) -> 0 | R30: =HLOOKUP(R$20,'Compte Résultat ML'!$C$58:$J$300,99,FALSE) -> 0 | S30: =HLOOKUP(S$20,'Compte Résultat ML'!$C$58:$J$300,99,FALSE) -> 0 | T30: =HLOOKUP(T$20,'Compte Résultat ML'!$C$58:$J$300,99,FALSE) -> 0
C31: =C12 -> 2023/2024 | D31: =D12 -> 2024/2025 | E31: =E12 -> 2025/2026 | F31: =F12 -> 2026/2027 | G31: =G12 -> 2027/2028 | H31: =H12 -> 2028/2029 | I31: =I12 -> 2029/2030 | J31: =J12 -> 2030/2031 | K31: =K12 -> 2031/2032 | M31: LYCEE | N31: =HLOOKUP(N$20,'Compte Résultat ML'!$C$4:$J$10,7,FALSE) -> #N/A | O31: =HLOOKUP(O$20,'Compte Résultat ML'!$C$4:$J$10,7,FALSE) -> #N/A | P31: =HLOOKUP(P$20,'Compte Résultat ML'!$C$4:$J$10,7,FALSE) -> #N/A | Q31: =HLOOKUP(Q$20,'Compte Résultat ML'!$C$4:$J$10,7,FALSE) -> #N/A | R31: =HLOOKUP(R$20,'Compte Résultat ML'!$C$4:$J$10,7,FALSE) -> #N/A | S31: =HLOOKUP(S$20,'Compte Résultat ML'!$C$4:$J$10,7,FALSE) -> #N/A | T31: =HLOOKUP(T$20,'Compte Résultat ML'!$C$4:$J$10,7,FALSE) -> #N/A
B32: Taux augmentation frais scolarité | M32: MS enseignants PDL | N32: =HLOOKUP(N$20,'Compte Résultat ML'!$C$58:$J$164,107,FALSE) -> 0 | O32: =HLOOKUP(O$20,'Compte Résultat ML'!$C$58:$J$164,107,FALSE) -> 0 | P32: =HLOOKUP(P$20,'Compte Résultat ML'!$C$58:$J$164,107,FALSE) -> 0 | Q32: =HLOOKUP(Q$20,'Compte Résultat ML'!$C$58:$J$164,107,FALSE) -> 0 | R32: =HLOOKUP(R$20,'Compte Résultat ML'!$C$58:$J$164,107,FALSE) -> 0 | S32: =HLOOKUP(S$20,'Compte Résultat ML'!$C$58:$J$164,107,FALSE) -> 0 | T32: =HLOOKUP(T$20,'Compte Résultat ML'!$C$58:$J$164,107,FALSE) -> 0
M33: Frais réseau AEFE (FC+Partenariat) | N33: =HLOOKUP(N$20,'Compte Résultat ML'!$C$58:$J$300,125,FALSE) -> 0 | O33: =HLOOKUP(O$20,'Compte Résultat ML'!$C$58:$J$300,125,FALSE) -> 0 | P33: =HLOOKUP(P$20,'Compte Résultat ML'!$C$58:$J$300,125,FALSE) -> 0 | Q33: =HLOOKUP(Q$20,'Compte Résultat ML'!$C$58:$J$300,125,FALSE) -> 0 | R33: =HLOOKUP(R$20,'Compte Résultat ML'!$C$58:$J$300,125,FALSE) -> 0 | S33: =HLOOKUP(S$20,'Compte Résultat ML'!$C$58:$J$300,125,FALSE) -> #N/A | T33: =HLOOKUP(T$20,'Compte Résultat ML'!$C$58:$J$300,125,FALSE) -> #N/A
C34: =D34-1 -> 2023 | D34: =C9 -> 2024 | E34: =D34+1 -> 2025 | F34: =E34+1 -> 2026 | G34: =F34+1 -> 2027 | H34: =G34+1 -> 2028 | I34: =H34+1 -> 2029 | J34: =I34+1 -> 2030 | K34: =J34+1 -> 2031 | M34: Résultat en nb jours fonct | N34: =ABS(N$21/(HLOOKUP(N$20,'Compte Résultat ML'!$C$4:$J$120,57,FALSE)/360)) -> #N/A | O34: =ABS(O$21/(HLOOKUP(O$20,'Compte Résultat ML'!$C$4:$J$120,57,FALSE)/360)) -> #N/A | P34: =ABS(P$21/(HLOOKUP(P$20,'Compte Résultat ML'!$C$4:$J$120,57,FALSE)/360)) -> #N/A | Q34: =ABS(Q$21/(HLOOKUP(Q$20,'Compte Résultat ML'!$C$4:$J$120,57,FALSE)/360)) -> #N/A | R34: =ABS(R$21/(HLOOKUP(R$20,'Compte Résultat ML'!$C$4:$J$120,57,FALSE)/360)) -> #N/A | S34: =ABS(S$21/(HLOOKUP(S$20,'Compte Résultat ML'!$C$4:$J$120,57,FALSE)/360)) -> #N/A | T34: =ABS(T$21/(HLOOKUP(T$20,'Compte Résultat ML'!$C$4:$J$120,57,FALSE)/360)) -> #N/A
B35: Taux augmentation annuel salaires | M35: Résultat en nb d'élèves | N35: =ABS(N$21/E$22) -> #N/A | O35: =ABS(O$21/F$22) -> #N/A | P35: =ABS(P$21/G$22) -> #N/A | Q35: =ABS(Q$21/H$22) -> #N/A | R35: =ABS(R$21/I$22) -> #N/A | S35: =ABS(S$21/J$22) -> #N/A | T35: =ABS(T$21/K$22) -> #N/A | U35: =IFERROR(HLOOKUP(U$20,'Compte Résultat ML'!$C$4:$J$10,3,FALSE),"")
B36: Taux annuel inflation | M36: Résultat en point d'augm des FS | N36: =ABS(N21/(HLOOKUP(N$20,'Compte Résultat ML'!$C$4:$J$120,58,FALSE)*1%)) -> #N/A | O36: =ABS(O21/(HLOOKUP(O$20,'Compte Résultat ML'!$C$4:$J$120,58,FALSE)*1%)) -> #N/A | P36: =ABS(P21/(HLOOKUP(P$20,'Compte Résultat ML'!$C$4:$J$120,58,FALSE)*1%)) -> #N/A | Q36: =ABS(Q21/(HLOOKUP(Q$20,'Compte Résultat ML'!$C$4:$J$120,58,FALSE)*1%)) -> #N/A | R36: =ABS(R21/(HLOOKUP(R$20,'Compte Résultat ML'!$C$4:$J$120,58,FALSE)*1%)) -> #N/A | S36: =ABS(S21/(HLOOKUP(S$20,'Compte Résultat ML'!$C$4:$J$120,58,FALSE)*1%)) -> #N/A | T36: =ABS(T21/(HLOOKUP(T$20,'Compte Résultat ML'!$C$4:$J$120,58,FALSE)*1%)) -> #N/A | U36: =IFERROR(HLOOKUP(U$20,'Compte Résultat ML'!$C$4:$J$10,3,FALSE),"")
B37: Taux change / chancellerie
B38: Monnaie : Riyal | C38: =1/4 -> 0.25 | D38: =C38 -> 0.25 | E38: =D38 -> 0.25 | F38: =E38 -> 0.25 | G38: =F38 -> 0.25 | H38: =G38 -> 0.25 | I38: =H38 -> 0.25 | J38: =I38 -> 0.25 | K38: =J38 -> 0.25
B40: Taux remontée PRRD (conventionnés) | C40: 0 | D40: 0 | E40: 0 | F40: 0 | G40: 0 | H40: 0 | I40: 0 | J40: 0 | K40: 0
B42: Nombre de divisions | C42: =C57 -> 2023/2024 | D42: =D57 -> 2024/2025 | E42: =E57 -> 2025/2026 | F42: =F57 -> 2026/2027 | G42: =G57 -> 2027/2028 | H42: =H57 -> 2028/2029 | I42: =I57 -> 2029/2030 | J42: =J57 -> 2030/2031 | K42: =K57 -> 2031/2032
B43: Maternelle | D43: =IFERROR(CEILING(HLOOKUP(D$42,'Projection Effectifs'!$C$31:$M$38,2,FALSE)/'Hypothèses '!D49,0.5),0) -> 1.5 | E43: =IFERROR(CEILING(HLOOKUP(E$42,'Projection Effectifs'!$C$31:$M$38,2,FALSE)/'Hypothèses '!E49,0.5),0) -> 0 | F43: =IFERROR(CEILING(HLOOKUP(F$42,'Projection Effectifs'!$C$31:$M$38,2,FALSE)/'Hypothèses '!F49,0.5),0) -> 0 | G43: =IFERROR(CEILING(HLOOKUP(G$42,'Projection Effectifs'!$C$31:$M$38,2,FALSE)/'Hypothèses '!G49,0.5),0) -> 0 | H43: =IFERROR(CEILING(HLOOKUP(H$42,'Projection Effectifs'!$C$31:$M$38,2,FALSE)/'Hypothèses '!H49,0.5),0) -> 0 | I43: =IFERROR(CEILING(HLOOKUP(I$42,'Projection Effectifs'!$C$31:$M$38,2,FALSE)/'Hypothèses '!I49,0.5),0) -> 0 | J43: =IFERROR(CEILING(HLOOKUP(J$42,'Projection Effectifs'!$C$31:$M$38,2,FALSE)/'Hypothèses '!J49,0.5),0) -> 0 | K43: =IFERROR(CEILING(HLOOKUP(K$42,'Projection Effectifs'!$C$31:$M$38,2,FALSE)/'Hypothèses '!K49,0.5),0) -> 0
B44: Elémentaire | D44: =IFERROR(CEILING(HLOOKUP(D$42,'Projection Effectifs'!$C$31:$M$38,3,FALSE)/'Hypothèses '!D50,0.5),0) -> 1 | E44: =IFERROR(CEILING(HLOOKUP(E$42,'Projection Effectifs'!$C$31:$M$38,3,FALSE)/'Hypothèses '!E50,0.5),0) -> 0 | F44: =IFERROR(CEILING(HLOOKUP(F$42,'Projection Effectifs'!$C$31:$M$38,3,FALSE)/'Hypothèses '!F50,0.5),0) -> 0 | G44: =IFERROR(CEILING(HLOOKUP(G$42,'Projection Effectifs'!$C$31:$M$38,3,FALSE)/'Hypothèses '!G50,0.5),0) -> 0 | H44: =IFERROR(CEILING(HLOOKUP(H$42,'Projection Effectifs'!$C$31:$M$38,3,FALSE)/'Hypothèses '!H50,0.5),0) -> 0 | I44: =IFERROR(CEILING(HLOOKUP(I$42,'Projection Effectifs'!$C$31:$M$38,3,FALSE)/'Hypothèses '!I50,0.5),0) -> 0 | J44: =IFERROR(CEILING(HLOOKUP(J$42,'Projection Effectifs'!$C$31:$M$38,3,FALSE)/'Hypothèses '!J50,0.5),0) -> 0 | K44: =IFERROR(CEILING(HLOOKUP(K$42,'Projection Effectifs'!$C$31:$M$38,3,FALSE)/'Hypothèses '!K50,0.5),0) -> 0
B45: Collège | D45: =IFERROR(ROUNDUP(HLOOKUP(D$42,'Projection Effectifs'!$C$31:$M$38,5,FALSE)/'Hypothèses '!D51,0),0) -> 1 | E45: =IFERROR(ROUNDUP(HLOOKUP(E$42,'Projection Effectifs'!$C$31:$M$38,5,FALSE)/'Hypothèses '!E51,0),0) -> 0 | F45: =IFERROR(ROUNDUP(HLOOKUP(F$42,'Projection Effectifs'!$C$31:$M$38,5,FALSE)/'Hypothèses '!F51,0),0) -> 0 | G45: =IFERROR(ROUNDUP(HLOOKUP(G$42,'Projection Effectifs'!$C$31:$M$38,5,FALSE)/'Hypothèses '!G51,0),0) -> 0 | H45: =IFERROR(ROUNDUP(HLOOKUP(H$42,'Projection Effectifs'!$C$31:$M$38,5,FALSE)/'Hypothèses '!H51,0),0) -> 0 | I45: =IFERROR(ROUNDUP(HLOOKUP(I$42,'Projection Effectifs'!$C$31:$M$38,5,FALSE)/'Hypothèses '!I51,0),0) -> 0 | J45: =IFERROR(ROUNDUP(HLOOKUP(J$42,'Projection Effectifs'!$C$31:$M$38,5,FALSE)/'Hypothèses '!J51,0),0) -> 0 | K45: =IFERROR(ROUNDUP(HLOOKUP(K$42,'Projection Effectifs'!$C$31:$M$38,5,FALSE)/'Hypothèses '!K51,0),0) -> 0 | M45: RESULTAT OPERATIONNEL SCOLAIRE
B46: Lycée | D46: =IFERROR(ROUNDUP(HLOOKUP(D$42,'Projection Effectifs'!$C$31:$M$38,6,FALSE)/'Hypothèses '!D52,0),0) -> 1 | E46: =IFERROR(ROUNDUP(HLOOKUP(E$42,'Projection Effectifs'!$C$31:$M$38,6,FALSE)/'Hypothèses '!E52,0),0) -> 0 | F46: =IFERROR(ROUNDUP(HLOOKUP(F$42,'Projection Effectifs'!$C$31:$M$38,6,FALSE)/'Hypothèses '!F52,0),0) -> 0 | G46: =IFERROR(ROUNDUP(HLOOKUP(G$42,'Projection Effectifs'!$C$31:$M$38,6,FALSE)/'Hypothèses '!G52,0),0) -> 0 | H46: =IFERROR(ROUNDUP(HLOOKUP(H$42,'Projection Effectifs'!$C$31:$M$38,6,FALSE)/'Hypothèses '!H52,0),0) -> 0 | I46: =IFERROR(ROUNDUP(HLOOKUP(I$42,'Projection Effectifs'!$C$31:$M$38,6,FALSE)/'Hypothèses '!I52,0),0) -> 0 | J46: =IFERROR(ROUNDUP(HLOOKUP(J$42,'Projection Effectifs'!$C$31:$M$38,6,FALSE)/'Hypothèses '!J52,0),0) -> 0 | K46: =IFERROR(ROUNDUP(HLOOKUP(K$42,'Projection Effectifs'!$C$31:$M$38,6,FALSE)/'Hypothèses '!K52,0),0) -> 0 | M46: en Euro
B48: Nb élèves/classe | C48: =C42 -> 2023/2024 | D48: =D42 -> 2024/2025 | E48: =E42 -> 2025/2026 | F48: =F42 -> 2026/2027 | G48: =G42 -> 2027/2028 | H48: =H42 -> 2028/2029 | I48: =I42 -> 2029/2030 | J48: =J42 -> 2030/2031 | K48: =K42 -> 2031/2032 | N48: ='Hypothèses '!$C$8 -> 2025 | O48: =N48+1 -> 2026 | P48: =O48+1 -> 2027 | Q48: =P48+1 -> 2028 | R48: =Q48+1 -> 2029 | S48: =R48+1 -> 2030 | T48: =S48+1 -> 2031
B49: Maternelle | D49: 272 | M49: GLOBAL | N49: =HLOOKUP(N$20,'Compte Résultat Euro'!$C$4:$J$10,3,FALSE) -> #N/A | O49: =HLOOKUP(O$20,'Compte Résultat Euro'!$C$4:$J$10,3,FALSE) -> #N/A | P49: =HLOOKUP(P$20,'Compte Résultat Euro'!$C$4:$J$10,3,FALSE) -> #N/A | Q49: =HLOOKUP(Q$20,'Compte Résultat Euro'!$C$4:$J$10,3,FALSE) -> #N/A | R49: =HLOOKUP(R$20,'Compte Résultat Euro'!$C$4:$J$10,3,FALSE) -> #N/A | S49: =HLOOKUP(S$20,'Compte Résultat Euro'!$C$4:$J$10,3,FALSE) -> #N/A | T49: =HLOOKUP(T$20,'Compte Résultat Euro'!$C$4:$J$10,3,FALSE) -> #N/A
B50: Elémentaire | D50: 652 | M50: MATERNELLE | N50: =HLOOKUP(N$20,'Compte Résultat Euro'!$C$4:$J$10,4,FALSE) -> #N/A | O50: =HLOOKUP(O$20,'Compte Résultat Euro'!$C$4:$J$10,4,FALSE) -> #N/A | P50: =HLOOKUP(P$20,'Compte Résultat Euro'!$C$4:$J$10,4,FALSE) -> #N/A | Q50: =HLOOKUP(Q$20,'Compte Résultat Euro'!$C$4:$J$10,4,FALSE) -> #N/A | R50: =HLOOKUP(R$20,'Compte Résultat Euro'!$C$4:$J$10,4,FALSE) -> #N/A | S50: =HLOOKUP(S$20,'Compte Résultat Euro'!$C$4:$J$10,4,FALSE) -> #N/A | T50: =HLOOKUP(T$20,'Compte Résultat Euro'!$C$4:$J$10,4,FALSE) -> #N/A
B51: Collège | D51: 535 | M51: MS enseignants PDL | N51: =HLOOKUP(N$20,'Compte Résultat Euro'!$C$58:$J$87,29,FALSE) -> 0 | O51: =HLOOKUP(O$20,'Compte Résultat Euro'!$C$58:$J$87,29,FALSE) -> 0 | P51: =HLOOKUP(P$20,'Compte Résultat Euro'!$C$58:$J$87,29,FALSE) -> 0 | Q51: =HLOOKUP(Q$20,'Compte Résultat Euro'!$C$58:$J$87,29,FALSE) -> 0 | R51: =HLOOKUP(R$20,'Compte Résultat Euro'!$C$58:$J$87,29,FALSE) -> 0 | S51: =HLOOKUP(S$20,'Compte Résultat Euro'!$C$58:$J$87,29,FALSE) -> 0 | T51: =HLOOKUP(T$20,'Compte Résultat Euro'!$C$58:$J$87,29,FALSE) -> 0
B52: Lycée | D52: 366 | M52: ELEMENTAIRE | N52: =HLOOKUP(N$20,'Compte Résultat Euro'!$C$4:$J$10,5,FALSE) -> #N/A | O52: =HLOOKUP(O$20,'Compte Résultat Euro'!$C$4:$J$10,5,FALSE) -> #N/A | P52: =HLOOKUP(P$20,'Compte Résultat Euro'!$C$4:$J$10,5,FALSE) -> #N/A | Q52: =HLOOKUP(Q$20,'Compte Résultat Euro'!$C$4:$J$10,5,FALSE) -> #N/A | R52: =HLOOKUP(R$20,'Compte Résultat Euro'!$C$4:$J$10,5,FALSE) -> #N/A | S52: =HLOOKUP(S$20,'Compte Résultat Euro'!$C$4:$J$10,5,FALSE) -> #N/A | T52: =HLOOKUP(T$20,'Compte Résultat Euro'!$C$4:$J$10,5,FALSE) -> #N/A
M53: MS enseignants PDL | N53: =HLOOKUP(N$20,'Compte Résultat Euro'!$C$58:$J$112,55,FALSE) -> 0 | O53: =HLOOKUP(O$20,'Compte Résultat Euro'!$C$58:$J$112,55,FALSE) -> 0 | P53: =HLOOKUP(P$20,'Compte Résultat Euro'!$C$58:$J$112,55,FALSE) -> 0 | Q53: =HLOOKUP(Q$20,'Compte Résultat Euro'!$C$58:$J$112,55,FALSE) -> 0 | R53: =HLOOKUP(R$20,'Compte Résultat Euro'!$C$58:$J$112,55,FALSE) -> 0 | S53: =HLOOKUP(S$20,'Compte Résultat Euro'!$C$58:$J$112,55,FALSE) -> 0 | T53: =HLOOKUP(T$20,'Compte Résultat Euro'!$C$58:$J$112,55,FALSE) -> 0
M54: COLLEGE | N54: =HLOOKUP(N$20,'Compte Résultat Euro'!$C$4:$J$10,6,FALSE) -> #N/A | O54: =HLOOKUP(O$20,'Compte Résultat Euro'!$C$4:$J$10,6,FALSE) -> #N/A | P54: =HLOOKUP(P$20,'Compte Résultat Euro'!$C$4:$J$10,6,FALSE) -> #N/A | Q54: =HLOOKUP(Q$20,'Compte Résultat Euro'!$C$4:$J$10,6,FALSE) -> #N/A | R54: =HLOOKUP(R$20,'Compte Résultat Euro'!$C$4:$J$10,6,FALSE) -> #N/A | S54: =HLOOKUP(S$20,'Compte Résultat Euro'!$C$4:$J$10,6,FALSE) -> #N/A | T54: =HLOOKUP(T$20,'Compte Résultat Euro'!$C$4:$J$10,6,FALSE) -> #N/A
A55: HYPOTHESES ET DONNEES de PERSONNEL | M55: MS enseignants PDL | N55: =HLOOKUP(N$20,'Compte Résultat Euro'!$C$58:$J$138,81,FALSE) -> 0 | O55: =HLOOKUP(O$20,'Compte Résultat Euro'!$C$58:$J$138,81,FALSE) -> 0 | P55: =HLOOKUP(P$20,'Compte Résultat Euro'!$C$58:$J$138,81,FALSE) -> 0 | Q55: =HLOOKUP(Q$20,'Compte Résultat Euro'!$C$58:$J$138,81,FALSE) -> 0 | R55: =HLOOKUP(R$20,'Compte Résultat Euro'!$C$58:$J$138,81,FALSE) -> 0 | S55: =HLOOKUP(S$20,'Compte Résultat Euro'!$C$58:$J$138,81,FALSE) -> 0 | T55: =HLOOKUP(T$20,'Compte Résultat Euro'!$C$58:$J$138,81,FALSE) -> 0
B56: Réferentiel- Avec commentaire | C56: 2 | D56: 3 | E56: 4 | F56: 5 | G56: 6 | H56: 7 | I56: 8 | J56: 9 | K56: 10 | M56: LYCEE | N56: =HLOOKUP(N$20,'Compte Résultat Euro'!$C$4:$J$10,7,FALSE) -> #N/A | O56: =HLOOKUP(O$20,'Compte Résultat Euro'!$C$4:$J$10,7,FALSE) -> #N/A | P56: =HLOOKUP(P$20,'Compte Résultat Euro'!$C$4:$J$10,7,FALSE) -> #N/A | Q56: =HLOOKUP(Q$20,'Compte Résultat Euro'!$C$4:$J$10,7,FALSE) -> #N/A | R56: =HLOOKUP(R$20,'Compte Résultat Euro'!$C$4:$J$10,7,FALSE) -> #N/A | S56: =HLOOKUP(S$20,'Compte Résultat Euro'!$C$4:$J$10,7,FALSE) -> #N/A | T56: =HLOOKUP(T$20,'Compte Résultat Euro'!$C$4:$J$10,7,FALSE) -> #N/A | X56: A titre indicatif (à finaliser )
B57: Personnel non enseignants ni ASEM | C57: =C12 -> 2023/2024 | D57: =D12 -> 2024/2025 | E57: =E12 -> 2025/2026 | F57: =F12 -> 2026/2027 | G57: =G12 -> 2027/2028 | H57: =H12 -> 2028/2029 | I57: =I12 -> 2029/2030 | J57: =J12 -> 2030/2031 | K57: =K12 -> 2031/2032 | M57: MS enseignants PDL | N57: =HLOOKUP(N$20,'Compte Résultat Euro'!$C$58:$J$164,107,FALSE) -> 0 | O57: =HLOOKUP(O$20,'Compte Résultat Euro'!$C$58:$J$164,107,FALSE) -> 0 | P57: =HLOOKUP(P$20,'Compte Résultat Euro'!$C$58:$J$164,107,FALSE) -> 0 | Q57: =HLOOKUP(Q$20,'Compte Résultat Euro'!$C$58:$J$164,107,FALSE) -> 0 | R57: =HLOOKUP(R$20,'Compte Résultat Euro'!$C$58:$J$164,107,FALSE) -> 0 | S57: =HLOOKUP(S$20,'Compte Résultat Euro'!$C$58:$J$164,107,FALSE) -> 0 | T57: =HLOOKUP(T$20,'Compte Résultat Euro'!$C$58:$J$164,107,FALSE) -> 0 | Y57: Moyenne existant AEFE
B58: Nbre personnels commun à tout établissement | C58: =SUM(C59:C66) -> 2 | D58: =SUM(D59:D66) -> 12 | E58: =SUM(E59:E66) -> 0 | F58: =SUM(F59:F66) -> 0 | G58: =SUM(G59:G66) -> 0 | H58: =SUM(H59:H66) -> 0 | I58: =SUM(I59:I66) -> 0 | J58: =SUM(J59:J66) -> 0 | K58: =SUM(K59:K66) -> 0 | M58: Résultat en nb jours fonct | N58: =ABS(N$49/(HLOOKUP(N$48,'Compte Résultat Euro'!$C$4:$J$120,57,FALSE)/360)) -> #N/A | O58: =ABS(O$49/(HLOOKUP(O$48,'Compte Résultat Euro'!$C$4:$J$120,57,FALSE)/360)) -> #N/A | P58: =ABS(P$49/(HLOOKUP(P$48,'Compte Résultat Euro'!$C$4:$J$120,57,FALSE)/360)) -> #N/A | Q58: =ABS(Q$49/(HLOOKUP(Q$48,'Compte Résultat Euro'!$C$4:$J$120,57,FALSE)/360)) -> #N/A | R58: =ABS(R$49/(HLOOKUP(R$48,'Compte Résultat Euro'!$C$4:$J$120,57,FALSE)/360)) -> #N/A | S58: =ABS(S$49/(HLOOKUP(S$48,'Compte Résultat Euro'!$C$4:$J$120,57,FALSE)/360)) -> #N/A | T58: =ABS(T$49/(HLOOKUP(T$48,'Compte Résultat Euro'!$C$4:$J$120,57,FALSE)/360)) -> #N/A | X58: Personnels Primaire
B59: Chef d'Etablissement D1 | C59: 2 | D59: 2 | M59: Résultat en nb d'élèves | N59: =ABS(N$21/E$22) -> #N/A | O59: =ABS(O$21/F$22) -> #N/A | P59: =ABS(P$21/G$22) -> #N/A | Q59: =ABS(Q$21/H$22) -> #N/A | R59: =ABS(R$21/I$22) -> #N/A | S59: =ABS(S$21/J$22) -> #N/A | T59: =ABS(T$21/K$22) -> #N/A | U59: =IF(T$20<2030,HLOOKUP(U$20,'Compte Résultat Euro'!$C$4:$J$10,3,FALSE),"") | X59: Nb elèves Primaire | Y59: <100 | Z59: 100 à 200 | AA59: 200 à 500 | AB59: 500 à 1000 | AC59: 1000 à 1500
B60: DAF D1 | D60: 1 | M60: Résultat en point d'augm des FS | N60: =ABS(N49/(HLOOKUP(N$20,'Compte Résultat Euro'!$C$4:$J$120,58,FALSE)*1%)) -> #N/A | O60: =ABS(O49/(HLOOKUP(O$20,'Compte Résultat Euro'!$C$4:$J$120,58,FALSE)*1%)) -> #N/A | P60: =ABS(P49/(HLOOKUP(P$20,'Compte Résultat Euro'!$C$4:$J$120,58,FALSE)*1%)) -> #N/A | Q60: =ABS(Q49/(HLOOKUP(Q$20,'Compte Résultat Euro'!$C$4:$J$120,58,FALSE)*1%)) -> #N/A | R60: =ABS(R49/(HLOOKUP(R$20,'Compte Résultat Euro'!$C$4:$J$120,58,FALSE)*1%)) -> #N/A | S60: =ABS(S49/(HLOOKUP(S$20,'Compte Résultat Euro'!$C$4:$J$120,58,FALSE)*1%)) -> #N/A | T60: =ABS(T49/(HLOOKUP(T$20,'Compte Résultat Euro'!$C$4:$J$120,58,FALSE)*1%)) -> #N/A | U60: =IF(T$20<2030,HLOOKUP(U$20,'Compte Résultat Euro'!$C$4:$J$10,3,FALSE),"") | X60: Directrice ou directeur | Y60: 1 | Z60: 1 | AA60: 1 | AB60: 1 | AC60: 1
B61: DRH | D61: 2 | X61: direction adjoint | Y61: 0 | Z61: 0 | AA61: 0 | AB61: 1 | AC61: 1
B62: Autre Administratif | X62: Vie scolaire - CPE /Educateurs | Y62: 0 | Z62: 0.5 | AA62: 1 | AB62: 2 | AC62: 3
B63: Technique - Informatique - MG | D63: 4 | X63: Documentation | Y63: 0 | Z63: 0.5 | AA63: 1 | AB63: 1.5 | AC63: 2
B64: Entretien / Sécurité | D64: 1 | X64: Infirmière | Y64: 0.5 | Z64: 1 | AA64: 1.5 | AB64: 2 | AC64: 2.5
B65: Documentation | D65: 2
B66: Autre commun
B67: Nbre personnels primaire (hors enseignants) | C67: =SUM(C68:C74) -> 1 | D67: =SUM(D68:D74) -> 6 | E67: =SUM(E68:E74) -> 0 | F67: =SUM(F68:F74) -> 0 | G67: =SUM(G68:G74) -> 0 | H67: =SUM(H68:H74) -> 0 | I67: =SUM(I68:I74) -> 0 | J67: =SUM(J68:J74) -> 0 | K67: =SUM(K68:K74) -> 0
B68: Direction D1 | C68: 1 | D68: 2
B69: Direction adjointe
B70: Conseiller pédagogique | M70: Nombre de PERSONNELS
B71: Vie scolaire - Educateurs | D71: 1
B72: Documentation | D72: 1
B73: Infirmière | M73: en ETP | N73: =C$12 -> 2023/2024 | O73: =D$12 -> 2024/2025 | P73: =E$12 -> 2025/2026 | Q73: =F$12 -> 2026/2027 | R73: =G$12 -> 2027/2028 | S73: =H$12 -> 2028/2029 | T73: =I$12 -> 2029/2030 | U73: =J$12 -> 2030/2031
B74: Autre primaire commun | D74: 2 | M74: Total personnel | N74: =N76+N78+N80+N82 -> #N/A | O74: =O76+O78+O80+O82 -> #N/A | P74: =P76+P78+P80+P82 -> #N/A | Q74: =Q76+Q78+Q80+Q82 -> #N/A | R74: =R76+R78+R80+R82 -> #N/A | S74: =S76+S78+S80+S82 -> #N/A | T74: =T76+T78+T80+T82 -> #N/A | U74: =U76+U78+U80+U82 -> #N/A
B75: Nbre personnels secondaire (hors enseignants) | C75: =SUM(C76:C83) -> 20 | D75: =SUM(D76:D83) -> 21 | E75: =SUM(E76:E83) -> 21 | F75: =SUM(F76:F83) -> 21 | G75: =SUM(G76:G83) -> 21 | H75: =SUM(H76:H83) -> 21 | I75: =SUM(I76:I83) -> 21 | J75: =SUM(J76:J83) -> 21 | K75: =SUM(K76:K83) -> 21 | M75: Total enseignants | N75: =N77+N79+N81+N83 -> 0 | O75: =O77+O79+O81+O83 -> 3.25 | P75: =P77+P79+P81+P83 -> 0 | Q75: =Q77+Q79+Q81+Q83 -> 0 | R75: =R77+R79+R81+R83 -> 0 | S75: =S77+S79+S81+S83 -> 0 | T75: =T77+T79+T81+T83 -> 0 | U75: =U77+U79+U81+U83 -> 0
B76: Proviseur adjoint D1 | C76: 1 | D76: 1 | E76: =D76 -> 1 | F76: =E76 -> 1 | G76: =F76 -> 1 | H76: =G76 -> 1 | I76: =H76 -> 1 | J76: =I76 -> 1 | K76: =J76 -> 1 | M76: MATERNELLE Tot personnel | N76: =HLOOKUP(N$73,'Calcul MS Personnels'!$C$38:$K$60,2,FALSE) -> #N/A | O76: =SUM('Calcul MS Personnels'!D42:D65) -> #N/A | P76: =SUM('Calcul MS Personnels'!E42:E65) -> #N/A | Q76: =SUM('Calcul MS Personnels'!F42:F65) -> #N/A | R76: =SUM('Calcul MS Personnels'!G42:G65) -> #N/A | S76: =SUM('Calcul MS Personnels'!H42:H65) -> #N/A | T76: =SUM('Calcul MS Personnels'!I42:I65) -> #N/A | U76: =SUM('Calcul MS Personnels'!J42:J65) -> #N/A
B77: CPE (Conseiller Principal d'Education) PDL | C77: 1 | D77: 1 | E77: =D77 -> 1 | F77: =E77 -> 1 | G77: =F77 -> 1 | H77: =G77 -> 1 | I77: =H77 -> 1 | J77: =I77 -> 1 | K77: =J77 -> 1 | M77: Tot enseignants | N77: =HLOOKUP(N$73,'Calcul MS Personnels'!$C$38:$K$60,23,FALSE) -> 0 | O77: =SUM('Calcul MS Personnels'!D62:D64) -> 1.95 | P77: =SUM('Calcul MS Personnels'!E62:E64) -> 0 | Q77: =SUM('Calcul MS Personnels'!F62:F64) -> 0 | R77: =SUM('Calcul MS Personnels'!G62:G64) -> 0 | S77: =SUM('Calcul MS Personnels'!H62:H64) -> 0 | T77: =SUM('Calcul MS Personnels'!I62:I64) -> 0 | U77: =SUM('Calcul MS Personnels'!J62:J64) -> 0
B78: Vie scolaire - Educateurs | C78: 11 | D78: 14 | E78: =D78 -> 14 | F78: =E78 -> 14 | G78: =F78 -> 14 | H78: =G78 -> 14 | I78: =H78 -> 14 | J78: =I78 -> 14 | K78: =J78 -> 14 | M78: ELEMENTAIRE Tot personnel | N78: =HLOOKUP(N$73,'Calcul MS Personnels'!$C$90:$K$112,2,FALSE) -> #N/A | O78: =HLOOKUP(O$73,'Calcul MS Personnels'!$C$90:$K$112,2,FALSE) -> #N/A | P78: =HLOOKUP(P$73,'Calcul MS Personnels'!$C$90:$K$112,2,FALSE) -> #N/A | Q78: =HLOOKUP(Q$73,'Calcul MS Personnels'!$C$90:$K$112,2,FALSE) -> #N/A | R78: =HLOOKUP(R$73,'Calcul MS Personnels'!$C$90:$K$112,2,FALSE) -> #N/A | S78: =HLOOKUP(S$73,'Calcul MS Personnels'!$C$90:$K$112,2,FALSE) -> #N/A | T78: =HLOOKUP(T$73,'Calcul MS Personnels'!$C$90:$K$112,2,FALSE) -> #N/A | U78: =HLOOKUP(U$73,'Calcul MS Personnels'!$C$90:$K$112,2,FALSE) -> #N/A
B79: Documentation | C79: 1 | D79: 2 | E79: =D79 -> 2 | F79: =E79 -> 2 | G79: =F79 -> 2 | H79: =G79 -> 2 | I79: =H79 -> 2 | J79: =I79 -> 2 | K79: =J79 -> 2 | M79: Tot enseignants | N79: =HLOOKUP(N$73,'Calcul MS Personnels'!$C$90:$K$112,23,FALSE) -> 0 | O79: =HLOOKUP(O$73,'Calcul MS Personnels'!$C$90:$K$112,23,FALSE) -> 1.3 | P79: =HLOOKUP(P$73,'Calcul MS Personnels'!$C$90:$K$112,23,FALSE) -> 0 | Q79: =HLOOKUP(Q$73,'Calcul MS Personnels'!$C$90:$K$112,23,FALSE) -> 0 | R79: =HLOOKUP(R$73,'Calcul MS Personnels'!$C$90:$K$112,23,FALSE) -> 0 | S79: =HLOOKUP(S$73,'Calcul MS Personnels'!$C$90:$K$112,23,FALSE) -> 0 | T79: =HLOOKUP(T$73,'Calcul MS Personnels'!$C$90:$K$112,23,FALSE) -> 0 | U79: =HLOOKUP(U$73,'Calcul MS Personnels'!$C$90:$K$112,23,FALSE) -> 0
B80: Infirmière | C80: 1 | D80: 2 | E80: =D80 -> 2 | F80: =E80 -> 2 | G80: =F80 -> 2 | H80: =G80 -> 2 | I80: =H80 -> 2 | J80: =I80 -> 2 | K80: =J80 -> 2 | M80: COLLEGE Tot personnel | N80: =HLOOKUP(N$73,'Calcul MS Personnels'!$C$142:$K$165,2,FALSE) -> #N/A | O80: =HLOOKUP(O$73,'Calcul MS Personnels'!$C$142:$K$165,2,FALSE) -> #N/A | P80: =HLOOKUP(P$73,'Calcul MS Personnels'!$C$142:$K$165,2,FALSE) -> #N/A | Q80: =HLOOKUP(Q$73,'Calcul MS Personnels'!$C$142:$K$165,2,FALSE) -> #N/A | R80: =HLOOKUP(R$73,'Calcul MS Personnels'!$C$142:$K$165,2,FALSE) -> #N/A | S80: =HLOOKUP(S$73,'Calcul MS Personnels'!$C$142:$K$165,2,FALSE) -> #N/A | T80: =HLOOKUP(T$73,'Calcul MS Personnels'!$C$142:$K$165,2,FALSE) -> #N/A | U80: =HLOOKUP(U$73,'Calcul MS Personnels'!$C$142:$K$165,2,FALSE) -> #N/A
B81: Laboratoire | C81: 2 | D81: 1 | E81: =D81 -> 1 | F81: =E81 -> 1 | G81: =F81 -> 1 | H81: =G81 -> 1 | I81: =H81 -> 1 | J81: =I81 -> 1 | K81: =J81 -> 1 | M81: Tot enseignants | N81: =HLOOKUP(N$73,'Calcul MS Personnels'!$C$142:$K$165,24,FALSE) -> 0 | O81: =HLOOKUP(O$73,'Calcul MS Personnels'!$C$142:$K$165,24,FALSE) -> 0 | P81: =HLOOKUP(P$73,'Calcul MS Personnels'!$C$142:$K$165,24,FALSE) -> 0 | Q81: =HLOOKUP(Q$73,'Calcul MS Personnels'!$C$142:$K$165,24,FALSE) -> 0 | R81: =HLOOKUP(R$73,'Calcul MS Personnels'!$C$142:$K$165,24,FALSE) -> 0 | S81: =HLOOKUP(S$73,'Calcul MS Personnels'!$C$142:$K$165,24,FALSE) -> 0 | T81: =HLOOKUP(T$73,'Calcul MS Personnels'!$C$142:$K$165,24,FALSE) -> 0 | U81: =HLOOKUP(U$73,'Calcul MS Personnels'!$C$142:$K$165,24,FALSE) -> 0
B82: Orientation | C82: 1 | E82: =D82 -> 0 | F82: =E82 -> 0 | G82: =F82 -> 0 | H82: =G82 -> 0 | I82: =H82 -> 0 | J82: =I82 -> 0 | K82: =J82 -> 0 | M82: LYCEE Tot personnel | N82: =HLOOKUP(N$73,'Calcul MS Personnels'!$C$196:$K$219,2,FALSE) -> #N/A | O82: =HLOOKUP(O$73,'Calcul MS Personnels'!$C$196:$K$219,2,FALSE) -> #N/A | P82: =HLOOKUP(P$73,'Calcul MS Personnels'!$C$196:$K$219,2,FALSE) -> #N/A | Q82: =HLOOKUP(Q$73,'Calcul MS Personnels'!$C$196:$K$219,2,FALSE) -> #N/A | R82: =HLOOKUP(R$73,'Calcul MS Personnels'!$C$196:$K$219,2,FALSE) -> #N/A | S82: =HLOOKUP(S$73,'Calcul MS Personnels'!$C$196:$K$219,2,FALSE) -> #N/A | T82: =HLOOKUP(T$73,'Calcul MS Personnels'!$C$196:$K$219,2,FALSE) -> #N/A | U82: =HLOOKUP(U$73,'Calcul MS Personnels'!$C$196:$K$219,2,FALSE) -> #N/A
B83: Autre secondaire commun | C83: 2 | E83: =D83 -> 0 | F83: =E83 -> 0 | G83: =F83 -> 0 | H83: =G83 -> 0 | I83: =H83 -> 0 | J83: =I83 -> 0 | K83: =J83 -> 0 | M83: Tot enseignants | N83: =HLOOKUP(N$73,'Calcul MS Personnels'!$C$196:$K$219,24,FALSE) -> 0 | O83: =HLOOKUP(O$73,'Calcul MS Personnels'!$C$196:$K$219,24,FALSE) -> 0 | P83: =HLOOKUP(P$73,'Calcul MS Personnels'!$C$196:$K$219,24,FALSE) -> 0 | Q83: =HLOOKUP(Q$73,'Calcul MS Personnels'!$C$196:$K$219,24,FALSE) -> 0 | R83: =HLOOKUP(R$73,'Calcul MS Personnels'!$C$196:$K$219,24,FALSE) -> 0 | S83: =HLOOKUP(S$73,'Calcul MS Personnels'!$C$196:$K$219,24,FALSE) -> 0 | T83: =HLOOKUP(T$73,'Calcul MS Personnels'!$C$196:$K$219,24,FALSE) -> 0 | U83: =HLOOKUP(U$73,'Calcul MS Personnels'!$C$196:$K$219,24,FALSE) -> 0
C85: =C57 -> 2023/2024 | D85: =D57 -> 2024/2025
B86: Nombre intervenants 1er degré | C86: 0 | D86: 0 | E86: Données issues MAGE, à vérifier par l'établissement; à comparer avec la table de l'onglet "Tables Enseignants"
B87: H/E collège | C87: 0 | D87: 0
B88: H/E lycée | C88: 0 | D88: 0
C90: =C48 -> 2023/2024 | D90: =D48 -> 2024/2025 | E90: =E48 -> 2025/2026 | F90: =F48 -> 2026/2027 | G90: =G48 -> 2027/2028 | H90: =H48 -> 2028/2029 | I90: =I48 -> 2029/2030 | J90: =J48 -> 2030/2031 | K90: =K48 -> 2031/2032
B91: Nb résidents ou D3 maternelle
B92: Nb résidents ou D3 élémentaire
B93: Nb résidents ou D3 secondaire
B94: Sections internationales / Enseignements renforcés ou complémentaires
B95: Choisir le niveau par niveau et par année. Ce choix impact le nombre d'enseignants par élève
B96: Indice 1 = sans SI
B97: Indice 2 = avec SI | C97: =C90 -> 2023/2024 | D97: =D12 -> 2024/2025 | E97: =E12 -> 2025/2026 | F97: =F12 -> 2026/2027 | G97: =G12 -> 2027/2028 | H97: =H12 -> 2028/2029 | I97: =I12 -> 2029/2030 | J97: =J12 -> 2030/2031 | K97: =K12 -> 2031/2032
B98: Primaire | C98: 1 | D98: 1 | E98: =D98 -> 1 | F98: 2 | G98: =F98 -> 2 | H98: =G98 -> 2 | I98: =H98 -> 2 | J98: =I98 -> 2 | K98: =J98 -> 2
B99: Collège | C99: 1 | D99: 1 | E99: =D99 -> 1 | F99: =E99 -> 1 | G99: =F99 -> 1 | H99: =G99 -> 1 | I99: =H99 -> 1 | J99: =I99 -> 1 | K99: =J99 -> 1
B100: Lycée | C100: 1 | D100: 1 | E100: =D100 -> 1 | F100: =E100 -> 1 | G100: =F100 -> 1 | H100: =G100 -> 1 | I100: =H100 -> 1 | J100: =I100 -> 1 | K100: =J100 -> 1
A102: HYPOTHESES ET DONNEES de COÛT
B103: Rémunérations des personnels
B104: Cout annuel chargé moyen par catégorie en monnaie Locale
D105: =D34 -> 2024
B106: Chef d'Etablissement D1
B107: Proviseur adjoint D1
B108: Direction PDL
B109: Direction adjointe
...

Sheet Calcul MS Personnels
C3: 2 | D3: 3 | E3: 4 | F3: 5 | G3: 6 | H3: 7 | I3: 8 | J3: 9 | K3: 10
C4: ='Hypothèses '!C12 -> 2023/2024 | D4: ='Hypothèses '!D12 -> 2024/2025 | E4: ='Hypothèses '!E12 -> 2025/2026 | F4: ='Hypothèses '!F12 -> 2026/2027 | G4: ='Hypothèses '!G12 -> 2027/2028 | H4: ='Hypothèses '!H12 -> 2028/2029 | I4: ='Hypothèses '!I12 -> 2029/2030 | J4: ='Hypothèses '!J12 -> 2030/2031 | K4: ='Hypothèses '!K12 -> 2031/2032 | M4: Référenciel | N4: Moyenne existant AEFE
A5: Report Hypothèses | B5: Personnels généraux communs | C5: =SUM(C6:C13) -> #N/A | D5: =SUM(D6:D13) -> #N/A | E5: =SUM(E6:E13) -> #N/A | F5: =SUM(F6:F13) -> #N/A | G5: =SUM(G6:G13) -> #N/A | H5: =SUM(H6:H13) -> #N/A | I5: =SUM(I6:I13) -> #N/A | J5: =SUM(J6:J13) -> #N/A | K5: =SUM(K6:K13) -> #N/A | M5: Personnels Primaire
A6: Ne pas modifier - voir onglet Hypothèses | B6: Chef d'Etablissement PDL | C6: =VLOOKUP($B6,'Hypothèses '!$B$56:$K$66,'Hypothèses '!C$56,FALSE) -> #N/A | D6: =VLOOKUP($B6,'Hypothèses '!$B$56:$K$66,'Hypothèses '!D$56,FALSE) -> #N/A | E6: =VLOOKUP($B6,'Hypothèses '!$B$56:$K$66,'Hypothèses '!E$56,FALSE) -> #N/A | F6: =VLOOKUP($B6,'Hypothèses '!$B$56:$K$66,'Hypothèses '!F$56,FALSE) -> #N/A | G6: =VLOOKUP($B6,'Hypothèses '!$B$56:$K$66,'Hypothèses '!G$56,FALSE) -> #N/A | H6: =VLOOKUP($B6,'Hypothèses '!$B$56:$K$66,'Hypothèses '!H$56,FALSE) -> #N/A | I6: =VLOOKUP($B6,'Hypothèses '!$B$56:$K$66,'Hypothèses '!I$56,FALSE) -> #N/A | J6: =VLOOKUP($B6,'Hypothèses '!$B$56:$K$66,'Hypothèses '!J$56,FALSE) -> #N/A | K6: =VLOOKUP($B6,'Hypothèses '!$B$56:$K$66,'Hypothèses '!K$56,FALSE) -> #N/A | M6: Nb elèves Primaire | N6: <100 | O6: 100 à 200 | P6: 200 à 500 | Q6: 500 à 1000 | R6: 1000 à 1500
B7: DAF PDL | C7: =VLOOKUP($B7,'Hypothèses '!$B$56:$K$66,'Hypothèses '!C$56,FALSE) -> #N/A | D7: =VLOOKUP($B7,'Hypothèses '!$B$56:$K$66,'Hypothèses '!D$56,FALSE) -> #N/A | E7: =VLOOKUP($B7,'Hypothèses '!$B$56:$K$66,'Hypothèses '!E$56,FALSE) -> #N/A | F7: =VLOOKUP($B7,'Hypothèses '!$B$56:$K$66,'Hypothèses '!F$56,FALSE) -> #N/A | G7: =VLOOKUP($B7,'Hypothèses '!$B$56:$K$66,'Hypothèses '!G$56,FALSE) -> #N/A | H7: =VLOOKUP($B7,'Hypothèses '!$B$56:$K$66,'Hypothèses '!H$56,FALSE) -> #N/A | I7: =VLOOKUP($B7,'Hypothèses '!$B$56:$K$66,'Hypothèses '!I$56,FALSE) -> #N/A | J7: =VLOOKUP($B7,'Hypothèses '!$B$56:$K$66,'Hypothèses '!J$56,FALSE) -> #N/A | K7: =VLOOKUP($B7,'Hypothèses '!$B$56:$K$66,'Hypothèses '!K$56,FALSE) -> #N/A | M7: Directrice ou directeur | N7: 1 | O7: 1 | P7: 1 | Q7: 1 | R7: 1
B8: DRH | C8: =VLOOKUP($B8,'Hypothèses '!$B$56:$K$66,'Hypothèses '!C$56,FALSE) -> 0 | D8: =VLOOKUP($B8,'Hypothèses '!$B$56:$K$66,'Hypothèses '!D$56,FALSE) -> 2 | E8: =VLOOKUP($B8,'Hypothèses '!$B$56:$K$66,'Hypothèses '!E$56,FALSE) -> 0 | F8: =VLOOKUP($B8,'Hypothèses '!$B$56:$K$66,'Hypothèses '!F$56,FALSE) -> 0 | G8: =VLOOKUP($B8,'Hypothèses '!$B$56:$K$66,'Hypothèses '!G$56,FALSE) -> 0 | H8: =VLOOKUP($B8,'Hypothèses '!$B$56:$K$66,'Hypothèses '!H$56,FALSE) -> 0 | I8: =VLOOKUP($B8,'Hypothèses '!$B$56:$K$66,'Hypothèses '!I$56,FALSE) -> 0 | J8: =VLOOKUP($B8,'Hypothèses '!$B$56:$K$66,'Hypothèses '!J$56,FALSE) -> 0 | K8: =VLOOKUP($B8,'Hypothèses '!$B$56:$K$66,'Hypothèses '!K$56,FALSE) -> 0 | M8: direction adjoint | N8: 0 | O8: 0 | P8: 0 | Q8: 1 | R8: 1
B9: Autre Administratif | C9: =VLOOKUP($B9,'Hypothèses '!$B$56:$K$66,'Hypothèses '!C$56,FALSE) -> 0 | D9: =VLOOKUP($B9,'Hypothèses '!$B$56:$K$66,'Hypothèses '!D$56,FALSE) -> 0 | E9: =VLOOKUP($B9,'Hypothèses '!$B$56:$K$66,'Hypothèses '!E$56,FALSE) -> 0 | F9: =VLOOKUP($B9,'Hypothèses '!$B$56:$K$66,'Hypothèses '!F$56,FALSE) -> 0 | G9: =VLOOKUP($B9,'Hypothèses '!$B$56:$K$66,'Hypothèses '!G$56,FALSE) -> 0 | H9: =VLOOKUP($B9,'Hypothèses '!$B$56:$K$66,'Hypothèses '!H$56,FALSE) -> 0 | I9: =VLOOKUP($B9,'Hypothèses '!$B$56:$K$66,'Hypothèses '!I$56,FALSE) -> 0 | J9: =VLOOKUP($B9,'Hypothèses '!$B$56:$K$66,'Hypothèses '!J$56,FALSE) -> 0 | K9: =VLOOKUP($B9,'Hypothèses '!$B$56:$K$66,'Hypothèses '!K$56,FALSE) -> 0 | M9: Vie scolaire - CPE /Educateurs | N9: 0 | O9: 0.5 | P9: 1 | Q9: 2 | R9: 3
B10: Technique - Informatique - Maintenance | C10: =VLOOKUP($B10,'Hypothèses '!$B$56:$K$66,'Hypothèses '!C$56,FALSE) -> #N/A | D10: =VLOOKUP($B10,'Hypothèses '!$B$56:$K$66,'Hypothèses '!D$56,FALSE) -> #N/A | E10: =VLOOKUP($B10,'Hypothèses '!$B$56:$K$66,'Hypothèses '!E$56,FALSE) -> #N/A | F10: =VLOOKUP($B10,'Hypothèses '!$B$56:$K$66,'Hypothèses '!F$56,FALSE) -> #N/A | G10: =VLOOKUP($B10,'Hypothèses '!$B$56:$K$66,'Hypothèses '!G$56,FALSE) -> #N/A | H10: =VLOOKUP($B10,'Hypothèses '!$B$56:$K$66,'Hypothèses '!H$56,FALSE) -> #N/A | I10: =VLOOKUP($B10,'Hypothèses '!$B$56:$K$66,'Hypothèses '!I$56,FALSE) -> #N/A | J10: =VLOOKUP($B10,'Hypothèses '!$B$56:$K$66,'Hypothèses '!J$56,FALSE) -> #N/A | K10: =VLOOKUP($B10,'Hypothèses '!$B$56:$K$66,'Hypothèses '!K$56,FALSE) -> #N/A | M10: Documentation | N10: 0 | O10: 0.5 | P10: 1 | Q10: 1.5 | R10: 2
B11: Entretien / Sécurité | C11: =VLOOKUP($B11,'Hypothèses '!$B$56:$K$66,'Hypothèses '!C$56,FALSE) -> 0 | D11: =VLOOKUP($B11,'Hypothèses '!$B$56:$K$66,'Hypothèses '!D$56,FALSE) -> 1 | E11: =VLOOKUP($B11,'Hypothèses '!$B$56:$K$66,'Hypothèses '!E$56,FALSE) -> 0 | F11: =VLOOKUP($B11,'Hypothèses '!$B$56:$K$66,'Hypothèses '!F$56,FALSE) -> 0 | G11: =VLOOKUP($B11,'Hypothèses '!$B$56:$K$66,'Hypothèses '!G$56,FALSE) -> 0 | H11: =VLOOKUP($B11,'Hypothèses '!$B$56:$K$66,'Hypothèses '!H$56,FALSE) -> 0 | I11: =VLOOKUP($B11,'Hypothèses '!$B$56:$K$66,'Hypothèses '!I$56,FALSE) -> 0 | J11: =VLOOKUP($B11,'Hypothèses '!$B$56:$K$66,'Hypothèses '!J$56,FALSE) -> 0 | K11: =VLOOKUP($B11,'Hypothèses '!$B$56:$K$66,'Hypothèses '!K$56,FALSE) -> 0 | M11: Infirmière | N11: 0.5 | O11: 1 | P11: 1.5 | Q11: 2 | R11: 2.5
B12: Documentation | C12: =VLOOKUP($B12,'Hypothèses '!$B$56:$K$66,'Hypothèses '!C$56,FALSE) -> 0 | D12: =VLOOKUP($B12,'Hypothèses '!$B$56:$K$66,'Hypothèses '!D$56,FALSE) -> 2 | E12: =VLOOKUP($B12,'Hypothèses '!$B$56:$K$66,'Hypothèses '!E$56,FALSE) -> 0 | F12: =VLOOKUP($B12,'Hypothèses '!$B$56:$K$66,'Hypothèses '!F$56,FALSE) -> 0 | G12: =VLOOKUP($B12,'Hypothèses '!$B$56:$K$66,'Hypothèses '!G$56,FALSE) -> 0 | H12: =VLOOKUP($B12,'Hypothèses '!$B$56:$K$66,'Hypothèses '!H$56,FALSE) -> 0 | I12: =VLOOKUP($B12,'Hypothèses '!$B$56:$K$66,'Hypothèses '!I$56,FALSE) -> 0 | J12: =VLOOKUP($B12,'Hypothèses '!$B$56:$K$66,'Hypothèses '!J$56,FALSE) -> 0 | K12: =VLOOKUP($B12,'Hypothèses '!$B$56:$K$66,'Hypothèses '!K$56,FALSE) -> 0
B13: Autre commun | C13: 0 | D13: =VLOOKUP($B13,'Hypothèses '!$B$56:$K$66,'Hypothèses '!D$56,FALSE) -> 0 | E13: =VLOOKUP($B13,'Hypothèses '!$B$56:$K$66,'Hypothèses '!E$56,FALSE) -> 0 | F13: =VLOOKUP($B13,'Hypothèses '!$B$56:$K$66,'Hypothèses '!F$56,FALSE) -> 0 | G13: =VLOOKUP($B13,'Hypothèses '!$B$56:$K$66,'Hypothèses '!G$56,FALSE) -> 0 | H13: =VLOOKUP($B13,'Hypothèses '!$B$56:$K$66,'Hypothèses '!H$56,FALSE) -> 0 | I13: =VLOOKUP($B13,'Hypothèses '!$B$56:$K$66,'Hypothèses '!I$56,FALSE) -> 0 | J13: =VLOOKUP($B13,'Hypothèses '!$B$56:$K$66,'Hypothèses '!J$56,FALSE) -> 0 | K13: =VLOOKUP($B13,'Hypothèses '!$B$56:$K$66,'Hypothèses '!K$56,FALSE) -> 0
A14: Report Hypothèses
A15: Ne pas modifier - voir onglet Hypothèses | B15: Personnels Primaire Commun | C15: =SUM(C16:C22) -> #N/A | D15: =SUM(D16:D22) -> #N/A | E15: =SUM(E16:E22) -> #N/A | F15: =SUM(F16:F22) -> #N/A | G15: =SUM(G16:G22) -> #N/A | H15: =SUM(H16:H22) -> #N/A | I15: =SUM(I16:I22) -> #N/A | J15: =SUM(J16:J22) -> #N/A | K15: =SUM(K16:K22) -> #N/A
B16: Direction PDL | C16: =VLOOKUP($B16,'Hypothèses '!$B$68:$K$74,'Hypothèses '!C$56,FALSE) -> #N/A | D16: =VLOOKUP($B16,'Hypothèses '!$B$68:$K$74,'Hypothèses '!D$56,FALSE) -> #N/A | E16: =VLOOKUP($B16,'Hypothèses '!$B$68:$K$74,'Hypothèses '!E$56,FALSE) -> #N/A | F16: =VLOOKUP($B16,'Hypothèses '!$B$68:$K$74,'Hypothèses '!F$56,FALSE) -> #N/A | G16: =VLOOKUP($B16,'Hypothèses '!$B$68:$K$74,'Hypothèses '!G$56,FALSE) -> #N/A | H16: =VLOOKUP($B16,'Hypothèses '!$B$68:$K$74,'Hypothèses '!H$56,FALSE) -> #N/A | I16: =VLOOKUP($B16,'Hypothèses '!$B$68:$K$74,'Hypothèses '!I$56,FALSE) -> #N/A | J16: =VLOOKUP($B16,'Hypothèses '!$B$68:$K$74,'Hypothèses '!J$56,FALSE) -> #N/A | K16: =VLOOKUP($B16,'Hypothèses '!$B$68:$K$74,'Hypothèses '!K$56,FALSE) -> #N/A
B17: Direction adjointe | C17: =VLOOKUP($B17,'Hypothèses '!$B$68:$K$74,'Hypothèses '!C$56,FALSE) -> 0 | D17: =VLOOKUP($B17,'Hypothèses '!$B$68:$K$74,'Hypothèses '!D$56,FALSE) -> 0 | E17: =VLOOKUP($B17,'Hypothèses '!$B$68:$K$74,'Hypothèses '!E$56,FALSE) -> 0 | F17: =VLOOKUP($B17,'Hypothèses '!$B$68:$K$74,'Hypothèses '!F$56,FALSE) -> 0 | G17: =VLOOKUP($B17,'Hypothèses '!$B$68:$K$74,'Hypothèses '!G$56,FALSE) -> 0 | H17: =VLOOKUP($B17,'Hypothèses '!$B$68:$K$74,'Hypothèses '!H$56,FALSE) -> 0 | I17: =VLOOKUP($B17,'Hypothèses '!$B$68:$K$74,'Hypothèses '!I$56,FALSE) -> 0 | J17: =VLOOKUP($B17,'Hypothèses '!$B$68:$K$74,'Hypothèses '!J$56,FALSE) -> 0 | K17: =VLOOKUP($B17,'Hypothèses '!$B$68:$K$74,'Hypothèses '!K$56,FALSE) -> 0
B18: Conseiller pédagogique | C18: =VLOOKUP($B18,'Hypothèses '!$B$68:$K$74,'Hypothèses '!C$56,FALSE) -> 0 | D18: =VLOOKUP($B18,'Hypothèses '!$B$68:$K$74,'Hypothèses '!D$56,FALSE) -> 0 | E18: =VLOOKUP($B18,'Hypothèses '!$B$68:$K$74,'Hypothèses '!E$56,FALSE) -> 0 | F18: =VLOOKUP($B18,'Hypothèses '!$B$68:$K$74,'Hypothèses '!F$56,FALSE) -> 0 | G18: =VLOOKUP($B18,'Hypothèses '!$B$68:$K$74,'Hypothèses '!G$56,FALSE) -> 0 | H18: =VLOOKUP($B18,'Hypothèses '!$B$68:$K$74,'Hypothèses '!H$56,FALSE) -> 0 | I18: =VLOOKUP($B18,'Hypothèses '!$B$68:$K$74,'Hypothèses '!I$56,FALSE) -> 0 | J18: =VLOOKUP($B18,'Hypothèses '!$B$68:$K$74,'Hypothèses '!J$56,FALSE) -> 0 | K18: =VLOOKUP($B18,'Hypothèses '!$B$68:$K$74,'Hypothèses '!K$56,FALSE) -> 0
B19: Vie scolaire - Educateurs | C19: =VLOOKUP($B19,'Hypothèses '!$B$68:$K$74,'Hypothèses '!C$56,FALSE) -> 0 | D19: =VLOOKUP($B19,'Hypothèses '!$B$68:$K$74,'Hypothèses '!D$56,FALSE) -> 1 | E19: =VLOOKUP($B19,'Hypothèses '!$B$68:$K$74,'Hypothèses '!E$56,FALSE) -> 0 | F19: =VLOOKUP($B19,'Hypothèses '!$B$68:$K$74,'Hypothèses '!F$56,FALSE) -> 0 | G19: =VLOOKUP($B19,'Hypothèses '!$B$68:$K$74,'Hypothèses '!G$56,FALSE) -> 0 | H19: =VLOOKUP($B19,'Hypothèses '!$B$68:$K$74,'Hypothèses '!H$56,FALSE) -> 0 | I19: =VLOOKUP($B19,'Hypothèses '!$B$68:$K$74,'Hypothèses '!I$56,FALSE) -> 0 | J19: =VLOOKUP($B19,'Hypothèses '!$B$68:$K$74,'Hypothèses '!J$56,FALSE) -> 0 | K19: =VLOOKUP($B19,'Hypothèses '!$B$68:$K$74,'Hypothèses '!K$56,FALSE) -> 0
B20: Documentation | C20: =VLOOKUP($B20,'Hypothèses '!$B$68:$K$74,'Hypothèses '!C$56,FALSE) -> 0 | D20: =VLOOKUP($B20,'Hypothèses '!$B$68:$K$74,'Hypothèses '!D$56,FALSE) -> 1 | E20: =VLOOKUP($B20,'Hypothèses '!$B$68:$K$74,'Hypothèses '!E$56,FALSE) -> 0 | F20: =VLOOKUP($B20,'Hypothèses '!$B$68:$K$74,'Hypothèses '!F$56,FALSE) -> 0 | G20: =VLOOKUP($B20,'Hypothèses '!$B$68:$K$74,'Hypothèses '!G$56,FALSE) -> 0 | H20: =VLOOKUP($B20,'Hypothèses '!$B$68:$K$74,'Hypothèses '!H$56,FALSE) -> 0 | I20: =VLOOKUP($B20,'Hypothèses '!$B$68:$K$74,'Hypothèses '!I$56,FALSE) -> 0 | J20: =VLOOKUP($B20,'Hypothèses '!$B$68:$K$74,'Hypothèses '!J$56,FALSE) -> 0 | K20: =VLOOKUP($B20,'Hypothèses '!$B$68:$K$74,'Hypothèses '!K$56,FALSE) -> 0
B21: Infirmière | C21: =VLOOKUP($B21,'Hypothèses '!$B$68:$K$74,'Hypothèses '!C$56,FALSE) -> 0 | D21: =VLOOKUP($B21,'Hypothèses '!$B$68:$K$74,'Hypothèses '!D$56,FALSE) -> 0 | E21: =VLOOKUP($B21,'Hypothèses '!$B$68:$K$74,'Hypothèses '!E$56,FALSE) -> 0 | F21: =VLOOKUP($B21,'Hypothèses '!$B$68:$K$74,'Hypothèses '!F$56,FALSE) -> 0 | G21: =VLOOKUP($B21,'Hypothèses '!$B$68:$K$74,'Hypothèses '!G$56,FALSE) -> 0 | H21: =VLOOKUP($B21,'Hypothèses '!$B$68:$K$74,'Hypothèses '!H$56,FALSE) -> 0 | I21: =VLOOKUP($B21,'Hypothèses '!$B$68:$K$74,'Hypothèses '!I$56,FALSE) -> 0 | J21: =VLOOKUP($B21,'Hypothèses '!$B$68:$K$74,'Hypothèses '!J$56,FALSE) -> 0 | K21: =VLOOKUP($B21,'Hypothèses '!$B$68:$K$74,'Hypothèses '!K$56,FALSE) -> 0
A22: Report Hypothèses | B22: Autre primaire commun | C22: =VLOOKUP($B22,'Hypothèses '!$B$68:$K$74,'Hypothèses '!C$56,FALSE) -> 0 | D22: =VLOOKUP($B22,'Hypothèses '!$B$68:$K$74,'Hypothèses '!D$56,FALSE) -> 2 | E22: =VLOOKUP($B22,'Hypothèses '!$B$68:$K$74,'Hypothèses '!E$56,FALSE) -> 0 | F22: =VLOOKUP($B22,'Hypothèses '!$B$68:$K$74,'Hypothèses '!F$56,FALSE) -> 0 | G22: =VLOOKUP($B22,'Hypothèses '!$B$68:$K$74,'Hypothèses '!G$56,FALSE) -> 0 | H22: =VLOOKUP($B22,'Hypothèses '!$B$68:$K$74,'Hypothèses '!H$56,FALSE) -> 0 | I22: =VLOOKUP($B22,'Hypothèses '!$B$68:$K$74,'Hypothèses '!I$56,FALSE) -> 0 | J22: =VLOOKUP($B22,'Hypothèses '!$B$68:$K$74,'Hypothèses '!J$56,FALSE) -> 0 | K22: =VLOOKUP($B22,'Hypothèses '!$B$68:$K$74,'Hypothèses '!K$56,FALSE) -> 0
A23: Ne pas modifier - voir onglet Hypothèses
B24: Personnels secondaire commun | C24: =SUM(C25:C32) -> #N/A | D24: =SUM(D25:D32) -> #N/A | E24: =SUM(E25:E32) -> #N/A | F24: =SUM(F25:F32) -> #N/A | G24: =SUM(G25:G32) -> #N/A | H24: =SUM(H25:H32) -> #N/A | I24: =SUM(I25:I32) -> #N/A | J24: =SUM(J25:J32) -> #N/A | K24: =SUM(K25:K32) -> #N/A
B25: Proviseur adjoint PDL | C25: =VLOOKUP($B25,'Hypothèses '!$B$76:$K$83,'Hypothèses '!C$56,FALSE) -> #N/A | D25: =VLOOKUP($B25,'Hypothèses '!$B$76:$K$83,'Hypothèses '!D$56,FALSE) -> #N/A | E25: =VLOOKUP($B25,'Hypothèses '!$B$76:$K$83,'Hypothèses '!E$56,FALSE) -> #N/A | F25: =VLOOKUP($B25,'Hypothèses '!$B$76:$K$83,'Hypothèses '!F$56,FALSE) -> #N/A | G25: =VLOOKUP($B25,'Hypothèses '!$B$76:$K$83,'Hypothèses '!G$56,FALSE) -> #N/A | H25: =VLOOKUP($B25,'Hypothèses '!$B$76:$K$83,'Hypothèses '!H$56,FALSE) -> #N/A | I25: =VLOOKUP($B25,'Hypothèses '!$B$76:$K$83,'Hypothèses '!I$56,FALSE) -> #N/A | J25: =VLOOKUP($B25,'Hypothèses '!$B$76:$K$83,'Hypothèses '!J$56,FALSE) -> #N/A | K25: =VLOOKUP($B25,'Hypothèses '!$B$76:$K$83,'Hypothèses '!K$56,FALSE) -> #N/A
B26: CPE (Conseiller Principal d'Education) PDL | C26: =VLOOKUP($B26,'Hypothèses '!$B$76:$K$83,'Hypothèses '!C$56,FALSE) -> 1 | D26: =VLOOKUP($B26,'Hypothèses '!$B$76:$K$83,'Hypothèses '!D$56,FALSE) -> 1 | E26: =VLOOKUP($B26,'Hypothèses '!$B$76:$K$83,'Hypothèses '!E$56,FALSE) -> 1 | F26: =VLOOKUP($B26,'Hypothèses '!$B$76:$K$83,'Hypothèses '!F$56,FALSE) -> 1 | G26: =VLOOKUP($B26,'Hypothèses '!$B$76:$K$83,'Hypothèses '!G$56,FALSE) -> 1 | H26: =VLOOKUP($B26,'Hypothèses '!$B$76:$K$83,'Hypothèses '!H$56,FALSE) -> 1 | I26: =VLOOKUP($B26,'Hypothèses '!$B$76:$K$83,'Hypothèses '!I$56,FALSE) -> 1 | J26: =VLOOKUP($B26,'Hypothèses '!$B$76:$K$83,'Hypothèses '!J$56,FALSE) -> 1 | K26: =VLOOKUP($B26,'Hypothèses '!$B$76:$K$83,'Hypothèses '!K$56,FALSE) -> 1
B27: Vie scolaire - Educateurs | C27: =VLOOKUP($B27,'Hypothèses '!$B$76:$K$83,'Hypothèses '!C$56,FALSE) -> 11 | D27: =VLOOKUP($B27,'Hypothèses '!$B$76:$K$83,'Hypothèses '!D$56,FALSE) -> 14 | E27: =VLOOKUP($B27,'Hypothèses '!$B$76:$K$83,'Hypothèses '!E$56,FALSE) -> 14 | F27: =VLOOKUP($B27,'Hypothèses '!$B$76:$K$83,'Hypothèses '!F$56,FALSE) -> 14 | G27: =VLOOKUP($B27,'Hypothèses '!$B$76:$K$83,'Hypothèses '!G$56,FALSE) -> 14 | H27: =VLOOKUP($B27,'Hypothèses '!$B$76:$K$83,'Hypothèses '!H$56,FALSE) -> 14 | I27: =VLOOKUP($B27,'Hypothèses '!$B$76:$K$83,'Hypothèses '!I$56,FALSE) -> 14 | J27: =VLOOKUP($B27,'Hypothèses '!$B$76:$K$83,'Hypothèses '!J$56,FALSE) -> 14 | K27: =VLOOKUP($B27,'Hypothèses '!$B$76:$K$83,'Hypothèses '!K$56,FALSE) -> 14
B28: Documentation | C28: =VLOOKUP($B28,'Hypothèses '!$B$76:$K$83,'Hypothèses '!C$56,FALSE) -> 1 | D28: =VLOOKUP($B28,'Hypothèses '!$B$76:$K$83,'Hypothèses '!D$56,FALSE) -> 2 | E28: =VLOOKUP($B28,'Hypothèses '!$B$76:$K$83,'Hypothèses '!E$56,FALSE) -> 2 | F28: =VLOOKUP($B28,'Hypothèses '!$B$76:$K$83,'Hypothèses '!F$56,FALSE) -> 2 | G28: =VLOOKUP($B28,'Hypothèses '!$B$76:$K$83,'Hypothèses '!G$56,FALSE) -> 2 | H28: =VLOOKUP($B28,'Hypothèses '!$B$76:$K$83,'Hypothèses '!H$56,FALSE) -> 2 | I28: =VLOOKUP($B28,'Hypothèses '!$B$76:$K$83,'Hypothèses '!I$56,FALSE) -> 2 | J28: =VLOOKUP($B28,'Hypothèses '!$B$76:$K$83,'Hypothèses '!J$56,FALSE) -> 2 | K28: =VLOOKUP($B28,'Hypothèses '!$B$76:$K$83,'Hypothèses '!K$56,FALSE) -> 2
B29: Infirmière | C29: =VLOOKUP($B29,'Hypothèses '!$B$76:$K$83,'Hypothèses '!C$56,FALSE) -> 1 | D29: =VLOOKUP($B29,'Hypothèses '!$B$76:$K$83,'Hypothèses '!D$56,FALSE) -> 2 | E29: =VLOOKUP($B29,'Hypothèses '!$B$76:$K$83,'Hypothèses '!E$56,FALSE) -> 2 | F29: =VLOOKUP($B29,'Hypothèses '!$B$76:$K$83,'Hypothèses '!F$56,FALSE) -> 2 | G29: =VLOOKUP($B29,'Hypothèses '!$B$76:$K$83,'Hypothèses '!G$56,FALSE) -> 2 | H29: =VLOOKUP($B29,'Hypothèses '!$B$76:$K$83,'Hypothèses '!H$56,FALSE) -> 2 | I29: =VLOOKUP($B29,'Hypothèses '!$B$76:$K$83,'Hypothèses '!I$56,FALSE) -> 2 | J29: =VLOOKUP($B29,'Hypothèses '!$B$76:$K$83,'Hypothèses '!J$56,FALSE) -> 2 | K29: =VLOOKUP($B29,'Hypothèses '!$B$76:$K$83,'Hypothèses '!K$56,FALSE) -> 2
B30: Laboratoire | C30: =VLOOKUP($B30,'Hypothèses '!$B$76:$K$83,'Hypothèses '!C$56,FALSE) -> 2 | D30: =VLOOKUP($B30,'Hypothèses '!$B$76:$K$83,'Hypothèses '!D$56,FALSE) -> 1 | E30: =VLOOKUP($B30,'Hypothèses '!$B$76:$K$83,'Hypothèses '!E$56,FALSE) -> 1 | F30: =VLOOKUP($B30,'Hypothèses '!$B$76:$K$83,'Hypothèses '!F$56,FALSE) -> 1 | G30: =VLOOKUP($B30,'Hypothèses '!$B$76:$K$83,'Hypothèses '!G$56,FALSE) -> 1 | H30: =VLOOKUP($B30,'Hypothèses '!$B$76:$K$83,'Hypothèses '!H$56,FALSE) -> 1 | I30: =VLOOKUP($B30,'Hypothèses '!$B$76:$K$83,'Hypothèses '!I$56,FALSE) -> 1 | J30: =VLOOKUP($B30,'Hypothèses '!$B$76:$K$83,'Hypothèses '!J$56,FALSE) -> 1 | K30: =VLOOKUP($B30,'Hypothèses '!$B$76:$K$83,'Hypothèses '!K$56,FALSE) -> 1
B31: Orientation | C31: =VLOOKUP($B31,'Hypothèses '!$B$76:$K$83,'Hypothèses '!C$56,FALSE) -> 1 | D31: =VLOOKUP($B31,'Hypothèses '!$B$76:$K$83,'Hypothèses '!D$56,FALSE) -> 0 | E31: =VLOOKUP($B31,'Hypothèses '!$B$76:$K$83,'Hypothèses '!E$56,FALSE) -> 0 | F31: =VLOOKUP($B31,'Hypothèses '!$B$76:$K$83,'Hypothèses '!F$56,FALSE) -> 0 | G31: =VLOOKUP($B31,'Hypothèses '!$B$76:$K$83,'Hypothèses '!G$56,FALSE) -> 0 | H31: =VLOOKUP($B31,'Hypothèses '!$B$76:$K$83,'Hypothèses '!H$56,FALSE) -> 0 | I31: =VLOOKUP($B31,'Hypothèses '!$B$76:$K$83,'Hypothèses '!I$56,FALSE) -> 0 | J31: =VLOOKUP($B31,'Hypothèses '!$B$76:$K$83,'Hypothèses '!J$56,FALSE) -> 0 | K31: =VLOOKUP($B31,'Hypothèses '!$B$76:$K$83,'Hypothèses '!K$56,FALSE) -> 0
B32: Autre secondaire commun | C32: =VLOOKUP($B32,'Hypothèses '!$B$76:$K$83,'Hypothèses '!C$56,FALSE) -> 2 | D32: =VLOOKUP($B32,'Hypothèses '!$B$76:$K$83,'Hypothèses '!D$56,FALSE) -> 0 | E32: =VLOOKUP($B32,'Hypothèses '!$B$76:$K$83,'Hypothèses '!E$56,FALSE) -> 0 | F32: =VLOOKUP($B32,'Hypothèses '!$B$76:$K$83,'Hypothèses '!F$56,FALSE) -> 0 | G32: =VLOOKUP($B32,'Hypothèses '!$B$76:$K$83,'Hypothèses '!G$56,FALSE) -> 0 | H32: =VLOOKUP($B32,'Hypothèses '!$B$76:$K$83,'Hypothèses '!H$56,FALSE) -> 0 | I32: =VLOOKUP($B32,'Hypothèses '!$B$76:$K$83,'Hypothèses '!I$56,FALSE) -> 0 | J32: =VLOOKUP($B32,'Hypothèses '!$B$76:$K$83,'Hypothèses '!J$56,FALSE) -> 0 | K32: =VLOOKUP($B32,'Hypothèses '!$B$76:$K$83,'Hypothèses '!K$56,FALSE) -> 0
A34: CALCULS MASSE SALARIALE | D34: ='Hypothèses '!C9 -> 2024 | E34: =D34+1 -> 2025 | F34: =E34+1 -> 2026 | G34: =F34+1 -> 2027 | H34: =G34+1 -> 2028 | I34: =H34+1 -> 2029 | J34: =I34+1 -> 2030 | K34: =J34+1 -> 2031
B35: augmentation salariale | D35: =HLOOKUP(D$34,'Hypothèses '!$C$34:$K$35,2,FALSE) -> 0 | E35: =HLOOKUP(E$34,'Hypothèses '!$C$34:$K$35,2,FALSE) -> 0 | F35: =HLOOKUP(F$34,'Hypothèses '!$C$34:$K$35,2,FALSE) -> 0 | G35: =HLOOKUP(G$34,'Hypothèses '!$C$34:$K$35,2,FALSE) -> 0 | H35: =HLOOKUP(H$34,'Hypothèses '!$C$34:$K$35,2,FALSE) -> 0 | I35: =HLOOKUP(I$34,'Hypothèses '!$C$34:$K$35,2,FALSE) -> 0 | J35: =HLOOKUP(J$34,'Hypothèses '!$C$34:$K$35,2,FALSE) -> 0 | K35: =HLOOKUP(K$34,'Hypothèses '!$C$34:$K$35,2,FALSE) -> 0
B36: taux PRRD | D36: =HLOOKUP(D$34,'Hypothèses '!$C$34:$K$40,7,FALSE) -> 0 | E36: =HLOOKUP(E$34,'Hypothèses '!$C$34:$K$40,7,FALSE) -> 0 | F36: =HLOOKUP(F$34,'Hypothèses '!$C$34:$K$40,7,FALSE) -> 0 | G36: =HLOOKUP(G$34,'Hypothèses '!$C$34:$K$40,7,FALSE) -> 0 | H36: =HLOOKUP(H$34,'Hypothèses '!$C$34:$K$40,7,FALSE) -> 0 | I36: =HLOOKUP(I$34,'Hypothèses '!$C$34:$K$40,7,FALSE) -> 0 | J36: =HLOOKUP(J$34,'Hypothèses '!$C$34:$K$40,7,FALSE) -> 0 | K36: =HLOOKUP(K$34,'Hypothèses '!$C$34:$K$40,7,FALSE) -> 0
B37: Taux change | D37: =HLOOKUP(D$34,'Hypothèses '!$C$34:$K$40,5,FALSE) -> 0.25 | E37: =HLOOKUP(E$34,'Hypothèses '!$C$34:$K$40,5,FALSE) -> 0.25 | F37: =HLOOKUP(F$34,'Hypothèses '!$C$34:$K$40,5,FALSE) -> 0.25 | G37: =HLOOKUP(G$34,'Hypothèses '!$C$34:$K$40,5,FALSE) -> 0.25 | H37: =HLOOKUP(H$34,'Hypothèses '!$C$34:$K$40,5,FALSE) -> 0.25 | I37: =HLOOKUP(I$34,'Hypothèses '!$C$34:$K$40,5,FALSE) -> 0.25 | J37: =HLOOKUP(J$34,'Hypothèses '!$C$34:$K$40,5,FALSE) -> 0.25 | K37: =HLOOKUP(K$34,'Hypothèses '!$C$34:$K$40,5,FALSE) -> 0.25
A38: MATERNELLE | C38: =C$4 -> 2023/2024 | D38: =D$4 -> 2024/2025 | E38: =E$4 -> 2025/2026 | F38: =F$4 -> 2026/2027 | G38: =G$4 -> 2027/2028 | H38: =H$4 -> 2028/2029 | I38: =I$4 -> 2029/2030 | J38: =J$4 -> 2030/2031 | K38: =K$4 -> 2031/2032
A39: Personnel total | C39: =C40+C60 -> #N/A | D39: =D40+D60 -> #N/A | E39: =E40+E60 -> #N/A | F39: =F40+F60 -> #N/A | G39: =G40+G60 -> #N/A | H39: =H40+H60 -> #N/A | I39: =I40+I60 -> #N/A | J39: =J40+J60 -> #N/A | K39: =K40+K60 -> #N/A
A40: Personnels non enseignants - Proratisation par niveau | C40: =SUM(C42:C49)+SUM(C52:C58)+C65 -> #N/A | D40: =SUM(D42:D49)+SUM(D52:D58)+D65 -> #N/A | E40: =SUM(E42:E49)+SUM(E52:E58)+E65 -> #N/A | F40: =SUM(F42:F49)+SUM(F52:F58)+F65 -> #N/A | G40: =SUM(G42:G49)+SUM(G52:G58)+G65 -> #N/A | H40: =SUM(H42:H49)+SUM(H52:H58)+H65 -> #N/A | I40: =SUM(I42:I49)+SUM(I52:I58)+I65 -> #N/A | J40: =SUM(J42:J49)+SUM(J52:J58)+J65 -> #N/A | K40: =SUM(K42:K49)+SUM(K52:K58)+K65 -> #N/A
A41: Communs | B41: Clé répartition | C41: =HLOOKUP(C38,'Projection Effectifs'!$S$31:$AC$35,2,FALSE) -> 0 | D41: =HLOOKUP(D38,'Projection Effectifs'!$S$31:$AC$35,2,FALSE) -> 0.16314031 | E41: =HLOOKUP(E38,'Projection Effectifs'!$S$31:$AC$35,2,FALSE) -> 0.1490411 | F41: =HLOOKUP(F38,'Projection Effectifs'!$S$31:$AC$35,2,FALSE) -> 0.11380282 | G41: =HLOOKUP(G38,'Projection Effectifs'!$S$31:$AC$35,2,FALSE) -> 0.11117613 | H41: =HLOOKUP(H38,'Projection Effectifs'!$S$31:$AC$35,2,FALSE) -> 0.14125956 | I41: =HLOOKUP(I38,'Projection Effectifs'!$S$31:$AC$35,2,FALSE) -> 0.17584994 | J41: =HLOOKUP(J38,'Projection Effectifs'!$S$31:$AC$35,2,FALSE) -> 0.21176471 | K41: =HLOOKUP(K38,'Projection Effectifs'!$S$31:$AC$35,2,FALSE) -> 0.21466905
B42: =$B$6 -> Chef d'Etablissement PDL | C42: =VLOOKUP($B42,$B$6:$K$13,C$3,FALSE)*C$41 -> #N/A | D42: =VLOOKUP($B42,$B$6:$K$13,D$3,FALSE)*D$41 -> #N/A | E42: =VLOOKUP($B42,$B$6:$K$13,E$3,FALSE)*E$41 -> #N/A | F42: =VLOOKUP($B42,$B$6:$K$13,F$3,FALSE)*F$41 -> #N/A | G42: =VLOOKUP($B42,$B$6:$K$13,G$3,FALSE)*G$41 -> #N/A | H42: =VLOOKUP($B42,$B$6:$K$13,H$3,FALSE)*H$41 -> #N/A | I42: =VLOOKUP($B42,$B$6:$K$13,I$3,FALSE)*I$41 -> #N/A | J42: =VLOOKUP($B42,$B$6:$K$13,J$3,FALSE)*J$41 -> #N/A | K42: =VLOOKUP($B42,$B$6:$K$13,K$3,FALSE)*K$41 -> #N/A
B43: =$B$7 -> DAF PDL | C43: =VLOOKUP($B43,$B$6:$K$13,C$3,FALSE)*C$41 -> #N/A | D43: =VLOOKUP($B43,$B$6:$K$13,D$3,FALSE)*D$41 -> #N/A | E43: =VLOOKUP($B43,$B$6:$K$13,E$3,FALSE)*E$41 -> #N/A | F43: =VLOOKUP($B43,$B$6:$K$13,F$3,FALSE)*F$41 -> #N/A | G43: =VLOOKUP($B43,$B$6:$K$13,G$3,FALSE)*G$41 -> #N/A | H43: =VLOOKUP($B43,$B$6:$K$13,H$3,FALSE)*H$41 -> #N/A | I43: =VLOOKUP($B43,$B$6:$K$13,I$3,FALSE)*I$41 -> #N/A | J43: =VLOOKUP($B43,$B$6:$K$13,J$3,FALSE)*J$41 -> #N/A | K43: =VLOOKUP($B43,$B$6:$K$13,K$3,FALSE)*K$41 -> #N/A
B44: =$B$8 -> DRH | C44: =VLOOKUP($B44,$B$6:$K$13,C$3,FALSE)*C$41 -> 0 | D44: =VLOOKUP($B44,$B$6:$K$13,D$3,FALSE)*D$41 -> 0.32628062 | E44: =VLOOKUP($B44,$B$6:$K$13,E$3,FALSE)*E$41 -> 0 | F44: =VLOOKUP($B44,$B$6:$K$13,F$3,FALSE)*F$41 -> 0 | G44: =VLOOKUP($B44,$B$6:$K$13,G$3,FALSE)*G$41 -> 0 | H44: =VLOOKUP($B44,$B$6:$K$13,H$3,FALSE)*H$41 -> 0 | I44: =VLOOKUP($B44,$B$6:$K$13,I$3,FALSE)*I$41 -> 0 | J44: =VLOOKUP($B44,$B$6:$K$13,J$3,FALSE)*J$41 -> 0 | K44: =VLOOKUP($B44,$B$6:$K$13,K$3,FALSE)*K$41 -> 0
B45: =$B$9 -> Autre Administratif | C45: =VLOOKUP($B45,$B$6:$K$13,C$3,FALSE)*C$41 -> 0 | D45: =VLOOKUP($B45,$B$6:$K$13,D$3,FALSE)*D$41 -> 0 | E45: =VLOOKUP($B45,$B$6:$K$13,E$3,FALSE)*E$41 -> 0 | F45: =VLOOKUP($B45,$B$6:$K$13,F$3,FALSE)*F$41 -> 0 | G45: =VLOOKUP($B45,$B$6:$K$13,G$3,FALSE)*G$41 -> 0 | H45: =VLOOKUP($B45,$B$6:$K$13,H$3,FALSE)*H$41 -> 0 | I45: =VLOOKUP($B45,$B$6:$K$13,I$3,FALSE)*I$41 -> 0 | J45: =VLOOKUP($B45,$B$6:$K$13,J$3,FALSE)*J$41 -> 0 | K45: =VLOOKUP($B45,$B$6:$K$13,K$3,FALSE)*K$41 -> 0
B46: =$B$10 -> Technique - Informatique - Maintenance | C46: =VLOOKUP($B46,$B$6:$K$13,C$3,FALSE)*C$41 -> #N/A | D46: =VLOOKUP($B46,$B$6:$K$13,D$3,FALSE)*D$41 -> #N/A | E46: =VLOOKUP($B46,$B$6:$K$13,E$3,FALSE)*E$41 -> #N/A | F46: =VLOOKUP($B46,$B$6:$K$13,F$3,FALSE)*F$41 -> #N/A | G46: =VLOOKUP($B46,$B$6:$K$13,G$3,FALSE)*G$41 -> #N/A | H46: =VLOOKUP($B46,$B$6:$K$13,H$3,FALSE)*H$41 -> #N/A | I46: =VLOOKUP($B46,$B$6:$K$13,I$3,FALSE)*I$41 -> #N/A | J46: =VLOOKUP($B46,$B$6:$K$13,J$3,FALSE)*J$41 -> #N/A | K46: =VLOOKUP($B46,$B$6:$K$13,K$3,FALSE)*K$41 -> #N/A
B47: =$B$11 -> Entretien / Sécurité | C47: =VLOOKUP($B47,$B$6:$K$13,C$3,FALSE)*C$41 -> 0 | D47: =VLOOKUP($B47,$B$6:$K$13,D$3,FALSE)*D$41 -> 0.16314031 | E47: =VLOOKUP($B47,$B$6:$K$13,E$3,FALSE)*E$41 -> 0 | F47: =VLOOKUP($B47,$B$6:$K$13,F$3,FALSE)*F$41 -> 0 | G47: =VLOOKUP($B47,$B$6:$K$13,G$3,FALSE)*G$41 -> 0 | H47: =VLOOKUP($B47,$B$6:$K$13,H$3,FALSE)*H$41 -> 0 | I47: =VLOOKUP($B47,$B$6:$K$13,I$3,FALSE)*I$41 -> 0 | J47: =VLOOKUP($B47,$B$6:$K$13,J$3,FALSE)*J$41 -> 0 | K47: =VLOOKUP($B47,$B$6:$K$13,K$3,FALSE)*K$41 -> 0
B48: =$B$12 -> Documentation | C48: =VLOOKUP($B48,$B$6:$K$13,C$3,FALSE)*C$41 -> 0 | D48: =VLOOKUP($B48,$B$6:$K$13,D$3,FALSE)*D$41 -> 0.32628062 | E48: =VLOOKUP($B48,$B$6:$K$13,E$3,FALSE)*E$41 -> 0 | F48: =VLOOKUP($B48,$B$6:$K$13,F$3,FALSE)*F$41 -> 0 | G48: =VLOOKUP($B48,$B$6:$K$13,G$3,FALSE)*G$41 -> 0 | H48: =VLOOKUP($B48,$B$6:$K$13,H$3,FALSE)*H$41 -> 0 | I48: =VLOOKUP($B48,$B$6:$K$13,I$3,FALSE)*I$41 -> 0 | J48: =VLOOKUP($B48,$B$6:$K$13,J$3,FALSE)*J$41 -> 0 | K48: =VLOOKUP($B48,$B$6:$K$13,K$3,FALSE)*K$41 -> 0
B49: =$B$13 -> Autre commun | C49: =VLOOKUP($B49,$B$6:$K$13,C$3,FALSE)*C$41 -> 0 | D49: =VLOOKUP($B49,$B$6:$K$13,D$3,FALSE)*D$41 -> 0 | E49: =VLOOKUP($B49,$B$6:$K$13,E$3,FALSE)*E$41 -> 0 | F49: =VLOOKUP($B49,$B$6:$K$13,F$3,FALSE)*F$41 -> 0 | G49: =VLOOKUP($B49,$B$6:$K$13,G$3,FALSE)*G$41 -> 0 | H49: =VLOOKUP($B49,$B$6:$K$13,H$3,FALSE)*H$41 -> 0 | I49: =VLOOKUP($B49,$B$6:$K$13,I$3,FALSE)*I$41 -> 0 | J49: =VLOOKUP($B49,$B$6:$K$13,J$3,FALSE)*J$41 -> 0 | K49: =VLOOKUP($B49,$B$6:$K$13,K$3,FALSE)*K$41 -> 0
A51: Communs Primaire | B51: Clé répartition | C51: =HLOOKUP(C$38,'Projection Effectifs'!$S$37:$AC$43,2,FALSE) -> 0 | D51: =HLOOKUP(D$38,'Projection Effectifs'!$S$37:$AC$43,2,FALSE) -> 0.31038136 | E51: =HLOOKUP(E$38,'Projection Effectifs'!$S$37:$AC$43,2,FALSE) -> 0.29437229 | F51: =HLOOKUP(F$38,'Projection Effectifs'!$S$37:$AC$43,2,FALSE) -> 0.23625731 | G51: =HLOOKUP(G$38,'Projection Effectifs'!$S$37:$AC$43,2,FALSE) -> 0.24142313 | H51: =HLOOKUP(H$38,'Projection Effectifs'!$S$37:$AC$43,2,FALSE) -> 0.31168831 | I51: =HLOOKUP(I$38,'Projection Effectifs'!$S$37:$AC$43,2,FALSE) -> 0.39164491 | J51: =HLOOKUP(J$38,'Projection Effectifs'!$S$37:$AC$43,2,FALSE) -> 0.4787234 | K51: =HLOOKUP(K$38,'Projection Effectifs'!$S$37:$AC$43,2,FALSE) -> 0.4851752
B52: =$B$16 -> Direction PDL | C52: =VLOOKUP($B52,$B$16:$K$22,C$3,FALSE)*C$51 -> #N/A | D52: =VLOOKUP($B52,$B$16:$K$22,D$3,FALSE)*D$51 -> #N/A | E52: =VLOOKUP($B52,$B$16:$K$22,E$3,FALSE)*E$51 -> #N/A | F52: =VLOOKUP($B52,$B$16:$K$22,F$3,FALSE)*F$51 -> #N/A | G52: =VLOOKUP($B52,$B$16:$K$22,G$3,FALSE)*G$51 -> #N/A | H52: =VLOOKUP($B52,$B$16:$K$22,H$3,FALSE)*H$51 -> #N/A | I52: =VLOOKUP($B52,$B$16:$K$22,I$3,FALSE)*I$51 -> #N/A | J52: =VLOOKUP($B52,$B$16:$K$22,J$3,FALSE)*J$51 -> #N/A | K52: =VLOOKUP($B52,$B$16:$K$22,K$3,FALSE)*K$51 -> #N/A
B53: =$B$17 -> Direction adjointe | C53: =VLOOKUP($B53,$B$16:$K$22,C$3,FALSE)*C$51 -> 0 | D53: =VLOOKUP($B53,$B$16:$K$22,D$3,FALSE)*D$51 -> 0 | E53: =VLOOKUP($B53,$B$16:$K$22,E$3,FALSE)*E$51 -> 0 | F53: =VLOOKUP($B53,$B$16:$K$22,F$3,FALSE)*F$51 -> 0 | G53: =VLOOKUP($B53,$B$16:$K$22,G$3,FALSE)*G$51 -> 0 | H53: =VLOOKUP($B53,$B$16:$K$22,H$3,FALSE)*H$51 -> 0 | I53: =VLOOKUP($B53,$B$16:$K$22,I$3,FALSE)*I$51 -> 0 | J53: =VLOOKUP($B53,$B$16:$K$22,J$3,FALSE)*J$51 -> 0 | K53: =VLOOKUP($B53,$B$16:$K$22,K$3,FALSE)*K$51 -> 0
B54: =$B$18 -> Conseiller pédagogique | C54: =VLOOKUP($B54,$B$16:$K$22,C$3,FALSE)*C$51 -> 0 | D54: =VLOOKUP($B54,$B$16:$K$22,D$3,FALSE)*D$51 -> 0 | E54: =VLOOKUP($B54,$B$16:$K$22,E$3,FALSE)*E$51 -> 0 | F54: =VLOOKUP($B54,$B$16:$K$22,F$3,FALSE)*F$51 -> 0 | G54: =VLOOKUP($B54,$B$16:$K$22,G$3,FALSE)*G$51 -> 0 | H54: =VLOOKUP($B54,$B$16:$K$22,H$3,FALSE)*H$51 -> 0 | I54: =VLOOKUP($B54,$B$16:$K$22,I$3,FALSE)*I$51 -> 0 | J54: =VLOOKUP($B54,$B$16:$K$22,J$3,FALSE)*J$51 -> 0 | K54: =VLOOKUP($B54,$B$16:$K$22,K$3,FALSE)*K$51 -> 0
B55: =$B$19 -> Vie scolaire - Educateurs | C55: =VLOOKUP($B55,$B$16:$K$22,C$3,FALSE)*C$51 -> 0 | D55: =VLOOKUP($B55,$B$16:$K$22,D$3,FALSE)*D$51 -> 0.31038136 | E55: =VLOOKUP($B55,$B$16:$K$22,E$3,FALSE)*E$51 -> 0 | F55: =VLOOKUP($B55,$B$16:$K$22,F$3,FALSE)*F$51 -> 0 | G55: =VLOOKUP($B55,$B$16:$K$22,G$3,FALSE)*G$51 -> 0 | H55: =VLOOKUP($B55,$B$16:$K$22,H$3,FALSE)*H$51 -> 0 | I55: =VLOOKUP($B55,$B$16:$K$22,I$3,FALSE)*I$51 -> 0 | J55: =VLOOKUP($B55,$B$16:$K$22,J$3,FALSE)*J$51 -> 0 | K55: =VLOOKUP($B55,$B$16:$K$22,K$3,FALSE)*K$51 -> 0
B56: =$B$20 -> Documentation | C56: =VLOOKUP($B56,$B$16:$K$22,C$3,FALSE)*C$51 -> 0 | D56: =VLOOKUP($B56,$B$16:$K$22,D$3,FALSE)*D$51 -> 0.31038136 | E56: =VLOOKUP($B56,$B$16:$K$22,E$3,FALSE)*E$51 -> 0 | F56: =VLOOKUP($B56,$B$16:$K$22,F$3,FALSE)*F$51 -> 0 | G56: =VLOOKUP($B56,$B$16:$K$22,G$3,FALSE)*G$51 -> 0 | H56: =VLOOKUP($B56,$B$16:$K$22,H$3,FALSE)*H$51 -> 0 | I56: =VLOOKUP($B56,$B$16:$K$22,I$3,FALSE)*I$51 -> 0 | J56: =VLOOKUP($B56,$B$16:$K$22,J$3,FALSE)*J$51 -> 0 | K56: =VLOOKUP($B56,$B$16:$K$22,K$3,FALSE)*K$51 -> 0 | M56: =(8/12+4/12) -> 1
B57: =$B$21 -> Infirmière | C57: =VLOOKUP($B57,$B$16:$K$22,C$3,FALSE)*C$51 -> 0 | D57: =VLOOKUP($B57,$B$16:$K$22,D$3,FALSE)*D$51 -> 0 | E57: =VLOOKUP($B57,$B$16:$K$22,E$3,FALSE)*E$51 -> 0 | F57: =VLOOKUP($B57,$B$16:$K$22,F$3,FALSE)*F$51 -> 0 | G57: =VLOOKUP($B57,$B$16:$K$22,G$3,FALSE)*G$51 -> 0 | H57: =VLOOKUP($B57,$B$16:$K$22,H$3,FALSE)*H$51 -> 0 | I57: =VLOOKUP($B57,$B$16:$K$22,I$3,FALSE)*I$51 -> 0 | J57: =VLOOKUP($B57,$B$16:$K$22,J$3,FALSE)*J$51 -> 0 | K57: =VLOOKUP($B57,$B$16:$K$22,K$3,FALSE)*K$51 -> 0
B58: =$B$22 -> Autre primaire commun | C58: =VLOOKUP($B58,$B$16:$K$22,C$3,FALSE)*C$51 -> 0 | D58: =VLOOKUP($B58,$B$16:$K$22,D$3,FALSE)*D$51 -> 0.62076271 | E58: =VLOOKUP($B58,$B$16:$K$22,E$3,FALSE)*E$51 -> 0 | F58: =VLOOKUP($B58,$B$16:$K$22,F$3,FALSE)*F$51 -> 0 | G58: =VLOOKUP($B58,$B$16:$K$22,G$3,FALSE)*G$51 -> 0 | H58: =VLOOKUP($B58,$B$16:$K$22,H$3,FALSE)*H$51 -> 0 | I58: =VLOOKUP($B58,$B$16:$K$22,I$3,FALSE)*I$51 -> 0 | J58: =VLOOKUP($B58,$B$16:$K$22,J$3,FALSE)*J$51 -> 0 | K58: =VLOOKUP($B58,$B$16:$K$22,K$3,FALSE)*K$51 -> 0
A60: Personnels Enseignants et ASEM | C60: =SUM(C62:C64) -> 0 | D60: =SUM(D62:D64) -> 1.95 | E60: =SUM(E62:E64) -> 0 | F60: =SUM(F62:F64) -> 0 | G60: =SUM(G62:G64) -> 0 | H60: =SUM(H62:H64) -> 0 | I60: =SUM(I62:I64) -> 0 | J60: =SUM(J62:J64) -> 0 | K60: =SUM(K62:K64) -> 0
B61: Nb divisions | C61: =HLOOKUP(C$38,'Hypothèses '!$C$42:$K$46,2,FALSE) -> 0 | D61: =HLOOKUP(D$38,'Hypothèses '!$C$42:$K$46,2,FALSE) -> 1.5 | E61: =HLOOKUP(E$38,'Hypothèses '!$C$42:$K$46,2,FALSE) -> 0 | F61: =HLOOKUP(F$38,'Hypothèses '!$C$42:$K$46,2,FALSE) -> 0 | G61: =HLOOKUP(G$38,'Hypothèses '!$C$42:$K$46,2,FALSE) -> 0 | H61: =HLOOKUP(H$38,'Hypothèses '!$C$42:$K$46,2,FALSE) -> 0 | I61: =HLOOKUP(I$38,'Hypothèses '!$C$42:$K$46,2,FALSE) -> 0 | J61: =HLOOKUP(J$38,'Hypothèses '!$C$42:$K$46,2,FALSE) -> 0 | K61: =HLOOKUP(K$38,'Hypothèses '!$C$42:$K$46,2,FALSE) -> 0
B62: Enseignants Détachés | C62: =IFERROR(HLOOKUP(C$38,'Hypothèses '!$C$90:$K$93,2,FALSE),0) -> 0 | D62: =IFERROR(HLOOKUP(D$38,'Hypothèses '!$C$90:$K$93,2,FALSE),0) -> 0 | E62: =IFERROR(HLOOKUP(E$38,'Hypothèses '!$C$90:$K$93,2,FALSE),0) -> 0 | F62: =IFERROR(HLOOKUP(F$38,'Hypothèses '!$C$90:$K$93,2,FALSE),0) -> 0 | G62: =IFERROR(HLOOKUP(G$38,'Hypothèses '!$C$90:$K$93,2,FALSE),0) -> 0 | H62: =IFERROR(HLOOKUP(H$38,'Hypothèses '!$C$90:$K$93,2,FALSE),0) -> 0 | I62: =IFERROR(HLOOKUP(I$38,'Hypothèses '!$C$90:$K$93,2,FALSE),0) -> 0 | J62: =IFERROR(HLOOKUP(J$38,'Hypothèses '!$C$90:$K$93,2,FALSE),0) -> 0 | K62: =IFERROR(HLOOKUP(K$38,'Hypothèses '!$C$90:$K$93,2,FALSE),0) -> 0
B63: Enseignants classe PDL | C63: =C61-C$62 -> 0 | D63: =D61-D$62 -> 1.5 | E63: =E61-E$62 -> 0 | F63: =F61-F$62 -> 0 | G63: =G61-G$62 -> 0 | H63: =H61-H$62 -> 0 | I63: =I61-I$62 -> 0 | J63: =J61-J$62 -> 0 | K63: =K61-K$62 -> 0
B64: Enseignants Langues et complémentaires | C64: =IF(HLOOKUP(C$38,'Hypothèses '!$C$97:$K$100,2,FALSE)=1,'Tables Enseignants'!$C$7*C61,'Tables Enseignants'!$C$8*C61) -> 0 | D64: =IF(HLOOKUP(D$38,'Hypothèses '!$C$97:$K$100,2,FALSE)=1,'Tables Enseignants'!$C$7*D61,'Tables Enseignants'!$C$8*D61) -> 0.45 | E64: =IF(HLOOKUP(E$38,'Hypothèses '!$C$97:$K$100,2,FALSE)=1,'Tables Enseignants'!$C$7*E61,'Tables Enseignants'!$C$8*E61) -> 0 | F64: =IF(HLOOKUP(F$38,'Hypothèses '!$C$97:$K$100,2,FALSE)=1,'Tables Enseignants'!$C$7*F61,'Tables Enseignants'!$C$8*F61) -> 0 | G64: =IF(HLOOKUP(G$38,'Hypothèses '!$C$97:$K$100,2,FALSE)=1,'Tables Enseignants'!$C$7*G61,'Tables Enseignants'!$C$8*G61) -> 0 | H64: =IF(HLOOKUP(H$38,'Hypothèses '!$C$97:$K$100,2,FALSE)=1,'Tables Enseignants'!$C$7*H61,'Tables Enseignants'!$C$8*H61) -> 0 | I64: =IF(HLOOKUP(I$38,'Hypothèses '!$C$97:$K$100,2,FALSE)=1,'Tables Enseignants'!$C$7*I61,'Tables Enseignants'!$C$8*I61) -> 0 | J64: =IF(HLOOKUP(J$38,'Hypothèses '!$C$97:$K$100,2,FALSE)=1,'Tables Enseignants'!$C$7*J61,'Tables Enseignants'!$C$8*J61) -> 0 | K64: =IF(HLOOKUP(K$38,'Hypothèses '!$C$97:$K$100,2,FALSE)=1,'Tables Enseignants'!$C$7*K61,'Tables Enseignants'!$C$8*K61) -> 0
B65: ASEM | C65: =C61 -> 0 | D65: =HLOOKUP(D$38,'Hypothèses '!$C$42:$K$46,2,FALSE) -> 1.5 | E65: =HLOOKUP(E$38,'Hypothèses '!$C$42:$K$46,2,FALSE) -> 0 | F65: =HLOOKUP(F$38,'Hypothèses '!$C$42:$K$46,2,FALSE) -> 0 | G65: =HLOOKUP(G$38,'Hypothèses '!$C$42:$K$46,2,FALSE) -> 0 | H65: =HLOOKUP(H$38,'Hypothèses '!$C$42:$K$46,2,FALSE) -> 0 | I65: =HLOOKUP(I$38,'Hypothèses '!$C$42:$K$46,2,FALSE) -> 0 | J65: =HLOOKUP(J$38,'Hypothèses '!$C$42:$K$46,2,FALSE) -> 0 | K65: =HLOOKUP(K$38,'Hypothèses '!$C$42:$K$46,2,FALSE) -> 0
A67: Personnels Calculs masse salariale | B67: indice année | C67: 0 | D67: 0 | E67: 1 | F67: 2 | G67: 3 | H67: 4 | I67: 5 | J67: 6 | K67: 7
A68: Année civile - Exercice comptable | D68: ='Hypothèses '!C9 -> 2024 | E68: =D68+1 -> 2025 | F68: =E68+1 -> 2026 | G68: =F68+1 -> 2027 | H68: =G68+1 -> 2028 | I68: =H68+1 -> 2029 | J68: =I68+1 -> 2030 | K68: =J68+1 -> 2031
A69: Communs | B69: =B42 -> Chef d'Etablissement PDL | D69: =(C42*8/12+D42*4/12)*VLOOKUP($B69,'Hypothèses '!$B$106:$E$126,3,FALSE) -> #N/A | E69: =(D42*8/12+E42*4/12)*VLOOKUP($B69,'Hypothèses '!$B$106:$E$126,3,FALSE)*(1+$E$35) -> #N/A | F69: =(E42*8/12+F42*4/12)*VLOOKUP($B69,'Hypothèses '!$B$106:$E$126,3,FALSE)*(1+$E$35)*(1+$F$35) -> #N/A | G69: =(F42*8/12+G42*4/12)*VLOOKUP($B69,'Hypothèses '!$B$106:$E$126,3,FALSE)*(1+$E$35)*(1+$F$35)*(1+$G$35) -> #N/A | H69: =(G42*8/12+H42*4/12)*VLOOKUP($B69,'Hypothèses '!$B$106:$E$126,3,FALSE)*(1+$E$35)*(1+$F$35)*(1+$G$35)*(1+$H$35) -> #N/A | I69: =(H42*8/12+I42*4/12)*VLOOKUP($B69,'Hypothèses '!$B$106:$E$126,3,FALSE)*(1+$E$35)*(1+$F$35)*(1+$G$35)*(1+$H$35)*(1+$I$35) -> #N/A | J69: =(I42*8/12+J42*4/12)*VLOOKUP($B69,'Hypothèses '!$B$106:$E$126,3,FALSE)*(1+$E$35)*(1+$F$35)*(1+$G$35)*(1+$H$35)*(1+$I$35)*(1+$J$35) -> #N/A | K69: =(J42*8/12+K42*4/12)*VLOOKUP($B69,'Hypothèses '!$B$106:$E$126,3,FALSE)*(1+$E$35)*(1+$F$35)*(1+$G$35)*(1+$H$35)*(1+$I$35)*(1+$J$35)*(1+$K$35) -> #N/A
B70: =B43 -> DAF PDL | D70: =(C43*8/12+D43*4/12)*VLOOKUP($B70,'Hypothèses '!$B$106:$E$126,3,FALSE) -> #N/A | E70: =(D43*8/12+E43*4/12)*VLOOKUP($B70,'Hypothèses '!$B$106:$E$126,3,FALSE)*(1+$E$35) -> #N/A | F70: =(E43*8/12+F43*4/12)*VLOOKUP($B70,'Hypothèses '!$B$106:$E$126,3,FALSE)*(1+$E$35)*(1+$F$35) -> #N/A | G70: =(F43*8/12+G43*4/12)*VLOOKUP($B70,'Hypothèses '!$B$106:$E$126,3,FALSE)*(1+$E$35)*(1+$F$35)*(1+$G$35) -> #N/A | H70: =(G43*8/12+H43*4/12)*VLOOKUP($B70,'Hypothèses '!$B$106:$E$126,3,FALSE)*(1+$E$35)*(1+$F$35)*(1+$G$35)*(1+$H$35) -> #N/A | I70: =(H43*8/12+I43*4/12)*VLOOKUP($B70,'Hypothèses '!$B$106:$E$126,3,FALSE)*(1+$E$35)*(1+$F$35)*(1+$G$35)*(1+$H$35)*(1+$I$35) -> #N/A | J70: =(I43*8/12+J43*4/12)*VLOOKUP($B70,'Hypothèses '!$B$106:$E$126,3,FALSE)*(1+$E$35)*(1+$F$35)*(1+$G$35)*(1+$H$35)*(1+$I$35)*(1+$J$35) -> #N/A | K70: =(J43*8/12+K43*4/12)*VLOOKUP($B70,'Hypothèses '!$B$106:$E$126,3,FALSE)*(1+$E$35)*(1+$F$35)*(1+$G$35)*(1+$H$35)*(1+$I$35)*(1+$J$35)*(1+$K$35) -> #N/A
B71: =B44 -> DRH | D71: =(C44*8/12+D44*4/12)*VLOOKUP($B71,'Hypothèses '!$B$106:$E$126,3,FALSE) -> 0 | E71: =(D44*8/12+E44*4/12)*VLOOKUP($B71,'Hypothèses '!$B$106:$E$126,3,FALSE)*(1+$E$35) -> 0 | F71: =(E44*8/12+F44*4/12)*VLOOKUP($B71,'Hypothèses '!$B$106:$E$126,3,FALSE)*(1+$E$35)*(1+$F$35) -> 0 | G71: =(F44*8/12+G44*4/12)*VLOOKUP($B71,'Hypothèses '!$B$106:$E$126,3,FALSE)*(1+$E$35)*(1+$F$35)*(1+$G$35) -> 0 | H71: =(G44*8/12+H44*4/12)*VLOOKUP($B71,'Hypothèses '!$B$106:$E$126,3,FALSE)*(1+$E$35)*(1+$F$35)*(1+$G$35)*(1+$H$35) -> 0 | I71: =(H44*8/12+I44*4/12)*VLOOKUP($B71,'Hypothèses '!$B$106:$E$126,3,FALSE)*(1+$E$35)*(1+$F$35)*(1+$G$35)*(1+$H$35)*(1+$I$35) -> 0 | J71: =(I44*8/12+J44*4/12)*VLOOKUP($B71,'Hypothèses '!$B$106:$E$126,3,FALSE)*(1+$E$35)*(1+$F$35)*(1+$G$35)*(1+$H$35)*(1+$I$35)*(1+$J$35) -> 0 | K71: =(J44*8/12+K44*4/12)*VLOOKUP($B71,'Hypothèses '!$B$106:$E$126,3,FALSE)*(1+$E$35)*(1+$F$35)*(1+$G$35)*(1+$H$35)*(1+$I$35)*(1+$J$35)*(1+$K$35) -> 0
B72: =B45 -> Autre Administratif | D72: =(C45*8/12+D45*4/12)*VLOOKUP($B72,'Hypothèses '!$B$106:$E$126,3,FALSE) -> 0 | E72: =(D45*8/12+E45*4/12)*VLOOKUP($B72,'Hypothèses '!$B$106:$E$126,3,FALSE)*(1+$E$35) -> 0 | F72: =(E45*8/12+F45*4/12)*VLOOKUP($B72,'Hypothèses '!$B$106:$E$126,3,FALSE)*(1+$E$35)*(1+$F$35) -> 0 | G72: =(F45*8/12+G45*4/12)*VLOOKUP($B72,'Hypothèses '!$B$106:$E$126,3,FALSE)*(1+$E$35)*(1+$F$35)*(1+$G$35) -> 0 | H72: =(G45*8/12+H45*4/12)*VLOOKUP($B72,'Hypothèses '!$B$106:$E$126,3,FALSE)*(1+$E$35)*(1+$F$35)*(1+$G$35)*(1+$H$35) -> 0 | I72: =(H45*8/12+I45*4/12)*VLOOKUP($B72,'Hypothèses '!$B$106:$E$126,3,FALSE)*(1+$E$35)*(1+$F$35)*(1+$G$35)*(1+$H$35)*(1+$I$35) -> 0 | J72: =(I45*8/12+J45*4/12)*VLOOKUP($B72,'Hypothèses '!$B$106:$E$126,3,FALSE)*(1+$E$35)*(1+$F$35)*(1+$G$35)*(1+$H$35)*(1+$I$35)*(1+$J$35) -> 0 | K72: =(J45*8/12+K45*4/12)*VLOOKUP($B72,'Hypothèses '!$B$106:$E$126,3,FALSE)*(1+$E$35)*(1+$F$35)*(1+$G$35)*(1+$H$35)*(1+$I$35)*(1+$J$35)*(1+$K$35) -> 0
B73: =B46 -> Technique - Informatique - Maintenance | D73: =(C46*8/12+D46*4/12)*VLOOKUP($B73,'Hypothèses '!$B$106:$E$126,3,FALSE) -> #N/A | E73: =(D46*8/12+E46*4/12)*VLOOKUP($B73,'Hypothèses '!$B$106:$E$126,3,FALSE)*(1+$E$35) -> #N/A | F73: =(E46*8/12+F46*4/12)*VLOOKUP($B73,'Hypothèses '!$B$106:$E$126,3,FALSE)*(1+$E$35)*(1+$F$35) -> #N/A | G73: =(F46*8/12+G46*4/12)*VLOOKUP($B73,'Hypothèses '!$B$106:$E$126,3,FALSE)*(1+$E$35)*(1+$F$35)*(1+$G$35) -> #N/A | H73: =(G46*8/12+H46*4/12)*VLOOKUP($B73,'Hypothèses '!$B$106:$E$126,3,FALSE)*(1+$E$35)*(1+$F$35)*(1+$G$35)*(1+$H$35) -> #N/A | I73: =(H46*8/12+I46*4/12)*VLOOKUP($B73,'Hypothèses '!$B$106:$E$126,3,FALSE)*(1+$E$35)*(1+$F$35)*(1+$G$35)*(1+$H$35)*(1+$I$35) -> #N/A | J73: =(I46*8/12+J46*4/12)*VLOOKUP($B73,'Hypothèses '!$B$106:$E$126,3,FALSE)*(1+$E$35)*(1+$F$35)*(1+$G$35)*(1+$H$35)*(1+$I$35)*(1+$J$35) -> #N/A | K73: =(J46*8/12+K46*4/12)*VLOOKUP($B73,'Hypothèses '!$B$106:$E$126,3,FALSE)*(1+$E$35)*(1+$F$35)*(1+$G$35)*(1+$H$35)*(1+$I$35)*(1+$J$35)*(1+$K$35) -> #N/A
B74: =B47 -> Entretien / Sécurité | D74: =(C47*8/12+D47*4/12)*VLOOKUP($B74,'Hypothèses '!$B$106:$E$126,3,FALSE) -> 0 | E74: =(D47*8/12+E47*4/12)*VLOOKUP($B74,'Hypothèses '!$B$106:$E$126,3,FALSE)*(1+$E$35) -> 0 | F74: =(E47*8/12+F47*4/12)*VLOOKUP($B74,'Hypothèses '!$B$106:$E$126,3,FALSE)*(1+$E$35)*(1+$F$35) -> 0 | G74: =(F47*8/12+G47*4/12)*VLOOKUP($B74,'Hypothèses '!$B$106:$E$126,3,FALSE)*(1+$E$35)*(1+$F$35)*(1+$G$35) -> 0 | H74: =(G47*8/12+H47*4/12)*VLOOKUP($B74,'Hypothèses '!$B$106:$E$126,3,FALSE)*(1+$E$35)*(1+$F$35)*(1+$G$35)*(1+$H$35) -> 0 | I74: =(H47*8/12+I47*4/12)*VLOOKUP($B74,'Hypothèses '!$B$106:$E$126,3,FALSE)*(1+$E$35)*(1+$F$35)*(1+$G$35)*(1+$H$35)*(1+$I$35) -> 0 | J74: =(I47*8/12+J47*4/12)*VLOOKUP($B74,'Hypothèses '!$B$106:$E$126,3,FALSE)*(1+$E$35)*(1+$F$35)*(1+$G$35)*(1+$H$35)*(1+$I$35)*(1+$J$35) -> 0 | K74: =(J47*8/12+K47*4/12)*VLOOKUP($B74,'Hypothèses '!$B$106:$E$126,3,FALSE)*(1+$E$35)*(1+$F$35)*(1+$G$35)*(1+$H$35)*(1+$I$35)*(1+$J$35)*(1+$K$35) -> 0
B75: =B48 -> Documentation | D75: =(C48*8/12+D48*4/12)*VLOOKUP($B75,'Hypothèses '!$B$106:$E$126,3,FALSE) -> 0 | E75: =(D48*8/12+E48*4/12)*VLOOKUP($B75,'Hypothèses '!$B$106:$E$126,3,FALSE)*(1+$E$35) -> 0 | F75: =(E48*8/12+F48*4/12)*VLOOKUP($B75,'Hypothèses '!$B$106:$E$126,3,FALSE)*(1+$E$35)*(1+$F$35) -> 0 | G75: =(F48*8/12+G48*4/12)*VLOOKUP($B75,'Hypothèses '!$B$106:$E$126,3,FALSE)*(1+$E$35)*(1+$F$35)*(1+$G$35) -> 0 | H75: =(G48*8/12+H48*4/12)*VLOOKUP($B75,'Hypothèses '!$B$106:$E$126,3,FALSE)*(1+$E$35)*(1+$F$35)*(1+$G$35)*(1+$H$35) -> 0 | I75: =(H48*8/12+I48*4/12)*VLOOKUP($B75,'Hypothèses '!$B$106:$E$126,3,FALSE)*(1+$E$35)*(1+$F$35)*(1+$G$35)*(1+$H$35)*(1+$I$35) -> 0 | J75: =(I48*8/12+J48*4/12)*VLOOKUP($B75,'Hypothèses '!$B$106:$E$126,3,FALSE)*(1+$E$35)*(1+$F$35)*(1+$G$35)*(1+$H$35)*(1+$I$35)*(1+$J$35) -> 0 | K75: =(J48*8/12+K48*4/12)*VLOOKUP($B75,'Hypothèses '!$B$106:$E$126,3,FALSE)*(1+$E$35)*(1+$F$35)*(1+$G$35)*(1+$H$35)*(1+$I$35)*(1+$J$35)*(1+$K$35) -> 0
B76: =B49 -> Autre commun | D76: =(C49*8/12+D49*4/12)*VLOOKUP($B76,'Hypothèses '!$B$106:$E$126,3,FALSE) -> 0 | E76: =(D49*8/12+E49*4/12)*VLOOKUP($B76,'Hypothèses '!$B$106:$E$126,3,FALSE)*(1+$E$35) -> 0 | F76: =(E49*8/12+F49*4/12)*VLOOKUP($B76,'Hypothèses '!$B$106:$E$126,3,FALSE)*(1+$E$35)*(1+$F$35) -> 0 | G76: =(F49*8/12+G49*4/12)*VLOOKUP($B76,'Hypothèses '!$B$106:$E$126,3,FALSE)*(1+$E$35)*(1+$F$35)*(1+$G$35) -> 0 | H76: =(G49*8/12+H49*4/12)*VLOOKUP($B76,'Hypothèses '!$B$106:$E$126,3,FALSE)*(1+$E$35)*(1+$F$35)*(1+$G$35)*(1+$H$35) -> 0 | I76: =(H49*8/12+I49*4/12)*VLOOKUP($B76,'Hypothèses '!$B$106:$E$126,3,FALSE)*(1+$E$35)*(1+$F$35)*(1+$G$35)*(1+$H$35)*(1+$I$35) -> 0 | J76: =(I49*8/12+J49*4/12)*VLOOKUP($B76,'Hypothèses '!$B$106:$E$126,3,FALSE)*(1+$E$35)*(1+$F$35)*(1+$G$35)*(1+$H$35)*(1+$I$35)*(1+$J$35) -> 0 | K76: =(J49*8/12+K49*4/12)*VLOOKUP($B76,'Hypothèses '!$B$106:$E$126,3,FALSE)*(1+$E$35)*(1+$F$35)*(1+$G$35)*(1+$H$35)*(1+$I$35)*(1+$J$35)*(1+$K$35) -> 0
A78: Communs Primaire | B78: =B52 -> Direction PDL | D78: =(C52*8/12+D52*4/12)*VLOOKUP($B78,'Hypothèses '!$B$106:$E$126,3,FALSE) -> #N/A | E78: =(D52*8/12+E52*4/12)*VLOOKUP($B78,'Hypothèses '!$B$106:$E$126,3,FALSE)*(1+$E$35) -> #N/A | F78: =(E52*8/12+F52*4/12)*VLOOKUP($B78,'Hypothèses '!$B$106:$E$126,3,FALSE)*(1+$E$35)*(1+$F$35) -> #N/A | G78: =(F52*8/12+G52*4/12)*VLOOKUP($B78,'Hypothèses '!$B$106:$E$126,3,FALSE)*(1+$E$35)*(1+$F$35)*(1+$G$35) -> #N/A | H78: =(G52*8/12+H52*4/12)*VLOOKUP($B78,'Hypothèses '!$B$106:$E$126,3,FALSE)*(1+$E$35)*(1+$F$35)*(1+$G$35)*(1+$H$35) -> #N/A | I78: =(H52*8/12+I52*4/12)*VLOOKUP($B78,'Hypothèses '!$B$106:$E$126,3,FALSE)*(1+$E$35)*(1+$F$35)*(1+$G$35)*(1+$H$35)*(1+$I$35) -> #N/A | J78: =(I52*8/12+J52*4/12)*VLOOKUP($B78,'Hypothèses '!$B$106:$E$126,3,FALSE)*(1+$E$35)*(1+$F$35)*(1+$G$35)*(1+$H$35)*(1+$I$35)*(1+$J$35) -> #N/A | K78: =(J52*8/12+K52*4/12)*VLOOKUP($B78,'Hypothèses '!$B$106:$E$126,3,FALSE)*(1+$E$35)*(1+$F$35)*(1+$G$35)*(1+$H$35)*(1+$I$35)*(1+$J$35)*(1+$K$35) -> #N/A
B79: =B53 -> Direction adjointe | D79: =(C53*8/12+D53*4/12)*VLOOKUP($B79,'Hypothèses '!$B$106:$E$126,3,FALSE) -> 0 | E79: =(D53*8/12+E53*4/12)*VLOOKUP($B79,'Hypothèses '!$B$106:$E$126,3,FALSE)*(1+$E$35) -> 0 | F79: =(E53*8/12+F53*4/12)*VLOOKUP($B79,'Hypothèses '!$B$106:$E$126,3,FALSE)*(1+$E$35)*(1+$F$35) -> 0 | G79: =(F53*8/12+G53*4/12)*VLOOKUP($B79,'Hypothèses '!$B$106:$E$126,3,FALSE)*(1+$E$35)*(1+$F$35)*(1+$G$35) -> 0 | H79: =(G53*8/12+H53*4/12)*VLOOKUP($B79,'Hypothèses '!$B$106:$E$126,3,FALSE)*(1+$E$35)*(1+$F$35)*(1+$G$35)*(1+$H$35) -> 0 | I79: =(H53*8/12+I53*4/12)*VLOOKUP($B79,'Hypothèses '!$B$106:$E$126,3,FALSE)*(1+$E$35)*(1+$F$35)*(1+$G$35)*(1+$H$35)*(1+$I$35) -> 0 | J79: =(I53*8/12+J53*4/12)*VLOOKUP($B79,'Hypothèses '!$B$106:$E$126,3,FALSE)*(1+$E$35)*(1+$F$35)*(1+$G$35)*(1+$H$35)*(1+$I$35)*(1+$J$35) -> 0 | K79: =(J53*8/12+K53*4/12)*VLOOKUP($B79,'Hypothèses '!$B$106:$E$126,3,FALSE)*(1+$E$35)*(1+$F$35)*(1+$G$35)*(1+$H$35)*(1+$I$35)*(1+$J$35)*(1+$K$35) -> 0
B80: =B54 -> Conseiller pédagogique | D80: =(C54*8/12+D54*4/12)*VLOOKUP($B80,'Hypothèses '!$B$106:$E$126,3,FALSE) -> 0 | E80: =(D54*8/12+E54*4/12)*VLOOKUP($B80,'Hypothèses '!$B$106:$E$126,3,FALSE)*(1+$E$35) -> 0 | F80: =(E54*8/12+F54*4/12)*VLOOKUP($B80,'Hypothèses '!$B$106:$E$126,3,FALSE)*(1+$E$35)*(1+$F$35) -> 0 | G80: =(F54*8/12+G54*4/12)*VLOOKUP($B80,'Hypothèses '!$B$106:$E$126,3,FALSE)*(1+$E$35)*(1+$F$35)*(1+$G$35) -> 0 | H80: =(G54*8/12+H54*4/12)*VLOOKUP($B80,'Hypothèses '!$B$106:$E$126,3,FALSE)*(1+$E$35)*(1+$F$35)*(1+$G$35)*(1+$H$35) -> 0 | I80: =(H54*8/12+I54*4/12)*VLOOKUP($B80,'Hypothèses '!$B$106:$E$126,3,FALSE)*(1+$E$35)*(1+$F$35)*(1+$G$35)*(1+$H$35)*(1+$I$35) -> 0 | J80: =(I54*8/12+J54*4/12)*VLOOKUP($B80,'Hypothèses '!$B$106:$E$126,3,FALSE)*(1+$E$35)*(1+$F$35)*(1+$G$35)*(1+$H$35)*(1+$I$35)*(1+$J$35) -> 0 | K80: =(J54*8/12+K54*4/12)*VLOOKUP($B80,'Hypothèses '!$B$106:$E$126,3,FALSE)*(1+$E$35)*(1+$F$35)*(1+$G$35)*(1+$H$35)*(1+$I$35)*(1+$J$35)*(1+$K$35) -> 0
B81: =B55 -> Vie scolaire - Educateurs | D81: =(C55*8/12+D55*4/12)*VLOOKUP($B81,'Hypothèses '!$B$106:$E$126,3,FALSE) -> 0 | E81: =(D55*8/12+E55*4/12)*VLOOKUP($B81,'Hypothèses '!$B$106:$E$126,3,FALSE)*(1+$E$35) -> 0 | F81: =(E55*8/12+F55*4/12)*VLOOKUP($B81,'Hypothèses '!$B$106:$E$126,3,FALSE)*(1+$E$35)*(1+$F$35) -> 0 | G81: =(F55*8/12+G55*4/12)*VLOOKUP($B81,'Hypothèses '!$B$106:$E$126,3,FALSE)*(1+$E$35)*(1+$F$35)*(1+$G$35) -> 0 | H81: =(G55*8/12+H55*4/12)*VLOOKUP($B81,'Hypothèses '!$B$106:$E$126,3,FALSE)*(1+$E$35)*(1+$F$35)*(1+$G$35)*(1+$H$35) -> 0 | I81: =(H55*8/12+I55*4/12)*VLOOKUP($B81,'Hypothèses '!$B$106:$E$126,3,FALSE)*(1+$E$35)*(1+$F$35)*(1+$G$35)*(1+$H$35)*(1+$I$35) -> 0 | J81: =(I55*8/12+J55*4/12)*VLOOKUP($B81,'Hypothèses '!$B$106:$E$126,3,FALSE)*(1+$E$35)*(1+$F$35)*(1+$G$35)*(1+$H$35)*(1+$I$35)*(1+$J$35) -> 0 | K81: =(J55*8/12+K55*4/12)*VLOOKUP($B81,'Hypothèses '!$B$106:$E$126,3,FALSE)*(1+$E$35)*(1+$F$35)*(1+$G$35)*(1+$H$35)*(1+$I$35)*(1+$J$35)*(1+$K$35) -> 0
B82: =B56 -> Documentation | D82: =(C56*8/12+D56*4/12)*VLOOKUP($B82,'Hypothèses '!$B$106:$E$126,3,FALSE) -> 0 | E82: =(D56*8/12+E56*4/12)*VLOOKUP($B82,'Hypothèses '!$B$106:$E$126,3,FALSE)*(1+$E$35) -> 0 | F82: =(E56*8/12+F56*4/12)*VLOOKUP($B82,'Hypothèses '!$B$106:$E$126,3,FALSE)*(1+$E$35)*(1+$F$35) -> 0 | G82: =(F56*8/12+G56*4/12)*VLOOKUP($B82,'Hypothèses '!$B$106:$E$126,3,FALSE)*(1+$E$35)*(1+$F$35)*(1+$G$35) -> 0 | H82: =(G56*8/12+H56*4/12)*VLOOKUP($B82,'Hypothèses '!$B$106:$E$126,3,FALSE)*(1+$E$35)*(1+$F$35)*(1+$G$35)*(1+$H$35) -> 0 | I82: =(H56*8/12+I56*4/12)*VLOOKUP($B82,'Hypothèses '!$B$106:$E$126,3,FALSE)*(1+$E$35)*(1+$F$35)*(1+$G$35)*(1+$H$35)*(1+$I$35) -> 0 | J82: =(I56*8/12+J56*4/12)*VLOOKUP($B82,'Hypothèses '!$B$106:$E$126,3,FALSE)*(1+$E$35)*(1+$F$35)*(1+$G$35)*(1+$H$35)*(1+$I$35)*(1+$J$35) -> 0 | K82: =(J56*8/12+K56*4/12)*VLOOKUP($B82,'Hypothèses '!$B$106:$E$126,3,FALSE)*(1+$E$35)*(1+$F$35)*(1+$G$35)*(1+$H$35)*(1+$I$35)*(1+$J$35)*(1+$K$35) -> 0
B83: =B57 -> Infirmière | D83: =(C57*8/12+D57*4/12)*VLOOKUP($B83,'Hypothèses '!$B$106:$E$126,3,FALSE) -> 0 | E83: =(D57*8/12+E57*4/12)*VLOOKUP($B83,'Hypothèses '!$B$106:$E$126,3,FALSE)*(1+$E$35) -> 0 | F83: =(E57*8/12+F57*4/12)*VLOOKUP($B83,'Hypothèses '!$B$106:$E$126,3,FALSE)*(1+$E$35)*(1+$F$35) -> 0 | G83: =(F57*8/12+G57*4/12)*VLOOKUP($B83,'Hypothèses '!$B$106:$E$126,3,FALSE)*(1+$E$35)*(1+$F$35)*(1+$G$35) -> 0 | H83: =(G57*8/12+H57*4/12)*VLOOKUP($B83,'Hypothèses '!$B$106:$E$126,3,FALSE)*(1+$E$35)*(1+$F$35)*(1+$G$35)*(1+$H$35) -> 0 | I83: =(H57*8/12+I57*4/12)*VLOOKUP($B83,'Hypothèses '!$B$106:$E$126,3,FALSE)*(1+$E$35)*(1+$F$35)*(1+$G$35)*(1+$H$35)*(1+$I$35) -> 0 | J83: =(I57*8/12+J57*4/12)*VLOOKUP($B83,'Hypothèses '!$B$106:$E$126,3,FALSE)*(1+$E$35)*(1+$F$35)*(1+$G$35)*(1+$H$35)*(1+$I$35)*(1+$J$35) -> 0 | K83: =(J57*8/12+K57*4/12)*VLOOKUP($B83,'Hypothèses '!$B$106:$E$126,3,FALSE)*(1+$E$35)*(1+$F$35)*(1+$G$35)*(1+$H$35)*(1+$I$35)*(1+$J$35)*(1+$K$35) -> 0
B84: =B58 -> Autre primaire commun | D84: =(C58*8/12+D58*4/12)*VLOOKUP($B84,'Hypothèses '!$B$106:$E$126,3,FALSE) -> 0 | E84: =(D58*8/12+E58*4/12)*VLOOKUP($B84,'Hypothèses '!$B$106:$E$126,3,FALSE)*(1+$E$35) -> 0 | F84: =(E58*8/12+F58*4/12)*VLOOKUP($B84,'Hypothèses '!$B$106:$E$126,3,FALSE)*(1+$E$35)*(1+$F$35) -> 0 | G84: =(F58*8/12+G58*4/12)*VLOOKUP($B84,'Hypothèses '!$B$106:$E$126,3,FALSE)*(1+$E$35)*(1+$F$35)*(1+$G$35) -> 0 | H84: =(G58*8/12+H58*4/12)*VLOOKUP($B84,'Hypothèses '!$B$106:$E$126,3,FALSE)*(1+$E$35)*(1+$F$35)*(1+$G$35)*(1+$H$35) -> 0 | I84: =(H58*8/12+I58*4/12)*VLOOKUP($B84,'Hypothèses '!$B$106:$E$126,3,FALSE)*(1+$E$35)*(1+$F$35)*(1+$G$35)*(1+$H$35)*(1+$I$35) -> 0 | J84: =(I58*8/12+J58*4/12)*VLOOKUP($B84,'Hypothèses '!$B$106:$E$126,3,FALSE)*(1+$E$35)*(1+$F$35)*(1+$G$35)*(1+$H$35)*(1+$I$35)*(1+$J$35) -> 0 | K84: =(J58*8/12+K58*4/12)*VLOOKUP($B84,'Hypothèses '!$B$106:$E$126,3,FALSE)*(1+$E$35)*(1+$F$35)*(1+$G$35)*(1+$H$35)*(1+$I$35)*(1+$J$35)*(1+$K$35) -> 0
A86: Personnels Enseignants et ASEM | B86: =B62 -> Enseignants Détachés | D86: =((C62*8/12+D62*4/12)*((('Calcul Cout Détaché'!$B$12*D$36+'Calcul Cout Détaché'!$G$11)*1)+'Calcul Cout Détaché'!$H$12))/D$37 -> 0 | E86: =((D62*8/12+E62*4/12)*((('Calcul Cout Détaché'!$B$12*E$36+'Calcul Cout Détaché'!$G$11)*1)+'Calcul Cout Détaché'!$H$12))/E$37 -> 0 | F86: =((E62*8/12+F62*4/12)*((('Calcul Cout Détaché'!$B$12*F$36+'Calcul Cout Détaché'!$G$11)*1)+'Calcul Cout Détaché'!$H$12))/F$37 -> 0 | G86: =((F62*8/12+G62*4/12)*((('Calcul Cout Détaché'!$B$12*G$36+'Calcul Cout Détaché'!$G$11)*1)+'Calcul Cout Détaché'!$H$12))/G$37 -> 0 | H86: =((G62*8/12+H62*4/12)*((('Calcul Cout Détaché'!$B$12*H$36+'Calcul Cout Détaché'!$G$11)*1)+'Calcul Cout Détaché'!$H$12))/H$37 -> 0 | I86: =((H62*8/12+I62*4/12)*((('Calcul Cout Détaché'!$B$12*I$36+'Calcul Cout Détaché'!$G$11)*1)+'Calcul Cout Détaché'!$H$12))/I$37 -> 0 | J86: =((I62*8/12+J62*4/12)*((('Calcul Cout Détaché'!$B$12*J$36+'Calcul Cout Détaché'!$G$11)*1)+'Calcul Cout Détaché'!$H$12))/J$37 -> 0 | K86: =((J62*8/12+K62*4/12)*((('Calcul Cout Détaché'!$B$12*K$36+'Calcul Cout Détaché'!$G$11)*1)+'Calcul Cout Détaché'!$H$12))/K$37 -> 0
B87: Enseignant PDL | D87: =((C63+C64)*8/12+(D64+D63)*4/12)*VLOOKUP($B87,'Hypothèses '!$B$106:$E$126,3,FALSE) -> 0 | E87: =((D63+D64)*8/12+(E64+E63)*4/12)*VLOOKUP($B87,'Hypothèses '!$B$106:$E$126,3,FALSE)*(1+$E$35) -> 0 | F87: =((E63+E64)*8/12+(F64+F63)*4/12)*VLOOKUP($B87,'Hypothèses '!$B$106:$E$126,3,FALSE)*(1+$E$35)*(1+$F$35) -> 0 | G87: =((F63+F64)*8/12+(G64+G63)*4/12)*VLOOKUP($B87,'Hypothèses '!$B$106:$E$126,3,FALSE)*(1+$E$35)*(1+$F$35)*(1+$G$35) -> 0 | H87: =((G63+G64)*8/12+(H64+H63)*4/12)*VLOOKUP($B87,'Hypothèses '!$B$106:$E$126,3,FALSE)*(1+$E$35)*(1+$F$35)*(1+$G$35)*(1+$H$35) -> 0 | I87: =((H63+H64)*8/12+(I64+I63)*4/12)*VLOOKUP($B87,'Hypothèses '!$B$106:$E$126,3,FALSE)*(1+$E$35)*(1+$F$35)*(1+$G$35)*(1+$H$35)*(1+$I$35) -> 0 | J87: =((I63+I64)*8/12+(J64+J63)*4/12)*VLOOKUP($B87,'Hypothèses '!$B$106:$E$126,3,FALSE)*(1+$E$35)*(1+$F$35)*(1+$G$35)*(1+$H$35)*(1+$I$35)*(1+$J$35) -> 0 | K87: =((J63+J64)*8/12+(K64+K63)*4/12)*VLOOKUP($B87,'Hypothèses '!$B$106:$E$126,3,FALSE)*(1+$E$35)*(1+$F$35)*(1+$G$35)*(1+$H$35)*(1+$I$35)*(1+$J$35)*(1+$K$35) -> 0
B88: =B65 -> ASEM | D88: =(C65*8/12+D65*4/12)*VLOOKUP($B88,'Hypothèses '!$B$106:$E$126,3,FALSE) -> 0 | E88: =(D65*8/12+E65*4/12)*VLOOKUP($B88,'Hypothèses '!$B$106:$E$126,3,FALSE)*(1+$E$35) -> 0 | F88: =(E65*8/12+F65*4/12)*VLOOKUP($B88,'Hypothèses '!$B$106:$E$126,3,FALSE)*(1+$E$35)*(1+$F$35) -> 0 | G88: =(F65*8/12+G65*4/12)*VLOOKUP($B88,'Hypothèses '!$B$106:$E$126,3,FALSE)*(1+$E$35)*(1+$F$35)*(1+$G$35) -> 0 | H88: =(G65*8/12+H65*4/12)*VLOOKUP($B88,'Hypothèses '!$B$106:$E$126,3,FALSE)*(1+$E$35)*(1+$F$35)*(1+$G$35)*(1+$H$35) -> 0 | I88: =(H65*8/12+I65*4/12)*VLOOKUP($B88,'Hypothèses '!$B$106:$E$126,3,FALSE)*(1+$E$35)*(1+$F$35)*(1+$G$35)*(1+$H$35)*(1+$I$35) -> 0 | J88: =(I65*8/12+J65*4/12)*VLOOKUP($B88,'Hypothèses '!$B$106:$E$126,3,FALSE)*(1+$E$35)*(1+$F$35)*(1+$G$35)*(1+$H$35)*(1+$I$35)*(1+$J$35) -> 0 | K88: =(J65*8/12+K65*4/12)*VLOOKUP($B88,'Hypothèses '!$B$106:$E$126,3,FALSE)*(1+$E$35)*(1+$F$35)*(1+$G$35)*(1+$H$35)*(1+$I$35)*(1+$J$35)*(1+$K$35) -> 0
A90: ELEMENTAIRE | C90: =C$4 -> 2023/2024 | D90: =D$4 -> 2024/2025 | E90: =E$4 -> 2025/2026 | F90: =F$4 -> 2026/2027 | G90: =G$4 -> 2027/2028 | H90: =H$4 -> 2028/2029 | I90: =I$4 -> 2029/2030 | J90: =J$4 -> 2030/2031 | K90: =K$4 -> 2031/2032
A91: Personnel total | C91: =C92+C112 -> #N/A | D91: =D92+D112 -> #N/A | E91: =E92+E112 -> #N/A | F91: =F92+F112 -> #N/A | G91: =G92+G112 -> #N/A | H91: =H92+H112 -> #N/A | I91: =I92+I112 -> #N/A | J91: =J92+J112 -> #N/A | K91: =K92+K112 -> #N/A
A92: Personnels non enseignants - Proratisation par niveau | C92: =SUM(C94:C101)+SUM(C104:C110) -> #N/A | D92: =SUM(D94:D101)+SUM(D104:D110) -> #N/A | E92: =SUM(E94:E101)+SUM(E104:E110) -> #N/A | F92: =SUM(F94:F101)+SUM(F104:F110) -> #N/A | G92: =SUM(G94:G101)+SUM(G104:G110) -> #N/A | H92: =SUM(H94:H101)+SUM(H104:H110) -> #N/A | I92: =SUM(I94:I101)+SUM(I104:I110) -> #N/A | J92: =SUM(J94:J101)+SUM(J104:J110) -> #N/A | K92: =SUM(K94:K101)+SUM(K104:K110) -> #N/A
A93: Communs | B93: Clé répartition | C93: =HLOOKUP(C38,'Projection Effectifs'!$S$31:$AC$35,3,FALSE) -> 0 | D93: =HLOOKUP(D38,'Projection Effectifs'!$S$31:$AC$35,3,FALSE) -> 0.36247216 | E93: =HLOOKUP(E38,'Projection Effectifs'!$S$31:$AC$35,3,FALSE) -> 0.35726027 | F93: =HLOOKUP(F38,'Projection Effectifs'!$S$31:$AC$35,3,FALSE) -> 0.36788732 | G93: =HLOOKUP(G38,'Projection Effectifs'!$S$31:$AC$35,3,FALSE) -> 0.34932709 | H93: =HLOOKUP(H38,'Projection Effectifs'!$S$31:$AC$35,3,FALSE) -> 0.3119482 | I93: =HLOOKUP(I38,'Projection Effectifs'!$S$31:$AC$35,3,FALSE) -> 0.27315358 | J93: =HLOOKUP(J38,'Projection Effectifs'!$S$31:$AC$35,3,FALSE) -> 0.23058824 | K93: =HLOOKUP(K38,'Projection Effectifs'!$S$31:$AC$35,3,FALSE) -> 0.22778772
B94: =$B$6 -> Chef d'Etablissement PDL | C94: =VLOOKUP($B94,$B$6:$K$13,C$3,FALSE)*C$93 -> #N/A | D94: =VLOOKUP($B94,$B$6:$K$13,D$3,FALSE)*D$93 -> #N/A | E94: =VLOOKUP($B94,$B$6:$K$13,E$3,FALSE)*E$93 -> #N/A | F94: =VLOOKUP($B94,$B$6:$K$13,F$3,FALSE)*F$93 -> #N/A | G94: =VLOOKUP($B94,$B$6:$K$13,G$3,FALSE)*G$93 -> #N/A | H94: =VLOOKUP($B94,$B$6:$K$13,H$3,FALSE)*H$93 -> #N/A | I94: =VLOOKUP($B94,$B$6:$K$13,I$3,FALSE)*I$93 -> #N/A | J94: =VLOOKUP($B94,$B$6:$K$13,J$3,FALSE)*J$93 -> #N/A | K94: =VLOOKUP($B94,$B$6:$K$13,K$3,FALSE)*K$93 -> #N/A
B95: =$B$7 -> DAF PDL | C95: =VLOOKUP($B95,$B$6:$K$13,C$3,FALSE)*C$93 -> #N/A | D95: =VLOOKUP($B95,$B$6:$K$13,D$3,FALSE)*D$93 -> #N/A | E95: =VLOOKUP($B95,$B$6:$K$13,E$3,FALSE)*E$93 -> #N/A | F95: =VLOOKUP($B95,$B$6:$K$13,F$3,FALSE)*F$93 -> #N/A | G95: =VLOOKUP($B95,$B$6:$K$13,G$3,FALSE)*G$93 -> #N/A | H95: =VLOOKUP($B95,$B$6:$K$13,H$3,FALSE)*H$93 -> #N/A | I95: =VLOOKUP($B95,$B$6:$K$13,I$3,FALSE)*I$93 -> #N/A | J95: =VLOOKUP($B95,$B$6:$K$13,J$3,FALSE)*J$93 -> #N/A | K95: =VLOOKUP($B95,$B$6:$K$13,K$3,FALSE)*K$93 -> #N/A
B96: =$B$8 -> DRH | C96: =VLOOKUP($B96,$B$6:$K$13,C$3,FALSE)*C$93 -> 0 | D96: =VLOOKUP($B96,$B$6:$K$13,D$3,FALSE)*D$93 -> 0.72494432 | E96: =VLOOKUP($B96,$B$6:$K$13,E$3,FALSE)*E$93 -> 0 | F96: =VLOOKUP($B96,$B$6:$K$13,F$3,FALSE)*F$93 -> 0 | G96: =VLOOKUP($B96,$B$6:$K$13,G$3,FALSE)*G$93 -> 0 | H96: =VLOOKUP($B96,$B$6:$K$13,H$3,FALSE)*H$93 -> 0 | I96: =VLOOKUP($B96,$B$6:$K$13,I$3,FALSE)*I$93 -> 0 | J96: =VLOOKUP($B96,$B$6:$K$13,J$3,FALSE)*J$93 -> 0 | K96: =VLOOKUP($B96,$B$6:$K$13,K$3,FALSE)*K$93 -> 0
B97: =$B$9 -> Autre Administratif | C97: =VLOOKUP($B97,$B$6:$K$13,C$3,FALSE)*C$93 -> 0 | D97: =VLOOKUP($B97,$B$6:$K$13,D$3,FALSE)*D$93 -> 0 | E97: =VLOOKUP($B97,$B$6:$K$13,E$3,FALSE)*E$93 -> 0 | F97: =VLOOKUP($B97,$B$6:$K$13,F$3,FALSE)*F$93 -> 0 | G97: =VLOOKUP($B97,$B$6:$K$13,G$3,FALSE)*G$93 -> 0 | H97: =VLOOKUP($B97,$B$6:$K$13,H$3,FALSE)*H$93 -> 0 | I97: =VLOOKUP($B97,$B$6:$K$13,I$3,FALSE)*I$93 -> 0 | J97: =VLOOKUP($B97,$B$6:$K$13,J$3,FALSE)*J$93 -> 0 | K97: =VLOOKUP($B97,$B$6:$K$13,K$3,FALSE)*K$93 -> 0
B98: =$B$10 -> Technique - Informatique - Maintenance | C98: =VLOOKUP($B98,$B$6:$K$13,C$3,FALSE)*C$93 -> #N/A | D98: =VLOOKUP($B98,$B$6:$K$13,D$3,FALSE)*D$93 -> #N/A | E98: =VLOOKUP($B98,$B$6:$K$13,E$3,FALSE)*E$93 -> #N/A | F98: =VLOOKUP($B98,$B$6:$K$13,F$3,FALSE)*F$93 -> #N/A | G98: =VLOOKUP($B98,$B$6:$K$13,G$3,FALSE)*G$93 -> #N/A | H98: =VLOOKUP($B98,$B$6:$K$13,H$3,FALSE)*H$93 -> #N/A | I98: =VLOOKUP($B98,$B$6:$K$13,I$3,FALSE)*I$93 -> #N/A | J98: =VLOOKUP($B98,$B$6:$K$13,J$3,FALSE)*J$93 -> #N/A | K98: =VLOOKUP($B98,$B$6:$K$13,K$3,FALSE)*K$93 -> #N/A
B99: =$B$11 -> Entretien / Sécurité | C99: =VLOOKUP($B99,$B$6:$K$13,C$3,FALSE)*C$93 -> 0 | D99: =VLOOKUP($B99,$B$6:$K$13,D$3,FALSE)*D$93 -> 0.36247216 | E99: =VLOOKUP($B99,$B$6:$K$13,E$3,FALSE)*E$93 -> 0 | F99: =VLOOKUP($B99,$B$6:$K$13,F$3,FALSE)*F$93 -> 0 | G99: =VLOOKUP($B99,$B$6:$K$13,G$3,FALSE)*G$93 -> 0 | H99: =VLOOKUP($B99,$B$6:$K$13,H$3,FALSE)*H$93 -> 0 | I99: =VLOOKUP($B99,$B$6:$K$13,I$3,FALSE)*I$93 -> 0 | J99: =VLOOKUP($B99,$B$6:$K$13,J$3,FALSE)*J$93 -> 0 | K99: =VLOOKUP($B99,$B$6:$K$13,K$3,FALSE)*K$93 -> 0
B100: =$B$12 -> Documentation | C100: =VLOOKUP($B100,$B$6:$K$13,C$3,FALSE)*C$93 -> 0 | D100: =VLOOKUP($B100,$B$6:$K$13,D$3,FALSE)*D$93 -> 0.72494432 | E100: =VLOOKUP($B100,$B$6:$K$13,E$3,FALSE)*E$93 -> 0 | F100: =VLOOKUP($B100,$B$6:$K$13,F$3,FALSE)*F$93 -> 0 | G100: =VLOOKUP($B100,$B$6:$K$13,G$3,FALSE)*G$93 -> 0 | H100: =VLOOKUP($B100,$B$6:$K$13,H$3,FALSE)*H$93 -> 0 | I100: =VLOOKUP($B100,$B$6:$K$13,I$3,FALSE)*I$93 -> 0 | J100: =VLOOKUP($B100,$B$6:$K$13,J$3,FALSE)*J$93 -> 0 | K100: =VLOOKUP($B100,$B$6:$K$13,K$3,FALSE)*K$93 -> 0
B101: =$B$13 -> Autre commun | C101: =VLOOKUP($B101,$B$6:$K$13,C$3,FALSE)*C$93 -> 0 | D101: =VLOOKUP($B101,$B$6:$K$13,D$3,FALSE)*D$93 -> 0 | E101: =VLOOKUP($B101,$B$6:$K$13,E$3,FALSE)*E$93 -> 0 | F101: =VLOOKUP($B101,$B$6:$K$13,F$3,FALSE)*F$93 -> 0 | G101: =VLOOKUP($B101,$B$6:$K$13,G$3,FALSE)*G$93 -> 0 | H101: =VLOOKUP($B101,$B$6:$K$13,H$3,FALSE)*H$93 -> 0 | I101: =VLOOKUP($B101,$B$6:$K$13,I$3,FALSE)*I$93 -> 0 | J101: =VLOOKUP($B101,$B$6:$K$13,J$3,FALSE)*J$93 -> 0 | K101: =VLOOKUP($B101,$B$6:$K$13,K$3,FALSE)*K$93 -> 0
A103: Communs Primaire | B103: Clé répartition | C103: =HLOOKUP(C$38,'Projection Effectifs'!$S$37:$AC$43,3,FALSE) -> 0 | D103: =HLOOKUP(D$38,'Projection Effectifs'!$S$37:$AC$43,3,FALSE) -> 0.68961864 | E103: =HLOOKUP(E$38,'Projection Effectifs'!$S$37:$AC$43,3,FALSE) -> 0.70562771 | F103: =HLOOKUP(F$38,'Projection Effectifs'!$S$37:$AC$43,3,FALSE) -> 0.76374269 | G103: =HLOOKUP(G$38,'Projection Effectifs'!$S$37:$AC$43,3,FALSE) -> 0.75857687 | H103: =HLOOKUP(H$38,'Projection Effectifs'!$S$37:$AC$43,3,FALSE) -> 0.68831169 | I103: =HLOOKUP(I$38,'Projection Effectifs'!$S$37:$AC$43,3,FALSE) -> 0.60835509 | J103: =HLOOKUP(J$38,'Projection Effectifs'!$S$37:$AC$43,3,FALSE) -> 0.5212766 | K103: =HLOOKUP(K$38,'Projection Effectifs'!$S$37:$AC$43,3,FALSE) -> 0.5148248
B104: =$B$16 -> Direction PDL | C104: =VLOOKUP($B104,$B$16:$K$22,C$3,FALSE)*C$103 -> #N/A | D104: =VLOOKUP($B104,$B$16:$K$22,D$3,FALSE)*D$103 -> #N/A | E104: =VLOOKUP($B104,$B$16:$K$22,E$3,FALSE)*E$103 -> #N/A | F104: =VLOOKUP($B104,$B$16:$K$22,F$3,FALSE)*F$103 -> #N/A | G104: =VLOOKUP($B104,$B$16:$K$22,G$3,FALSE)*G$103 -> #N/A | H104: =VLOOKUP($B104,$B$16:$K$22,H$3,FALSE)*H$103 -> #N/A | I104: =VLOOKUP($B104,$B$16:$K$22,I$3,FALSE)*I$103 -> #N/A | J104: =VLOOKUP($B104,$B$16:$K$22,J$3,FALSE)*J$103 -> #N/A | K104: =VLOOKUP($B104,$B$16:$K$22,K$3,FALSE)*K$103 -> #N/A
B105: =$B$17 -> Direction adjointe | C105: =VLOOKUP($B105,$B$16:$K$22,C$3,FALSE)*C$103 -> 0 | D105: =VLOOKUP($B105,$B$16:$K$22,D$3,FALSE)*D$103 -> 0 | E105: =VLOOKUP($B105,$B$16:$K$22,E$3,FALSE)*E$103 -> 0 | F105: =VLOOKUP($B105,$B$16:$K$22,F$3,FALSE)*F$103 -> 0 | G105: =VLOOKUP($B105,$B$16:$K$22,G$3,FALSE)*G$103 -> 0 | H105: =VLOOKUP($B105,$B$16:$K$22,H$3,FALSE)*H$103 -> 0 | I105: =VLOOKUP($B105,$B$16:$K$22,I$3,FALSE)*I$103 -> 0 | J105: =VLOOKUP($B105,$B$16:$K$22,J$3,FALSE)*J$103 -> 0 | K105: =VLOOKUP($B105,$B$16:$K$22,K$3,FALSE)*K$103 -> 0
B106: =$B$18 -> Conseiller pédagogique | C106: =VLOOKUP($B106,$B$16:$K$22,C$3,FALSE)*C$103 -> 0 | D106: =VLOOKUP($B106,$B$16:$K$22,D$3,FALSE)*D$103 -> 0 | E106: =VLOOKUP($B106,$B$16:$K$22,E$3,FALSE)*E$103 -> 0 | F106: =VLOOKUP($B106,$B$16:$K$22,F$3,FALSE)*F$103 -> 0 | G106: =VLOOKUP($B106,$B$16:$K$22,G$3,FALSE)*G$103 -> 0 | H106: =VLOOKUP($B106,$B$16:$K$22,H$3,FALSE)*H$103 -> 0 | I106: =VLOOKUP($B106,$B$16:$K$22,I$3,FALSE)*I$103 -> 0 | J106: =VLOOKUP($B106,$B$16:$K$22,J$3,FALSE)*J$103 -> 0 | K106: =VLOOKUP($B106,$B$16:$K$22,K$3,FALSE)*K$103 -> 0
B107: =$B$19 -> Vie scolaire - Educateurs | C107: =VLOOKUP($B107,$B$16:$K$22,C$3,FALSE)*C$103 -> 0 | D107: =VLOOKUP($B107,$B$16:$K$22,D$3,FALSE)*D$103 -> 0.68961864 | E107: =VLOOKUP($B107,$B$16:$K$22,E$3,FALSE)*E$103 -> 0 | F107: =VLOOKUP($B107,$B$16:$K$22,F$3,FALSE)*F$103 -> 0 | G107: =VLOOKUP($B107,$B$16:$K$22,G$3,FALSE)*G$103 -> 0 | H107: =VLOOKUP($B107,$B$16:$K$22,H$3,FALSE)*H$103 -> 0 | I107: =VLOOKUP($B107,$B$16:$K$22,I$3,FALSE)*I$103 -> 0 | J107: =VLOOKUP($B107,$B$16:$K$22,J$3,FALSE)*J$103 -> 0 | K107: =VLOOKUP($B107,$B$16:$K$22,K$3,FALSE)*K$103 -> 0
B108: =$B$20 -> Documentation | C108: =VLOOKUP($B108,$B$16:$K$22,C$3,FALSE)*C$103 -> 0 | D108: =VLOOKUP($B108,$B$16:$K$22,D$3,FALSE)*D$103 -> 0.68961864 | E108: =VLOOKUP($B108,$B$16:$K$22,E$3,FALSE)*E$103 -> 0 | F108: =VLOOKUP($B108,$B$16:$K$22,F$3,FALSE)*F$103 -> 0 | G108: =VLOOKUP($B108,$B$16:$K$22,G$3,FALSE)*G$103 -> 0 | H108: =VLOOKUP($B108,$B$16:$K$22,H$3,FALSE)*H$103 -> 0 | I108: =VLOOKUP($B108,$B$16:$K$22,I$3,FALSE)*I$103 -> 0 | J108: =VLOOKUP($B108,$B$16:$K$22,J$3,FALSE)*J$103 -> 0 | K108: =VLOOKUP($B108,$B$16:$K$22,K$3,FALSE)*K$103 -> 0
B109: =$B$21 -> Infirmière | C109: =VLOOKUP($B109,$B$16:$K$22,C$3,FALSE)*C$103 -> 0 | D109: =VLOOKUP($B109,$B$16:$K$22,D$3,FALSE)*D$103 -> 0 | E109: =VLOOKUP($B109,$B$16:$K$22,E$3,FALSE)*E$103 -> 0 | F109: =VLOOKUP($B109,$B$16:$K$22,F$3,FALSE)*F$103 -> 0 | G109: =VLOOKUP($B109,$B$16:$K$22,G$3,FALSE)*G$103 -> 0 | H109: =VLOOKUP($B109,$B$16:$K$22,H$3,FALSE)*H$103 -> 0 | I109: =VLOOKUP($B109,$B$16:$K$22,I$3,FALSE)*I$103 -> 0 | J109: =VLOOKUP($B109,$B$16:$K$22,J$3,FALSE)*J$103 -> 0 | K109: =VLOOKUP($B109,$B$16:$K$22,K$3,FALSE)*K$103 -> 0
B110: =$B$22 -> Autre primaire commun | C110: =VLOOKUP($B110,$B$16:$K$22,C$3,FALSE)*C$103 -> 0 | D110: =VLOOKUP($B110,$B$16:$K$22,D$3,FALSE)*D$103 -> 1.3792373 | E110: =VLOOKUP($B110,$B$16:$K$22,E$3,FALSE)*E$103 -> 0 | F110: =VLOOKUP($B110,$B$16:$K$22,F$3,FALSE)*F$103 -> 0 | G110: =VLOOKUP($B110,$B$16:$K$22,G$3,FALSE)*G$103 -> 0 | H110: =VLOOKUP($B110,$B$16:$K$22,H$3,FALSE)*H$103 -> 0 | I110: =VLOOKUP($B110,$B$16:$K$22,I$3,FALSE)*I$103 -> 0 | J110: =VLOOKUP($B110,$B$16:$K$22,J$3,FALSE)*J$103 -> 0 | K110: =VLOOKUP($B110,$B$16:$K$22,K$3,FALSE)*K$103 -> 0
...

Sheet Compte Résultat ML
A2: COMPTE DE RESULTAT PREVISIONNEL
A3: Monnaie Locale
C4: ='Hypothèses '!$C$9 -> 2024 | D4: =C4+1 -> 2025 | E4: =D4+1 -> 2026 | F4: =E4+1 -> 2027 | G4: =F4+1 -> 2028 | H4: =G4+1 -> 2029 | I4: =H4+1 -> 2030 | J4: =I4+1 -> 2031
A5: RESULTAT OPERATIONNEL
A6: GLOBAL | C6: =C15-C60 -> #N/A | D6: =D15-D60 -> #N/A | E6: =E15-E60 -> #N/A | F6: =F15-F60 -> #N/A | G6: =G15-G60 -> #N/A | H6: =H15-H60 -> #N/A | I6: =I15-I60 -> #N/A | J6: =J15-J60 -> #N/A
A7: MATERNELLE | C7: =C24-C84 -> #N/A | D7: =D24-D84 -> #N/A | E7: =E24-E84 -> #N/A | F7: =F24-F84 -> #N/A | G7: =G24-G84 -> #N/A | H7: =H24-H84 -> #N/A | I7: =I24-I84 -> #N/A | J7: =J24-J84 -> #N/A
A8: ELEMENTAIRE | C8: =C32-C110 -> #N/A | D8: =D32-D110 -> #N/A | E8: =E32-E110 -> #N/A | F8: =F32-F110 -> #N/A | G8: =G32-G110 -> #N/A | H8: =H32-H110 -> #N/A | I8: =I32-I110 -> #N/A | J8: =J32-J110 -> #N/A
A9: COLLEGE | C9: =C40-C136 -> #N/A | D9: =D40-D136 -> #N/A | E9: =E40-E136 -> #N/A | F9: =F40-F136 -> #N/A | G9: =G40-G136 -> #N/A | H9: =H40-H136 -> #N/A | I9: =I40-I136 -> #N/A | J9: =J40-J136 -> #N/A
A10: LYCEE | C10: =C48-C162 -> #N/A | D10: =D48-D162 -> #N/A | E10: =E48-E162 -> #N/A | F10: =F48-F162 -> #N/A | G10: =G48-G162 -> #N/A | H10: =H48-H162 -> #N/A | I10: =I48-I162 -> #N/A | J10: =J48-J162 -> #N/A
A13: PRODUITS | C13: ='Hypothèses '!$C$9 -> 2024 | D13: =C13+1 -> 2025 | E13: =D13+1 -> 2026 | F13: =E13+1 -> 2027 | G13: =F13+1 -> 2028 | H13: =G13+1 -> 2029 | I13: =H13+1 -> 2030 | J13: =I13+1 -> 2031
A14: produits liés à la scolarité, hors services de restauration, de transport, d'activités extra scolaires et d'examen
A15: GLOBAL | C15: =SUM(C20:C23) -> 0 | D15: =SUM(D20:D23) -> 0 | E15: =SUM(E20:E23) -> 205625000 | F15: =SUM(F20:F23) -> 198515000 | G15: =SUM(G20:G23) -> 195685000 | H15: =SUM(H20:H23) -> 195980000 | I15: =SUM(I20:I23) -> 195680000 | J15: =SUM(J20:J23) -> 193545000
B16: taux nouveaux inscrits | C16: =HLOOKUP(VLOOKUP(C$13,'table années scolaires'!$C$17:$E$27,2,FALSE),'Hypothèses '!$C$19:$K$29,10,FALSE) -> 0 | D16: =HLOOKUP(VLOOKUP(D$13,'table années scolaires'!$C$17:$E$27,2,FALSE),'Hypothèses '!$C$19:$K$29,10,FALSE) -> 0.1 | E16: =HLOOKUP(VLOOKUP(E$13,'table années scolaires'!$C$17:$E$27,2,FALSE),'Hypothèses '!$C$19:$K$29,10,FALSE) -> 0.1 | F16: =HLOOKUP(VLOOKUP(F$13,'table années scolaires'!$C$17:$E$27,2,FALSE),'Hypothèses '!$C$19:$K$29,10,FALSE) -> 0.1 | G16: =HLOOKUP(VLOOKUP(G$13,'table années scolaires'!$C$17:$E$27,2,FALSE),'Hypothèses '!$C$19:$K$29,10,FALSE) -> 0.1 | H16: =HLOOKUP(VLOOKUP(H$13,'table années scolaires'!$C$17:$E$27,2,FALSE),'Hypothèses '!$C$19:$K$29,10,FALSE) -> 0.1 | I16: =HLOOKUP(VLOOKUP(I$13,'table années scolaires'!$C$17:$E$27,2,FALSE),'Hypothèses '!$C$19:$K$29,10,FALSE) -> 0.1 | J16: =HLOOKUP(VLOOKUP(J$13,'table années scolaires'!$C$17:$E$27,2,FALSE),'Hypothèses '!$C$19:$K$29,10,FALSE) -> 0.1
B17: Taus abattement | C17: =HLOOKUP(VLOOKUP(C$13,'table années scolaires'!$C$17:$E$27,2,FALSE),'Hypothèses '!$C$19:$K$29,11,FALSE) -> 0 | D17: =HLOOKUP(VLOOKUP(D$13,'table années scolaires'!$C$17:$E$27,2,FALSE),'Hypothèses '!$C$19:$K$29,11,FALSE) -> 0.06 | E17: =HLOOKUP(VLOOKUP(E$13,'table années scolaires'!$C$17:$E$27,2,FALSE),'Hypothèses '!$C$19:$K$29,11,FALSE) -> 0.06 | F17: =HLOOKUP(VLOOKUP(F$13,'table années scolaires'!$C$17:$E$27,2,FALSE),'Hypothèses '!$C$19:$K$29,11,FALSE) -> 0.06 | G17: =HLOOKUP(VLOOKUP(G$13,'table années scolaires'!$C$17:$E$27,2,FALSE),'Hypothèses '!$C$19:$K$29,11,FALSE) -> 0.06 | H17: =HLOOKUP(VLOOKUP(H$13,'table années scolaires'!$C$17:$E$27,2,FALSE),'Hypothèses '!$C$19:$K$29,11,FALSE) -> 0.06 | I17: =HLOOKUP(VLOOKUP(I$13,'table années scolaires'!$C$17:$E$27,2,FALSE),'Hypothèses '!$C$19:$K$29,11,FALSE) -> 0.06 | J17: =HLOOKUP(VLOOKUP(J$13,'table années scolaires'!$C$17:$E$27,2,FALSE),'Hypothèses '!$C$19:$K$29,11,FALSE) -> 0.06
B18: DPI | C18: =HLOOKUP(VLOOKUP(C$13,'table années scolaires'!$C$17:$E$27,2,FALSE),'Hypothèses '!$C$19:$K$26,3,FALSE) -> 0 | D18: =HLOOKUP(VLOOKUP(D$13,'table années scolaires'!$C$17:$E$27,2,FALSE),'Hypothèses '!$C$19:$K$26,3,FALSE) -> 0 | E18: =HLOOKUP(VLOOKUP(E$13,'table années scolaires'!$C$17:$E$27,2,FALSE),'Hypothèses '!$C$19:$K$26,3,FALSE) -> 500000 | F18: =HLOOKUP(VLOOKUP(F$13,'table années scolaires'!$C$17:$E$27,2,FALSE),'Hypothèses '!$C$19:$K$26,3,FALSE) -> 500000 | G18: =HLOOKUP(VLOOKUP(G$13,'table années scolaires'!$C$17:$E$27,2,FALSE),'Hypothèses '!$C$19:$K$26,3,FALSE) -> 500000 | H18: =HLOOKUP(VLOOKUP(H$13,'table années scolaires'!$C$17:$E$27,2,FALSE),'Hypothèses '!$C$19:$K$26,3,FALSE) -> 500000 | I18: =HLOOKUP(VLOOKUP(I$13,'table années scolaires'!$C$17:$E$27,2,FALSE),'Hypothèses '!$C$19:$K$26,3,FALSE) -> 500000 | J18: =HLOOKUP(VLOOKUP(J$13,'table années scolaires'!$C$17:$E$27,2,FALSE),'Hypothèses '!$C$19:$K$26,3,FALSE) -> 500000
B19: Frais Réinscption | C19: =HLOOKUP(VLOOKUP(C$13,'table années scolaires'!$C$17:$E$27,2,FALSE),'Hypothèses '!$C$19:$K$26,2,FALSE) -> 0 | D19: =HLOOKUP(VLOOKUP(D$13,'table années scolaires'!$C$17:$E$27,2,FALSE),'Hypothèses '!$C$19:$K$26,2,FALSE) -> 0 | E19: =HLOOKUP(VLOOKUP(E$13,'table années scolaires'!$C$17:$E$27,2,FALSE),'Hypothèses '!$C$19:$K$26,2,FALSE) -> 65000 | F19: =HLOOKUP(VLOOKUP(F$13,'table années scolaires'!$C$17:$E$27,2,FALSE),'Hypothèses '!$C$19:$K$26,2,FALSE) -> 65000 | G19: =HLOOKUP(VLOOKUP(G$13,'table années scolaires'!$C$17:$E$27,2,FALSE),'Hypothèses '!$C$19:$K$26,2,FALSE) -> 65000 | H19: =HLOOKUP(VLOOKUP(H$13,'table années scolaires'!$C$17:$E$27,2,FALSE),'Hypothèses '!$C$19:$K$26,2,FALSE) -> 65000 | I19: =HLOOKUP(VLOOKUP(I$13,'table années scolaires'!$C$17:$E$27,2,FALSE),'Hypothèses '!$C$19:$K$26,2,FALSE) -> 65000 | J19: =HLOOKUP(VLOOKUP(J$13,'table années scolaires'!$C$17:$E$27,2,FALSE),'Hypothèses '!$C$19:$K$26,2,FALSE) -> 65000
B20: Frais scolarité | C20: =C29+C37+C45+C53 -> 0 | D20: =D29+D37+D45+D53 -> 0 | E20: =E29+E37+E45+E53 -> 0 | F20: =F29+F37+F45+F53 -> 0 | G20: =G29+G37+G45+G53 -> 0 | H20: =H29+H37+H45+H53 -> 0 | I20: =I29+I37+I45+I53 -> 0 | J20: =J29+J37+J45+J53 -> 0
B21: DPI | C21: =C30+C38+C46+C54 -> 0 | D21: =D30+D38+D46+D54 -> 0 | E21: =E30+E38+E46+E54 -> 90250000 | F21: =F30+F38+F46+F54 -> 87430000 | G21: =G30+G38+G46+G54 -> 85250000 | H21: =H30+H38+H46+H54 -> 85090000 | I21: =I30+I38+I46+I54 -> 85180000 | J21: =J30+J38+J46+J54 -> 84540000
B22: Frais Réinscription | C22: =C31+C39+C47+C55 -> 0 | D22: =D31+D39+D47+D55 -> 0 | E22: =E31+E39+E47+E55 -> 115375000 | F22: =F31+F39+F47+F55 -> 111085000 | G22: =G31+G39+G47+G55 -> 110435000 | H22: =H31+H39+H47+H55 -> 110890000 | I22: =I31+I39+I47+I55 -> 110500000 | J22: =J31+J39+J47+J55 -> 109005000
B23: Subvention spécifique (hors AEFE) | C23: =HLOOKUP(C13,'Hypothèses '!$D$148:$K$149,2,FALSE) -> 0 | D23: =HLOOKUP(D13,'Hypothèses '!$D$148:$K$149,2,FALSE) -> 0 | E23: =HLOOKUP(E13,'Hypothèses '!$D$148:$K$149,2,FALSE) -> 0 | F23: =HLOOKUP(F13,'Hypothèses '!$D$148:$K$149,2,FALSE) -> 0 | G23: =HLOOKUP(G13,'Hypothèses '!$D$148:$K$149,2,FALSE) -> 0 | H23: =HLOOKUP(H13,'Hypothèses '!$D$148:$K$149,2,FALSE) -> 0 | I23: =HLOOKUP(I13,'Hypothèses '!$D$148:$K$149,2,FALSE) -> 0 | J23: =HLOOKUP(J13,'Hypothèses '!$D$148:$K$149,2,FALSE) -> 0
A24: MATERNELLE | C24: =SUM(C29:C31) -> 0 | D24: =SUM(D29:D31) -> 0 | E24: =SUM(E29:E31) -> 25330000 | F24: =SUM(F29:F31) -> 22210000 | G24: =SUM(G29:G31) -> 26100000 | H24: =SUM(H29:H31) -> 32700000 | I24: =SUM(I29:I31) -> 39600000 | J24: =SUM(J29:J31) -> 41400000
B25: Effectifs AS N-1 | C25: =HLOOKUP(VLOOKUP(C$13,'table années scolaires'!$C$17:$E$27,2,FALSE),'Projection Effectifs'!$C$31:$M$36,2,FALSE) -> 0 | D25: =HLOOKUP(VLOOKUP(D$13,'table années scolaires'!$C$17:$E$27,2,FALSE),'Projection Effectifs'!$C$31:$M$36,2,FALSE) -> 293 | E25: =HLOOKUP(VLOOKUP(E$13,'table années scolaires'!$C$17:$E$27,2,FALSE),'Projection Effectifs'!$C$31:$M$36,2,FALSE) -> 272 | F25: =HLOOKUP(VLOOKUP(F$13,'table années scolaires'!$C$17:$E$27,2,FALSE),'Projection Effectifs'!$C$31:$M$36,2,FALSE) -> 202 | G25: =HLOOKUP(VLOOKUP(G$13,'table années scolaires'!$C$17:$E$27,2,FALSE),'Projection Effectifs'!$C$31:$M$36,2,FALSE) -> 190 | H25: =HLOOKUP(VLOOKUP(H$13,'table années scolaires'!$C$17:$E$27,2,FALSE),'Projection Effectifs'!$C$31:$M$36,2,FALSE) -> 240 | I25: =HLOOKUP(VLOOKUP(I$13,'table années scolaires'!$C$17:$E$27,2,FALSE),'Projection Effectifs'!$C$31:$M$36,2,FALSE) -> 300 | J25: =HLOOKUP(VLOOKUP(J$13,'table années scolaires'!$C$17:$E$27,2,FALSE),'Projection Effectifs'!$C$31:$M$36,2,FALSE) -> 360
B26: Effectifs AS N | C26: =HLOOKUP(VLOOKUP(C$13,'table années scolaires'!$C$17:$E$27,3,FALSE),'Projection Effectifs'!$C$31:$M$36,2,FALSE) -> 293 | D26: =HLOOKUP(VLOOKUP(D$13,'table années scolaires'!$C$17:$E$27,3,FALSE),'Projection Effectifs'!$C$31:$M$36,2,FALSE) -> 272 | E26: =HLOOKUP(VLOOKUP(E$13,'table années scolaires'!$C$17:$E$27,3,FALSE),'Projection Effectifs'!$C$31:$M$36,2,FALSE) -> 202 | F26: =HLOOKUP(VLOOKUP(F$13,'table années scolaires'!$C$17:$E$27,3,FALSE),'Projection Effectifs'!$C$31:$M$36,2,FALSE) -> 190 | G26: =HLOOKUP(VLOOKUP(G$13,'table années scolaires'!$C$17:$E$27,3,FALSE),'Projection Effectifs'!$C$31:$M$36,2,FALSE) -> 240 | H26: =HLOOKUP(VLOOKUP(H$13,'table années scolaires'!$C$17:$E$27,3,FALSE),'Projection Effectifs'!$C$31:$M$36,2,FALSE) -> 300 | I26: =HLOOKUP(VLOOKUP(I$13,'table années scolaires'!$C$17:$E$27,3,FALSE),'Projection Effectifs'!$C$31:$M$36,2,FALSE) -> 360 | J26: =HLOOKUP(VLOOKUP(J$13,'table années scolaires'!$C$17:$E$27,3,FALSE),'Projection Effectifs'!$C$31:$M$36,2,FALSE) -> 360
B27: Frais scol AS N-1 | C27: =HLOOKUP(VLOOKUP(C$13,'table années scolaires'!$C$17:$E$27,2,FALSE),'Hypothèses '!$C$19:$K$26,5,FALSE) -> 0 | D27: =HLOOKUP(VLOOKUP(D$13,'table années scolaires'!$C$17:$E$27,2,FALSE),'Hypothèses '!$C$19:$K$26,5,FALSE) -> 0 | E27: =HLOOKUP(VLOOKUP(E$13,'table années scolaires'!$C$17:$E$27,2,FALSE),'Hypothèses '!$C$19:$K$26,5,FALSE) -> 0 | F27: =HLOOKUP(VLOOKUP(F$13,'table années scolaires'!$C$17:$E$27,2,FALSE),'Hypothèses '!$C$19:$K$26,5,FALSE) -> 0 | G27: =HLOOKUP(VLOOKUP(G$13,'table années scolaires'!$C$17:$E$27,2,FALSE),'Hypothèses '!$C$19:$K$26,5,FALSE) -> 0 | H27: =HLOOKUP(VLOOKUP(H$13,'table années scolaires'!$C$17:$E$27,2,FALSE),'Hypothèses '!$C$19:$K$26,5,FALSE) -> 0 | I27: =HLOOKUP(VLOOKUP(I$13,'table années scolaires'!$C$17:$E$27,2,FALSE),'Hypothèses '!$C$19:$K$26,5,FALSE) -> 0 | J27: =HLOOKUP(VLOOKUP(J$13,'table années scolaires'!$C$17:$E$27,2,FALSE),'Hypothèses '!$C$19:$K$26,5,FALSE) -> 0
B28: Frais scol AS N | C28: =HLOOKUP(VLOOKUP(C$13,'table années scolaires'!$C$17:$E$27,3,FALSE),'Hypothèses '!$C$19:$K$26,5,FALSE) -> 0 | D28: =HLOOKUP(VLOOKUP(D$13,'table années scolaires'!$C$17:$E$27,3,FALSE),'Hypothèses '!$C$19:$K$26,5,FALSE) -> 0 | E28: =HLOOKUP(VLOOKUP(E$13,'table années scolaires'!$C$17:$E$27,3,FALSE),'Hypothèses '!$C$19:$K$26,5,FALSE) -> 0 | F28: =HLOOKUP(VLOOKUP(F$13,'table années scolaires'!$C$17:$E$27,3,FALSE),'Hypothèses '!$C$19:$K$26,5,FALSE) -> 0 | G28: =HLOOKUP(VLOOKUP(G$13,'table années scolaires'!$C$17:$E$27,3,FALSE),'Hypothèses '!$C$19:$K$26,5,FALSE) -> 0 | H28: =HLOOKUP(VLOOKUP(H$13,'table années scolaires'!$C$17:$E$27,3,FALSE),'Hypothèses '!$C$19:$K$26,5,FALSE) -> 0 | I28: =HLOOKUP(VLOOKUP(I$13,'table années scolaires'!$C$17:$E$27,3,FALSE),'Hypothèses '!$C$19:$K$26,5,FALSE) -> 0 | J28: =HLOOKUP(VLOOKUP(J$13,'table années scolaires'!$C$17:$E$27,3,FALSE),'Hypothèses '!$C$19:$K$26,5,FALSE) -> 0
B29: Frais scolarité | C29: =IFERROR(((C25*C27/10*6)+(C26*C28/10*4))*(1-C$17),0) -> 0 | D29: =IFERROR(((D25*D27/10*6)+(D26*D28/10*4))*(1-D$17),0) -> 0 | E29: =IFERROR(((E25*E27/10*6)+(E26*E28/10*4))*(1-E$17),0) -> 0 | F29: =IFERROR(((F25*F27/10*6)+(F26*F28/10*4))*(1-F$17),0) -> 0 | G29: =IFERROR(((G25*G27/10*6)+(G26*G28/10*4))*(1-G$17),0) -> 0 | H29: =IFERROR(((H25*H27/10*6)+(H26*H28/10*4))*(1-H$17),0) -> 0 | I29: =IFERROR(((I25*I27/10*6)+(I26*I28/10*4))*(1-I$17),0) -> 0 | J29: =IFERROR(((J25*J27/10*6)+(J26*J28/10*4))*(1-J$17),0) -> 0
B30: DPI | C30: =IFERROR((C25/10*6+C26/10*4)*C$18*C$16,0) -> 0 | D30: =IFERROR((D25/10*6+D26/10*4)*D$18*D$16,0) -> 0 | E30: =IFERROR((E25/10*6+E26/10*4)*E$18*E$16,0) -> 12200000 | F30: =IFERROR((F25/10*6+F26/10*4)*F$18*F$16,0) -> 9860000 | G30: =IFERROR((G25/10*6+G26/10*4)*G$18*G$16,0) -> 10500000 | H30: =IFERROR((H25/10*6+H26/10*4)*H$18*H$16,0) -> 13200000 | I30: =IFERROR((I25/10*6+I26/10*4)*I$18*I$16,0) -> 16200000 | J30: =IFERROR((J25/10*6+J26/10*4)*J$18*J$16,0) -> 18000000
B31: Frais Réinscription | C31: =C26*C$19 -> 0 | D31: =D26*D$19 -> 0 | E31: =E26*E$19 -> 13130000 | F31: =F26*F$19 -> 12350000 | G31: =G26*G$19 -> 15600000 | H31: =H26*H$19 -> 19500000 | I31: =I26*I$19 -> 23400000 | J31: =J26*J$19 -> 23400000
A32: ELEMENTAIRE | C32: =SUM(C37:C39) -> 0 | D32: =SUM(D37:D39) -> 0 | E32: =SUM(E37:E39) -> 75065000 | F32: =SUM(F37:F39) -> 70335000 | G32: =SUM(G37:G39) -> 62960000 | H32: =SUM(H37:H39) -> 55510000 | I32: =SUM(I37:I39) -> 47300000 | J32: =SUM(J37:J39) -> 44230000
B33: Effectifs AS N-1 | C33: =HLOOKUP(VLOOKUP(C$13,'table années scolaires'!$C$17:$E$27,2,FALSE),'Projection Effectifs'!$C$31:$M$36,3,FALSE) -> 0 | D33: =HLOOKUP(VLOOKUP(D$13,'table années scolaires'!$C$17:$E$27,2,FALSE),'Projection Effectifs'!$C$31:$M$36,3,FALSE) -> 651 | E33: =HLOOKUP(VLOOKUP(E$13,'table années scolaires'!$C$17:$E$27,2,FALSE),'Projection Effectifs'!$C$31:$M$36,3,FALSE) -> 652 | F33: =HLOOKUP(VLOOKUP(F$13,'table années scolaires'!$C$17:$E$27,2,FALSE),'Projection Effectifs'!$C$31:$M$36,3,FALSE) -> 653 | G33: =HLOOKUP(VLOOKUP(G$13,'table années scolaires'!$C$17:$E$27,2,FALSE),'Projection Effectifs'!$C$31:$M$36,3,FALSE) -> 597 | H33: =HLOOKUP(VLOOKUP(H$13,'table années scolaires'!$C$17:$E$27,2,FALSE),'Projection Effectifs'!$C$31:$M$36,3,FALSE) -> 530 | I33: =HLOOKUP(VLOOKUP(I$13,'table années scolaires'!$C$17:$E$27,2,FALSE),'Projection Effectifs'!$C$31:$M$36,3,FALSE) -> 466 | J33: =HLOOKUP(VLOOKUP(J$13,'table années scolaires'!$C$17:$E$27,2,FALSE),'Projection Effectifs'!$C$31:$M$36,3,FALSE) -> 392
B34: Effectifs AS N | C34: =HLOOKUP(VLOOKUP(C$13,'table années scolaires'!$C$17:$E$27,3,FALSE),'Projection Effectifs'!$C$31:$M$36,3,FALSE) -> 651 | D34: =HLOOKUP(VLOOKUP(D$13,'table années scolaires'!$C$17:$E$27,3,FALSE),'Projection Effectifs'!$C$31:$M$36,3,FALSE) -> 652 | E34: =HLOOKUP(VLOOKUP(E$13,'table années scolaires'!$C$17:$E$27,3,FALSE),'Projection Effectifs'!$C$31:$M$36,3,FALSE) -> 653 | F34: =HLOOKUP(VLOOKUP(F$13,'table années scolaires'!$C$17:$E$27,3,FALSE),'Projection Effectifs'!$C$31:$M$36,3,FALSE) -> 597 | G34: =HLOOKUP(VLOOKUP(G$13,'table années scolaires'!$C$17:$E$27,3,FALSE),'Projection Effectifs'!$C$31:$M$36,3,FALSE) -> 530 | H34: =HLOOKUP(VLOOKUP(H$13,'table années scolaires'!$C$17:$E$27,3,FALSE),'Projection Effectifs'!$C$31:$M$36,3,FALSE) -> 466 | I34: =HLOOKUP(VLOOKUP(I$13,'table années scolaires'!$C$17:$E$27,3,FALSE),'Projection Effectifs'!$C$31:$M$36,3,FALSE) -> 392 | J34: =HLOOKUP(VLOOKUP(J$13,'table années scolaires'!$C$17:$E$27,3,FALSE),'Projection Effectifs'!$C$31:$M$36,3,FALSE) -> 382
B35: Frais scol AS N-1 | C35: =HLOOKUP(VLOOKUP(C$13,'table années scolaires'!$C$17:$E$27,2,FALSE),'Hypothèses '!$C$19:$K$26,6,FALSE) -> 0 | D35: =HLOOKUP(VLOOKUP(D$13,'table années scolaires'!$C$17:$E$27,2,FALSE),'Hypothèses '!$C$19:$K$26,6,FALSE) -> 0 | E35: =HLOOKUP(VLOOKUP(E$13,'table années scolaires'!$C$17:$E$27,2,FALSE),'Hypothèses '!$C$19:$K$26,6,FALSE) -> 0 | F35: =HLOOKUP(VLOOKUP(F$13,'table années scolaires'!$C$17:$E$27,2,FALSE),'Hypothèses '!$C$19:$K$26,6,FALSE) -> 0 | G35: =HLOOKUP(VLOOKUP(G$13,'table années scolaires'!$C$17:$E$27,2,FALSE),'Hypothèses '!$C$19:$K$26,6,FALSE) -> 0 | H35: =HLOOKUP(VLOOKUP(H$13,'table années scolaires'!$C$17:$E$27,2,FALSE),'Hypothèses '!$C$19:$K$26,6,FALSE) -> 0 | I35: =HLOOKUP(VLOOKUP(I$13,'table années scolaires'!$C$17:$E$27,2,FALSE),'Hypothèses '!$C$19:$K$26,6,FALSE) -> 0 | J35: =HLOOKUP(VLOOKUP(J$13,'table années scolaires'!$C$17:$E$27,2,FALSE),'Hypothèses '!$C$19:$K$26,6,FALSE) -> 0
B36: Frais scol AS N | C36: =HLOOKUP(VLOOKUP(C$13,'table années scolaires'!$C$17:$E$27,3,FALSE),'Hypothèses '!$C$19:$K$26,6,FALSE) -> 0 | D36: =HLOOKUP(VLOOKUP(D$13,'table années scolaires'!$C$17:$E$27,3,FALSE),'Hypothèses '!$C$19:$K$26,6,FALSE) -> 0 | E36: =HLOOKUP(VLOOKUP(E$13,'table années scolaires'!$C$17:$E$27,3,FALSE),'Hypothèses '!$C$19:$K$26,6,FALSE) -> 0 | F36: =HLOOKUP(VLOOKUP(F$13,'table années scolaires'!$C$17:$E$27,3,FALSE),'Hypothèses '!$C$19:$K$26,6,FALSE) -> 0 | G36: =HLOOKUP(VLOOKUP(G$13,'table années scolaires'!$C$17:$E$27,3,FALSE),'Hypothèses '!$C$19:$K$26,6,FALSE) -> 0 | H36: =HLOOKUP(VLOOKUP(H$13,'table années scolaires'!$C$17:$E$27,3,FALSE),'Hypothèses '!$C$19:$K$26,6,FALSE) -> 0 | I36: =HLOOKUP(VLOOKUP(I$13,'table années scolaires'!$C$17:$E$27,3,FALSE),'Hypothèses '!$C$19:$K$26,6,FALSE) -> 0 | J36: =HLOOKUP(VLOOKUP(J$13,'table années scolaires'!$C$17:$E$27,3,FALSE),'Hypothèses '!$C$19:$K$26,6,FALSE) -> 0
B37: Frais scolarité | C37: =IFERROR(((C33*C35/10*6)+(C34*C36/10*4))*(1-C$17),0) -> 0 | D37: =IFERROR(((D33*D35/10*6)+(D34*D36/10*4))*(1-D$17),0) -> 0 | E37: =IFERROR(((E33*E35/10*6)+(E34*E36/10*4))*(1-E$17),0) -> 0 | F37: =IFERROR(((F33*F35/10*6)+(F34*F36/10*4))*(1-F$17),0) -> 0 | G37: =IFERROR(((G33*G35/10*6)+(G34*G36/10*4))*(1-G$17),0) -> 0 | H37: =IFERROR(((H33*H35/10*6)+(H34*H36/10*4))*(1-H$17),0) -> 0 | I37: =IFERROR(((I33*I35/10*6)+(I34*I36/10*4))*(1-I$17),0) -> 0 | J37: =IFERROR(((J33*J35/10*6)+(J34*J36/10*4))*(1-J$17),0) -> 0
B38: DPI | C38: =IFERROR((C33/10*6+C34/10*4)*C$18*C$16,0) -> 0 | D38: =IFERROR((D33/10*6+D34/10*4)*D$18*D$16,0) -> 0 | E38: =IFERROR((E33/10*6+E34/10*4)*E$18*E$16,0) -> 32620000 | F38: =IFERROR((F33/10*6+F34/10*4)*F$18*F$16,0) -> 31530000 | G38: =IFERROR((G33/10*6+G34/10*4)*G$18*G$16,0) -> 28510000 | H38: =IFERROR((H33/10*6+H34/10*4)*H$18*H$16,0) -> 25220000 | I38: =IFERROR((I33/10*6+I34/10*4)*I$18*I$16,0) -> 21820000 | J38: =IFERROR((J33/10*6+J34/10*4)*J$18*J$16,0) -> 19400000
B39: Frais Réinscription | C39: =C34*C$19 -> 0 | D39: =D34*D$19 -> 0 | E39: =E34*E$19 -> 42445000 | F39: =F34*F$19 -> 38805000 | G39: =G34*G$19 -> 34450000 | H39: =H34*H$19 -> 30290000 | I39: =I34*I$19 -> 25480000 | J39: =J34*J$19 -> 24830000
A40: COLLEGE | C40: =SUM(C45:C47) -> 0 | D40: =SUM(D45:D47) -> 0 | E40: =SUM(E45:E47) -> 62885000 | F40: =SUM(F45:F47) -> 63535000 | G40: =SUM(G45:G47) -> 63085000 | H40: =SUM(H45:H47) -> 60440000 | I40: =SUM(I45:I47) -> 59995000 | J40: =SUM(J45:J47) -> 60315000
B41: Effectifs AS N-1 | C41: =HLOOKUP(VLOOKUP(C$13,'table années scolaires'!$C$17:$E$27,2,FALSE),'Projection Effectifs'!$C$31:$M$36,5,FALSE) -> 0 | D41: =HLOOKUP(VLOOKUP(D$13,'table années scolaires'!$C$17:$E$27,2,FALSE),'Projection Effectifs'!$C$31:$M$36,5,FALSE) -> 499 | E41: =HLOOKUP(VLOOKUP(E$13,'table années scolaires'!$C$17:$E$27,2,FALSE),'Projection Effectifs'!$C$31:$M$36,5,FALSE) -> 535 | F41: =HLOOKUP(VLOOKUP(F$13,'table années scolaires'!$C$17:$E$27,2,FALSE),'Projection Effectifs'!$C$31:$M$36,5,FALSE) -> 551 | G41: =HLOOKUP(VLOOKUP(G$13,'table années scolaires'!$C$17:$E$27,2,FALSE),'Projection Effectifs'!$C$31:$M$36,5,FALSE) -> 553 | H41: =HLOOKUP(VLOOKUP(H$13,'table années scolaires'!$C$17:$E$27,2,FALSE),'Projection Effectifs'!$C$31:$M$36,5,FALSE) -> 547 | I41: =HLOOKUP(VLOOKUP(I$13,'table années scolaires'!$C$17:$E$27,2,FALSE),'Projection Effectifs'!$C$31:$M$36,5,FALSE) -> 518 | J41: =HLOOKUP(VLOOKUP(J$13,'table années scolaires'!$C$17:$E$27,2,FALSE),'Projection Effectifs'!$C$31:$M$36,5,FALSE) -> 523
B42: Effectifs AS N | C42: =HLOOKUP(VLOOKUP(C$13,'table années scolaires'!$C$17:$E$27,3,FALSE),'Projection Effectifs'!$C$31:$M$36,5,FALSE) -> 499 | D42: =HLOOKUP(VLOOKUP(D$13,'table années scolaires'!$C$17:$E$27,3,FALSE),'Projection Effectifs'!$C$31:$M$36,5,FALSE) -> 535 | E42: =HLOOKUP(VLOOKUP(E$13,'table années scolaires'!$C$17:$E$27,3,FALSE),'Projection Effectifs'!$C$31:$M$36,5,FALSE) -> 551 | F42: =HLOOKUP(VLOOKUP(F$13,'table années scolaires'!$C$17:$E$27,3,FALSE),'Projection Effectifs'!$C$31:$M$36,5,FALSE) -> 553 | G42: =HLOOKUP(VLOOKUP(G$13,'table années scolaires'!$C$17:$E$27,3,FALSE),'Projection Effectifs'!$C$31:$M$36,5,FALSE) -> 547 | H42: =HLOOKUP(VLOOKUP(H$13,'table années scolaires'!$C$17:$E$27,3,FALSE),'Projection Effectifs'!$C$31:$M$36,5,FALSE) -> 518 | I42: =HLOOKUP(VLOOKUP(I$13,'table années scolaires'!$C$17:$E$27,3,FALSE),'Projection Effectifs'!$C$31:$M$36,5,FALSE) -> 523 | J42: =HLOOKUP(VLOOKUP(J$13,'table années scolaires'!$C$17:$E$27,3,FALSE),'Projection Effectifs'!$C$31:$M$36,5,FALSE) -> 525
B43: Frais scol AS N-1 | C43: =HLOOKUP(VLOOKUP(C$13,'table années scolaires'!$C$17:$E$27,2,FALSE),'Hypothèses '!$C$19:$K$26,7,FALSE) -> 0 | D43: =HLOOKUP(VLOOKUP(D$13,'table années scolaires'!$C$17:$E$27,2,FALSE),'Hypothèses '!$C$19:$K$26,7,FALSE) -> 0 | E43: =HLOOKUP(VLOOKUP(E$13,'table années scolaires'!$C$17:$E$27,2,FALSE),'Hypothèses '!$C$19:$K$26,7,FALSE) -> 0 | F43: =HLOOKUP(VLOOKUP(F$13,'table années scolaires'!$C$17:$E$27,2,FALSE),'Hypothèses '!$C$19:$K$26,7,FALSE) -> 0 | G43: =HLOOKUP(VLOOKUP(G$13,'table années scolaires'!$C$17:$E$27,2,FALSE),'Hypothèses '!$C$19:$K$26,7,FALSE) -> 0 | H43: =HLOOKUP(VLOOKUP(H$13,'table années scolaires'!$C$17:$E$27,2,FALSE),'Hypothèses '!$C$19:$K$26,7,FALSE) -> 0 | I43: =HLOOKUP(VLOOKUP(I$13,'table années scolaires'!$C$17:$E$27,2,FALSE),'Hypothèses '!$C$19:$K$26,7,FALSE) -> 0 | J43: =HLOOKUP(VLOOKUP(J$13,'table années scolaires'!$C$17:$E$27,2,FALSE),'Hypothèses '!$C$19:$K$26,7,FALSE) -> 0
B44: Frais scol AS N | C44: =HLOOKUP(VLOOKUP(C$13,'table années scolaires'!$C$17:$E$27,3,FALSE),'Hypothèses '!$C$19:$K$26,7,FALSE) -> 0 | D44: =HLOOKUP(VLOOKUP(D$13,'table années scolaires'!$C$17:$E$27,3,FALSE),'Hypothèses '!$C$19:$K$26,7,FALSE) -> 0 | E44: =HLOOKUP(VLOOKUP(E$13,'table années scolaires'!$C$17:$E$27,3,FALSE),'Hypothèses '!$C$19:$K$26,7,FALSE) -> 0 | F44: =HLOOKUP(VLOOKUP(F$13,'table années scolaires'!$C$17:$E$27,3,FALSE),'Hypothèses '!$C$19:$K$26,7,FALSE) -> 0 | G44: =HLOOKUP(VLOOKUP(G$13,'table années scolaires'!$C$17:$E$27,3,FALSE),'Hypothèses '!$C$19:$K$26,7,FALSE) -> 0 | H44: =HLOOKUP(VLOOKUP(H$13,'table années scolaires'!$C$17:$E$27,3,FALSE),'Hypothèses '!$C$19:$K$26,7,FALSE) -> 0 | I44: =HLOOKUP(VLOOKUP(I$13,'table années scolaires'!$C$17:$E$27,3,FALSE),'Hypothèses '!$C$19:$K$26,7,FALSE) -> 0 | J44: =HLOOKUP(VLOOKUP(J$13,'table années scolaires'!$C$17:$E$27,3,FALSE),'Hypothèses '!$C$19:$K$26,7,FALSE) -> 0
B45: Frais scolarité | C45: =IFERROR(((C41*C43/10*6)+(C42*C44/10*4))*(1-C$17),0) -> 0 | D45: =IFERROR(((D41*D43/10*6)+(D42*D44/10*4))*(1-D$17),0) -> 0 | E45: =IFERROR(((E41*E43/10*6)+(E42*E44/10*4))*(1-E$17),0) -> 0 | F45: =IFERROR(((F41*F43/10*6)+(F42*F44/10*4))*(1-F$17),0) -> 0 | G45: =IFERROR(((G41*G43/10*6)+(G42*G44/10*4))*(1-G$17),0) -> 0 | H45: =IFERROR(((H41*H43/10*6)+(H42*H44/10*4))*(1-H$17),0) -> 0 | I45: =IFERROR(((I41*I43/10*6)+(I42*I44/10*4))*(1-I$17),0) -> 0 | J45: =IFERROR(((J41*J43/10*6)+(J42*J44/10*4))*(1-J$17),0) -> 0
B46: DPI | C46: =IFERROR((C41/10*6+C42/10*4)*C$18*C$16,0) -> 0 | D46: =IFERROR((D41/10*6+D42/10*4)*D$18*D$16,0) -> 0 | E46: =IFERROR((E41/10*6+E42/10*4)*E$18*E$16,0) -> 27070000 | F46: =IFERROR((F41/10*6+F42/10*4)*F$18*F$16,0) -> 27590000 | G46: =IFERROR((G41/10*6+G42/10*4)*G$18*G$16,0) -> 27530000 | H46: =IFERROR((H41/10*6+H42/10*4)*H$18*H$16,0) -> 26770000 | I46: =IFERROR((I41/10*6+I42/10*4)*I$18*I$16,0) -> 26000000 | J46: =IFERROR((J41/10*6+J42/10*4)*J$18*J$16,0) -> 26190000
B47: Frais Réinscription | C47: =C42*C$19 -> 0 | D47: =D42*D$19 -> 0 | E47: =E42*E$19 -> 35815000 | F47: =F42*F$19 -> 35945000 | G47: =G42*G$19 -> 35555000 | H47: =H42*H$19 -> 33670000 | I47: =I42*I$19 -> 33995000 | J47: =J42*J$19 -> 34125000
A48: LYCEE | C48: =SUM(C53:C55) -> 0 | D48: =SUM(D53:D55) -> 0 | E48: =SUM(E53:E55) -> 42345000 | F48: =SUM(F53:F55) -> 42435000 | G48: =SUM(G53:G55) -> 43540000 | H48: =SUM(H53:H55) -> 47330000 | I48: =SUM(I53:I55) -> 48785000 | J48: =SUM(J53:J55) -> 47600000
B49: Effectifs AS N-1 | C49: =HLOOKUP(VLOOKUP(C$13,'table années scolaires'!$C$17:$E$27,2,FALSE),'Projection Effectifs'!$C$31:$M$36,6,FALSE) -> 0 | D49: =HLOOKUP(VLOOKUP(D$13,'table années scolaires'!$C$17:$E$27,2,FALSE),'Projection Effectifs'!$C$31:$M$36,6,FALSE) -> 353 | E49: =HLOOKUP(VLOOKUP(E$13,'table années scolaires'!$C$17:$E$27,2,FALSE),'Projection Effectifs'!$C$31:$M$36,6,FALSE) -> 366 | F49: =HLOOKUP(VLOOKUP(F$13,'table années scolaires'!$C$17:$E$27,2,FALSE),'Projection Effectifs'!$C$31:$M$36,6,FALSE) -> 369 | G49: =HLOOKUP(VLOOKUP(G$13,'table années scolaires'!$C$17:$E$27,2,FALSE),'Projection Effectifs'!$C$31:$M$36,6,FALSE) -> 369 | H49: =HLOOKUP(VLOOKUP(H$13,'table années scolaires'!$C$17:$E$27,2,FALSE),'Projection Effectifs'!$C$31:$M$36,6,FALSE) -> 382 | I49: =HLOOKUP(VLOOKUP(I$13,'table années scolaires'!$C$17:$E$27,2,FALSE),'Projection Effectifs'!$C$31:$M$36,6,FALSE) -> 422 | J49: =HLOOKUP(VLOOKUP(J$13,'table années scolaires'!$C$17:$E$27,2,FALSE),'Projection Effectifs'!$C$31:$M$36,6,FALSE) -> 425
B50: Effectifs AS N | C50: =HLOOKUP(VLOOKUP(C$13,'table années scolaires'!$C$17:$E$27,3,FALSE),'Projection Effectifs'!$C$31:$M$36,6,FALSE) -> 353 | D50: =HLOOKUP(VLOOKUP(D$13,'table années scolaires'!$C$17:$E$27,3,FALSE),'Projection Effectifs'!$C$31:$M$36,6,FALSE) -> 366 | E50: =HLOOKUP(VLOOKUP(E$13,'table années scolaires'!$C$17:$E$27,3,FALSE),'Projection Effectifs'!$C$31:$M$36,6,FALSE) -> 369 | F50: =HLOOKUP(VLOOKUP(F$13,'table années scolaires'!$C$17:$E$27,3,FALSE),'Projection Effectifs'!$C$31:$M$36,6,FALSE) -> 369 | G50: =HLOOKUP(VLOOKUP(G$13,'table années scolaires'!$C$17:$E$27,3,FALSE),'Projection Effectifs'!$C$31:$M$36,6,FALSE) -> 382 | H50: =HLOOKUP(VLOOKUP(H$13,'table années scolaires'!$C$17:$E$27,3,FALSE),'Projection Effectifs'!$C$31:$M$36,6,FALSE) -> 422 | I50: =HLOOKUP(VLOOKUP(I$13,'table années scolaires'!$C$17:$E$27,3,FALSE),'Projection Effectifs'!$C$31:$M$36,6,FALSE) -> 425 | J50: =HLOOKUP(VLOOKUP(J$13,'table années scolaires'!$C$17:$E$27,3,FALSE),'Projection Effectifs'!$C$31:$M$36,6,FALSE) -> 410
B51: Frais scol AS N-1 | C51: =HLOOKUP(VLOOKUP(C$13,'table années scolaires'!$C$17:$E$27,2,FALSE),'Hypothèses '!$C$19:$K$26,8,FALSE) -> 0 | D51: =HLOOKUP(VLOOKUP(D$13,'table années scolaires'!$C$17:$E$27,2,FALSE),'Hypothèses '!$C$19:$K$26,8,FALSE) -> 0 | E51: =HLOOKUP(VLOOKUP(E$13,'table années scolaires'!$C$17:$E$27,2,FALSE),'Hypothèses '!$C$19:$K$26,8,FALSE) -> 0 | F51: =HLOOKUP(VLOOKUP(F$13,'table années scolaires'!$C$17:$E$27,2,FALSE),'Hypothèses '!$C$19:$K$26,8,FALSE) -> 0 | G51: =HLOOKUP(VLOOKUP(G$13,'table années scolaires'!$C$17:$E$27,2,FALSE),'Hypothèses '!$C$19:$K$26,8,FALSE) -> 0 | H51: =HLOOKUP(VLOOKUP(H$13,'table années scolaires'!$C$17:$E$27,2,FALSE),'Hypothèses '!$C$19:$K$26,8,FALSE) -> 0 | I51: =HLOOKUP(VLOOKUP(I$13,'table années scolaires'!$C$17:$E$27,2,FALSE),'Hypothèses '!$C$19:$K$26,8,FALSE) -> 0 | J51: =HLOOKUP(VLOOKUP(J$13,'table années scolaires'!$C$17:$E$27,2,FALSE),'Hypothèses '!$C$19:$K$26,8,FALSE) -> 0
B52: Frais scol AS N | C52: =HLOOKUP(VLOOKUP(C$13,'table années scolaires'!$C$17:$E$27,3,FALSE),'Hypothèses '!$C$19:$K$26,8,FALSE) -> 0 | D52: =HLOOKUP(VLOOKUP(D$13,'table années scolaires'!$C$17:$E$27,3,FALSE),'Hypothèses '!$C$19:$K$26,8,FALSE) -> 0 | E52: =HLOOKUP(VLOOKUP(E$13,'table années scolaires'!$C$17:$E$27,3,FALSE),'Hypothèses '!$C$19:$K$26,8,FALSE) -> 0 | F52: =HLOOKUP(VLOOKUP(F$13,'table années scolaires'!$C$17:$E$27,3,FALSE),'Hypothèses '!$C$19:$K$26,8,FALSE) -> 0 | G52: =HLOOKUP(VLOOKUP(G$13,'table années scolaires'!$C$17:$E$27,3,FALSE),'Hypothèses '!$C$19:$K$26,8,FALSE) -> 0 | H52: =HLOOKUP(VLOOKUP(H$13,'table années scolaires'!$C$17:$E$27,3,FALSE),'Hypothèses '!$C$19:$K$26,8,FALSE) -> 0 | I52: =HLOOKUP(VLOOKUP(I$13,'table années scolaires'!$C$17:$E$27,3,FALSE),'Hypothèses '!$C$19:$K$26,8,FALSE) -> 0 | J52: =HLOOKUP(VLOOKUP(J$13,'table années scolaires'!$C$17:$E$27,3,FALSE),'Hypothèses '!$C$19:$K$26,8,FALSE) -> 0
B53: Frais scolarité | C53: =IFERROR(((C49*C51/10*6)+(C50*C52/10*4))*(1-C$17),0) -> 0 | D53: =IFERROR(((D49*D51/10*6)+(D50*D52/10*4))*(1-D$17),0) -> 0 | E53: =IFERROR(((E49*E51/10*6)+(E50*E52/10*4))*(1-E$17),0) -> 0 | F53: =IFERROR(((F49*F51/10*6)+(F50*F52/10*4))*(1-F$17),0) -> 0 | G53: =IFERROR(((G49*G51/10*6)+(G50*G52/10*4))*(1-G$17),0) -> 0 | H53: =IFERROR(((H49*H51/10*6)+(H50*H52/10*4))*(1-H$17),0) -> 0 | I53: =IFERROR(((I49*I51/10*6)+(I50*I52/10*4))*(1-I$17),0) -> 0 | J53: =IFERROR(((J49*J51/10*6)+(J50*J52/10*4))*(1-J$17),0) -> 0
B54: DPI | C54: =IFERROR((C49/10*6+C50/10*4)*C$18*C$16,0) -> 0 | D54: =IFERROR((D49/10*6+D50/10*4)*D$18*D$16,0) -> 0 | E54: =IFERROR((E49/10*6+E50/10*4)*E$18*E$16,0) -> 18360000 | F54: =IFERROR((F49/10*6+F50/10*4)*F$18*F$16,0) -> 18450000 | G54: =IFERROR((G49/10*6+G50/10*4)*G$18*G$16,0) -> 18710000 | H54: =IFERROR((H49/10*6+H50/10*4)*H$18*H$16,0) -> 19900000 | I54: =IFERROR((I49/10*6+I50/10*4)*I$18*I$16,0) -> 21160000 | J54: =IFERROR((J49/10*6+J50/10*4)*J$18*J$16,0) -> 20950000
B55: Frais Réinscription | C55: =C50*C$19 -> 0 | D55: =D50*D$19 -> 0 | E55: =E50*E$19 -> 23985000 | F55: =F50*F$19 -> 23985000 | G55: =G50*G$19 -> 24830000 | H55: =H50*H$19 -> 27430000 | I55: =I50*I$19 -> 27625000 | J55: =J50*J$19 -> 26650000
A58: CHARGES | C58: =C13 -> 2024 | D58: =C58+1 -> 2025 | E58: =D58+1 -> 2026 | F58: =E58+1 -> 2027 | G58: =F58+1 -> 2028 | H58: =G58+1 -> 2029 | I58: =H58+1 -> 2030 | J58: =I58+1 -> 2031
B59: Inflation report | C59: =HLOOKUP(C$58,'Hypothèses '!$C$34:$K$36,3,FALSE) -> 0 | D59: =HLOOKUP(D$58,'Hypothèses '!$C$34:$K$36,3,FALSE) -> 0 | E59: =HLOOKUP(E$58,'Hypothèses '!$C$34:$K$36,3,FALSE) -> 0 | F59: =HLOOKUP(F$58,'Hypothèses '!$C$34:$K$36,3,FALSE) -> 0 | G59: =HLOOKUP(G$58,'Hypothèses '!$C$34:$K$36,3,FALSE) -> 0 | H59: =HLOOKUP(H$58,'Hypothèses '!$C$34:$K$36,3,FALSE) -> 0 | I59: =HLOOKUP(I$58,'Hypothèses '!$C$34:$K$36,3,FALSE) -> 0 | J59: =HLOOKUP(J$58,'Hypothèses '!$C$34:$K$36,3,FALSE) -> 0
A60: GLOBAL | B60: Charges globales | C60: =C61+C65+C70+C80 -> #N/A | D60: =D61+D65+D70+D80 -> #N/A | E60: =E61+E65+E70+E80 -> #N/A | F60: =F61+F65+F70+F80 -> #N/A | G60: =G61+G65+G70+G80 -> #N/A | H60: =H61+H65+H70+H80 -> #N/A | I60: =I61+I65+I70+I80 -> #N/A | J60: =J61+J65+J70+J80 -> #N/A
B61: Masse salariale | C61: =C85+C111+C137+C163 -> #N/A | D61: =D85+D111+D137+D163 -> #N/A | E61: =E85+E111+E137+E163 -> #N/A | F61: =F85+F111+F137+F163 -> #N/A | G61: =G85+G111+G137+G163 -> #N/A | H61: =H85+H111+H137+H163 -> #N/A | I61: =I85+I111+I137+I163 -> #N/A | J61: =J85+J111+J137+J163 -> #N/A
B62: Masse salariale Enseignants PDL | C62: =C86+C112+C138+C164 -> 0 | D62: =D86+D112+D138+D164 -> 0 | E62: =E86+E112+E138+E164 -> 0 | F62: =F86+F112+F138+F164 -> 0 | G62: =G86+G112+G138+G164 -> 0 | H62: =H86+H112+H138+H164 -> 0 | I62: =I86+I112+I138+I164 -> 0 | J62: =J86+J112+J138+J164 -> 0
B63: Masse salariale Enseignants Détachés | C63: =C87+C113+C139+C165 -> 0 | D63: =D87+D113+D139+D165 -> 0 | E63: =E87+E113+E139+E165 -> 0 | F63: =F87+F113+F139+F165 -> 0 | G63: =G87+G113+G139+G165 -> 0 | H63: =H87+H113+H139+H165 -> 0 | I63: =I87+I113+I139+I165 -> 0 | J63: =J87+J113+J139+J165 -> 0
B64: Masse salariale non enseignants | C64: =C88+C114+C140+C166 -> #N/A | D64: =D88+D114+D140+D166 -> #N/A | E64: =E88+E114+E140+E166 -> #N/A | F64: =F88+F114+F140+F166 -> #N/A | G64: =G88+G114+G140+G166 -> #N/A | H64: =H88+H114+H140+H166 -> #N/A | I64: =I88+I114+I140+I166 -> #N/A | J64: =J88+J114+J140+J166 -> #N/A
B65: Charges variables | C65: =C89+C115+C141+C167 -> 0 | D65: =D89+D115+D141+D167 -> 0 | E65: =E89+E115+E141+E167 -> 0 | F65: =F89+F115+F141+F167 -> 0 | G65: =G89+G115+G141+G167 -> 0 | H65: =H89+H115+H141+H167 -> 0 | I65: =I89+I115+I141+I167 -> 0 | J65: =J89+J115+J141+J167 -> 0
B66: Crédits disciplinaires | C66: =C90+C116+C142+C168 -> 0 | D66: =D90+D116+D142+D168 -> 0 | E66: =E90+E116+E142+E168 -> 0 | F66: =F90+F116+F142+F168 -> 0 | G66: =G90+G116+G142+G168 -> 0 | H66: =H90+H116+H142+H168 -> 0 | I66: =I90+I116+I142+I168 -> 0 | J66: =J90+J116+J142+J168 -> 0
B67: Manuels scolaires | C67: =C91+C117+C143+C169 -> 0 | D67: =D91+D117+D143+D169 -> 0 | E67: =E91+E117+E143+E169 -> 0 | F67: =F91+F117+F143+F169 -> 0 | G67: =G91+G117+G143+G169 -> 0 | H67: =H91+H117+H143+H169 -> 0 | I67: =I91+I117+I143+I169 -> 0 | J67: =J91+J117+J143+J169 -> 0
B68: Equipements individuels (tablettes …) | C68: =C92+C118+C144+C170 -> 0 | D68: =D92+D118+D144+D170 -> 0 | E68: =E92+E118+E144+E170 -> 0 | F68: =F92+F118+F144+F170 -> 0 | G68: =G92+G118+G144+G170 -> 0 | H68: =H92+H118+H144+H170 -> 0 | I68: =I92+I118+I144+I170 -> 0 | J68: =J92+J118+J144+J170 -> 0
B69: Autres charges variables | C69: =C93+C119+C145+C171 -> 0 | D69: =D93+D119+D145+D171 -> 0 | E69: =E93+E119+E145+E171 -> 0 | F69: =F93+F119+F145+F171 -> 0 | G69: =G93+G119+G145+G171 -> 0 | H69: =H93+H119+H145+H171 -> 0 | I69: =I93+I119+I145+I171 -> 0 | J69: =J93+J119+J145+J171 -> 0
B70: Charges fixes | C70: =C94+C120+C146+C172 -> 0 | D70: =D94+D120+D146+D172 -> 0 | E70: =E94+E120+E146+E172 -> 0 | F70: =F94+F120+F146+F172 -> 0 | G70: =G94+G120+G146+G172 -> 0 | H70: =H94+H120+H146+H172 -> 0 | I70: =I94+I120+I146+I172 -> 0 | J70: =J94+J120+J146+J172 -> 0
B71: Loyer | C71: =C95+C121+C147+C173 -> 0 | D71: =D95+D121+D147+D173 -> 0 | E71: =E95+E121+E147+E173 -> 0 | F71: =F95+F121+F147+F173 -> 0 | G71: =G95+G121+G147+G173 -> 0 | H71: =H95+H121+H147+H173 -> 0 | I71: =I95+I121+I147+I173 -> 0 | J71: =J95+J121+J147+J173 -> 0
B72: Viabilisation (Eau, énergies) | C72: =C96+C122+C148+C174 -> 0 | D72: =D96+D122+D148+D174 -> 0 | E72: =E96+E122+E148+E174 -> 0 | F72: =F96+F122+F148+F174 -> 0 | G72: =G96+G122+G148+G174 -> 0 | H72: =H96+H122+H148+H174 -> 0 | I72: =I96+I122+I148+I174 -> 0 | J72: =J96+J122+J148+J174 -> 0
... B83: Formation continue | C83: =C107+C133+C159+C185 -> 0 | D83: =D107+D133+D159+D185 -> 0 | E83: =E107+E133+E159+E185 -> 0 | F83: =F107+F133+F159+F185 -> #N/A | G83: =G107+G133+G159+G185 -> #N/A | H83: =H107+H133+H159+H185 -> #N/A | I83: =I107+I133+I159+I185 -> #N/A | J83: =J107+J133+J159+J185 -> #N/A
A84: MATERNELLE | B84: Charges Maternelle | C84: =C85+C89+C94+C104 -> #N/A | D84: =D85+D89+D94+D104 -> #N/A | E84: =E85+E89+E94+E104 -> #N/A | F84: =F85+F89+F94+F104 -> #N/A | G84: =G85+G89+G94+G104 -> #N/A | H84: =H85+H89+H94+H104 -> #N/A | I84: =I85+I89+I94+I104 -> #N/A | J84: =J85+J89+J94+J104 -> #N/A
B85: Masse salariale | C85: =SUM(C86:C88) -> #N/A | D85: =SUM(D86:D88) -> #N/A | E85: =SUM(E86:E88) -> #N/A | F85: =SUM(F86:F88) -> #N/A | G85: =SUM(G86:G88) -> #N/A | H85: =SUM(H86:H88) -> #N/A | I85: =SUM(I86:I88) -> #N/A | J85: =SUM(J86:J88) -> #N/A
B86: Masse salariale Enseignants PDL | C86: ='Calcul MS Personnels'!D87 -> 0 | D86: ='Calcul MS Personnels'!E87 -> 0 | E86: ='Calcul MS Personnels'!F87 -> 0 | F86: ='Calcul MS Personnels'!G87 -> 0 | G86: ='Calcul MS Personnels'!H87 -> 0 | H86: ='Calcul MS Personnels'!I87 -> 0 | I86: ='Calcul MS Personnels'!J87 -> 0 | J86: ='Calcul MS Personnels'!K87 -> 0
B87: Masse salariale Enseignants Détachés | C87: ='Calcul MS Personnels'!D86 -> 0 | D87: ='Calcul MS Personnels'!E86 -> 0 | E87: ='Calcul MS Personnels'!F86 -> 0 | F87: ='Calcul MS Personnels'!G86 -> 0 | G87: ='Calcul MS Personnels'!H86 -> 0 | H87: ='Calcul MS Personnels'!I86 -> 0 | I87: ='Calcul MS Personnels'!J86 -> 0 | J87: ='Calcul MS Personnels'!K86 -> 0
B88: Masse salariale non enseignants | C88: =SUM('Calcul MS Personnels'!D69:D76)+SUM('Calcul MS Personnels'!D78:D84)+'Calcul MS Personnels'!D88 -> #N/A | D88: =SUM('Calcul MS Personnels'!E69:E76)+SUM('Calcul MS Personnels'!E78:E84)+'Calcul MS Personnels'!E88 -> #N/A | E88: =SUM('Calcul MS Personnels'!F69:F76)+SUM('Calcul MS Personnels'!F78:F84)+'Calcul MS Personnels'!F88 -> #N/A | F88: =SUM('Calcul MS Personnels'!G69:G76)+SUM('Calcul MS Personnels'!G78:G84)+'Calcul MS Personnels'!G88 -> #N/A | G88: =SUM('Calcul MS Personnels'!H69:H76)+SUM('Calcul MS Personnels'!H78:H84)+'Calcul MS Personnels'!H88 -> #N/A | H88: =SUM('Calcul MS Personnels'!I69:I76)+SUM('Calcul MS Personnels'!I78:I84)+'Calcul MS Personnels'!I88 -> #N/A | I88: =SUM('Calcul MS Personnels'!J69:J76)+SUM('Calcul MS Personnels'!J78:J84)+'Calcul MS Personnels'!J88 -> #N/A | J88: =SUM('Calcul MS Personnels'!K69:K76)+SUM('Calcul MS Personnels'!K78:K84)+'Calcul MS Personnels'!K88 -> #N/A
B89: Charges variables | C89: =SUM(C90:C93) -> 0 | D89: =SUM(D90:D93) -> 0 | E89: =SUM(E90:E93) -> 0 | F89: =SUM(F90:F93) -> 0 | G89: =SUM(G90:G93) -> 0 | H89: =SUM(H90:H93) -> 0 | I89: =SUM(I90:I93) -> 0 | J89: =SUM(J90:J93) -> 0
B90: Crédits disciplinaires | C90: =VLOOKUP($B90,'Hypothèses '!$B$133:$D$146,3,FALSE)*HLOOKUP(VLOOKUP(C$13,'table années scolaires'!$C$17:$E$27,2,FALSE),'Projection Effectifs'!$S$31:$AC$35,2,FALSE) -> 0 | D90: =C90*(1+(HLOOKUP(VLOOKUP(C$13,'table années scolaires'!$C$17:$E$27,3,FALSE),'Projection Effectifs'!$S$44:$AC$48,2,FALSE)))*(1+$D$59) -> 0 | E90: =D90*(1+(HLOOKUP(VLOOKUP(D$13,'table années scolaires'!$C$17:$E$27,3,FALSE),'Projection Effectifs'!$S$44:$AC$48,2,FALSE)))*(1+$D$59)*(1+$E$59) -> 0 | F90: =E90*(1+(HLOOKUP(VLOOKUP(E$13,'table années scolaires'!$C$17:$E$27,3,FALSE),'Projection Effectifs'!$S$44:$AC$48,2,FALSE)))*(1+$D$59)*(1+$E$59)*(1+$F$59) -> 0 | G90: =F90*(1+(HLOOKUP(VLOOKUP(F$13,'table années scolaires'!$C$17:$E$27,3,FALSE),'Projection Effectifs'!$S$44:$AC$48,2,FALSE)))*(1+$D$59)*(1+$E$59)*(1+$F$59)*(1+$G$59) -> 0 | H90: =G90*(1+(HLOOKUP(VLOOKUP(G$13,'table années scolaires'!$C$17:$E$27,3,FALSE),'Projection Effectifs'!$S$44:$AC$48,2,FALSE)))*(1+$D$59)*(1+$E$59)*(1+$F$59)*(1+$G$59)*(1+$H$59) -> 0 | I90: =H90*(1+(HLOOKUP(VLOOKUP(H$13,'table années scolaires'!$C$17:$E$27,3,FALSE),'Projection Effectifs'!$S$44:$AC$48,2,FALSE)))*(1+$D$59)*(1+$E$59)*(1+$F$59)*(1+$G$59)*(1+$H$59)*(1+$I$59) -> 0 | J90: =I90*(1+(HLOOKUP(VLOOKUP(I$13,'table années scolaires'!$C$17:$E$27,3,FALSE),'Projection Effectifs'!$S$44:$AC$48,2,FALSE)))*(1+$D$59)*(1+$E$59)*(1+$F$59)*(1+$G$59)*(1+$H$59)*(1+$I$59)*(1+$J$59) -> 0
B91: Manuels scolaires | C91: =VLOOKUP($B91,'Hypothèses '!$B$133:$D$146,3,FALSE)*HLOOKUP(VLOOKUP(C$13,'table années scolaires'!$C$17:$E$27,2,FALSE),'Projection Effectifs'!$S$31:$AC$35,2,FALSE) -> 0 | D91: =C91*(1+(HLOOKUP(VLOOKUP(C$13,'table années scolaires'!$C$17:$E$27,3,FALSE),'Projection Effectifs'!$S$44:$AC$48,2,FALSE)))*(1+$D$59) -> 0 | E91: =D91*(1+(HLOOKUP(VLOOKUP(D$13,'table années scolaires'!$C$17:$E$27,3,FALSE),'Projection Effectifs'!$S$44:$AC$48,2,FALSE)))*(1+$D$59)*(1+$E$59) -> 0 | F91: =E91*(1+(HLOOKUP(VLOOKUP(E$13,'table années scolaires'!$C$17:$E$27,3,FALSE),'Projection Effectifs'!$S$44:$AC$48,2,FALSE)))*(1+$D$59)*(1+$E$59)*(1+$F$59) -> 0 | G91: =F91*(1+(HLOOKUP(VLOOKUP(F$13,'table années scolaires'!$C$17:$E$27,3,FALSE),'Projection Effectifs'!$S$44:$AC$48,2,FALSE)))*(1+$D$59)*(1+$E$59)*(1+$F$59)*(1+$G$59) -> 0 | H91: =G91*(1+(HLOOKUP(VLOOKUP(G$13,'table années scolaires'!$C$17:$E$27,3,FALSE),'Projection Effectifs'!$S$44:$AC$48,2,FALSE)))*(1+$D$59)*(1+$E$59)*(1+$F$59)*(1+$G$59)*(1+$H$59) -> 0 | I91: =H91*(1+(HLOOKUP(VLOOKUP(H$13,'table années scolaires'!$C$17:$E$27,3,FALSE),'Projection Effectifs'!$S$44:$AC$48,2,FALSE)))*(1+$D$59)*(1+$E$59)*(1+$F$59)*(1+$G$59)*(1+$H$59)*(1+$I$59) -> 0 | J91: =I91*(1+(HLOOKUP(VLOOKUP(I$13,'table années scolaires'!$C$17:$E$27,3,FALSE),'Projection Effectifs'!$S$44:$AC$48,2,FALSE)))*(1+$D$59)*(1+$E$59)*(1+$F$59)*(1+$G$59)*(1+$H$59)*(1+$I$59)*(1+$J$59) -> 0
B92: Equipements individuels (tablettes …) | C92: =VLOOKUP($B92,'Hypothèses '!$B$133:$D$146,3,FALSE)*HLOOKUP(VLOOKUP(C$13,'table années scolaires'!$C$17:$E$27,2,FALSE),'Projection Effectifs'!$S$31:$AC$35,2,FALSE) -> 0 | D92: =C92*(1+(HLOOKUP(VLOOKUP(C$13,'table années scolaires'!$C$17:$E$27,3,FALSE),'Projection Effectifs'!$S$44:$AC$48,2,FALSE)))*(1+$D$59) -> 0 | E92: =D92*(1+(HLOOKUP(VLOOKUP(D$13,'table années scolaires'!$C$17:$E$27,3,FALSE),'Projection Effectifs'!$S$44:$AC$48,2,FALSE)))*(1+$D$59)*(1+$E$59) -> 0 | F92: =E92*(1+(HLOOKUP(VLOOKUP(E$13,'table années scolaires'!$C$17:$E$27,3,FALSE),'Projection Effectifs'!$S$44:$AC$48,2,FALSE)))*(1+$D$59)*(1+$E$59)*(1+$F$59) -> 0 | G92: =F92*(1+(HLOOKUP(VLOOKUP(F$13,'table années scolaires'!$C$17:$E$27,3,FALSE),'Projection Effectifs'!$S$44:$AC$48,2,FALSE)))*(1+$D$59)*(1+$E$59)*(1+$F$59)*(1+$G$59) -> 0 | H92: =G92*(1+(HLOOKUP(VLOOKUP(G$13,'table années scolaires'!$C$17:$E$27,3,FALSE),'Projection Effectifs'!$S$44:$AC$48,2,FALSE)))*(1+$D$59)*(1+$E$59)*(1+$F$59)*(1+$G$59)*(1+$H$59) -> 0 | I92: =H92*(1+(HLOOKUP(VLOOKUP(H$13,'table années scolaires'!$C$17:$E$27,3,FALSE),'Projection Effectifs'!$S$44:$AC$48,2,FALSE)))*(1+$D$59)*(1+$E$59)*(1+$F$59)*(1+$G$59)*(1+$H$59)*(1+$I$59) -> 0 | J92: =I92*(1+(HLOOKUP(VLOOKUP(I$13,'table années scolaires'!$C$17:$E$27,3,FALSE),'Projection Effectifs'!$S$44:$AC$48,2,FALSE)))*(1+$D$59)*(1+$E$59)*(1+$F$59)*(1+$G$59)*(1+$H$59)*(1+$I$59)*(1+$J$59) -> 0
B93: Autres charges variables | C93: =VLOOKUP($B93,'Hypothèses '!$B$133:$D$146,3,FALSE)*HLOOKUP(VLOOKUP(C$13,'table années scolaires'!$C$17:$E$27,2,FALSE),'Projection Effectifs'!$S$31:$AC$35,2,FALSE) -> 0 | D93: =C93*(1+(HLOOKUP(VLOOKUP(C$13,'table années scolaires'!$C$17:$E$27,3,FALSE),'Projection Effectifs'!$S$44:$AC$48,2,FALSE)))*(1+$D$59) -> 0 | E93: =D93*(1+(HLOOKUP(VLOOKUP(D$13,'table années scolaires'!$C$17:$E$27,3,FALSE),'Projection Effectifs'!$S$44:$AC$48,2,FALSE)))*(1+$D$59)*(1+$E$59) -> 0 | F93: =E93*(1+(HLOOKUP(VLOOKUP(E$13,'table années scolaires'!$C$17:$E$27,3,FALSE),'Projection Effectifs'!$S$44:$AC$48,2,FALSE)))*(1+$D$59)*(1+$E$59)*(1+$F$59) -> 0 | G93: =F93*(1+(HLOOKUP(VLOOKUP(F$13,'table années scolaires'!$C$17:$E$27,3,FALSE),'Projection Effectifs'!$S$44:$AC$48,2,FALSE)))*(1+$D$59)*(1+$E$59)*(1+$F$59)*(1+$G$59) -> 0 | H93: =G93*(1+(HLOOKUP(VLOOKUP(G$13,'table années scolaires'!$C$17:$E$27,3,FALSE),'Projection Effectifs'!$S$44:$AC$48,2,FALSE)))*(1+$D$59)*(1+$E$59)*(1+$F$59)*(1+$G$59)*(1+$H$59) -> 0 | I93: =H93*(1+(HLOOKUP(VLOOKUP(H$13,'table années scolaires'!$C$17:$E$27,3,FALSE),'Projection Effectifs'!$S$44:$AC$48,2,FALSE)))*(1+$D$59)*(1+$E$59)*(1+$F$59)*(1+$G$59)*(1+$H$59)*(1+$I$59) -> 0 | J93: =I93*(1+(HLOOKUP(VLOOKUP(I$13,'table années scolaires'!$C$17:$E$27,3,FALSE),'Projection Effectifs'!$S$44:$AC$48,2,FALSE)))*(1+$D$59)*(1+$E$59)*(1+$F$59)*(1+$G$59)*(1+$H$59)*(1+$I$59)*(1+$J$59) -> 0
B94: Charges fixes | C94: =SUM(C95:C103) -> 0 | D94: =SUM(D95:D103) -> 0 | E94: =SUM(E95:E103) -> 0 | F94: =SUM(F95:F103) -> 0 | G94: =SUM(G95:G103) -> 0 | H94: =SUM(H95:H103) -> 0 | I94: =SUM(I95:I103) -> 0 | J94: =SUM(J95:J103) -> 0
B95: Loyer | C95: =VLOOKUP($B95,'Hypothèses '!$B$133:$D$146,3,FALSE)*HLOOKUP(VLOOKUP(C$13,'table années scolaires'!$C$17:$E$27,2,FALSE),'Projection Effectifs'!$S$31:$AC$35,2,FALSE) -> 0 | D95: =VLOOKUP($B95,'Hypothèses '!$B$133:$D$146,3,FALSE)*HLOOKUP(VLOOKUP(D$13,'table années scolaires'!$C$17:$E$27,2,FALSE),'Projection Effectifs'!$S$31:$AC$35,2,FALSE)*(1+$D$59) -> 0 | E95: =VLOOKUP($B95,'Hypothèses '!$B$133:$D$146,3,FALSE)*HLOOKUP(VLOOKUP(E$13,'table années scolaires'!$C$17:$E$27,2,FALSE),'Projection Effectifs'!$S$31:$AC$35,2,FALSE)*(1+$E$59)*(1+$D$59) -> 0 | F95: =VLOOKUP($B95,'Hypothèses '!$B$133:$D$146,3,FALSE)*HLOOKUP(VLOOKUP(F$13,'table années scolaires'!$C$17:$E$27,2,FALSE),'Projection Effectifs'!$S$31:$AC$35,2,FALSE)*(1+$E$59)*(1+$F$59)*(1+$D$59) -> 0 | G95: =VLOOKUP($B95,'Hypothèses '!$B$133:$D$146,3,FALSE)*HLOOKUP(VLOOKUP(G$13,'table années scolaires'!$C$17:$E$27,2,FALSE),'Projection Effectifs'!$S$31:$AC$35,2,FALSE)*(1+$E$59)*(1+$F$59)*(1+$G$59)*(1+$D$59) -> 0 | H95: =VLOOKUP($B95,'Hypothèses '!$B$133:$D$146,3,FALSE)*HLOOKUP(VLOOKUP(H$13,'table années scolaires'!$C$17:$E$27,2,FALSE),'Projection Effectifs'!$S$31:$AC$35,2,FALSE)*(1+$E$59)*(1+$F$59)*(1+$G$59)*(1+$H$59)*(1+$D$59) -> 0 | I95: =VLOOKUP($B95,'Hypothèses '!$B$133:$D$146,3,FALSE)*HLOOKUP(VLOOKUP(I$13,'table années scolaires'!$C$17:$E$27,2,FALSE),'Projection Effectifs'!$S$31:$AC$35,2,FALSE)*(1+$E$59)*(1+$F$59)*(1+$G$59)*(1+$H$59)*(1+$I$59)*(1+$D$59) -> 0 | J95: =VLOOKUP($B95,'Hypothèses '!$B$133:$D$146,3,FALSE)*HLOOKUP(VLOOKUP(J$13,'table années scolaires'!$C$17:$E$27,2,FALSE),'Projection Effectifs'!$S$31:$AC$35,2,FALSE)*(1+$E$59)*(1+$F$59)*(1+$G$59)*(1+$H$59)*(1+$I$59)*(1+$J$59)*(1+$D$59) -> 0
B96: Viabilisation (Eau, énergies) | C96: =VLOOKUP($B96,'Hypothèses '!$B$133:$D$146,3,FALSE)*HLOOKUP(VLOOKUP(C$13,'table années scolaires'!$C$17:$E$27,2,FALSE),'Projection Effectifs'!$S$31:$AC$35,2,FALSE) -> 0 | D96: =VLOOKUP($B96,'Hypothèses '!$B$133:$D$146,3,FALSE)*HLOOKUP(VLOOKUP(D$13,'table années scolaires'!$C$17:$E$27,2,FALSE),'Projection Effectifs'!$S$31:$AC$35,2,FALSE)*(1+$D$59) -> 0 | E96: =VLOOKUP($B96,'Hypothèses '!$B$133:$D$146,3,FALSE)*HLOOKUP(VLOOKUP(E$13,'table années scolaires'!$C$17:$E$27,2,FALSE),'Projection Effectifs'!$S$31:$AC$35,2,FALSE)*(1+$E$59)*(1+$D$59) -> 0 | F96: =VLOOKUP($B96,'Hypothèses '!$B$133:$D$146,3,FALSE)*HLOOKUP(VLOOKUP(F$13,'table années scolaires'!$C$17:$E$27,2,FALSE),'Projection Effectifs'!$S$31:$AC$35,2,FALSE)*(1+$E$59)*(1+$F$59)*(1+$D$59) -> 0 | G96: =VLOOKUP($B96,'Hypothèses '!$B$133:$D$146,3,FALSE)*HLOOKUP(VLOOKUP(G$13,'table années scolaires'!$C$17:$E$27,2,FALSE),'Projection Effectifs'!$S$31:$AC$35,2,FALSE)*(1+$E$59)*(1+$F$59)*(1+$G$59)*(1+$D$59) -> 0 | H96: =VLOOKUP($B96,'Hypothèses '!$B$133:$D$146,3,FALSE)*HLOOKUP(VLOOKUP(H$13,'table années scolaires'!$C$17:$E$27,2,FALSE),'Projection Effectifs'!$S$31:$AC$35,2,FALSE)*(1+$E$59)*(1+$F$59)*(1+$G$59)*(1+$H$59)*(1+$D$59) -> 0 | I96: =VLOOKUP($B96,'Hypothèses '!$B$133:$D$146,3,FALSE)*HLOOKUP(VLOOKUP(I$13,'table années scolaires'!$C$17:$E$27,2,FALSE),'Projection Effectifs'!$S$31:$AC$35,2,FALSE)*(1+$E$59)*(1+$F$59)*(1+$G$59)*(1+$H$59)*(1+$I$59)*(1+$D$59) -> 0 | J96: =VLOOKUP($B96,'Hypothèses '!$B$133:$D$146,3,FALSE)*HLOOKUP(VLOOKUP(J$13,'table années scolaires'!$C$17:$E$27,2,FALSE),'Projection Effectifs'!$S$31:$AC$35,2,FALSE)*(1+$E$59)*(1+$F$59)*(1+$G$59)*(1+$H$59)*(1+$I$59)*(1+$J$59)*(1+$D$59) -> 0
B97: Maintenance courante | C97: =VLOOKUP($B97,'Hypothèses '!$B$133:$D$146,3,FALSE)*HLOOKUP(VLOOKUP(C$13,'table années scolaires'!$C$17:$E$27,2,FALSE),'Projection Effectifs'!$S$31:$AC$35,2,FALSE) -> 0 | D97: =VLOOKUP($B97,'Hypothèses '!$B$133:$D$146,3,FALSE)*HLOOKUP(VLOOKUP(D$13,'table années scolaires'!$C$17:$E$27,2,FALSE),'Projection Effectifs'!$S$31:$AC$35,2,FALSE)*(1+$D$59) -> 0 | E97: =VLOOKUP($B97,'Hypothèses '!$B$133:$D$146,3,FALSE)*HLOOKUP(VLOOKUP(E$13,'table années scolaires'!$C$17:$E$27,2,FALSE),'Projection Effectifs'!$S$31:$AC$35,2,FALSE)*(1+$E$59)*(1+$D$59) -> 0 | F97: =VLOOKUP($B97,'Hypothèses '!$B$133:$D$146,3,FALSE)*HLOOKUP(VLOOKUP(F$13,'table années scolaires'!$C$17:$E$27,2,FALSE),'Projection Effectifs'!$S$31:$AC$35,2,FALSE)*(1+$E$59)*(1+$F$59)*(1+$D$59) -> 0 | G97: =VLOOKUP($B97,'Hypothèses '!$B$133:$D$146,3,FALSE)*HLOOKUP(VLOOKUP(G$13,'table années scolaires'!$C$17:$E$27,2,FALSE),'Projection Effectifs'!$S$31:$AC$35,2,FALSE)*(1+$E$59)*(1+$F$59)*(1+$G$59)*(1+$D$59) -> 0 | H97: =VLOOKUP($B97,'Hypothèses '!$B$133:$D$146,3,FALSE)*HLOOKUP(VLOOKUP(H$13,'table années scolaires'!$C$17:$E$27,2,FALSE),'Projection Effectifs'!$S$31:$AC$35,2,FALSE)*(1+$E$59)*(1+$F$59)*(1+$G$59)*(1+$H$59)*(1+$D$59) -> 0 | I97: =VLOOKUP($B97,'Hypothèses '!$B$133:$D$146,3,FALSE)*HLOOKUP(VLOOKUP(I$13,'table années scolaires'!$C$17:$E$27,2,FALSE),'Projection Effectifs'!$S$31:$AC$35,2,FALSE)*(1+$E$59)*(1+$F$59)*(1+$G$59)*(1+$H$59)*(1+$I$59)*(1+$D$59) -> 0 | J97: =VLOOKUP($B97,'Hypothèses '!$B$133:$D$146,3,FALSE)*HLOOKUP(VLOOKUP(J$13,'table années scolaires'!$C$17:$E$27,2,FALSE),'Projection Effectifs'!$S$31:$AC$35,2,FALSE)*(1+$E$59)*(1+$F$59)*(1+$G$59)*(1+$H$59)*(1+$I$59)*(1+$J$59)*(1+$D$59) -> 0
B98: Aménagements | C98: =VLOOKUP($B98,'Hypothèses '!$B$133:$D$146,3,FALSE)*HLOOKUP(VLOOKUP(C$13,'table années scolaires'!$C$17:$E$27,2,FALSE),'Projection Effectifs'!$S$31:$AC$35,2,FALSE) -> 0 | D98: =VLOOKUP($B98,'Hypothèses '!$B$133:$D$146,3,FALSE)*HLOOKUP(VLOOKUP(D$13,'table années scolaires'!$C$17:$E$27,2,FALSE),'Projection Effectifs'!$S$31:$AC$35,2,FALSE)*(1+$D$59) -> 0 | E98: =VLOOKUP($B98,'Hypothèses '!$B$133:$D$146,3,FALSE)*HLOOKUP(VLOOKUP(E$13,'table années scolaires'!$C$17:$E$27,2,FALSE),'Projection Effectifs'!$S$31:$AC$35,2,FALSE)*(1+$E$59)*(1+$D$59) -> 0 | F98: =VLOOKUP($B98,'Hypothèses '!$B$133:$D$146,3,FALSE)*HLOOKUP(VLOOKUP(F$13,'table années scolaires'!$C$17:$E$27,2,FALSE),'Projection Effectifs'!$S$31:$AC$35,2,FALSE)*(1+$E$59)*(1+$F$59)*(1+$D$59) -> 0 | G98: =VLOOKUP($B98,'Hypothèses '!$B$133:$D$146,3,FALSE)*HLOOKUP(VLOOKUP(G$13,'table années scolaires'!$C$17:$E$27,2,FALSE),'Projection Effectifs'!$S$31:$AC$35,2,FALSE)*(1+$E$59)*(1+$F$59)*(1+$G$59)*(1+$D$59) -> 0 | H98: =VLOOKUP($B98,'Hypothèses '!$B$133:$D$146,3,FALSE)*HLOOKUP(VLOOKUP(H$13,'table années scolaires'!$C$17:$E$27,2,FALSE),'Projection Effectifs'!$S$31:$AC$35,2,FALSE)*(1+$E$59)*(1+$F$59)*(1+$G$59)*(1+$H$59)*(1+$D$59) -> 0 | I98: =VLOOKUP($B98,'Hypothèses '!$B$133:$D$146,3,FALSE)*HLOOKUP(VLOOKUP(I$13,'table années scolaires'!$C$17:$E$27,2,FALSE),'Projection Effectifs'!$S$31:$AC$35,2,FALSE)*(1+$E$59)*(1+$F$59)*(1+$G$59)*(1+$H$59)*(1+$I$59)*(1+$D$59) -> 0 | J98: =VLOOKUP($B98,'Hypothèses '!$B$133:$D$146,3,FALSE)*HLOOKUP(VLOOKUP(J$13,'table années scolaires'!$C$17:$E$27,2,FALSE),'Projection Effectifs'!$S$31:$AC$35,2,FALSE)*(1+$E$59)*(1+$F$59)*(1+$G$59)*(1+$H$59)*(1+$I$59)*(1+$J$59)*(1+$D$59) -> 0
B99: Informatique / Licences / hébergement | C99: =VLOOKUP($B99,'Hypothèses '!$B$133:$D$146,3,FALSE)*HLOOKUP(VLOOKUP(C$13,'table années scolaires'!$C$17:$E$27,2,FALSE),'Projection Effectifs'!$S$31:$AC$35,2,FALSE) -> 0 | D99: =VLOOKUP($B99,'Hypothèses '!$B$133:$D$146,3,FALSE)*HLOOKUP(VLOOKUP(D$13,'table années scolaires'!$C$17:$E$27,2,FALSE),'Projection Effectifs'!$S$31:$AC$35,2,FALSE)*(1+$D$59) -> 0 | E99: =VLOOKUP($B99,'Hypothèses '!$B$133:$D$146,3,FALSE)*HLOOKUP(VLOOKUP(E$13,'table années scolaires'!$C$17:$E$27,2,FALSE),'Projection Effectifs'!$S$31:$AC$35,2,FALSE)*(1+$E$59)*(1+$D$59) -> 0 | F99: =VLOOKUP($B99,'Hypothèses '!$B$133:$D$146,3,FALSE)*HLOOKUP(VLOOKUP(F$13,'table années scolaires'!$C$17:$E$27,2,FALSE),'Projection Effectifs'!$S$31:$AC$35,2,FALSE)*(1+$E$59)*(1+$F$59)*(1+$D$59) -> 0 | G99: =VLOOKUP($B99,'Hypothèses '!$B$133:$D$146,3,FALSE)*HLOOKUP(VLOOKUP(G$13,'table années scolaires'!$C$17:$E$27,2,FALSE),'Projection Effectifs'!$S$31:$AC$35,2,FALSE)*(1+$E$59)*(1+$F$59)*(1+$G$59)*(1+$D$59) -> 0 | H99: =VLOOKUP($B99,'Hypothèses '!$B$133:$D$146,3,FALSE)*HLOOKUP(VLOOKUP(H$13,'table années scolaires'!$C$17:$E$27,2,FALSE),'Projection Effectifs'!$S$31:$AC$35,2,FALSE)*(1+$E$59)*(1+$F$59)*(1+$G$59)*(1+$H$59)*(1+$D$59) -> 0 | I99: =VLOOKUP($B99,'Hypothèses '!$B$133:$D$146,3,FALSE)*HLOOKUP(VLOOKUP(I$13,'table années scolaires'!$C$17:$E$27,2,FALSE),'Projection Effectifs'!$S$31:$AC$35,2,FALSE)*(1+$E$59)*(1+$F$59)*(1+$G$59)*(1+$H$59)*(1+$I$59)*(1+$D$59) -> 0 | J99: =VLOOKUP($B99,'Hypothèses '!$B$133:$D$146,3,FALSE)*HLOOKUP(VLOOKUP(J$13,'table années scolaires'!$C$17:$E$27,2,FALSE),'Projection Effectifs'!$S$31:$AC$35,2,FALSE)*(1+$E$59)*(1+$F$59)*(1+$G$59)*(1+$H$59)*(1+$I$59)*(1+$J$59)*(1+$D$59) -> 0
B100: Sécurité | C100: =VLOOKUP($B100,'Hypothèses '!$B$133:$D$146,3,FALSE)*HLOOKUP(VLOOKUP(C$13,'table années scolaires'!$C$17:$E$27,2,FALSE),'Projection Effectifs'!$S$31:$AC$35,2,FALSE) -> 0 | D100: =VLOOKUP($B100,'Hypothèses '!$B$133:$D$146,3,FALSE)*HLOOKUP(VLOOKUP(D$13,'table années scolaires'!$C$17:$E$27,2,FALSE),'Projection Effectifs'!$S$31:$AC$35,2,FALSE)*(1+$D$59) -> 0 | E100: =VLOOKUP($B100,'Hypothèses '!$B$133:$D$146,3,FALSE)*HLOOKUP(VLOOKUP(E$13,'table années scolaires'!$C$17:$E$27,2,FALSE),'Projection Effectifs'!$S$31:$AC$35,2,FALSE)*(1+$E$59)*(1+$D$59) -> 0 | F100: =VLOOKUP($B100,'Hypothèses '!$B$133:$D$146,3,FALSE)*HLOOKUP(VLOOKUP(F$13,'table années scolaires'!$C$17:$E$27,2,FALSE),'Projection Effectifs'!$S$31:$AC$35,2,FALSE)*(1+$E$59)*(1+$F$59)*(1+$D$59) -> 0 | G100: =VLOOKUP($B100,'Hypothèses '!$B$133:$D$146,3,FALSE)*HLOOKUP(VLOOKUP(G$13,'table années scolaires'!$C$17:$E$27,2,FALSE),'Projection Effectifs'!$S$31:$AC$35,2,FALSE)*(1+$E$59)*(1+$F$59)*(1+$G$59)*(1+$D$59) -> 0 | H100: =VLOOKUP($B100,'Hypothèses '!$B$133:$D$146,3,FALSE)*HLOOKUP(VLOOKUP(H$13,'table années scolaires'!$C$17:$E$27,2,FALSE),'Projection Effectifs'!$S$31:$AC$35,2,FALSE)*(1+$E$59)*(1+$F$59)*(1+$G$59)*(1+$H$59)*(1+$D$59) -> 0 | I100: =VLOOKUP($B100,'Hypothèses '!$B$133:$D$146,3,FALSE)*HLOOKUP(VLOOKUP(I$13,'table années scolaires'!$C$17:$E$27,2,FALSE),'Projection Effectifs'!$S$31:$AC$35,2,FALSE)*(1+$E$59)*(1+$F$59)*(1+$G$59)*(1+$H$59)*(1+$I$59)*(1+$D$59) -> 0 | J100: =VLOOKUP($B100,'Hypothèses '!$B$133:$D$146,3,FALSE)*HLOOKUP(VLOOKUP(J$13,'table années scolaires'!$C$17:$E$27,2,FALSE),'Projection Effectifs'!$S$31:$AC$35,2,FALSE)*(1+$E$59)*(1+$F$59)*(1+$G$59)*(1+$H$59)*(1+$I$59)*(1+$J$59)*(1+$D$59) -> 0
B101: Communication | C101: =VLOOKUP($B101,'Hypothèses '!$B$133:$D$146,3,FALSE)*HLOOKUP(VLOOKUP(C$13,'table années scolaires'!$C$17:$E$27,2,FALSE),'Projection Effectifs'!$S$31:$AC$35,2,FALSE) -> 0 | D101: =VLOOKUP($B101,'Hypothèses '!$B$133:$D$146,3,FALSE)*HLOOKUP(VLOOKUP(D$13,'table années scolaires'!$C$17:$E$27,2,FALSE),'Projection Effectifs'!$S$31:$AC$35,2,FALSE)*(1+$D$59) -> 0 | E101: =VLOOKUP($B101,'Hypothèses '!$B$133:$D$146,3,FALSE)*HLOOKUP(VLOOKUP(E$13,'table années scolaires'!$C$17:$E$27,2,FALSE),'Projection Effectifs'!$S$31:$AC$35,2,FALSE)*(1+$E$59)*(1+$D$59) -> 0 | F101: =VLOOKUP($B101,'Hypothèses '!$B$133:$D$146,3,FALSE)*HLOOKUP(VLOOKUP(F$13,'table années scolaires'!$C$17:$E$27,2,FALSE),'Projection Effectifs'!$S$31:$AC$35,2,FALSE)*(1+$E$59)*(1+$F$59)*(1+$D$59) -> 0 | G101: =VLOOKUP($B101,'Hypothèses '!$B$133:$D$146,3,FALSE)*HLOOKUP(VLOOKUP(G$13,'table années scolaires'!$C$17:$E$27,2,FALSE),'Projection Effectifs'!$S$31:$AC$35,2,FALSE)*(1+$E$59)*(1+$F$59)*(1+$G$59)*(1+$D$59) -> 0 | H101: =VLOOKUP($B101,'Hypothèses '!$B$133:$D$146,3,FALSE)*HLOOKUP(VLOOKUP(H$13,'table années scolaires'!$C$17:$E$27,2,FALSE),'Projection Effectifs'!$S$31:$AC$35,2,FALSE)*(1+$E$59)*(1+$F$59)*(1+$G$59)*(1+$H$59)*(1+$D$59) -> 0 | I101: =VLOOKUP($B101,'Hypothèses '!$B$133:$D$146,3,FALSE)*HLOOKUP(VLOOKUP(I$13,'table années scolaires'!$C$17:$E$27,2,FALSE),'Projection Effectifs'!$S$31:$AC$35,2,FALSE)*(1+$E$59)*(1+$F$59)*(1+$G$59)*(1+$H$59)*(1+$I$59)*(1+$D$59) -> 0 | J101: =VLOOKUP($B101,'Hypothèses '!$B$133:$D$146,3,FALSE)*HLOOKUP(VLOOKUP(J$13,'table années scolaires'!$C$17:$E$27,2,FALSE),'Projection Effectifs'!$S$31:$AC$35,2,FALSE)*(1+$E$59)*(1+$F$59)*(1+$G$59)*(1+$H$59)*(1+$I$59)*(1+$J$59)*(1+$D$59) -> 0
B102: Administratif | C102: =VLOOKUP($B102,'Hypothèses '!$B$133:$D$146,3,FALSE)*HLOOKUP(VLOOKUP(C$13,'table années scolaires'!$C$17:$E$27,2,FALSE),'Projection Effectifs'!$S$31:$AC$35,2,FALSE) -> 0 | D102: =VLOOKUP($B102,'Hypothèses '!$B$133:$D$146,3,FALSE)*HLOOKUP(VLOOKUP(D$13,'table années scolaires'!$C$17:$E$27,2,FALSE),'Projection Effectifs'!$S$31:$AC$35,2,FALSE)*(1+$D$59) -> 0 | E102: =VLOOKUP($B102,'Hypothèses '!$B$133:$D$146,3,FALSE)*HLOOKUP(VLOOKUP(E$13,'table années scolaires'!$C$17:$E$27,2,FALSE),'Projection Effectifs'!$S$31:$AC$35,2,FALSE)*(1+$E$59)*(1+$D$59) -> 0 | F102: =VLOOKUP($B102,'Hypothèses '!$B$133:$D$146,3,FALSE)*HLOOKUP(VLOOKUP(F$13,'table années scolaires'!$C$17:$E$27,2,FALSE),'Projection Effectifs'!$S$31:$AC$35,2,FALSE)*(1+$E$59)*(1+$F$59)*(1+$D$59) -> 0 | G102: =VLOOKUP($B102,'Hypothèses '!$B$133:$D$146,3,FALSE)*HLOOKUP(VLOOKUP(G$13,'table années scolaires'!$C$17:$E$27,2,FALSE),'Projection Effectifs'!$S$31:$AC$35,2,FALSE)*(1+$E$59)*(1+$F$59)*(1+$G$59)*(1+$D$59) -> 0 | H102: =VLOOKUP($B102,'Hypothèses '!$B$133:$D$146,3,FALSE)*HLOOKUP(VLOOKUP(H$13,'table années scolaires'!$C$17:$E$27,2,FALSE),'Projection Effectifs'!$S$31:$AC$35,2,FALSE)*(1+$E$59)*(1+$F$59)*(1+$G$59)*(1+$H$59)*(1+$D$59) -> 0 | I102: =VLOOKUP($B102,'Hypothèses '!$B$133:$D$146,3,FALSE)*HLOOKUP(VLOOKUP(I$13,'table années scolaires'!$C$17:$E$27,2,FALSE),'Projection Effectifs'!$S$31:$AC$35,2,FALSE)*(1+$E$59)*(1+$F$59)*(1+$G$59)*(1+$H$59)*(1+$I$59)*(1+$D$59) -> 0 | J102: =VLOOKUP($B102,'Hypothèses '!$B$133:$D$146,3,FALSE)*HLOOKUP(VLOOKUP(J$13,'table années scolaires'!$C$17:$E$27,2,FALSE),'Projection Effectifs'!$S$31:$AC$35,2,FALSE)*(1+$E$59)*(1+$F$59)*(1+$G$59)*(1+$H$59)*(1+$I$59)*(1+$J$59)*(1+$D$59) -> 0
B103: Autres dépenses | C103: =VLOOKUP($B103,'Hypothèses '!$B$133:$D$146,3,FALSE)*HLOOKUP(VLOOKUP(C$13,'table années scolaires'!$C$17:$E$27,2,FALSE),'Projection Effectifs'!$S$31:$AC$35,2,FALSE) -> 0 | D103: =VLOOKUP($B103,'Hypothèses '!$B$133:$D$146,3,FALSE)*HLOOKUP(VLOOKUP(D$13,'table années scolaires'!$C$17:$E$27,2,FALSE),'Projection Effectifs'!$S$31:$AC$35,2,FALSE)*(1+$D$59) -> 0 | E103: =VLOOKUP($B103,'Hypothèses '!$B$133:$D$146,3,FALSE)*HLOOKUP(VLOOKUP(E$13,'table années scolaires'!$C$17:$E$27,2,FALSE),'Projection Effectifs'!$S$31:$AC$35,2,FALSE)*(1+$E$59)*(1+$D$59) -> 0 | F103: =VLOOKUP($B103,'Hypothèses '!$B$133:$D$146,3,FALSE)*HLOOKUP(VLOOKUP(F$13,'table années scolaires'!$C$17:$E$27,2,FALSE),'Projection Effectifs'!$S$31:$AC$35,2,FALSE)*(1+$E$59)*(1+$F$59)*(1+$D$59) -> 0 | G103: =VLOOKUP($B103,'Hypothèses '!$B$133:$D$146,3,FALSE)*HLOOKUP(VLOOKUP(G$13,'table années scolaires'!$C$17:$E$27,2,FALSE),'Projection Effectifs'!$S$31:$AC$35,2,FALSE)*(1+$E$59)*(1+$F$59)*(1+$G$59)*(1+$D$59) -> 0 | H103: =VLOOKUP($B103,'Hypothèses '!$B$133:$D$146,3,FALSE)*HLOOKUP(VLOOKUP(H$13,'table années scolaires'!$C$17:$E$27,2,FALSE),'Projection Effectifs'!$S$31:$AC$35,2,FALSE)*(1+$E$59)*(1+$F$59)*(1+$G$59)*(1+$H$59)*(1+$D$59) -> 0 | I103: =VLOOKUP($B103,'Hypothèses '!$B$133:$D$146,3,FALSE)*HLOOKUP(VLOOKUP(I$13,'table années scolaires'!$C$17:$E$27,2,FALSE),'Projection Effectifs'!$S$31:$AC$35,2,FALSE)*(1+$E$59)*(1+$F$59)*(1+$G$59)*(1+$H$59)*(1+$I$59)*(1+$D$59) -> 0 | J103: =VLOOKUP($B103,'Hypothèses '!$B$133:$D$146,3,FALSE)*HLOOKUP(VLOOKUP(J$13,'table années scolaires'!$C$17:$E$27,2,FALSE),'Projection Effectifs'!$S$31:$AC$35,2,FALSE)*(1+$E$59)*(1+$F$59)*(1+$G$59)*(1+$H$59)*(1+$I$59)*(1+$J$59)*(1+$D$59) -> 0
B104: Charges réseau AEFE | C104: =SUM(C105:C107) -> 0 | D104: =SUM(D105:D107) -> 0 | E104: =SUM(E105:E107) -> 0 | F104: =SUM(F105:F107) -> #N/A | G104: =SUM(G105:G107) -> #N/A | H104: =SUM(H105:H107) -> #N/A | I104: =SUM(I105:I107) -> #N/A | J104: =SUM(J105:J107) -> #N/A
B105: PFC | C105: =IF(HLOOKUP(VLOOKUP(C$13,'table années scolaires'!$C$17:$E$27,2,FALSE),'Hypothèses '!$C$12:$K$16,2,FALSE)="non",0,IF('Hypothèses '!$C$7="conventionné",(C$29+C$31)*0.06*0.94,0)) -> 0 | D105: =IF(HLOOKUP(VLOOKUP(D$13,'table années scolaires'!$C$17:$E$27,2,FALSE),'Hypothèses '!$C$12:$K$16,2,FALSE)="non",0,IF('Hypothèses '!$C$7="conventionné",(D$29+D$31)*0.06*0.94,0)) -> 0 | E105: =IF(HLOOKUP(VLOOKUP(E$13,'table années scolaires'!$C$17:$E$27,2,FALSE),'Hypothèses '!$C$12:$K$16,2,FALSE)="non",0,IF('Hypothèses '!$C$7="conventionné",(E$29+E$31)*0.06*0.94,0)) -> 0 | F105: =IF(HLOOKUP(VLOOKUP(F$13,'table années scolaires'!$C$17:$E$27,2,FALSE),'Hypothèses '!$C$12:$K$16,2,FALSE)="non",0,IF('Hypothèses '!$C$7="conventionné",(F$29+F$31)*0.06*0.94,0)) -> 696540 | G105: =IF(HLOOKUP(VLOOKUP(G$13,'table années scolaires'!$C$17:$E$27,2,FALSE),'Hypothèses '!$C$12:$K$16,2,FALSE)="non",0,IF('Hypothèses '!$C$7="conventionné",(G$29+G$31)*0.06*0.94,0)) -> 879840 | H105: =IF(HLOOKUP(VLOOKUP(H$13,'table années scolaires'!$C$17:$E$27,2,FALSE),'Hypothèses '!$C$12:$K$16,2,FALSE)="non",0,IF('Hypothèses '!$C$7="conventionné",(H$29+H$31)*0.06*0.94,0)) -> 1099800 | I105: =IF(HLOOKUP(VLOOKUP(I$13,'table années scolaires'!$C$17:$E$27,2,FALSE),'Hypothèses '!$C$12:$K$16,2,FALSE)="non",0,IF('Hypothèses '!$C$7="conventionné",(I$29+I$31)*0.06*0.94,0)) -> 1319760 | J105: =IF(HLOOKUP(VLOOKUP(J$13,'table années scolaires'!$C$17:$E$27,2,FALSE),'Hypothèses '!$C$12:$K$16,2,FALSE)="non",0,IF('Hypothèses '!$C$7="conventionné",(J$29+J$31)*0.06*0.94,0)) -> 1319760
B106: Frais fonctionnement | C106: =IF(HLOOKUP(VLOOKUP(C$13,'table années scolaires'!$C$17:$E$27,2,FALSE),'Hypothèses '!$C$12:$K$16,2,FALSE)="non",0,(C$29+C$31)*C108) -> 0 | D106: =IF(HLOOKUP(VLOOKUP(D$13,'table années scolaires'!$C$17:$E$27,2,FALSE),'Hypothèses '!$C$12:$K$16,2,FALSE)="non",0,(D$29+D$31)*D108) -> 0 | E106: =IF(HLOOKUP(VLOOKUP(E$13,'table années scolaires'!$C$17:$E$27,2,FALSE),'Hypothèses '!$C$12:$K$16,2,FALSE)="non",0,(E$29+E$31)*E108) -> 0 | F106: =IF(HLOOKUP(VLOOKUP(F$13,'table années scolaires'!$C$17:$E$27,2,FALSE),'Hypothèses '!$C$12:$K$16,2,FALSE)="non",0,(F$29+F$31)*F108) -> 247000 | G106: =IF(HLOOKUP(VLOOKUP(G$13,'table années scolaires'!$C$17:$E$27,2,FALSE),'Hypothèses '!$C$12:$K$16,2,FALSE)="non",0,(G$29+G$31)*G108) -> 312000 | H106: =IF(HLOOKUP(VLOOKUP(H$13,'table années scolaires'!$C$17:$E$27,2,FALSE),'Hypothèses '!$C$12:$K$16,2,FALSE)="non",0,(H$29+H$31)*H108) -> 390000 | I106: =IF(HLOOKUP(VLOOKUP(I$13,'table années scolaires'!$C$17:$E$27,2,FALSE),'Hypothèses '!$C$12:$K$16,2,FALSE)="non",0,(I$29+I$31)*I108) -> 468000 | J106: =IF(HLOOKUP(VLOOKUP(J$13,'table années scolaires'!$C$17:$E$27,2,FALSE),'Hypothèses '!$C$12:$K$16,2,FALSE)="non",0,(J$29+J$31)*J108) -> 468000
B107: Formation continue | C107: =IF(HLOOKUP(VLOOKUP(C$13,'table années scolaires'!$C$17:$E$27,2,FALSE),'Hypothèses '!$C$12:$K$16,2,FALSE)="non",0,C109*C85) -> 0 | D107: =IF(HLOOKUP(VLOOKUP(D$13,'table années scolaires'!$C$17:$E$27,2,FALSE),'Hypothèses '!$C$12:$K$16,2,FALSE)="non",0,D109*C85) -> 0 | E107: =IF(HLOOKUP(VLOOKUP(E$13,'table années scolaires'!$C$17:$E$27,2,FALSE),'Hypothèses '!$C$12:$K$16,2,FALSE)="non",0,E109*D85) -> 0 | F107: =IF(HLOOKUP(VLOOKUP(F$13,'table années scolaires'!$C$17:$E$27,2,FALSE),'Hypothèses '!$C$12:$K$16,2,FALSE)="non",0,F109*E85) -> #N/A | G107: =IF(HLOOKUP(VLOOKUP(G$13,'table années scolaires'!$C$17:$E$27,2,FALSE),'Hypothèses '!$C$12:$K$16,2,FALSE)="non",0,G109*F85) -> #N/A | H107: =IF(HLOOKUP(VLOOKUP(H$13,'table années scolaires'!$C$17:$E$27,2,FALSE),'Hypothèses '!$C$12:$K$16,2,FALSE)="non",0,H109*G85) -> #N/A | I107: =IF(HLOOKUP(VLOOKUP(I$13,'table années scolaires'!$C$17:$E$27,2,FALSE),'Hypothèses '!$C$12:$K$16,2,FALSE)="non",0,I109*H85) -> #N/A | J107: =IF(HLOOKUP(VLOOKUP(J$13,'table années scolaires'!$C$17:$E$27,2,FALSE),'Hypothèses '!$C$12:$K$16,2,FALSE)="non",0,J109*I85) -> #N/A
B108: Taux frais fonctionnement | C108: =IF(HLOOKUP(VLOOKUP(C$13,'table années scolaires'!$C$17:$E$27,2,FALSE),'Hypothèses '!$C$12:$K$16,2,FALSE)="non",0,2%) -> 0 | D108: =IF(HLOOKUP(VLOOKUP(D$13,'table années scolaires'!$C$17:$E$27,2,FALSE),'Hypothèses '!$C$12:$K$16,2,FALSE)="non",0,2%) -> 0 | E108: =IF(HLOOKUP(VLOOKUP(E$13,'table années scolaires'!$C$17:$E$27,2,FALSE),'Hypothèses '!$C$12:$K$16,2,FALSE)="non",0,2%) -> 0 | F108: =IF(HLOOKUP(VLOOKUP(F$13,'table années scolaires'!$C$17:$E$27,2,FALSE),'Hypothèses '!$C$12:$K$16,2,FALSE)="non",0,2%) -> 0.02 | G108: =IF(HLOOKUP(VLOOKUP(G$13,'table années scolaires'!$C$17:$E$27,2,FALSE),'Hypothèses '!$C$12:$K$16,2,FALSE)="non",0,2%) -> 0.02 | H108: =IF(HLOOKUP(VLOOKUP(H$13,'table années scolaires'!$C$17:$E$27,2,FALSE),'Hypothèses '!$C$12:$K$16,2,FALSE)="non",0,2%) -> 0.02 | I108: =IF(HLOOKUP(VLOOKUP(I$13,'table années scolaires'!$C$17:$E$27,2,FALSE),'Hypothèses '!$C$12:$K$16,2,FALSE)="non",0,2%) -> 0.02 | J108: =IF(HLOOKUP(VLOOKUP(J$13,'table années scolaires'!$C$17:$E$27,2,FALSE),'Hypothèses '!$C$12:$K$16,2,FALSE)="non",0,2%) -> 0.02
B109: Taux FC | C109: =IF(HLOOKUP(VLOOKUP(C$13,'table années scolaires'!$C$17:$E$27,2,FALSE),'Hypothèses '!$C$12:$K$16,2,FALSE)="non",0,1%) -> 0 | D109: =IF(HLOOKUP(VLOOKUP(D$13,'table années scolaires'!$C$17:$E$27,2,FALSE),'Hypothèses '!$C$12:$K$16,2,FALSE)="non",0,1%) -> 0 | E109: =IF(HLOOKUP(VLOOKUP(E$13,'table années scolaires'!$C$17:$E$27,2,FALSE),'Hypothèses '!$C$12:$K$16,2,FALSE)="non",0,1%) -> 0 | F109: =IF(HLOOKUP(VLOOKUP(F$13,'table années scolaires'!$C$17:$E$27,2,FALSE),'Hypothèses '!$C$12:$K$16,2,FALSE)="non",0,1%) -> 0.01 | G109: =IF(HLOOKUP(VLOOKUP(G$13,'table années scolaires'!$C$17:$E$27,2,FALSE),'Hypothèses '!$C$12:$K$16,2,FALSE)="non",0,1%) -> 0.01 | H109: =IF(HLOOKUP(VLOOKUP(H$13,'table années scolaires'!$C$17:$E$27,2,FALSE),'Hypothèses '!$C$12:$K$16,2,FALSE)="non",0,1%) -> 0.01 | I109: =IF(HLOOKUP(VLOOKUP(I$13,'table années scolaires'!$C$17:$E$27,2,FALSE),'Hypothèses '!$C$12:$K$16,2,FALSE)="non",0,1%) -> 0.01 | J109: =IF(HLOOKUP(VLOOKUP(J$13,'table années scolaires'!$C$17:$E$27,2,FALSE),'Hypothèses '!$C$12:$K$16,2,FALSE)="non",0,1%) -> 0.01
A110: ELEMENTAIRE | B110: Charges Elémentaire | C110: =C111+C115+C120+C130 -> #N/A | D110: =D111+D115+D120+D130 -> #N/A | E110: =E111+E115+E120+E130 -> #N/A | F110: =F111+F115+F120+F130 -> #N/A | G110: =G111+G115+G120+G130 -> #N/A | H110: =H111+H115+H120+H130 -> #N/A | I110: =I111+I115+I120+I130 -> #N/A | J110: =J111+J115+J120+J130 -> #N/A
B111: Masse salariale | C111: =SUM(C112:C114) -> #N/A | D111: =SUM(D112:D114) -> #N/A | E111: =SUM(E112:E114) -> #N/A | F111: =SUM(F112:F114) -> #N/A | G111: =SUM(G112:G114) -> #N/A | H111: =SUM(H112:H114) -> #N/A | I111: =SUM(I112:I114) -> #N/A | J111: =SUM(J112:J114) -> #N/A
B112: Masse salariale Enseignants PDL | C112: ='Calcul MS Personnels'!D138 -> 0 | D112: ='Calcul MS Personnels'!E138 -> 0 | E112: ='Calcul MS Personnels'!F138 -> 0 | F112: ='Calcul MS Personnels'!G138 -> 0 | G112: ='Calcul MS Personnels'!H138 -> 0 | H112: ='Calcul MS Personnels'!I138 -> 0 | I112: ='Calcul MS Personnels'!J138 -> 0 | J112: ='Calcul MS Personnels'!K138 -> 0
B113: Masse salariale Enseignants Détachés | C113: ='Calcul MS Personnels'!D137 -> 0 | D113: ='Calcul MS Personnels'!E137 -> 0 | E113: ='Calcul MS Personnels'!F137 -> 0 | F113: ='Calcul MS Personnels'!G137 -> 0 | G113: ='Calcul MS Personnels'!H137 -> 0 | H113: ='Calcul MS Personnels'!I137 -> 0 | I113: ='Calcul MS Personnels'!J137 -> 0 | J113: ='Calcul MS Personnels'!K137 -> 0
B114: Masse salariale non enseignants | C114: =SUM('Calcul MS Personnels'!D120:D127)+SUM('Calcul MS Personnels'!D129:D135) -> #N/A | D114: =SUM('Calcul MS Personnels'!E120:E127)+SUM('Calcul MS Personnels'!E129:E135) -> #N/A | E114: =SUM('Calcul MS Personnels'!F120:F127)+SUM('Calcul MS Personnels'!F129:F135) -> #N/A | F114: =SUM('Calcul MS Personnels'!G120:G127)+SUM('Calcul MS Personnels'!G129:G135) -> #N/A | G114: =SUM('Calcul MS Personnels'!H120:H127)+SUM('Calcul MS Personnels'!H129:H135) -> #N/A | H114: =SUM('Calcul MS Personnels'!I120:I127)+SUM('Calcul MS Personnels'!I129:I135) -> #N/A | I114: =SUM('Calcul MS Personnels'!J120:J127)+SUM('Calcul MS Personnels'!J129:J135) -> #N/A | J114: =SUM('Calcul MS Personnels'!K120:K127)+SUM('Calcul MS Personnels'!K129:K135) -> #N/A
B115: Charges variables | C115: =SUM(C116:C119) -> 0 | D115: =SUM(D116:D119) -> 0 | E115: =SUM(E116:E119) -> 0 | F115: =SUM(F116:F119) -> 0 | G115: =SUM(G116:G119) -> 0 | H115: =SUM(H116:H119) -> 0 | I115: =SUM(I116:I119) -> 0 | J115: =SUM(J116:J119) -> 0
...

Sheet Compte Résultat Euro
A2: COMPTE DE RESULTAT PREVISIONNEL
A3: Monnaie Locale
C4: ='Hypothèses '!$C$9 -> 2024 | D4: =C4+1 -> 2025 | E4: =D4+1 -> 2026 | F4: =E4+1 -> 2027 | G4: =F4+1 -> 2028 | H4: =G4+1 -> 2029 | I4: =H4+1 -> 2030 | J4: =I4+1 -> 2031
A5: RESULTAT OPERATIONNEL | C5: =HLOOKUP(C$4,'Hypothèses '!$C$34:$K$38,5,FALSE) -> 0.25 | D5: =HLOOKUP(D$4,'Hypothèses '!$C$34:$K$38,5,FALSE) -> 0.25 | E5: =HLOOKUP(E$4,'Hypothèses '!$C$34:$K$38,5,FALSE) -> 0.25 | F5: =HLOOKUP(F$4,'Hypothèses '!$C$34:$K$38,5,FALSE) -> 0.25 | G5: =HLOOKUP(G$4,'Hypothèses '!$C$34:$K$38,5,FALSE) -> 0.25 | H5: =HLOOKUP(H$4,'Hypothèses '!$C$34:$K$38,5,FALSE) -> 0.25 | I5: =HLOOKUP(I$4,'Hypothèses '!$C$34:$K$38,5,FALSE) -> 0.25 | J5: =HLOOKUP(J$4,'Hypothèses '!$C$34:$K$38,5,FALSE) -> 0.25
A6: GLOBAL | C6: =C15-C60 -> #N/A | D6: =D15-D60 -> #N/A | E6: =E15-E60 -> #N/A | F6: =F15-F60 -> #N/A | G6: =G15-G60 -> #N/A | H6: =H15-H60 -> #N/A | I6: =I15-I60 -> #N/A | J6: =J15-J60 -> #N/A
A7: MATERNELLE | C7: =C24-C84 -> #N/A | D7: =D24-D84 -> #N/A | E7: =E24-E84 -> #N/A | F7: =F24-F84 -> #N/A | G7: =G24-G84 -> #N/A | H7: =H24-H84 -> #N/A | I7: =I24-I84 -> #N/A | J7: =J24-J84 -> #N/A
A8: ELEMENTAIRE | C8: =C32-C110 -> #N/A | D8: =D32-D110 -> #N/A | E8: =E32-E110 -> #N/A | F8: =F32-F110 -> #N/A | G8: =G32-G110 -> #N/A | H8: =H32-H110 -> #N/A | I8: =I32-I110 -> #N/A | J8: =J32-J110 -> #N/A
A9: COLLEGE | C9: =C40-C136 -> #N/A | D9: =D40-D136 -> #N/A | E9: =E40-E136 -> #N/A | F9: =F40-F136 -> #N/A | G9: =G40-G136 -> #N/A | H9: =H40-H136 -> #N/A | I9: =I40-I136 -> #N/A | J9: =J40-J136 -> #N/A
A10: LYCEE | C10: =C48-C162 -> #N/A | D10: =D48-D162 -> #N/A | E10: =E48-E162 -> #N/A | F10: =F48-F162 -> #N/A | G10: =G48-G162 -> #N/A | H10: =H48-H162 -> #N/A | I10: =I48-I162 -> #N/A | J10: =J48-J162 -> #N/A
A13: PRODUITS | C13: ='Hypothèses '!$C$9 -> 2024 | D13: =C13+1 -> 2025 | E13: =D13+1 -> 2026 | F13: =E13+1 -> 2027 | G13: =F13+1 -> 2028 | H13: =G13+1 -> 2029 | I13: =H13+1 -> 2030 | J13: =I13+1 -> 2031
A14: produits liés à la scolarité, hors services de restauration, de transport, d'activités extra scolaires et d'examen
A15: GLOBAL | C15: =SUM(C20:C23) -> 0 | D15: =SUM(D20:D23) -> 0 | E15: =SUM(E20:E23) -> 51406250 | F15: =SUM(F20:F23) -> 49628750 | G15: =SUM(G20:G23) -> 48921250 | H15: =SUM(H20:H23) -> 48995000 | I15: =SUM(I20:I23) -> 48920000 | J15: =SUM(J20:J23) -> 48386250
B16: taux nouveaux inscrits | C16: ='Compte Résultat ML'!C16 -> 0 | D16: ='Compte Résultat ML'!D16 -> 0.1 | E16: ='Compte Résultat ML'!E16 -> 0.1 | F16: ='Compte Résultat ML'!F16 -> 0.1 | G16: ='Compte Résultat ML'!G16 -> 0.1 | H16: ='Compte Résultat ML'!H16 -> 0.1 | I16: ='Compte Résultat ML'!I16 -> 0.1 | J16: ='Compte Résultat ML'!J16 -> 0.1
B17: Taus abattement | C17: ='Compte Résultat ML'!C17 -> 0 | D17: ='Compte Résultat ML'!D17 -> 0.06 | E17: ='Compte Résultat ML'!E17 -> 0.06 | F17: ='Compte Résultat ML'!F17 -> 0.06 | G17: ='Compte Résultat ML'!G17 -> 0.06 | H17: ='Compte Résultat ML'!H17 -> 0.06 | I17: ='Compte Résultat ML'!I17 -> 0.06 | J17: ='Compte Résultat ML'!J17 -> 0.06
B18: DPI | C18: ='Compte Résultat ML'!C18*C$5 -> 0 | D18: ='Compte Résultat ML'!D18*D$5 -> 0 | E18: ='Compte Résultat ML'!E18*E$5 -> 125000 | F18: ='Compte Résultat ML'!F18*F$5 -> 125000 | G18: ='Compte Résultat ML'!G18*G$5 -> 125000 | H18: ='Compte Résultat ML'!H18*H$5 -> 125000 | I18: ='Compte Résultat ML'!I18*I$5 -> 125000 | J18: ='Compte Résultat ML'!J18*J$5 -> 125000
B19: Frais Réinscption | C19: ='Compte Résultat ML'!C19*C$5 -> 0 | D19: ='Compte Résultat ML'!D19*D$5 -> 0 | E19: ='Compte Résultat ML'!E19*E$5 -> 16250 | F19: ='Compte Résultat ML'!F19*F$5 -> 16250 | G19: ='Compte Résultat ML'!G19*G$5 -> 16250 | H19: ='Compte Résultat ML'!H19*H$5 -> 16250 | I19: ='Compte Résultat ML'!I19*I$5 -> 16250 | J19: ='Compte Résultat ML'!J19*J$5 -> 16250
B20: Frais scolarité | C20: ='Compte Résultat ML'!C20*C$5 -> 0 | D20: ='Compte Résultat ML'!D20*D$5 -> 0 | E20: ='Compte Résultat ML'!E20*E$5 -> 0 | F20: ='Compte Résultat ML'!F20*F$5 -> 0 | G20: ='Compte Résultat ML'!G20*G$5 -> 0 | H20: ='Compte Résultat ML'!H20*H$5 -> 0 | I20: ='Compte Résultat ML'!I20*I$5 -> 0 | J20: ='Compte Résultat ML'!J20*J$5 -> 0
B21: DPI | C21: ='Compte Résultat ML'!C21*C$5 -> 0 | D21: ='Compte Résultat ML'!D21*D$5 -> 0 | E21: ='Compte Résultat ML'!E21*E$5 -> 22562500 | F21: ='Compte Résultat ML'!F21*F$5 -> 21857500 | G21: ='Compte Résultat ML'!G21*G$5 -> 21312500 | H21: ='Compte Résultat ML'!H21*H$5 -> 21272500 | I21: ='Compte Résultat ML'!I21*I$5 -> 21295000 | J21: ='Compte Résultat ML'!J21*J$5 -> 21135000
B22: Frais Réinscription | C22: ='Compte Résultat ML'!C22*C$5 -> 0 | D22: ='Compte Résultat ML'!D22*D$5 -> 0 | E22: ='Compte Résultat ML'!E22*E$5 -> 28843750 | F22: ='Compte Résultat ML'!F22*F$5 -> 27771250 | G22: ='Compte Résultat ML'!G22*G$5 -> 27608750 | H22: ='Compte Résultat ML'!H22*H$5 -> 27722500 | I22: ='Compte Résultat ML'!I22*I$5 -> 27625000 | J22: ='Compte Résultat ML'!J22*J$5 -> 27251250
B23: Subvention spécifique (hors AEFE) | C23: ='Compte Résultat ML'!C23*C$5 -> 0 | D23: ='Compte Résultat ML'!D23*D$5 -> 0 | E23: ='Compte Résultat ML'!E23*E$5 -> 0 | F23: ='Compte Résultat ML'!F23*F$5 -> 0 | G23: ='Compte Résultat ML'!G23*G$5 -> 0 | H23: ='Compte Résultat ML'!H23*H$5 -> 0 | I23: ='Compte Résultat ML'!I23*I$5 -> 0 | J23: ='Compte Résultat ML'!J23*J$5 -> 0
A24: MATERNELLE | C24: =SUM(C29:C31) -> 0 | D24: =SUM(D29:D31) -> 0 | E24: =SUM(E29:E31) -> 6332500 | F24: =SUM(F29:F31) -> 5552500 | G24: =SUM(G29:G31) -> 6525000 | H24: =SUM(H29:H31) -> 8175000 | I24: =SUM(I29:I31) -> 9900000 | J24: =SUM(J29:J31) -> 10350000
B25: Effectifs AS N-1 | C25: ='Compte Résultat ML'!C25 -> 0 | D25: ='Compte Résultat ML'!D25 -> 293 | E25: ='Compte Résultat ML'!E25 -> 272 | F25: ='Compte Résultat ML'!F25 -> 202 | G25: ='Compte Résultat ML'!G25 -> 190 | H25: ='Compte Résultat ML'!H25 -> 240 | I25: ='Compte Résultat ML'!I25 -> 300 | J25: ='Compte Résultat ML'!J25 -> 360
B26: Effectifs AS N | C26: ='Compte Résultat ML'!C26 -> 293 | D26: ='Compte Résultat ML'!D26 -> 272 | E26: ='Compte Résultat ML'!E26 -> 202 | F26: ='Compte Résultat ML'!F26 -> 190 | G26: ='Compte Résultat ML'!G26 -> 240 | H26: ='Compte Résultat ML'!H26 -> 300 | I26: ='Compte Résultat ML'!I26 -> 360 | J26: ='Compte Résultat ML'!J26 -> 360
B27: Frais scol AS N-1 | C27: ='Compte Résultat ML'!C27*C$5 -> 0 | D27: ='Compte Résultat ML'!D27*D$5 -> 0 | E27: ='Compte Résultat ML'!E27*E$5 -> 0 | F27: ='Compte Résultat ML'!F27*F$5 -> 0 | G27: ='Compte Résultat ML'!G27*G$5 -> 0 | H27: ='Compte Résultat ML'!H27*H$5 -> 0 | I27: ='Compte Résultat ML'!I27*I$5 -> 0 | J27: ='Compte Résultat ML'!J27*J$5 -> 0
B28: Frais scol AS N | C28: ='Compte Résultat ML'!C28*C$5 -> 0 | D28: ='Compte Résultat ML'!D28*D$5 -> 0 | E28: ='Compte Résultat ML'!E28*E$5 -> 0 | F28: ='Compte Résultat ML'!F28*F$5 -> 0 | G28: ='Compte Résultat ML'!G28*G$5 -> 0 | H28: ='Compte Résultat ML'!H28*H$5 -> 0 | I28: ='Compte Résultat ML'!I28*I$5 -> 0 | J28: ='Compte Résultat ML'!J28*J$5 -> 0
B29: Frais scolarité | C29: ='Compte Résultat ML'!C29*C$5 -> 0 | D29: ='Compte Résultat ML'!D29*D$5 -> 0 | E29: ='Compte Résultat ML'!E29*E$5 -> 0 | F29: ='Compte Résultat ML'!F29*F$5 -> 0 | G29: ='Compte Résultat ML'!G29*G$5 -> 0 | H29: ='Compte Résultat ML'!H29*H$5 -> 0 | I29: ='Compte Résultat ML'!I29*I$5 -> 0 | J29: ='Compte Résultat ML'!J29*J$5 -> 0
B30: DPI | C30: ='Compte Résultat ML'!C30*C$5 -> 0 | D30: ='Compte Résultat ML'!D30*D$5 -> 0 | E30: ='Compte Résultat ML'!E30*E$5 -> 3050000 | F30: ='Compte Résultat ML'!F30*F$5 -> 2465000 | G30: ='Compte Résultat ML'!G30*G$5 -> 2625000 | H30: ='Compte Résultat ML'!H30*H$5 -> 3300000 | I30: ='Compte Résultat ML'!I30*I$5 -> 4050000 | J30: ='Compte Résultat ML'!J30*J$5 -> 4500000
B31: Frais Réinscription | C31: ='Compte Résultat ML'!C31*C$5 -> 0 | D31: ='Compte Résultat ML'!D31*D$5 -> 0 | E31: ='Compte Résultat ML'!E31*E$5 -> 3282500 | F31: ='Compte Résultat ML'!F31*F$5 -> 3087500 | G31: ='Compte Résultat ML'!G31*G$5 -> 3900000 | H31: ='Compte Résultat ML'!H31*H$5 -> 4875000 | I31: ='Compte Résultat ML'!I31*I$5 -> 5850000 | J31: ='Compte Résultat ML'!J31*J$5 -> 5850000
A32: ELEMENTAIRE | C32: =SUM(C37:C39) -> 0 | D32: =SUM(D37:D39) -> 0 | E32: =SUM(E37:E39) -> 18766250 | F32: =SUM(F37:F39) -> 17583750 | G32: =SUM(G37:G39) -> 15740000 | H32: =SUM(H37:H39) -> 13877500 | I32: =SUM(I37:I39) -> 11825000 | J32: =SUM(J37:J39) -> 11057500
B33: Effectifs AS N-1 | C33: ='Compte Résultat ML'!C33 -> 0 | D33: ='Compte Résultat ML'!D33 -> 651 | E33: ='Compte Résultat ML'!E33 -> 652 | F33: ='Compte Résultat ML'!F33 -> 653 | G33: ='Compte Résultat ML'!G33 -> 597 | H33: ='Compte Résultat ML'!H33 -> 530 | I33: ='Compte Résultat ML'!I33 -> 466 | J33: ='Compte Résultat ML'!J33 -> 392
B34: Effectifs AS N | C34: ='Compte Résultat ML'!C34 -> 651 | D34: ='Compte Résultat ML'!D34 -> 652 | E34: ='Compte Résultat ML'!E34 -> 653 | F34: ='Compte Résultat ML'!F34 -> 597 | G34: ='Compte Résultat ML'!G34 -> 530 | H34: ='Compte Résultat ML'!H34 -> 466 | I34: ='Compte Résultat ML'!I34 -> 392 | J34: ='Compte Résultat ML'!J34 -> 382
B35: Frais scol AS N-1 | C35: ='Compte Résultat ML'!C35*C$5 -> 0 | D35: ='Compte Résultat ML'!D35*D$5 -> 0 | E35: ='Compte Résultat ML'!E35*E$5 -> 0 | F35: ='Compte Résultat ML'!F35*F$5 -> 0 | G35: ='Compte Résultat ML'!G35*G$5 -> 0 | H35: ='Compte Résultat ML'!H35*H$5 -> 0 | I35: ='Compte Résultat ML'!I35*I$5 -> 0 | J35: ='Compte Résultat ML'!J35*J$5 -> 0
B36: Frais scol AS N | C36: ='Compte Résultat ML'!C36*C$5 -> 0 | D36: ='Compte Résultat ML'!D36*D$5 -> 0 | E36: ='Compte Résultat ML'!E36*E$5 -> 0 | F36: ='Compte Résultat ML'!F36*F$5 -> 0 | G36: ='Compte Résultat ML'!G36*G$5 -> 0 | H36: ='Compte Résultat ML'!H36*H$5 -> 0 | I36: ='Compte Résultat ML'!I36*I$5 -> 0 | J36: ='Compte Résultat ML'!J36*J$5 -> 0
B37: Frais scolarité | C37: ='Compte Résultat ML'!C37*C$5 -> 0 | D37: ='Compte Résultat ML'!D37*D$5 -> 0 | E37: ='Compte Résultat ML'!E37*E$5 -> 0 | F37: ='Compte Résultat ML'!F37*F$5 -> 0 | G37: ='Compte Résultat ML'!G37*G$5 -> 0 | H37: ='Compte Résultat ML'!H37*H$5 -> 0 | I37: ='Compte Résultat ML'!I37*I$5 -> 0 | J37: ='Compte Résultat ML'!J37*J$5 -> 0
B38: DPI | C38: ='Compte Résultat ML'!C38*C$5 -> 0 | D38: ='Compte Résultat ML'!D38*D$5 -> 0 | E38: ='Compte Résultat ML'!E38*E$5 -> 8155000 | F38: ='Compte Résultat ML'!F38*F$5 -> 7882500 | G38: ='Compte Résultat ML'!G38*G$5 -> 7127500 | H38: ='Compte Résultat ML'!H38*H$5 -> 6305000 | I38: ='Compte Résultat ML'!I38*I$5 -> 5455000 | J38: ='Compte Résultat ML'!J38*J$5 -> 4850000
B39: Frais Réinscription | C39: ='Compte Résultat ML'!C39*C$5 -> 0 | D39: ='Compte Résultat ML'!D39*D$5 -> 0 | E39: ='Compte Résultat ML'!E39*E$5 -> 10611250 | F39: ='Compte Résultat ML'!F39*F$5 -> 9701250 | G39: ='Compte Résultat ML'!G39*G$5 -> 8612500 | H39: ='Compte Résultat ML'!H39*H$5 -> 7572500 | I39: ='Compte Résultat ML'!I39*I$5 -> 6370000 | J39: ='Compte Résultat ML'!J39*J$5 -> 6207500
A40: COLLEGE | C40: =SUM(C45:C47) -> 0 | D40: =SUM(D45:D47) -> 0 | E40: =SUM(E45:E47) -> 15721250 | F40: =SUM(F45:F47) -> 15883750 | G40: =SUM(G45:G47) -> 15771250 | H40: =SUM(H45:H47) -> 15110000 | I40: =SUM(I45:I47) -> 14998750 | J40: =SUM(J45:J47) -> 15078750
B41: Effectifs AS N-1 | C41: ='Compte Résultat ML'!C41 -> 0 | D41: ='Compte Résultat ML'!D41 -> 499 | E41: ='Compte Résultat ML'!E41 -> 535 | F41: ='Compte Résultat ML'!F41 -> 551 | G41: ='Compte Résultat ML'!G41 -> 553 | H41: ='Compte Résultat ML'!H41 -> 547 | I41: ='Compte Résultat ML'!I41 -> 518 | J41: ='Compte Résultat ML'!J41 -> 523
B42: Effectifs AS N | C42: ='Compte Résultat ML'!C42 -> 499 | D42: ='Compte Résultat ML'!D42 -> 535 | E42: ='Compte Résultat ML'!E42 -> 551 | F42: ='Compte Résultat ML'!F42 -> 553 | G42: ='Compte Résultat ML'!G42 -> 547 | H42: ='Compte Résultat ML'!H42 -> 518 | I42: ='Compte Résultat ML'!I42 -> 523 | J42: ='Compte Résultat ML'!J42 -> 525
B43: Frais scol AS N-1 | C43: ='Compte Résultat ML'!C43*C$5 -> 0 | D43: ='Compte Résultat ML'!D43*D$5 -> 0 | E43: ='Compte Résultat ML'!E43*E$5 -> 0 | F43: ='Compte Résultat ML'!F43*F$5 -> 0 | G43: ='Compte Résultat ML'!G43*G$5 -> 0 | H43: ='Compte Résultat ML'!H43*H$5 -> 0 | I43: ='Compte Résultat ML'!I43*I$5 -> 0 | J43: ='Compte Résultat ML'!J43*J$5 -> 0
B44: Frais scol AS N | C44: ='Compte Résultat ML'!C44*C$5 -> 0 | D44: ='Compte Résultat ML'!D44*D$5 -> 0 | E44: ='Compte Résultat ML'!E44*E$5 -> 0 | F44: ='Compte Résultat ML'!F44*F$5 -> 0 | G44: ='Compte Résultat ML'!G44*G$5 -> 0 | H44: ='Compte Résultat ML'!H44*H$5 -> 0 | I44: ='Compte Résultat ML'!I44*I$5 -> 0 | J44: ='Compte Résultat ML'!J44*J$5 -> 0
B45: Frais scolarité | C45: ='Compte Résultat ML'!C45*C$5 -> 0 | D45: ='Compte Résultat ML'!D45*D$5 -> 0 | E45: ='Compte Résultat ML'!E45*E$5 -> 0 | F45: ='Compte Résultat ML'!F45*F$5 -> 0 | G45: ='Compte Résultat ML'!G45*G$5 -> 0 | H45: ='Compte Résultat ML'!H45*H$5 -> 0 | I45: ='Compte Résultat ML'!I45*I$5 -> 0 | J45: ='Compte Résultat ML'!J45*J$5 -> 0
B46: DPI | C46: ='Compte Résultat ML'!C46*C$5 -> 0 | D46: ='Compte Résultat ML'!D46*D$5 -> 0 | E46: ='Compte Résultat ML'!E46*E$5 -> 6767500 | F46: ='Compte Résultat ML'!F46*F$5 -> 6897500 | G46: ='Compte Résultat ML'!G46*G$5 -> 6882500 | H46: ='Compte Résultat ML'!H46*H$5 -> 6692500 | I46: ='Compte Résultat ML'!I46*I$5 -> 6500000 | J46: ='Compte Résultat ML'!J46*J$5 -> 6547500
B47: Frais Réinscription | C47: ='Compte Résultat ML'!C47*C$5 -> 0 | D47: ='Compte Résultat ML'!D47*D$5 -> 0 | E47: ='Compte Résultat ML'!E47*E$5 -> 8953750 | F47: ='Compte Résultat ML'!F47*F$5 -> 8986250 | G47: ='Compte Résultat ML'!G47*G$5 -> 8888750 | H47: ='Compte Résultat ML'!H47*H$5 -> 8417500 | I47: ='Compte Résultat ML'!I47*I$5 -> 8498750 | J47: ='Compte Résultat ML'!J47*J$5 -> 8531250
A48: LYCEE | C48: =SUM(C53:C55) -> 0 | D48: =SUM(D53:D55) -> 0 | E48: =SUM(E53:E55) -> 10586250 | F48: =SUM(F53:F55) -> 10608750 | G48: =SUM(G53:G55) -> 10885000 | H48: =SUM(H53:H55) -> 11832500 | I48: =SUM(I53:I55) -> 12196250 | J48: =SUM(J53:J55) -> 11900000
B49: Effectifs AS N-1 | C49: ='Compte Résultat ML'!C49 -> 0 | D49: ='Compte Résultat ML'!D49 -> 353 | E49: ='Compte Résultat ML'!E49 -> 366 | F49: ='Compte Résultat ML'!F49 -> 369 | G49: ='Compte Résultat ML'!G49 -> 369 | H49: ='Compte Résultat ML'!H49 -> 382 | I49: ='Compte Résultat ML'!I49 -> 422 | J49: ='Compte Résultat ML'!J49 -> 425
B50: Effectifs AS N | C50: ='Compte Résultat ML'!C50 -> 353 | D50: ='Compte Résultat ML'!D50 -> 366 | E50: ='Compte Résultat ML'!E50 -> 369 | F50: ='Compte Résultat ML'!F50 -> 369 | G50: ='Compte Résultat ML'!G50 -> 382 | H50: ='Compte Résultat ML'!H50 -> 422 | I50: ='Compte Résultat ML'!I50 -> 425 | J50: ='Compte Résultat ML'!J50 -> 410
