Workbook

Sheet Number of class 2025-26
A1: École Française Internationale de Riyad (EFIR) - Classes by Level
A3: Cycle | B3: Level | C3: Number of students | D3: Number of Classes
A4: Maternelle | B4: Petite Section (PS) | C4: 65 | D4: 3
A5: Maternelle | B5: Moyenne Section (MS) | C5: 77 | D5: 3
A6: Maternelle | B6: Grande Section (GS) | C6: 124 | D6: 5
A7: Élémentaire | B7: CP (Cours Préparatoire) | C7: 126 | D7: 6
A8: Élémentaire | B8: CE1 | C8: 118 | D8: 5
A9: Élémentaire | B9: CE2 | C9: 132 | D9: 6
A10: Élémentaire | B10: CM1 | C10: 121 | D10: 5
A11: Élémentaire | B11: CM2 | C11: 121 | D11: 5
A12: Collège | B12: 6ème | C12: 151 | D12: 6
A13: Collège | B13: 5ème | C13: 139 | D13: 6
A14: Collège | B14: 4ème | C14: 120 | D14: 5
A15: Collège | B15: 3ème | C15: 103 | D15: 4
... A18: Lycée | B18: Terminale | C18: 111 | D18: 4
A20: SUMMARY BY CYCLE
A21: Maternelle (Kindergarten) | C21: =SUM(C4:C6) -> 266 | D21: =SUM(D4:D6) -> 11
A22: Élémentaire (Elementary) | C22: =SUM(C7:C11) -> 618 | D22: =SUM(D7:D11) -> 27
A23: Collège (Middle School) | C23: =SUM(C12:C15) -> 513 | D23: =SUM(D12:D15) -> 21
A24: Lycée (High School) | C24: =SUM(C16:C18) -> 356 | D24: =SUM(D16:D18) -> 14
A26: TOTAL CLASSES | C26: =SUM(C21:C24) -> 1753 | D26: =SUM(D21:D24) -> 73
A27: Source: EFIR Structure Pédagogique — https://www.efiriyad.com/structure-pedagogique/

Sheet Teacher Requirements
A1: EFIR — Teacher Staffing Requirements Matrix 2025-26
A2: Purpose: Calculate FTE requirements per teacher profile. Blue cells = editable assumptions.
A4: PARAMETERS
A5: Statutory Hours / Week | C5: Certifié | D5: 18 | E5: h/week | G5: HSA (Supp. Hrs) | H5: 0 | I5: h/week
C6: Prof. des Écoles (PE) | D6: 24 | E6: h/week | G6: Effective Certifié | H6: =$D$5+$H$5 -> 18 | I6: h/week
A7: LV2/LVB Student Split | C7: % Arabic | D7: 0.5 | E7: % German | F7: 0.1 | G7: % Spanish | H7: 0.4 | I7: =IF(D7+F7+H7=1,"✓","≠100%!") -> ✓
G8: MATERNELLE | J8: ÉLÉMENTAIRE | O8: COLLÈGE | S8: LYCÉE | V8: COMPUTATION
A9: Category | B9: Type | C9: Subject / Matière | D9: Teacher Profile | E9: Groups / Class | G9: PS | H9: MS | I9: GS | J9: CP | K9: CE1 | L9: CE2 | M9: CM1 | N9: CM2 | O9: 6ème | P9: 5ème | Q9: 4ème | R9: 3ème | S9: 2nde | T9: 1ère | U9: Tle | V9: Total Hrs/Wk | W9: Statutory | X9: FTE Req. | Y9: Headcount
C10: Number of Classes | G10: 3 | H10: 3 | I10: 5 | J10: 6 | K10: 5 | L10: 6 | M10: 5 | N10: 5 | O10: 6 | P10: 6 | Q10: 5 | R10: 4 | S10: 5 | T10: 5 | U10: 4
A11: BLOCK 1 — MATERNELLE / PRIMAIRE
A12: HOMEROOM
A13: Homeroom | C13: Homeroom Maternelle | D13: Professeur des écoles (PE) | E13: 1 | G13: 24 | H13: 24 | I13: 24 | V13: {=SUMPRODUCT(IF(ISNUMBER(G13:U13),G13:U13,0),$G$10:$U$10)*E13} -> 264 | W13: =IF(ISNUMBER(SEARCH("PE",D13)),$D$6,$D$5) -> 24 | X13: =SUM($G$10:$I$10) -> 11 | Y13: =X13 -> 11
A14: Homeroom | B14: Homeroom | C14: ASEM Maternelle | D14: ASEM | E14: 1 | G14: 24 | H14: 24 | I14: 24 | V14: {=SUMPRODUCT(IF(ISNUMBER(G14:U14),G14:U14,0),$G$10:$U$10)*E14} -> 264 | W14: =$D$6 -> 24 | X14: =SUM($G$10:$I$10) -> 11 | Y14: =X14 -> 11
B15: Homeroom | C15: ⬛ Subtotal Maternelle | V15: =V13+V14 -> 528 | W15: =$D$6 -> 24 | X15: =X13 -> 11 | Y15: =X15 -> 11
A16: Homeroom | C16: Homeroom Élémentaire | D16: Professeur des écoles (PE) | E16: 1 | J16: 24 | K16: 24 | L16: 24 | M16: 24 | N16: 24 | V16: {=SUMPRODUCT(IF(ISNUMBER(G16:U16),G16:U16,0),$G$10:$U$10)*E16} -> 648 | W16: =IF(ISNUMBER(SEARCH("PE",D16)),$D$6,$D$5) -> 24 | X16: =SUM($J$10:$N$10) -> 27 | Y16: =X16 -> 27
B17: Homeroom | C17: ⬛ Subtotal Élémentaire | V17: =V16 -> 648 | W17: =$D$6 -> 24 | X17: =X16 -> 27 | Y17: =X16 -> 27
A18: ARABIC LANGUAGE
A19: ▸ Primaire | C19: Arabe (Arabophone group) | D19: Enseignant Arabe | E19: 1 | G19: 2 | H19: 2 | I19: 2.67 | J19: 2 | K19: 2 | L19: 2 | M19: 2 | N19: 2 | V19: {=SUMPRODUCT(IF(ISNUMBER(G19:U19),G19:U19,0),$G$10:$U$10)*E19} -> 79.35 | W19: =IF(ISNUMBER(SEARCH("PE",D19)),$D$6,$D$5) -> 18 | X19: =IF(V19=0,"",V19/$H$6) -> 4.4083333 | Y19: =IF(X19="","",ROUNDUP(X19,0)) -> 5
A20: ▸ Primaire | B20: Core | C20: Arabe (Non-Arabophone group) | D20: Enseignant Arabe | E20: 1 | I20: 2.67 | J20: 2 | K20: 2 | L20: 2 | M20: 2 | N20: 2 | V20: {=SUMPRODUCT(IF(ISNUMBER(G20:U20),G20:U20,0),$G$10:$U$10)*E20} -> 67.35 | W20: =IF(ISNUMBER(SEARCH("PE",D20)),$D$6,$D$5) -> 18 | X20: =IF(V20=0,"",V20/$H$6) -> 3.7416667 | Y20: =IF(X20="","",ROUNDUP(X20,0)) -> 4
B21: Core | C21: ⬛ Subtotal Primaire (shared pool) | V21: =V19+V20 -> 146.7 | W21: =$D$5 -> 18 | X21: =IF(V21=0,"",V21/$H$6) -> 8.15 | Y21: =IF(X21="","",ROUNDUP(X21,0)) -> 9
A22: ENGLISH LANGUAGE
A23: ▸ Primaire | C23: Anglais (Primaire) | D23: Enseignant Anglais Primaire | E23: 1 | I23: 0.67 | J23: 1.5 | K23: 1.5 | L23: 1.5 | M23: 1.5 | N23: 1.5 | V23: {=SUMPRODUCT(IF(ISNUMBER(G23:U23),G23:U23,0),$G$10:$U$10)*E23} -> 43.85 | W23: =IF(ISNUMBER(SEARCH("PE",D23)),$D$6,$D$5) -> 18 | X23: =IF(V23=0,"",V23/$H$6) -> 2.4361111 | Y23: =IF(X23="","",ROUNDUP(X23,0)) -> 3
B24: Core | C24: ⬛ Subtotal Primaire (shared pool) | V24: =V23 -> 43.85 | W24: =$D$5 -> 18 | X24: =IF(V24=0,"",V24/$H$6) -> 2.4361111 | Y24: =IF(X24="","",ROUNDUP(X24,0)) -> 3
A26: BLOCK 2 — COLLÈGE / LYCÉE
A27: CORE SUBJECTS — TRONC COMMUN
A28: FRENCH LANGUAGE
A29: Français | B29: Core | C29: Français | D29: Certifié Lettres | E29: 1 | O29: {=IFERROR(INDEX(Curriculum_Detail!H:H,MATCH(1,(Curriculum_Detail!D:D="6e")*(Curriculum_Detail!F:F="Français")*(Curriculum_Detail!E:E="Core"),0)),"")} -> 4.5 | P29: {=IFERROR(INDEX(Curriculum_Detail!H:H,MATCH(1,(Curriculum_Detail!D:D="5e")*(Curriculum_Detail!F:F="Français")*(Curriculum_Detail!E:E="Core"),0)),"")} -> 4.5 | Q29: {=IFERROR(INDEX(Curriculum_Detail!H:H,MATCH(1,(Curriculum_Detail!D:D="4e")*(Curriculum_Detail!F:F="Français")*(Curriculum_Detail!E:E="Core"),0)),"")} -> 4.5 | R29: {=IFERROR(INDEX(Curriculum_Detail!H:H,MATCH(1,(Curriculum_Detail!D:D="3e")*(Curriculum_Detail!F:F="Français")*(Curriculum_Detail!E:E="Core"),0)),"")} -> 4 | S29: {=IFERROR(INDEX(Curriculum_Detail!H:H,MATCH(1,(Curriculum_Detail!D:D="Seconde")*(Curriculum_Detail!F:F="Français")*(Curriculum_Detail!E:E="Core"),0)),"")} -> 4 | T29: {=IFERROR(INDEX(Curriculum_Detail!H:H,MATCH(1,(Curriculum_Detail!D:D="Première")*(Curriculum_Detail!F:F="Français")*(Curriculum_Detail!E:E="Core"),0)),"")} -> 4 | V29: {=SUMPRODUCT(IF(ISNUMBER(G29:U29),G29:U29,0),$G$10:$U$10)*E29} -> 132.5 | W29: =IF(ISNUMBER(SEARCH("PE",D29)),$D$6,$D$5) -> 18 | X29: =IF(V29=0,"",V29/$H$6) -> 7.3611111 | Y29: =IF(X29="","",ROUNDUP(X29,0)) -> 8
A30: Français | B30: Core | C30: Philosophie | D30: Certifié Philosophie | E30: 1 | U30: {=IFERROR(INDEX(Curriculum_Detail!H:H,MATCH(1,(Curriculum_Detail!D:D="Terminale")*(Curriculum_Detail!F:F="Philosophie")*(Curriculum_Detail!E:E="Core"),0)),"")} -> 4 | V30: {=SUMPRODUCT(IF(ISNUMBER(G30:U30),G30:U30,0),$G$10:$U$10)*E30} -> 16 | W30: =IF(ISNUMBER(SEARCH("PE",D30)),$D$6,$D$5) -> 18 | X30: =IF(V30=0,"",V30/$H$6) -> 0.88888889 | Y30: =IF(X30="","",ROUNDUP(X30,0)) -> 1
A31: Français | B31: Specialty | C31: Spé. HLP (1ère) | D31: Certifié Lettres | E31: 1 | T31: {=IFERROR(INDEX(Curriculum_Detail!H:H,MATCH(1,(Curriculum_Detail!D:D="Première")*(Curriculum_Detail!F:F="Humanités, littérature et philosophie")*(Curriculum_Detail!E:E="Specialty"),0)),0)} -> 4 | V31: =T31*E31 -> 4 | W31: =$D$5 -> 18 | X31: =IF(V31=0,"",V31/$H$6) -> 0.22222222 | Y31: =IF(X31="","",ROUNDUP(X31,0)) -> 1
A32: Français | B32: Specialty | C32: Spé. HLP (Tle) | D32: Certifié Philosophie | F32: 1 | U32: {=IFERROR(INDEX(Curriculum_Detail!H:H,MATCH(1,(Curriculum_Detail!D:D="Terminale")*(Curriculum_Detail!F:F="Humanités, littérature et philosophie")*(Curriculum_Detail!E:E="Specialty"),0)),0)} -> 6 | V32: =U32*F32 -> 6 | W32: =$D$5 -> 18 | X32: =IF(V32=0,"",V32/$H$6) -> 0.33333333 | Y32: =IF(X32="","",ROUNDUP(X32,0)) -> 1
A33: MATHEMATICS
A34: Maths | B34: Core | C34: Mathématiques | D34: Certifié Maths | E34: 1 | O34: {=IFERROR(INDEX(Curriculum_Detail!H:H,MATCH(1,(Curriculum_Detail!D:D="6e")*(Curriculum_Detail!F:F="Mathématiques")*(Curriculum_Detail!E:E="Core"),0)),"")} -> 4.5 | P34: {=IFERROR(INDEX(Curriculum_Detail!H:H,MATCH(1,(Curriculum_Detail!D:D="5e")*(Curriculum_Detail!F:F="Mathématiques")*(Curriculum_Detail!E:E="Core"),0)),"")} -> 3.5 | Q34: {=IFERROR(INDEX(Curriculum_Detail!H:H,MATCH(1,(Curriculum_Detail!D:D="4e")*(Curriculum_Detail!F:F="Mathématiques")*(Curriculum_Detail!E:E="Core"),0)),"")} -> 3.5 | R34: {=IFERROR(INDEX(Curriculum_Detail!H:H,MATCH(1,(Curriculum_Detail!D:D="3e")*(Curriculum_Detail!F:F="Mathématiques")*(Curriculum_Detail!E:E="Core"),0)),"")} -> 3.5 | S34: {=IFERROR(INDEX(Curriculum_Detail!H:H,MATCH(1,(Curriculum_Detail!D:D="Seconde")*(Curriculum_Detail!F:F="Mathématiques")*(Curriculum_Detail!E:E="Core"),0)),"")} -> 4 | V34: {=SUMPRODUCT(IF(ISNUMBER(G34:U34),G34:U34,0),$G$10:$U$10)*E34} -> 99.5 | W34: =IF(ISNUMBER(SEARCH("PE",D34)),$D$6,$D$5) -> 18 | X34: =IF(V34=0,"",V34/$H$6) -> 5.5277778 | Y34: =IF(X34="","",ROUNDUP(X34,0)) -> 6
A35: Maths | B35: Core | C35: Soutien / approfondissement | D35: Certifié Maths | E35: 1 | O35: {=IFERROR(INDEX(Curriculum_Detail!H:H,MATCH(1,(Curriculum_Detail!D:D="6e")*(Curriculum_Detail!F:F="Soutien / approfondissement en français ou mathématiques")*(Curriculum_Detail!E:E="Core"),0)),"")} -> 1 | V35: {=SUMPRODUCT(IF(ISNUMBER(G35:U35),G35:U35,0),$G$10:$U$10)*E35} -> 6 | W35: =IF(ISNUMBER(SEARCH("PE",D35)),$D$6,$D$5) -> 18 | X35: =IF(V35=0,"",V35/$H$6) -> 0.33333333 | Y35: =IF(X35="","",ROUNDUP(X35,0)) -> 1
A36: Maths | B36: Specialty | C36: Spé. Mathématiques | D36: Certifié Maths | E36: 2 | F36: 2 | T36: {=IFERROR(INDEX(Curriculum_Detail!H:H,MATCH(1,(Curriculum_Detail!D:D="Première")*(Curriculum_Detail!F:F="Mathématiques")*(Curriculum_Detail!E:E="Specialty"),0)),0)} -> 4 | U36: {=IFERROR(INDEX(Curriculum_Detail!H:H,MATCH(1,(Curriculum_Detail!D:D="Terminale")*(Curriculum_Detail!F:F="Mathématiques")*(Curriculum_Detail!E:E="Specialty"),0)),0)} -> 6 | V36: =T36*E36+U36*F36 -> 20 | W36: =$D$5 -> 18 | X36: =IF(V36=0,"",V36/$H$6) -> 1.1111111 | Y36: =IF(X36="","",ROUNDUP(X36,0)) -> 2
A37: Maths | B37: Option | C37: Maths Complémentaires (opt.) | D37: Certifié Maths | E37: 0 | F37: 4 | T37: 0 | U37: 3 | V37: =T37*E37+U37*F37 -> 12 | W37: =$D$5 -> 18 | X37: =IF(V37=0,"",V37/$H$6) -> 0.66666667 | Y37: =IF(X37="","",ROUNDUP(X37,0)) -> 1
A38: Maths | B38: Option | C38: Maths Expertes (opt.) | D38: Certifié Maths | E38: 0 | F38: 2 | T38: 0 | U38: 3 | V38: =T38*E38+U38*F38 -> 6 | W38: =$D$5 -> 18 | X38: =IF(V38=0,"",V38/$H$6) -> 0.33333333 | Y38: =IF(X38="","",ROUNDUP(X38,0)) -> 1
A39: HISTORY, GEOGRAPHY & CIVICS
A40: HG-EMC | B40: Core | C40: Histoire-Géographie | D40: Certifié Hist-Géo | E40: 1 | O40: {=IFERROR(INDEX(Curriculum_Detail!H:H,MATCH(1,(Curriculum_Detail!D:D="6e")*(Curriculum_Detail!F:F="Histoire-géographie")*(Curriculum_Detail!E:E="Core"),0)),"")} -> 2.5 | P40: {=IFERROR(INDEX(Curriculum_Detail!H:H,MATCH(1,(Curriculum_Detail!D:D="5e")*(Curriculum_Detail!F:F="Histoire-géographie")*(Curriculum_Detail!E:E="Core"),0)),"")} -> 2.5 | Q40: {=IFERROR(INDEX(Curriculum_Detail!H:H,MATCH(1,(Curriculum_Detail!D:D="4e")*(Curriculum_Detail!F:F="Histoire-géographie")*(Curriculum_Detail!E:E="Core"),0)),"")} -> 2.5 | R40: {=IFERROR(INDEX(Curriculum_Detail!H:H,MATCH(1,(Curriculum_Detail!D:D="3e")*(Curriculum_Detail!F:F="Histoire-géographie")*(Curriculum_Detail!E:E="Core"),0)),"")} -> 3 | S40: {=IFERROR(INDEX(Curriculum_Detail!H:H,MATCH(1,(Curriculum_Detail!D:D="Seconde")*(Curriculum_Detail!F:F="Histoire-géographie")*(Curriculum_Detail!E:E="Core"),0)),"")} -> 3 | T40: {=IFERROR(INDEX(Curriculum_Detail!H:H,MATCH(1,(Curriculum_Detail!D:D="Première")*(Curriculum_Detail!F:F="Histoire-géographie")*(Curriculum_Detail!E:E="Core"),0)),"")} -> 3 | U40: {=IFERROR(INDEX(Curriculum_Detail!H:H,MATCH(1,(Curriculum_Detail!D:D="Terminale")*(Curriculum_Detail!F:F="Histoire-géographie")*(Curriculum_Detail!E:E="Core"),0)),"")} -> 3 | V40: {=SUMPRODUCT(IF(ISNUMBER(G40:U40),G40:U40,0),$G$10:$U$10)*E40} -> 96.5 | W40: =IF(ISNUMBER(SEARCH("PE",D40)),$D$6,$D$5) -> 18 | X40: =IF(V40=0,"",V40/$H$6) -> 5.3611111 | Y40: =IF(X40="","",ROUNDUP(X40,0)) -> 6
A41: HG-EMC | B41: Core | C41: Enseignement moral et civique | D41: Certifié EMC | E41: 1 | O41: {=IFERROR(INDEX(Curriculum_Detail!H:H,MATCH(1,(Curriculum_Detail!D:D="6e")*(Curriculum_Detail!F:F="Enseignement moral et civique")*(Curriculum_Detail!E:E="Core"),0)),"")} -> 0.5 | P41: {=IFERROR(INDEX(Curriculum_Detail!H:H,MATCH(1,(Curriculum_Detail!D:D="5e")*(Curriculum_Detail!F:F="Enseignement moral et civique")*(Curriculum_Detail!E:E="Core"),0)),"")} -> 0.5 | Q41: {=IFERROR(INDEX(Curriculum_Detail!H:H,MATCH(1,(Curriculum_Detail!D:D="4e")*(Curriculum_Detail!F:F="Enseignement moral et civique")*(Curriculum_Detail!E:E="Core"),0)),"")} -> 0.5 | R41: {=IFERROR(INDEX(Curriculum_Detail!H:H,MATCH(1,(Curriculum_Detail!D:D="3e")*(Curriculum_Detail!F:F="Enseignement moral et civique")*(Curriculum_Detail!E:E="Core"),0)),"")} -> 0.5 | S41: {=IFERROR(INDEX(Curriculum_Detail!H:H,MATCH(1,(Curriculum_Detail!D:D="Seconde")*(Curriculum_Detail!F:F="Enseignement moral et civique")*(Curriculum_Detail!E:E="Core"),0)),"")} -> 0.5 | T41: {=IFERROR(INDEX(Curriculum_Detail!H:H,MATCH(1,(Curriculum_Detail!D:D="Première")*(Curriculum_Detail!F:F="Enseignement moral et civique")*(Curriculum_Detail!E:E="Core"),0)),"")} -> 0.5 | U41: {=IFERROR(INDEX(Curriculum_Detail!H:H,MATCH(1,(Curriculum_Detail!D:D="Terminale")*(Curriculum_Detail!F:F="Enseignement moral et civique")*(Curriculum_Detail!E:E="Core"),0)),"")} -> 0.5 | V41: {=SUMPRODUCT(IF(ISNUMBER(G41:U41),G41:U41,0),$G$10:$U$10)*E41} -> 17.5 | W41: =IF(ISNUMBER(SEARCH("PE",D41)),$D$6,$D$5) -> 18 | X41: =IF(V41=0,"",V41/$H$6) -> 0.97222222 | Y41: =IF(X41="","",ROUNDUP(X41,0)) -> 1
A42: HG-EMC | B42: Specialty | C42: Spé. HGGSP | D42: Certifié Hist-Géo | E42: 2 | F42: 1 | T42: {=IFERROR(INDEX(Curriculum_Detail!H:H,MATCH(1,(Curriculum_Detail!D:D="Première")*(Curriculum_Detail!F:F="Histoire-géographie, géopolitique et sciences politiques")*(Curriculum_Detail!E:E="Specialty"),0)),0)} -> 4 | U42: {=IFERROR(INDEX(Curriculum_Detail!H:H,MATCH(1,(Curriculum_Detail!D:D="Terminale")*(Curriculum_Detail!F:F="Histoire-géographie, géopolitique et sciences politiques")*(Curriculum_Detail!E:E="Specialty"),0)),0)} -> 6 | V42: =T42*E42+U42*F42 -> 14 | W42: =$D$5 -> 18 | X42: =IF(V42=0,"",V42/$H$6) -> 0.77777778 | Y42: =IF(X42="","",ROUNDUP(X42,0)) -> 1
A43: ENGLISH LANGUAGE
A44: ▸ Col | B44: Core | C44: Anglais — LV1 (Collège) | D44: Certifié Anglais | E44: 1 | O44: {=IFERROR(INDEX(Curriculum_Detail!H:H,MATCH(1,(Curriculum_Detail!D:D="6e")*(Curriculum_Detail!F:F="Langue vivante 1")*(Curriculum_Detail!E:E="Core"),0)),"")} -> 4 | P44: {=IFERROR(INDEX(Curriculum_Detail!H:H,MATCH(1,(Curriculum_Detail!D:D="5e")*(Curriculum_Detail!F:F="Langue vivante 1")*(Curriculum_Detail!E:E="Core"),0)),"")} -> 3 | Q44: {=IFERROR(INDEX(Curriculum_Detail!H:H,MATCH(1,(Curriculum_Detail!D:D="4e")*(Curriculum_Detail!F:F="Langue vivante 1")*(Curriculum_Detail!E:E="Core"),0)),"")} -> 3 | R44: {=IFERROR(INDEX(Curriculum_Detail!H:H,MATCH(1,(Curriculum_Detail!D:D="3e")*(Curriculum_Detail!F:F="Langue vivante 1")*(Curriculum_Detail!E:E="Core"),0)),"")} -> 3 | V44: {=SUMPRODUCT(IF(ISNUMBER(G44:U44),G44:U44,0),$G$10:$U$10)*E44} -> 69 | W44: =IF(ISNUMBER(SEARCH("PE",D44)),$D$6,$D$5) -> 18 | X44: =IF(V44=0,"",V44/$H$6) -> 3.8333333 | Y44: =IF(X44="","",ROUNDUP(X44,0)) -> 4
A45: ▸ Lyc | B45: Core | C45: Anglais — LVA (Lycée) | D45: Certifié Anglais | E45: 1 | S45: {=IFERROR(INDEX(Curriculum_Detail!H:H,MATCH(1,(Curriculum_Detail!D:D="Seconde")*(Curriculum_Detail!F:F="LVA + LVB")*(Curriculum_Detail!E:E="Core"),0)),"") - 2.5} -> 3 | T45: {=IFERROR(INDEX(Curriculum_Detail!H:H,MATCH(1,(Curriculum_Detail!D:D="Première")*(Curriculum_Detail!F:F="LVA + LVB")*(Curriculum_Detail!E:E="Core"),0)),"") - 2.5} -> 2 | U45: {=IFERROR(INDEX(Curriculum_Detail!H:H,MATCH(1,(Curriculum_Detail!D:D="Terminale")*(Curriculum_Detail!F:F="LVA + LVB")*(Curriculum_Detail!E:E="Core"),0)),"") - 2.5} -> 1.5 | V45: {=SUMPRODUCT(IF(ISNUMBER(G45:U45),G45:U45,0),$G$10:$U$10)*E45} -> 31 | W45: =IF(ISNUMBER(SEARCH("PE",D45)),$D$6,$D$5) -> 18 | X45: =IF(V45=0,"",V45/$H$6) -> 1.7222222 | Y45: =IF(X45="","",ROUNDUP(X45,0)) -> 2
A46: ▸ Lyc | B46: Specialty | C46: Spé. LLCE Anglais | D46: Certifié Anglais | E46: 0 | F46: 0 | T46: {=IFERROR(INDEX(Curriculum_Detail!H:H,MATCH(1,(Curriculum_Detail!D:D="Première")*(Curriculum_Detail!F:F="Langues, littératures et cultures étrangères et régionales")*(Curriculum_Detail!E:E="Specialty"),0)),0)} -> 4 | U46: {=IFERROR(INDEX(Curriculum_Detail!H:H,MATCH(1,(Curriculum_Detail!D:D="Terminale")*(Curriculum_Detail!F:F="Langues, littératures et cultures étrangères et régionales")*(Curriculum_Detail!E:E="Specialty"),0)),0)} -> 6 | V46: =T46*E46+U46*F46 -> 0 | W46: =$D$5 -> 18 | X46: =IF(V46=0,"",V46/$H$6) | Y46: =IF(X46="","",ROUNDUP(X46,0))
C47: Total Certifié Anglais | V47: =V44+V45+V46 -> 100 | W47: =$D$5 -> 18 | X47: =IF(V47=0,"",V47/$H$6) -> 5.5555556 | Y47: =IF(X47="","",ROUNDUP(X47,0)) -> 6
A48: ARABIC LANGUAGE
A49: ▸ Col | B49: Core | C49: Arabe — LV2 (Collège 5e–3e) | D49: Certifié Arabe | E49: =$D$7 -> 0.5 | P49: {=IFERROR(INDEX(Curriculum_Detail!H:H,MATCH(1,(Curriculum_Detail!D:D="5e")*(Curriculum_Detail!F:F="Langue vivante 2")*(Curriculum_Detail!E:E="Core"),0)),"")} -> 2.5 | Q49: {=IFERROR(INDEX(Curriculum_Detail!H:H,MATCH(1,(Curriculum_Detail!D:D="4e")*(Curriculum_Detail!F:F="Langue vivante 2")*(Curriculum_Detail!E:E="Core"),0)),"")} -> 2.5 | R49: {=IFERROR(INDEX(Curriculum_Detail!H:H,MATCH(1,(Curriculum_Detail!D:D="3e")*(Curriculum_Detail!F:F="Langue vivante 2")*(Curriculum_Detail!E:E="Core"),0)),"")} -> 2.5 | V49: {=SUMPRODUCT(IF(ISNUMBER(G49:U49),G49:U49,0),$G$10:$U$10)*E49} -> 18.75 | W49: =IF(ISNUMBER(SEARCH("PE",D49)),$D$6,$D$5) -> 18 | X49: =IF(V49=0,"",V49/$H$6) -> 1.0416667 | Y49: =IF(X49="","",ROUNDUP(X49,0)) -> 2
A50: ▸ Lyc | B50: Core | C50: Arabe — LVB (Lycée) | D50: Certifié Arabe | E50: =$D$7 -> 0.5 | S50: 2.5 | T50: 2.5 | U50: 2.5 | V50: {=SUMPRODUCT(IF(ISNUMBER(G50:U50),G50:U50,0),$G$10:$U$10)*E50} -> 17.5 | W50: =IF(ISNUMBER(SEARCH("PE",D50)),$D$6,$D$5) -> 18 | X50: =IF(V50=0,"",V50/$H$6) -> 0.97222222 | Y50: =IF(X50="","",ROUNDUP(X50,0)) -> 1
C51: Total Certifié Arabe | V51: =V49+V50 -> 36.25 | W51: =$D$5 -> 18 | X51: =IF(V51=0,"",V51/$H$6) -> 2.0138889 | Y51: =IF(X51="","",ROUNDUP(X51,0)) -> 3
A52: GERMAN LANGUAGE
A53: ▸ Col | B53: Core | C53: Allemand — LV2 (Collège 5e–3e) | D53: Certifié Allemand | E53: =$F$7 -> 0.1 | P53: {=IFERROR(INDEX(Curriculum_Detail!H:H,MATCH(1,(Curriculum_Detail!D:D="5e")*(Curriculum_Detail!F:F="Langue vivante 2")*(Curriculum_Detail!E:E="Core"),0)),"")} -> 2.5 | Q53: {=IFERROR(INDEX(Curriculum_Detail!H:H,MATCH(1,(Curriculum_Detail!D:D="4e")*(Curriculum_Detail!F:F="Langue vivante 2")*(Curriculum_Detail!E:E="Core"),0)),"")} -> 2.5 | R53: {=IFERROR(INDEX(Curriculum_Detail!H:H,MATCH(1,(Curriculum_Detail!D:D="3e")*(Curriculum_Detail!F:F="Langue vivante 2")*(Curriculum_Detail!E:E="Core"),0)),"")} -> 2.5 | V53: {=SUMPRODUCT(IF(ISNUMBER(G53:U53),G53:U53,0),$G$10:$U$10)*E53} -> 3.75 | W53: =IF(ISNUMBER(SEARCH("PE",D53)),$D$6,$D$5) -> 18 | X53: =IF(V53=0,"",V53/$H$6) -> 0.20833333 | Y53: =IF(X53="","",ROUNDUP(X53,0)) -> 1
A54: ▸ Lyc | B54: Core | C54: Allemand — LVB (Lycée) | D54: Certifié Allemand | E54: =$F$7 -> 0.1 | S54: 2.5 | T54: 2.5 | U54: 2.5 | V54: {=SUMPRODUCT(IF(ISNUMBER(G54:U54),G54:U54,0),$G$10:$U$10)*E54} -> 3.5 | W54: =IF(ISNUMBER(SEARCH("PE",D54)),$D$6,$D$5) -> 18 | X54: =IF(V54=0,"",V54/$H$6) -> 0.19444444 | Y54: =IF(X54="","",ROUNDUP(X54,0)) -> 1
C55: Total Certifié Allemand | V55: =V53+V54 -> 7.25 | W55: =$D$5 -> 18 | X55: =IF(V55=0,"",V55/$H$6) -> 0.40277778 | Y55: =IF(X55="","",ROUNDUP(X55,0)) -> 1
A56: SPANISH LANGUAGE
A57: ▸ Col | B57: Core | C57: Espagnol — LV2 (Collège 5e–3e) | D57: Certifié Espagnol | E57: =$H$7 -> 0.4 | P57: {=IFERROR(INDEX(Curriculum_Detail!H:H,MATCH(1,(Curriculum_Detail!D:D="5e")*(Curriculum_Detail!F:F="Langue vivante 2")*(Curriculum_Detail!E:E="Core"),0)),"")} -> 2.5 | Q57: {=IFERROR(INDEX(Curriculum_Detail!H:H,MATCH(1,(Curriculum_Detail!D:D="4e")*(Curriculum_Detail!F:F="Langue vivante 2")*(Curriculum_Detail!E:E="Core"),0)),"")} -> 2.5 | R57: {=IFERROR(INDEX(Curriculum_Detail!H:H,MATCH(1,(Curriculum_Detail!D:D="3e")*(Curriculum_Detail!F:F="Langue vivante 2")*(Curriculum_Detail!E:E="Core"),0)),"")} -> 2.5 | V57: {=SUMPRODUCT(IF(ISNUMBER(G57:U57),G57:U57,0),$G$10:$U$10)*E57} -> 15 | W57: =IF(ISNUMBER(SEARCH("PE",D57)),$D$6,$D$5) -> 18 | X57: =IF(V57=0,"",V57/$H$6) -> 0.83333333 | Y57: =IF(X57="","",ROUNDUP(X57,0)) -> 1
A58: ▸ Lyc | B58: Core | C58: Espagnol — LVB (Lycée) | D58: Certifié Espagnol | E58: =$H$7 -> 0.4 | S58: 2.5 | T58: 2.5 | U58: 2.5 | V58: {=SUMPRODUCT(IF(ISNUMBER(G58:U58),G58:U58,0),$G$10:$U$10)*E58} -> 14 | W58: =IF(ISNUMBER(SEARCH("PE",D58)),$D$6,$D$5) -> 18 | X58: =IF(V58=0,"",V58/$H$6) -> 0.77777778 | Y58: =IF(X58="","",ROUNDUP(X58,0)) -> 1
C59: Total Certifié Espagnol | V59: =V57+V58 -> 29 | W59: =$D$5 -> 18 | X59: =IF(V59=0,"",V59/$H$6) -> 1.6111111 | Y59: =IF(X59="","",ROUNDUP(X59,0)) -> 2
A60: SCIENCES
A61: Sciences | B61: Core | C61: SVT | D61: Certifié SVT | E61: 1 | O61: 1.5 | P61: {=IFERROR(INDEX(Curriculum_Detail!H:H,MATCH(1,(Curriculum_Detail!D:D="5e")*(Curriculum_Detail!F:F="Sciences de la vie et de la Terre")*(Curriculum_Detail!E:E="Core"),0)),"")} -> 1.5 | Q61: {=IFERROR(INDEX(Curriculum_Detail!H:H,MATCH(1,(Curriculum_Detail!D:D="4e")*(Curriculum_Detail!F:F="Sciences de la vie et de la Terre")*(Curriculum_Detail!E:E="Core"),0)),"")} -> 1.5 | R61: {=IFERROR(INDEX(Curriculum_Detail!H:H,MATCH(1,(Curriculum_Detail!D:D="3e")*(Curriculum_Detail!F:F="Sciences de la vie et de la Terre")*(Curriculum_Detail!E:E="Core"),0)),"")} -> 1.5 | S61: {=IFERROR(INDEX(Curriculum_Detail!H:H,MATCH(1,(Curriculum_Detail!D:D="Seconde")*(Curriculum_Detail!F:F="Sciences de la vie et de la Terre")*(Curriculum_Detail!E:E="Core"),0)),"")} -> 1.5 | V61: {=SUMPRODUCT(IF(ISNUMBER(G61:U61),G61:U61,0),$G$10:$U$10)*E61} -> 39 | W61: =IF(ISNUMBER(SEARCH("PE",D61)),$D$6,$D$5) -> 18 | X61: =IF(V61=0,"",V61/$H$6) -> 2.1666667 | Y61: =IF(X61="","",ROUNDUP(X61,0)) -> 3
A62: Sciences | B62: Specialty | C62: Spé. SVT | D62: Certifié SVT | E62: 1 | F62: 1 | T62: {=IFERROR(INDEX(Curriculum_Detail!H:H,MATCH(1,(Curriculum_Detail!D:D="Première")*(Curriculum_Detail!F:F="Sciences de la vie et de la Terre")*(Curriculum_Detail!E:E="Specialty"),0)),0)} -> 4 | U62: {=IFERROR(INDEX(Curriculum_Detail!H:H,MATCH(1,(Curriculum_Detail!D:D="Terminale")*(Curriculum_Detail!F:F="Sciences de la vie et de la Terre")*(Curriculum_Detail!E:E="Specialty"),0)),0)} -> 6 | V62: =T62*E62+U62*F62 -> 10 | W62: =$D$5 -> 18 | X62: =IF(V62=0,"",V62/$H$6) -> 0.55555556 | Y62: =IF(X62="","",ROUNDUP(X62,0)) -> 1
A63: Sciences | B63: Core | C63: Physique-Chimie | D63: Certifié Physique-Chimie | E63: 1 | O63: 1.5 | P63: {=IFERROR(INDEX(Curriculum_Detail!H:H,MATCH(1,(Curriculum_Detail!D:D="5e")*(Curriculum_Detail!F:F="Physique-chimie")*(Curriculum_Detail!E:E="Core"),0)),"")} -> 1.5 | Q63: {=IFERROR(INDEX(Curriculum_Detail!H:H,MATCH(1,(Curriculum_Detail!D:D="4e")*(Curriculum_Detail!F:F="Physique-chimie")*(Curriculum_Detail!E:E="Core"),0)),"")} -> 1.5 | R63: {=IFERROR(INDEX(Curriculum_Detail!H:H,MATCH(1,(Curriculum_Detail!D:D="3e")*(Curriculum_Detail!F:F="Physique-chimie")*(Curriculum_Detail!E:E="Core"),0)),"")} -> 1.5 | S63: {=IFERROR(INDEX(Curriculum_Detail!H:H,MATCH(1,(Curriculum_Detail!D:D="Seconde")*(Curriculum_Detail!F:F="Physique-chimie")*(Curriculum_Detail!E:E="Core"),0)),"")} -> 3 | V63: {=SUMPRODUCT(IF(ISNUMBER(G63:U63),G63:U63,0),$G$10:$U$10)*E63} -> 46.5 | W63: =IF(ISNUMBER(SEARCH("PE",D63)),$D$6,$D$5) -> 18 | X63: =IF(V63=0,"",V63/$H$6) -> 2.5833333 | Y63: =IF(X63="","",ROUNDUP(X63,0)) -> 3
A64: Sciences | B64: Specialty | C64: Spé. Physique-Chimie | D64: Certifié Physique-Chimie | E64: 1 | F64: 1 | T64: {=IFERROR(INDEX(Curriculum_Detail!H:H,MATCH(1,(Curriculum_Detail!D:D="Première")*(Curriculum_Detail!F:F="Physique-chimie")*(Curriculum_Detail!E:E="Specialty"),0)),0)} -> 4 | U64: {=IFERROR(INDEX(Curriculum_Detail!H:H,MATCH(1,(Curriculum_Detail!D:D="Terminale")*(Curriculum_Detail!F:F="Physique-chimie")*(Curriculum_Detail!E:E="Specialty"),0)),0)} -> 6 | V64: =T64*E64+U64*F64 -> 10 | W64: =$D$5 -> 18 | X64: =IF(V64=0,"",V64/$H$6) -> 0.55555556 | Y64: =IF(X64="","",ROUNDUP(X64,0)) -> 1
A65: Sciences | B65: Core | C65: Technologie (Cycle 4) | D65: Certifié Technologie | E65: 1 | P65: {=IFERROR(INDEX(Curriculum_Detail!H:H,MATCH(1,(Curriculum_Detail!D:D="5e")*(Curriculum_Detail!F:F="Technologie")*(Curriculum_Detail!E:E="Core"),0)),"")} -> 1.5 | Q65: {=IFERROR(INDEX(Curriculum_Detail!H:H,MATCH(1,(Curriculum_Detail!D:D="4e")*(Curriculum_Detail!F:F="Technologie")*(Curriculum_Detail!E:E="Core"),0)),"")} -> 1.5 | R65: {=IFERROR(INDEX(Curriculum_Detail!H:H,MATCH(1,(Curriculum_Detail!D:D="3e")*(Curriculum_Detail!F:F="Technologie")*(Curriculum_Detail!E:E="Core"),0)),"")} -> 1.5 | V65: {=SUMPRODUCT(IF(ISNUMBER(G65:U65),G65:U65,0),$G$10:$U$10)*E65} -> 22.5 | W65: =IF(ISNUMBER(SEARCH("PE",D65)),$D$6,$D$5) -> 18 | X65: =IF(V65=0,"",V65/$H$6) -> 1.25 | Y65: =IF(X65="","",ROUNDUP(X65,0)) -> 2
A66: Sciences | B66: Core | C66: SNT (2nde) | D66: Certifié Technologie | E66: 1 | S66: {=IFERROR(INDEX(Curriculum_Detail!H:H,MATCH(1,(Curriculum_Detail!D:D="Seconde")*(Curriculum_Detail!F:F="Sciences numériques et technologie")*(Curriculum_Detail!E:E="Core"),0)),"")} -> 1.5 | V66: {=SUMPRODUCT(IF(ISNUMBER(G66:U66),G66:U66,0),$G$10:$U$10)*E66} -> 7.5 | W66: =IF(ISNUMBER(SEARCH("PE",D66)),$D$6,$D$5) -> 18 | X66: =IF(V66=0,"",V66/$H$6) -> 0.41666667 | Y66: =IF(X66="","",ROUNDUP(X66,0)) -> 1
A67: Sciences | B67: Core | C67: Enseignement Scientifique | D67: Certifié Sciences (mutualisé) | E67: 1 | T67: {=IFERROR(INDEX(Curriculum_Detail!H:H,MATCH(1,(Curriculum_Detail!D:D="Première")*(Curriculum_Detail!F:F="Enseignement scientifique")*(Curriculum_Detail!E:E="Core"),0)),"")} -> 2 | U67: {=IFERROR(INDEX(Curriculum_Detail!H:H,MATCH(1,(Curriculum_Detail!D:D="Terminale")*(Curriculum_Detail!F:F="Enseignement scientifique")*(Curriculum_Detail!E:E="Core"),0)),"")} -> 2 | V67: {=SUMPRODUCT(IF(ISNUMBER(G67:U67),G67:U67,0),$G$10:$U$10)*E67} -> 18 | W67: =IF(ISNUMBER(SEARCH("PE",D67)),$D$6,$D$5) -> 18 | X67: =IF(V67=0,"",V67/$H$6) -> 1 | Y67: =IF(X67="","",ROUNDUP(X67,0)) -> 1
A68: Sciences | B68: Core | C68: SES (2nde) | D68: Certifié SES | E68: 1 | S68: {=IFERROR(INDEX(Curriculum_Detail!H:H,MATCH(1,(Curriculum_Detail!D:D="Seconde")*(Curriculum_Detail!F:F="Sciences économiques et sociales")*(Curriculum_Detail!E:E="Core"),0)),"")} -> 1.5 | V68: {=SUMPRODUCT(IF(ISNUMBER(G68:U68),G68:U68,0),$G$10:$U$10)*E68} -> 7.5 | W68: =IF(ISNUMBER(SEARCH("PE",D68)),$D$6,$D$5) -> 18 | X68: =IF(V68=0,"",V68/$H$6) -> 0.41666667 | Y68: =IF(X68="","",ROUNDUP(X68,0)) -> 1
A69: Sciences | B69: Specialty | C69: Spé. SES | D69: Certifié SES | E69: 1 | F69: 4 | T69: {=IFERROR(INDEX(Curriculum_Detail!H:H,MATCH(1,(Curriculum_Detail!D:D="Première")*(Curriculum_Detail!F:F="Sciences économiques et sociales")*(Curriculum_Detail!E:E="Specialty"),0)),0)} -> 4 | U69: {=IFERROR(INDEX(Curriculum_Detail!H:H,MATCH(1,(Curriculum_Detail!D:D="Terminale")*(Curriculum_Detail!F:F="Sciences économiques et sociales")*(Curriculum_Detail!E:E="Specialty"),0)),0)} -> 6 | V69: =T69*E69+U69*F69 -> 28 | W69: =$D$5 -> 18 | X69: =IF(V69=0,"",V69/$H$6) -> 1.5555556 | Y69: =IF(X69="","",ROUNDUP(X69,0)) -> 2
A70: Sciences | B70: Specialty | C70: Spé. NSI | D70: Certifié NSI/Maths | E70: 1 | F70: 1 | T70: {=IFERROR(INDEX(Curriculum_Detail!H:H,MATCH(1,(Curriculum_Detail!D:D="Première")*(Curriculum_Detail!F:F="Numérique et sciences informatiques")*(Curriculum_Detail!E:E="Specialty"),0)),0)} -> 4 | U70: {=IFERROR(INDEX(Curriculum_Detail!H:H,MATCH(1,(Curriculum_Detail!D:D="Terminale")*(Curriculum_Detail!F:F="Numérique et sciences informatiques")*(Curriculum_Detail!E:E="Specialty"),0)),0)} -> 6 | V70: =T70*E70+U70*F70 -> 10 | W70: =$D$5 -> 18 | X70: =IF(V70=0,"",V70/$H$6) -> 0.55555556 | Y70: =IF(X70="","",ROUNDUP(X70,0)) -> 1
A71: Arts | B71: Core | C71: Arts Plastiques | D71: Certifié Arts Plastiques | E71: 1 | O71: {=IFERROR(INDEX(Curriculum_Detail!H:H,MATCH(1,(Curriculum_Detail!D:D="6e")*(Curriculum_Detail!F:F="Arts plastiques")*(Curriculum_Detail!E:E="Core"),0)),"")} -> 1 | P71: {=IFERROR(INDEX(Curriculum_Detail!H:H,MATCH(1,(Curriculum_Detail!D:D="5e")*(Curriculum_Detail!F:F="Arts plastiques")*(Curriculum_Detail!E:E="Core"),0)),"")} -> 1 | Q71: {=IFERROR(INDEX(Curriculum_Detail!H:H,MATCH(1,(Curriculum_Detail!D:D="4e")*(Curriculum_Detail!F:F="Arts plastiques")*(Curriculum_Detail!E:E="Core"),0)),"")} -> 1 | R71: {=IFERROR(INDEX(Curriculum_Detail!H:H,MATCH(1,(Curriculum_Detail!D:D="3e")*(Curriculum_Detail!F:F="Arts plastiques")*(Curriculum_Detail!E:E="Core"),0)),"")} -> 1 | V71: {=SUMPRODUCT(IF(ISNUMBER(G71:U71),G71:U71,0),$G$10:$U$10)*E71} -> 21 | W71: =IF(ISNUMBER(SEARCH("PE",D71)),$D$6,$D$5) -> 18 | X71: =IF(V71=0,"",V71/$H$6) -> 1.1666667 | Y71: =IF(X71="","",ROUNDUP(X71,0)) -> 2
A72: Arts | B72: Core | C72: Éducation Musicale | D72: Certifié Éducation Musicale | E72: 1 | O72: {=IFERROR(INDEX(Curriculum_Detail!H:H,MATCH(1,(Curriculum_Detail!D:D="6e")*(Curriculum_Detail!F:F="Éducation musicale")*(Curriculum_Detail!E:E="Core"),0)),"")} -> 1 | P72: {=IFERROR(INDEX(Curriculum_Detail!H:H,MATCH(1,(Curriculum_Detail!D:D="5e")*(Curriculum_Detail!F:F="Éducation musicale")*(Curriculum_Detail!E:E="Core"),0)),"")} -> 1 | Q72: {=IFERROR(INDEX(Curriculum_Detail!H:H,MATCH(1,(Curriculum_Detail!D:D="4e")*(Curriculum_Detail!F:F="Éducation musicale")*(Curriculum_Detail!E:E="Core"),0)),"")} -> 1 | R72: {=IFERROR(INDEX(Curriculum_Detail!H:H,MATCH(1,(Curriculum_Detail!D:D="3e")*(Curriculum_Detail!F:F="Éducation musicale")*(Curriculum_Detail!E:E="Core"),0)),"")} -> 1 | V72: {=SUMPRODUCT(IF(ISNUMBER(G72:U72),G72:U72,0),$G$10:$U$10)*E72} -> 21 | W72: =IF(ISNUMBER(SEARCH("PE",D72)),$D$6,$D$5) -> 18 | X72: =IF(V72=0,"",V72/$H$6) -> 1.1666667 | Y72: =IF(X72="","",ROUNDUP(X72,0)) -> 2
A73: EPS
A74: EPS | B74: Core | C74: EPS | D74: Certifié EPS | E74: 1 | O74: {=IFERROR(INDEX(Curriculum_Detail!H:H,MATCH(1,(Curriculum_Detail!D:D="6e")*(Curriculum_Detail!F:F="Éducation physique et sportive")*(Curriculum_Detail!E:E="Core"),0)),"")} -> 4 | P74: {=IFERROR(INDEX(Curriculum_Detail!H:H,MATCH(1,(Curriculum_Detail!D:D="5e")*(Curriculum_Detail!F:F="Éducation physique et sportive")*(Curriculum_Detail!E:E="Core"),0)),"")} -> 3 | Q74: {=IFERROR(INDEX(Curriculum_Detail!H:H,MATCH(1,(Curriculum_Detail!D:D="4e")*(Curriculum_Detail!F:F="Éducation physique et sportive")*(Curriculum_Detail!E:E="Core"),0)),"")} -> 3 | R74: {=IFERROR(INDEX(Curriculum_Detail!H:H,MATCH(1,(Curriculum_Detail!D:D="3e")*(Curriculum_Detail!F:F="Éducation physique et sportive")*(Curriculum_Detail!E:E="Core"),0)),"")} -> 3 | S74: {=IFERROR(INDEX(Curriculum_Detail!H:H,MATCH(1,(Curriculum_Detail!D:D="Seconde")*(Curriculum_Detail!F:F="Éducation physique et sportive")*(Curriculum_Detail!E:E="Core"),0)),"")} -> 2 | T74: {=IFERROR(INDEX(Curriculum_Detail!H:H,MATCH(1,(Curriculum_Detail!D:D="Première")*(Curriculum_Detail!F:F="Éducation physique et sportive")*(Curriculum_Detail!E:E="Core"),0)),"")} -> 2 | U74: {=IFERROR(INDEX(Curriculum_Detail!H:H,MATCH(1,(Curriculum_Detail!D:D="Terminale")*(Curriculum_Detail!F:F="Éducation physique et sportive")*(Curriculum_Detail!E:E="Core"),0)),"")} -> 2 | V74: {=SUMPRODUCT(IF(ISNUMBER(G74:U74),G74:U74,0),$G$10:$U$10)*E74} -> 97 | W74: =IF(ISNUMBER(SEARCH("PE",D74)),$D$6,$D$5) -> 18 | X74: =IF(V74=0,"",V74/$H$6) -> 5.3888889 | Y74: =IF(X74="","",ROUNDUP(X74,0)) -> 6
A75: ⬛ SUBTOTAL BLOCK 2 — COLLÈGE / LYCÉE | V75: =V29+V30+V31+V34+V35+V36+V37+V38+V40+V41+V42+V44+V45+V48+V49+V50+V59+V61+V62+V63+V64+V65+V66+V67+V68+V69+V70+V71+V72+V74 -> 927.25 | W75: =$D$5 -> 18 | X75: =IF(V75=0,"",V75/$H$6) -> 51.513889 | Y75: =IF(X75="","",ROUNDUP(X75,0)) -> 52
A77: # | B77: Teacher Profile | C77: Block | D77: Total Hrs/Wk | E77: Statutory | F77: FTE Req. | G77: Headcount
A78: 1 | B78: Professeur des écoles (PE) | C78: Primaire | D78: =SUMIF($D$11:$D$74,B78,$V$11:$V$74) -> 912 | E78: =$D$6 -> 24 | F78: =IF(D78=0,"",D78/E78) -> 38 | G78: =IF(F78="","",ROUNDUP(F78,0)) -> 38
A79: 2 | B79: ASEM | C79: Primaire | D79: =SUMIF($D$11:$D$74,B79,$V$11:$V$74) -> 264 | E79: =$D$6 -> 24 | F79: =IF(D79=0,"",D79/E79) -> 11 | G79: =IF(F79="","",ROUNDUP(F79,0)) -> 11
A80: 3 | B80: Enseignant Arabe | C80: Primaire | D80: =SUMIF($D$11:$D$74,B80,$V$11:$V$74) -> 146.7 | E80: =$D$5 -> 18 | F80: =IF(D80=0,"",D80/E80) -> 8.15 | G80: =IF(F80="","",ROUNDUP(F80,0)) -> 9
A81: 4 | B81: Enseignant Anglais Primaire | C81: Primaire | D81: =SUMIF($D$11:$D$74,B81,$V$11:$V$74) -> 43.85 | E81: =$D$5 -> 18 | F81: =IF(D81=0,"",D81/E81) -> 2.4361111 | G81: =IF(F81="","",ROUNDUP(F81,0)) -> 3
A82: 5 | B82: Certifié Lettres | C82: Collège/Lycée | D82: =SUMIF($D$11:$D$74,B82,$V$11:$V$74) -> 136.5 | E82: =$D$5 -> 18 | F82: =IF(D82=0,"",D82/E82) -> 7.5833333 | G82: =IF(F82="","",ROUNDUP(F82,0)) -> 8
A83: 6 | B83: Certifié Philosophie | C83: Collège/Lycée | D83: =SUMIF($D$11:$D$74,B83,$V$11:$V$74) -> 22 | E83: =$D$5 -> 18 | F83: =IF(D83=0,"",D83/E83) -> 1.2222222 | G83: =IF(F83="","",ROUNDUP(F83,0)) -> 2
A84: 7 | B84: Certifié Maths | C84: Collège/Lycée | D84: =SUMIF($D$11:$D$74,B84,$V$11:$V$74) -> 143.5 | E84: =$D$5 -> 18 | F84: =IF(D84=0,"",D84/E84) -> 7.9722222 | G84: =IF(F84="","",ROUNDUP(F84,0)) -> 8
A85: 8 | B85: Certifié Hist-Géo | C85: Collège/Lycée | D85: =SUMIF($D$11:$D$74,B85,$V$11:$V$74) -> 110.5 | E85: =$D$5 -> 18 | F85: =IF(D85=0,"",D85/E85) -> 6.1388889 | G85: =IF(F85="","",ROUNDUP(F85,0)) -> 7
A86: 9 | B86: Certifié EMC | C86: Collège/Lycée | D86: =SUMIF($D$11:$D$74,B86,$V$11:$V$74) -> 17.5 | E86: =$D$5 -> 18 | F86: =IF(D86=0,"",D86/E86) -> 0.97222222 | G86: =IF(F86="","",ROUNDUP(F86,0)) -> 1
A87: 10 | B87: Certifié Anglais | C87: Collège/Lycée | D87: =SUMIF($D$11:$D$74,B87,$V$11:$V$74) -> 100 | E87: =$D$5 -> 18 | F87: =IF(D87=0,"",D87/E87) -> 5.5555556 | G87: =IF(F87="","",ROUNDUP(F87,0)) -> 6
A88: 11 | B88: Certifié Arabe | C88: Collège/Lycée | D88: =SUMIF($D$11:$D$74,B88,$V$11:$V$74) -> 36.25 | E88: =$D$5 -> 18 | F88: =IF(D88=0,"",D88/E88) -> 2.0138889 | G88: =IF(F88="","",ROUNDUP(F88,0)) -> 3
A89: 12 | B89: Certifié Allemand | C89: Collège/Lycée | D89: =SUMIF($D$11:$D$74,B89,$V$11:$V$74) -> 7.25 | E89: =$D$5 -> 18 | F89: =IF(D89=0,"",D89/E89) -> 0.40277778 | G89: =IF(F89="","",ROUNDUP(F89,0)) -> 1
A90: 13 | B90: Certifié Espagnol | C90: Collège/Lycée | D90: =SUMIF($D$11:$D$74,B90,$V$11:$V$74) -> 29 | E90: =$D$5 -> 18 | F90: =IF(D90=0,"",D90/E90) -> 1.6111111 | G90: =IF(F90="","",ROUNDUP(F90,0)) -> 2
A91: 14 | B91: Certifié SVT | C91: Collège/Lycée | D91: =SUMIF($D$11:$D$74,B91,$V$11:$V$74) -> 49 | E91: =$D$5 -> 18 | F91: =IF(D91=0,"",D91/E91) -> 2.7222222 | G91: =IF(F91="","",ROUNDUP(F91,0)) -> 3
... A99: 22 | B99: Certifié EPS | C99: Collège/Lycée | D99: =SUMIF($D$11:$D$74,B99,$V$11:$V$74) -> 97 | E99: =$D$5 -> 18 | F99: =IF(D99=0,"",D99/E99) -> 5.3888889 | G99: =IF(F99="","",ROUNDUP(F99,0)) -> 6
B100: TOTAL | D100: =SUM(D78:D99) -> 2307.05 | F100: =SUM(F78:F99) -> 111.83611 | G100: =SUM(G78:G99) -> 122

Sheet Curriculum_Detail
A1: Sort Order | B1: Cycle | C1: Stage | D1: Level | E1: Track | F1: Subject | G1: Hour Status | H1: Weekly Hours | I1: Annual Hours | J1: Planning Groups | K1: Delivered Hours/Wk | L1: Teacher Load Hrs/Wk | M1: Required FTE | N1: Avg Cost per FTE | O1: Est Annual Cost | P1: Source URL | Q1: Notes
A2: 300 | B2: Cycle 3 | C2: Collège | D2: 6e | E2: Core | F2: Français | G2: Official | H2: 4.5 | I2: 162 | J2: 6 | K2: 27 | L2: 18 | M2: 1.5 | N2: 0 | O2: 0 | P2: https://www.education.gouv.fr/les-horaires-par-cycle-au-college-9884
A3: 301 | B3: Cycle 3 | C3: Collège | D3: 6e | E3: Core | F3: Mathématiques | G3: Official | H3: 4.5 | I3: 162 | J3: 6 | K3: 27 | L3: 18 | M3: 1.5 | N3: 0 | O3: 0 | P3: https://www.education.gouv.fr/les-horaires-par-cycle-au-college-9884
A4: 302 | B4: Cycle 3 | C4: Collège | D4: 6e | E4: Core | F4: Histoire-géographie | G4: Derived from official grouped block | H4: 2.5 | I4: 90 | J4: 6 | K4: 15 | L4: 18 | M4: 0.83333333 | N4: 0 | O4: 0 | P4: https://www.education.gouv.fr/les-horaires-par-cycle-au-college-9884 | Q4: Derived from official 3 h grouped block 'Histoire-géographie + EMC', of which EMC is 30 minutes.
A5: 303 | B5: Cycle 3 | C5: Collège | D5: 6e | E5: Core | F5: Enseignement moral et civique | G5: Derived from official grouped block | H5: 0.5 | I5: 18 | J5: 6 | K5: 3 | L5: 18 | M5: 0.16666667 | N5: 0 | O5: 0 | P5: https://www.education.gouv.fr/les-horaires-par-cycle-au-college-9884 | Q5: Derived from official 3 h grouped block 'Histoire-géographie + EMC', of which EMC is 30 minutes.
A6: 304 | B6: Cycle 3 | C6: Collège | D6: 6e | E6: Core | F6: Langue vivante 1 | G6: Official | H6: 4 | I6: 144 | J6: 6 | K6: 24 | L6: 18 | M6: 1.3333333 | N6: 0 | O6: 0 | P6: https://www.education.gouv.fr/les-horaires-par-cycle-au-college-9884
A7: 305 | B7: Cycle 3 | C7: Collège | D7: 6e | E7: Core | F7: Sciences de la vie et de la Terre + Physique-chimie | G7: Official grouped sciences block | H7: 3 | I7: 108 | J7: 6 | K7: 18 | L7: 18 | M7: 1 | N7: 0 | O7: 0 | P7: https://www.education.gouv.fr/les-horaires-par-cycle-au-college-9884 | Q7: Current official 6e timetable groups the sciences block at 3 h/week.
A8: 306 | B8: Cycle 3 | C8: Collège | D8: 6e | E8: Core | F8: Éducation physique et sportive | G8: Official | H8: 4 | I8: 144 | J8: 6 | K8: 24 | L8: 18 | M8: 1.3333333 | N8: 0 | O8: 0 | P8: https://www.education.gouv.fr/les-horaires-par-cycle-au-college-9884
A9: 307 | B9: Cycle 3 | C9: Collège | D9: 6e | E9: Core | F9: Arts plastiques | G9: Official | H9: 1 | I9: 36 | J9: 6 | K9: 6 | L9: 18 | M9: 0.33333333 | N9: 0 | O9: 0 | P9: https://www.education.gouv.fr/les-horaires-par-cycle-au-college-9884
A10: 308 | B10: Cycle 3 | C10: Collège | D10: 6e | E10: Core | F10: Éducation musicale | G10: Official | H10: 1 | I10: 36 | J10: 6 | K10: 6 | L10: 18 | M10: 0.33333333 | N10: 0 | O10: 0 | P10: https://www.education.gouv.fr/les-horaires-par-cycle-au-college-9884
A11: 309 | B11: Cycle 3 | C11: Collège | D11: 6e | E11: Core | F11: Soutien / approfondissement en français ou mathématiques | G11: Official | H11: 1 | I11: 36 | J11: 6 | K11: 6 | L11: 18 | M11: 0.33333333 | N11: 0 | O11: 0 | P11: https://www.education.gouv.fr/les-horaires-par-cycle-au-college-9884
A12: 400 | B12: Cycle 4 | C12: Collège | D12: 5e | E12: Core | F12: Français | G12: Official | H12: 4.5 | I12: 162 | J12: 6 | K12: 27 | L12: 18 | M12: 1.5 | N12: 0 | O12: 0 | P12: https://www.education.gouv.fr/les-horaires-par-cycle-au-college-9884
A13: 401 | B13: Cycle 4 | C13: Collège | D13: 5e | E13: Core | F13: Mathématiques | G13: Official | H13: 3.5 | I13: 126 | J13: 6 | K13: 21 | L13: 18 | M13: 1.1666667 | N13: 0 | O13: 0 | P13: https://www.education.gouv.fr/les-horaires-par-cycle-au-college-9884
A14: 402 | B14: Cycle 4 | C14: Collège | D14: 5e | E14: Core | F14: Histoire-géographie | G14: Derived from official grouped block | H14: 2.5 | I14: 90 | J14: 6 | K14: 15 | L14: 18 | M14: 0.83333333 | N14: 0 | O14: 0 | P14: https://www.education.gouv.fr/les-horaires-par-cycle-au-college-9884 | Q14: Derived from official grouped block 'Histoire-géographie + EMC' with EMC = 30 minutes.
A15: 403 | B15: Cycle 4 | C15: Collège | D15: 5e | E15: Core | F15: Enseignement moral et civique | G15: Derived from official grouped block | H15: 0.5 | I15: 18 | J15: 6 | K15: 3 | L15: 18 | M15: 0.16666667 | N15: 0 | O15: 0 | P15: https://www.education.gouv.fr/les-horaires-par-cycle-au-college-9884 | Q15: Derived from official grouped block 'Histoire-géographie + EMC' with EMC = 30 minutes.
A16: 404 | B16: Cycle 4 | C16: Collège | D16: 5e | E16: Core | F16: Langue vivante 1 | G16: Official | H16: 3 | I16: 108 | J16: 6 | K16: 18 | L16: 18 | M16: 1 | N16: 0 | O16: 0 | P16: https://www.education.gouv.fr/les-horaires-par-cycle-au-college-9884
A17: 405 | B17: Cycle 4 | C17: Collège | D17: 5e | E17: Core | F17: Langue vivante 2 | G17: Official | H17: 2.5 | I17: 90 | J17: 6 | K17: 15 | L17: 18 | M17: 0.83333333 | N17: 0 | O17: 0 | P17: https://www.education.gouv.fr/les-horaires-par-cycle-au-college-9884
A18: 406 | B18: Cycle 4 | C18: Collège | D18: 5e | E18: Core | F18: Sciences de la vie et de la Terre | G18: Official | H18: 1.5 | I18: 54 | J18: 6 | K18: 9 | L18: 18 | M18: 0.5 | N18: 0 | O18: 0 | P18: https://www.education.gouv.fr/les-horaires-par-cycle-au-college-9884
A19: 407 | B19: Cycle 4 | C19: Collège | D19: 5e | E19: Core | F19: Physique-chimie | G19: Official | H19: 1.5 | I19: 54 | J19: 6 | K19: 9 | L19: 18 | M19: 0.5 | N19: 0 | O19: 0 | P19: https://www.education.gouv.fr/les-horaires-par-cycle-au-college-9884
A20: 408 | B20: Cycle 4 | C20: Collège | D20: 5e | E20: Core | F20: Technologie | G20: Official | H20: 1.5 | I20: 54 | J20: 6 | K20: 9 | L20: 18 | M20: 0.5 | N20: 0 | O20: 0 | P20: https://www.education.gouv.fr/les-horaires-par-cycle-au-college-9884
A21: 409 | B21: Cycle 4 | C21: Collège | D21: 5e | E21: Core | F21: Éducation physique et sportive | G21: Official | H21: 3 | I21: 108 | J21: 6 | K21: 18 | L21: 18 | M21: 1 | N21: 0 | O21: 0 | P21: https://www.education.gouv.fr/les-horaires-par-cycle-au-college-9884
A22: 410 | B22: Cycle 4 | C22: Collège | D22: 5e | E22: Core | F22: Arts plastiques | G22: Official | H22: 1 | I22: 36 | J22: 6 | K22: 6 | L22: 18 | M22: 0.33333333 | N22: 0 | O22: 0 | P22: https://www.education.gouv.fr/les-horaires-par-cycle-au-college-9884
A23: 411 | B23: Cycle 4 | C23: Collège | D23: 5e | E23: Core | F23: Éducation musicale | G23: Official | H23: 1 | I23: 36 | J23: 6 | K23: 6 | L23: 18 | M23: 0.33333333 | N23: 0 | O23: 0 | P23: https://www.education.gouv.fr/les-horaires-par-cycle-au-college-9884
A24: 412 | B24: Cycle 4 | C24: Collège | D24: 4e | E24: Core | F24: Français | G24: Official | H24: 4.5 | I24: 162 | J24: 5 | K24: 22.5 | L24: 18 | M24: 1.25 | N24: 0 | O24: 0 | P24: https://www.education.gouv.fr/les-horaires-par-cycle-au-college-9884
A25: 413 | B25: Cycle 4 | C25: Collège | D25: 4e | E25: Core | F25: Mathématiques | G25: Official | H25: 3.5 | I25: 126 | J25: 5 | K25: 17.5 | L25: 18 | M25: 0.97222222 | N25: 0 | O25: 0 | P25: https://www.education.gouv.fr/les-horaires-par-cycle-au-college-9884
A26: 414 | B26: Cycle 4 | C26: Collège | D26: 4e | E26: Core | F26: Histoire-géographie | G26: Derived from official grouped block | H26: 2.5 | I26: 90 | J26: 5 | K26: 12.5 | L26: 18 | M26: 0.69444444 | N26: 0 | O26: 0 | P26: https://www.education.gouv.fr/les-horaires-par-cycle-au-college-9884 | Q26: Derived from official grouped block 'Histoire-géographie + EMC' with EMC = 30 minutes.
A27: 415 | B27: Cycle 4 | C27: Collège | D27: 4e | E27: Core | F27: Enseignement moral et civique | G27: Derived from official grouped block | H27: 0.5 | I27: 18 | J27: 5 | K27: 2.5 | L27: 18 | M27: 0.13888889 | N27: 0 | O27: 0 | P27: https://www.education.gouv.fr/les-horaires-par-cycle-au-college-9884 | Q27: Derived from official grouped block 'Histoire-géographie + EMC' with EMC = 30 minutes.
A28: 416 | B28: Cycle 4 | C28: Collège | D28: 4e | E28: Core | F28: Langue vivante 1 | G28: Official | H28: 3 | I28: 108 | J28: 5 | K28: 15 | L28: 18 | M28: 0.83333333 | N28: 0 | O28: 0 | P28: https://www.education.gouv.fr/les-horaires-par-cycle-au-college-9884
A29: 417 | B29: Cycle 4 | C29: Collège | D29: 4e | E29: Core | F29: Langue vivante 2 | G29: Official | H29: 2.5 | I29: 90 | J29: 5 | K29: 12.5 | L29: 18 | M29: 0.69444444 | N29: 0 | O29: 0 | P29: https://www.education.gouv.fr/les-horaires-par-cycle-au-college-9884
A30: 418 | B30: Cycle 4 | C30: Collège | D30: 4e | E30: Core | F30: Sciences de la vie et de la Terre | G30: Official | H30: 1.5 | I30: 54 | J30: 5 | K30: 7.5 | L30: 18 | M30: 0.41666667 | N30: 0 | O30: 0 | P30: https://www.education.gouv.fr/les-horaires-par-cycle-au-college-9884
A31: 419 | B31: Cycle 4 | C31: Collège | D31: 4e | E31: Core | F31: Physique-chimie | G31: Official | H31: 1.5 | I31: 54 | J31: 5 | K31: 7.5 | L31: 18 | M31: 0.41666667 | N31: 0 | O31: 0 | P31: https://www.education.gouv.fr/les-horaires-par-cycle-au-college-9884
A32: 420 | B32: Cycle 4 | C32: Collège | D32: 4e | E32: Core | F32: Technologie | G32: Official | H32: 1.5 | I32: 54 | J32: 5 | K32: 7.5 | L32: 18 | M32: 0.41666667 | N32: 0 | O32: 0 | P32: https://www.education.gouv.fr/les-horaires-par-cycle-au-college-9884
A33: 421 | B33: Cycle 4 | C33: Collège | D33: 4e | E33: Core | F33: Éducation physique et sportive | G33: Official | H33: 3 | I33: 108 | J33: 5 | K33: 15 | L33: 18 | M33: 0.83333333 | N33: 0 | O33: 0 | P33: https://www.education.gouv.fr/les-horaires-par-cycle-au-college-9884
A34: 422 | B34: Cycle 4 | C34: Collège | D34: 4e | E34: Core | F34: Arts plastiques | G34: Official | H34: 1 | I34: 36 | J34: 5 | K34: 5 | L34: 18 | M34: 0.27777778 | N34: 0 | O34: 0 | P34: https://www.education.gouv.fr/les-horaires-par-cycle-au-college-9884
A35: 423 | B35: Cycle 4 | C35: Collège | D35: 4e | E35: Core | F35: Éducation musicale | G35: Official | H35: 1 | I35: 36 | J35: 5 | K35: 5 | L35: 18 | M35: 0.27777778 | N35: 0 | O35: 0 | P35: https://www.education.gouv.fr/les-horaires-par-cycle-au-college-9884
A36: 424 | B36: Cycle 4 | C36: Collège | D36: 3e | E36: Core | F36: Français | G36: Official | H36: 4 | I36: 144 | J36: 4 | K36: 16 | L36: 18 | M36: 0.88888889 | N36: 0 | O36: 0 | P36: https://www.education.gouv.fr/les-horaires-par-cycle-au-college-9884
A37: 425 | B37: Cycle 4 | C37: Collège | D37: 3e | E37: Core | F37: Mathématiques | G37: Official | H37: 3.5 | I37: 126 | J37: 4 | K37: 14 | L37: 18 | M37: 0.77777778 | N37: 0 | O37: 0 | P37: https://www.education.gouv.fr/les-horaires-par-cycle-au-college-9884
A38: 426 | B38: Cycle 4 | C38: Collège | D38: 3e | E38: Core | F38: Histoire-géographie | G38: Derived from official grouped block | H38: 3 | I38: 108 | J38: 4 | K38: 12 | L38: 18 | M38: 0.66666667 | N38: 0 | O38: 0 | P38: https://www.education.gouv.fr/les-horaires-par-cycle-au-college-9884 | Q38: Derived from official grouped block 'Histoire-géographie + EMC' with EMC = 30 minutes.
A39: 427 | B39: Cycle 4 | C39: Collège | D39: 3e | E39: Core | F39: Enseignement moral et civique | G39: Derived from official grouped block | H39: 0.5 | I39: 18 | J39: 4 | K39: 2 | L39: 18 | M39: 0.11111111 | N39: 0 | O39: 0 | P39: https://www.education.gouv.fr/les-horaires-par-cycle-au-college-9884 | Q39: Derived from official grouped block 'Histoire-géographie + EMC' with EMC = 30 minutes.
A40: 428 | B40: Cycle 4 | C40: Collège | D40: 3e | E40: Core | F40: Langue vivante 1 | G40: Official | H40: 3 | I40: 108 | J40: 4 | K40: 12 | L40: 18 | M40: 0.66666667 | N40: 0 | O40: 0 | P40: https://www.education.gouv.fr/les-horaires-par-cycle-au-college-9884
A41: 429 | B41: Cycle 4 | C41: Collège | D41: 3e | E41: Core | F41: Langue vivante 2 | G41: Official | H41: 2.5 | I41: 90 | J41: 4 | K41: 10 | L41: 18 | M41: 0.55555556 | N41: 0 | O41: 0 | P41: https://www.education.gouv.fr/les-horaires-par-cycle-au-college-9884
A42: 430 | B42: Cycle 4 | C42: Collège | D42: 3e | E42: Core | F42: Sciences de la vie et de la Terre | G42: Official | H42: 1.5 | I42: 54 | J42: 4 | K42: 6 | L42: 18 | M42: 0.33333333 | N42: 0 | O42: 0 | P42: https://www.education.gouv.fr/les-horaires-par-cycle-au-college-9884
A43: 431 | B43: Cycle 4 | C43: Collège | D43: 3e | E43: Core | F43: Physique-chimie | G43: Official | H43: 1.5 | I43: 54 | J43: 4 | K43: 6 | L43: 18 | M43: 0.33333333 | N43: 0 | O43: 0 | P43: https://www.education.gouv.fr/les-horaires-par-cycle-au-college-9884
A44: 432 | B44: Cycle 4 | C44: Collège | D44: 3e | E44: Core | F44: Technologie | G44: Official | H44: 1.5 | I44: 54 | J44: 4 | K44: 6 | L44: 18 | M44: 0.33333333 | N44: 0 | O44: 0 | P44: https://www.education.gouv.fr/les-horaires-par-cycle-au-college-9884
A45: 433 | B45: Cycle 4 | C45: Collège | D45: 3e | E45: Core | F45: Éducation physique et sportive | G45: Official | H45: 3 | I45: 108 | J45: 4 | K45: 12 | L45: 18 | M45: 0.66666667 | N45: 0 | O45: 0 | P45: https://www.education.gouv.fr/les-horaires-par-cycle-au-college-9884
A46: 434 | B46: Cycle 4 | C46: Collège | D46: 3e | E46: Core | F46: Arts plastiques | G46: Official | H46: 1 | I46: 36 | J46: 4 | K46: 4 | L46: 18 | M46: 0.22222222 | N46: 0 | O46: 0 | P46: https://www.education.gouv.fr/les-horaires-par-cycle-au-college-9884
A47: 435 | B47: Cycle 4 | C47: Collège | D47: 3e | E47: Core | F47: Éducation musicale | G47: Official | H47: 1 | I47: 36 | J47: 4 | K47: 4 | L47: 18 | M47: 0.22222222 | N47: 0 | O47: 0 | P47: https://www.education.gouv.fr/les-horaires-par-cycle-au-college-9884
A48: 500 | B48: Lycée | C48: Lycée | D48: Seconde | E48: Core | F48: Français | G48: Official | H48: 4 | I48: 144 | J48: 5 | K48: 20 | L48: 18 | M48: 1.1111111 | N48: 0 | O48: 0 | P48: https://eduscol.education.gouv.fr/5466/seconde-generale-et-technologique
A49: 501 | B49: Lycée | C49: Lycée | D49: Seconde | E49: Core | F49: Histoire-géographie | G49: Official | H49: 3 | I49: 108 | J49: 5 | K49: 15 | L49: 18 | M49: 0.83333333 | N49: 0 | O49: 0 | P49: https://eduscol.education.gouv.fr/5466/seconde-generale-et-technologique
A50: 502 | B50: Lycée | C50: Lycée | D50: Seconde | E50: Core | F50: LVA + LVB | G50: Official | H50: 5.5 | I50: 198 | J50: 5 | K50: 27.5 | L50: 18 | M50: 1.5277778 | N50: 0 | O50: 0 | P50: https://eduscol.education.gouv.fr/5466/seconde-generale-et-technologique
A51: 503 | B51: Lycée | C51: Lycée | D51: Seconde | E51: Core | F51: Sciences économiques et sociales | G51: Official | H51: 1.5 | I51: 54 | J51: 5 | K51: 7.5 | L51: 18 | M51: 0.41666667 | N51: 0 | O51: 0 | P51: https://eduscol.education.gouv.fr/5466/seconde-generale-et-technologique
... A60: 602 | B60: Lycée | C60: Lycée | D60: Première | E60: Core | F60: LVA + LVB | G60: Official | H60: 4.5 | I60: 162 | J60: 5 | K60: 22.5 | L60: 18 | M60: 1.25 | N60: 0 | O60: 0 | P60: https://eduscol.education.gouv.fr/5418/cycle-terminal-de-la-voie-generale
A61: 603 | B61: Lycée | C61: Lycée | D61: Première | E61: Core | F61: Enseignement scientifique | G61: Official | H61: 2 | I61: 72 | J61: 5 | K61: 10 | L61: 18 | M61: 0.55555556 | N61: 0 | O61: 0 | P61: https://eduscol.education.gouv.fr/5418/cycle-terminal-de-la-voie-generale | Q61: Base common hours for all Première générale students.
A62: 604 | B62: Lycée | C62: Lycée | D62: Première | E62: Conditional | F62: Mathématiques spécifiques intégrées à l'enseignement scientifique | G62: Conditional | H62: 1.5 | I62: 54 | J62: 0 | K62: 0 | L62: 18 | M62: 0 | N62: 0 | O62: 0 | P62: https://eduscol.education.gouv.fr/5790/programmes-et-ressources-en-enseignement-scientifique-voie-g | Q62: Only for students not choosing the math specialty.
A63: 605 | B63: Lycée | C63: Lycée | D63: Première | E63: Core | F63: Éducation physique et sportive | G63: Official | H63: 2 | I63: 72 | J63: 5 | K63: 10 | L63: 18 | M63: 0.55555556 | N63: 0 | O63: 0 | P63: https://eduscol.education.gouv.fr/5418/cycle-terminal-de-la-voie-generale
A64: 606 | B64: Lycée | C64: Lycée | D64: Première | E64: Core | F64: Enseignement moral et civique | G64: Official annual 18h converted to weekly equivalent | H64: 0.5 | I64: 18 | J64: 5 | K64: 2.5 | L64: 18 | M64: 0.13888889 | N64: 0 | O64: 0 | P64: https://eduscol.education.gouv.fr/5418/cycle-terminal-de-la-voie-generale | Q64: 18 annual hours expressed here as a 0.5 h weekly equivalent.
A65: 650 | B65: Lycée | C65: Lycée | D65: Terminale | E65: Core | F65: Philosophie | G65: Official | H65: 4 | I65: 144 | J65: 4 | K65: 16 | L65: 18 | M65: 0.88888889 | N65: 0 | O65: 0 | P65: https://eduscol.education.gouv.fr/5418/cycle-terminal-de-la-voie-generale
A66: 651 | B66: Lycée | C66: Lycée | D66: Terminale | E66: Core | F66: Histoire-géographie | G66: Official | H66: 3 | I66: 108 | J66: 4 | K66: 12 | L66: 18 | M66: 0.66666667 | N66: 0 | O66: 0 | P66: https://eduscol.education.gouv.fr/5418/cycle-terminal-de-la-voie-generale
A67: 652 | B67: Lycée | C67: Lycée | D67: Terminale | E67: Core | F67: LVA + LVB | G67: Official | H67: 4 | I67: 144 | J67: 4 | K67: 16 | L67: 18 | M67: 0.88888889 | N67: 0 | O67: 0 | P67: https://eduscol.education.gouv.fr/5418/cycle-terminal-de-la-voie-generale
A68: 653 | B68: Lycée | C68: Lycée | D68: Terminale | E68: Core | F68: Enseignement scientifique | G68: Official | H68: 2 | I68: 72 | J68: 4 | K68: 8 | L68: 18 | M68: 0.44444444 | N68: 0 | O68: 0 | P68: https://eduscol.education.gouv.fr/5418/cycle-terminal-de-la-voie-generale
A69: 654 | B69: Lycée | C69: Lycée | D69: Terminale | E69: Core | F69: Éducation physique et sportive | G69: Official | H69: 2 | I69: 72 | J69: 4 | K69: 8 | L69: 18 | M69: 0.44444444 | N69: 0 | O69: 0 | P69: https://eduscol.education.gouv.fr/5418/cycle-terminal-de-la-voie-generale
A70: 655 | B70: Lycée | C70: Lycée | D70: Terminale | E70: Core | F70: Enseignement moral et civique | G70: Official annual 18h converted to weekly equivalent | H70: 0.5 | I70: 18 | J70: 4 | K70: 2 | L70: 18 | M70: 0.11111111 | N70: 0 | O70: 0 | P70: https://eduscol.education.gouv.fr/5418/cycle-terminal-de-la-voie-generale | Q70: 18 annual hours expressed here as a 0.5 h weekly equivalent.
A71: 700 | B71: Lycée | C71: Lycée | D71: Première | E71: Specialty | F71: Arts | G71: Official specialty | H71: 4 | I71: 144 | J71: 0 | K71: 0 | L71: 18 | M71: 0 | N71: 0 | O71: 0 | P71: https://eduscol.education.gouv.fr/5418/cycle-terminal-de-la-voie-generale | Q71: National list; local school availability may differ. Students choose 3 specialties in Première.
A72: 701 | B72: Lycée | C72: Lycée | D72: Première | E72: Specialty | F72: Biologie-écologie | G72: Official specialty | H72: 4 | I72: 144 | J72: 0 | K72: 0 | L72: 18 | M72: 0 | N72: 0 | O72: 0 | P72: https://eduscol.education.gouv.fr/5418/cycle-terminal-de-la-voie-generale | Q72: Agricultural lycée specialty; usually not applicable in mainstream AEFE schools. Students choose 3 specialties in Première.
A73: 702 | B73: Lycée | C73: Lycée | D73: Première | E73: Specialty | F73: Éducation physique, pratiques et culture sportives | G73: Official specialty | H73: 4 | I73: 144 | J73: 0 | K73: 0 | L73: 18 | M73: 0 | N73: 0 | O73: 0 | P73: https://eduscol.education.gouv.fr/5418/cycle-terminal-de-la-voie-generale | Q73: School availability dependent. Students choose 3 specialties in Première.
A74: 703 | B74: Lycée | C74: Lycée | D74: Première | E74: Specialty | F74: Histoire-géographie, géopolitique et sciences politiques | G74: Official specialty | H74: 4 | I74: 144 | J74: 0 | K74: 0 | L74: 18 | M74: 0 | N74: 0 | O74: 0 | P74: https://eduscol.education.gouv.fr/5418/cycle-terminal-de-la-voie-generale | Q74: Students choose 3 specialties in Première.
A75: 704 | B75: Lycée | C75: Lycée | D75: Première | E75: Specialty | F75: Humanités, littérature et philosophie | G75: Official specialty | H75: 4 | I75: 144 | J75: 0 | K75: 0 | L75: 18 | M75: 0 | N75: 0 | O75: 0 | P75: https://eduscol.education.gouv.fr/5418/cycle-terminal-de-la-voie-generale | Q75: Students choose 3 specialties in Première.
A76: 705 | B76: Lycée | C76: Lycée | D76: Première | E76: Specialty | F76: Langues, littératures et cultures étrangères et régionales | G76: Official specialty | H76: 4 | I76: 144 | J76: 0 | K76: 0 | L76: 18 | M76: 0 | N76: 0 | O76: 0 | P76: https://eduscol.education.gouv.fr/5418/cycle-terminal-de-la-voie-generale | Q76: Students choose 3 specialties in Première.
A77: 706 | B77: Lycée | C77: Lycée | D77: Première | E77: Specialty | F77: Littératures et langues et cultures de l'Antiquité | G77: Official specialty | H77: 4 | I77: 144 | J77: 0 | K77: 0 | L77: 18 | M77: 0 | N77: 0 | O77: 0 | P77: https://eduscol.education.gouv.fr/5418/cycle-terminal-de-la-voie-generale | Q77: Students choose 3 specialties in Première.
A78: 707 | B78: Lycée | C78: Lycée | D78: Première | E78: Specialty | F78: Mathématiques | G78: Official specialty | H78: 4 | I78: 144 | J78: 0 | K78: 0 | L78: 18 | M78: 0 | N78: 0 | O78: 0 | P78: https://eduscol.education.gouv.fr/5418/cycle-terminal-de-la-voie-generale | Q78: Students choose 3 specialties in Première.
A79: 708 | B79: Lycée | C79: Lycée | D79: Première | E79: Specialty | F79: Numérique et sciences informatiques | G79: Official specialty | H79: 4 | I79: 144 | J79: 0 | K79: 0 | L79: 18 | M79: 0 | N79: 0 | O79: 0 | P79: https://eduscol.education.gouv.fr/5418/cycle-terminal-de-la-voie-generale | Q79: Students choose 3 specialties in Première.
A80: 709 | B80: Lycée | C80: Lycée | D80: Première | E80: Specialty | F80: Physique-chimie | G80: Official specialty | H80: 4 | I80: 144 | J80: 0 | K80: 0 | L80: 18 | M80: 0 | N80: 0 | O80: 0 | P80: https://eduscol.education.gouv.fr/5418/cycle-terminal-de-la-voie-generale | Q80: Students choose 3 specialties in Première.
A81: 710 | B81: Lycée | C81: Lycée | D81: Première | E81: Specialty | F81: Sciences de la vie et de la Terre | G81: Official specialty | H81: 4 | I81: 144 | J81: 0 | K81: 0 | L81: 18 | M81: 0 | N81: 0 | O81: 0 | P81: https://eduscol.education.gouv.fr/5418/cycle-terminal-de-la-voie-generale | Q81: Students choose 3 specialties in Première.
... A96: 725 | B96: Lycée | C96: Lycée | D96: Terminale | E96: Specialty | F96: Sciences économiques et sociales | G96: Official specialty | H96: 6 | I96: 216 | J96: 0 | K96: 0 | L96: 18 | M96: 0 | N96: 0 | O96: 0 | P96: https://eduscol.education.gouv.fr/5418/cycle-terminal-de-la-voie-generale | Q96: Students continue 2 specialties in Terminale.

Sheet Master Data
A1: EFIR — Staff Master Data FY2025-2026
A2: Active: 185 (159 Local + 26 AEFE) | Departed: 1 | Total rows: 186 | Currency: SAR | QA Validated: 2026-03-21
A4: # | B4: Last Name | C4: First Name | D4: Contract Type | E4: Function / Role | F4: Department | G4: Subject / Discipline | H4: Teacher / Non-Teacher | I4: Teacher Profile | J4: Allocation (Band) | K4: Level | L4: Status | M4: Joining Date | N4: YoS | O4: Base Salary (SAR) | P4: Housing (IL) | Q4: Transport (IT) | R4: Resp. Premium | S4: HSA (10m) | T4: Monthly Gross (SAR) | U4: Hourly % | V4: Payment Method | W4: Aug. 2026-27 | X4: Notes (QA)
A5: 1 | B5: ABED | C5: Ghina | D5: Contrat Local | E5: Assistant(e) d'éducation | F5: Vie Scolaire & Support | G5: Vie scolaire | H5: Non-Teacher | J5: Secondaire | K5: Vie Scolaire & Support | L5: Existing | M5: 45170 | N5: 3.3 | O5: 7400 | P5: 2500 | Q5: 500 | T5: 10400 | U5: 1 | V5: Liquide | W5: 200 | X5: ✓ Verified: All salary fields match payroll file.
A6: 2 | B6: ABID | C6: Hamdi | D6: Contrat Local | E6: Assistant(e) d'éducation | F6: Vie Scolaire & Support | G6: Vie scolaire | H6: Non-Teacher | J6: Secondaire | K6: Vie Scolaire & Support | L6: Existing | M6: 42614 | N6: 10.3 | O6: 9000 | P6: 2500 | Q6: 500 | T6: 12000 | U6: 1 | V6: Virement | W6: 400 | X6: ✓ Verified: All salary fields match payroll file.
A7: 3 | B7: ABOU RJEILI | C7: Christina | D7: Contrat Local | E7: Assistant(e) d'éducation | F7: Vie Scolaire & Support | G7: Vie scolaire | H7: Non-Teacher | J7: Secondaire | K7: Vie Scolaire & Support | L7: Existing | M7: 45536 | N7: 2.3 | O7: 7200 | P7: 2500 | Q7: 500 | T7: 10200 | U7: 1 | V7: Virement | W7: 200 | X7: ✓ Verified: All salary fields match payroll file.
A8: 4 | B8: ABOUTALEB | C8: Hasnae | D8: Contrat Local | E8: Professeur(e) des écoles | F8: Élémentaire | G8: Generaliste | H8: Teacher | I8: Professeur des écoles (PE) | J8: PSB | K8: Maternelle | L8: Existing | M8: 44440 | N8: 5.3 | O8: 9000 | P8: 2500 | Q8: 500 | T8: 12000 | U8: 1 | V8: Virement | W8: 250 | X8: ✓ Verified: All salary fields match payroll file.
A9: 5 | B9: ABSIL | C9: Marie-Savine | D9: Contrat Local | E9: Professeur(e) des écoles | F9: Élémentaire | G9: Generaliste | H9: Teacher | I9: Professeur des écoles (PE) | J9: Élémentaire (TBD) | K9: Élémentaire | L9: Existing | M9: 45901 | N9: 1.3 | O9: 10500 | P9: 2500 | Q9: 500 | T9: 13500 | U9: 1 | V9: Liquide | W9: Nouveau Contrat | X9: ✓ Verified: All salary fields match payroll file.
A10: 6 | B10: ACHATOU | C10: Nadia | D10: Contrat Local | E10: Responsable RH | F10: Administration | G10: Ressources humaines | H10: Non-Teacher | J10: Administration | K10: Administration | L10: Existing | M10: 42614 | N10: 10.3 | O10: 12250 | P10: 2500 | Q10: 500 | R10: 1000 | T10: 16250 | U10: 1 | V10: Mudad | W10: 250 | X10: ✓ Verified: All salary fields match payroll file.
A11: 7 | B11: ADJTOUTAH | C11: Anissa | D11: Contrat Local | E11: Professeur(e) des écoles | F11: Élémentaire | G11: Generaliste | H11: Teacher | I11: Professeur des écoles (PE) | J11: Élémentaire (TBD) | K11: Élémentaire | L11: Existing | M11: 45901 | N11: 1.3 | O11: 8250 | P11: 2500 | Q11: 500 | T11: 11250 | U11: 1 | V11: Liquide | W11: Nouveau Contrat | X11: ✓ Verified: All salary fields match payroll file.
A12: 8 | B12: AHYOUD | C12: Hanan | D12: Contrat Local | E12: Professeur(e) des écoles | F12: Élémentaire | G12: Generaliste | H12: Teacher | I12: Professeur des écoles (PE) | J12: GSD | K12: Maternelle | L12: Existing | M12: 42614 | N12: 10.3 | O12: 10250 | P12: 2500 | Q12: 500 | T12: 13250 | U12: 1 | V12: Virement | W12: 250 | X12: ✓ Verified: All salary fields match payroll file.
A13: 9 | B13: AL JUNDI | C13: Tamara | D13: Contrat Local | E13: Enseignant de langue étrangère | F13: Élémentaire | G13: Arabe | H13: Teacher | I13: Enseignant Arabe | J13: PS-CM2 (Primaire) | K13: Primaire | L13: Existing | M13: 35309 | N13: 30.3 | O13: 9750 | P13: 2500 | Q13: 500 | S13: 1140 | T13: 13890 | U13: 1 | V13: Virement | W13: 250 | X13: ✓ Verified: All salary fields match payroll file.
A14: 10 | B14: AL NAHED | C14: Saliha | D14: Contrat Local | E14: Professeur(e) des écoles | F14: Élémentaire | G14: Generaliste | H14: Teacher | I14: Professeur des écoles (PE) | J14: CE2 D | K14: Élémentaire | L14: Existing | M14: 45536 | N14: 2.3 | O14: 8750 | P14: 2500 | Q14: 500 | T14: 11750 | U14: 1 | V14: Virement | W14: 250 | X14: ✓ Verified: All salary fields match payroll file.
A15: 11 | B15: AL OSSAIMI AL OTAIBI | C15: BADR | D15: Contrat Local | E15: Démarcheur | F15: Administration | G15: Relations publiques | H15: Non-Teacher | J15: Administration | K15: Administration | L15: Existing | O15: 2000 | P15: 2500 | Q15: 500 | T15: 5000 | U15: 1 | V15: Virement | W15: Nouveau Contrat | X15: ✓ Verified: All salary fields match payroll file. | MISSING: Joining Date is blank. Needs HR input. | MISSING: YoS is blank. Needs HR input.
A16: 12 | B16: AL SHAKHAA | C16: Nada | D16: Contrat Local | E16: Chargé(e) du programme noor | F16: Administration | G16: Programme Noor | H16: Non-Teacher | J16: Administration | K16: Administration | L16: Existing | M16: 42283 | N16: 11.2 | O16: 9500 | P16: 2500 | Q16: 500 | T16: 12500 | U16: 1 | V16: Mudad | W16: 250 | X16: ✓ Verified: All salary fields match payroll file.
A17: 13 | B17: ALAMRI | C17: Shalan | D17: Contrat Local | E17: Chargé(e) des relations publiques | F17: Administration | G17: Relations publiques | H17: Non-Teacher | J17: Administration | K17: Administration | L17: Existing | M17: 44867 | N17: 4.2 | O17: 12250 | P17: 2500 | Q17: 500 | R17: 1000 | T17: 16250 | U17: 1 | V17: Mudad | W17: 250 | X17: ✓ Verified: All salary fields match payroll file.
A18: 14 | B18: ALNACHAR | C18: Farah | D18: Contrat Local | E18: Assistant(e) d'éducation | F18: Vie Scolaire & Support | G18: Vie scolaire | H18: Non-Teacher | J18: Primaire | K18: Vie Scolaire & Support | L18: Existing | M18: 45901 | N18: 1.3 | O18: 7000 | P18: 2500 | Q18: 500 | T18: 10000 | U18: 1 | V18: Virement | W18: Nouveau Contrat | X18: ✓ Verified: All salary fields match payroll file.
A19: 15 | B19: AMANAT | C19: Aisha | D19: Contrat Local | E19: Professeur(e) des écoles | F19: Élémentaire | G19: Generaliste | H19: Teacher | I19: Professeur des écoles (PE) | J19: MSB | K19: Maternelle | L19: Existing | M19: 45536 | N19: 2.3 | O19: 8250 | P19: 2500 | Q19: 500 | T19: 11250 | U19: 1 | V19: Liquide | W19: 250 | X19: ✓ Verified: All salary fields match payroll file.
A20: 16 | B20: AMRI | C20: Kehena | D20: Contrat Local | E20: Enseignant second degré | F20: Collège / Lycée | G20: Francais | H20: Teacher | I20: Certifié Lettres | J20: PP 6eme B | K20: Secondaire | L20: Existing | M20: 40787 | N20: 15.3 | O20: 12000 | P20: 2500 | Q20: 500 | S20: 900 | T20: 15900 | U20: 1 | V20: Virement | W20: 250 | X20: ✓ Verified: All salary fields match payroll file.
A21: 17 | B21: ASSEKOUR | C21: Soufiane | D21: Contrat Local | E21: Enseignant second degré | F21: Collège / Lycée | G21: EPS | H21: Teacher | I21: Certifié EPS | J21: Collège & Lycée | K21: Secondaire | L21: Existing | M21: 45901 | N21: 1.3 | O21: 8750 | P21: 2500 | Q21: 500 | S21: 700 | T21: 12450 | U21: 1 | V21: Liquide | W21: Nouveau Contrat | X21: ✓ Verified: All salary fields match payroll file.
A22: 18 | B22: AYACHI | C22: Amen | D22: Contrat Local | E22: Professeur(e) des écoles | F22: Élémentaire | G22: Generaliste | H22: Teacher | I22: Professeur des écoles (PE) | J22: MSE | K22: Maternelle | L22: Existing | M22: 45536 | N22: 2.3 | O22: 9000 | P22: 2500 | Q22: 500 | T22: 12000 | U22: 1 | V22: Virement | W22: 250 | X22: ✓ Verified: All salary fields match payroll file.
A23: 19 | B23: BACHOUR | C23: Reem | D23: Contrat Local | E23: Enseignant de langue étrangère | F23: Élémentaire | G23: Arabe | H23: Teacher | I23: Enseignant Arabe | J23: PS-CM2 (Primaire) | K23: Primaire | L23: Existing | M23: 36404 | N23: 27.3 | O23: 13250 | P23: 2500 | Q23: 500 | S23: 1140 | T23: 17390 | U23: 1 | V23: Virement | W23: 250 | X23: ✓ Verified: All salary fields match payroll file.
A24: 20 | B24: BADR | C24: Chantal | D24: Contrat Local | E24: Enseignant de langue étrangère | F24: Élémentaire | G24: Arabe | H24: Teacher | I24: Enseignant Arabe | J24: PS-CM2 (Primaire) | K24: Primaire | L24: Existing | M24: 40787 | N24: 15.3 | O24: 10250 | P24: 2500 | Q24: 500 | S24: 70 | T24: 13320 | U24: 1 | V24: Virement | W24: 250 | X24: ✓ Verified: All salary fields match payroll file.
A25: 21 | B25: BALLAN | C25: Christiane | D25: Contrat Local | E25: Enseignant de langue étrangère second degré | F25: Collège / Lycée | G25: Arabe | H25: Teacher | I25: Certifié Arabe | J25: Collège & Lycée | K25: Secondaire | L25: Existing | M25: 44805 | N25: 4.3 | O25: 8750 | P25: 2500 | Q25: 500 | S25: 1300 | T25: 13050 | U25: 1 | V25: Virement | W25: 250 | X25: ✓ Verified: All salary fields match payroll file.
A26: 22 | B26: BASBOUS | C26: Carla | D26: Contrat Local | E26: Enseignant de langue étrangère second degré | F26: Collège / Lycée | G26: Arabe (coordinatrice) | H26: Teacher | I26: Certifié Arabe | J26: Collège & Lycée | K26: Secondaire | L26: Existing | M26: 36770 | N26: 26.3 | O26: 9500 | P26: 2500 | Q26: 500 | S26: 400 | T26: 12900 | U26: 1 | V26: Liquide | W26: -3250 (nouveau contrat retraite) | X26: ✓ Verified: All salary fields match payroll file.
A27: 23 | B27: BAYDOUN | C27: Fayza | D27: Contrat Local | E27: Assistante de direction | F27: Administration | G27: Secretariat | H27: Non-Teacher | J27: Administration | K27: Administration | L27: Existing | M27: 45902 | N27: 1.3 | O27: 7400 | P27: 2500 | Q27: 500 | T27: 10400 | U27: 1 | V27: Virement | W27: Nouveau Contrat | X27: ✓ Verified: All salary fields match payroll file.
A28: 24 | B28: BELLILA LAOUATI | C28: Ilham | D28: Contrat Local | E28: Enseignant second degré | F28: Collège / Lycée | G28: SVT | H28: Teacher | I28: Certifié SVT | J28: PP 5eme E | K28: Secondaire | L28: Existing | M28: 45170 | N28: 3.3 | O28: 9500 | P28: 2500 | Q28: 500 | S28: 880 | T28: 13380 | U28: 1 | V28: Liquide | W28: 250 | X28: ✓ Verified: All salary fields match payroll file.
A29: 25 | B29: BEN ABDESSALEM | C29: Yousra | D29: Contrat Local | E29: Professeur(e) des écoles | F29: Élémentaire | G29: Generaliste | H29: Teacher | I29: Professeur des écoles (PE) | J29: CM2 F | K29: Élémentaire | L29: Existing | M29: 45536 | N29: 2.3 | O29: 9000 | P29: 2500 | Q29: 500 | T29: 12000 | U29: 1 | V29: Liquide | W29: 250 | X29: ✓ Verified: All salary fields match payroll file.
A30: 26 | B30: BEN AMAR | C30: Amira | D30: Contrat Local | E30: Professeur(e) des écoles | F30: Élémentaire | G30: Generaliste | H30: Teacher | I30: Professeur des écoles (PE) | J30: CE2 A | K30: Élémentaire | L30: Existing | M30: 45170 | N30: 3.3 | O30: 11000 | P30: 2500 | Q30: 500 | T30: 14000 | U30: 1 | V30: Virement | W30: 250 | X30: ✓ Verified: All salary fields match payroll file.
A31: 27 | B31: BEN FGUIRA | C31: Fares | D31: Contrat Local | E31: Professeur(e) d'EPS | F31: Collège / Lycée | G31: EPS | H31: Teacher | I31: Certifié EPS | J31: Collège & Lycée | K31: Secondaire | L31: Existing | M31: 44805 | N31: 4.3 | O31: 8750 | P31: 2500 | Q31: 500 | S31: 500 | T31: 12250 | U31: 1 | V31: Liquide | W31: 250 | X31: ✓ Verified: All salary fields match payroll file.
A32: 28 | B32: BEN HIBA | C32: Nesrine | D32: Contrat Local | E32: Enseignant second degré | F32: Collège / Lycée | G32: EMC | H32: Teacher | I32: Certifié EMC | J32: Secondaire (TBD) | K32: Secondaire | L32: Existing | M32: 45901 | N32: 1.3 | O32: 7200 | P32: 2250 | Q32: 450 | T32: 9900 | U32: 0.9 | V32: Liquide | W32: Nouveau Contrat | X32: ✓ Verified: All salary fields match payroll file.
A33: 29 | B33: BEN KIRAN | C33: Ambre | D33: Contrat Local | E33: Responsable APS | F33: Vie Scolaire & Support | G33: Activites periscolaires | H33: Non-Teacher | J33: Primaire & Secondaire | K33: Vie Scolaire & Support | L33: Existing | M33: 45908 | N33: 1.3 | O33: 13000 | P33: 2500 | Q33: 500 | T33: 16000 | U33: 1 | V33: Liquide | W33: Nouveau Contrat | X33: ✓ Verified: All salary fields match payroll file.
A34: 30 | B34: BEN OTHMAN | C34: Noelle | D34: Contrat Local | E34: Enseignant second degré | F34: Collège / Lycée | G34: Sciences economiques (SES) | H34: Teacher | I34: Certifié SES | J34: Collège & Lycée | K34: Secondaire | L34: Existing | M34: 44075 | N34: 6.3 | O34: 9250 | P34: 2500 | Q34: 500 | T34: 12250 | U34: 1 | V34: Virement | W34: 250 | X34: ✓ Verified: All salary fields match payroll file.
A35: 31 | B35: BEN SMIDA ÉP BEN IDRIS | C35: Khadija | D35: Contrat Local | E35: Enseignant second degré | F35: Collège / Lycée | G35: Mathematiques | H35: Teacher | I35: Certifié Maths | J35: PP 2nde A | K35: Secondaire | L35: Existing | M35: 44440 | N35: 5.3 | O35: 9000 | P35: 2500 | Q35: 500 | S35: 1080 | T35: 13080 | U35: 1 | V35: Liquide | W35: 250 | X35: ✓ Verified: All salary fields match payroll file.
A36: 32 | B36: BENBERNOU | C36: Rabia | D36: Contrat Local | E36: Assistante maternelle | F36: Maternelle | G36: ASEM | H36: Non-Teacher | J36: MSA | K36: Maternelle | L36: Existing | M36: 42979 | N36: 9.3 | O36: 7200 | P36: 2500 | Q36: 500 | T36: 10200 | U36: 1 | V36: Virement | W36: 200 | X36: ✓ Verified: All salary fields match payroll file.
A37: 33 | B37: BOUGATFA | C37: Rim | D37: Contrat Local | E37: Enseignant second degré | F37: Collège / Lycée | G37: TBD | H37: Teacher | I37: TBD | J37: Secondaire (TBD) | K37: Secondaire | L37: Existing | M37: 45901 | N37: 1.3 | O37: 8250 | P37: 2500 | Q37: 500 | T37: 11250 | U37: 1 | V37: Virement | W37: Nouveau Contrat | X37: ✓ Verified: All salary fields match payroll file.
A38: 34 | B38: BOUHJAR | C38: Fahmi | D38: Contrat Local | E38: Enseignant second degré | F38: Collège / Lycée | G38: Sciences physiques | H38: Teacher | I38: Certifié Physique-Chimie | J38: Collège & Lycée | K38: Secondaire | L38: Existing | M38: 43344 | N38: 8.3 | O38: 10000 | P38: 2500 | Q38: 500 | S38: 1300 | T38: 14300 | U38: 1 | V38: Virement | W38: 250 | X38: ✓ Verified: All salary fields match payroll file.
A39: 35 | B39: BOULMANE | C39: Lala-Malika | D39: Contrat Local | E39: Coordinatrice inclusion | F39: Vie Scolaire & Support | G39: Inclusion | H39: Non-Teacher | J39: Primaire & Secondaire | K39: Vie Scolaire & Support | L39: Existing | M39: 44805 | N39: 4.3 | O39: 11750 | P39: 2500 | Q39: 500 | T39: 14750 | U39: 1 | V39: Virement | W39: 250 | X39: ✓ Verified: All salary fields match payroll file.
A40: 36 | B40: BOURAOUI | C40: Nasri | D40: Contrat Local | E40: Assistant(e) d'éducation | F40: Vie Scolaire & Support | G40: Vie scolaire | H40: Non-Teacher | J40: Secondaire | K40: Vie Scolaire & Support | L40: Existing | M40: 45536 | N40: 2.3 | O40: 7600 | P40: 2500 | Q40: 500 | T40: 10600 | U40: 1 | V40: Virement | W40: 200 | X40: ✓ Verified: All salary fields match payroll file.
A41: 37 | B41: BOURSAULT | C41: Géraldine | D41: Contrat Local | E41: Enseignant second degré | F41: Collège / Lycée | G41: Mathematiques | H41: Teacher | I41: Certifié Maths | J41: Collège & Lycée | K41: Secondaire | L41: Existing | M41: 45536 | N41: 2.3 | O41: 10000 | P41: 2500 | Q41: 500 | S41: 900 | T41: 13900 | U41: 1 | V41: Virement | W41: 250 | X41: ✓ Verified: All salary fields match payroll file.
A42: 38 | B42: BOUSSAID | C42: Amira | D42: Contrat Local | E42: Professeur(e) des écoles | F42: Élémentaire | G42: Generaliste | H42: Teacher | I42: Professeur des écoles (PE) | J42: Élémentaire (TBD) | K42: Élémentaire | L42: Existing | M42: 43709 | N42: 7.3 | O42: 9500 | P42: 2500 | Q42: 500 | T42: 12500 | U42: 1 | V42: Virement | W42: 250 | X42: ✓ Verified: All salary fields match payroll file.
A43: 39 | B43: BOUZID | C43: Rafahiya | D43: Contrat Local | E43: Assistante maternelle | F43: Maternelle | G43: ASEM | H43: Non-Teacher | J43: GSD | K43: Maternelle | L43: Existing | M43: 45170 | N43: 3.3 | O43: 6200 | P43: 2500 | Q43: 500 | T43: 9200 | U43: 1 | V43: Liquide | W43: 200 | X43: ✓ Verified: All salary fields match payroll file.
A44: 40 | B44: BRAX | C44: Nathalie | D44: Contrat Local | E44: Assistante maternelle | F44: Maternelle | G44: ASEM | H44: Non-Teacher | J44: GSB | K44: Maternelle | L44: Existing | M44: 42614 | N44: 10.3 | O44: 8500 | P44: 2500 | Q44: 500 | T44: 11500 | U44: 1 | V44: Liquide | W44: 250 | X44: ✓ Verified: All salary fields match payroll file.
A45: 41 | B45: BRUNET | C45: Clemence | D45: Contrat Local | E45: Professeur(e) des écoles | F45: Élémentaire | G45: Generaliste | H45: Teacher | I45: Professeur des écoles (PE) | J45: PSA | K45: Maternelle | L45: Existing | M45: 44805 | N45: 4.3 | O45: 9000 | P45: 2500 | Q45: 500 | T45: 12000 | U45: 1 | V45: Virement | W45: 250 | X45: ✓ Verified: All salary fields match payroll file.
A46: 42 | B46: BUZIT | C46: Cécile | D46: Contrat Local | E46: Chargée des moyens généraux | F46: Administration | G46: Moyens generaux | H46: Non-Teacher | J46: Administration | K46: Administration | L46: Existing | M46: 45908 | N46: 1.3 | O46: 7400 | P46: 2500 | Q46: 500 | T46: 10400 | U46: 1 | V46: Liquide | W46: Nouveau Contrat | X46: ✓ Verified: All salary fields match payroll file.
A47: 43 | B47: CABRERA | C47: Victor | D47: Contrat Local | E47: Enseignant de langue étrangère second degré | F47: Collège / Lycée | G47: Espagnol | H47: Teacher | I47: Certifié Espagnol | J47: Collège & Lycée | K47: Secondaire | L47: Existing | M47: 44805 | N47: 4.3 | O47: 8000 | P47: 2500 | Q47: 500 | S47: 900 | T47: 11900 | U47: 1 | V47: Virement | W47: 200 | X47: ✓ Verified: All salary fields match payroll file.
A48: 44 | B48: CATRY | C48: Vanessa | D48: Contrat Local | E48: Professeur(e) d'EPS | F48: Collège / Lycée | G48: EPS | H48: Teacher | I48: Certifié EPS | J48: PP 6eme E | K48: Secondaire | L48: Existing | M48: 42979 | N48: 9.3 | O48: 12250 | P48: 2500 | Q48: 500 | T48: 15250 | U48: 1 | V48: Virement | W48: 250 | X48: ✓ Verified: All salary fields match payroll file.
A49: 45 | B49: CHAABAN | C49: Amani | D49: Contrat Local | E49: Enseignant de langue étrangère second degré | F49: Collège / Lycée | G49: Anglais | H49: Teacher | I49: Certifié Anglais | J49: Collège & Lycée | K49: Secondaire | L49: Existing | M49: 45194 | N49: 3.3 | O49: 7400 | P49: 2500 | Q49: 500 | T49: 10400 | U49: 1 | V49: Liquide | W49: 200 | X49: ✓ Verified: All salary fields match payroll file.
A50: 46 | B50: CHABIRAND | C50: Estelle | D50: Contrat Local | E50: Professeur(e) des écoles | F50: Élémentaire | G50: Generaliste | H50: Teacher | I50: Professeur des écoles (PE) | J50: CP B | K50: Élémentaire | L50: Existing | M50: 45170 | N50: 3.3 | O50: 9000 | P50: 2500 | Q50: 500 | T50: 12000 | U50: 1 | V50: Liquide | W50: 250 | X50: ✓ Verified: All salary fields match payroll file.
A51: 47 | B51: CHAIEB | C51: Iheb | D51: Contrat Local | E51: Enseignant second degré | F51: Collège / Lycée | G51: Sciences physiques | H51: Teacher | I51: Certifié Physique-Chimie | J51: Collège & Lycée | K51: Secondaire | L51: Existing | M51: 44440 | N51: 5.3 | O51: 9000 | P51: 2500 | Q51: 500 | S51: 1860 | T51: 13860 | U51: 1 | V51: Liquide | W51: 250 | X51: ✓ Verified: All salary fields match payroll file.
A52: 48 | B52: CHARIF | C52: Hiba | D52: Contrat Local | E52: Assistant(e) d'éducation | F52: Vie Scolaire & Support | G52: Vie scolaire | H52: Non-Teacher | J52: Secondaire | K52: Vie Scolaire & Support | L52: Existing | M52: 45536 | N52: 2.3 | O52: 7200 | P52: 2500 | Q52: 500 | T52: 10200 | U52: 1 | V52: Virement | W52: 200 | X52: ✓ Verified: All salary fields match payroll file.
A53: 49 | B53: CHAUVET | C53: Aurelie | D53: Contrat Local | E53: Enseignant second degré | F53: Élémentaire | G53: Generaliste | H53: Teacher | I53: Professeur des écoles (PE) | J53: CM2 E | K53: Élémentaire | L53: Existing | M53: 44805 | N53: 4.3 | O53: 8750 | P53: 2500 | Q53: 500 | T53: 11750 | U53: 1 | V53: Virement | W53: 250 | X53: ✓ Verified: All salary fields match payroll file.
A54: 50 | B54: CHBEIR | C54: Grece | D54: Contrat Local | E54: Enseignant de langue étrangère second degré | F54: Collège / Lycée | G54: Espagnol | H54: Teacher | I54: Certifié Espagnol | J54: Collège & Lycée | K54: Secondaire | L54: Existing | M54: 43054 | N54: 9.1 | O54: 9250 | P54: 2500 | Q54: 500 | S54: 1100 | T54: 13350 | U54: 1 | V54: Virement | W54: 250 | X54: ✓ Verified: All salary fields match payroll file.
A55: 51 | B55: CHEBLI | C55: Amal | D55: Contrat Local | E55: Professeur(e) des écoles | F55: Élémentaire | G55: Generaliste | H55: Teacher | I55: Professeur des écoles (PE) | J55: CE2 E | K55: Élémentaire | L55: Existing | M55: 44805 | N55: 4.3 | O55: 8750 | P55: 2500 | Q55: 500 | T55: 11750 | U55: 1 | V55: Virement | W55: 250 | X55: ✓ Verified: All salary fields match payroll file.
A56: 52 | B56: CHERFAN | C56: Randa | D56: Contrat Local | E56: Enseignant de langue étrangère second degré | F56: Collège / Lycée | G56: Anglais | H56: Teacher | I56: Certifié Anglais | J56: PP 6eme D | K56: Secondaire | L56: Existing | M56: 41153 | N56: 14.3 | O56: 10250 | P56: 2500 | Q56: 500 | T56: 13250 | U56: 1 | V56: Virement | W56: 250 | X56: ✓ Verified: All salary fields match payroll file.
A57: 53 | B57: CHIKHANI | C57: Roula | D57: Contrat Local | E57: Responsable des moyens généraux | F57: Administration | G57: Moyens generaux | H57: Non-Teacher | J57: Administration | K57: Administration | L57: Existing | M57: 44440 | N57: 5.3 | O57: 13250 | P57: 2500 | Q57: 500 | R57: 500 | T57: 16750 | U57: 1 | V57: Liquide | W57: 250 | X57: ✓ Verified: All salary fields match payroll file.
A58: 54 | B58: CHOUT | C58: Valérie | D58: Contrat Local | E58: Enseignant second degré | F58: Élémentaire | G58: FLE | H58: Teacher | I58: Professeur des écoles (PE) | J58: FLE | K58: Élémentaire | L58: Existing | M58: 45170 | N58: 3.3 | O58: 10250 | P58: 2500 | Q58: 500 | T58: 13250 | U58: 1 | V58: Virement | W58: 1250 | X58: ✓ Verified: All salary fields match payroll file.
A59: 55 | B59: CORNETTE | C59: Myriem | D59: Contrat Local | E59: Enseignant second degré | F59: Collège / Lycée | G59: Mathematiques | H59: Teacher | I59: Certifié Maths | J59: Collège & Lycée | K59: Secondaire | L59: Existing | M59: 44440 | N59: 5.3 | O59: 8250 | P59: 2292 | Q59: 458 | T59: 11000 | U59: 0.91666667 | V59: Liquide | W59: 250 | X59: ✓ Verified: All salary fields match payroll file.
A60: 56 | B60: COSSIN ÉP FAYE | C60: Maryelle | D60: Contrat Local | E60: Enseignant second degré | F60: Collège / Lycée | G60: Francais | H60: Teacher | I60: Certifié Lettres | J60: PP 3eme C | K60: Secondaire | L60: Existing | M60: 44440 | N60: 5.3 | O60: 10750 | P60: 2500 | Q60: 500 | S60: 900 | T60: 14650 | U60: 1 | V60: Liquide | W60: 250 | X60: ✓ Verified: All salary fields match payroll file.
A61: 57 | B61: DAOUK | C61: Zeina | D61: Contrat Local | E61: Professeur(e) des écoles | F61: Élémentaire | G61: Generaliste | H61: Teacher | I61: Professeur des écoles (PE) | J61: GSA | K61: Maternelle | L61: Existing | M61: 42248 | N61: 11.3 | O61: 12000 | P61: 2500 | Q61: 500 | T61: 15000 | U61: 1 | V61: Virement | W61: 250 | X61: ✓ Verified: All salary fields match payroll file.
A62: 58 | B62: DELLAH | C62: Sawssen | D62: Contrat Local | E62: Professeur(e) des écoles | F62: Élémentaire | G62: Generaliste | H62: Teacher | I62: Professeur des écoles (PE) | J62: MSC | K62: Maternelle | L62: Existing | M62: 45901 | N62: 1.3 | O62: 8250 | P62: 2500 | Q62: 500 | T62: 11250 | U62: 1 | V62: Liquide | W62: Nouveau Contrat | X62: ✓ Verified: All salary fields match payroll file.
A63: 59 | B63: DESBARRES | C63: Chloé | D63: Contrat Local | E63: Enseignant de langue étrangère second degré | F63: Collège / Lycée | G63: Anglais | H63: Teacher | I63: Certifié Anglais | J63: Collège & Lycée | K63: Secondaire | L63: Existing | M63: 45901 | N63: 1.3 | O63: 8750 | P63: 2500 | Q63: 500 | T63: 11750 | U63: 1 | V63: Liquide | W63: Nouveau Contrat | X63: ✓ Verified: All salary fields match payroll file.
A64: 60 | B64: DIAZ | C64: Maud | D64: Contrat Local | E64: Professeur(e) des écoles | F64: Élémentaire | G64: Generaliste | H64: Teacher | I64: Professeur des écoles (PE) | J64: Élémentaire (TBD) | K64: Élémentaire | L64: Existing | M64: 45901 | N64: 1.3 | O64: 8750 | P64: 2500 | Q64: 500 | T64: 11750 | U64: 1 | V64: Virement | W64: Nouveau Contrat | X64: ✓ Verified: All salary fields match payroll file.
A65: 61 | B65: DIOURI | C65: Yousra | D65: Contrat Local | E65: Assistante maternelle | F65: Maternelle | G65: ASEM | H65: Non-Teacher | J65: MSB | K65: Maternelle | L65: Existing | M65: 44440 | N65: 5.3 | O65: 6800 | P65: 2500 | Q65: 500 | T65: 9800 | U65: 1 | V65: Virement | W65: 200 | X65: ✓ Verified: All salary fields match payroll file.
A66: 62 | B66: DJEBARI | C66: Yasmina | D66: Contrat Local | E66: CPE | F66: Collège / Lycée | G66: Vie scolaire | H66: Non-Teacher | J66: Secondaire | K66: Vie Scolaire & Support | L66: Existing | M66: 40057 | N66: 17.3 | O66: 11000 | P66: 2500 | Q66: 500 | R66: 2500 | T66: 16500 | U66: 1 | V66: Virement | W66: 3000 (changement de poste) | X66: ✓ Verified: All salary fields match payroll file.
A67: 63 | B67: DJERAD | C67: Islem | D67: Contrat Local | E67: Responsable informatique | F67: Administration | G67: Informatique | H67: Non-Teacher | J67: Administration | K67: Administration | L67: Existing | M67: 44440 | N67: 5.3 | O67: 12500 | P67: 2500 | Q67: 500 | R67: 500 | T67: 16000 | U67: 1 | V67: Liquide | W67: 500 (alignement des Resp Admin) | X67: ✓ Verified: All salary fields match payroll file.
A68: 64 | B68: DOMLOGE | C68: Racha | D68: Contrat Local | E68: Enseignant second degré | F68: Collège / Lycée | G68: Francais | H68: Teacher | I68: Certifié Lettres | J68: PP 2nde E | K68: Secondaire | L68: Existing | M68: 44075 | N68: 6.3 | O68: 12000 | P68: 2500 | Q68: 500 | S68: 1300 | T68: 16300 | U68: 1 | V68: Liquide | W68: 250 | X68: ✓ Verified: All salary fields match payroll file.
A69: 65 | B69: DUMAS | C69: Tiphaine | D69: Contrat Local | E69: Professeur(e) des écoles | F69: Élémentaire | G69: Generaliste | H69: Teacher | I69: Professeur des écoles (PE) | J69: CE1 B | K69: Élémentaire | L69: Existing | M69: 45170 | N69: 3.3 | O69: 9500 | P69: 2500 | Q69: 500 | T69: 12500 | U69: 1 | V69: Liquide | W69: 250 | X69: ✓ Verified: All salary fields match payroll file.
A70: 66 | B70: EDOUJ | C70: Fatima | D70: Contrat Local | E70: Assistante maternelle | F70: Maternelle | G70: ASEM | H70: Non-Teacher | J70: GSA | K70: Maternelle | L70: Existing | M70: 42979 | N70: 9.3 | O70: 7200 | P70: 2500 | Q70: 500 | T70: 10200 | U70: 1 | V70: Virement | W70: 200 | X70: ✓ Verified: All salary fields match payroll file.
A71: 67 | B71: EL BOUFRAHI | C71: NAJLAA | D71: Contrat Local | E71: Infirmière | F71: Vie Scolaire & Support | G71: Sante scolaire | H71: Non-Teacher | J71: Primaire & Secondaire | K71: Vie Scolaire & Support | L71: Existing | M71: 44805 | N71: 4.3 | O71: 9500 | P71: 2500 | Q71: 500 | T71: 12500 | U71: 1 | V71: Virement | W71: 250 | X71: ✓ Verified: All salary fields match payroll file.
A72: 68 | B72: EL GHAZAL | C72: Lina | D72: Contrat Local | E72: Enseignant de langue étrangère | F72: Élémentaire | G72: Anglais | H72: Teacher | I72: Enseignant Anglais Primaire | J72: PS-CM2 (Primaire) | K72: Primaire | L72: Existing | M72: 40787 | N72: 15.3 | O72: 10500 | P72: 2500 | Q72: 500 | S72: 1952 | T72: 15452 | U72: 1 | V72: Liquide | W72: 250 | X72: ✓ Verified: All salary fields match payroll file.
A73: 69 | B73: EL KHATIB | C73: Ghislaine | D73: Contrat Local | E73: Enseignant second degré | F73: Collège / Lycée | G73: Mathematiques | H73: Teacher | I73: Certifié Maths | J73: Collège & Lycée | K73: Secondaire | L73: Existing | M73: 44805 | N73: 4.3 | O73: 9750 | P73: 2500 | Q73: 500 | S73: 1100 | T73: 13850 | U73: 1 | V73: Liquide | W73: 250 | X73: ✓ Verified: All salary fields match payroll file.
A74: 70 | B74: EL OUAFI | C74: Hassan | D74: Contrat Local | E74: Enseignant second degré | F74: Collège / Lycée | G74: TBD | H74: Teacher | I74: TBD | J74: Secondaire (TBD) | K74: Secondaire | L74: Existing | M74: 45536 | N74: 2.3 | O74: 9250 | P74: 2500 | Q74: 500 | T74: 12250 | U74: 1 | V74: Virement | W74: Nouveau Contrat | X74: ✓ Verified: All salary fields match payroll file.
A75: 71 | B75: EL OUAHABI/LAHLOU | C75: Amal | D75: Contrat Local | E75: Assistante maternelle | F75: Maternelle | G75: ASEM | H75: Non-Teacher | J75: MSD | K75: Maternelle | L75: Existing | M75: 43709 | N75: 7.3 | O75: 7400 | P75: 2500 | Q75: 500 | T75: 10400 | U75: 1 | V75: Virement | W75: 200 | X75: ✓ Verified: All salary fields match payroll file.
A76: 72 | B76: EL OUARDI | C76: Nawale | D76: Contrat Local | E76: Assistant(e) d'éducation | F76: Vie Scolaire & Support | G76: Vie scolaire | H76: Non-Teacher | J76: Secondaire | K76: Vie Scolaire & Support | L76: Existing | M76: 45536 | N76: 2.3 | O76: 7200 | P76: 2500 | Q76: 500 | T76: 10200 | U76: 1 | V76: Virement | W76: 200 | X76: ✓ Verified: All salary fields match payroll file.
A77: 73 | B77: EL SMAILI | C77: Laila | D77: Contrat Local | E77: Professeur(e) des écoles | F77: Élémentaire | G77: Generaliste | H77: Teacher | I77: Professeur des écoles (PE) | J77: CM1 B | K77: Élémentaire | L77: Existing | M77: 44440 | N77: 5.3 | O77: 10500 | P77: 2500 | Q77: 500 | T77: 13500 | U77: 1 | V77: Virement | W77: 250 | X77: ✓ Verified: All salary fields match payroll file.
A78: 74 | B78: EZZOUHOURI | C78: Sana | D78: Contrat Local | E78: Assistante maternelle | F78: Maternelle | G78: ASEM | H78: Non-Teacher | J78: PSB | K78: Maternelle | L78: Existing | M78: 44805 | N78: 4.3 | O78: 6600 | P78: 2500 | Q78: 500 | T78: 9600 | U78: 1 | V78: Virement | W78: 200 | X78: ✓ Verified: All salary fields match payroll file.
A79: 75 | B79: FERJANI | C79: Chokri | D79: Contrat Local | E79: Chauffeur | F79: Administration | G79: Transport | H79: Non-Teacher | J79: Administration | K79: Administration | L79: Existing | M79: 45901 | N79: 1.3 | O79: 5000 | P79: 2500 | Q79: 500 | T79: 8000 | U79: 1 | V79: Liquide | W79: Nouveau Contrat | X79: ✓ Verified: All salary fields match payroll file.
A80: 76 | B80: FESSI | C80: Salwa | D80: Contrat Local | E80: Enseignant second degré | F80: Collège / Lycée | G80: Mathematiques | H80: Teacher | I80: Certifié Maths | J80: PP 6eme F | K80: Secondaire | L80: Existing | M80: 36770 | N80: 26.3 | O80: 10750 | P80: 2500 | Q80: 500 | S80: 1900 | T80: 15650 | U80: 1 | V80: Virement | W80: 250 | X80: ✓ Verified: All salary fields match payroll file.
A81: 77 | B81: FOUAL | C81: Kenza | D81: Contrat Local | E81: AED Collège / Assistante APS | F81: Collège / Lycée | G81: Remplacement | H81: Non-Teacher | J81: Élémentaire | K81: Vie Scolaire & Support | L81: Existing | M81: 45936 | N81: 1.2 | O81: 7000 | P81: 2500 | Q81: 500 | T81: 10000 | U81: 1 | V81: Virement | W81: Nouveau Contrat | X81: ✓ Verified: All salary fields match payroll file.
A82: 78 | B82: FRIGUI | C82: Amir | D82: Contrat Local | E82: Assistant(e) d'éducation | F82: Vie Scolaire & Support | G82: Vie scolaire | H82: Non-Teacher | J82: Secondaire | K82: Vie Scolaire & Support | L82: Existing | M82: 44440 | N82: 5.3 | O82: 7800 | P82: 2500 | Q82: 500 | T82: 10800 | U82: 1 | V82: Virement | W82: 200 | X82: ✓ Verified: All salary fields match payroll file.
A83: 79 | B83: GHAZOUANI | C83: Slim | D83: Contrat Local | E83: Professeur(e) d'EPS | F83: Collège / Lycée | G83: EPS | H83: Teacher | I83: Certifié EPS | J83: Collège & Lycée | K83: Secondaire | L83: Existing | M83: 45170 | N83: 3.3 | O83: 9750 | P83: 2500 | Q83: 500 | S83: 500 | T83: 13250 | U83: 1 | V83: Virement | W83: 250 | X83: ✓ Verified: All salary fields match payroll file.
A84: 80 | B84: GRATEAU | C84: Michele | D84: Contrat Local | E84: Bibliothécaire | F84: Vie Scolaire & Support | G84: Bibliotheque | H84: Non-Teacher | J84: Primaire | K84: Vie Scolaire & Support | L84: Existing | M84: 40422 | N84: 16.3 | O84: 11000 | P84: 2500 | Q84: 500 | T84: 14000 | U84: 1 | V84: Virement | W84: 250 | X84: ✓ Verified: All salary fields match payroll file. | TYPO FIXED: 'Bibliothécaire' corrected to 'Bibliothécaire' (corrupted in source file).
A85: 81 | B85: GRENIER-MERAUD | C85: Laetitia | D85: Contrat Local | E85: Assistante maternelle | F85: Maternelle | G85: ASEM | H85: Non-Teacher | J85: PSC | K85: Maternelle | L85: Existing | M85: 45536 | N85: 2.3 | O85: 5800 | P85: 2500 | Q85: 500 | T85: 8800 | U85: 1 | V85: Liquide | W85: 200 | X85: ✓ Verified: All salary fields match payroll file.
A86: 82 | B86: HADJ TAIEB | C86: Amine | D86: Contrat Local | E86: Enseignant second degré (55.6%) + Animateur Fab/Lab (42.9%) | F86: Collège / Lycée + Vie Scolaire | G86: Technologie / SNT | H86: Teacher | I86: Certifié Technologie | J86: Collège & Lycée | K86: Secondaire | L86: Existing | M86: 45189 | N86: 3.3 | O86: 7796 | P86: 2460 | Q86: 492 | T86: 10748 | U86: 0.9841 | V86: Virement | W86: 250 + 200 | X86: MERGED: Was 2 rows (#82 Enseignant 55.6% + #83 Animateur 42.9%). Combined salary = Base 7796 + IL 2460 + IT 492 = Gross 10748. Total hourly ~98.4%. Aug: 250 (Enseignant) + 200 (Animateur). Salary file also had 2 rows - both verified matching.
A87: 83 | B87: HAJJEJ | C87: Mohamed | D87: Contrat Local | E87: Référent sécurité | F87: Administration | G87: Securite | H87: Non-Teacher | J87: Administration | K87: Administration | L87: Existing | M87: 44440 | N87: 5.3 | O87: 7800 | P87: 2500 | Q87: 500 | T87: 10800 | U87: 1 | V87: Virement | W87: 2200 (changement de poste) | X87: ✓ Verified: All salary fields match payroll file.
A88: 84 | B88: HAMMOUD | C88: Noura | D88: Contrat Local | E88: Enseignant de langue étrangère | F88: Élémentaire | G88: Anglais | H88: Teacher | I88: Enseignant Anglais Primaire | J88: PS-CM2 (Primaire) | K88: Primaire | L88: Existing | M88: 41153 | N88: 14.3 | O88: 10750 | P88: 2500 | Q88: 500 | S88: 1940 | T88: 15690 | U88: 1 | V88: Virement | W88: 250 | X88: ✓ Verified: All salary fields match payroll file.
A89: 85 | B89: HARB | C89: HIBA | D89: Contrat Local | E89: Inclusion | F89: Élémentaire | G89: Generaliste | H89: Non-Teacher | J89: CM1 C | K89: Élémentaire | L89: Existing | M89: 44805 | N89: 4.3 | O89: 8500 | P89: 2500 | Q89: 500 | T89: 11500 | U89: 1 | V89: Liquide | W89: Nouveau Contrat | X89: ✓ Verified: All salary fields match payroll file.
A90: 86 | B90: HARBI | C90: Emna | D90: Contrat Local | E90: Enseignant second degré | F90: Collège / Lycée | G90: Francais | H90: Teacher | I90: Certifié Lettres | J90: Collège & Lycée | K90: Secondaire | L90: Existing | M90: 45901 | N90: 1.3 | O90: 4000 | P90: 1250 | Q90: 250 | T90: 5500 | U90: 0.5 | V90: Virement | W90: Nouveau Contrat | X90: ✓ Verified: All salary fields match payroll file.
A91: 87 | B91: HELOU - SEMAAN | C91: Sylvana | D91: Contrat Local | E91: Professeur(e) des écoles | F91: Élémentaire | G91: Generaliste | H91: Teacher | I91: Professeur des écoles (PE) | J91: CE1 D | K91: Élémentaire | L91: Existing | M91: 44805 | N91: 4.3 | O91: 9250 | P91: 2500 | Q91: 500 | T91: 12250 | U91: 1 | V91: Liquide | W91: 250 | X91: ✓ Verified: All salary fields match payroll file.
A92: 88 | B92: HEMAYA | C92: Loubna | D92: Contrat Local | E92: Professeur(e) des écoles | F92: Élémentaire | G92: Generaliste | H92: Teacher | I92: Professeur des écoles (PE) | J92: CE1 F | K92: Élémentaire | L92: Existing | M92: 41883 | N92: 12.3 | O92: 11500 | P92: 2500 | Q92: 500 | T92: 14500 | U92: 1 | V92: Virement | W92: 250 | X92: ✓ Verified: All salary fields match payroll file.
A93: 89 | B93: HOFFMAN | C93: Anne-Sophie | D93: Contrat Local | E93: Professeure de Musique | F93: Vie Scolaire & Support | G93: Musique | H93: Teacher | I93: Certifié Éducation Musicale | J93: Primaire | K93: Primaire | L93: Existing | M93: 45901 | N93: 1.3 | O93: 4000 | P93: 1250 | Q93: 250 | T93: 5500 | U93: 0.5 | V93: Virement | W93: Nouveau Contrat | X93: ✓ Verified: All salary fields match payroll file.
A94: 90 | B94: HUSSEIN | C94: Waad | D94: Contrat Local | E94: Enseignant de langue étrangère | F94: Élémentaire | G94: Arabe | H94: Teacher | I94: Enseignant Arabe | J94: PS-CM2 (Primaire) | K94: Primaire | L94: Existing | M94: 45170 | N94: 3.3 | O94: 7800 | P94: 2500 | Q94: 500 | S94: 90 | T94: 10890 | U94: 1 | V94: Liquide | W94: 200 | X94: ✓ Verified: All salary fields match payroll file.
A95: 91 | B95: IMRANE | C95: Lounes | D95: Contrat Local | E95: Professeur(e) d'EPS | F95: Collège / Lycée | G95: EPS | H95: Teacher | I95: Certifié EPS | J95: Collège & Lycée | K95: Secondaire | L95: Existing | M95: 45536 | N95: 2.3 | O95: 8500 | P95: 2500 | Q95: 500 | T95: 11500 | U95: 1 | V95: Virement | W95: 250 | X95: ✓ Verified: All salary fields match payroll file.
A96: 92 | B96: JAMGOSSIAN | C96: Anahid-Lydia | D96: Contrat Local | E96: Enseignant second degré | F96: Collège / Lycée | G96: Musique | H96: Teacher | I96: Certifié Éducation Musicale | J96: Collège & Lycée | K96: Secondaire | L96: Existing | M96: 41216 | N96: 14.2 | O96: 7333 | P96: 1667 | Q96: 333 | T96: 9333 | U96: 0.66666667 | V96: Liquide | W96: 250 | X96: ✓ Verified: All salary fields match payroll file.
A97: 93 | B97: JEANSON | C97: Marianne | D97: Contrat Local | E97: Professeur(e) des écoles | F97: Élémentaire | G97: Generaliste | H97: Teacher | I97: Professeur des écoles (PE) | J97: CP E | K97: Élémentaire | L97: Existing | M97: 45170 | N97: 3.3 | O97: 8750 | P97: 2500 | Q97: 500 | T97: 11750 | U97: 1 | V97: Virement | W97: 250 | X97: ✓ Verified: All salary fields match payroll file.
A98: 94 | B98: JEMAA ÉP KHALDI | C98: Fatma Chiraz | D98: Contrat Local | E98: Enseignant second degré | F98: Collège / Lycée | G98: SVT | H98: Teacher | I98: Certifié SVT | J98: PP 4eme A | K98: Secondaire | L98: Existing | M98: 44440 | N98: 5.3 | O98: 9000 | P98: 2500 | Q98: 500 | S98: 1640 | T98: 13640 | U98: 1 | V98: Liquide | W98: 250 | X98: ✓ Verified: All salary fields match payroll file.
A99: 95 | B99: KABBANI | C99: Farah | D99: Contrat Local | E99: Enseignant de langue étrangère | F99: Élémentaire | G99: Anglais | H99: Teacher | I99: Enseignant Anglais Primaire | J99: PS-CM2 (Primaire) | K99: Primaire | L99: Existing | M99: 45170 | N99: 3.3 | O99: 8250 | P99: 2500 | Q99: 500 | S99: 1940 | T99: 13190 | U99: 1 | V99: Liquide | W99: 250 | X99: ✓ Verified: All salary fields match payroll file.
A100: 96 | B100: KARAM | C100: Nadine | D100: Contrat Local | E100: Chef comptable | F100: Administration | G100: Comptabilite | H100: Non-Teacher | J100: Administration | K100: Administration | L100: Existing | M100: 44805 | N100: 4.3 | O100: 12750 | P100: 2500 | Q100: 500 | R100: 1000 | T100: 16750 | U100: 1 | V100: Liquide | W100: 250 | X100: ✓ Verified: All salary fields match payroll file.
A101: 97 | B101: KARE CHEVALIER | C101: Yacine | D101: Contrat Local | E101: Chargée des frais de scolarité | F101: Administration | G101: Frais de scolarite | H101: Non-Teacher | J101: Administration | K101: Administration | L101: Existing | M101: 44805 | N101: 4.3 | O101: 8750 | P101: 2500 | Q101: 500 | T101: 11750 | U101: 1 | V101: Virement | W101: 250 | X101: ✓ Verified: All salary fields match payroll file.
...
